Workbook

Sheet Cover
B2: Grupo Bimbo, S.A.B. de C.V. (BMV: BIMBO A) - DCF valuation workbook
B3: Valuation date 2026-10-16; MXN millions; IFRS. Generated 2026-10-17 by valuation/build/build_spg_workbooks.py from the canonical model inputs.
B4: '
B5: Sheets
B6: DCF - assumptions, drivers, projected free cash flow, working capital, discounting, terminal value, equity bridge, cross-checks, lease-schedule variant and sensitivity tables (layout after S&P 'DCF Analysis').
B7: Reverse_DCF - terminal growth and revenue-growth shift implied by the market price.
B8: Dated_Check - independent valuation anchored at the 30-Jun-2026 balance sheet, rolled to the valuation date.
B9: Engine_Recon - line-by-line agreement with the project's model engine (model/model-summary.json).
B10: Inputs_Sources - every input with value, tag, source and date. Checks - integrity checks.
B11: '
B12: Conventions
B13: Cash flows discounted to 31-Dec-2025 (mid-year); Gordon TV discounted N - offset, exit TV discounted N; net debt incl. IFRS 16 leases at 31-Dec-2025; value per share rolled forward to today at the cost of equity.
... B17: [sourced] from a filing or public source; [guidance] management statement; [assumption] team or assistant judgment (proposal until the team confirms); [calc] computed; [unverified] not yet tied to a source.

Sheet DCF
B2: Discounted Cash Flow Analysis
B3: Grupo Bimbo, S.A.B. de C.V. (BMV:BIMBO A) | valuation date 2026-10-16 | MXN millions, IFRS | layout after S&P Capital IQ Pro 'DCF Analysis'
B4: Blue on yellow = input (change here); black = formula; green = link to another sheet. Every input carries a tag and source in 'Inputs_Sources'. [sourced] from a filing or public source; [guidance] management statement; [assumption] team or assistant judgment (proposal until the team confirms); [calc] computed; [unverified] not yet tied to a source.
B6: KEY OUTPUTS (engine conventions; see 'Checks' and 'Engine_Recon')
B7: Value per share today - Gordon (MXN) | D7: =$D$138 -> 46.144022
B8: Value per share today - exit multiple (MXN) | D8: =$D$145 -> 47.421921
B9: 12-month target - Gordon, engine definition (MXN) | D9: =$D$140 -> 50.797086
B10: Current share price (MXN) | D10: =$D$132 -> 58.6
B11: Premium / (discount) today - Gordon / exit | D11: =$D$139 -> -0.21255936 | E11: =$D$146 -> -0.19075221
B12: WACC / cost of equity | D12: =$D$32 -> 0.1015131 | E12: =$D$28 -> 0.12643898
B13: Terminal growth / exit multiple | D13: =$D$37 -> 0.0425 | E13: =$D$38 -> 6
B14: Enterprise value - Gordon / exit (MXN m) | D14: =$D$110 -> 381149.83 | E14: =$D$113 -> 386162.69
B15: Terminal value share of EV - Gordon / exit | D15: =$D$114 -> 0.5568889 | E15: =$D$115 -> 0.56264102
B16: Lease-schedule adjustment per share - Gordon / exit (MXN) | D16: =$D$176 -> -4.6486551 | E16: =$D$177 -> -1.9639038
B17: Team target price | D17: null - team decision (CFA rules: the team sets the target and rating)
B19: ASSUMPTIONS - COST OF CAPITAL (from valuation/valuation.yaml; full build in BIMBOA_WACC_v1.xlsx)
B20: Risk-free rate | D20: 0.0926 | E20: [sourced] M-Bono 10y 9.26%, S&P Capital IQ rates 2026-10-16 (wacc_inputs F1)
B21: Equity risk premium (mature market) | D21: 0.042 | E21: [sourced] Damodaran implied ERP 4.20%, 1-Oct-2026 (wacc_inputs G1)
B22: Country risk premium | D22: 0 | E22: [assumption] 0 on the local route (project guide wacc-latam.md); variant B in BIMBOA_WACC_v1.xlsx
B23: Unlevered beta | D23: 0.53 | E23: [sourced] Damodaran Food Processing, Global, unlevered 0.53 (Jan-2026; wacc_inputs G6) - proposal; peer 5Y betas too low to use alone
B24: Target debt / equity (market values, debt incl. leases) | D24: 0.7431 | E24: [calc] Bimbo current market D/E incl. leases 0.743 = (153,660 + 33,361) / 251,684 (wacc_inputs D2) - proposal
B25: Pre-tax cost of debt (MXN) | D25: 0.0971 | E25: [calc] M-Bono 10y 9.26% + 0.45pp BIMBO 26 issue spread = 9.71% (wacc_inputs J2-B) - proposal
B26: Marginal tax rate (WACC) | D26: 0.3 | E26: [sourced] Mexico statutory 30% (wacc_inputs D7)
B27: Relevered beta = unlevered x (1 + (1 - tax) x D/E) | D27: =$D$23*(1+(1-$D$26)*$D$24) -> 0.8056901
B28: Cost of equity = rf + beta x ERP + CRP | D28: =$D$20+$D$27*$D$21+$D$22 -> 0.12643898
B29: After-tax cost of debt | D29: =$D$25*(1-$D$26) -> 0.06797
B30: Equity weight = 1 / (1 + D/E) | D30: =1/(1+$D$24) -> 0.57369055
B31: Debt weight = D/E / (1 + D/E) | D31: =$D$24/(1+$D$24) -> 0.42630945
B32: WACC | D32: =$D$30*$D$28+$D$31*$D$29 -> 0.1015131 | E32: Same formula as the engine's WACC sheet; the reconciliation is in 'Engine_Recon'.
B34: ASSUMPTIONS - DISCOUNTING, TERMINAL VALUE AND SCENARIO SHIFTS
B35: Mid-year convention offset (0.5 = mid-year, 0 = end of year) | D35: 0.5 | E35: Engine convention: cash flow t is discounted t - offset years from 31-Dec-2025.
B36: Years since last fiscal year-end (31-Dec-2025 to the valuation date) | D36: 0.7918 | E36: Roll-forward of equity value to today at the cost of equity (engine approximation).
B37: Terminal growth (g), nominal MXN | D37: 0.0425 | E37: [assumption] 4.25%: long-run mix of ~36% North America at ~3% in MXN and ~64% Mexico/LatAm/EAA at ~5% (team decision)
B38: Exit EV / EBITDA multiple (trailing, applied to final-year EBITDA) | D38: 6 | E38: [calc] eligible-peer median LTM EV/EBITDA on the IFRS 16 basis (BIMBOA_PeerAnalysis_v1.xlsx) - team decision
B39: Long-term nominal GDP growth, MXN (cap for g) | D39: 0.05 | E39: [assumption] 5.0% = ~2% real potential growth + 3% Banxico target (real growth source not yet retrieved)
B40: Scenario: revenue growth shift added to every forecast year (0 = base case) | D40: 0 | E40: Used by the reverse DCF (Goal Seek this cell). Keep 0 for the base case.
B41: Scenario: gross margin shift, all forecast years (e.g. -0.01 = -100 bp wheat shock) | D41: 0 | E41: Climate / input-cost scenario lever. Keep 0 for the base case.
B42: Scenario: capex / revenue shift, all forecast years (e.g. +0.005 = +50 bp) | D42: 0 | E42: Reinvestment lever (debt / FCF pillar). Keep 0 for the base case.
B44: FORECAST DRIVERS (model/drivers.yaml; history = implied values) | D44: FY2021A | E44: FY2022A | F44: FY2023A | G44: FY2024A | H44: FY2025A | I44: FY2026E | J44: FY2027E | K44: FY2028E | L44: FY2029E | M44: FY2030E | N44: FY2031E | O44: FY2032E | P44: FY2033E | Q44: FY2034E | R44: FY2035E | S44: Tag / source / note
B45: North America revenue growth | I45: -0.074 | J45: 0.03 | K45: 0.03 | L45: 0.03 | M45: 0.03 | N45: 0.03 | O45: 0.03 | P45: 0.03 | Q45: 0.03 | R45: 0.03 | S45: [assumption] STORY DRIVER (proposal). FY26 = 1H26 actual (84,901, -11.3% in MXN; ex-FX +0.7%/+1.3% in 1Q/2Q26) plus 2H26 at -3.5% (ex-FX +1.5%, peso about -5% vs 2H25) [calc] wiki quarterly trend. FY27+: USD growth ~+1.5% (category volume -2% to -4%, price/mix +1-2%, share gains claimed by management) plus ~1.5%/yr MXN depreciation (inflation differential) [assumption].
B46: Mexico revenue growth | I46: 0.046 | J46: 0.055 | K46: 0.0525 | L46: 0.0525 | M46: 0.0525 | N46: 0.0515 | O46: 0.051 | P46: 0.0505 | Q46: 0.05 | R46: 0.05 | S46: [assumption] STORY DRIVER (proposal). FY26 = 1H26 +4.6% and 2H26 +4.7% (1Q26 +4.5%, 2Q26 +4.7%) [calc]. FY27+: packaged bakery market ~3.5% value CAGR 2024-29E (RA25 p.111) plus price/mix with ~3.5-3.8% inflation; fades to 5.0% (long-run nominal) [assumption].
B47: Europe, Asia & Africa revenue growth | I47: 0.006 | J47: 0.045 | K47: 0.045 | L47: 0.045 | M47: 0.045 | N47: 0.0445 | O47: 0.044 | P47: 0.0435 | Q47: 0.043 | R47: 0.0425 | S47: [assumption] Proposal. FY26 = 1H26 +1.3% in MXN (ex-FX +12.6%/+8.4% incl. 2025 bolt-ons) with flat 2H26 after FX [calc]. FY27+: organic ~4.5% (European market 3.4%, Eastern Europe 6.6% CAGR per RA25 p.108), no new M&A [assumption].
B48: Latin America revenue growth | I48: 0.085 | J48: 0.07 | K48: 0.065 | L48: 0.065 | M48: 0.065 | N48: 0.063 | O48: 0.061 | P48: 0.059 | Q48: 0.057 | R48: 0.055 | S48: [assumption] Proposal. FY26 = 1H26 +7.1% plus 2H26 ~+10% (Wickbold consolidated from Oct-2025) [calc]. FY27+: LatAm bakery 5.5% CAGR (RA25 p.108) plus Wickbold synergies, fading to 5.5% [assumption].
B49: Inter-regional eliminations revenue growth | I49: 0.036 | J49: 0.045 | K49: 0.045 | L49: 0.045 | M49: 0.045 | N49: 0.045 | O49: 0.045 | P49: 0.045 | Q49: 0.045 | R49: 0.045 | S49: [assumption] Mechanical: inter-regional eliminations grow with regional sales (1H26 eliminations -8,545 vs -8,202 in 1H25, +4.2%) [calc].
B50: Gross margin | I50: 0.524 | J50: 0.52 | K50: 0.523 | L50: 0.525 | M50: 0.525 | N50: 0.525 | O50: 0.525 | P50: 0.525 | Q50: 0.525 | R50: 0.525 | S50: [assumption] pillar 1: STORY DRIVER (proposal; climate pillar). History 53.4/51.5/51.4/52.6/52.3% (FY21-25, model mapping). 1H26 ~52.6% on the model basis (CIQ 52.9% less the 0.33pp mapping gap) [calc]. CBOT wheat 2026 YTD average +17% vs 2025 and gross margin follows wheat with ~1-year lag (r = -0.74, n = 9; wiki bimbo-climate-metrics-capiq-2026-10) -> FY27 dip of 40bp, recovery to 52.5% [assumption].
B51: Operating expenses / revenue | I51: 0.436 | J51: 0.434 | K51: 0.433 | L51: 0.4325 | M51: 0.4305 | N51: 0.4305 | O51: 0.4305 | P51: 0.4305 | Q51: 0.4305 | R51: 0.4305 | S51: [assumption] pillar 2: STORY DRIVER (proposal; new-CEO pillar). Set so model EBITDA margin = 14.7% FY26 (FY25 13.8% + ~90bp, mid of the +70-120bp guidance raised on 2026-07-23 [guidance] 2Q26 call), 14.5% FY27 (wheat lag), then +20bp/yr productivity to 15.3% by FY30. Includes restructuring at a run-rate (FY24 6,293; FY25 3,908). History 43.8/38.0/42.5/44.5/44.4%.
B52: D&A / revenue | I52: 0.059 | J52: 0.059 | K52: 0.059 | L52: 0.0585 | M52: 0.0585 | N52: 0.0585 | O52: 0.0585 | P52: 0.0585 | Q52: 0.0585 | R52: 0.0585 | S52: [assumption] pillar -: Mechanical: FY24-FY25 5.65-5.82% incl. right-of-use depreciation (6,142 in FY25); held near 5.85-5.9% as capex normalises [calc] data/financials.csv.
B53: Capex / revenue | I53: 0.046 | J53: 0.05 | K53: 0.052 | L53: 0.054 | M53: 0.055 | N53: 0.056 | O53: 0.057 | P53: 0.058 | Q53: 0.059 | R53: 0.06 | S53: [assumption] pillar 3: STORY DRIVER (proposal; debt/FCF pillar). FY26 = guidance US$1.0-1.2bn (cut on 2026-07-23 [guidance]) at ~Ps 17.6/US$ = ~Ps 19.4bn = 4.6% of revenue; FY27-28 ~5.0-5.2% (consensus capex US$1.21-1.24bn [sourced] CIQ 2026-10-17). Rises to 6.0% by FY35 so terminal reinvestment (capex + new leases - D&A - NWC release ~1.4% of revenue) funds 4.25% nominal growth at a ~19% return on new capital (history 6.3/7.4/8.9/7.4/5.4%, FY21-25 average 7.0%) [assumption].
B54: Lease principal repaid / revenue (engine: = new leases) | I54: 0.0139 | J54: 0.0139 | K54: 0.0139 | L54: 0.0139 | M54: 0.0139 | N54: 0.0139 | O54: 0.0139 | P54: 0.0139 | Q54: 0.0139 | R54: 0.0139 | S54: [assumption] pillar -: Mechanical: FY25 lease principal 5,923 / revenue 426,952 = 1.39% (FY23-25: 1.20/1.30/1.39%) [calc]. Principal is derived (payments 8,060 less lease interest 2,137) and tagged unverified in data/financials.csv. The engine also uses it as new leases; the right-of-use-addition variant is in valuation/BIMBOA_DCF_v1.xlsx.
B55: Receivable days (DSO, on revenue) | I55: 20.3 | J55: 20.3 | K55: 20.3 | L55: 20.3 | M55: 20.3 | N55: 20.3 | O55: 20.3 | P55: 20.3 | Q55: 20.3 | R55: 20.3 | S55: [assumption] pillar -: Mechanical: FY25 20.3 days (FY21-25 range 19.4-21.1) on trade receivables only [calc].
B56: Inventory days (DIO, on cost of sales) | I56: 30.8 | J56: 30.8 | K56: 30.8 | L56: 30.8 | M56: 30.8 | N56: 30.8 | O56: 30.8 | P56: 30.8 | Q56: 30.8 | R56: 30.8 | S56: [assumption] pillar -: Mechanical: FY25 30.8 days on cost of sales (FY21-25 range 30.3-35.5) [calc].
... B61: Right-of-use additions / revenue (lease-schedule variant only) | I61: 0.0163 | J61: 0.0163 | K61: 0.0163 | L61: 0.0163 | M61: 0.0163 | N61: 0.0163 | O61: 0.0163 | P61: 0.0163 | Q61: 0.0163 | R61: 0.0163 | S61: [calc] FY23-25 average (new leases + modifications) / revenue = 1.63% (data/adjustments.md lease table)
B63: PROJECTED CASH FLOWS (MXN millions) | D63: FY2021A | E63: FY2022A | F63: FY2023A | G63: FY2024A | H63: FY2025A | I63: FY2026E | J63: FY2027E | K63: FY2028E | L63: FY2029E | M63: FY2030E | N63: FY2031E | O63: FY2032E | P63: FY2033E | Q63: FY2034E | R63: FY2035E | S63: Tag / source / note
B64: North America | D64: 175369 | E64: 205674 | F64: 192534 | G64: 189330 | H64: 190211 | I64: =H64*(1+I45+$D$40) -> 176135.39 | J64: =I64*(1+J45+$D$40) -> 181419.45 | K64: =J64*(1+K45+$D$40) -> 186862.03 | L64: =K64*(1+L45+$D$40) -> 192467.89 | M64: =L64*(1+M45+$D$40) -> 198241.93 | N64: =M64*(1+N45+$D$40) -> 204189.19 | O64: =N64*(1+O45+$D$40) -> 210314.86 | P64: =O64*(1+P45+$D$40) -> 216624.31 | ... R64: =Q64*(1+R45+$D$40) -> 229816.73 | S64: [sourced] segment revenue, data/financials.csv (history)
B65: Mexico | D65: 109089 | E65: 130401 | F65: 145387 | G65: 151164 | H65: 154809 | I65: =H65*(1+I46+$D$40) -> 161930.21 | J65: =I65*(1+J46+$D$40) -> 170836.38 | K65: =J65*(1+K46+$D$40) -> 179805.29 | L65: =K65*(1+L46+$D$40) -> 189245.06 | M65: =L65*(1+M46+$D$40) -> 199180.43 | N65: =M65*(1+N46+$D$40) -> 209438.22 | O65: =N65*(1+O46+$D$40) -> 220119.57 | P65: =O65*(1+P46+$D$40) -> 231235.61 | ... R65: =Q65*(1+R46+$D$40) -> 254937.26 | S65: [sourced] segment revenue, data/financials.csv (history)
B66: Europe, Asia & Africa | D66: 34195 | E66: 37536 | F66: 40545 | G66: 45044 | H66: 54214 | I66: =H66*(1+I47+$D$40) -> 54539.284 | J66: =I66*(1+J47+$D$40) -> 56993.552 | K66: =J66*(1+K47+$D$40) -> 59558.262 | L66: =K66*(1+L47+$D$40) -> 62238.383 | M66: =L66*(1+M47+$D$40) -> 65039.111 | N66: =M66*(1+N47+$D$40) -> 67933.351 | O66: =N66*(1+O47+$D$40) -> 70922.419 | P66: =O66*(1+P47+$D$40) -> 74007.544 | ... R66: =Q66*(1+R47+$D$40) -> 80470.437 | S66: [sourced] segment revenue, data/financials.csv (history)
B67: Latin America | D67: 31109 | E67: 38411 | F67: 36647 | G67: 39879 | H67: 44120 | I67: =H67*(1+I48+$D$40) -> 47870.2 | J67: =I67*(1+J48+$D$40) -> 51221.114 | K67: =J67*(1+K48+$D$40) -> 54550.486 | L67: =K67*(1+L48+$D$40) -> 58096.268 | M67: =L67*(1+M48+$D$40) -> 61872.525 | N67: =M67*(1+N48+$D$40) -> 65770.495 | O67: =N67*(1+O48+$D$40) -> 69782.495 | P67: =O67*(1+P48+$D$40) -> 73899.662 | ... R67: =Q67*(1+R48+$D$40) -> 82408.099 | S67: [sourced] segment revenue, data/financials.csv (history)
B68: Inter-regional eliminations | D68: -10970 | E68: -13316 | F68: -15234 | G68: -17082 | H68: -16402 | I68: =H68*(1+I49+$D$40) -> -16992.472 | J68: =I68*(1+J49+$D$40) -> -17757.133 | K68: =J68*(1+K49+$D$40) -> -18556.204 | L68: =K68*(1+L49+$D$40) -> -19391.233 | M68: =L68*(1+M49+$D$40) -> -20263.839 | N68: =M68*(1+N49+$D$40) -> -21175.712 | O68: =N68*(1+O49+$D$40) -> -22128.619 | P68: =O68*(1+P49+$D$40) -> -23124.407 | ... R68: =Q68*(1+R49+$D$40) -> -25252.43 | S68: [sourced] segment revenue, data/financials.csv (history)
B69: Total revenue | D69: 338792 | E69: 398706 | F69: 399879 | G69: 408335 | H69: 426952 | I69: =SUM(I64:I68) -> 423482.61 | J69: =SUM(J64:J68) -> 442713.36 | K69: =SUM(K64:K68) -> 462219.86 | L69: =SUM(L64:L68) -> 482656.37 | M69: =SUM(M64:M68) -> 504070.15 | N69: =SUM(N64:N68) -> 526155.54 | O69: =SUM(O64:O68) -> 549010.73 | P69: =SUM(P64:P68) -> 572642.72 | ... R69: =SUM(R64:R68) -> 622380.09 | S69: [sourced] history data/financials.csv; forecast = sum of segments (or growth driver)
B70: Annual growth | E70: =E69/D69-1 -> 0.17684597 | F70: =F69/E69-1 -> 0.0029420174 | G70: =G69/F69-1 -> 0.021146397 | H70: =H69/G69-1 -> 0.045592467 | I70: =I69/H69-1 -> -0.0081259439 | J70: =J69/I69-1 -> 0.045410941 | K70: =K69/J69-1 -> 0.044061251 | L70: =L69/K69-1 -> 0.044213835 | ... R70: =R69/Q69-1 -> 0.042412788
B71: Cost of sales | D71: 157703 | E71: 193325 | F71: 194369 | G71: 193407 | H71: 203465 | I71: =I69*(1-(I50+$D$41)) -> 201577.72 | J71: =J69*(1-(J50+$D$41)) -> 212502.41 | K71: =K69*(1-(K50+$D$41)) -> 220478.87 | L71: =L69*(1-(L50+$D$41)) -> 229261.78 | M71: =M69*(1-(M50+$D$41)) -> 239433.32 | N71: =N69*(1-(N50+$D$41)) -> 249923.88 | O71: =O69*(1-(O50+$D$41)) -> 260780.1 | P71: =P69*(1-(P50+$D$41)) -> 272005.29 | ... R71: =R69*(1-(R50+$D$41)) -> 295630.54 | S71: Forecast = revenue x (1 - (gross margin + scenario shift))
B72: Gross profit | D72: =D69-D71 -> 181089 | E72: =E69-E71 -> 205381 | F72: =F69-F71 -> 205510 | G72: =G69-G71 -> 214928 | H72: =H69-H71 -> 223487 | I72: =I69-I71 -> 221904.89 | J72: =J69-J71 -> 230210.95 | K72: =K69-K71 -> 241740.99 | ... R72: =R69-R71 -> 326749.55
B73: Gross margin | D73: =D72/D69 -> 0.5345138 | E73: =E72/E69 -> 0.51511891 | F73: =F72/F69 -> 0.51393046 | G73: =G72/G69 -> 0.52635214 | H73: =H72/H69 -> 0.5234476 | I73: =I72/I69 -> 0.524 | J73: =J72/J69 -> 0.52 | K73: =K72/K69 -> 0.523 | ... R73: =R72/R69 -> 0.525
B74: Operating expenses (net, incl. PTU) | D74: 148509 | E74: 151685 | F74: 170055 | G74: 181779 | H74: 189341 | I74: =I69*I51 -> 184638.42 | J74: =J69*J51 -> 192137.6 | K74: =K69*K51 -> 200141.2 | L74: =L69*L51 -> 208748.88 | M74: =M69*M51 -> 217002.2 | N74: =N69*N51 -> 226509.96 | O74: =O69*O51 -> 236349.12 | P74: =P69*P51 -> 246522.69 | ... R74: =R69*R51 -> 267934.63
B75: EBIT | D75: =D72-D74 -> 32580 | E75: =E72-E74 -> 53696 | F75: =F72-F74 -> 35455 | G75: =G72-G74 -> 33149 | H75: =H72-H74 -> 34146 | I75: =I72-I74 -> 37266.47 | J75: =J72-J74 -> 38073.349 | K75: =K72-K74 -> 41599.787 | ... R75: =R72-R74 -> 58814.919
B76: EBIT margin | D76: =D75/D69 -> 0.096165199 | E76: =E75/E69 -> 0.13467568 | F76: =F75/F69 -> 0.088664321 | G76: =G75/G69 -> 0.081180893 | H76: =H75/H69 -> 0.079976203 | I76: =I75/I69 -> 0.088 | J76: =J75/J69 -> 0.086 | K76: =K75/K69 -> 0.09 | ... R76: =R75/R69 -> 0.0945
B77: D&A (incl. right-of-use depreciation) | D77: 16126 | E77: 18038 | F77: 18929 | G77: 23051 | H77: 24838 | I77: =I69*I52 -> 24985.474 | J77: =J69*J52 -> 26120.088 | K77: =K69*K52 -> 27270.972 | L77: =L69*L52 -> 28235.398 | M77: =M69*M52 -> 29488.104 | N77: =N69*N52 -> 30780.099 | O77: =O69*O52 -> 32117.128 | P77: =P69*P52 -> 33499.599 | ... R77: =R69*R52 -> 36409.235
B78: EBITDA (post-IFRS 16) = EBIT + D&A | D78: =D75+D77 -> 48706 | E78: =E75+E77 -> 71734 | F78: =F75+F77 -> 54384 | G78: =G75+G77 -> 56200 | H78: =H75+H77 -> 58984 | I78: =I75+I77 -> 62251.944 | J78: =J75+J77 -> 64193.437 | K78: =K75+K77 -> 68870.759 | ... R78: =R75+R77 -> 95224.154 | S78: Engine definition. Company Adjusted EBITDA adds back one-offs (bridge in data/adjustments.md).
B79: EBITDA margin | D79: =D78/D69 -> 0.14376373 | E79: =E78/E69 -> 0.17991703 | F79: =F78/F69 -> 0.13600114 | G79: =G78/G69 -> 0.13763209 | H79: =H78/H69 -> 0.13815136 | I79: =I78/I69 -> 0.147 | J79: =J78/J69 -> 0.145 | K79: =K78/K69 -> 0.149 | ... R79: =R78/R69 -> 0.153
B80: Tax rate on EBIT | D80: 0.33422706 | E80: 0.2287564 | F80: 0.33135767 | G80: 0.32615163 | H80: 0.35729534 | I80: =I60 -> 0.34 | J80: =J60 -> 0.34 | K80: =K60 -> 0.34 | L80: =L60 -> 0.34 | M80: =M60 -> 0.34 | N80: =N60 -> 0.34 | O80: =O60 -> 0.34 | P80: =P60 -> 0.34 | ... R80: =R60 -> 0.34 | S80: History: effective rate = income tax / pre-tax income (display only); forecast: tax driver
B81: Less: taxes on EBIT | D81: =-D75*D80 -> -10889.118 | E81: =-E75*E80 -> -12283.304 | F81: =-F75*F80 -> -11748.286 | G81: =-G75*G80 -> -10811.6 | H81: =-H75*H80 -> -12200.207 | I81: =-I75*I80 -> -12670.6 | J81: =-J75*J80 -> -12944.939 | K81: =-K75*K80 -> -14143.928 | ... R81: =-R75*R80 -> -19997.072
B82: NOPAT (unlevered net income) | D82: =D75+D81 -> 21690.882 | E82: =E75+E81 -> 41412.696 | F82: =F75+F81 -> 23706.714 | G82: =G75+G81 -> 22337.4 | H82: =H75+H81 -> 21945.793 | I82: =I75+I81 -> 24595.87 | J82: =J75+J81 -> 25128.41 | K82: =K75+K81 -> 27455.86 | ... R82: =R75+R81 -> 38817.846
B83: Plus: D&A | D83: =D77 -> 16126 | E83: =E77 -> 18038 | F83: =F77 -> 18929 | G83: =G77 -> 23051 | H83: =H77 -> 24838 | I83: =I77 -> 24985.474 | J83: =J77 -> 26120.088 | K83: =K77 -> 27270.972 | ... R83: =R77 -> 36409.235
B84: Less: capital expenditures (PP&E + intangibles) | D84: -21293 | E84: -29467 | F84: -35672 | G84: -30174 | H84: -22841 | I84: =-I69*(I53+$D$42) -> -19480.2 | J84: =-J69*(J53+$D$42) -> -22135.668 | K84: =-K69*(K53+$D$42) -> -24035.433 | L84: =-L69*(L53+$D$42) -> -26063.444 | M84: =-M69*(M53+$D$42) -> -27723.859 | N84: =-N69*(N53+$D$42) -> -29464.71 | O84: =-O69*(O53+$D$42) -> -31293.611 | P84: =-P69*(P53+$D$42) -> -33213.278 | ... R84: =-R69*(R53+$D$42) -> -37342.806
B85: Less: new leases (IFRS 16; engine proxy = lease principal repaid) | D85: -4117 | E85: -5056 | F85: -4802 | G85: -5321 | H85: -5923 | I85: =-I69*I54 -> -5886.4083 | J85: =-J69*J54 -> -6153.7156 | K85: =-K69*K54 -> -6424.8561 | L85: =-L69*L54 -> -6708.9236 | M85: =-M69*M54 -> -7006.5751 | N85: =-N69*N54 -> -7313.562 | O85: =-O69*O54 -> -7631.2491 | P85: =-P69*P54 -> -7959.7337 | ... R85: =-R69*R54 -> -8651.0833 | S85: Engine replacement approximation; the lease-schedule variant below uses right-of-use additions.
B86: Plus / (less): change in operating working capital | E86: =E98 -> 6533 | F86: =F98 -> -10264 | G86: =G98 -> -1918 | H86: =H98 -> 696 | I86: =I98 -> -100.99899 | J86: =J98 -> 854.80503 | K86: =K98 -> 532.75628 | L86: =L98 -> 604.04037 | ... R86: =R98 -> 871.80022 | S86: From the working-capital schedule below
B87: Unlevered free cash flow (FCFF) | E87: =E82+E83+E84+E85+E86 -> 31460.696 | F87: =F82+F83+F84+F85+F86 -> -8102.2863 | G87: =G82+G83+G84+G85+G86 -> 7975.3996 | H87: =H82+H83+H84+H85+H86 -> 18715.793 | I87: =I82+I83+I84+I85+I86 -> 24113.737 | J87: =J82+J83+J84+J85+J86 -> 23813.92 | K87: =K82+K83+K84+K85+K86 -> 24799.299 | L87: =L82+L83+L84+L85+L86 -> 25533.242 | ... R87: =R82+R83+R84+R85+R86 -> 30104.993 | S87: Engine: FCFF = NOPAT + D&A - capex - new leases + change in NWC. History: display only.
B88: Annual growth | J88: =IFERROR(J87/I87-1,0) -> -0.012433457 | K88: =IFERROR(K87/J87-1,0) -> 0.04137829 | L88: =IFERROR(L87/K87-1,0) -> 0.029595316 | M88: =IFERROR(M87/L87-1,0) -> 0.054850249 | N88: =IFERROR(N87/M87-1,0) -> 0.023938133 | O88: =IFERROR(O87/N87-1,0) -> 0.02329425 | P88: =IFERROR(P87/O87-1,0) -> 0.022500729 | Q88: =IFERROR(Q87/P87-1,0) -> 0.021675359 | R88: =IFERROR(R87/Q87-1,0) -> 0.021153348
B89: FCFF margin | I89: =I87/I69 -> 0.056941504 | J89: =J87/J69 -> 0.053790832 | K89: =K87/K69 -> 0.053652604 | L89: =L87/L69 -> 0.052901492 | M89: =M87/M69 -> 0.053432536 | N89: =N87/N69 -> 0.052415091 | O89: =O87/O69 -> 0.051403204 | P89: =P87/P69 -> 0.05039076 | ... R89: =R87/R69 -> 0.048370752
B91: WORKING CAPITAL SCHEDULE (operating items only; financing balances excluded) | D91: FY2021A | E91: FY2022A | F91: FY2023A | G91: FY2024A | H91: FY2025A | I91: FY2026E | J91: FY2027E | K91: FY2028E | L91: FY2029E | M91: FY2030E | N91: FY2031E | O91: FY2032E | P91: FY2033E | Q91: FY2034E | R91: FY2035E | S91: Tag / source / note
B92: Accounts receivable | D92: 19184 | E92: 21600 | F92: 21268 | G92: 23555 | H92: 23784 | I92: =I69*I55/365 -> 23552.595 | J92: =J69*J55/365 -> 24622.14 | K92: =K69*K55/365 -> 25707.022 | L92: =L69*L55/365 -> 26843.628 | M92: =M69*M55/365 -> 28034.587 | N92: =N69*N55/365 -> 29262.897 | O92: =O69*O55/365 -> 30534.021 | P92: =P69*P55/365 -> 31848.348 | ... R92: =R69*R55/365 -> 34614.564
B93: Inventories | D93: 13710 | E93: 16989 | F93: 16120 | G93: 18832 | H93: 17151 | I93: =I71*I56/365 -> 17009.846 | J93: =J71*J56/365 -> 17931.71 | K93: =K71*K56/365 -> 18604.793 | L93: =L71*L56/365 -> 19345.925 | M93: =M71*M56/365 -> 20204.237 | N93: =N71*N56/365 -> 21089.467 | O93: =O71*O56/365 -> 22005.553 | P93: =P71*P56/365 -> 22952.775 | ... R93: =R71*R56/365 -> 24946.358
B94: Other current assets | D94: 11769 | E94: 12568 | F94: 15173 | G94: 16736 | H94: 15201 | I94: =I69*I58 -> 15075.981 | J94: =J69*J58 -> 15760.595 | K94: =K69*K58 -> 16455.027 | L94: =L69*L58 -> 17182.567 | M94: =M69*M58 -> 17944.898 | N94: =N69*N58 -> 18731.137 | O94: =O69*O58 -> 19544.782 | P94: =P69*P58 -> 20386.081 | ... R94: =R69*R58 -> 22156.731
B95: Accounts payable | D95: 35752 | E95: 44058 | F95: 40409 | G95: 40815 | H95: 39074 | I95: =I71*I57/365 -> 38713.968 | J95: =J71*J57/365 -> 40812.107 | K95: =K71*K57/365 -> 42344.025 | L95: =L71*L57/365 -> 44030.823 | M95: =M71*M57/365 -> 45984.318 | N95: =N71*N57/365 -> 47999.08 | O95: =O71*O57/365 -> 50084.068 | P95: =P71*P57/365 -> 52239.92 | ... R95: =R71*R57/365 -> 56777.263
B96: Other current liabilities (non-debt) | D96: 28590 | E96: 33311 | F96: 28100 | G96: 32338 | H96: 31788 | I96: =I69*I59 -> 31549.455 | J96: =J69*J59 -> 32982.145 | K96: =K69*K59 -> 34435.38 | L96: =L69*L59 -> 35957.9 | M96: =M69*M59 -> 37553.227 | N96: =N69*N59 -> 39198.588 | O96: =O69*O59 -> 40901.299 | P96: =P69*P59 -> 42661.882 | ... R96: =R69*R59 -> 46367.317
B97: Net operating working capital | D97: =D92+D93+D94-D95-D96 -> -19679 | E97: =E92+E93+E94-E95-E96 -> -26212 | F97: =F92+F93+F94-F95-F96 -> -15948 | G97: =G92+G93+G94-G95-G96 -> -14030 | H97: =H92+H93+H94-H95-H96 -> -14726 | I97: =I92+I93+I94-I95-I96 -> -14625.001 | J97: =J92+J93+J94-J95-J96 -> -15479.806 | K97: =K92+K93+K94-K95-K96 -> -16012.562 | ... R97: =R92+R93+R94-R95-R96 -> -21426.927
B98: (Increase) / decrease in working capital (cash-flow sign) | E98: =-(E97-D97) -> 6533 | F98: =-(F97-E97) -> -10264 | G98: =-(G97-F97) -> -1918 | H98: =-(H97-G97) -> 696 | I98: =-(I97-H97) -> -100.99899 | J98: =-(J97-I97) -> 854.80503 | K98: =-(K97-J97) -> 532.75628 | L98: =-(L97-K97) -> 604.04037 | ... R98: =-(R97-Q97) -> 871.80022 | S98: Engine: change_nwc = -(dAR + dInv + dOCA - dAP - dOCL); an increase in NWC reduces FCFF.
B100: DISCOUNTING (to 31-Dec-2025; engine convention) | D100: FY2021A | E100: FY2022A | F100: FY2023A | G100: FY2024A | H100: FY2025A | I100: FY2026E | J100: FY2027E | K100: FY2028E | L100: FY2029E | M100: FY2030E | N100: FY2031E | O100: FY2032E | P100: FY2033E | Q100: FY2034E | R100: FY2035E | S100: Tag / source / note
B101: Forecast year number | I101: 1 | J101: 2 | K101: 3 | L101: 4 | M101: 5 | N101: 6 | O101: 7 | P101: 8 | Q101: 9 | R101: 10
B102: Discount period = year number - mid-year offset | I102: =I101-$D$35 -> 0.5 | J102: =J101-$D$35 -> 1.5 | K102: =K101-$D$35 -> 2.5 | L102: =L101-$D$35 -> 3.5 | M102: =M101-$D$35 -> 4.5 | N102: =N101-$D$35 -> 5.5 | O102: =O101-$D$35 -> 6.5 | P102: =P101-$D$35 -> 7.5 | ... R102: =R101-$D$35 -> 9.5
B103: Discount factor = 1 / (1 + WACC) ^ period | I103: =1/(1+$D$32)^I102 -> 0.9528075 | J103: =1/(1+$D$32)^J102 -> 0.86499879 | K103: =1/(1+$D$32)^K102 -> 0.78528234 | L103: =1/(1+$D$32)^L102 -> 0.71291239 | M103: =1/(1+$D$32)^M102 -> 0.6472119 | N103: =1/(1+$D$32)^N102 -> 0.58756623 | O103: =1/(1+$D$32)^O102 -> 0.53341738 | P103: =1/(1+$D$32)^P102 -> 0.48425877 | ... R103: =1/(1+$D$32)^R102 -> 0.3991151
B104: Present value of FCFF | I104: =I87*I103 -> 22975.749 | J104: =J87*J103 -> 20599.012 | K104: =K87*K103 -> 19474.451 | L104: =L87*L103 -> 18202.965 | M104: =M87*M103 -> 17431.841 | N104: =N87*N103 -> 16204.19 | O104: =O87*O103 -> 15053.524 | P104: =P87*P103 -> 13973.723 | ... R104: =R87*R103 -> 12015.357
B106: PRESENT VALUE OF THE ENTERPRISE
B107: Sum of PV of FCFF, FY2026E-FY2035E | D107: =SUM(I104:R104) -> 168891.72
B108: Terminal value - Gordon growth = FCFF_N x (1 + g) / (WACC - g) | D108: =R87*(1+$D$37)/($D$32-$D$37) -> 531821.81
B109: PV of terminal value - Gordon (discounted N - offset: value as of the last cash flow's date) | D109: =$D$108/(1+$D$32)^(10-$D$35) -> 212258.11
B110: Enterprise value - Gordon | D110: =$D$107+$D$109 -> 381149.83
B111: Terminal value - exit multiple = final-year EBITDA x multiple | D111: =R78*$D$38 -> 571344.93
B112: PV of terminal value - exit (a year-end value, discounted N) | D112: =$D$111/(1+$D$32)^10 -> 217270.97
B113: Enterprise value - exit multiple | D113: =$D$107+$D$112 -> 386162.69
...

Sheet Reverse_DCF
B2: Reverse Discounted Cash Flow - what the market price implies
B3: Layout after the S&P 'Reverse_DCF' tab. The template imputes growth with a VBA macro; here the procedure is Excel Goal Seek on a single input cell (no macros).
B5: 1. Terminal growth implied by the market price (closed form, engine definition)
B6: Market EV at FYE = price / roll-forward x shares + net debt + NCI + debt-like - non-op | D6: =DCF!$D$132/DCF!$D$134*DCF!$D$131+DCF!$D$122+DCF!$D$129+DCF!$D$127-DCF!$D$130 -> 430011.29
B7: PV of explicit FCFF (from the DCF) | D7: =DCF!$D$107 -> 168891.72
B8: Terminal value implied by the market (at the Gordon discount date) | D8: =($D$6-$D$7)*(1+DCF!$D$32)^(10-DCF!$D$35) -> 654246.3
B9: Terminal growth implied by the market price | D9: =IF($D$6>$D$7,($D$8*DCF!$D$32-DCF!R87)/($D$8+DCF!R87),"n.m.") -> 0.053056931
B10: Terminal growth used in the DCF | D10: =DCF!$D$37 -> 0.0425
B11: Guard: defined only when the market EV exceeds the PV of the explicit cash flows.
B13: 2. Revenue growth shift implied by the market price (all other drivers fixed)
B14: Procedure | E14: Data > What-If Analysis > Goal Seek: set 'DCF'!D138 (Gordon value today) to the current price by changing 'DCF'!D40. Reset the shift to 0 afterwards.
B15: Reference solution - Gordon (Python bisection, valuation/build/dcf_core.py) | D15: 0.014874779 | E15: Uniform shift added to every forecast year's growth driver; n.a. if no solution in -10%..+10%.
B16: Reference solution - exit multiple | D16: 0.013850744 | E16: '

Sheet Levers
B2: Story levers - value per share today (Gordon and exit), MXN
B3: STATIC values computed by valuation/build/dcf_core.py from the same inputs (same engine conventions); rebuild to refresh. Live single-scenario levers: the shift inputs on the 'DCF' sheet.
B5: Value per share today - Gordon: capex/revenue shift (rows) x gross margin shift (columns)
B6: Capex shift (rows) / GM shift (columns) | C6: -0.01 | D6: -0.005 | E6: 0 | F6: 0.005 | G6: 0.01
B7: -0.01 | C7: 52.921717 | D7: 59.217568 | E7: 65.513418 | F7: 71.809268 | G7: 78.105118
B8: -0.005 | C8: 43.237019 | D8: 49.53287 | E8: 55.82872 | F8: 62.12457 | G8: 68.42042
B9: 0 | C9: 33.552321 | D9: 39.848171 | E9: 46.144022 | F9: 52.439872 | G9: 58.735722
B10: 0.005 | C10: 23.867623 | D10: 30.163473 | E10: 36.459324 | F10: 42.755174 | G10: 49.051024
B11: 0.01 | C11: 14.182925 | D11: 20.478775 | E11: 26.774625 | F11: 33.070476 | G11: 39.366326
B13: Value per share today - exit multiple: capex/revenue shift (rows) x gross margin shift (columns)
B14: Capex shift (rows) / GM shift (columns) | C14: -0.01 | D14: -0.005 | E14: 0 | F14: 0.005 | G14: 0.01
B15: -0.01 | C15: 46.727104 | D15: 51.165979 | E15: 55.604853 | F15: 60.043728 | G15: 64.482602
B16: -0.005 | C16: 42.635638 | D16: 47.074512 | E16: 51.513387 | F16: 55.952262 | G16: 60.391136
B17: 0 | C17: 38.544171 | D17: 42.983046 | E17: 47.421921 | F17: 51.860795 | G17: 56.29967
B18: 0.005 | C18: 34.452705 | D18: 38.89158 | E18: 43.330454 | F18: 47.769329 | G18: 52.208204
B19: 0.01 | C19: 30.361239 | D19: 34.800113 | E19: 39.238988 | F19: 43.677863 | G19: 48.116737
B21: Terminal economics by capex shift (Gordon)
B22: Capex shift | C22: Value / share | D22: tv_ronic | E22: FY2035 FCFF margin
B23: -0.01 | C23: 65.513418 | D23: 0.66280587 | E23: 0.058370752
B24: -0.005 | C24: 55.82872 | D24: 0.29454961 | E24: 0.053370752
B25: 0 | C25: 46.144022 | D25: 0.18934767 | E25: 0.048370752
B26: 0.005 | C26: 36.459324 | D26: 0.13951736 | E26: 0.043370752
B27: 0.01 | C27: 26.774625 | D27: 0.11045034 | E27: 0.038370752
B29: Revenue growth shift (all segments, all years) - value per share today
B30: Growth shift | C30: Gordon | D30: Exit
B31: -0.01 | C31: 38.579753 | D31: 40.064278
B32: -0.005 | C32: 42.284604 | D32: 43.671769
B33: 0 | C33: 46.144022 | D33: 47.421921
B34: 0.005 | C34: 50.164069 | D34: 51.320031
B35: 0.01 | C35: 54.351022 | D35: 55.371573

Sheet Dated_Check
B2: Valuation-date cross-check (anchored at the latest balance sheet, 30-Jun-2026)
B3: Independent of the engine's FYE roll-forward. Still a roll-forward approximation from 30-Jun to the valuation date, not an observed October balance sheet.
B5: 1H26 actual FCFF (same definition as the forecast FCFF)
B6: EBIT 1H26 (operating income) | D6: 18858.3 | E6: [sourced] Operating income 1Q26 10,030.8 + 2Q26 8,827.5, S&P Capital IQ quarterly (data/capitaliq/income_statement.csv)
B7: Less: one-off gain in 1H26 EBIT (La Moderna stake sale, ~50 bp of 1Q26 sales) | D7: 501.6 | E7: [unverified] Gain on the sale of a minority stake in Grupo La Moderna, ~50 bp of 1Q26 sales 100,319 (call 2026-04-29 p.7; amount not disclosed); cash already in Jun-26 cash
B8: Tax rate (FY2026 forecast driver) | D8: =DCF!I60 -> 0.34
B9: D&A 1H26 | D9: 12125.1 | E9: [sourced] D&A total 1Q26 6,028.4 + 2Q26 6,096.7, CIQ quarterly cash flow (CIQ D&A runs ~3% below the filing basis)
B10: Capex 1H26 (positive) | D10: 6942 | E10: [sourced] PP&E 6,892 + intangibles 50, BMV Jun-26 p.17-18 (wiki bimbo-cash-flow-and-fcf)
B11: Lease principal paid 1H26 (positive) | D11: 2879 | E11: [unverified] Lease payments 3,948 (BMV Jun-26 p.17-18) less lease interest ~1,069 (half of FY25 2,137), same derivation as data/financials.csv
B12: Change in operating NWC 1H26, cash-flow sign (Dec-25 to Jun-26 balance sheets, model mapping) | D12: 2529 | E12: [calc] Model mapping, Dec-25 to Jun-26 balance sheets (CIQ quarterly): AR +772, inventory -44, other CA +2,047, trade payables -830 (related-party split assumed equal to Dec-25), other CL +6,134 incl. seasonal tax payable +4,538; cash-flow sign. CIQ cash-flow basis shows -2,528 (memo)
B13: FCFF 1H26 = (EBIT - one-off) x (1 - tax) + D&A - capex - lease principal + change in NWC | D13: =($D$6-$D$7)*(1-$D$8)+$D$9-$D$10-$D$11+$D$12 -> 16948.522
B14: FY2026E FCFF (DCF) | D14: =DCF!I87 -> 24113.737
B15: 2H26E FCFF = FY2026E - 1H26 actual | D15: =$D$14-$D$13 -> 7165.2148
B17: Present value at 30-Jun-2026 (mid-period convention, same WACC)
B18: Discount time of 2H26 = 0.5 x (1 - offset) | D18: =0.5*(1-DCF!$D$35) -> 0.25
B19: PV of 2H26E FCFF | D19: =$D$15/(1+DCF!$D$32)^$D$18 -> 6994.0993
B20: PV of FY2027E FCFF (time = 1 + 0.5 - offset) | D20: =DCF!J87/(1+DCF!$D$32)^(1+0.5-DCF!$D$35) -> 21619.28
B21: PV of FY2028E FCFF (time = 2 + 0.5 - offset) | D21: =DCF!K87/(1+DCF!$D$32)^(2+0.5-DCF!$D$35) -> 20439.02
B22: PV of FY2029E FCFF (time = 3 + 0.5 - offset) | D22: =DCF!L87/(1+DCF!$D$32)^(3+0.5-DCF!$D$35) -> 19104.556
B23: PV of FY2030E FCFF (time = 4 + 0.5 - offset) | D23: =DCF!M87/(1+DCF!$D$32)^(4+0.5-DCF!$D$35) -> 18295.24
B24: PV of FY2031E FCFF (time = 5 + 0.5 - offset) | D24: =DCF!N87/(1+DCF!$D$32)^(5+0.5-DCF!$D$35) -> 17006.782
B25: PV of FY2032E FCFF (time = 6 + 0.5 - offset) | D25: =DCF!O87/(1+DCF!$D$32)^(6+0.5-DCF!$D$35) -> 15799.124
B26: PV of FY2033E FCFF (time = 7 + 0.5 - offset) | D26: =DCF!P87/(1+DCF!$D$32)^(7+0.5-DCF!$D$35) -> 14665.841
B27: PV of FY2034E FCFF (time = 8 + 0.5 - offset) | D27: =DCF!Q87/(1+DCF!$D$32)^(8+0.5-DCF!$D$35) -> 13602.86
B28: PV of FY2035E FCFF (time = 9 + 0.5 - offset) | D28: =DCF!R87/(1+DCF!$D$32)^(9+0.5-DCF!$D$35) -> 12610.477
B29: PV of terminal value - Gordon (at the final cash flow's date) | D29: =DCF!$D$108/(1+DCF!$D$32)^(9+0.5-DCF!$D$35) -> 222771.24
B30: PV of terminal value - exit (year-end FY2035) | D30: =DCF!$D$111/(1+DCF!$D$32)^(9+0.5) -> 228032.38
B31: EV at 30-Jun-2026 - Gordon | D31: =$D$19+$D$20+$D$21+$D$22+$D$23+$D$24+$D$25+$D$26+$D$27+$D$28+$D$29 -> 382908.52
B32: EV at 30-Jun-2026 - exit | D32: =$D$19+$D$20+$D$21+$D$22+$D$23+$D$24+$D$25+$D$26+$D$27+$D$28+$D$30 -> 388169.66
B34: Bridge at 30-Jun-2026 and roll to the valuation date
B35: Total debt ex-leases, 30-Jun-2026 | D35: 153660 | E35: [sourced] Total financial debt 30-Jun-2026 (BMV Jun-26 debt note; 2Q26 release p.6)
B36: Lease liabilities, 30-Jun-2026 | D36: 33361 | E36: [sourced] Lease liabilities 7,113 + 26,248, CIQ balance sheet 2026 FQ2
B37: Cash and equivalents, 30-Jun-2026 | D37: 16563 | E37: [sourced] Cash and equivalents 30-Jun-2026 (CIQ; net debt 137,097 per 2Q26 release p.6)
B38: Non-controlling interests, 30-Jun-2026 | D38: 721.7 | E38: [sourced] Total minority interest 30-Jun-2026, CIQ balance sheet
B39: Debt-like items, 30-Jun-2026 (same policy as valuation.yaml) | D39: 25593.2 | E39: [calc] Employee benefits incl. MEPP 6,202 x 0.7 + net derivative liabilities 3,185 (Dec-25; Jun-26 not disclosed) + NCI market-value uplift 18,066.8 (same policy as valuation.yaml)
B40: Non-operating assets, 30-Jun-2026 (same policy as valuation.yaml) | D40: 6497.5 | E40: [sourced] Equity-method investments 30-Jun-2026, CIQ balance sheet
B41: Equity at 30-Jun-2026 - Gordon | D41: =$D$31-($D$35+$D$36-$D$37)-$D$38-$D$39+$D$40 -> 192633.12
B42: Equity at 30-Jun-2026 - exit | D42: =$D$32-($D$35+$D$36-$D$37)-$D$38-$D$39+$D$40 -> 197894.26
B43: Days from 30-Jun-2026 to the valuation date | D43: 108 | E43: [calc] 30-Jun-2026 to 16-Oct-2026
B44: Roll factor = (1 + ke) ^ (days / 365) | D44: =(1+DCF!$D$28)^($D$43/365) -> 1.035857
B45: Distributions paid between 30-Jun and the valuation date (dividends + buybacks) | D45: 76 | E45: [unverified] July 2026 buybacks of 1,340,500 shares at ~MXN 57 (no cash disclosed); dividend paid 13-May-2026, before 30-Jun
B46: Shares outstanding at the valuation date, millions | D46: 4294.9437 | E46: [sourced] Shares outstanding 29-Jul-2026, BMV notice (wacc_inputs A8)
B47: Value per share at the valuation date - Gordon | D47: =($D$41*$D$44-$D$45)/$D$46 -> 46.441672
B48: Value per share at the valuation date - exit | D48: =($D$42*$D$44-$D$45)/$D$46 -> 47.710557
B50: Reconciliation with the engine's FYE roll-forward
B51: Engine-basis value today - Gordon ('DCF') | D51: =DCF!$D$138 -> 46.144022
B52: Dated value - Gordon | D52: =$D$47 -> 46.441672
B53: Difference - Gordon (dated - engine) | D53: =$D$47-DCF!$D$138 -> 0.29765053
B54: Difference - Gordon, % of engine value | D54: =$D$47/DCF!$D$138-1 -> 0.0064504678
B55: Engine-basis value today - exit | D55: =DCF!$D$145 -> 47.421921
B56: Dated value - exit | D56: =$D$48 -> 47.710557
B57: Difference - exit, % of engine value | D57: =$D$48/DCF!$D$145-1 -> 0.0060865675
B58: What explains the gap (filled from the build; tagged)
B59: The engine rolls Dec-25 equity forward at the cost of equity; the dated check starts from the 30-Jun-2026 balance sheet, which already reflects the 13-May-2026 dividend (MXN 4,627m) and 1H26 buybacks (MXN 496m).
B60: Net debt ex-IFRS 16 fell from 145,128 (Dec-25) to 137,097 (Jun-26), helped by peso strength on USD debt and 1H26 cash generation.
B61: Still an approximation: the roll from 30-Jun to 16-Oct uses the cost of equity, not an observed October balance sheet.

Sheet Engine_Recon
B2: Reconciliation with the model engine (model/model-summary.json)
B3: Engine values are pasted from the engine's summary (constants); workbook values are live formulas. Tolerance: relative difference below 1e-6.
B5: Item | D5: Engine summary | E5: This workbook | F5: Difference | G5: Rel. diff. | H5: Status | I5: Python replica | J5: Rel. diff. vs replica | K5: Status vs replica
B6: WACC | D6: 0.101513 | E6: =DCF!$D$32 -> 0.1015131 | F6: =IFERROR(E6-D6,"n.a.") -> 1.0378062e-07 | G6: =IFERROR(IF(D6=0,E6-D6,E6/D6-1),"n.a.") -> 1.0223382e-06 | H6: =IFERROR(IF(OR(ABS(G6)<0.000001,ABS(F6)<=0.0000005),"OK","CHECK"),"CHECK") -> OK | I6: 0.1015131 | J6: =IFERROR(IF(I6=0,E6-I6,E6/I6-1),"n.a.") -> 2.220446e-16 | K6: =IFERROR(IF(ABS(J6)<0.000001,"OK","CHECK"),"CHECK") -> OK
B7: EV - Gordon | D7: 381149.83 | E7: =DCF!$D$110 -> 381149.83 | F7: =IFERROR(E7-D7,"n.a.") -> 1.4959369e-08 | G7: =IFERROR(IF(D7=0,E7-D7,E7/D7-1),"n.a.") -> 3.9301895e-14 | H7: =IFERROR(IF(OR(ABS(G7)<0.000001,ABS(F7)<=0.0000005),"OK","CHECK"),"CHECK") -> OK | I7: 381149.83 | J7: =IFERROR(IF(I7=0,E7-I7,E7/I7-1),"n.a.") -> -1.110223e-16 | K7: =IFERROR(IF(ABS(J7)<0.000001,"OK","CHECK"),"CHECK") -> OK
B8: EV - exit | D8: 386162.69 | E8: =DCF!$D$113 -> 386162.69 | F8: =IFERROR(E8-D8,"n.a.") -> -2.7241185e-07 | G8: =IFERROR(IF(D8=0,E8-D8,E8/D8-1),"n.a.") -> -7.0543571e-13 | H8: =IFERROR(IF(OR(ABS(G8)<0.000001,ABS(F8)<=0.0000005),"OK","CHECK"),"CHECK") -> OK | I8: 386162.69 | J8: =IFERROR(IF(I8=0,E8-I8,E8/I8-1),"n.a.") -> 0 | K8: =IFERROR(IF(ABS(J8)<0.000001,"OK","CHECK"),"CHECK") -> OK
B9: Value per share today - Gordon | D9: 46.144022 | E9: =DCF!$D$138 -> 46.144022 | F9: =IFERROR(E9-D9,"n.a.") -> -3.276629e-07 | G9: =IFERROR(IF(D9=0,E9-D9,E9/D9-1),"n.a.") -> -7.1008742e-09 | H9: =IFERROR(IF(OR(ABS(G9)<0.000001,ABS(F9)<=0.0000005),"OK","CHECK"),"CHECK") -> OK | I9: 46.144022 | J9: =IFERROR(IF(I9=0,E9-I9,E9/I9-1),"n.a.") -> -3.3306691e-16 | K9: =IFERROR(IF(ABS(J9)<0.000001,"OK","CHECK"),"CHECK") -> OK
B10: Value per share today - exit | D10: 47.421921 | E10: =DCF!$D$145 -> 47.421921 | F10: =IFERROR(E10-D10,"n.a.") -> -3.9867041e-07 | G10: =IFERROR(IF(D10=0,E10-D10,E10/D10-1),"n.a.") -> -8.4068802e-09 | H10: =IFERROR(IF(OR(ABS(G10)<0.000001,ABS(F10)<=0.0000005),"OK","CHECK"),"CHECK") -> OK | I10: 47.421921 | J10: =IFERROR(IF(I10=0,E10-I10,E10/I10-1),"n.a.") -> 0 | K10: =IFERROR(IF(ABS(J10)<0.000001,"OK","CHECK"),"CHECK") -> OK
B11: 12-month target - Gordon | D11: 50.797086 | E11: =DCF!$D$140 -> 50.797086 | F11: =IFERROR(E11-D11,"n.a.") -> -1.0050981e-07 | G11: =IFERROR(IF(D11=0,E11-D11,E11/D11-1),"n.a.") -> -1.978653e-09 | H11: =IFERROR(IF(OR(ABS(G11)<0.000001,ABS(F11)<=0.0000005),"OK","CHECK"),"CHECK") -> OK | I11: 50.797086 | J11: =IFERROR(IF(I11=0,E11-I11,E11/I11-1),"n.a.") -> -4.4408921e-16 | K11: =IFERROR(IF(ABS(J11)<0.000001,"OK","CHECK"),"CHECK") -> OK
B12: Implied exit multiple | D12: 5.861569 | E12: =DCF!$D$156 -> 5.8615686 | F12: =IFERROR(E12-D12,"n.a.") -> -4.2807928e-07 | G12: =IFERROR(IF(D12=0,E12-D12,E12/D12-1),"n.a.") -> -7.3031518e-08 | H12: =IFERROR(IF(OR(ABS(G12)<0.000001,ABS(F12)<=0.0000005),"OK","CHECK"),"CHECK") -> OK | I12: 5.8615686 | J12: =IFERROR(IF(I12=0,E12-I12,E12/I12-1),"n.a.") -> -1.110223e-16 | K12: =IFERROR(IF(ABS(J12)<0.000001,"OK","CHECK"),"CHECK") -> OK
B13: Growth implied by exit | D13: 0.04379 | E13: =DCF!$D$157 -> 0.043790195 | F13: =IFERROR(E13-D13,"n.a.") -> 1.9528587e-07 | G13: =IFERROR(IF(D13=0,E13-D13,E13/D13-1),"n.a.") -> 4.4595998e-06 | H13: =IFERROR(IF(OR(ABS(G13)<0.000001,ABS(F13)<=0.0000005),"OK","CHECK"),"CHECK") -> OK | I13: 0.043790195 | J13: =IFERROR(IF(I13=0,E13-I13,E13/I13-1),"n.a.") -> 2.220446e-16 | K13: =IFERROR(IF(ABS(J13)<0.000001,"OK","CHECK"),"CHECK") -> OK
B14: Terminal growth implied by the price | D14: 0.053057 | E14: =Reverse_DCF!$D$9 -> 0.053056931 | F14: =IFERROR(E14-D14,"n.a.") -> -6.8823183e-08 | G14: =IFERROR(IF(D14=0,E14-D14,E14/D14-1),"n.a.") -> -1.2971556e-06 | H14: =IFERROR(IF(OR(ABS(G14)<0.000001,ABS(F14)<=0.0000005),"OK","CHECK"),"CHECK") -> OK | I14: 0.053056931 | J14: =IFERROR(IF(I14=0,E14-I14,E14/I14-1),"n.a.") -> 0 | K14: =IFERROR(IF(ABS(J14)<0.000001,"OK","CHECK"),"CHECK") -> OK
B15: TV share of EV - Gordon | D15: 0.556889 | E15: =DCF!$D$114 -> 0.5568889 | F15: =IFERROR(E15-D15,"n.a.") -> -9.6701793e-08 | G15: =IFERROR(IF(D15=0,E15-D15,E15/D15-1),"n.a.") -> -1.7364644e-07 | H15: =IFERROR(IF(OR(ABS(G15)<0.000001,ABS(F15)<=0.0000005),"OK","CHECK"),"CHECK") -> OK | I15: 0.5568889 | J15: =IFERROR(IF(I15=0,E15-I15,E15/I15-1),"n.a.") -> -2.220446e-16 | K15: =IFERROR(IF(ABS(J15)<0.000001,"OK","CHECK"),"CHECK") -> OK
B16: FCFF FY2026E | D16: 24113.737 | E16: =DCF!I87 -> 24113.737 | F16: =IFERROR(E16-D16,"n.a.") -> 2.3833491e-07 | G16: =IFERROR(IF(D16=0,E16-D16,E16/D16-1),"n.a.") -> 9.8838715e-12 | H16: =IFERROR(IF(OR(ABS(G16)<0.000001,ABS(F16)<=0.0000005),"OK","CHECK"),"CHECK") -> OK | I16: 24113.737 | J16: =IFERROR(IF(I16=0,E16-I16,E16/I16-1),"n.a.") -> -1.110223e-16 | K16: =IFERROR(IF(ABS(J16)<0.000001,"OK","CHECK"),"CHECK") -> OK
B17: FCFF FY2027E | D17: 23813.92 | E17: =DCF!J87 -> 23813.92 | F17: =IFERROR(E17-D17,"n.a.") -> 2.2944369e-07 | G17: =IFERROR(IF(D17=0,E17-D17,E17/D17-1),"n.a.") -> 9.6349595e-12 | H17: =IFERROR(IF(OR(ABS(G17)<0.000001,ABS(F17)<=0.0000005),"OK","CHECK"),"CHECK") -> OK | I17: 23813.92 | J17: =IFERROR(IF(I17=0,E17-I17,E17/I17-1),"n.a.") -> 2.220446e-16 | K17: =IFERROR(IF(ABS(J17)<0.000001,"OK","CHECK"),"CHECK") -> OK
B18: FCFF FY2028E | D18: 24799.299 | E18: =DCF!K87 -> 24799.299 | F18: =IFERROR(E18-D18,"n.a.") -> -4.3284672e-07 | G18: =IFERROR(IF(D18=0,E18-D18,E18/D18-1),"n.a.") -> -1.7454038e-11 | H18: =IFERROR(IF(OR(ABS(G18)<0.000001,ABS(F18)<=0.0000005),"OK","CHECK"),"CHECK") -> OK | I18: 24799.299 | J18: =IFERROR(IF(I18=0,E18-I18,E18/I18-1),"n.a.") -> -3.3306691e-16 | K18: =IFERROR(IF(ABS(J18)<0.000001,"OK","CHECK"),"CHECK") -> OK
B19: FCFF FY2029E | D19: 25533.242 | E19: =DCF!L87 -> 25533.242 | F19: =IFERROR(E19-D19,"n.a.") -> -2.970155e-07 | G19: =IFERROR(IF(D19=0,E19-D19,E19/D19-1),"n.a.") -> -1.1632473e-11 | H19: =IFERROR(IF(OR(ABS(G19)<0.000001,ABS(F19)<=0.0000005),"OK","CHECK"),"CHECK") -> OK | I19: 25533.242 | J19: =IFERROR(IF(I19=0,E19-I19,E19/I19-1),"n.a.") -> 2.220446e-16 | K19: =IFERROR(IF(ABS(J19)<0.000001,"OK","CHECK"),"CHECK") -> OK
B20: FCFF FY2030E | D20: 26933.747 | E20: =DCF!M87 -> 26933.747 | F20: =IFERROR(E20-D20,"n.a.") -> 3.5196354e-07 | G20: =IFERROR(IF(D20=0,E20-D20,E20/D20-1),"n.a.") -> 1.3067769e-11 | H20: =IFERROR(IF(OR(ABS(G20)<0.000001,ABS(F20)<=0.0000005),"OK","CHECK"),"CHECK") -> OK | I20: 26933.747 | J20: =IFERROR(IF(I20=0,E20-I20,E20/I20-1),"n.a.") -> 2.220446e-16 | K20: =IFERROR(IF(ABS(J20)<0.000001,"OK","CHECK"),"CHECK") -> OK
B21: FCFF FY2031E | D21: 27578.49 | E21: =DCF!N87 -> 27578.49 | F21: =IFERROR(E21-D21,"n.a.") -> 3.1921081e-07 | G21: =IFERROR(IF(D21=0,E21-D21,E21/D21-1),"n.a.") -> 1.1574519e-11 | H21: =IFERROR(IF(OR(ABS(G21)<0.000001,ABS(F21)<=0.0000005),"OK","CHECK"),"CHECK") -> OK | I21: 27578.49 | J21: =IFERROR(IF(I21=0,E21-I21,E21/I21-1),"n.a.") -> -4.4408921e-16 | K21: =IFERROR(IF(ABS(J21)<0.000001,"OK","CHECK"),"CHECK") -> OK
B22: FCFF FY2032E | D22: 28220.911 | E22: =DCF!O87 -> 28220.911 | F22: =IFERROR(E22-D22,"n.a.") -> -3.696623e-07 | G22: =IFERROR(IF(D22=0,E22-D22,E22/D22-1),"n.a.") -> -1.3098855e-11 | H22: =IFERROR(IF(OR(ABS(G22)<0.000001,ABS(F22)<=0.0000005),"OK","CHECK"),"CHECK") -> OK | I22: 28220.911 | J22: =IFERROR(IF(I22=0,E22-I22,E22/I22-1),"n.a.") -> 2.220446e-16 | K22: =IFERROR(IF(ABS(J22)<0.000001,"OK","CHECK"),"CHECK") -> OK
B23: FCFF FY2033E | D23: 28855.902 | E23: =DCF!P87 -> 28855.902 | F23: =IFERROR(E23-D23,"n.a.") -> 2.3110988e-07 | G23: =IFERROR(IF(D23=0,E23-D23,E23/D23-1),"n.a.") -> 8.0091489e-12 | H23: =IFERROR(IF(OR(ABS(G23)<0.000001,ABS(F23)<=0.0000005),"OK","CHECK"),"CHECK") -> OK | I23: 28855.902 | J23: =IFERROR(IF(I23=0,E23-I23,E23/I23-1),"n.a.") -> -3.3306691e-16 | K23: =IFERROR(IF(ABS(J23)<0.000001,"OK","CHECK"),"CHECK") -> OK
B24: FCFF FY2034E | D24: 29481.364 | E24: =DCF!Q87 -> 29481.364 | F24: =IFERROR(E24-D24,"n.a.") -> 3.6891288e-07 | G24: =IFERROR(IF(D24=0,E24-D24,E24/D24-1),"n.a.") -> 1.2513324e-11 | H24: =IFERROR(IF(OR(ABS(G24)<0.000001,ABS(F24)<=0.0000005),"OK","CHECK"),"CHECK") -> OK | I24: 29481.364 | J24: =IFERROR(IF(I24=0,E24-I24,E24/I24-1),"n.a.") -> 2.220446e-16 | K24: =IFERROR(IF(ABS(J24)<0.000001,"OK","CHECK"),"CHECK") -> OK
B25: FCFF FY2035E | D25: 30104.993 | E25: =DCF!R87 -> 30104.993 | F25: =IFERROR(E25-D25,"n.a.") -> -3.5411358e-07 | G25: =IFERROR(IF(D25=0,E25-D25,E25/D25-1),"n.a.") -> -1.1762591e-11 | H25: =IFERROR(IF(OR(ABS(G25)<0.000001,ABS(F25)<=0.0000005),"OK","CHECK"),"CHECK") -> OK | I25: 30104.993 | J25: =IFERROR(IF(I25=0,E25-I25,E25/I25-1),"n.a.") -> -1.110223e-16 | K25: =IFERROR(IF(ABS(J25)<0.000001,"OK","CHECK"),"CHECK") -> OK
B26: EBITDA FY2026E | D26: 62251.944 | E26: =DCF!I78 -> 62251.944 | F26: =IFERROR(E26-D26,"n.a.") -> -2.1827873e-11 | G26: =IFERROR(IF(D26=0,E26-D26,E26/D26-1),"n.a.") -> -3.3306691e-16 | H26: =IFERROR(IF(OR(ABS(G26)<0.000001,ABS(F26)<=0.0000005),"OK","CHECK"),"CHECK") -> OK | I26: 62251.944 | J26: =IFERROR(IF(I26=0,E26-I26,E26/I26-1),"n.a.") -> 0 | K26: =IFERROR(IF(ABS(J26)<0.000001,"OK","CHECK"),"CHECK") -> OK
B27: EBITDA FY2027E | D27: 64193.437 | E27: =DCF!J78 -> 64193.437 | F27: =IFERROR(E27-D27,"n.a.") -> 5.0000381e-08 | G27: =IFERROR(IF(D27=0,E27-D27,E27/D27-1),"n.a.") -> 7.7893247e-13 | H27: =IFERROR(IF(OR(ABS(G27)<0.000001,ABS(F27)<=0.0000005),"OK","CHECK"),"CHECK") -> OK | I27: 64193.437 | J27: =IFERROR(IF(I27=0,E27-I27,E27/I27-1),"n.a.") -> 0 | K27: =IFERROR(IF(ABS(J27)<0.000001,"OK","CHECK"),"CHECK") -> OK
B28: EBITDA FY2028E | D28: 68870.759 | E28: =DCF!K78 -> 68870.759 | F28: =IFERROR(E28-D28,"n.a.") -> 1.5413389e-07 | G28: =IFERROR(IF(D28=0,E28-D28,E28/D28-1),"n.a.") -> 2.2379876e-12 | H28: =IFERROR(IF(OR(ABS(G28)<0.000001,ABS(F28)<=0.0000005),"OK","CHECK"),"CHECK") -> OK | I28: 68870.759 | J28: =IFERROR(IF(I28=0,E28-I28,E28/I28-1),"n.a.") -> 0 | K28: =IFERROR(IF(ABS(J28)<0.000001,"OK","CHECK"),"CHECK") -> OK
B29: EBITDA FY2029E | D29: 72881.112 | E29: =DCF!L78 -> 72881.112 | F29: =IFERROR(E29-D29,"n.a.") -> -4.5751221e-08 | G29: =IFERROR(IF(D29=0,E29-D29,E29/D29-1),"n.a.") -> -6.277201e-13 | H29: =IFERROR(IF(OR(ABS(G29)<0.000001,ABS(F29)<=0.0000005),"OK","CHECK"),"CHECK") -> OK | I29: 72881.112 | J29: =IFERROR(IF(I29=0,E29-I29,E29/I29-1),"n.a.") -> 0 | K29: =IFERROR(IF(ABS(J29)<0.000001,"OK","CHECK"),"CHECK") -> OK
B30: EBITDA FY2030E | D30: 77122.734 | E30: =DCF!M78 -> 77122.734 | F30: =IFERROR(E30-D30,"n.a.") -> 1.7455022e-07 | G30: =IFERROR(IF(D30=0,E30-D30,E30/D30-1),"n.a.") -> 2.2633007e-12 | H30: =IFERROR(IF(OR(ABS(G30)<0.000001,ABS(F30)<=0.0000005),"OK","CHECK"),"CHECK") -> OK | I30: 77122.734 | J30: =IFERROR(IF(I30=0,E30-I30,E30/I30-1),"n.a.") -> 0 | K30: =IFERROR(IF(ABS(J30)<0.000001,"OK","CHECK"),"CHECK") -> OK
B31: EBITDA FY2031E | D31: 80501.798 | E31: =DCF!N78 -> 80501.798 | F31: =IFERROR(E31-D31,"n.a.") -> 8.1941835e-08 | G31: =IFERROR(IF(D31=0,E31-D31,E31/D31-1),"n.a.") -> 1.0178525e-12 | H31: =IFERROR(IF(OR(ABS(G31)<0.000001,ABS(F31)<=0.0000005),"OK","CHECK"),"CHECK") -> OK | I31: 80501.798 | J31: =IFERROR(IF(I31=0,E31-I31,E31/I31-1),"n.a.") -> 0 | K31: =IFERROR(IF(ABS(J31)<0.000001,"OK","CHECK"),"CHECK") -> OK
B32: EBITDA FY2032E | D32: 83998.641 | E32: =DCF!O78 -> 83998.641 | F32: =IFERROR(E32-D32,"n.a.") -> -8.6904038e-08 | G32: =IFERROR(IF(D32=0,E32-D32,E32/D32-1),"n.a.") -> -1.0346168e-12 | H32: =IFERROR(IF(OR(ABS(G32)<0.000001,ABS(F32)<=0.0000005),"OK","CHECK"),"CHECK") -> OK | I32: 83998.641 | J32: =IFERROR(IF(I32=0,E32-I32,E32/I32-1),"n.a.") -> 0 | K32: =IFERROR(IF(ABS(J32)<0.000001,"OK","CHECK"),"CHECK") -> OK
B33: EBITDA FY2033E | D33: 87614.335 | E33: =DCF!P78 -> 87614.335 | F33: =IFERROR(E33-D33,"n.a.") -> 2.7274655e-07 | G33: =IFERROR(IF(D33=0,E33-D33,E33/D33-1),"n.a.") -> 3.1130654e-12 | H33: =IFERROR(IF(OR(ABS(G33)<0.000001,ABS(F33)<=0.0000005),"OK","CHECK"),"CHECK") -> OK | I33: 87614.335 | J33: =IFERROR(IF(I33=0,E33-I33,E33/I33-1),"n.a.") -> 0 | K33: =IFERROR(IF(ABS(J33)<0.000001,"OK","CHECK"),"CHECK") -> OK
B34: EBITDA FY2034E | D34: 91349.756 | E34: =DCF!Q78 -> 91349.756 | F34: =IFERROR(E34-D34,"n.a.") -> 5.2634277e-08 | G34: =IFERROR(IF(D34=0,E34-D34,E34/D34-1),"n.a.") -> 5.7620575e-13 | H34: =IFERROR(IF(OR(ABS(G34)<0.000001,ABS(F34)<=0.0000005),"OK","CHECK"),"CHECK") -> OK | I34: 91349.756 | J34: =IFERROR(IF(I34=0,E34-I34,E34/I34-1),"n.a.") -> 0 | K34: =IFERROR(IF(ABS(J34)<0.000001,"OK","CHECK"),"CHECK") -> OK
B35: EBITDA FY2035E | D35: 95224.154 | E35: =DCF!R78 -> 95224.154 | F35: =IFERROR(E35-D35,"n.a.") -> -1.4624675e-08 | G35: =IFERROR(IF(D35=0,E35-D35,E35/D35-1),"n.a.") -> -1.5354384e-13 | H35: =IFERROR(IF(OR(ABS(G35)<0.000001,ABS(F35)<=0.0000005),"OK","CHECK"),"CHECK") -> OK | I35: 95224.154 | J35: =IFERROR(IF(I35=0,E35-I35,E35/I35-1),"n.a.") -> 0 | K35: =IFERROR(IF(ABS(J35)<0.000001,"OK","CHECK"),"CHECK") -> OK
B36: Discount factor FY2026E (replica only) | D36: not in summary | E36: =DCF!I103 -> 0.9528075 | H36: replica only | I36: 0.9528075 | J36: =IFERROR(IF(I36=0,E36-I36,E36/I36-1),"n.a.") -> 0 | K36: =IFERROR(IF(ABS(J36)<0.000001,"OK","CHECK"),"CHECK") -> OK
B37: Discount factor FY2027E (replica only) | D37: not in summary | E37: =DCF!J103 -> 0.86499879 | H37: replica only | I37: 0.86499879 | J37: =IFERROR(IF(I37=0,E37-I37,E37/I37-1),"n.a.") -> 0 | K37: =IFERROR(IF(ABS(J37)<0.000001,"OK","CHECK"),"CHECK") -> OK
B38: Discount factor FY2028E (replica only) | D38: not in summary | E38: =DCF!K103 -> 0.78528234 | H38: replica only | I38: 0.78528234 | J38: =IFERROR(IF(I38=0,E38-I38,E38/I38-1),"n.a.") -> 0 | K38: =IFERROR(IF(ABS(J38)<0.000001,"OK","CHECK"),"CHECK") -> OK
B39: Discount factor FY2029E (replica only) | D39: not in summary | E39: =DCF!L103 -> 0.71291239 | H39: replica only | I39: 0.71291239 | J39: =IFERROR(IF(I39=0,E39-I39,E39/I39-1),"n.a.") -> 0 | K39: =IFERROR(IF(ABS(J39)<0.000001,"OK","CHECK"),"CHECK") -> OK
B40: Discount factor FY2030E (replica only) | D40: not in summary | E40: =DCF!M103 -> 0.6472119 | H40: replica only | I40: 0.6472119 | J40: =IFERROR(IF(I40=0,E40-I40,E40/I40-1),"n.a.") -> 0 | K40: =IFERROR(IF(ABS(J40)<0.000001,"OK","CHECK"),"CHECK") -> OK
B41: Discount factor FY2031E (replica only) | D41: not in summary | E41: =DCF!N103 -> 0.58756623 | H41: replica only | I41: 0.58756623 | J41: =IFERROR(IF(I41=0,E41-I41,E41/I41-1),"n.a.") -> 0 | K41: =IFERROR(IF(ABS(J41)<0.000001,"OK","CHECK"),"CHECK") -> OK
B42: Discount factor FY2032E (replica only) | D42: not in summary | E42: =DCF!O103 -> 0.53341738 | H42: replica only | I42: 0.53341738 | J42: =IFERROR(IF(I42=0,E42-I42,E42/I42-1),"n.a.") -> 0 | K42: =IFERROR(IF(ABS(J42)<0.000001,"OK","CHECK"),"CHECK") -> OK
B43: Discount factor FY2033E (replica only) | D43: not in summary | E43: =DCF!P103 -> 0.48425877 | H43: replica only | I43: 0.48425877 | J43: =IFERROR(IF(I43=0,E43-I43,E43/I43-1),"n.a.") -> -3.3306691e-16 | K43: =IFERROR(IF(ABS(J43)<0.000001,"OK","CHECK"),"CHECK") -> OK
B44: Discount factor FY2034E (replica only) | D44: not in summary | E44: =DCF!Q103 -> 0.43963051 | H44: replica only | I44: 0.43963051 | J44: =IFERROR(IF(I44=0,E44-I44,E44/I44-1),"n.a.") -> 0 | K44: =IFERROR(IF(ABS(J44)<0.000001,"OK","CHECK"),"CHECK") -> OK
B45: Discount factor FY2035E (replica only) | D45: not in summary | E45: =DCF!R103 -> 0.3991151 | H45: replica only | I45: 0.3991151 | J45: =IFERROR(IF(I45=0,E45-I45,E45/I45-1),"n.a.") -> 0 | K45: =IFERROR(IF(ABS(J45)<0.000001,"OK","CHECK"),"CHECK") -> OK
B46: Sum of PV of FCFF (replica only) | D46: not in summary | E46: =DCF!$D$107 -> 168891.72 | H46: replica only | I46: 168891.72 | J46: =IFERROR(IF(I46=0,E46-I46,E46/I46-1),"n.a.") -> -5.5511151e-16 | K46: =IFERROR(IF(ABS(J46)<0.000001,"OK","CHECK"),"CHECK") -> OK
B47: Terminal value - Gordon (replica only) | D47: not in summary | E47: =DCF!$D$108 -> 531821.81 | H47: replica only | I47: 531821.81 | J47: =IFERROR(IF(I47=0,E47-I47,E47/I47-1),"n.a.") -> -2.220446e-16 | K47: =IFERROR(IF(ABS(J47)<0.000001,"OK","CHECK"),"CHECK") -> OK
B48: PV of terminal value - Gordon (replica only) | D48: not in summary | E48: =DCF!$D$109 -> 212258.11 | H48: replica only | I48: 212258.11 | J48: =IFERROR(IF(I48=0,E48-I48,E48/I48-1),"n.a.") -> -2.220446e-16 | K48: =IFERROR(IF(ABS(J48)<0.000001,"OK","CHECK"),"CHECK") -> OK
B49: Terminal value - exit (replica only) | D49: not in summary | E49: =DCF!$D$111 -> 571344.93 | H49: replica only | I49: 571344.93 | J49: =IFERROR(IF(I49=0,E49-I49,E49/I49-1),"n.a.") -> 0 | K49: =IFERROR(IF(ABS(J49)<0.000001,"OK","CHECK"),"CHECK") -> OK
B50: PV of terminal value - exit (replica only) | D50: not in summary | E50: =DCF!$D$112 -> 217270.97 | H50: replica only | I50: 217270.97 | J50: =IFERROR(IF(I50=0,E50-I50,E50/I50-1),"n.a.") -> -2.220446e-16 | K50: =IFERROR(IF(ABS(J50)<0.000001,"OK","CHECK"),"CHECK") -> OK
B51: Net debt incl. leases (replica only) | D51: not in summary | E51: =DCF!$D$122 -> 179918 | H51: replica only | I51: 179918 | J51: =IFERROR(IF(I51=0,E51-I51,E51/I51-1),"n.a.") -> 0 | K51: =IFERROR(IF(ABS(J51)<0.000001,"OK","CHECK"),"CHECK") -> OK
B52: Shares (replica only) | D52: not in summary | E52: =DCF!$D$131 -> 4310.531 | H52: replica only | I52: 4310.531 | J52: =IFERROR(IF(I52=0,E52-I52,E52/I52-1),"n.a.") -> 0 | K52: =IFERROR(IF(ABS(J52)<0.000001,"OK","CHECK"),"CHECK") -> OK
B53: Roll-forward factor (replica only) | D53: not in summary | E53: =DCF!$D$134 -> 1.0988594 | H53: replica only | I53: 1.0988594 | J53: =IFERROR(IF(I53=0,E53-I53,E53/I53-1),"n.a.") -> 0 | K53: =IFERROR(IF(ABS(J53)<0.000001,"OK","CHECK"),"CHECK") -> OK
B55: Rows checked against the engine summary | D55: 30
B56: Rows OK vs engine (must equal the count above) | D56: =COUNTIF(H6:H35,"OK") -> 30
B57: Rows checked against the Python replica | D57: 48
B58: Rows OK vs replica (must equal the count above) | D58: =COUNTIF(K6:K53,"OK") -> 48

Sheet Inputs_Sources
B2: Inputs and sources
B3: [sourced] from a filing or public source; [guidance] management statement; [assumption] team or assistant judgment (proposal until the team confirms); [calc] computed; [unverified] not yet tied to a source.
B5: Item | C5: Value | D5: Unit | E5: Tag | F5: Source | G5: As of
B6: Share price, BMV close | C6: 58.6 | D6: MXN | E6: sourced | F6: investing.com / Yahoo (delayed); wacc_inputs A1 | G6: 2026-10-16
B7: 52-week high / low | C7: 68.67 / 53.03 | D7: MXN | E7: sourced | F7: CIQ corporate_issuance.csv (wacc_inputs A4-A5) | G7: 2026-10-06
B8: Shares outstanding | C8: 4294.9437 | D8: m | E8: sourced | F8: BMV notice (wacc_inputs A8) | G8: 2026-07-29
B9: Market capitalisation | C9: 251683.7 | D9: MXN m | E9: calc | F9: price x shares (wacc_inputs A9) | G9: 2026-10-16
B10: M-Bono 10y | C10: 0.0926 | D10: % | E10: sourced | F10: S&P Capital IQ rates | G10: 2026-10-16
B11: UST 10y | C11: 0.0509 | D11: % | E11: sourced | F11: S&P Capital IQ rates | G11: 2026-10-16
B12: Mexico 5y CDS | C12: 0.00953 | D12: % | E12: sourced | F12: S&P Capital IQ CDS | G12: 2026-10-16
B13: Damodaran implied ERP | C13: 0.042 | D13: % | E13: sourced | F13: Damodaran home page | G13: 2026-10-01
B14: Damodaran Mexico default spread / CRP | C14: 1.62% / 2.46% | D14: % | E14: sourced | F14: Damodaran ctryprem (Jan-2026 copy) | G14: 2026-01-05
B15: Damodaran Food Processing unlevered beta, Global / US | C15: 0.53 / 0.46 | D15: x | E15: sourced | F15: Damodaran betas (Jan-2026) | G15: 2026-01
B16: Bimbo published beta | C16: 0.32 | D16: x | E16: unverified | F16: investing.com (window not stated) | G16: 2026-10-16
B17: BIMBO 23L yield | C17: 0.0926 | D17: % | E17: sourced | F17: LSEG export (pricing ~10-Oct) | G17: 2026-10-10
B18: Debt / leases / cash, 31-Dec-2025 | C18: 153,663 / 34,790 / 8,535 | D18: MXN m | E18: sourced | F18: EEFF25 p.12 via data/financials.csv | G18: 2025-12-31
B19: Debt / leases / cash, 30-Jun-2026 | C19: 153,660 / 33,361 / 16,563 | D19: MXN m | E19: sourced | F19: BMV Jun-26; CIQ | G19: 2026-06-30
B20: Employee benefits / MEPP / derivatives (net liab.) | C20: 6,507 / 985 / 3,185 | D20: MXN m | E20: sourced | F20: EEFF25 p.12, p.79 (data/adjustments.md) | G20: 2025-12-31
B21: Investments in associates | C21: 7018 | D21: MXN m | E21: sourced | F21: EEFF25 p.12 | G21: 2025-12-31
B22: NCI income 1H26 (annualised 1,814) | C22: 907 | D22: MXN m | E22: sourced | F22: CIQ quarterly: 1Q26 436 + 2Q26 471 | G22: 2026-06-30
B23: 2026 dividend paid (13-May) | C23: 1.075 | D23: MXN/share | E23: sourced | F23: wacc_inputs C1-C4 | G23: 2026-05-13
B24: Consensus DPS FY2027E (next 12 months) | C24: 1.05 | D24: MXN/share | E24: sourced | F24: CIQ consensus (data/capitaliq/consensus.csv) | G24: 2026-09-20
B26: Drivers: model/drivers.yaml (tag, rationale and pillar per driver). History: data/financials.csv (document and page per figure) and data/adjustments.md.

Sheet Checks
B2: Integrity checks
B4: WACC - g at least 2 points | C4: =IF(DCF!$D$154>=0.02,"OK","WARN") -> OK
B5: g not above long-term nominal GDP growth | C5: =IF(DCF!$D$155<=0,"OK","FAIL") -> OK
B6: Weights add up to 100% | C6: =IF(ABS(DCF!$D$30+DCF!$D$31-1)<0.000001,"OK","FAIL") -> OK
B7: Engine reconciliation: every row OK (count of OK = rows checked) | C7: =IF(Engine_Recon!$D$56=Engine_Recon!$D$55,"OK","CHECK") -> OK
B8: Python replica reconciliation: every row OK | C8: =IF(Engine_Recon!$D$58=Engine_Recon!$D$57,"OK","CHECK") -> OK
B9: Gordon TV share of EV below 85% | C9: =IF(DCF!$D$114<0.85,"OK","WARN") -> OK
B10: Exit multiple implied by Gordon within 2x of the exit multiple | C10: =IF(ABS(DCF!$D$156-DCF!$D$38)<=2,"OK","WARN") -> OK
B11: Debt-like components add up to valuation.yaml debt_like_items | C11: =IF(ABS(DCF!$D$127-DCF!$D$128)<0.5,"OK","FAIL") -> OK
B12: Segments add up to revenue FY2021 | C12: =IF(ABS(SUM(DCF!D64:D68)-DCF!D69)<0.5,"OK","FAIL") -> OK
B13: Segments add up to revenue FY2022 | C13: =IF(ABS(SUM(DCF!E64:E68)-DCF!E69)<0.5,"OK","FAIL") -> OK
B14: Segments add up to revenue FY2023 | C14: =IF(ABS(SUM(DCF!F64:F68)-DCF!F69)<0.5,"OK","FAIL") -> OK
B15: Segments add up to revenue FY2024 | C15: =IF(ABS(SUM(DCF!G64:G68)-DCF!G69)<0.5,"OK","FAIL") -> OK
B16: Segments add up to revenue FY2025 | C16: =IF(ABS(SUM(DCF!H64:H68)-DCF!H69)<0.5,"OK","FAIL") -> OK
B18: Formula errors are scanned after recalculation with valuation/build/scan_errors.py.
