Workbook

Sheet Cover
B2: Grupo Bimbo, S.A.B. de C.V. (BMV: BIMBO A) - Libro de valuación por DCF
B3: Fecha de valuación 2026-10-16; millones de MXN; IFRS. Generado el 2026-10-17 por valuation/build/build_spg_workbooks.py a partir de los insumos canónicos del modelo.
B5: Hojas
B6: DCF - supuestos generales, supuestos de proyección, flujo libre de efectivo proyectado, capital de trabajo, descuento, valor terminal, puente al valor del capital, controles cruzados, base publicada (crecimiento de arrendamientos, reclamos de salida consistentes con el EV de los pares, puente de valor, casos de menor retorno) y tablas de sensibilidad (estructura según S&P 'DCF Analysis').
B7: Base publicada = mecánica del motor más dos correcciones técnicas: (1) el FCFF también deduce el crecimiento del pasivo por arrendamiento, mantenido en la proporción de ventas de FY2025; (2) el método de salida resta solo los reclamos dentro de la definición de EV de los pares (deuda neta, NCI a valor de mercado). Los valores de la base del motor se conservan para la conciliación.
B8: Reverse_DCF - crecimiento perpetuo y ajuste del crecimiento de ventas implícitos en el precio de mercado.
B9: Levers - tablas estáticas de las palancas clave (capex, margen bruto, crecimiento) sobre la base publicada.
B10: Escenarios - un cambio a la vez contra la base: rutas de costo de capital y ponderación del riesgo país, beta de regresión propia de Bimbo, consistencia de moneda en Norteamérica (PPP), capex terminal vs el referente de pares, múltiplos de salida con las medianas de pares de la v3.
B11: v3 (2026-10-17): el costo de capital base es la ruta B - tasa libre de impago en MXN (M-Bono a 10 años menos el diferencial de impago de México) más una prima de riesgo país del capital ponderada por dónde opera Bimbo (países -> regiones -> pesos de EBITDA ajustado FY2025); construcción completa en BIMBOA_WACC_v3.xlsx. Es una propuesta hasta que el equipo la confirme.
B12: Dated_Check - valuación independiente anclada en el balance general del 30-Jun-2026, trasladada a la fecha de valuación.
B13: Engine_Recon - concordancia línea por línea con el motor del modelo del proyecto (model/model-summary.json).
B14: Inputs_Sources - cada insumo con valor, etiqueta, fuente y fecha. Checks - controles de integridad.
... B21: [sourced] de un reporte presentado o fuente pública; [guidance] declaración de la administración; [assumption] juicio del equipo o del asistente (propuesta hasta que el equipo confirme); [calc] calculado; [unverified] aún sin vincular a una fuente.

Sheet DCF
B2: Análisis de flujos de efectivo descontados
B3: Grupo Bimbo, S.A.B. de C.V. (BMV:BIMBO A) | fecha de valuación 2026-10-16 | millones de MXN, IFRS | estructura según S&P Capital IQ Pro 'DCF Analysis'
B4: Azul sobre amarillo = insumo (cambiar aquí); negro = fórmula; verde = vínculo a otra hoja. Cada insumo lleva una etiqueta y una fuente en 'Inputs_Sources'. [sourced] de un reporte presentado o fuente pública; [guidance] declaración de la administración; [assumption] juicio del equipo o del asistente (propuesta hasta que el equipo confirme); [calc] calculado; [unverified] aún sin vincular a una fuente.
B6: RESULTADOS CLAVE - BASE PUBLICADA (los arrendamientos crecen con el negocio; salida con reclamos consistentes con el EV de los pares). Base del motor conservada para la conciliación ('Engine_Recon')
B7: Valor por acción hoy PUBLICADO - Gordon (MXN) | D7: =$D$192 -> 33.551593
B8: Valor por acción hoy PUBLICADO - múltiplo de salida, reclamos consistentes con el EV de los pares (MXN) | D8: =$D$194 -> 45.715085
B9: Valor a 12 meses PUBLICADO - Gordon = valor x (1 + ke) - siguiente dividendo no pagado (MXN) | D9: =$D$198 -> 36.844394
B10: Precio actual de la acción (MXN) | D10: =$D$146 -> 58.6
B11: Prima / (descuento) hoy - Gordon / salida | D11: =$D$195 -> -0.42744722 | E11: =$D$196 -> -0.2198791
B12: WACC / costo del capital propio | D12: =$D$34 -> 0.10323276 | E12: =$D$30 -> 0.12943651
B13: Crecimiento perpetuo (g) / múltiplo de salida | D13: =$D$39 -> 0.0425 | E13: =$D$40 -> 6
B14: Valor de la empresa (EV) - Gordon / salida, publicado (MXN m) | D14: =$D$187 -> 342034.15 | E14: =$D$188 -> 370093.87
B15: Valor terminal como % del EV - Gordon / salida, publicado | D15: =$D$189 -> 0.54336157 | E15: =$D$190 -> 0.57798291
B16: Retorno sobre capital nuevo implícito en el valor terminal - base publicada / base del motor | D16: =$D$200 -> 0.14618391 | E16: =$D$169 -> 0.17897127
B17: Gordon con RONIC = WACC / con RONIC 12.5% (casos de menor retorno, MXN) | D17: =$E$219 -> 25.454699 | E17: =$E$220 -> 30.253543
B18: Base del motor, solo para conciliación - Gordon / salida (MXN) | D18: =$D$152 -> 39.481483 | E18: =$D$159 -> 43.084454
B19: Precio objetivo del equipo | D19: null - decisión del equipo (reglas del CFA: el equipo fija el precio objetivo y la recomendación)
B21: SUPUESTOS - COSTO DE CAPITAL (de valuation/valuation.yaml; construcción completa en BIMBOA_WACC_v3.xlsx)
B22: Tasa libre de riesgo | D22: 0.075101188 | E22: [calc] Ruta B (base, propuesta): tasa libre de incumplimiento en MXN 7.5101% = M-Bono 10y 9.26% [sourced] S&P Capital IQ 16-Oct-2026 (data/capitaliq/capiq-ai-model-gaps-2_2026-10-17.md) - diferencial por incumplimiento de México 1.7499% [sourced] Damodaran julio de 2026 (Baa3). La ruta A mantiene el M-Bono 9.26% sin prima de riesgo país
B23: Prima de riesgo de mercado (mercado maduro) | D23: 0.042 | E23: [sourced] ERP implícita de Damodaran 4.20%, 1-Oct-2026 (wacc_inputs G1)
B24: Prima de riesgo país | D24: 0.020496339 | E24: [calc] Ruta B (base, propuesta): CRP de capital ponderado por donde opera Bimbo = 2.0496% con ponderaciones de EBITDA ajustado de FY2025 (ventas 1.7048%; EBITDA FY2023-25 1.9900%; ventas FY2023-25 1.6517%; ponderaciones de EBITDA sin Argentina 2.0151%). CRP por país: actualización de Damodaran de julio de 2026 (México Baa3 2.72%); dentro de cada región, los países se ponderan por el número de plantas de FY2025 [assumption: sin revelación de ventas por país]; las eliminaciones se atribuyen a México [assumption]; se aplican de forma aditiva (fórmula de la guía del proyecto para la ruta en USD). Se construye en BIMBOA_WACC_v3.xlsx
B25: Beta desapalancada | D25: 0.53 | E25: [sourced] Damodaran Food Processing, Global, desapalancada 0.53, base de datos de Jan-2026: betaGlobal.xls 'Industry Averages' B1 'Date updated' = 5-Jan-2026; el encabezado de la página HTML dice 'Data used is as of January 2026' y su pie 'Last Updated in January 2025' está desactualizado (el historial del propio archivo da 0.536 para la base de 2025 vs 0.560 ahora, corregida por efectivo) (wacc_inputs G6) - propuesta; las betas a 5 años de los pares son demasiado bajas para usarse solas
B26: Deuda / capital objetivo (valores de mercado, deuda con arrendamientos) | D26: 0.7431 | E26: [calc] D/E de mercado actual de Bimbo con arrendamientos 0.743 = (153,660 + 33,361) / 251,684 (wacc_inputs D2) - propuesta
B27: Costo de la deuda antes de impuestos (MXN) | D27: 0.0971 | E27: [calc] M-Bono a 10 años 9.26% + 0.45pp de diferencial de la emisión BIMBO 26 = 9.71% (wacc_inputs J2-B) - propuesta
B28: Tasa marginal de impuestos (WACC) | D28: 0.3 | E28: [sourced] Tasa legal de México 30% (wacc_inputs D7)
B29: Beta reapalancada = desapalancada x (1 + (1 - tasa de impuestos) x D/E) | D29: =$D$25*(1+(1-$D$28)*$D$26) -> 0.8056901
B30: Costo del capital propio = rf + beta x ERP + CRP | D30: =$D$22+$D$29*$D$23+$D$24 -> 0.12943651
B31: Costo de la deuda después de impuestos | D31: =$D$27*(1-$D$28) -> 0.06797
B32: Peso del capital = 1 / (1 + D/E) | D32: =1/(1+$D$26) -> 0.57369055
B33: Peso de la deuda = D/E / (1 + D/E) | D33: =$D$26/(1+$D$26) -> 0.42630945
B34: WACC | D34: =$D$32*$D$30+$D$33*$D$31 -> 0.10323276 | E34: Misma fórmula que la hoja WACC del motor; la conciliación está en 'Engine_Recon'.
B36: SUPUESTOS - DESCUENTO, VALOR TERMINAL Y AJUSTES DE ESCENARIO
B37: Desfase de la convención de mitad de año (0.5 = mitad de año, 0 = fin de año) | D37: 0.5 | E37: Convención del motor: el flujo de efectivo t se descuenta t - desfase años desde el 31-Dec-2025.
B38: Años desde el último cierre fiscal (31-Dec-2025 a la fecha de valuación) | D38: 0.7918 | E38: Traslado del valor del capital a hoy al costo del capital propio (aproximación del motor).
B39: Crecimiento perpetuo (g), MXN nominal | D39: 0.0425 | E39: [assumption] 4.25%: mezcla de largo plazo de ~36% Norteamérica a ~3% en MXN y ~64% México/LatAm/EAA a ~5% (decisión del equipo)
B40: Múltiplo de salida EV / EBITDA (retrospectivo, aplicado al EBITDA del último año) | D40: 6 | E40: [assumption] 6.0x: criterio por encima de la mediana LTM del núcleo de panificación de 5.53x (Flowers 5.61x, Gruma 5.44x; base IFRS 16) para la mezcla de México; todos los pares elegibles 8.27x (NTM 8.79x); Bimbo hoy 6.94x con NCI a valor en libros (BIMBOA_PeerAnalysis_v3.xlsx) - decisión del equipo
B41: Crecimiento del PIB nominal de largo plazo, MXN (tope para g) | D41: 0.05 | E41: [assumption] 5.0% = ~2% real + 3% meta de Banxico. Crecimiento real [sourced]: FMI WEO Oct-2026, México 2.1% anual en 2029-31 (DataMapper NGDP_RPCH, última modificación 2026-10-08); encuesta del sector privado de Banxico Sep-2026 (publicada 1-Oct-2026, Cuadro 6 p.8), promedio 2027-36: promedio 1.88% / mediana 1.80%. Compuesto con inflación de 3.0% (meta; IPC del FMI 2029-31 3.0%), el rango es 4.85-5.16%; 5.0% es su punto medio redondeado. El 3.0% es la meta y la proyección del FMI, no la encuesta: las medianas de inflación de largo plazo de la propia encuesta son 3.80% (2027-30) y 3.70% (2031-34) (Cuadro 5 p.6), lo que daría ~5.6% nominal
B42: Escenario: ajuste del crecimiento de ventas sumado a cada año proyectado (0 = caso base) | D42: 0 | E42: Lo usa el DCF inverso (aplicar Goal Seek a esta celda). Dejar en 0 para el caso base.
B43: Escenario: ajuste del margen bruto, todos los años proyectados (p. ej., -0.01 = -100 pb por choque del trigo) | D43: 0 | E43: Palanca de escenario climático / de costo de insumos. Dejar en 0 para el caso base.
B44: Escenario: ajuste de capex / ventas, todos los años proyectados (p. ej., +0.005 = +50 pb) | D44: 0 | E44: Palanca de reinversión (pilar de deuda / FCF). Dejar en 0 para el caso base.
B46: SUPUESTOS DE PROYECCIÓN (model/drivers.yaml; histórico = valores implícitos) | D46: FY2021A | E46: FY2022A | F46: FY2023A | G46: FY2024A | H46: FY2025A | I46: FY2026E | J46: FY2027E | K46: FY2028E | L46: FY2029E | M46: FY2030E | N46: FY2031E | O46: FY2032E | P46: FY2033E | Q46: FY2034E | R46: FY2035E | S46: Etiqueta / fuente / nota
B47: Crecimiento de ventas de Norteamérica | I47: -0.074 | J47: 0.03 | K47: 0.03 | L47: 0.03 | M47: 0.03 | N47: 0.03 | O47: 0.03 | P47: 0.03 | Q47: 0.03 | R47: 0.03 | S47: [assumption] DRIVER DE LA HISTORIA (propuesta). FY26 = 1H26 real (84,901, -11.3% en MXN; ex-FX +0.7%/+1.3% en 1Q/2Q26) más 2H26 a -3.5% (ex-FX +1.5%, peso alrededor de -5% vs 2H25) [calc] tendencia trimestral del wiki. FY27+: crecimiento en USD de ~+1.5% (volumen de la categoría de -2% a -4%, precio/mezcla de +1-2%, ganancias de participación de mercado que afirma la administración) más una depreciación del MXN de ~1.5% anual (diferencial de inflación) [assumption]. Alternativas en valuation/BIMBOA_DCF_v3.xlsx 'Scenarios': PPP con las metas de inflación de 3%/2% (0.98% anual; Gordon -2.18 por acción) o con la inflación de la encuesta de Banxico (1.67% anual; +0.75); la inflación (CPI) de Sep-2026 fue de 3.45% en México vs 3.74% en EE.UU. [sourced] macro/macro-view.yaml.
B48: Crecimiento de ventas de México | I48: 0.046 | J48: 0.055 | K48: 0.0525 | L48: 0.0525 | M48: 0.0525 | N48: 0.0515 | O48: 0.051 | P48: 0.0505 | Q48: 0.05 | R48: 0.05 | S48: [assumption] SUPUESTO CLAVE (propuesta). FY26 = 1H26 +4.6% y 2H26 +4.7% (1Q26 +4.5%, 2Q26 +4.7%) [calc]. FY27+: mercado de panificación empacada ~3.5% de CAGR en valor 2024-29E (RA25 p.111) más precio/mezcla con inflación de ~3.5-3.8%; se atenúa hasta 5.0% (nominal de largo plazo) [assumption].
B49: Crecimiento de ventas de Europa, Asia y África | I49: 0.006 | J49: 0.045 | K49: 0.045 | L49: 0.045 | M49: 0.045 | N49: 0.0445 | O49: 0.044 | P49: 0.0435 | Q49: 0.043 | R49: 0.0425 | S49: [assumption] Propuesta. FY26 = 1H26 +1.3% en MXN (sin efecto cambiario +12.6%/+8.4% incl. adquisiciones complementarias de 2025) con 2H26 plano tras el efecto cambiario [calc]. FY27+: orgánico ~4.5% (mercado europeo 3.4%, Europa del Este 6.6% de CAGR según RA25 p.108), sin nuevas operaciones de M&A [assumption].
B50: Crecimiento de ventas de Latinoamérica | I50: 0.085 | J50: 0.07 | K50: 0.065 | L50: 0.065 | M50: 0.065 | N50: 0.063 | O50: 0.061 | P50: 0.059 | Q50: 0.057 | R50: 0.055 | S50: [assumption] Propuesta. FY26 = 1H26 +7.1% más 2H26 ~+10% (Wickbold consolidada desde Oct-2025) [calc]. FY27+: panificación en LatAm 5.5% de CAGR (RA25 p.108) más sinergias de Wickbold, atenuándose hasta 5.5% [assumption].
B51: Crecimiento de ventas de eliminaciones interregionales | I51: 0.036 | J51: 0.045 | K51: 0.045 | L51: 0.045 | M51: 0.045 | N51: 0.045 | O51: 0.045 | P51: 0.045 | Q51: 0.045 | R51: 0.045 | S51: [assumption] Mecánico: las eliminaciones interregionales crecen con las ventas regionales (eliminaciones de 1H26 -8,545 vs -8,202 en 1H25, +4.2%) [calc].
B52: Margen bruto | I52: 0.524 | J52: 0.52 | K52: 0.523 | L52: 0.525 | M52: 0.525 | N52: 0.525 | O52: 0.525 | P52: 0.525 | Q52: 0.525 | R52: 0.525 | S52: [assumption] pilar 1: SUPUESTO CLAVE (propuesta; pilar climático). Histórico 53.4/51.5/51.4/52.6/52.3% (FY21-25, mapeo del modelo). 1H26 ~52.6% en la base del modelo (CIQ 52.9% menos la brecha de mapeo de 0.33pp) [calc]. El promedio del trigo CBOT en 2026 a la fecha es +17% vs 2025 y el margen bruto sigue al trigo con un rezago de ~1 año (r = -0.74, n = 9; wiki bimbo-climate-metrics-capiq-2026-10) -> caída de 40pb en FY27, recuperación a 52.5% [assumption].
B53: Gastos de operación / ventas | I53: 0.436 | J53: 0.434 | K53: 0.433 | L53: 0.4325 | M53: 0.4305 | N53: 0.4305 | O53: 0.4305 | P53: 0.4305 | Q53: 0.4305 | R53: 0.4305 | S53: [assumption] pilar 2: SUPUESTO CLAVE (propuesta; pilar del nuevo CEO). Calibrado para que el margen EBITDA del modelo sea 14.7% en FY26 (FY25 13.8% + ~90pb, punto medio de la guía de la administración de +70-120pb, elevada el 2026-07-23 [guidance] conferencia de resultados 2Q26), 14.5% en FY27 (rezago del trigo), y luego +20pb/año de productividad hasta 15.3% en FY30. Incluye reestructuración a un nivel recurrente (FY24 6,293; FY25 3,908). Histórico 43.8/38.0/42.5/44.5/44.4%.
B54: D&A / ventas | I54: 0.059 | J54: 0.059 | K54: 0.059 | L54: 0.0585 | M54: 0.0585 | N54: 0.0585 | O54: 0.0585 | P54: 0.0585 | Q54: 0.0585 | R54: 0.0585 | S54: [assumption] pilar -: Mecánico: FY24-FY25 5.65-5.82% incl. depreciación de activos por derecho de uso (6,142 en FY25); se mantiene cerca de 5.85-5.9% conforme el capex se normaliza [calc] data/financials.csv.
B55: Capex / ventas | I55: 0.046 | J55: 0.05 | K55: 0.052 | L55: 0.054 | M55: 0.055 | N55: 0.056 | O55: 0.057 | P55: 0.058 | Q55: 0.059 | R55: 0.06 | S55: [assumption] pillar 3: DRIVER DE LA HISTORIA (propuesta; pilar de deuda/FCF). FY26 = guía de la administración US$1.0-1.2bn (recortada el 2026-07-23 [guidance]) a ~Ps 17.6/US$ = ~Ps 19.4bn = 4.6% de las ventas; FY27-28 ~5.0-5.2% (consenso de capex US$1.21-1.24bn [sourced] CIQ 2026-10-17). Sube a 6.0% para FY35 [assumption] (historial 6.3/7.4/8.9/7.4/5.4%, promedio FY21-25 de 7.0%). En la base publicada (el pasivo por arrendamiento crece con las ventas), la reinversión neta terminal total equivale a 29% del NOPAT y el rendimiento sobre el capital nuevo implícito en el valor terminal es de 14.6% (base del motor 17.9%); cada 50 pb de capex = Ps 9.44 por acción (valuation/BIMBOA_DCF_v3.xlsx, Levers). Referencias [calc] valuation/BIMBOA_PeerAnalysis_v3.xlsx: capex / ventas del consenso de pares 3.66/3.82/3.79% (FY1-FY3), consenso de Bimbo 5.16/5.02/4.90% (FY2026-28); las pruebas de deterioro de la compañía suponen 3.3-4.3% (RA25 p.265, capex de continuidad). El nivel terminal es decisión del equipo (valuation/valuation.md, sección 11).
B56: Principal de arrendamientos pagado / ventas (motor: = nuevos arrendamientos) | I56: 0.0139 | J56: 0.0139 | K56: 0.0139 | L56: 0.0139 | M56: 0.0139 | N56: 0.0139 | O56: 0.0139 | P56: 0.0139 | Q56: 0.0139 | R56: 0.0139 | S56: [assumption] pillar -: Mecánico: principal de arrendamientos de FY25 5,923 / ventas 426,952 = 1.39% (FY23-25: 1.20/1.30/1.39%) [calc]. El principal se deriva (pagos de 8,060 menos interés por arrendamiento de 2,137) y se etiqueta como calc en data/financials.csv: los reportes presentados no separan el interés en efectivo dentro de los pagos de arrendamiento (data/adjustments.md #6). El motor también lo usa como nuevos arrendamientos, lo que mantiene constante el pasivo por arrendamiento; la base publicada en valuation/BIMBOA_DCF_v3.xlsx suma el crecimiento del pasivo por arrendamiento (mantenido en el 8.15% de las ventas de FY2025).
B57: Días de cuentas por cobrar (DSO, sobre ventas) | I57: 20.3 | J57: 20.3 | K57: 20.3 | L57: 20.3 | M57: 20.3 | N57: 20.3 | O57: 20.3 | P57: 20.3 | Q57: 20.3 | R57: 20.3 | S57: [assumption] pilar -: Mecánico: FY25 20.3 días (rango FY21-25 19.4-21.1) solo sobre cuentas por cobrar comerciales [calc].
B58: Días de inventario (DIO, sobre costo de ventas) | I58: 30.8 | J58: 30.8 | K58: 30.8 | L58: 30.8 | M58: 30.8 | N58: 30.8 | O58: 30.8 | P58: 30.8 | Q58: 30.8 | R58: 30.8 | S58: [assumption] pilar -: Mecánico: FY25 30.8 días sobre costo de ventas (rango FY21-25 30.3-35.5) [calc].
... B62: Tasa efectiva de impuestos (sobre EBIT en el DCF) | I62: 0.34 | J62: 0.34 | K62: 0.34 | L62: 0.34 | M62: 0.34 | N62: 0.34 | O62: 0.34 | P62: 0.34 | Q62: 0.34 | R62: 0.34 | S62: [assumption] pilar -: Tasa efectiva (no marginal): FY23-25 33.1/32.6/35.7%, 1H26 ~37% [calc]; tasa legal de 30% más partidas no deducibles y unidades con pérdidas. El WACC usa por separado la tasa marginal de 30%.
B64: FLUJOS DE EFECTIVO PROYECTADOS (millones de MXN) | D64: FY2021A | E64: FY2022A | F64: FY2023A | G64: FY2024A | H64: FY2025A | I64: FY2026E | J64: FY2027E | K64: FY2028E | L64: FY2029E | M64: FY2030E | N64: FY2031E | O64: FY2032E | P64: FY2033E | Q64: FY2034E | R64: FY2035E | S64: Etiqueta / fuente / nota
B65: Norteamérica | D65: 175369 | E65: 205674 | F65: 192534 | G65: 189330 | H65: 190211 | I65: =H65*(1+I47+$D$42) -> 176135.39 | J65: =I65*(1+J47+$D$42) -> 181419.45 | K65: =J65*(1+K47+$D$42) -> 186862.03 | L65: =K65*(1+L47+$D$42) -> 192467.89 | M65: =L65*(1+M47+$D$42) -> 198241.93 | N65: =M65*(1+N47+$D$42) -> 204189.19 | O65: =N65*(1+O47+$D$42) -> 210314.86 | P65: =O65*(1+P47+$D$42) -> 216624.31 | ... R65: =Q65*(1+R47+$D$42) -> 229816.73 | S65: [sourced] ventas por segmento, data/financials.csv (histórico)
B66: México | D66: 109089 | E66: 130401 | F66: 145387 | G66: 151164 | H66: 154809 | I66: =H66*(1+I48+$D$42) -> 161930.21 | J66: =I66*(1+J48+$D$42) -> 170836.38 | K66: =J66*(1+K48+$D$42) -> 179805.29 | L66: =K66*(1+L48+$D$42) -> 189245.06 | M66: =L66*(1+M48+$D$42) -> 199180.43 | N66: =M66*(1+N48+$D$42) -> 209438.22 | O66: =N66*(1+O48+$D$42) -> 220119.57 | P66: =O66*(1+P48+$D$42) -> 231235.61 | ... R66: =Q66*(1+R48+$D$42) -> 254937.26 | S66: [sourced] ventas por segmento, data/financials.csv (histórico)
B67: Europa, Asia y África | D67: 34195 | E67: 37536 | F67: 40545 | G67: 45044 | H67: 54214 | I67: =H67*(1+I49+$D$42) -> 54539.284 | J67: =I67*(1+J49+$D$42) -> 56993.552 | K67: =J67*(1+K49+$D$42) -> 59558.262 | L67: =K67*(1+L49+$D$42) -> 62238.383 | M67: =L67*(1+M49+$D$42) -> 65039.111 | N67: =M67*(1+N49+$D$42) -> 67933.351 | O67: =N67*(1+O49+$D$42) -> 70922.419 | P67: =O67*(1+P49+$D$42) -> 74007.544 | ... R67: =Q67*(1+R49+$D$42) -> 80470.437 | S67: [sourced] ventas por segmento, data/financials.csv (histórico)
B68: Latinoamérica | D68: 31109 | E68: 38411 | F68: 36647 | G68: 39879 | H68: 44120 | I68: =H68*(1+I50+$D$42) -> 47870.2 | J68: =I68*(1+J50+$D$42) -> 51221.114 | K68: =J68*(1+K50+$D$42) -> 54550.486 | L68: =K68*(1+L50+$D$42) -> 58096.268 | M68: =L68*(1+M50+$D$42) -> 61872.525 | N68: =M68*(1+N50+$D$42) -> 65770.495 | O68: =N68*(1+O50+$D$42) -> 69782.495 | P68: =O68*(1+P50+$D$42) -> 73899.662 | ... R68: =Q68*(1+R50+$D$42) -> 82408.099 | S68: [sourced] ventas por segmento, data/financials.csv (histórico)
B69: Eliminaciones interregionales | D69: -10970 | E69: -13316 | F69: -15234 | G69: -17082 | H69: -16402 | I69: =H69*(1+I51+$D$42) -> -16992.472 | J69: =I69*(1+J51+$D$42) -> -17757.133 | K69: =J69*(1+K51+$D$42) -> -18556.204 | L69: =K69*(1+L51+$D$42) -> -19391.233 | M69: =L69*(1+M51+$D$42) -> -20263.839 | N69: =M69*(1+N51+$D$42) -> -21175.712 | O69: =N69*(1+O51+$D$42) -> -22128.619 | P69: =O69*(1+P51+$D$42) -> -23124.407 | ... R69: =Q69*(1+R51+$D$42) -> -25252.43 | S69: [sourced] ventas por segmento, data/financials.csv (histórico)
B70: Ventas totales | D70: 338792 | E70: 398706 | F70: 399879 | G70: 408335 | H70: 426952 | I70: =SUM(I65:I69) -> 423482.61 | J70: =SUM(J65:J69) -> 442713.36 | K70: =SUM(K65:K69) -> 462219.86 | L70: =SUM(L65:L69) -> 482656.37 | M70: =SUM(M65:M69) -> 504070.15 | N70: =SUM(N65:N69) -> 526155.54 | O70: =SUM(O65:O69) -> 549010.73 | P70: =SUM(P65:P69) -> 572642.72 | ... R70: =SUM(R65:R69) -> 622380.09 | S70: [sourced] histórico data/financials.csv; proyección = suma de segmentos (o supuesto de crecimiento)
B71: Crecimiento anual | E71: =E70/D70-1 -> 0.17684597 | F71: =F70/E70-1 -> 0.0029420174 | G71: =G70/F70-1 -> 0.021146397 | H71: =H70/G70-1 -> 0.045592467 | I71: =I70/H70-1 -> -0.0081259439 | J71: =J70/I70-1 -> 0.045410941 | K71: =K70/J70-1 -> 0.044061251 | L71: =L70/K70-1 -> 0.044213835 | ... R71: =R70/Q70-1 -> 0.042412788
B72: Costo de ventas | D72: 157703 | E72: 193325 | F72: 194369 | G72: 193407 | H72: 203465 | I72: =I70*(1-(I52+$D$43)) -> 201577.72 | J72: =J70*(1-(J52+$D$43)) -> 212502.41 | K72: =K70*(1-(K52+$D$43)) -> 220478.87 | L72: =L70*(1-(L52+$D$43)) -> 229261.78 | M72: =M70*(1-(M52+$D$43)) -> 239433.32 | N72: =N70*(1-(N52+$D$43)) -> 249923.88 | O72: =O70*(1-(O52+$D$43)) -> 260780.1 | P72: =P70*(1-(P52+$D$43)) -> 272005.29 | ... R72: =R70*(1-(R52+$D$43)) -> 295630.54 | S72: Proyección = ventas x (1 - (margen bruto + ajuste de escenario))
B73: Utilidad bruta | D73: =D70-D72 -> 181089 | E73: =E70-E72 -> 205381 | F73: =F70-F72 -> 205510 | G73: =G70-G72 -> 214928 | H73: =H70-H72 -> 223487 | I73: =I70-I72 -> 221904.89 | J73: =J70-J72 -> 230210.95 | K73: =K70-K72 -> 241740.99 | ... R73: =R70-R72 -> 326749.55
B74: Margen bruto | D74: =D73/D70 -> 0.5345138 | E74: =E73/E70 -> 0.51511891 | F74: =F73/F70 -> 0.51393046 | G74: =G73/G70 -> 0.52635214 | H74: =H73/H70 -> 0.5234476 | I74: =I73/I70 -> 0.524 | J74: =J73/J70 -> 0.52 | K74: =K73/K70 -> 0.523 | ... R74: =R73/R70 -> 0.525
B75: Gastos de operación (netos, incl. PTU) | D75: 148509 | E75: 151685 | F75: 170055 | G75: 181779 | H75: 189341 | I75: =I70*I53 -> 184638.42 | J75: =J70*J53 -> 192137.6 | K75: =K70*K53 -> 200141.2 | L75: =L70*L53 -> 208748.88 | M75: =M70*M53 -> 217002.2 | N75: =N70*N53 -> 226509.96 | O75: =O70*O53 -> 236349.12 | P75: =P70*P53 -> 246522.69 | ... R75: =R70*R53 -> 267934.63
B76: EBIT | D76: =D73-D75 -> 32580 | E76: =E73-E75 -> 53696 | F76: =F73-F75 -> 35455 | G76: =G73-G75 -> 33149 | H76: =H73-H75 -> 34146 | I76: =I73-I75 -> 37266.47 | J76: =J73-J75 -> 38073.349 | K76: =K73-K75 -> 41599.787 | ... R76: =R73-R75 -> 58814.919
B77: Margen EBIT | D77: =D76/D70 -> 0.096165199 | E77: =E76/E70 -> 0.13467568 | F77: =F76/F70 -> 0.088664321 | G77: =G76/G70 -> 0.081180893 | H77: =H76/H70 -> 0.079976203 | I77: =I76/I70 -> 0.088 | J77: =J76/J70 -> 0.086 | K77: =K76/K70 -> 0.09 | ... R77: =R76/R70 -> 0.0945
B78: D&A (incl. depreciación de activos por derecho de uso) | D78: 16126 | E78: 18038 | F78: 18929 | G78: 23051 | H78: 24838 | I78: =I70*I54 -> 24985.474 | J78: =J70*J54 -> 26120.088 | K78: =K70*K54 -> 27270.972 | L78: =L70*L54 -> 28235.398 | M78: =M70*M54 -> 29488.104 | N78: =N70*N54 -> 30780.099 | O78: =O70*O54 -> 32117.128 | P78: =P70*P54 -> 33499.599 | ... R78: =R70*R54 -> 36409.235
B79: EBITDA (post-IFRS 16) = EBIT + D&A | D79: =D76+D78 -> 48706 | E79: =E76+E78 -> 71734 | F79: =F76+F78 -> 54384 | G79: =G76+G78 -> 56200 | H79: =H76+H78 -> 58984 | I79: =I76+I78 -> 62251.944 | J79: =J76+J78 -> 64193.437 | K79: =K76+K78 -> 68870.759 | ... R79: =R76+R78 -> 95224.154 | S79: Definición del motor. El EBITDA ajustado de la compañía suma de nuevo las partidas no recurrentes (puente en data/adjustments.md).
B80: Margen EBITDA | D80: =D79/D70 -> 0.14376373 | E80: =E79/E70 -> 0.17991703 | F80: =F79/F70 -> 0.13600114 | G80: =G79/G70 -> 0.13763209 | H80: =H79/H70 -> 0.13815136 | I80: =I79/I70 -> 0.147 | J80: =J79/J70 -> 0.145 | K80: =K79/K70 -> 0.149 | ... R80: =R79/R70 -> 0.153
B81: Tasa de impuestos sobre EBIT | D81: 0.33422706 | E81: 0.2287564 | F81: 0.33135767 | G81: 0.32615163 | H81: 0.35729534 | I81: =I62 -> 0.34 | J81: =J62 -> 0.34 | K81: =K62 -> 0.34 | L81: =L62 -> 0.34 | M81: =M62 -> 0.34 | N81: =N62 -> 0.34 | O81: =O62 -> 0.34 | P81: =P62 -> 0.34 | ... R81: =R62 -> 0.34 | S81: Histórico: tasa efectiva = impuesto a la utilidad / utilidad antes de impuestos (solo informativo); proyección: supuesto de impuestos
B82: Menos: impuestos sobre EBIT | D82: =-D76*D81 -> -10889.118 | E82: =-E76*E81 -> -12283.304 | F82: =-F76*F81 -> -11748.286 | G82: =-G76*G81 -> -10811.6 | H82: =-H76*H81 -> -12200.207 | I82: =-I76*I81 -> -12670.6 | J82: =-J76*J81 -> -12944.939 | K82: =-K76*K81 -> -14143.928 | ... R82: =-R76*R81 -> -19997.072
B83: NOPAT (utilidad neta no apalancada) | D83: =D76+D82 -> 21690.882 | E83: =E76+E82 -> 41412.696 | F83: =F76+F82 -> 23706.714 | G83: =G76+G82 -> 22337.4 | H83: =H76+H82 -> 21945.793 | I83: =I76+I82 -> 24595.87 | J83: =J76+J82 -> 25128.41 | K83: =K76+K82 -> 27455.86 | ... R83: =R76+R82 -> 38817.846
B84: Más: D&A | D84: =D78 -> 16126 | E84: =E78 -> 18038 | F84: =F78 -> 18929 | G84: =G78 -> 23051 | H84: =H78 -> 24838 | I84: =I78 -> 24985.474 | J84: =J78 -> 26120.088 | K84: =K78 -> 27270.972 | ... R84: =R78 -> 36409.235
B85: Menos: inversión de capital (capex; PP&E + intangibles) | D85: -21293 | E85: -29467 | F85: -35672 | G85: -30174 | H85: -22841 | I85: =-I70*(I55+$D$44) -> -19480.2 | J85: =-J70*(J55+$D$44) -> -22135.668 | K85: =-K70*(K55+$D$44) -> -24035.433 | L85: =-L70*(L55+$D$44) -> -26063.444 | M85: =-M70*(M55+$D$44) -> -27723.859 | N85: =-N70*(N55+$D$44) -> -29464.71 | O85: =-O70*(O55+$D$44) -> -31293.611 | P85: =-P70*(P55+$D$44) -> -33213.278 | ... R85: =-R70*(R55+$D$44) -> -37342.806
B86: Menos: nuevos arrendamientos (IFRS 16; aproximación del motor = principal de arrendamientos pagado) | D86: -4117 | E86: -5056 | F86: -4802 | G86: -5321 | H86: -5923 | I86: =-I70*I56 -> -5886.4083 | J86: =-J70*J56 -> -6153.7156 | K86: =-K70*K56 -> -6424.8561 | L86: =-L70*L56 -> -6708.9236 | M86: =-M70*M56 -> -7006.5751 | N86: =-N70*N56 -> -7313.562 | O86: =-O70*O56 -> -7631.2491 | P86: =-P70*P56 -> -7959.7337 | ... R86: =-R70*R56 -> -8651.0833 | S86: Aproximación del motor (mantiene constante el pasivo por arrendamiento). La base publicada de abajo también deduce el crecimiento del pasivo por arrendamiento.
B87: Más / (menos): cambio en el capital de trabajo operativo | E87: =E102 -> 6533 | F87: =F102 -> -10264 | G87: =G102 -> -1918 | H87: =H102 -> 696 | I87: =I102 -> -53.145454 | J87: =J102 -> 471.37477 | K87: =K102 -> 143.57226 | L87: =L102 -> 196.00661 | ... R87: =R102 -> 366.64602 | S87: De la cédula de capital de trabajo de abajo
B88: Flujo libre de efectivo no apalancado (FCFF) | E88: =E83+E84+E85+E86+E87 -> 31460.696 | F88: =F83+F84+F85+F86+F87 -> -8102.2863 | G88: =G83+G84+G85+G86+G87 -> 7975.3996 | H88: =H83+H84+H85+H86+H87 -> 18715.793 | I88: =I83+I84+I85+I86+I87 -> 24161.59 | J88: =J83+J84+J85+J86+J87 -> 23430.489 | K88: =K83+K84+K85+K86+K87 -> 24410.115 | L88: =L83+L84+L85+L86+L87 -> 25125.208 | ... R88: =R83+R84+R85+R86+R87 -> 29599.839 | S88: Motor: FCFF = NOPAT + D&A - capex - nuevos arrendamientos + cambio en el capital de trabajo. Histórico: solo informativo.
B89: Crecimiento anual | J89: =IFERROR(J88/I88-1,0) -> -0.030258807 | K89: =IFERROR(K88/J88-1,0) -> 0.041809862 | L89: =IFERROR(L88/K88-1,0) -> 0.02929496 | M89: =IFERROR(M88/L88-1,0) -> 0.054994167 | N89: =IFERROR(N88/M88-1,0) -> 0.023813304 | O89: =IFERROR(O88/N88-1,0) -> 0.023101658 | P89: =IFERROR(P88/O88-1,0) -> 0.022321074 | Q89: =IFERROR(Q88/P88-1,0) -> 0.021466298 | R89: =IFERROR(R88/Q88-1,0) -> 0.020889431
B90: Margen FCFF | I90: =I88/I70 -> 0.057054504 | J90: =J88/J70 -> 0.05292474 | K90: =K88/K70 -> 0.052810615 | L90: =L88/L70 -> 0.0520561 | M90: =M88/M70 -> 0.052585831 | N90: =N88/N70 -> 0.05157822 | O90: =O88/O70 -> 0.05057297 | P90: =P88/P70 -> 0.049568167 | ... R90: =R88/R70 -> 0.047559103
B92: CÉDULA DE CAPITAL DE TRABAJO (esquema del motor; los saldos no operativos se muestran por separado y se mantienen constantes en la proyección, por lo que solo las partidas operativas mueven el FCFF) | D92: FY2021A | E92: FY2022A | F92: FY2023A | G92: FY2024A | H92: FY2025A | I92: FY2026E | J92: FY2027E | K92: FY2028E | L92: FY2029E | M92: FY2030E | N92: FY2031E | O92: FY2032E | P92: FY2033E | Q92: FY2034E | R92: FY2035E | S92: Etiqueta / fuente / nota
B93: Cuentas por cobrar comerciales | D93: 19184 | E93: 21600 | F93: 21268 | G93: 23555 | H93: 23784 | I93: =I70*I57/365 -> 23552.595 | J93: =J70*J57/365 -> 24622.14 | K93: =K70*K57/365 -> 25707.022 | L93: =L70*L57/365 -> 26843.628 | M93: =M70*M57/365 -> 28034.587 | N93: =N70*N57/365 -> 29262.897 | O93: =O70*O57/365 -> 30534.021 | P93: =P70*P57/365 -> 31848.348 | ... R93: =R70*R57/365 -> 34614.564
B94: Inventarios | D94: 13710 | E94: 16989 | F94: 16120 | G94: 18832 | H94: 17151 | I94: =I72*I58/365 -> 17009.846 | J94: =J72*J58/365 -> 17931.71 | K94: =K72*K58/365 -> 18604.793 | L94: =L72*L58/365 -> 19345.925 | M94: =M72*M58/365 -> 20204.237 | N94: =N72*N58/365 -> 21089.467 | O94: =O72*O58/365 -> 22005.553 | P94: =P72*P58/365 -> 22952.775 | ... R94: =R72*R58/365 -> 24946.358
B95: Otros activos circulantes (total) | D95: 11769 | E95: 12568 | F95: 15173 | G95: 16736 | H95: 15201 | I95: =I70*I60 -> 15088.685 | J95: =J70*J60 -> 15710.126 | K95: =K70*K60 -> 16340.397 | L95: =L70*L60 -> 17001.088 | M95: =M70*M60 -> 17692.862 | N95: =N70*N60 -> 18406.499 | O95: =O70*O60 -> 19145.102 | P95: =P70*P60 -> 19908.497 | ... R95: =R70*R60 -> 21515.68
B96: de los cuales no operativos: derivados, depósitos de colateral, mantenidos para la venta (constantes) | D96: 1487 | E96: 1055 | F96: 1794 | G96: 2261 | H96: 1405 | I96: =$H96 -> 1405 | J96: =$H96 -> 1405 | K96: =$H96 -> 1405 | L96: =$H96 -> 1405 | M96: =$H96 -> 1405 | N96: =$H96 -> 1405 | O96: =$H96 -> 1405 | P96: =$H96 -> 1405 | ... R96: =$H96 -> 1405 | S96: [calc] histórico = total menos otras cuentas por cobrar y pagos anticipados (tabla de capital de trabajo operativo de data/adjustments.md); proyección constante en FY2025
B97: Cuentas por pagar comerciales | D97: 35752 | E97: 44058 | F97: 40409 | G97: 40815 | H97: 39074 | I97: =I72*I59/365 -> 38713.968 | J97: =J72*J59/365 -> 40812.107 | K97: =K72*K59/365 -> 42344.025 | L97: =L72*L59/365 -> 44030.823 | M97: =M72*M59/365 -> 45984.318 | N97: =N72*N59/365 -> 47999.08 | O97: =O72*O59/365 -> 50084.068 | P97: =P72*P59/365 -> 52239.92 | ... R97: =R72*R59/365 -> 56777.263
B98: Otros pasivos circulantes, sin deuda (total) | D98: 28590 | E98: 33311 | F98: 28100 | G98: 32338 | H98: 31788 | I98: =I70*I61 -> 31610.013 | J98: =J70*J61 -> 32596.099 | K98: =K70*K61 -> 33595.988 | L98: =L70*L61 -> 34643.626 | M98: =M70*M61 -> 35741.598 | N98: =N70*N61 -> 36874.033 | O98: =O70*O61 -> 38045.894 | P98: =P70*P61 -> 39257.521 | ... R98: =R70*R61 -> 41807.138
B99: de los cuales no operativos: impuestos a la utilidad y otros impuestos, intereses devengados, derivados (constantes) | D99: 6306 | E99: 11914 | F99: 9143 | G99: 10012 | H99: 9899 | I99: =$H99 -> 9899 | J99: =$H99 -> 9899 | K99: =$H99 -> 9899 | L99: =$H99 -> 9899 | M99: =$H99 -> 9899 | N99: =$H99 -> 9899 | O99: =$H99 -> 9899 | P99: =$H99 -> 9899 | ... R99: =$H99 -> 9899 | S99: [calc] histórico = total menos cuentas por pagar a partes relacionadas, PTU y pasivos acumulados operativos (nota 14); proyección constante en FY2025
B100: Capital de trabajo neto - base del motor (incl. saldos no operativos) | D100: =D93+D94+D95-D97-D98 -> -19679 | E100: =E93+E94+E95-E97-E98 -> -26212 | F100: =F93+F94+F95-F97-F98 -> -15948 | G100: =G93+G94+G95-G97-G98 -> -14030 | H100: =H93+H94+H95-H97-H98 -> -14726 | I100: =I93+I94+I95-I97-I98 -> -14672.855 | J100: =J93+J94+J95-J97-J98 -> -15144.229 | K100: =K93+K94+K95-K97-K98 -> -15287.802 | ... R100: =R93+R94+R95-R97-R98 -> -17507.799
B101: Capital de trabajo operativo = base del motor - activos no operativos + pasivos no operativos | D101: =D100-D96+D99 -> -14860 | E101: =E100-E96+E99 -> -15353 | F101: =F100-F96+F99 -> -8599 | G101: =G100-G96+G99 -> -6279 | H101: =H100-H96+H99 -> -6232 | I101: =I100-I96+I99 -> -6178.8545 | J101: =J100-J96+J99 -> -6650.2293 | K101: =K100-K96+K99 -> -6793.8016 | ... R101: =R100-R96+R99 -> -9013.7993 | S101: Cuadra con data/adjustments.md: -14,860 / -15,353 / -8,599 / -6,279 / -6,232 (Dec-21 a Dec-25); ver 'Checks'
B102: (Aumento) / disminución del capital de trabajo (signo de flujo de efectivo; usado en el FCFF) | E102: =-(E100-D100) -> 6533 | F102: =-(F100-E100) -> -10264 | G102: =-(G100-F100) -> -1918 | H102: =-(H100-G100) -> 696 | I102: =-(I100-H100) -> -53.145454 | J102: =-(J100-I100) -> 471.37477 | K102: =-(K100-J100) -> 143.57226 | L102: =-(L100-K100) -> 196.00661 | ... R102: =-(R100-Q100) -> 366.64602 | S102: Motor: change_nwc = -(dAR + dInv + dOCA - dAP - dOCL). Los saldos no operativos son constantes en la proyección (los supuestos los codifican como una proporción decreciente de las ventas), por lo que esto equivale al cambio operativo en la trayectoria base de ventas; bajo el escenario g_shift se mueven ligeramente con las ventas.
B103: Memo: (aumento) / disminución del capital de trabajo operativo | E103: =-(E101-D101) -> 493 | F103: =-(F101-E101) -> -6754 | G103: =-(G101-F101) -> -2320 | H103: =-(H101-G101) -> -47 | I103: =-(I101-H101) -> -53.145454 | J103: =-(J101-I101) -> 471.37477 | K103: =-(K101-J101) -> 143.57226 | L103: =-(L101-K101) -> 196.00661 | ... R103: =-(R101-Q101) -> 366.64602
B105: DESCUENTO (al 31-Dec-2025; convención del motor) | D105: FY2021A | E105: FY2022A | F105: FY2023A | G105: FY2024A | H105: FY2025A | I105: FY2026E | J105: FY2027E | K105: FY2028E | L105: FY2029E | M105: FY2030E | N105: FY2031E | O105: FY2032E | P105: FY2033E | Q105: FY2034E | R105: FY2035E | S105: Etiqueta / fuente / nota
B106: Número de año proyectado | I106: 1 | J106: 2 | K106: 3 | L106: 4 | M106: 5 | N106: 6 | O106: 7 | P106: 8 | Q106: 9 | R106: 10
B107: Periodo de descuento = número de año - desfase de mitad de año | I107: =I106-$D$37 -> 0.5 | J107: =J106-$D$37 -> 1.5 | K107: =K106-$D$37 -> 2.5 | L107: =L106-$D$37 -> 3.5 | M107: =M106-$D$37 -> 4.5 | N107: =N106-$D$37 -> 5.5 | O107: =O106-$D$37 -> 6.5 | P107: =P106-$D$37 -> 7.5 | ... R107: =R106-$D$37 -> 9.5
B108: Factor de descuento = 1 / (1 + WACC) ^ periodo | I108: =1/(1+$D$34)^I107 -> 0.95206462 | J108: =1/(1+$D$34)^J107 -> 0.86297711 | K108: =1/(1+$D$34)^K107 -> 0.78222579 | L108: =1/(1+$D$34)^L107 -> 0.7090306 | M108: =1/(1+$D$34)^M107 -> 0.64268451 | N108: =1/(1+$D$34)^N107 -> 0.58254662 | O108: =1/(1+$D$34)^O107 -> 0.528036 | P108: =1/(1+$D$34)^P107 -> 0.47862611 | ... R108: =1/(1+$D$34)^R107 -> 0.39324399
B109: Valor presente del FCFF | I109: =I88*I108 -> 23003.395 | J109: =J88*J108 -> 20219.976 | K109: =K88*K108 -> 19094.221 | L109: =L88*L108 -> 17814.542 | M109: =M88*M108 -> 17035.605 | N109: =N88*N108 -> 15809.247 | O109: =O88*O108 -> 14660.974 | P109: =P88*P108 -> 13585.73 | ... R109: =R88*R108 -> 11639.959
B111: VALOR PRESENTE DE LA EMPRESA
B112: Suma del VP del FCFF, FY2026E-FY2035E | D112: =SUM(I109:R109) -> 165442.47
...

Sheet Reverse_DCF
B2: DCF inverso - lo que implica el precio de mercado
B3: Estructura según la pestaña 'Reverse_DCF' de S&P. La plantilla obtiene el crecimiento implícito con una macro de VBA; aquí el procedimiento es Goal Seek de Excel sobre una sola celda de insumo (sin macros).
B5: 1. Crecimiento perpetuo implícito en el precio de mercado - base PUBLICADA (principal)
B6: EV de mercado al cierre fiscal = precio / factor de traslado x acciones + deuda neta + NCI + todas las partidas similares a deuda - no operativos | D6: =DCF!$D$146/DCF!$D$148*DCF!$D$145+DCF!$D$127+DCF!$D$128+DCF!$D$142-DCF!$D$144 -> 440085.8
B7: VP del FCFF explícito, base publicada | D7: =DCF!$D$183 -> 156185.94
B8: Valor terminal implícito en el mercado (a la fecha de descuento de Gordon) | D8: =($D$6-$D$7)*(1+DCF!$D$34)^(10-DCF!$D$37) -> 721943.29
B9: Crecimiento perpetuo implícito en el precio de mercado = (TV x WACC - FCFF_N) / (TV + FCFF_N - L_N) | D9: =IF($D$6>$D$7,($D$8*DCF!$D$34-DCF!R88)/($D$8+DCF!R88-DCF!R174),"n.m.") -> 0.064107468
B10: Crecimiento perpetuo usado en el DCF | D10: =DCF!$D$39 -> 0.0425
B12: 1b. Crecimiento perpetuo implícito en el precio de mercado - base del motor (conciliación con el motor)
B13: EV de mercado al cierre fiscal = precio / factor de traslado x acciones + deuda neta + NCI + partidas similares a deuda - no operativos | D13: =DCF!$D$146/DCF!$D$148*DCF!$D$145+DCF!$D$127+DCF!$D$128+DCF!$D$142-DCF!$D$144 -> 440085.8
B14: VP del FCFF explícito (del DCF) | D14: =DCF!$D$112 -> 165442.47
B15: Valor terminal implícito en el mercado (a la fecha de descuento de Gordon) | D15: =($D$13-$D$14)*(1+DCF!$D$34)^(10-DCF!$D$37) -> 698404.39
B16: Crecimiento perpetuo implícito en el precio de mercado | D16: =IF($D$13>$D$14,($D$15*DCF!$D$34-DCF!R88)/($D$15+DCF!R88),"n.m.") -> 0.058376545
B17: Crecimiento perpetuo usado en el DCF | D17: =DCF!$D$39 -> 0.0425
B18: Validación: definido solo cuando el EV de mercado excede el VP de los flujos de efectivo explícitos.
B20: 2. Ajuste del crecimiento de ventas implícito en el precio de mercado (los demás supuestos fijos)
B21: Procedimiento | E21: Datos > Análisis de hipótesis > Goal Seek: fijar 'DCF'!D192 (valor de Gordon publicado hoy) al precio actual cambiando 'DCF'!D42. Después, regresar el ajuste a 0.
B22: Solución de referencia - Gordon, publicado (bisección en Python, valuation/build/dcf_core.py) | D22: 0.034226966 | E22: Ajuste uniforme sumado al supuesto de crecimiento de cada año proyectado; n.a. si no hay solución en -10%..+10%.
B23: Solución de referencia - múltiplo de salida, publicado | D23: 0.017772774
B24: Solución de referencia - Gordon, base del motor | D24: 0.023347786 | E24: Solo para conciliación.

Sheet Levers
B2: Palancas clave - valor por acción hoy publicado (Gordon y salida), MXN
B3: Valores ESTÁTICOS calculados por valuation/build/dcf_core.py con los mismos insumos (base publicada: los arrendamientos crecen con las ventas; salida con reclamos consistentes con el EV de los pares); reconstruir para actualizar. Palancas dinámicas de un solo escenario: los insumos de ajuste en la hoja 'DCF'.
B5: Valor por acción hoy - Gordon: ajuste de capex/ventas (filas) x ajuste del margen bruto (columnas)
B6: Ajuste de capex (filas) / ajuste de margen bruto (columnas) | C6: -0.01 | D6: -0.005 | E6: 0 | F6: 0.005 | G6: 0.01
B7: -0.01 | C7: 40.159005 | D7: 46.292566 | E7: 52.426126 | F7: 58.559687 | G7: 64.693248
B8: -0.005 | C8: 30.721738 | D8: 36.855299 | E8: 42.98886 | F8: 49.122421 | G8: 55.255981
B9: 0 | C9: 21.284472 | D9: 27.418032 | E9: 33.551593 | F9: 39.685154 | G9: 45.818715
B10: 0.005 | C10: 11.847205 | D10: 17.980766 | E10: 24.114327 | F10: 30.247887 | G10: 36.381448
B11: 0.01 | C11: 2.4099383 | D11: 8.5434991 | E11: 14.67706 | F11: 20.810621 | G11: 26.944181
B13: Valor por acción hoy - múltiplo de salida: ajuste de capex/ventas (filas) x ajuste del margen bruto (columnas)
B14: Ajuste de capex (filas) / ajuste de margen bruto (columnas) | C14: -0.01 | D14: -0.005 | E14: 0 | F14: 0.005 | G14: 0.01
B15: -0.01 | C15: 45.054888 | D15: 49.456062 | E15: 53.857237 | F15: 58.258412 | G15: 62.659587
B16: -0.005 | C16: 40.983811 | D16: 45.384986 | E16: 49.786161 | F16: 54.187336 | G16: 58.58851
B17: 0 | C17: 36.912735 | D17: 41.31391 | E17: 45.715085 | F17: 50.116259 | G17: 54.517434
B18: 0.005 | C18: 32.841659 | D18: 37.242834 | E18: 41.644008 | F18: 46.045183 | G18: 50.446358
B19: 0.01 | C19: 28.770583 | D19: 33.171757 | E19: 37.572932 | F19: 41.974107 | G19: 46.375282
B21: Economía del valor terminal por ajuste de capex (Gordon, publicado)
B22: Ajuste de capex | C22: Valor / acción | D22: RONIC implícito en el TV | E22: Reinversión neta terminal / NOPAT | F22: Margen FCFF FY2035
B23: -0.01 | C23: 52.426126 | D23: 0.32592979 | E23: 0.13039618 | F23: 0.05424373
B24: -0.005 | C24: 42.98886 | D24: 0.2018399 | E24: 0.21056293 | F24: 0.04924373
B25: 0 | C25: 33.551593 | D25: 0.14618391 | E25: 0.29072968 | F25: 0.04424373
B26: 0.005 | C26: 24.114327 | D26: 0.11458725 | E26: 0.37089642 | F26: 0.03924373
B27: 0.01 | C27: 14.67706 | D27: 0.094221836 | E27: 0.45106317 | F27: 0.03424373
B29: Ajuste del crecimiento de ventas (todos los segmentos, todos los años) - valor por acción hoy publicado
B30: Ajuste de crecimiento | C30: Gordon | D30: Salida
B31: -0.01 | C31: 27.447029 | D31: 39.209542
B32: -0.005 | C32: 30.437369 | D32: 42.398975
B33: 0 | C33: 33.551593 | D33: 45.715085
B34: 0.005 | C34: 36.794547 | D34: 49.162589
B35: 0.01 | C35: 40.171244 | D35: 52.74636

Sheet Scenarios
B2: Escenarios - valor por acción hoy publicado (MXN), un cambio a la vez contra la base
B3: Valores ESTÁTICOS calculados por valuation/build/dcf_core.py con los mismos insumos que la hoja DCF (base publicada); reconstruir para actualizar. La base es propuesta del asistente; cada una de las demás filas es una alternativa que el equipo puede adoptar. El precio objetivo y la recomendación corresponden al equipo.
B5: BASE
B6: Escenario | C6: WACC | D6: ke | E6: g | F6: Gordon | G6: Salida | H6: vs precio (G) | I6: vs precio (X) | J6: RONIC (TV) | K6: Qué cambia
B7: Base: ruta B, CRP ponderada por EBITDA ajustado FY2025 (aditiva); propuestas para supuestos y valor terminal | C7: 0.10323276 | D7: 0.12943651 | E7: 0.0425 | F7: 33.551593 | G7: 45.715085 | H7: -0.42744722 | I7: -0.2198791 | J7: 0.14618391 | K7: valuation.yaml / drivers.yaml
B9: COSTO DE CAPITAL
B10: Escenario | C10: WACC | D10: ke | E10: g | F10: Gordon | G10: Salida | H10: vs precio (G) | I10: vs precio (X) | J10: RONIC (TV) | K10: Qué cambia
B11: Ruta A local: M-Bono a 10 años como tasa libre de riesgo, sin prima de riesgo país | C11: 0.1015131 | D11: 0.12643898 | E11: 0.0425 | F11: 35.717554 | G11: 46.604264 | H11: -0.39048543 | I11: -0.2047054 | J11: 0.14618391 | K11: ruta local preferida de la guía del proyecto
B12: Ruta B, CRP ponderada por ventas FY2025 | C12: 0.1012543 | D12: 0.12598786 | E12: 0.0425 | F12: 36.053921 | G12: 46.738485 | H12: -0.38474538 | I12: -0.20241493 | J12: 0.14618391 | K12: CRP 1.70%
B13: Ruta B, CRP ponderada por EBITDA ajustado promedio FY2023-25 | C13: 0.10289076 | D13: 0.12884038 | E13: 0.0425 | F13: 33.973047 | G13: 45.891538 | H13: -0.42025516 | I13: -0.21686795 | J13: 0.14618391 | K13: CRP 1.99%
B14: Ruta B, CRP ponderada por ventas promedio FY2023-25 | C14: 0.10094966 | D14: 0.12545684 | E14: 0.0425 | F14: 36.453471 | G14: 46.896602 | H14: -0.37792712 | I14: -0.19971669 | J14: 0.14618391 | K14: CRP 1.65%
B15: Ruta B, pesos de EBITDA, sin Argentina | C15: 0.10303474 | D15: 0.12909135 | E15: 0.0425 | F15: 33.795065 | G15: 45.817227 | H15: -0.42329241 | I15: -0.21813606 | J15: 0.14618391 | K15: CRP 2.02%
B16: Ruta B, CRP escalada por beta: ke = rf + beta_l x (ERP + CRP) | C16: 0.10094795 | D16: 0.12545387 | E16: 0.0425 | F16: 36.455716 | G16: 46.897486 | H16: -0.3778888 | I16: -0.1997016 | J16: 0.14618391 | K16: ERP de Damodaran ponderada por operaciones
B17: Beta: regresión de Bimbo a 5 años vs IPC (desapalancada) | C17: 0.10365799 | D17: 0.13017774 | E17: 0.0425 | F17: 33.033777 | G17: 45.49596 | H17: -0.43628367 | I17: -0.22361842 | J17: 0.14618391 | K17: valuation/inputs/beta_regression.json
B18: Beta: igual, ajustada por Blume | C18: 0.10506269 | D18: 0.13262627 | E18: 0.0425 | F18: 31.370541 | G18: 44.774389 | H18: -0.46466654 | I18: -0.23593193 | J18: 0.14618391 | K18: 0.67 x b + 0.33
B19: Beta: regresión de Bimbo a 3 años (desapalancada) | C19: 0.11486236 | D19: 0.14970807 | E19: 0.0425 | F19: 21.46403 | G19: 39.853109 | H19: -0.63371962 | I19: -0.31991282 | J19: 0.14618391 | K19: ventana de desvalorización 2023-24
B21: SUPUESTO DE FX EN NORTEAMÉRICA (base: depreciación del peso de ~1.5% anual dentro del crecimiento en MXN de 3.0%)
B22: Escenario | C22: WACC | D22: ke | E22: g | F22: Gordon | G22: Salida | H22: vs precio (G) | I22: vs precio (X) | J22: RONIC (TV) | K22: Qué cambia
B23: PPP con metas de inflación (3% México vs 2% EE.UU.): la depreciación de 0.98% anual sustituye al 1.5% | C23: 0.10323276 | D23: 0.12943651 | E23: 0.040609346 | F23: 31.365492 | G23: 44.802799 | H23: -0.4647527 | I23: -0.23544712 | J23: 0.14042586 | K23: Crecimiento de NA FY2027+ 2.47%; participación de NA en FY2035 35.9%; g 4.06%; el crecimiento de NCI también cambió
B24: PPP con la inflación de la encuesta de Banxico (3.70% vs 2%): la depreciación de 1.67% anual sustituye al 1.5% | C24: 0.10323276 | D24: 0.12943651 | E24: 0.043130347 | F24: 34.303464 | G24: 46.011427 | H24: -0.41461665 | I24: -0.21482207 | J24: 0.14809059 | K24: Crecimiento de NA FY2027+ 3.17%; participación de NA en FY2035 37.3%; g 4.31%
B26: SENSIBILIDAD DEL CAPEX (capex FY2031-35 / ventas, que también fija el valor terminal; trayectoria base de 5.6% a 6.0%)
B27: Escenario | C27: WACC | D27: ke | E27: g | F27: Gordon | G27: Salida | H27: vs precio (G) | I27: vs precio (X) | J27: RONIC (TV) | K27: Qué cambia
B28: Capex mantenido en 5.5% (nivel de FY2030) | C28: 0.10323276 | D28: 0.12943651 | E28: 0.0425 | F28: 39.931555 | G28: 46.728856 | H28: -0.31857414 | I28: -0.20257925 | J28: 0.2018399 | K28: sin más aumento
B29: Capex 5.0% (consenso de Bimbo FY2027-28: alrededor de 5.0%) | C29: 0.10323276 | D29: 0.12943651 | E29: 0.0425 | F29: 47.053102 | G29: 48.484213 | H29: -0.19704604 | I29: -0.17262436 | J29: 0.32592979 | K29: consenso de corto plazo, no una estimación de reinversión perpetua
B30: Capex 4.5% | C30: 0.10323276 | D30: 0.12943651 | E30: 0.0425 | F30: 54.174648 | G30: 50.239569 | H30: -0.075517944 | I30: -0.14266947 | J30: 0.84611742 | K30: cerca de la D&A FY2025 sin activos por derecho de uso (4.4%)
B31: Capex en la mediana del consenso de pares FY3 (3.8%) | C31: 0.10323276 | D31: 0.12943651 | E31: 0.0425 | F31: 64.35593 | G31: 52.749105 | H31: 0.098224061 | I31: -0.099844631 | J31: n.m. | K31: consenso de pares FY3; el RONIC muestra si es sostenible
B33: MÚLTIPLO DE SALIDA (solo método de salida)
B34: Escenario | C34: WACC | D34: ke | E34: g | F34: Gordon | G34: Salida | H34: vs precio (G) | I34: vs precio (X) | J34: RONIC (TV) | K34: Qué cambia
B35: Mediana EV/EBITDA LTM del núcleo de panificación (5.53x) | C35: 0.10323276 | D35: 0.12943651 | E35: 0.0425 | F35: 33.551593 | G35: 41.394318 | H35: -0.42744722 | I35: -0.29361232 | J35: 0.14618391 | K35: BIMBOA_PeerAnalysis_v3 (recalculado)
B36: Mediana EV/EBITDA LTM de todos los pares elegibles (8.27x) | C36: 0.10323276 | D36: 0.12943651 | E36: 0.0425 | F36: 33.551593 | G36: 66.383026 | H36: -0.42744722 | I36: 0.13281614 | J36: 0.14618391 | K36: BIMBOA_PeerAnalysis_v3 (recalculado)
B37: Múltiplo LTM propio de Bimbo sobre la misma base de reclamos (7.12x) | C37: 0.10323276 | D37: 0.12943651 | E37: 0.0425 | F37: 33.551593 | G37: 55.93701 | H37: -0.42744722 | I37: -0.04544351 | J37: 0.14618391 | K37: Puente de Jun-26, NCI a valor de mercado con el ke base
B39: Precio MXN 58.60 (cierre de BMV el 16-Oct-2026). RONIC = rendimiento sobre el capital nuevo implícito en el valor terminal de Gordon; 'n.m.' cuando la reinversión terminal es cero o negativa. Las filas de capex son sensibilidades: un capex menor, con la D&A mantenida en su trayectoria, eleva el RONIC implícito; un valor terminal sostenible requiere conciliar el capex, la depreciación no asociada a arrendamientos, la inversión en arrendamientos y el capital de trabajo (ver la tabla de menor rendimiento en la hoja DCF para el control cruzado con la fórmula de impulsores de valor).
B40: Las tasas de descuento de la prueba de deterioro de la compañía (RA25 p.265) son tasas contables posteriores a impuestos en cinco monedas; solo aparecen como contexto en los controles cruzados del libro WACC, sin valor implícito.
B41: El FCFF terminal de Gordon hace crecer el FCFF de FY2035 a la tasa g (convención del motor), por lo que el movimiento de capital de trabajo de FY2035 se traslada al año terminal; no se usa un año terminal de estado estable reconstruido.

Sheet Dated_Check
B2: Verificación cruzada a la fecha de valuación (anclada en el último balance general, 30-Jun-2026)
B3: Independiente del traslado del motor desde el cierre fiscal. Sigue siendo una aproximación por traslado del 30-Jun a la fecha de valuación, no un balance general observado de octubre.
B5: FCFF real de 1H26 (misma definición que el FCFF proyectado)
B6: EBIT 1H26 (utilidad de operación) | D6: 18858.3 | E6: [sourced] Utilidad de operación 1Q26 10,030.8 + 2Q26 8,827.5, S&P Capital IQ trimestral (data/capitaliq/income_statement.csv)
B7: Menos: ganancia no recurrente en el EBIT de 1H26 (venta de la participación en La Moderna, ~50 pb de las ventas de 1Q26) | D7: 501.6 | E7: [calc] Ganancia por la venta en 1Q26 de las participaciones de 4% en Grupo La Moderna (valor en libros 418.1) y Pasta4all (valor en libros 105.2) (BMV 1Q26 XBRL p.94-95) = ~50 pb [guidance] x ventas netas de 1Q26 100,318.7 [sourced] (BMV 1Q26 XBRL [310000] p.14). El monto no se divulga: CFO, llamada de 1Q26 2026-04-29 p.7 ('no divulgamos ... el monto'; 'aproximadamente 50 puntos base' del margen EBITDA de Grupo Bimbo). Verificación cruzada con el reporte presentado: ganancia por venta de activos no circulantes de 1Q26 441.1, incl. una ganancia en propiedades, planta y equipo de 29.5 (BMV 1Q26 XBRL [520000] p.17; nota de otros ingresos de operación p.103); 1H26 436.2, incl. una pérdida en propiedades, planta y equipo de 19.5 (BMV 2Q26 XBRL p.17, p.105). Rango ~412-502. Mientras one_off_in_fy26 = 1, el monto se cancela entre FY2026E y 1H26, por lo que no mueve Dated_Check. Los recursos ya están en el efectivo de Jun-26
B8: Tasa de impuestos (supuesto de proyección FY2026) | D8: =DCF!I62 -> 0.34
B9: D&A 1H26 | D9: 12125.1 | E9: [sourced] D&A total 1Q26 6,028.4 + 2Q26 6,096.7, flujo de efectivo trimestral de CIQ (la D&A de CIQ queda ~3% por debajo de la base del reporte presentado)
B10: Capex 1H26 (positivo) | D10: 6942 | E10: [sourced] Propiedades, planta y equipo 6,892 + intangibles 50, BMV Jun-26 p.17-18 (wiki bimbo-cash-flow-and-fcf)
B11: Principal de arrendamientos pagado 1H26 (positivo) | D11: 2906.39 | E11: [calc] Pagos de arrendamientos 3,948.42 menos intereses de arrendamientos devengados 1,042.03, movimiento de arrendamientos 1H26 (BMV 2Q26 XBRL p.100; pagos = flujo de efectivo 688.02 + 3,260.40, p.18). Misma base que data/financials.csv: la división en efectivo de los intereses no se divulga (data/adjustments.md ajuste 6)
B12: Cambio en el capital de trabajo operativo 1H26, signo de flujo de efectivo (balances generales de Dec-25 a Jun-26; impuestos a la utilidad excluidos) | D12: -2009 | E12: [calc] Base operativa, signo de flujo de efectivo, balances generales de CIQ de Dec-25 a Jun-26 (data/capitaliq/balance_sheet.csv): cuentas por cobrar comerciales +772, otras cuentas y documentos por cobrar +214, inventarios -44, otros activos circulantes +1,833, cuentas por pagar -830, gastos acumulados +1,816, otros pasivos circulantes -220 = -2,009. Impuestos a la utilidad por pagar (+4,538, estacionales) excluidos, como en el DCF, y deducidos abajo como reclamo de junio. Los desgloses de junio de otros activos circulantes y de acumulaciones no se divulgan, por lo que se tratan como operativos [assumption]. Base de flujo de efectivo de CIQ -2,528 (memo). Nueva verificación con Codex 2026-10-17
B13: FCFF 1H26 = (EBIT - partida no recurrente) x (1 - tasa de impuestos) + D&A - capex - principal de arrendamientos + cambio en capital de trabajo | D13: =($D$6-$D$7)*(1-$D$8)+$D$9-$D$10-$D$11+$D$12 -> 12383.132
B14: FCFF FY2026E, base publicada (DCF) | D14: =DCF!I179 -> 24444.292
B15: ¿La proyección FY2026E incluye la ganancia no recurrente de 1H26? (1 = sí, 0 = no) | D15: 1 | E15: [assumption] 1 = la proyección FY2026E incluye la ganancia (la propuesta de margen de 14.7% para FY2026 sigue la guía de la administración elevada después de 1Q26, que la contenía); el FCFF FY2026E se lleva entonces a la misma base antes de derivar 2H26. Usar 0 si la proyección la excluye
B16: FCFF FY2026E en la misma base de partida no recurrente que 1H26 = FY2026E - indicador x partida no recurrente x (1 - tasa de impuestos) | D16: =$D$14-$D$15*$D$7*(1-$D$8) -> 24113.236
B17: FCFF 2H26E = FY2026E (misma base) - 1H26 real | D17: =$D$16-$D$13 -> 11730.104 | E17: Ambas mitades excluyen la ganancia: los recursos de la venta de La Moderna ya están en el efectivo al 30-Jun-2026. La línea de arrendamientos de 1H26 es principal; el crecimiento del saldo de arrendamientos de FY2026 (base publicada) cae en 2H26.
B19: Valor presente al 30-Jun-2026 (convención de mitad de periodo, mismo WACC)
B20: Periodo de descuento de 2H26 = 0.5 x (1 - desfase) | D20: =0.5*(1-DCF!$D$37) -> 0.25
B21: VP del FCFF 2H26E | D21: =$D$17/(1+DCF!$D$34)^$D$20 -> 11445.508
B22: VP del FCFF FY2027E, publicado (periodo = 1 + 0.5 - desfase) | D22: =DCF!J179/(1+DCF!$D$34)^(1+0.5-DCF!$D$37) -> 19817.65
B23: VP del FCFF FY2028E, publicado (periodo = 2 + 0.5 - desfase) | D23: =DCF!K179/(1+DCF!$D$34)^(2+0.5-DCF!$D$37) -> 18749.662
B24: VP del FCFF FY2029E, publicado (periodo = 3 + 0.5 - desfase) | D24: =DCF!L179/(1+DCF!$D$34)^(3+0.5-DCF!$D$37) -> 17471.315
B25: VP del FCFF FY2030E, publicado (periodo = 4 + 0.5 - desfase) | D25: =DCF!M179/(1+DCF!$D$34)^(4+0.5-DCF!$D$37) -> 16715.451
B26: VP del FCFF FY2031E, publicado (periodo = 5 + 0.5 - desfase) | D26: =DCF!N179/(1+DCF!$D$34)^(5+0.5-DCF!$D$37) -> 15504.079
B27: VP del FCFF FY2032E, publicado (periodo = 6 + 0.5 - desfase) | D27: =DCF!O179/(1+DCF!$D$34)^(6+0.5-DCF!$D$37) -> 14366.24
B28: VP del FCFF FY2033E, publicado (periodo = 7 + 0.5 - desfase) | D28: =DCF!P179/(1+DCF!$D$34)^(7+0.5-DCF!$D$37) -> 13301.689
B29: VP del FCFF FY2034E, publicado (periodo = 8 + 0.5 - desfase) | D29: =DCF!Q179/(1+DCF!$D$34)^(8+0.5-DCF!$D$37) -> 12305.61
B30: VP del FCFF FY2035E, publicado (periodo = 9 + 0.5 - desfase) | D30: =DCF!R179/(1+DCF!$D$34)^(9+0.5-DCF!$D$37) -> 11373.735
B31: VP del valor terminal - Gordon, publicado (a la fecha del flujo final) | D31: =DCF!$D$185/(1+DCF!$D$34)^(9+0.5-DCF!$D$37) -> 195205.46
B32: VP del valor terminal - salida (fin de año FY2035) | D32: =DCF!$D$116/(1+DCF!$D$34)^(9+0.5) -> 224677.96
B33: EV al 30-Jun-2026 - Gordon | D33: =$D$21+$D$22+$D$23+$D$24+$D$25+$D$26+$D$27+$D$28+$D$29+$D$30+$D$31 -> 346256.4
B34: EV al 30-Jun-2026 - salida | D34: =$D$21+$D$22+$D$23+$D$24+$D$25+$D$26+$D$27+$D$28+$D$29+$D$30+$D$32 -> 375728.9
B36: Puente al valor del capital al 30-Jun-2026 y traslado a la fecha de valuación
B37: Deuda total sin arrendamientos, 30-Jun-2026 | D37: 153660 | E37: [sourced] Deuda financiera total al 30-Jun-2026 (nota de deuda de BMV Jun-26; comunicado de 2Q26 p.6)
B38: Pasivos por arrendamiento, 30-Jun-2026 | D38: 33361 | E38: [sourced] Pasivos por arrendamiento 7,113 + 26,248, balance general de CIQ 2026 FQ2
B39: Efectivo y equivalentes, 30-Jun-2026 | D39: 16563 | E39: [sourced] Efectivo y equivalentes al 30-Jun-2026 (CIQ; deuda neta 137,097 según el comunicado de 2Q26 p.6)
B40: Participación no controladora (en libros), 30-Jun-2026 | D40: 721.7 | E40: [sourced] Participación no controladora total al 30-Jun-2026, balance general de CIQ
B41: Prima a valor de mercado del NCI, 30-Jun-2026 = NCI a valor de mercado ('DCF', dinámico a ke) - valor en libros de junio | D41: =DCF!$D$132-$D$40 -> 17521.096
B42: Otras partidas similares a deuda, 30-Jun-2026 (misma política que el puente de Dec-25, excl. NCI) | D42: 18135 | E42: [calc] Misma política que Dec-25, 30-Jun-2026 (BMV 2Q26 XBRL, filings/bmv/Reporte_Definitivo_BMV_XBRL_Español_Jun_26.pdf): línea de beneficios a empleados 6,202 [sourced] p.13 x la proporción neta después de impuestos de Dec-25 0.6899 (4,489.35 / 6,507) = 4,278.92; provisiones 11,029.37 [sourced] p.59 = posiciones fiscales inciertas 8,692.48 + impuestos 1,318.41 (sin escudo fiscal) + laborales 511.64 y civiles 506.26 x 0.70 + otras 0.58 = 10,724.00; pasivos netos por derivados 1,864.18 [sourced] p.64-65 = pasivos 978.28 + 2,658.38 menos activos 784.79 + 987.70; MEPP 632.56 y compensaciones diferidas 635.34 después de impuestos. MEPP y compensaciones diferidas no se divulgan por separado en Jun-26: la línea de 'otras provisiones a largo plazo' es 13,011.49 (p.13), lo que deja 1,982.12 por encima de las provisiones (2,314.86 en Dec-25, formado por MEPP 985 + compensaciones diferidas 1,060 + otros 270), distribuido en las proporciones de Dec-25 [assumption]: MEPP 843.41 x 0.75, compensaciones diferidas 907.63 x 0.70. Antes: 19,343.67 con los valores de Dec-25 arrastrados. El reclamo de NCI se agrega de forma dinámica (valor de mercado menos valor en libros de junio)
B43: Impuestos a la utilidad por pagar estacionales al 30-Jun-2026 (junio menos el nivel de Dec-25; pagados en 2H26) | D43: 4538.05 | E43: [calc] Impuestos a la utilidad por pagar 5,597.05 (Jun-26) menos 1,059.0 (Dec-25), balance general de CIQ: impuestos devengados sobre las utilidades de 1H26 y pagados en 2H26. El nivel de Dec-25 permanece en los saldos no operativos constantes, como en el DCF. Se deduce en ambos métodos porque eleva el efectivo de junio
B44: Activos no operativos, 30-Jun-2026 (misma política que valuation.yaml) | D44: 6497.5 | E44: [sourced] Inversiones por el método de participación al 30-Jun-2026, balance general de CIQ
B45: Valor del capital al 30-Jun-2026 - Gordon (todos los reclamos) | D45: =$D$33-($D$37+$D$38-$D$39)-$D$43-$D$40-$D$41+$D$44-$D$42 -> 141380.05
B46: Valor del capital al 30-Jun-2026 - salida (reclamos consistentes con el EV de los pares: otras partidas similares a deuda reincorporadas) | D46: =$D$34-($D$37+$D$38-$D$39)-$D$43-$D$40-$D$41+$D$44 -> 188987.55
B47: Días del 30-Jun-2026 a la fecha de valuación | D47: 108 | E47: [calc] 30-Jun-2026 al 16-Oct-2026
B48: Factor de traslado = (1 + ke) ^ (días / 365) | D48: =(1+DCF!$D$30)^($D$47/365) -> 1.0366719
B49: Distribuciones pagadas entre el 30-Jun y la fecha de valuación (dividendos + recompras) | D49: 76 | E49: [unverified] Recompras en July 2026 por 1,340,500 acciones a ~MXN 57 (monto en efectivo no divulgado); dividendo pagado el 13-May-2026, antes del 30-Jun
B50: Acciones en circulación a la fecha de valuación, millones | D50: 4294.9437 | E50: [sourced] Acciones en circulación al 29-Jul-2026, aviso de la BMV (wacc_inputs A8)
B51: Valor por acción a la fecha de valuación - Gordon | D51: =($D$45*$D$48-$D$49)/$D$50 -> 34.107251
B52: Valor por acción a la fecha de valuación - salida | D52: =($D$46*$D$48-$D$49)/$D$50 -> 45.598286
B54: Conciliación con el traslado desde el cierre fiscal (base publicada, 'DCF')
B55: Valor hoy por traslado desde el cierre fiscal - Gordon, publicado ('DCF') | D55: =DCF!$D$192 -> 33.551593
B56: Valor a la fecha de valuación - Gordon | D56: =$D$51 -> 34.107251
B57: Diferencia - Gordon (valor a la fecha - traslado) | D57: =$D$51-DCF!$D$192 -> 0.55565743
B58: Diferencia - Gordon, % del valor por traslado desde el cierre fiscal | D58: =$D$51/DCF!$D$192-1 -> 0.016561283
B59: Valor hoy por traslado desde el cierre fiscal - salida, publicado | D59: =DCF!$D$194 -> 45.715085
B60: Valor a la fecha de valuación - salida | D60: =$D$52 -> 45.598286
B61: Diferencia - salida, % del valor por traslado desde el cierre fiscal | D61: =$D$52/DCF!$D$194-1 -> -0.0025549191
B62: Qué explica la diferencia (se completa desde la construcción del libro; con etiquetas)
B63: El motor traslada el valor del capital de Dec-25 al costo del capital propio; la verificación a la fecha de valuación parte del balance general al 30-Jun-2026, que ya refleja el dividendo del 13-May-2026 (MXN 4,627m) y las recompras de 1H26 (MXN 496m).
B64: La deuda neta sin IFRS 16 bajó de 145,128 (Dec-25) a 137,097 (Jun-26), apoyada por la fortaleza del peso sobre la deuda en USD y la generación de efectivo de 1H26.
B65: Sigue siendo una aproximación: el traslado del 30-Jun al 16-Oct usa el costo del capital propio, no un balance general observado de octubre.

Sheet Engine_Recon
B2: Conciliación con el motor del modelo (model/model-summary.json)
B3: Los valores del motor se pegan del resumen del motor (constantes); los valores del libro son fórmulas dinámicas. Tolerancia: diferencia relativa menor a 1e-6.
B5: Concepto | D5: Resumen del motor | E5: Este libro | F5: Diferencia | G5: Dif. rel. | H5: Estado | I5: Réplica en Python | J5: Dif. rel. vs réplica | K5: Estado vs réplica
B6: WACC | D6: 0.103233 | E6: =DCF!$D$34 -> 0.10323276 | F6: =IFERROR(E6-D6,"n.a.") -> -2.4326458e-07 | G6: =IFERROR(IF(D6=0,E6-D6,E6/D6-1),"n.a.") -> -2.3564614e-06 | H6: =IFERROR(IF(OR(ABS(G6)<0.000001,ABS(F6)<=0.0000005),"OK","CHECK"),"CHECK") -> OK | I6: 0.10323276 | J6: =IFERROR(IF(I6=0,E6-I6,E6/I6-1),"n.a.") -> 2.220446e-16 | K6: =IFERROR(IF(ABS(J6)<0.000001,"OK","CHECK"),"CHECK") -> OK
B7: EV - Gordon | D7: 365246.62 | E7: =DCF!$D$115 -> 365246.62 | F7: =IFERROR(E7-D7,"n.a.") -> -3.927853e-07 | G7: =IFERROR(IF(D7=0,E7-D7,E7/D7-1),"n.a.") -> -1.075362e-12 | H7: =IFERROR(IF(OR(ABS(G7)<0.000001,ABS(F7)<=0.0000005),"OK","CHECK"),"CHECK") -> OK | I7: 365246.62 | J7: =IFERROR(IF(I7=0,E7-I7,E7/I7-1),"n.a.") -> 2.220446e-16 | K7: =IFERROR(IF(ABS(J7)<0.000001,"OK","CHECK"),"CHECK") -> OK
B8: EV - salida | D8: 379350.4 | E8: =DCF!$D$118 -> 379350.4 | F8: =IFERROR(E8-D8,"n.a.") -> 4.763715e-07 | G8: =IFERROR(IF(D8=0,E8-D8,E8/D8-1),"n.a.") -> 1.2556622e-12 | H8: =IFERROR(IF(OR(ABS(G8)<0.000001,ABS(F8)<=0.0000005),"OK","CHECK"),"CHECK") -> OK | I8: 379350.4 | J8: =IFERROR(IF(I8=0,E8-I8,E8/I8-1),"n.a.") -> 0 | K8: =IFERROR(IF(ABS(J8)<0.000001,"OK","CHECK"),"CHECK") -> OK
B9: Valor por acción hoy - Gordon | D9: 39.481483 | E9: =DCF!$D$152 -> 39.481483 | F9: =IFERROR(E9-D9,"n.a.") -> -2.2708509e-07 | G9: =IFERROR(IF(D9=0,E9-D9,E9/D9-1),"n.a.") -> -5.7516859e-09 | H9: =IFERROR(IF(OR(ABS(G9)<0.000001,ABS(F9)<=0.0000005),"OK","CHECK"),"CHECK") -> OK | I9: 39.481483 | J9: =IFERROR(IF(I9=0,E9-I9,E9/I9-1),"n.a.") -> 7.4029671e-13 | K9: =IFERROR(IF(ABS(J9)<0.000001,"OK","CHECK"),"CHECK") -> OK
B10: Valor por acción hoy - salida | D10: 43.084454 | E10: =DCF!$D$159 -> 43.084454 | F10: =IFERROR(E10-D10,"n.a.") -> -1.1302988e-07 | G10: =IFERROR(IF(D10=0,E10-D10,E10/D10-1),"n.a.") -> -2.6234493e-09 | H10: =IFERROR(IF(OR(ABS(G10)<0.000001,ABS(F10)<=0.0000005),"OK","CHECK"),"CHECK") -> OK | I10: 43.084454 | J10: =IFERROR(IF(I10=0,E10-I10,E10/I10-1),"n.a.") -> 6.7745809e-13 | K10: =IFERROR(IF(ABS(J10)<0.000001,"OK","CHECK"),"CHECK") -> OK
B11: Precio objetivo a 12 meses - Gordon | D11: 43.410489 | E11: =DCF!$D$154 -> 43.410489 | F11: =IFERROR(E11-D11,"n.a.") -> 1.6263008e-07 | G11: =IFERROR(IF(D11=0,E11-D11,E11/D11-1),"n.a.") -> 3.7463315e-09 | H11: =IFERROR(IF(OR(ABS(G11)<0.000001,ABS(F11)<=0.0000005),"OK","CHECK"),"CHECK") -> OK | I11: 43.410489 | J11: =IFERROR(IF(I11=0,E11-I11,E11/I11-1),"n.a.") -> 7.6072482e-13 | K11: =IFERROR(IF(ABS(J11)<0.000001,"OK","CHECK"),"CHECK") -> OK
B12: Múltiplo de salida implícito | D12: 5.604397 | E12: =DCF!$D$167 -> 5.6043967 | F12: =IFERROR(E12-D12,"n.a.") -> -3.1274524e-07 | G12: =IFERROR(IF(D12=0,E12-D12,E12/D12-1),"n.a.") -> -5.5803549e-08 | H12: =IFERROR(IF(OR(ABS(G12)<0.000001,ABS(F12)<=0.0000005),"OK","CHECK"),"CHECK") -> OK | I12: 5.6043967 | J12: =IFERROR(IF(I12=0,E12-I12,E12/I12-1),"n.a.") -> 4.4408921e-16 | K12: =IFERROR(IF(ABS(J12)<0.000001,"OK","CHECK"),"CHECK") -> OK
B13: Crecimiento implícito en el múltiplo de salida | D13: 0.046298 | E13: =DCF!$D$168 -> 0.046297692 | F13: =IFERROR(E13-D13,"n.a.") -> -3.076193e-07 | G13: =IFERROR(IF(D13=0,E13-D13,E13/D13-1),"n.a.") -> -6.6443323e-06 | H13: =IFERROR(IF(OR(ABS(G13)<0.000001,ABS(F13)<=0.0000005),"OK","CHECK"),"CHECK") -> OK | I13: 0.046297692 | J13: =IFERROR(IF(I13=0,E13-I13,E13/I13-1),"n.a.") -> -4.4408921e-16 | K13: =IFERROR(IF(ABS(J13)<0.000001,"OK","CHECK"),"CHECK") -> OK
B14: Crecimiento perpetuo (g) implícito en el precio | D14: 0.058377 | E14: =Reverse_DCF!$D$16 -> 0.058376545 | F14: =IFERROR(E14-D14,"n.a.") -> -4.5531764e-07 | G14: =IFERROR(IF(D14=0,E14-D14,E14/D14-1),"n.a.") -> -7.7996066e-06 | H14: =IFERROR(IF(OR(ABS(G14)<0.000001,ABS(F14)<=0.0000005),"OK","CHECK"),"CHECK") -> OK | I14: 0.058376545 | J14: =IFERROR(IF(I14=0,E14-I14,E14/I14-1),"n.a.") -> -3.0697667e-13 | K14: =IFERROR(IF(ABS(J14)<0.000001,"OK","CHECK"),"CHECK") -> OK
B15: TV como % del EV - Gordon | D15: 0.547039 | E15: =DCF!$D$119 -> 0.54703902 | F15: =IFERROR(E15-D15,"n.a.") -> 1.675819e-08 | G15: =IFERROR(IF(D15=0,E15-D15,E15/D15-1),"n.a.") -> 3.0634361e-08 | H15: =IFERROR(IF(OR(ABS(G15)<0.000001,ABS(F15)<=0.0000005),"OK","CHECK"),"CHECK") -> OK | I15: 0.54703902 | J15: =IFERROR(IF(I15=0,E15-I15,E15/I15-1),"n.a.") -> 0 | K15: =IFERROR(IF(ABS(J15)<0.000001,"OK","CHECK"),"CHECK") -> OK
B16: FCFF FY2026E | D16: 24161.59 | E16: =DCF!I88 -> 24161.59 | F16: =IFERROR(E16-D16,"n.a.") -> 3.9433144e-07 | G16: =IFERROR(IF(D16=0,E16-D16,E16/D16-1),"n.a.") -> 1.6320501e-11 | H16: =IFERROR(IF(OR(ABS(G16)<0.000001,ABS(F16)<=0.0000005),"OK","CHECK"),"CHECK") -> OK | I16: 24161.59 | J16: =IFERROR(IF(I16=0,E16-I16,E16/I16-1),"n.a.") -> -3.3306691e-16 | K16: =IFERROR(IF(ABS(J16)<0.000001,"OK","CHECK"),"CHECK") -> OK
B17: FCFF FY2027E | D17: 23430.489 | E17: =DCF!J88 -> 23430.489 | F17: =IFERROR(E17-D17,"n.a.") -> 3.0883893e-07 | G17: =IFERROR(IF(D17=0,E17-D17,E17/D17-1),"n.a.") -> 1.3181012e-11 | H17: =IFERROR(IF(OR(ABS(G17)<0.000001,ABS(F17)<=0.0000005),"OK","CHECK"),"CHECK") -> OK | I17: 23430.489 | J17: =IFERROR(IF(I17=0,E17-I17,E17/I17-1),"n.a.") -> 6.6613381e-16 | K17: =IFERROR(IF(ABS(J17)<0.000001,"OK","CHECK"),"CHECK") -> OK
B18: FCFF FY2028E | D18: 24410.115 | E18: =DCF!K88 -> 24410.115 | F18: =IFERROR(E18-D18,"n.a.") -> 3.9762745e-07 | G18: =IFERROR(IF(D18=0,E18-D18,E18/D18-1),"n.a.") -> 1.6289414e-11 | H18: =IFERROR(IF(OR(ABS(G18)<0.000001,ABS(F18)<=0.0000005),"OK","CHECK"),"CHECK") -> OK | I18: 24410.115 | J18: =IFERROR(IF(I18=0,E18-I18,E18/I18-1),"n.a.") -> -4.4408921e-16 | K18: =IFERROR(IF(ABS(J18)<0.000001,"OK","CHECK"),"CHECK") -> OK
B19: FCFF FY2029E | D19: 25125.208 | E19: =DCF!L88 -> 25125.208 | F19: =IFERROR(E19-D19,"n.a.") -> 4.2443207e-07 | G19: =IFERROR(IF(D19=0,E19-D19,E19/D19-1),"n.a.") -> 1.6892709e-11 | H19: =IFERROR(IF(OR(ABS(G19)<0.000001,ABS(F19)<=0.0000005),"OK","CHECK"),"CHECK") -> OK | I19: 25125.208 | J19: =IFERROR(IF(I19=0,E19-I19,E19/I19-1),"n.a.") -> 0 | K19: =IFERROR(IF(ABS(J19)<0.000001,"OK","CHECK"),"CHECK") -> OK
B20: FCFF FY2030E | D20: 26506.948 | E20: =DCF!M88 -> 26506.948 | F20: =IFERROR(E20-D20,"n.a.") -> 1.0333679e-07 | G20: =IFERROR(IF(D20=0,E20-D20,E20/D20-1),"n.a.") -> 3.8984371e-12 | H20: =IFERROR(IF(OR(ABS(G20)<0.000001,ABS(F20)<=0.0000005),"OK","CHECK"),"CHECK") -> OK | I20: 26506.948 | J20: =IFERROR(IF(I20=0,E20-I20,E20/I20-1),"n.a.") -> -1.110223e-16 | K20: =IFERROR(IF(ABS(J20)<0.000001,"OK","CHECK"),"CHECK") -> OK
B21: FCFF FY2031E | D21: 27138.166 | E21: =DCF!N88 -> 27138.166 | F21: =IFERROR(E21-D21,"n.a.") -> 7.1118848e-08 | G21: =IFERROR(IF(D21=0,E21-D21,E21/D21-1),"n.a.") -> 2.6205704e-12 | H21: =IFERROR(IF(OR(ABS(G21)<0.000001,ABS(F21)<=0.0000005),"OK","CHECK"),"CHECK") -> OK | I21: 27138.166 | J21: =IFERROR(IF(I21=0,E21-I21,E21/I21-1),"n.a.") -> 0 | K21: =IFERROR(IF(ABS(J21)<0.000001,"OK","CHECK"),"CHECK") -> OK
B22: FCFF FY2032E | D22: 27765.103 | E22: =DCF!O88 -> 27765.103 | F22: =IFERROR(E22-D22,"n.a.") -> 3.1911623e-07 | G22: =IFERROR(IF(D22=0,E22-D22,E22/D22-1),"n.a.") -> 1.1493473e-11 | H22: =IFERROR(IF(OR(ABS(G22)<0.000001,ABS(F22)<=0.0000005),"OK","CHECK"),"CHECK") -> OK | I22: 27765.103 | J22: =IFERROR(IF(I22=0,E22-I22,E22/I22-1),"n.a.") -> 2.220446e-16 | K22: =IFERROR(IF(ABS(J22)<0.000001,"OK","CHECK"),"CHECK") -> OK
B23: FCFF FY2033E | D23: 28384.85 | E23: =DCF!P88 -> 28384.85 | F23: =IFERROR(E23-D23,"n.a.") -> 2.3863686e-07 | G23: =IFERROR(IF(D23=0,E23-D23,E23/D23-1),"n.a.") -> 8.4072749e-12 | H23: =IFERROR(IF(OR(ABS(G23)<0.000001,ABS(F23)<=0.0000005),"OK","CHECK"),"CHECK") -> OK | I23: 28384.85 | J23: =IFERROR(IF(I23=0,E23-I23,E23/I23-1),"n.a.") -> 2.220446e-16 | K23: =IFERROR(IF(ABS(J23)<0.000001,"OK","CHECK"),"CHECK") -> OK
B24: FCFF FY2034E | D24: 28994.167 | E24: =DCF!Q88 -> 28994.167 | F24: =IFERROR(E24-D24,"n.a.") -> -1.585795e-07 | G24: =IFERROR(IF(D24=0,E24-D24,E24/D24-1),"n.a.") -> -5.4694027e-12 | H24: =IFERROR(IF(OR(ABS(G24)<0.000001,ABS(F24)<=0.0000005),"OK","CHECK"),"CHECK") -> OK | I24: 28994.167 | J24: =IFERROR(IF(I24=0,E24-I24,E24/I24-1),"n.a.") -> -2.220446e-16 | K24: =IFERROR(IF(ABS(J24)<0.000001,"OK","CHECK"),"CHECK") -> OK
B25: FCFF FY2035E | D25: 29599.839 | E25: =DCF!R88 -> 29599.839 | F25: =IFERROR(E25-D25,"n.a.") -> -5.5701094e-08 | G25: =IFERROR(IF(D25=0,E25-D25,E25/D25-1),"n.a.") -> -1.881828e-12 | H25: =IFERROR(IF(OR(ABS(G25)<0.000001,ABS(F25)<=0.0000005),"OK","CHECK"),"CHECK") -> OK | I25: 29599.839 | J25: =IFERROR(IF(I25=0,E25-I25,E25/I25-1),"n.a.") -> 4.4408921e-16 | K25: =IFERROR(IF(ABS(J25)<0.000001,"OK","CHECK"),"CHECK") -> OK
B26: EBITDA FY2026E | D26: 62251.944 | E26: =DCF!I79 -> 62251.944 | F26: =IFERROR(E26-D26,"n.a.") -> -2.1827873e-11 | G26: =IFERROR(IF(D26=0,E26-D26,E26/D26-1),"n.a.") -> -3.3306691e-16 | H26: =IFERROR(IF(OR(ABS(G26)<0.000001,ABS(F26)<=0.0000005),"OK","CHECK"),"CHECK") -> OK | I26: 62251.944 | J26: =IFERROR(IF(I26=0,E26-I26,E26/I26-1),"n.a.") -> 0 | K26: =IFERROR(IF(ABS(J26)<0.000001,"OK","CHECK"),"CHECK") -> OK
B27: EBITDA FY2027E | D27: 64193.437 | E27: =DCF!J79 -> 64193.437 | F27: =IFERROR(E27-D27,"n.a.") -> 5.0000381e-08 | G27: =IFERROR(IF(D27=0,E27-D27,E27/D27-1),"n.a.") -> 7.7893247e-13 | H27: =IFERROR(IF(OR(ABS(G27)<0.000001,ABS(F27)<=0.0000005),"OK","CHECK"),"CHECK") -> OK | I27: 64193.437 | J27: =IFERROR(IF(I27=0,E27-I27,E27/I27-1),"n.a.") -> 0 | K27: =IFERROR(IF(ABS(J27)<0.000001,"OK","CHECK"),"CHECK") -> OK
B28: EBITDA FY2028E | D28: 68870.759 | E28: =DCF!K79 -> 68870.759 | F28: =IFERROR(E28-D28,"n.a.") -> 1.5413389e-07 | G28: =IFERROR(IF(D28=0,E28-D28,E28/D28-1),"n.a.") -> 2.2379876e-12 | H28: =IFERROR(IF(OR(ABS(G28)<0.000001,ABS(F28)<=0.0000005),"OK","CHECK"),"CHECK") -> OK | I28: 68870.759 | J28: =IFERROR(IF(I28=0,E28-I28,E28/I28-1),"n.a.") -> 0 | K28: =IFERROR(IF(ABS(J28)<0.000001,"OK","CHECK"),"CHECK") -> OK
B29: EBITDA FY2029E | D29: 72881.112 | E29: =DCF!L79 -> 72881.112 | F29: =IFERROR(E29-D29,"n.a.") -> -4.5751221e-08 | G29: =IFERROR(IF(D29=0,E29-D29,E29/D29-1),"n.a.") -> -6.277201e-13 | H29: =IFERROR(IF(OR(ABS(G29)<0.000001,ABS(F29)<=0.0000005),"OK","CHECK"),"CHECK") -> OK | I29: 72881.112 | J29: =IFERROR(IF(I29=0,E29-I29,E29/I29-1),"n.a.") -> 0 | K29: =IFERROR(IF(ABS(J29)<0.000001,"OK","CHECK"),"CHECK") -> OK
B30: EBITDA FY2030E | D30: 77122.734 | E30: =DCF!M79 -> 77122.734 | F30: =IFERROR(E30-D30,"n.a.") -> 1.7455022e-07 | G30: =IFERROR(IF(D30=0,E30-D30,E30/D30-1),"n.a.") -> 2.2633007e-12 | H30: =IFERROR(IF(OR(ABS(G30)<0.000001,ABS(F30)<=0.0000005),"OK","CHECK"),"CHECK") -> OK | I30: 77122.734 | J30: =IFERROR(IF(I30=0,E30-I30,E30/I30-1),"n.a.") -> 0 | K30: =IFERROR(IF(ABS(J30)<0.000001,"OK","CHECK"),"CHECK") -> OK
B31: EBITDA FY2031E | D31: 80501.798 | E31: =DCF!N79 -> 80501.798 | F31: =IFERROR(E31-D31,"n.a.") -> 8.1941835e-08 | G31: =IFERROR(IF(D31=0,E31-D31,E31/D31-1),"n.a.") -> 1.0178525e-12 | H31: =IFERROR(IF(OR(ABS(G31)<0.000001,ABS(F31)<=0.0000005),"OK","CHECK"),"CHECK") -> OK | I31: 80501.798 | J31: =IFERROR(IF(I31=0,E31-I31,E31/I31-1),"n.a.") -> 0 | K31: =IFERROR(IF(ABS(J31)<0.000001,"OK","CHECK"),"CHECK") -> OK
B32: EBITDA FY2032E | D32: 83998.641 | E32: =DCF!O79 -> 83998.641 | F32: =IFERROR(E32-D32,"n.a.") -> -8.6904038e-08 | G32: =IFERROR(IF(D32=0,E32-D32,E32/D32-1),"n.a.") -> -1.0346168e-12 | H32: =IFERROR(IF(OR(ABS(G32)<0.000001,ABS(F32)<=0.0000005),"OK","CHECK"),"CHECK") -> OK | I32: 83998.641 | J32: =IFERROR(IF(I32=0,E32-I32,E32/I32-1),"n.a.") -> 0 | K32: =IFERROR(IF(ABS(J32)<0.000001,"OK","CHECK"),"CHECK") -> OK
B33: EBITDA FY2033E | D33: 87614.335 | E33: =DCF!P79 -> 87614.335 | F33: =IFERROR(E33-D33,"n.a.") -> 2.7274655e-07 | G33: =IFERROR(IF(D33=0,E33-D33,E33/D33-1),"n.a.") -> 3.1130654e-12 | H33: =IFERROR(IF(OR(ABS(G33)<0.000001,ABS(F33)<=0.0000005),"OK","CHECK"),"CHECK") -> OK | I33: 87614.335 | J33: =IFERROR(IF(I33=0,E33-I33,E33/I33-1),"n.a.") -> 0 | K33: =IFERROR(IF(ABS(J33)<0.000001,"OK","CHECK"),"CHECK") -> OK
B34: EBITDA FY2034E | D34: 91349.756 | E34: =DCF!Q79 -> 91349.756 | F34: =IFERROR(E34-D34,"n.a.") -> 5.2634277e-08 | G34: =IFERROR(IF(D34=0,E34-D34,E34/D34-1),"n.a.") -> 5.7620575e-13 | H34: =IFERROR(IF(OR(ABS(G34)<0.000001,ABS(F34)<=0.0000005),"OK","CHECK"),"CHECK") -> OK | I34: 91349.756 | J34: =IFERROR(IF(I34=0,E34-I34,E34/I34-1),"n.a.") -> 0 | K34: =IFERROR(IF(ABS(J34)<0.000001,"OK","CHECK"),"CHECK") -> OK
B35: EBITDA FY2035E | D35: 95224.154 | E35: =DCF!R79 -> 95224.154 | F35: =IFERROR(E35-D35,"n.a.") -> -1.4624675e-08 | G35: =IFERROR(IF(D35=0,E35-D35,E35/D35-1),"n.a.") -> -1.5354384e-13 | H35: =IFERROR(IF(OR(ABS(G35)<0.000001,ABS(F35)<=0.0000005),"OK","CHECK"),"CHECK") -> OK | I35: 95224.154 | J35: =IFERROR(IF(I35=0,E35-I35,E35/I35-1),"n.a.") -> 0 | K35: =IFERROR(IF(ABS(J35)<0.000001,"OK","CHECK"),"CHECK") -> OK
B36: Factor de descuento FY2026E (solo réplica) | D36: no está en el resumen | E36: =DCF!I108 -> 0.95206462 | H36: solo réplica | I36: 0.95206462 | J36: =IFERROR(IF(I36=0,E36-I36,E36/I36-1),"n.a.") -> 0 | K36: =IFERROR(IF(ABS(J36)<0.000001,"OK","CHECK"),"CHECK") -> OK
B37: Factor de descuento FY2027E (solo réplica) | D37: no está en el resumen | E37: =DCF!J108 -> 0.86297711 | H37: solo réplica | I37: 0.86297711 | J37: =IFERROR(IF(I37=0,E37-I37,E37/I37-1),"n.a.") -> 0 | K37: =IFERROR(IF(ABS(J37)<0.000001,"OK","CHECK"),"CHECK") -> OK
B38: Factor de descuento FY2028E (solo réplica) | D38: no está en el resumen | E38: =DCF!K108 -> 0.78222579 | H38: solo réplica | I38: 0.78222579 | J38: =IFERROR(IF(I38=0,E38-I38,E38/I38-1),"n.a.") -> 0 | K38: =IFERROR(IF(ABS(J38)<0.000001,"OK","CHECK"),"CHECK") -> OK
B39: Factor de descuento FY2029E (solo réplica) | D39: no está en el resumen | E39: =DCF!L108 -> 0.7090306 | H39: solo réplica | I39: 0.7090306 | J39: =IFERROR(IF(I39=0,E39-I39,E39/I39-1),"n.a.") -> 0 | K39: =IFERROR(IF(ABS(J39)<0.000001,"OK","CHECK"),"CHECK") -> OK
B40: Factor de descuento FY2030E (solo réplica) | D40: no está en el resumen | E40: =DCF!M108 -> 0.64268451 | H40: solo réplica | I40: 0.64268451 | J40: =IFERROR(IF(I40=0,E40-I40,E40/I40-1),"n.a.") -> 0 | K40: =IFERROR(IF(ABS(J40)<0.000001,"OK","CHECK"),"CHECK") -> OK
B41: Factor de descuento FY2031E (solo réplica) | D41: no está en el resumen | E41: =DCF!N108 -> 0.58254662 | H41: solo réplica | I41: 0.58254662 | J41: =IFERROR(IF(I41=0,E41-I41,E41/I41-1),"n.a.") -> 0 | K41: =IFERROR(IF(ABS(J41)<0.000001,"OK","CHECK"),"CHECK") -> OK
B42: Factor de descuento FY2032E (solo réplica) | D42: no está en el resumen | E42: =DCF!O108 -> 0.528036 | H42: solo réplica | I42: 0.528036 | J42: =IFERROR(IF(I42=0,E42-I42,E42/I42-1),"n.a.") -> 0 | K42: =IFERROR(IF(ABS(J42)<0.000001,"OK","CHECK"),"CHECK") -> OK
B43: Factor de descuento FY2033E (solo réplica) | D43: no está en el resumen | E43: =DCF!P108 -> 0.47862611 | H43: solo réplica | I43: 0.47862611 | J43: =IFERROR(IF(I43=0,E43-I43,E43/I43-1),"n.a.") -> -1.110223e-16 | K43: =IFERROR(IF(ABS(J43)<0.000001,"OK","CHECK"),"CHECK") -> OK
B44: Factor de descuento FY2034E (solo réplica) | D44: no está en el resumen | E44: =DCF!Q108 -> 0.43383965 | H44: solo réplica | I44: 0.43383965 | J44: =IFERROR(IF(I44=0,E44-I44,E44/I44-1),"n.a.") -> -1.110223e-16 | K44: =IFERROR(IF(ABS(J44)<0.000001,"OK","CHECK"),"CHECK") -> OK
B45: Factor de descuento FY2035E (solo réplica) | D45: no está en el resumen | E45: =DCF!R108 -> 0.39324399 | H45: solo réplica | I45: 0.39324399 | J45: =IFERROR(IF(I45=0,E45-I45,E45/I45-1),"n.a.") -> 0 | K45: =IFERROR(IF(ABS(J45)<0.000001,"OK","CHECK"),"CHECK") -> OK
B46: Suma del VP del FCFF (solo réplica) | D46: no está en el resumen | E46: =DCF!$D$112 -> 165442.47 | H46: solo réplica | I46: 165442.47 | J46: =IFERROR(IF(I46=0,E46-I46,E46/I46-1),"n.a.") -> -2.220446e-16 | K46: =IFERROR(IF(ABS(J46)<0.000001,"OK","CHECK"),"CHECK") -> OK
B47: Valor terminal - Gordon (solo réplica) | D47: no está en el resumen | E47: =DCF!$D$113 -> 508092.07 | H47: solo réplica | I47: 508092.07 | J47: =IFERROR(IF(I47=0,E47-I47,E47/I47-1),"n.a.") -> 4.4408921e-16 | K47: =IFERROR(IF(ABS(J47)<0.000001,"OK","CHECK"),"CHECK") -> OK
B48: VP del valor terminal - Gordon (solo réplica) | D48: no está en el resumen | E48: =DCF!$D$114 -> 199804.15 | H48: solo réplica | I48: 199804.15 | J48: =IFERROR(IF(I48=0,E48-I48,E48/I48-1),"n.a.") -> 2.220446e-16 | K48: =IFERROR(IF(ABS(J48)<0.000001,"OK","CHECK"),"CHECK") -> OK
B49: Valor terminal - salida (solo réplica) | D49: no está en el resumen | E49: =DCF!$D$116 -> 571344.93 | H49: solo réplica | I49: 571344.93 | J49: =IFERROR(IF(I49=0,E49-I49,E49/I49-1),"n.a.") -> 0 | K49: =IFERROR(IF(ABS(J49)<0.000001,"OK","CHECK"),"CHECK") -> OK
B50: VP del valor terminal - salida (solo réplica) | D50: no está en el resumen | E50: =DCF!$D$117 -> 213907.93 | H50: solo réplica | I50: 213907.93 | J50: =IFERROR(IF(I50=0,E50-I50,E50/I50-1),"n.a.") -> -4.4408921e-16 | K50: =IFERROR(IF(ABS(J50)<0.000001,"OK","CHECK"),"CHECK") -> OK
B51: Deuda neta con arrendamientos (solo réplica) | D51: no está en el resumen | E51: =DCF!$D$127 -> 179918 | H51: solo réplica | I51: 179918 | J51: =IFERROR(IF(I51=0,E51-I51,E51/I51-1),"n.a.") -> 0 | K51: =IFERROR(IF(ABS(J51)<0.000001,"OK","CHECK"),"CHECK") -> OK
B52: Acciones (solo réplica) | D52: no está en el resumen | E52: =DCF!$D$145 -> 4310.531 | H52: solo réplica | I52: 4310.531 | J52: =IFERROR(IF(I52=0,E52-I52,E52/I52-1),"n.a.") -> 0 | K52: =IFERROR(IF(ABS(J52)<0.000001,"OK","CHECK"),"CHECK") -> OK
B53: Factor de traslado (solo réplica) | D53: no está en el resumen | E53: =DCF!$D$148 -> 1.1011741 | H53: solo réplica | I53: 1.1011741 | J53: =IFERROR(IF(I53=0,E53-I53,E53/I53-1),"n.a.") -> -4.4408921e-16 | K53: =IFERROR(IF(ABS(J53)<0.000001,"OK","CHECK"),"CHECK") -> OK
B54: FCFF FY2035E PUBLICADO (solo réplica) | D54: no está en el resumen | E54: =DCF!R179 -> 27536.417 | H54: solo réplica | I54: 27536.417 | J54: =IFERROR(IF(I54=0,E54-I54,E54/I54-1),"n.a.") -> 4.4408921e-16 | K54: =IFERROR(IF(ABS(J54)<0.000001,"OK","CHECK"),"CHECK") -> OK
B55: Pasivo por arrendamiento FY2035E PUBLICADO (solo réplica) | D55: no está en el resumen | E55: =DCF!R174 -> 50714.374 | H55: solo réplica | I55: 50714.374 | J55: =IFERROR(IF(I55=0,E55-I55,E55/I55-1),"n.a.") -> 0 | K55: =IFERROR(IF(ABS(J55)<0.000001,"OK","CHECK"),"CHECK") -> OK
B56: Suma del VP del FCFF PUBLICADA (solo réplica) | D56: no está en el resumen | E56: =DCF!$D$183 -> 156185.94 | H56: solo réplica | I56: 156185.94 | J56: =IFERROR(IF(I56=0,E56-I56,E56/I56-1),"n.a.") -> 0 | K56: =IFERROR(IF(ABS(J56)<0.000001,"OK","CHECK"),"CHECK") -> OK
B57: Valor terminal PUBLICADO - Gordon (solo réplica) | D57: no está en el resumen | E57: =DCF!$D$185 -> 472602.81 | H57: solo réplica | I57: 472602.81 | J57: =IFERROR(IF(I57=0,E57-I57,E57/I57-1),"n.a.") -> 4.4408921e-16 | K57: =IFERROR(IF(ABS(J57)<0.000001,"OK","CHECK"),"CHECK") -> OK
B58: EV PUBLICADO - Gordon (solo réplica) | D58: no está en el resumen | E58: =DCF!$D$187 -> 342034.15 | H58: solo réplica | I58: 342034.15 | J58: =IFERROR(IF(I58=0,E58-I58,E58/I58-1),"n.a.") -> 0 | K58: =IFERROR(IF(ABS(J58)<0.000001,"OK","CHECK"),"CHECK") -> OK
B59: EV PUBLICADO - salida (solo réplica) | D59: no está en el resumen | E59: =DCF!$D$188 -> 370093.87 | H59: solo réplica | I59: 370093.87 | J59: =IFERROR(IF(I59=0,E59-I59,E59/I59-1),"n.a.") -> -1.110223e-16 | K59: =IFERROR(IF(ABS(J59)<0.000001,"OK","CHECK"),"CHECK") -> OK
B60: Partidas similares a deuda, prima del NCI dinámica a ke (solo réplica) | D60: no está en el resumen | E60: =DCF!$D$142 -> 37053.896 | H60: solo réplica | I60: 37053.896 | J60: =IFERROR(IF(I60=0,E60-I60,E60/I60-1),"n.a.") -> -2.220446e-16 | K60: =IFERROR(IF(ABS(J60)<0.000001,"OK","CHECK"),"CHECK") -> OK
B61: Valor por acción hoy PUBLICADO - Gordon (solo réplica) | D61: no está en el resumen | E61: =DCF!$D$192 -> 33.551593 | H61: solo réplica | I61: 33.551593 | J61: =IFERROR(IF(I61=0,E61-I61,E61/I61-1),"n.a.") -> 4.4408921e-16 | K61: =IFERROR(IF(ABS(J61)<0.000001,"OK","CHECK"),"CHECK") -> OK
B62: Valor por acción hoy PUBLICADO - salida (solo réplica) | D62: no está en el resumen | E62: =DCF!$D$194 -> 45.715085 | H62: solo réplica | I62: 45.715085 | J62: =IFERROR(IF(I62=0,E62-I62,E62/I62-1),"n.a.") -> -1.110223e-16 | K62: =IFERROR(IF(ABS(J62)<0.000001,"OK","CHECK"),"CHECK") -> OK
B63: RONIC PUBLICADO implícito en el valor terminal (solo réplica) | D63: no está en el resumen | E63: =DCF!$D$200 -> 0.14618391 | H63: solo réplica | I63: 0.14618391 | J63: =IFERROR(IF(I63=0,E63-I63,E63/I63-1),"n.a.") -> 1.5543122e-15 | K63: =IFERROR(IF(ABS(J63)<0.000001,"OK","CHECK"),"CHECK") -> OK
B64: Crecimiento PUBLICADO implícito en el múltiplo de salida (solo réplica) | D64: no está en el resumen | E64: =DCF!$D$202 -> 0.050788447 | H64: solo réplica | I64: 0.050788447 | J64: =IFERROR(IF(I64=0,E64-I64,E64/I64-1),"n.a.") -> -4.4408921e-16 | K64: =IFERROR(IF(ABS(J64)<0.000001,"OK","CHECK"),"CHECK") -> OK
B65: Gordon PUBLICADO con RONIC = WACC (solo réplica) | D65: no está en el resumen | E65: =DCF!$E$219 -> 25.454699 | H65: solo réplica | I65: 25.454699 | J65: =IFERROR(IF(I65=0,E65-I65,E65/I65-1),"n.a.") -> 0 | K65: =IFERROR(IF(ABS(J65)<0.000001,"OK","CHECK"),"CHECK") -> OK
B66: Crecimiento perpetuo (g) PUBLICADO implícito en el precio (solo réplica) | D66: no está en el resumen | E66: =Reverse_DCF!$D$9 -> 0.064107468 | H66: solo réplica | I66: 0.064107468 | J66: =IFERROR(IF(I66=0,E66-I66,E66/I66-1),"n.a.") -> -2.220446e-16 | K66: =IFERROR(IF(ABS(J66)<0.000001,"OK","CHECK"),"CHECK") -> OK
B68: Filas verificadas contra el resumen del motor | D68: 30
B69: Filas OK vs motor (debe igualar el conteo anterior) | D69: =COUNTIF(H6:H35,"OK") -> 30
B70: Filas verificadas contra la réplica en Python | D70: 61
B71: Filas OK vs réplica (debe igualar el conteo anterior) | D71: =COUNTIF(K6:K66,"OK") -> 61

Sheet Inputs_Sources
B2: Insumos y fuentes
B3: [sourced] de un reporte presentado o fuente pública; [guidance] declaración de la administración; [assumption] juicio del equipo o del asistente (propuesta hasta que el equipo confirme); [calc] calculado; [unverified] aún sin vincular a una fuente.
B5: Concepto | C5: Valor | D5: Unidad | E5: Etiqueta | F5: Fuente | G5: Fecha
B6: Precio de la acción, cierre oficial de la BMV (PPP) | C6: 58.6 | D6: MXN | E6: sourced | F6: BMV 'Estadisticas de operacion' BIMBO serie A (https://www.bmv.com.mx/es/emisoras/estadisticas/BIMBO-5163): PPP 58.60, último 58.62, anterior 57.97; investing.com / Yahoo coinciden (wacc_inputs A1) | G6: 2026-10-16
B7: Máximo / mínimo de 52 semanas | C7: 68.67 / 53.03 | D7: MXN | E7: sourced | F7: CIQ corporate_issuance.csv (wacc_inputs A4-A5) | G7: 2026-10-06
B8: Acciones en circulación | C8: 4294.9437 | D8: m | E8: sourced | F8: Aviso de la BMV (wacc_inputs A8) | G8: 2026-07-29
B9: Capitalización de mercado | C9: 251683.7 | D9: MXN m | E9: calc | F9: precio x acciones (wacc_inputs A9) | G9: 2026-10-16
B10: M-Bono 10y | C10: 0.0926 | D10: % | E10: sourced | F10: Tasas de S&P Capital IQ | G10: 2026-10-16
B11: UST 10y | C11: 0.0509 | D11: % | E11: sourced | F11: Tasas de S&P Capital IQ | G11: 2026-10-16
B12: CDS 5y de México | C12: 0.00953 | D12: % | E12: sourced | F12: S&P Capital IQ CDS | G12: 2026-10-16
B13: ERP implícita de Damodaran | C13: 0.042 | D13: % | E13: sourced | F13: Página principal de Damodaran | G13: 2026-10-01
B14: Diferencial de impago / CRP de México de Damodaran | C14: 1.75% / 2.72% | D14: % | E14: sourced | F14: Damodaran ctrypremJuly26.xlsx (actualización de julio de 2026; México Baa3) | G14: 2026-07-01
B15: Beta desapalancada de Damodaran, Food Processing, Global / US | C15: 0.53 / 0.46 | D15: x | E15: sourced | F15: Betas de Damodaran; betaGlobal.xls 'Date updated' 5-Jan-2026 (https://pages.stern.nyu.edu/~adamodar/pc/datasets/betaGlobal.xls, consultado el 2026-10-17); encabezado de BetasGlobal.html 'January 2026', pie de página 'January 2025' desactualizado | G15: 2026-01-05
B16: Crecimiento del PIB real de México 2029-31 / inflación del IPC 2029-31 | C16: 2.1% / 3.0% | D16: % | E16: sourced | F16: FMI WEO October 2026, DataMapper NGDP_RPCH y PCPIPCH (https://www.imf.org/external/datamapper/api/v1/NGDP_RPCH/MEX, última modificación 2026-10-08) | G16: 2026-10-08
B17: Crecimiento del PIB real de México, promedio de los próximos 10 años (2027-36), promedio / mediana | C17: 1.88% / 1.80% | D17: % | E17: sourced | F17: Banxico, Encuesta sobre las Expectativas de los Especialistas en Economia del Sector Privado: septiembre 2026 (publicada el 1-Oct-2026), Cuadro 6 p.8 | G17: 2026-10-01
B18: Provisiones incl. posiciones fiscales inciertas (UTP 8,692; impuestos 1,318; laborales 512; civiles 506; otras 1) | C18: 11029.4 | D18: MXN m | E18: sourced | F18: BMV 2Q26 XBRL p.59 (pasivos contingentes) | G18: 2026-06-30
B19: Línea de otras provisiones a largo plazo (provisiones + MEPP + compensaciones diferidas + otras) | C19: 13011.5 | D19: MXN m | E19: sourced | F19: BMV 2Q26 XBRL [210000] p.13 (12,999.0 en Dec-25) | G19: 2026-06-30
B20: Pasivos por derivados 978 + 2,658 menos activos 785 + 988 (neto 1,864) | C20: 1864.2 | D20: MXN m | E20: calc | F20: BMV 2Q26 XBRL p.64-65 (instrumentos financieros por categoría) | G20: 2026-06-30
B21: Pagos de arrendamientos / intereses devengados 1H26 | C21: 3,948 / 1,042 | D21: MXN m | E21: sourced | F21: BMV 2Q26 XBRL p.100 (movimiento de arrendamientos) | G21: 2026-06-30
B22: Beta publicada de Bimbo | C22: 0.32 | D22: x | E22: unverified | F22: investing.com (ventana no indicada) | G22: 2026-10-16
B23: Rendimiento de BIMBO 23L | C23: 0.0926 | D23: % | E23: sourced | F23: Exportación de LSEG (precios ~10-Oct) | G23: 2026-10-10
B24: Deuda / arrendamientos / efectivo, 31-Dec-2025 | C24: 153,663 / 34,790 / 8,535 | D24: MXN m | E24: sourced | F24: EEFF25 p.12 vía data/financials.csv | G24: 2025-12-31
B25: Deuda / arrendamientos / efectivo, 30-Jun-2026 | C25: 153,660 / 33,361 / 16,563 | D25: MXN m | E25: sourced | F25: BMV Jun-26; CIQ | G25: 2026-06-30
B26: Línea de beneficios a empleados: retiro 2,130 + bienestar de EUA 3,272 + ajuste bruto de activos del plan 362 + bonos a largo plazo 743 | C26: 6507 | D26: MXN m | E26: sourced | F26: EEFF25 p.75 nota 18 | G26: 2025-12-31
B27: Otros pasivos a largo plazo: provisiones 10,684 (UTP 8,537; impuestos 1,196; laborales 439; civiles 511; otras 1) + MEPP 985 + compensaciones diferidas 1,060 + otros 270 | C27: 12999 | D27: MXN m | E27: sourced | F27: EEFF25 p.79-80 nota 19 | G27: 2025-12-31
B28: Pasivos netos por derivados (3,902 - 717) | C28: 3185 | D28: MXN m | E28: sourced | F28: EEFF25 p.12 (data/adjustments.md) | G28: 2025-12-31
B29: Pasivo por reclamaciones de autoseguro de EUA (en otras cuentas por pagar y pasivos acumulados: operativo) | C29: 4216 | D29: MXN m | E29: sourced | F29: EEFF25 p.36 | G29: 2025-12-31
B30: Inversiones en asociadas | C30: 7018 | D30: MXN m | E30: sourced | F30: EEFF25 p.12 | G30: 2025-12-31
B31: Utilidad de NCI 1H26 (anualizada 1,814) | C31: 907 | D31: MXN m | E31: sourced | F31: CIQ trimestral: 1Q26 436 + 2Q26 471 | G31: 2026-06-30
B32: Utilidad de NCI FY23 / FY24 / FY25; extracción mediante entidades estructuradas; dividendos de NCI | C32: 1,445 / 1,499 / 1,813; 1,851 / 3,120 / 2,240; 91 / 109 / 135 | D32: MXN m | E32: sourced | F32: EEFF25 p.13, p.15 | G32: 2025-12-31
B33: Dividendo de 2026 pagado (13-May) | C33: 1.075 | D33: MXN/acción | E33: sourced | F33: wacc_inputs C1-C4 | G33: 2026-05-13
B34: Dividendo por acción de consenso FY2027E (próximos 12 meses) | C34: 1.05 | D34: MXN/acción | E34: sourced | F34: Consenso de CIQ (data/capitaliq/consensus.csv) | G34: 2026-09-20
B36: Supuestos: model/drivers.yaml (etiqueta, justificación y pilar por supuesto). Histórico: data/financials.csv (documento y página por cifra) y data/adjustments.md.

Sheet Checks
B2: Controles de integridad
B4: WACC - g de al menos 2 puntos | C4: =IF(DCF!$D$165>=0.02,"OK","WARN") -> OK
B5: g no supera el crecimiento nominal del PIB de largo plazo | C5: =IF(DCF!$D$166<=0,"OK","FAIL") -> OK
B6: Los pesos suman 100% | C6: =IF(ABS(DCF!$D$32+DCF!$D$33-1)<0.000001,"OK","FAIL") -> OK
B7: Conciliación con el motor: todas las filas OK (conteo de OK = filas verificadas) | C7: =IF(Engine_Recon!$D$69=Engine_Recon!$D$68,"OK","CHECK") -> OK
B8: Conciliación con la réplica en Python: todas las filas OK | C8: =IF(Engine_Recon!$D$71=Engine_Recon!$D$70,"OK","CHECK") -> OK
B9: TV de Gordon como % del EV menor a 85% (publicado) | C9: =IF(DCF!$D$189<0.85,"OK","WARN") -> OK
B10: Múltiplo de salida implícito en el valor de Gordon publicado dentro de un factor de dos del múltiplo de salida (0.5x a 2x) | C10: =IF(AND(DCF!$D$201>=0.5*DCF!$D$40,DCF!$D$201<=2*DCF!$D$40),"OK","WARN") -> OK
B11: El crecimiento de arrendamientos no puede agregar valor: Gordon publicado <= Gordon de la base del motor | C11: =IF(DCF!$D$192<=DCF!$D$152+0.000001,"OK","CHECK") -> OK
B12: Prueba (a) de arrendamientos: crecimiento del pasivo por arrendamiento en FY2035 dentro de 10% de g x pasivo por arrendamiento FY2035 | C12: =IF(ABS(DCF!$D$203-1)<=0.1,"OK","WARN") -> OK
B13: La tabla de casos terminales de menor retorno reproduce el valor de Gordon publicado con el RONIC implícito | C13: =IF(ABS(DCF!$E$222-DCF!$D$192)<0.000001,"OK","FAIL") -> OK
B14: RONIC publicado mayor que el WACC (el crecimiento perpetuo crea valor) | C14: =IF(DCF!$D$200>DCF!$D$34,"OK","WARN") -> OK
B15: Verificación cruzada a la fecha de valuación dentro de 5% del traslado desde el cierre fiscal (Gordon y salida, publicado) | C15: =IF(AND(ABS(Dated_Check!$D$58)<0.05,ABS(Dated_Check!$D$61)<0.05),"OK","WARN") -> OK
B16: Escenarios: la fila base es igual a los resultados clave publicados (Gordon y salida) | C16: =IF(AND(ABS(Scenarios!$F$7-DCF!$D$192)<0.000001,ABS(Scenarios!$G$7-DCF!$D$194)<0.000001),"OK","FAIL") -> OK
B17: El capital de trabajo operativo FY2021 cuadra con data/adjustments.md (-14,860) | C17: =IF(ABS(DCF!D101-(-14860))<0.5,"OK","FAIL") -> OK
B18: El capital de trabajo operativo FY2022 cuadra con data/adjustments.md (-15,353) | C18: =IF(ABS(DCF!E101-(-15353))<0.5,"OK","FAIL") -> OK
B19: El capital de trabajo operativo FY2023 cuadra con data/adjustments.md (-8,599) | C19: =IF(ABS(DCF!F101-(-8599))<0.5,"OK","FAIL") -> OK
B20: El capital de trabajo operativo FY2024 cuadra con data/adjustments.md (-6,279) | C20: =IF(ABS(DCF!G101-(-6279))<0.5,"OK","FAIL") -> OK
B21: El capital de trabajo operativo FY2025 cuadra con data/adjustments.md (-6,232) | C21: =IF(ABS(DCF!H101-(-6232))<0.5,"OK","FAIL") -> OK
B22: Los componentes similares a deuda (prima del NCI dinámica a ke) suman valuation.yaml debt_like_items | C22: =IF(ABS(DCF!$D$142-DCF!$D$143)<0.5,"OK","FAIL") -> OK
B23: Los segmentos suman las ventas FY2021 | C23: =IF(ABS(SUM(DCF!D65:D69)-DCF!D70)<0.5,"OK","FAIL") -> OK
B24: Los segmentos suman las ventas FY2022 | C24: =IF(ABS(SUM(DCF!E65:E69)-DCF!E70)<0.5,"OK","FAIL") -> OK
B25: Los segmentos suman las ventas FY2023 | C25: =IF(ABS(SUM(DCF!F65:F69)-DCF!F70)<0.5,"OK","FAIL") -> OK
B26: Los segmentos suman las ventas FY2024 | C26: =IF(ABS(SUM(DCF!G65:G69)-DCF!G70)<0.5,"OK","FAIL") -> OK
B27: Los segmentos suman las ventas FY2025 | C27: =IF(ABS(SUM(DCF!H65:H69)-DCF!H70)<0.5,"OK","FAIL") -> OK
B29: Los errores de fórmula se revisan tras el recálculo con valuation/build/scan_errors.py.
