Workbook

Sheet TearSheet
A1: TearSheet: Grupo Bimbo, S.A.B. de C.V. (BMV:BIMBO A), MXN millions unless stated
A2: Actuals: CIQ quarterly CSVs (sum of quarters; FY2021 restated) with company annual values where the CSV lacks Q4 2024 (flagged). FY2026E-FY2028E: CIQ consensus mean (20-Sep-2026). Adjusted EBITDA is the company IFRS 16 figure; CIQ EBITDA is standardised and sits after lease depreciation.
A3: Tags: sourced = CIQ CSV or company filing; calc = computed here; consensus = CIQ mean estimate; memo rows are not used in valuation except where stated.
A5: Line item | B5: Unit | C5: FY2021A | D5: FY2022A | E5: FY2023A | F5: FY2024A | G5: FY2025A | H5: FY2026E | I5: FY2027E | J5: FY2028E | K5: Tag | L5: Source / note
A6: Income statement
A7: Total revenue | B7: MXN m | C7: 338792 | D7: 398706 | E7: 399879 | F7: 408335 | G7: 426963 | H7: 426274.7 | I7: 445288 | J7: 468430.9 | K7: sourced / consensus | L7: CSV income_statement 'Total Revenue' (FY2021 restated = 338,792); FY2024 company annual (4Q24 missing in CSV; wiki/Financials/bimbo-income-statement-fy21-fy25.md s.1); FY26E-28E consensus.csv Revenue mean
A8: Revenue growth YoY | B8: % | D8: =IFERROR(D7/C7-1,"n/a") -> 0.17684597 | E8: =IFERROR(E7/D7-1,"n/a") -> 0.0029420174 | F8: =IFERROR(F7/E7-1,"n/a") -> 0.021146397 | G8: =IFERROR(G7/F7-1,"n/a") -> 0.045619406 | H8: =IFERROR(H7/G7-1,"n/a") -> -0.0016120835 | I8: =IFERROR(I7/H7-1,"n/a") -> 0.044603398 | J8: =IFERROR(J7/I7-1,"n/a") -> 0.05197288 | K8: calc | L8: calc
A9: Gross profit | B9: MXN m | C9: 181789.4 | D9: 205974.4 | E9: 206159.5 | F9: 214928 | G9: 224241.7 | K9: sourced | L9: CSV 'Gross Profit' (CIQ basis; company FY24 214,928; company FY25 223,487 differs by 0.3%)
A10: Gross margin | B10: % | C10: =IFERROR(C9/C7,"n/a") -> 0.53658115 | D10: =IFERROR(D9/D7,"n/a") -> 0.51660722 | E10: =IFERROR(E9/E7,"n/a") -> 0.51555471 | F10: =IFERROR(F9/F7,"n/a") -> 0.52635214 | G10: =IFERROR(G9/G7,"n/a") -> 0.52520172 | K10: calc | L10: calc
A11: Gross margin, consensus mean | B11: % | H11: 52.3 | I11: 52 | J11: 52.05 | K11: consensus | L11: consensus.csv Gross Margin (%) mean
A12: SG&A (selling, general and administrative) | B12: MXN m | C12: 147963 | D12: 167254 | E12: 165748 | F12: 175164 | G12: 184186 | H12: 177262 | I12: 189938 | J12: 197030 | K12: sourced / consensus | L12: CSV 'Selling General & Admin Exp.' (CIQ basis); FY2024 company general expenses 175,164; FY26E-28E consensus mean
A13: SG&A / sales | B13: % | C13: =IFERROR(C12/C7,"n/a") -> 0.43673699 | D13: =IFERROR(D12/D7,"n/a") -> 0.41949206 | E13: =IFERROR(E12/E7,"n/a") -> 0.41449538 | F13: =IFERROR(F12/F7,"n/a") -> 0.42897131 | G13: =IFERROR(G12/G7,"n/a") -> 0.43138633 | H13: =IFERROR(H12/H7,"n/a") -> 0.41583983 | I13: =IFERROR(I12/I7,"n/a") -> 0.42655091 | J13: =IFERROR(J12/J7,"n/a") -> 0.420617 | K13: calc | L13: calc
A14: Total operating expenses, CIQ basis | B14: MXN m | C14: 148200.4 | D14: 169510.4 | E14: 168704.7 | F14: 181779 | G14: 187970.1 | K14: sourced | L14: CSV 'Other Operating Exp., Total'; FY2024 company total operating expenses (wiki s.1)
A15: EBIT, CIQ standardised | B15: MXN m | C15: 33588.9 | D15: 36464.1 | E15: 37454.8 | G15: 36271.6 | K15: sourced | L15: CSV 'Operating Income' (sum of quarters); not like-for-like with company operating income (see next row); FY2024 CSV Q4 missing
A16: Operating income, company basis (FY26E-28E: consensus EBIT) | B16: MXN m | C16: 32580 | D16: 53696 | E16: 35455 | F16: 33149 | G16: 34146 | H16: 37446 | I16: 38779 | J16: 41926 | K16: sourced / consensus | L16: Company FY21 restated 32,580 and FY22 53,696 incl. MEPP/Ricolino one-offs (wiki s.1); consensus.csv EBIT is company basis (FY25A 34,146)
A17: Operating margin, company basis | B17: % | C17: =IFERROR(C16/C7,"n/a") -> 0.096165199 | D17: =IFERROR(D16/D7,"n/a") -> 0.13467568 | E17: =IFERROR(E16/E7,"n/a") -> 0.088664321 | F17: =IFERROR(F16/F7,"n/a") -> 0.081180893 | G17: =IFERROR(G16/G7,"n/a") -> 0.079974143 | H17: =IFERROR(H16/H7,"n/a") -> 0.087844763 | I17: =IFERROR(I16/I7,"n/a") -> 0.087087458 | J17: =IFERROR(J16/J7,"n/a") -> 0.089503062 | K17: calc | L17: calc
A18: EBITDA, CIQ standardised (after lease depreciation) | B18: MXN m | C18: 45540.9 | D18: 50087.1 | E18: 51987.8 | G18: 54815.1 | K18: sourced | L18: CSV 'EBITDA' (sum of quarters); about 6 bn below company Adj. EBITDA (ROU depreciation); not the valuation basis
A19: Adjusted EBITDA, company, IFRS 16 (valuation basis) | B19: MXN m | C19: 47372 | D19: 53446 | E19: 54942 | F19: 55473 | G19: 59456 | H19: 62117 | I19: 64891 | J19: 68999 | K19: sourced / consensus | L19: Company Adj. EBITDA FY21 restated, FY22-25 (wiki s.1; FY24 55,473 vs 55,474 in releases); FY26E-28E consensus EBITDA mean (same definition, FY25A 59,456)
A20: Adjusted EBITDA margin | B20: % | C20: =IFERROR(C19/C7,"n/a") -> 0.13982621 | D20: =IFERROR(D19/D7,"n/a") -> 0.13404865 | E20: =IFERROR(E19/E7,"n/a") -> 0.13739656 | F20: =IFERROR(F19/F7,"n/a") -> 0.13585169 | G20: =IFERROR(G19/G7,"n/a") -> 0.13925328 | H20: =IFERROR(H19/H7,"n/a") -> 0.14572059 | I20: =IFERROR(I19/I7,"n/a") -> 0.14572816 | J20: =IFERROR(J19/J7,"n/a") -> 0.14729814 | K20: calc | L20: calc
A21: Pre-tax profit (continuing) | B21: MXN m | C21: 24854 | D21: 45878 | E21: 25324 | F21: 21034 | G21: 20143 | H21: 23597 | I21: 25677 | J21: 30308 | K21: sourced / consensus | L21: CSV 'EBT Incl. Unusual Items' (FY2024 company 21,034); FY26E-28E consensus EBT normalised mean
A22: Net income to majority | B22: MXN m | C22: 15916 | D22: 46910 | E22: 15477 | F22: 12544 | G22: 11133 | H22: 13688 | I22: 15011 | J22: 17371 | K22: sourced / consensus | L22: CSV 'NI to Common Incl Extra Items' (FY2024 company 12,544); FY26E-28E consensus net income normalised mean
A23: Net margin | B23: % | C23: =IFERROR(C22/C7,"n/a") -> 0.046978677 | D23: =IFERROR(D22/D7,"n/a") -> 0.11765562 | E23: =IFERROR(E22/E7,"n/a") -> 0.038704208 | F23: =IFERROR(F22/F7,"n/a") -> 0.030719875 | G23: =IFERROR(G22/G7,"n/a") -> 0.026074859 | H23: =IFERROR(H22/H7,"n/a") -> 0.032110749 | I23: =IFERROR(I22/I7,"n/a") -> 0.033710767 | J23: =IFERROR(J22/J7,"n/a") -> 0.037083378 | K23: calc | L23: calc
A24: EPS, basic, total (E = consensus normalised EPS mean) | B24: MXN/share | C24: 3.55 | D24: 10.54 | E24: 3.5 | F24: 2.88 | G24: 2.58 | H24: 3.07 | I24: 3.35 | J24: 3.8 | K24: sourced / consensus | L24: Company basic EPS total (wiki s.1); consensus.csv 'EPS Normalized' mean FY26E-28E (3.07 / 3.35 / 3.80)
A25: DPS declared for the fiscal year (E = consensus mean) | B25: MXN/share | C25: 1 | D25: 0.65 | E25: 0.78 | F25: 0.94 | G25: 1 | H25: 1.01 | I25: 1.05 | J25: 1.24 | K25: sourced / consensus | L25: Company declared DPS (wiki s.1). CIQ actual DPS differs for FY21-FY23 (memo row below)
A26: DPS, CIQ actual (memo; timing differs) | B26: MXN/share | C26: 0 | D26: 1.3 | E26: 0.94 | F26: 0.94 | G26: 1 | K26: sourced | L26: consensus.csv 'Dividend per share' Actual (A); see Checks
A27: Balance sheet (fiscal year-end; CSV Q4)
A28: Cash and short-term investments | B28: MXN m | C28: 8748 | D28: 12313 | E28: 6353 | F28: 8057 | G28: 8535 | K28: sourced | L28: CSV balance_sheet 'Cash & Short-term Investments' Q4
A29: Total current assets | B29: MXN m | C29: 53411 | D29: 63470 | E29: 58914 | F29: 67180 | G29: 64671 | K29: sourced | L29: CSV 'Total Current Assets' Q4
A30: Total assets | B30: MXN m | C30: 337640 | D30: 347764 | E30: 348102 | F30: 416804 | G30: 409805 | K30: sourced | L30: CSV 'Total Assets' Q4
A31: Non-current assets (total assets less current assets) | B31: MXN m | C31: =IFERROR(C30-C29,"n/a") -> 284229 | D31: =IFERROR(D30-D29,"n/a") -> 284294 | E31: =IFERROR(E30-E29,"n/a") -> 289188 | F31: =IFERROR(F30-F29,"n/a") -> 349624 | G31: =IFERROR(G30-G29,"n/a") -> 345134 | K31: calc | L31: calc
A32: Total current liabilities | B32: MXN m | C32: 80760 | D32: 89734 | E32: 87192 | F32: 85155 | G32: 90573 | K32: sourced | L32: CSV 'Total Current Liabilities' Q4
A33: Total liabilities (excl. NCI) | B33: MXN m | C33: 236034 | D33: 220162 | E33: 236474 | F33: 289106 | G33: 289550 | K33: sourced | L33: CSV 'Total Liabilities' Q4
A34: Non-current liabilities (total liabilities less current) | B34: MXN m | C34: =IFERROR(C33-C32,"n/a") -> 155274 | D34: =IFERROR(D33-D32,"n/a") -> 130428 | E34: =IFERROR(E33-E32,"n/a") -> 149282 | F34: =IFERROR(F33-F32,"n/a") -> 203951 | G34: =IFERROR(G33-G32,"n/a") -> 198977 | K34: calc | L34: calc
A35: Total equity incl. NCI | B35: MXN m | C35: 101606 | D35: 127602 | E35: 111628 | F35: 127698 | G35: 120255 | K35: sourced | L35: CSV 'Total Equity' Q4
A36: Total debt incl. IFRS 16 leases (CIQ) | B36: MXN m | C36: 124071 | D36: 113829 | E36: 139539 | F36: 187395 | G36: 190767 | K36: sourced | L36: CSV 'Total Debt' Q4 (= financial debt + lease liabilities)
A37: Net debt incl. IFRS 16 leases (CIQ) | B37: MXN m | C37: 115323 | D37: 101516 | E37: 133186 | F37: 179338 | G37: 182232 | K37: sourced | L37: CSV 'Net Debt' Q4
A38: Net debt ex-IFRS 16 (company; memo) | B38: MXN m | C38: 84107 | D38: 71741 | E38: 103582 | F38: 142848 | G38: 145128 | K38: sourced | L38: Company, RA25 p.299 and wiki; FY21 84,107 (wiki cross-source); FY22 71,741 from consensus.csv 'Net Debt' actual (basis unconfirmed)
A39: Net debt incl. leases / Adjusted EBITDA | B39: x | C39: =IFERROR(C37/C19,"n/a") -> 2.4344127 | D39: =IFERROR(D37/D19,"n/a") -> 1.8994125 | E39: =IFERROR(E37/E19,"n/a") -> 2.42412 | F39: =IFERROR(F37/F19,"n/a") -> 3.2328881 | G39: =IFERROR(G37/G19,"n/a") -> 3.0649892 | K39: calc | L39: calc
A40: Cash flow
A41: Cash from operations | B41: MXN m | C41: 45776 | D41: 38851 | E41: 31411 | F41: 39907 | G41: 47753 | K41: sourced | L41: CSV 'Cash from Ops.' FY22, FY23, FY25; FY21 and FY24 from company (wiki cash-flow article; CSV quarter missing). Consensus CFO actuals differ for FY23/FY24 (see Checks)
A42: Capital expenditure | B42: MXN m | C42: -20671 | D42: -28669 | E42: -34754 | F42: -29402 | G42: -22530 | H42: -21978.8 | I42: -22341.3 | J42: -22933.5 | K42: sourced / consensus | L42: CSV 'Capital Expenditure' FY22, FY23, FY25; FY21 and FY24 company (wiki); FY26E-28E consensus mean (sign flipped)
A43: Capex / sales | B43: % | C43: =IFERROR(-C42/C7,"n/a") -> 0.061013837 | D43: =IFERROR(-D42/D7,"n/a") -> 0.071905113 | E43: =IFERROR(-E42/E7,"n/a") -> 0.086911291 | F43: =IFERROR(-F42/F7,"n/a") -> 0.072004604 | G43: =IFERROR(-G42/G7,"n/a") -> 0.052768038 | H43: =IFERROR(-H42/H7,"n/a") -> 0.051560179 | I43: =IFERROR(-I42/I7,"n/a") -> 0.050172697 | J43: =IFERROR(-J42/J7,"n/a") -> 0.048958128 | K43: calc | L43: calc
A44: Cash from investing | B44: MXN m | D44: -9122 | E44: -42440 | F44: -36138 | G44: -34652 | K44: sourced / calc | L44: CSV 'Cash from Investing' FY22, FY23, FY25; FY24 = sum of company investing lines (wiki cash-flow article, incl. residual that ties to CFI) [calc]
A45: Cash from financing | B45: MXN m | D45: -25692 | E45: 5904 | G45: -11908 | K45: sourced | L45: CSV 'Cash from Financing'; FY21 and FY24 not available (CSV quarter missing; company totals not in wiki)
A46: Change in working capital, CIQ basis | B46: MXN m | C46: -5502 | D46: -6533 | E46: 11165 | F46: 1017 | G46: -696 | K46: sourced | L46: CSV 'Change in Net Working Capital' (CIQ definition; sign and size differ from company lines, see memo)
A47: Change in working capital, company lines (memo) | B47: MXN m | C47: 5451 | D47: -2737 | E47: -6542 | F47: -7733 | G47: -655 | K47: sourced | L47: wiki/Financials/bimbo-cash-flow-and-fcf.md (six working-capital lines); not used in valuation
A48: Levered free cash flow, CIQ (memo) | B48: MXN m | D48: 13502.3 | E48: -10624.6 | G48: 16360.6 | K48: sourced | L48: CSV 'Levered Free Cash Flow' (CIQ definition; memo only)
A49: Margins and ratios (calc from the rows above)
A50: EBITDA margin, CIQ standardised | B50: % | C50: =IFERROR(C18/C7,"n/a") -> 0.13442141 | D50: =IFERROR(D18/D7,"n/a") -> 0.12562414 | E50: =IFERROR(E18/E7,"n/a") -> 0.13000883 | G50: =IFERROR(G18/G7,"n/a") -> 0.12838372 | K50: calc | L50: calc

Sheet PeerAnalysis
A1: PeerAnalysis: Grupo Bimbo vs bakery and packaged-food peers (USD m unless stated)
A2: Pricing date 16-Oct-2026 (CIQ 15/16-Oct-2026). Forward horizon: NTM from 16-Oct-2026, calendarised from each company's fiscal-year consensus by day weights (block D).
A3: EV claim basis (one basis for all eligible peers and for Bimbo): EV = market cap + financial debt (incl. finance leases) + lease liabilities (operating or IFRS 16) + NCI at book incl. redeemable NCI - cash. Pensions/OPEB, MEPP and derivatives are excluded for every company (not sourced for all eligible peers).
A4: Lease basis: IFRS 16-equivalent. EBITDA is before operating lease cost: US GAAP peers add back operating lease cost (LTM; held flat for NTM) because EV includes their operating lease liabilities. Peers without a reconciled basis are shown but excluded from medians.
A5: Bimbo: company Adjusted EBITDA (IFRS 16, 60,919) includes consolidated BBU independent-operator earnings (profit to NCI per coordinator); NCI is taken at book (722), which understates the NCI claim if that profit is attributed to NCI. Model-basis EBIT + D&A is shown as a memo (block D).
A6: Bimbo price MXN 58.60 and shares 4,294.9m are coordinator-supplied (unverified here). USD columns convert at 17.46 MXN/USD for size only; multiples are computed in MXN.
A7: P/E for peers = CIQ multiples tool (NTM / LTM); EPS derived as price / P/E. Gross profit and price performance are not in the CIQ pull (blank = not retrieved, never zero).
A8: Medians and means use only peers with in-median flag = yes (AGGREGATE / SUMPRODUCT formulas; n/a cells are ignored). Core = Flowers, Gruma, Yamazaki, Aryzta; at present Yamazaki and Aryzta are excluded (basis not established).
A9: A. Market data and enterprise value on the claim basis
A10: Company | B10: Ticker | C10: Group | D10: Price currency | E10: Reporting currency | F10: Price (local) | G10: Shares (m) | H10: FX local to USD | I10: Market cap (USD m) | J10: Financial debt incl. finance leases (USD m) | K10: Lease liabilities, operating / IFRS 16 (USD m) | L10: NCI at book incl. redeemable (USD m) | M10: Cash (USD m) | N10: Net debt, claim basis (USD m) | O10: EV, claim basis (USD m) | P10: In median: valuation (yes/no) | Q10: In median: P/E (yes/no) | R10: EV claim basis (categories included and excluded) | S10: Distributor / IO earnings in EBITDA? | T10: Eligibility notes
A11: Grupo Bimbo, S.A.B. de C.V. (subject) | B11: BMV:BIMBO A | C11: Subject | D11: MXN | E11: MXN | F11: =Inputs_Sources!$D$13 -> 58.6 | G11: =Inputs_Sources!$D$14 -> 4294.9 | H11: =1/Inputs_Sources!$D$11 -> 0.057273769 | I11: =IFERROR(F11*G11*H11,"n/a") -> 14414.727 | J11: =IFERROR(Inputs_Sources!$D$18*H11,"n/a") -> 8800.6873 | K11: =IFERROR(Inputs_Sources!$D$19*H11,"n/a") -> 1910.7102 | L11: =IFERROR(Inputs_Sources!$D$17*H11,0) -> 41.351661 | M11: =IFERROR(Inputs_Sources!$D$16*H11,"n/a") -> 948.62543 | N11: =IFERROR(J11+K11+L11-M11,"n/a") -> 9804.1237 | O11: =IFERROR(I11+N11,"n/a") -> 24218.851 | P11: subject | Q11: subject | R11: Financial debt 153,660 + IFRS 16 lease liabilities 33,361 + NCI at book 722 - cash 16,563 (MXN m, 30-Jun-2026). Excludes MEPP, pensions/OPEB and derivatives. | S11: Yes: BBU independent operators (US route partners) are consolidated structured entities (RA25 p.249-250); their profit to NCI is the coordinator's statement, not confirmed in the wiki (FY25 NCI profit share 1,813). | T11: Subject. Price and shares are coordinator-supplied (unverified). EBITDA includes consolidated IO earnings.
A12: Flowers Foods, Inc. | B12: NYSE:FLO | C12: Core | D12: USD | E12: USD | F12: =IFERROR(Inputs_Sources!$D$37/Inputs_Sources!$D$38,"n/a") -> 6.1089109 | G12: =Inputs_Sources!$D$38 -> 212.1 | H12: 1 | I12: =IFERROR(F12*G12*H12,"n/a") -> 1295.7 | J12: =Inputs_Sources!$D$191+Inputs_Sources!$D$192 -> 1686.2 | K12: =Inputs_Sources!$D$193 -> 317.102 | L12: =Inputs_Sources!$D$194 -> 0 | M12: =Inputs_Sources!$D$195 -> 52.766 | N12: =IFERROR(J12+K12+L12-M12,"n/a") -> 1950.536 | O12: =IFERROR(I12+N12,"n/a") -> 3246.236 | P12: yes | Q12: yes | R12: Financial debt 1,686.2 (current 399.9, non-current 1,286.4; no finance leases tagged) + operating lease liabilities 317.1 (75.2 + 241.9) + NCI nil (no minority interest reported) - cash 52.8. CIQ total debt is 2,007.8, 4.5 above these components (not added). | S12: No: independent distributors not consolidated (coordinator statement; not re-verified in this session) | T12: US GAAP, lease basis reconciled: CIQ debt 2,007.8 vs financial debt 1,686.2 + operating leases 317.1 (-0.2%); EBITDA + LTM operating lease cost 91.8; NTM add-back held flat [assumption]
A13: Gruma, S.A.B. de C.V. | B13: BMV:GRUMA B | C13: Core | D13: MXN | E13: USD | F13: =Inputs_Sources!$D$54 -> 242.02 | G13: =Inputs_Sources!$D$55 -> 336.20799 | H13: =Inputs_Sources!$D$56 -> 0.057273769 | I13: =IFERROR(F13*G13*H13,"n/a") -> 4660.3125 | J13: =Inputs_Sources!$D$226+Inputs_Sources!$D$227 -> 1698.6 | K13: =Inputs_Sources!$D$228 -> 413.2 | L13: =Inputs_Sources!$D$229 -> 2.8 | M13: =Inputs_Sources!$D$230 -> 483.6 | N13: =IFERROR(J13+K13+L13-M13,"n/a") -> 1631 | O13: =IFERROR(I13+N13,"n/a") -> 6291.3125 | P13: yes | Q13: no | R13: Bank loans, carrying (ST 365.2 + LT 1,333.4) + IFRS 16 lease liabilities 413.2 (current 52.8, non-current 360.4) + NCI 2.8 - cash 483.6. Reports in USD. | S13: Not checked | T13: IFRS 16 reporter, USD statements: debt and IFRS 16 leases reconciled to CIQ (2,112); EBITDA before lease costs (inferred); price is a delayed quote (unverified); no EBITDA consensus, so LTM medians only
A14: Yamazaki Baking Co., Ltd. | B14: TSE:2212 | C14: Core | D14: JPY | E14: JPY | F14: =Inputs_Sources!$D$71 -> 3816 | G14: =Inputs_Sources!$D$72 -> n/a | H14: =Inputs_Sources!$D$73 -> 0.006482 | I14: =IFERROR(F14*G14*H14,"n/a") -> n/a | J14: n/a | K14: n/a | L14: n/a | M14: n/a | N14: =IFERROR(J14+K14+L14-M14,"n/a") -> n/a | O14: =IFERROR(I14+N14,"n/a") -> n/a | P14: no | Q14: no | R14: Not built: shares, NCI and lease split not sourced, so no EV on the claim basis | S14: Not checked | T14: J-GAAP: operating lease obligations not established (FY25 yuho unreadable); shares and NCI not found; EV not built; excluded from medians
A15: ARYZTA AG | B15: SWX:ARYN | C15: Core | D15: USD | E15: EUR | F15: =IFERROR(Inputs_Sources!$D$88/Inputs_Sources!$D$89,"n/a") -> 49.145161 | G15: =Inputs_Sources!$D$89 -> 24.8 | H15: 1 | I15: =IFERROR(F15*G15*H15,"n/a") -> 1218.8 | J15: =Inputs_Sources!$D$233+Inputs_Sources!$D$234 -> 986.9 | K15: =Inputs_Sources!$D$235 -> 0 | L15: =Inputs_Sources!$D$236 -> -17.4 | M15: =Inputs_Sources!$D$237 -> 85 | N15: =IFERROR(J15+K15+L15-M15,"n/a") -> 884.5 | O15: =IFERROR(I15+N15,"n/a") -> 2103.3 | P15: no | Q15: no | R15: CIQ basis, NOT verified: total debt 986.9 (lease split not verified) + CIQ EV residual -17.4 (unexplained; NCI not found) - cash 85.0. Descriptive only. | S15: Not checked | T15: IFRS 16 reporter: lease split, share count and NCI not verified (H1-26 report unreadable); CIQ values shown descriptively; excluded from medians
A16: The J. M. Smucker Company | B16: NYSE:SJM | C16: Secondary | D16: USD | E16: USD | F16: =IFERROR(Inputs_Sources!$D$105/Inputs_Sources!$D$106,"n/a") -> 127.45787 | G16: =Inputs_Sources!$D$106 -> 106.8 | H16: 1 | I16: =IFERROR(F16*G16*H16,"n/a") -> 13612.5 | J16: =Inputs_Sources!$D$198+Inputs_Sources!$D$199 -> 6747.4 | K16: =Inputs_Sources!$D$200 -> 192.8 | L16: =Inputs_Sources!$D$201 -> 0 | M16: =Inputs_Sources!$D$202 -> 43.2 | N16: =IFERROR(J16+K16+L16-M16,"n/a") -> 6897 | O16: =IFERROR(I16+N16,"n/a") -> 20509.5 | P16: yes | Q16: no | R16: Financial debt 6,737.8 (ST borrowings 193.5, current LTD 150.0, LTD 6,394.3) + finance leases 9.6 + operating lease liabilities 192.8 + NCI nil (not reported) - cash 43.2. Ties exactly to CIQ EV. | S16: Not checked | T16: US GAAP, lease basis reconciled (exact tie incl. finance leases 9.6); EBITDA + operating lease cost 46.9; in EV medians; excluded from P/E medians (depressed earnings, assumption)
A17: The Campbell's Company | B17: NasdaqGS:CPB | C17: Secondary | D17: USD | E17: USD | F17: =IFERROR(Inputs_Sources!$D$122/Inputs_Sources!$D$123,"n/a") -> 19.872233 | G17: =Inputs_Sources!$D$123 -> 298.2 | H17: 1 | I17: =IFERROR(F17*G17*H17,"n/a") -> 5925.9 | J17: =Inputs_Sources!$D$205+Inputs_Sources!$D$206 -> 7137 | K17: =Inputs_Sources!$D$207 -> 313 | L17: =Inputs_Sources!$D$208 -> 306 | M17: =Inputs_Sources!$D$209 -> 394 | N17: =IFERROR(J17+K17+L17-M17,"n/a") -> 7362 | O17: =IFERROR(I17+N17,"n/a") -> 13287.9 | P17: yes | Q17: yes | R17: Financial debt 7,053.0 + finance leases 84.0 + operating lease liabilities 313.0 + NCI 2.0 + redeemable NCI (mezzanine) 304.0 - cash 394.0. Ties to CIQ EV including the 306 residual. | S17: Not checked | T17: US GAAP, lease basis reconciled (exact tie); EBITDA + operating lease cost 114.0; EV includes redeemable NCI 304 (mezzanine) and NCI 2
A18: Mondelez International, Inc. | B18: NasdaqGS:MDLZ | C18: Secondary | D18: USD | E18: USD | F18: =IFERROR(Inputs_Sources!$D$139/Inputs_Sources!$D$140,"n/a") -> 63.910366 | G18: =Inputs_Sources!$D$140 -> 1276.3 | H18: 1 | I18: =IFERROR(F18*G18*H18,"n/a") -> 81568.8 | J18: =Inputs_Sources!$D$212+Inputs_Sources!$D$213 -> 21450 | K18: =Inputs_Sources!$D$214 -> 609 | L18: =Inputs_Sources!$D$215 -> 53 | M18: =Inputs_Sources!$D$216 -> 1716 | N18: =IFERROR(J18+K18+L18-M18,"n/a") -> 20396 | O18: =IFERROR(I18+N18,"n/a") -> 101964.8 | P18: yes | Q18: yes | R18: Financial debt 21,450 (includes finance leases, not separated at 30-Jun-26; 423 at 31-Dec-25) + noncurrent operating lease liabilities 609 (current portion not found; 164 at 31-Dec-25) + NCI 53 - cash 1,716. Ties to CIQ EV. | S18: Not checked | T18: US GAAP, lease basis reconciled on noncurrent leases (exact tie); current lease portion not found at 30-Jun-2026; EBITDA + FY25 operating lease cost 246 (LTM 10-Q not found) [assumption]
A19: Arca Continental, S.A.B. de C.V. | B19: BMV:AC | C19: Secondary | D19: MXN | E19: MXN | F19: =Inputs_Sources!$D$156 -> 209.66 | G19: =Inputs_Sources!$D$157 -> n/a | H19: =Inputs_Sources!$D$158 -> 0.057273769 | I19: =IFERROR(F19*G19*H19,"n/a") -> n/a | J19: n/a | K19: n/a | L19: n/a | M19: n/a | N19: =IFERROR(J19+K19+L19-M19,"n/a") -> n/a | O19: =IFERROR(I19+N19,"n/a") -> n/a | P19: no | Q19: no | R19: Not built: shares, NCI and lease split not sourced, so no EV on the claim basis | S19: Not checked | T19: IFRS 16 reporter: shares, NCI and lease split not found; price is an aggregator quote; EV not built; excluded from medians (CIQ tool 8.47x for audit only)
A20: PepsiCo, Inc. | B20: NasdaqGS:PEP | C20: Secondary | D20: USD | E20: USD | F20: =IFERROR(Inputs_Sources!$D$173/Inputs_Sources!$D$174,"n/a") -> 131.504 | G20: =Inputs_Sources!$D$174 -> 1362.7 | H20: 1 | I20: =IFERROR(F20*G20*H20,"n/a") -> 179200.5 | J20: =Inputs_Sources!$D$219+Inputs_Sources!$D$220 -> 51881 | K20: =Inputs_Sources!$D$221 -> 3846 | L20: =Inputs_Sources!$D$222 -> 195 | M20: =Inputs_Sources!$D$223 -> 10675 | N20: =IFERROR(J20+K20+L20-M20,"n/a") -> 45247 | O20: =IFERROR(I20+N20,"n/a") -> 224447.5 | P20: yes | Q20: yes | R20: Financial debt 51,881 (= CIQ total debt; finance leases not separated) + operating lease liabilities 3,846 (27-Dec-2025 10-K; Sep-2026 not found; CIQ excludes leases) + NCI 195 - cash 10,675. CIQ net debt (40,718) deducts a further 488 that is not cash and is not used. | S20: Not checked (franchise bottler consolidation not verified) | T20: US GAAP: CIQ debt excludes operating leases; EV adds 3,846 (27-Dec-2025 10-K; Sep-2026 not found) [assumption]; EBITDA + FY25 operating lease cost 880 [assumption]
A23: B. Financials (USD m; Bimbo converted at the MXN display rate)
A24: Company | B24: Revenue FY2024 | C24: Revenue FY2025 | D24: Revenue LTM | E24: Revenue NTM (calendarised) | F24: EBITDA FY2024 (reported) | G24: EBITDA FY2025 (reported) | H24: EBITDA LTM (reported) | I24: Operating lease cost add-back, LTM | J24: EBITDA LTM, IFRS 16-equivalent | K24: EBITDA NTM (reported, calendarised) | L24: EBITDA NTM, IFRS 16-equivalent | M24: Gross profit LTM | N24: Levered FCF LTM | O24: EBITDA margin LTM (IFRS 16-eq.) | P24: Gross margin LTM | Q24: EPS LTM (local) | R24: EPS NTM (local)
A25: Grupo Bimbo (subject) | B25: =IFERROR(TearSheet!$F$7*$H$11,"n/a") -> 23386.884 | C25: =IFERROR(TearSheet!$G$7*$H$11,"n/a") -> 24453.78 | D25: =IFERROR(Inputs_Sources!$D$29*$H$11,"n/a") -> 24136.483 | E25: =IFERROR(K60*$H$11,"n/a") -> 25273.595 | F25: =IFERROR(TearSheet!$F$19*$H$11,"n/a") -> 3177.1478 | G25: =IFERROR(TearSheet!$G$19*$H$11,"n/a") -> 3405.2692 | H25: =IFERROR((Inputs_Sources!$D$25+Inputs_Sources!$D$26+Inputs_Sources!$D$27+Inputs_Sources!$D$28)*$H$11,"n/a") -> 3489.0607 | I25: 0 | J25: =IFERROR(H25+I25,"n/a") -> 3489.0607 | K25: =IFERROR(H60*$H$11,"n/a") -> 3683.0355 | L25: =IFERROR(K25+I25,"n/a") -> 3683.0355 | M25: =IFERROR(Inputs_Sources!$D$34*$H$11,"n/a") -> 12685.582 | N25: =IFERROR(Inputs_Sources!$D$35*$H$11,"n/a") -> 1456.6638 | O25: =IFERROR(J25/D25,"n/a") -> 0.14455547 | P25: =IFERROR(M25/D25,"n/a") -> 0.52557706 | Q25: =IFERROR(Inputs_Sources!$D$30+Inputs_Sources!$D$31+Inputs_Sources!$D$32+Inputs_Sources!$D$33,"n/a") -> 3.175 | R25: =N60 -> 3.2909315
A26: Flowers Foods, Inc. | B26: =Inputs_Sources!$D$44 -> 5103.5 | C26: =Inputs_Sources!$D$45 -> 5256.5 | D26: =Inputs_Sources!$D$43 -> 5223.9 | E26: =K61 -> 5062.0877 | F26: =Inputs_Sources!$D$46 -> 520.7 | G26: =Inputs_Sources!$D$47 -> 514.8 | H26: =Inputs_Sources!$D$42 -> 486.9 | I26: =IF(ISNUMBER(Inputs_Sources!$D$289),Inputs_Sources!$D$289,0) -> 91.809 | J26: =IFERROR(H26+I26,"n/a") -> 578.709 | K26: =H61 -> 436.26849 | L26: =IFERROR(K26+I26,"n/a") -> 528.07749 | M26: =Inputs_Sources!$D$48 -> n/a | N26: =Inputs_Sources!$D$49 -> 298.5 | O26: =IFERROR(J26/D26,"n/a") -> 0.11078103 | P26: =IFERROR(M26/D26,"n/a") -> n/a | Q26: =IFERROR(F12/Inputs_Sources!$D$50,"n/a") -> 0.26050793 | R26: =IFERROR(F12/Inputs_Sources!$D$51,"n/a") -> 0.68408857
A27: Gruma, S.A.B. de C.V. | B27: =Inputs_Sources!$D$61 -> 6486.9 | C27: =Inputs_Sources!$D$62 -> 6374.6 | D27: =Inputs_Sources!$D$60 -> 6500.1 | E27: =K62 -> n/a | F27: =Inputs_Sources!$D$63 -> 1131.1 | G27: =Inputs_Sources!$D$64 -> 1136 | H27: =Inputs_Sources!$D$59 -> 1108.9 | I27: =IF(ISNUMBER(Inputs_Sources!$D$313),Inputs_Sources!$D$313,0) -> 0 | J27: =IFERROR(H27+I27,"n/a") -> 1108.9 | K27: =H62 -> n/a | L27: =IFERROR(K27+I27,"n/a") -> n/a | M27: =Inputs_Sources!$D$65 -> 2522.2 | N27: =Inputs_Sources!$D$66 -> n/a | O27: =IFERROR(J27/D27,"n/a") -> 0.17059738 | P27: =IFERROR(M27/D27,"n/a") -> 0.3880248 | Q27: =IFERROR(F13/Inputs_Sources!$D$67,"n/a") -> n/a | R27: =IFERROR(F13/Inputs_Sources!$D$68,"n/a") -> n/a
A28: Yamazaki Baking Co., Ltd. | B28: =Inputs_Sources!$D$78 -> 8224.6 | C28: =Inputs_Sources!$D$79 -> n/a | D28: =Inputs_Sources!$D$77 -> 8669.9 | E28: =K63 -> 8746.3529 | F28: =Inputs_Sources!$D$80 -> 630.3 | G28: =Inputs_Sources!$D$81 -> 712 | H28: =Inputs_Sources!$D$76 -> 706.7 | I28: 0 | J28: =IFERROR(H28+I28,"n/a") -> 706.7 | K28: =H63 -> 732.7663 | L28: =IFERROR(K28+I28,"n/a") -> 732.7663 | M28: =Inputs_Sources!$D$82 -> n/a | N28: =Inputs_Sources!$D$83 -> 113.4 | O28: =IFERROR(J28/D28,"n/a") -> 0.081511897 | P28: =IFERROR(M28/D28,"n/a") -> n/a | Q28: =IFERROR(F14/Inputs_Sources!$D$84,"n/a") -> 215.1071 | R28: =IFERROR(F14/Inputs_Sources!$D$85,"n/a") -> 226.60333
A29: ARYZTA AG | B29: =Inputs_Sources!$D$95 -> 2374.1 | C29: =Inputs_Sources!$D$96 -> 2513.7 | D29: =Inputs_Sources!$D$94 -> 2567.4 | E29: =K64 -> 2569.3718 | F29: =Inputs_Sources!$D$97 -> 295.3 | G29: =Inputs_Sources!$D$98 -> 287.4 | H29: =Inputs_Sources!$D$93 -> 252.4 | I29: =IF(ISNUMBER(Inputs_Sources!$D$317),Inputs_Sources!$D$317,0) -> 0 | J29: =IFERROR(H29+I29,"n/a") -> 252.4 | K29: =H64 -> 361.72247 | L29: =IFERROR(K29+I29,"n/a") -> 361.72247 | M29: =Inputs_Sources!$D$99 -> n/a | N29: =Inputs_Sources!$D$100 -> 138.1 | O29: =IFERROR(J29/D29,"n/a") -> 0.098309574 | P29: =IFERROR(M29/D29,"n/a") -> n/a | Q29: =IFERROR(F15/Inputs_Sources!$D$101,"n/a") -> 4.813434 | R29: =IFERROR(F15/Inputs_Sources!$D$102,"n/a") -> 5.4545129
A30: The J. M. Smucker Company | B30: =Inputs_Sources!$D$112 -> 8178.7 | C30: =Inputs_Sources!$D$113 -> 8726.1 | D30: =Inputs_Sources!$D$111 -> 9156.9 | E30: =K65 -> 8979.6414 | F30: =Inputs_Sources!$D$114 -> 1874.1 | G30: =Inputs_Sources!$D$115 -> 2156.2 | H30: =Inputs_Sources!$D$110 -> 2263.9 | I30: =IF(ISNUMBER(Inputs_Sources!$D$294),Inputs_Sources!$D$294,0) -> 46.9 | J30: =IFERROR(H30+I30,"n/a") -> 2310.8 | K30: =H65 -> 2178.5844 | L30: =IFERROR(K30+I30,"n/a") -> 2225.4844 | M30: =Inputs_Sources!$D$116 -> n/a | N30: =Inputs_Sources!$D$117 -> 1464.3 | O30: =IFERROR(J30/D30,"n/a") -> 0.25235615 | P30: =IFERROR(M30/D30,"n/a") -> n/a | Q30: =IFERROR(F16/Inputs_Sources!$D$118,"n/a") -> 2.173936 | R30: =IFERROR(F16/Inputs_Sources!$D$119,"n/a") -> 10.115704
A31: The Campbell's Company | B31: =Inputs_Sources!$D$129 -> 9636 | C31: =Inputs_Sources!$D$130 -> 10253 | D31: =Inputs_Sources!$D$128 -> 9744 | E31: =K66 -> 9491.011 | F31: =Inputs_Sources!$D$131 -> 1783 | G31: =Inputs_Sources!$D$132 -> 1888 | H31: =Inputs_Sources!$D$127 -> 1620 | I31: =IF(ISNUMBER(Inputs_Sources!$D$299),Inputs_Sources!$D$299,0) -> 114 | J31: =IFERROR(H31+I31,"n/a") -> 1734 | K31: =H66 -> 1475.9425 | L31: =IFERROR(K31+I31,"n/a") -> 1589.9425 | M31: =Inputs_Sources!$D$133 -> 2742 | N31: =Inputs_Sources!$D$134 -> 634.5 | O31: =IFERROR(J31/D31,"n/a") -> 0.17795567 | P31: =IFERROR(M31/D31,"n/a") -> 0.28140394 | Q31: =IFERROR(F17/Inputs_Sources!$D$135,"n/a") -> 1.315171 | R31: =IFERROR(F17/Inputs_Sources!$D$136,"n/a") -> 1.6955831
A32: Mondelez International, Inc. | B32: =Inputs_Sources!$D$146 -> 36441 | C32: =Inputs_Sources!$D$147 -> 38537 | D32: =Inputs_Sources!$D$145 -> 39675 | E32: =K67 -> 40994.158 | F32: =Inputs_Sources!$D$148 -> 7740 | G32: =Inputs_Sources!$D$149 -> 4990 | H32: =Inputs_Sources!$D$144 -> 6080 | I32: =IF(ISNUMBER(Inputs_Sources!$D$304),Inputs_Sources!$D$304,0) -> 246 | J32: =IFERROR(H32+I32,"n/a") -> 6326 | K32: =H67 -> 7153.234 | L32: =IFERROR(K32+I32,"n/a") -> 7399.234 | M32: =Inputs_Sources!$D$150 -> 12357 | N32: =Inputs_Sources!$D$151 -> 2252.4 | O32: =IFERROR(J32/D32,"n/a") -> 0.15944549 | P32: =IFERROR(M32/D32,"n/a") -> 0.31145558 | Q32: =IFERROR(F18/Inputs_Sources!$D$152,"n/a") -> 2.7666825 | R32: =IFERROR(F18/Inputs_Sources!$D$153,"n/a") -> 3.2229131
A33: Arca Continental, S.A.B. de C.V. | B33: =Inputs_Sources!$D$163 -> 13149.5 | C33: =Inputs_Sources!$D$164 -> 13058.3 | D33: =Inputs_Sources!$D$162 -> 13945.2 | E33: =K68 -> 14591.724 | F33: =Inputs_Sources!$D$165 -> 2599 | G33: =Inputs_Sources!$D$166 -> 2540.6 | H33: =Inputs_Sources!$D$161 -> 2707 | I33: =IF(ISNUMBER(Inputs_Sources!$D$321),Inputs_Sources!$D$321,0) -> 0 | J33: =IFERROR(H33+I33,"n/a") -> 2707 | K33: =H68 -> 2990.246 | L33: =IFERROR(K33+I33,"n/a") -> 2990.246 | M33: =Inputs_Sources!$D$167 -> n/a | N33: =Inputs_Sources!$D$168 -> 763.6 | O33: =IFERROR(J33/D33,"n/a") -> 0.19411697 | P33: =IFERROR(M33/D33,"n/a") -> n/a | Q33: =IFERROR(F19/Inputs_Sources!$D$169,"n/a") -> 11.205772 | R33: =IFERROR(F19/Inputs_Sources!$D$170,"n/a") -> 12.706667
A34: PepsiCo, Inc. | B34: =Inputs_Sources!$D$180 -> 91854 | C34: =Inputs_Sources!$D$181 -> 93925 | D34: =Inputs_Sources!$D$179 -> 98241 | E34: =K69 -> 101251.48 | F34: =Inputs_Sources!$D$182 -> 17842 | G34: =Inputs_Sources!$D$183 -> 18174 | H34: =Inputs_Sources!$D$178 -> 19171 | I34: =IF(ISNUMBER(Inputs_Sources!$D$309),Inputs_Sources!$D$309,0) -> 880 | J34: =IFERROR(H34+I34,"n/a") -> 20051 | K34: =H69 -> 19473.899 | L34: =IFERROR(K34+I34,"n/a") -> 20353.899 | M34: =Inputs_Sources!$D$184 -> 53216 | N34: =Inputs_Sources!$D$185 -> 9044.3 | O34: =IFERROR(J34/D34,"n/a") -> 0.20410012 | P34: =IFERROR(M34/D34,"n/a") -> 0.5416883 | Q34: =IFERROR(F20/Inputs_Sources!$D$186,"n/a") -> 8.1426625 | R34: =IFERROR(F20/Inputs_Sources!$D$187,"n/a") -> 8.4677398
A37: C. Valuation (EV on the claim basis; IFRS 16-equivalent EBITDA; medians over eligible peers)
A38: Company | B38: EV/EBITDA LTM (x) | C38: EV/EBITDA NTM (x) | D38: EV/Sales LTM (x) | E38: P/E LTM (x) | F38: P/E NTM (x) | G38: FCF yield LTM (levered, %) | H38: Net debt / EBITDA LTM (x, claim basis) | I38: EBITDA margin LTM (%) | J38: CIQ tool EV/EBITDA LTM (audit) | K38: CIQ tool EV/EBITDA NTM (audit) | L38: CIQ tool P/E LTM (audit) | M38: CIQ tool P/E NTM (audit) | N38: Notes
A39: Grupo Bimbo (subject) | B39: =IFERROR(O11/J25,"n/a") -> 6.9413671 | C39: =IFERROR(O11/L25,"n/a") -> 6.5757854 | D39: =IFERROR(O11/D25,"n/a") -> 1.0034126 | E39: =IFERROR(F11/Q25,"n/a") -> 18.456693 | F39: =IFERROR(F11/R25,"n/a") -> 17.806509 | G39: =IFERROR(N25/I11,"n/a") -> 0.10105385 | H39: =IFERROR(N11/J25,"n/a") -> 2.8099608 | I39: =O25 -> 0.14455547 | J39: n/a | K39: n/a | L39: n/a | M39: n/a | N39: Bimbo on the same claim basis (block D memo gives the model-basis EBIT + D&A multiple)
A40: Flowers Foods, Inc. | B40: =IFERROR(O12/J26,"n/a") -> 5.6094445 | C40: =IFERROR(O12/L26,"n/a") -> 6.147272 | D40: =IFERROR(O12/D26,"n/a") -> 0.62142001 | E40: =Inputs_Sources!$D$50 -> 23.45 | F40: =Inputs_Sources!$D$51 -> 8.93 | G40: =IFERROR(N26/I12,"n/a") -> 0.2303774 | H40: =IFERROR(N12/J26,"n/a") -> 3.3704954 | I40: =O26 -> 0.11078103 | J40: =Inputs_Sources!$D$52 -> 5.15 | K40: =Inputs_Sources!$D$53 -> 7.55 | L40: =Inputs_Sources!$D$50 -> 23.45 | M40: =Inputs_Sources!$D$51 -> 8.93 | N40: CIQ tool values are audit only; EV-based multiples use the claim-basis EV
A41: Gruma, S.A.B. de C.V. | B41: =IFERROR(O13/J27,"n/a") -> 5.6734715 | C41: =IFERROR(O13/L27,"n/a") -> n/a | D41: =IFERROR(O13/D27,"n/a") -> 0.96787934 | E41: =Inputs_Sources!$D$67 -> n/a | F41: =Inputs_Sources!$D$68 -> n/a | G41: =IFERROR(N27/I13,"n/a") -> n/a | H41: =IFERROR(N13/J27,"n/a") -> 1.4708269 | I41: =O27 -> 0.17059738 | J41: =Inputs_Sources!$D$69 -> n/a | K41: =Inputs_Sources!$D$70 -> n/a | L41: =Inputs_Sources!$D$67 -> n/a | M41: =Inputs_Sources!$D$68 -> n/a | N41: CIQ tool values are audit only; EV-based multiples use the claim-basis EV
A42: Yamazaki Baking Co., Ltd. | B42: =IFERROR(O14/J28,"n/a") -> n/a | C42: =IFERROR(O14/L28,"n/a") -> n/a | D42: =IFERROR(O14/D28,"n/a") -> n/a | E42: =Inputs_Sources!$D$84 -> 17.74 | F42: =Inputs_Sources!$D$85 -> 16.84 | G42: =IFERROR(N28/I14,"n/a") -> n/a | H42: =IFERROR(N14/J28,"n/a") -> n/a | I42: =O28 -> 0.081511897 | J42: =Inputs_Sources!$D$86 -> 6.58 | K42: =Inputs_Sources!$D$87 -> 6.37 | L42: =Inputs_Sources!$D$84 -> 17.74 | M42: =Inputs_Sources!$D$85 -> 16.84 | N42: CIQ tool values are audit only; EV-based multiples use the claim-basis EV
A43: ARYZTA AG | B43: =IFERROR(O15/J29,"n/a") -> 8.3332013 | C43: =IFERROR(O15/L29,"n/a") -> 5.8146789 | D43: =IFERROR(O15/D29,"n/a") -> 0.81923347 | E43: =Inputs_Sources!$D$101 -> 10.21 | F43: =Inputs_Sources!$D$102 -> 9.01 | G43: =IFERROR(N29/I15,"n/a") -> 0.11330817 | H43: =IFERROR(N15/J29,"n/a") -> 3.5043582 | I43: =O29 -> 0.098309574 | J43: =Inputs_Sources!$D$103 -> 7.31 | K43: =Inputs_Sources!$D$104 -> 5.94 | L43: =Inputs_Sources!$D$101 -> 10.21 | M43: =Inputs_Sources!$D$102 -> 9.01 | N43: CIQ tool values are audit only; EV-based multiples use the claim-basis EV
A44: The J. M. Smucker Company | B44: =IFERROR(O16/J30,"n/a") -> 8.8754977 | C44: =IFERROR(O16/L30,"n/a") -> 9.2157465 | D44: =IFERROR(O16/D30,"n/a") -> 2.2397864 | E44: =Inputs_Sources!$D$118 -> 58.63 | F44: =Inputs_Sources!$D$119 -> 12.6 | G44: =IFERROR(N30/I16,"n/a") -> 0.10757025 | H44: =IFERROR(N16/J30,"n/a") -> 2.9846806 | I44: =O30 -> 0.25235615 | J44: =Inputs_Sources!$D$120 -> 8.57 | K44: =Inputs_Sources!$D$121 -> 9.86 | L44: =Inputs_Sources!$D$118 -> 58.63 | M44: =Inputs_Sources!$D$119 -> 12.6 | N44: CIQ tool values are audit only; EV-based multiples use the claim-basis EV
A45: The Campbell's Company | B45: =IFERROR(O17/J31,"n/a") -> 7.6631488 | C45: =IFERROR(O17/L31,"n/a") -> 8.3574722 | D45: =IFERROR(O17/D31,"n/a") -> 1.3637007 | E45: =Inputs_Sources!$D$135 -> 15.11 | F45: =Inputs_Sources!$D$136 -> 11.72 | G45: =IFERROR(N31/I17,"n/a") -> 0.10707234 | H45: =IFERROR(N17/J31,"n/a") -> 4.2456747 | I45: =O31 -> 0.17795567 | J45: =Inputs_Sources!$D$137 -> 6.47 | K45: =Inputs_Sources!$D$138 -> 9.07 | L45: =Inputs_Sources!$D$135 -> 15.11 | M45: =Inputs_Sources!$D$136 -> 11.72 | N45: CIQ tool values are audit only; EV-based multiples use the claim-basis EV
A46: Mondelez International, Inc. | B46: =IFERROR(O18/J32,"n/a") -> 16.118369 | C46: =IFERROR(O18/L32,"n/a") -> 13.780454 | D46: =IFERROR(O18/D32,"n/a") -> 2.5700013 | E46: =Inputs_Sources!$D$152 -> 23.1 | F46: =Inputs_Sources!$D$153 -> 19.83 | G46: =IFERROR(N32/I18,"n/a") -> 0.027613499 | H46: =IFERROR(N18/J32,"n/a") -> 3.2241543 | I46: =O32 -> 0.15944549 | J46: =Inputs_Sources!$D$154 -> 14.48 | K46: =Inputs_Sources!$D$155 -> 14.13 | L46: =Inputs_Sources!$D$152 -> 23.1 | M46: =Inputs_Sources!$D$153 -> 19.83 | N46: CIQ tool values are audit only; EV-based multiples use the claim-basis EV
A47: Arca Continental, S.A.B. de C.V. | B47: =IFERROR(O19/J33,"n/a") -> n/a | C47: =IFERROR(O19/L33,"n/a") -> n/a | D47: =IFERROR(O19/D33,"n/a") -> n/a | E47: =Inputs_Sources!$D$169 -> 18.71 | F47: =Inputs_Sources!$D$170 -> 16.5 | G47: =IFERROR(N33/I19,"n/a") -> n/a | H47: =IFERROR(N19/J33,"n/a") -> n/a | I47: =O33 -> 0.19411697 | J47: =Inputs_Sources!$D$171 -> 8.47 | K47: =Inputs_Sources!$D$172 -> 7.87 | L47: =Inputs_Sources!$D$169 -> 18.71 | M47: =Inputs_Sources!$D$170 -> 16.5 | N47: CIQ tool values are audit only; EV-based multiples use the claim-basis EV
A48: PepsiCo, Inc. | B48: =IFERROR(O20/J34,"n/a") -> 11.193831 | C48: =IFERROR(O20/L34,"n/a") -> 11.027248 | D48: =IFERROR(O20/D34,"n/a") -> 2.2846622 | E48: =Inputs_Sources!$D$186 -> 16.15 | F48: =Inputs_Sources!$D$187 -> 15.53 | G48: =IFERROR(N34/I20,"n/a") -> 0.050470283 | H48: =IFERROR(N20/J34,"n/a") -> 2.2565957 | I48: =O34 -> 0.20410012 | J48: =Inputs_Sources!$D$188 -> 10.35 | K48: =Inputs_Sources!$D$189 -> 11.24 | L48: =Inputs_Sources!$D$186 -> 16.15 | M48: =Inputs_Sources!$D$187 -> 15.53 | N48: CIQ tool values are audit only; EV-based multiples use the claim-basis EV
A49: Statistics (valuation metrics)
A50: Core median (eligible peers) | B50: =IFERROR(_xlfn.AGGREGATE(16,6,B40:B48/(($C$12:$C$20="Core")*($P$12:$P$20="yes")*ISNUMBER(B40:B48)),0.5),"n/a") -> 5.641458 | C50: =IFERROR(_xlfn.AGGREGATE(16,6,C40:C48/(($C$12:$C$20="Core")*($P$12:$P$20="yes")*ISNUMBER(C40:C48)),0.5),"n/a") -> 6.147272 | D50: =IFERROR(_xlfn.AGGREGATE(16,6,D40:D48/(($C$12:$C$20="Core")*($P$12:$P$20="yes")*ISNUMBER(D40:D48)),0.5),"n/a") -> 0.79464968 | E50: =IFERROR(_xlfn.AGGREGATE(16,6,E40:E48/(($C$12:$C$20="Core")*($Q$12:$Q$20="yes")*ISNUMBER(E40:E48)),0.5),"n/a") -> 23.45 | F50: =IFERROR(_xlfn.AGGREGATE(16,6,F40:F48/(($C$12:$C$20="Core")*($Q$12:$Q$20="yes")*ISNUMBER(F40:F48)),0.5),"n/a") -> 8.93 | G50: =IFERROR(_xlfn.AGGREGATE(16,6,G40:G48/(($C$12:$C$20="Core")*($P$12:$P$20="yes")*ISNUMBER(G40:G48)),0.5),"n/a") -> 0.2303774 | H50: =IFERROR(_xlfn.AGGREGATE(16,6,H40:H48/(($C$12:$C$20="Core")*($P$12:$P$20="yes")*ISNUMBER(H40:H48)),0.5),"n/a") -> 2.4206612 | I50: =IFERROR(_xlfn.AGGREGATE(16,6,I40:I48/(($C$12:$C$20="Core")*($P$12:$P$20="yes")*ISNUMBER(I40:I48)),0.5),"n/a") -> 0.1406892
A51: Core mean (eligible peers) | B51: =IFERROR(SUMPRODUCT(($C$12:$C$20="Core")*($P$12:$P$20="yes")*ISNUMBER(B40:B48),B40:B48)/SUMPRODUCT(($C$12:$C$20="Core")*($P$12:$P$20="yes")*ISNUMBER(B40:B48)),"n/a") -> 5.641458 | C51: =IFERROR(SUMPRODUCT(($C$12:$C$20="Core")*($P$12:$P$20="yes")*ISNUMBER(C40:C48),C40:C48)/SUMPRODUCT(($C$12:$C$20="Core")*($P$12:$P$20="yes")*ISNUMBER(C40:C48)),"n/a") -> 6.147272 | D51: =IFERROR(SUMPRODUCT(($C$12:$C$20="Core")*($P$12:$P$20="yes")*ISNUMBER(D40:D48),D40:D48)/SUMPRODUCT(($C$12:$C$20="Core")*($P$12:$P$20="yes")*ISNUMBER(D40:D48)),"n/a") -> 0.79464968 | E51: =IFERROR(SUMPRODUCT(($C$12:$C$20="Core")*($Q$12:$Q$20="yes")*ISNUMBER(E40:E48),E40:E48)/SUMPRODUCT(($C$12:$C$20="Core")*($Q$12:$Q$20="yes")*ISNUMBER(E40:E48)),"n/a") -> 23.45 | F51: =IFERROR(SUMPRODUCT(($C$12:$C$20="Core")*($Q$12:$Q$20="yes")*ISNUMBER(F40:F48),F40:F48)/SUMPRODUCT(($C$12:$C$20="Core")*($Q$12:$Q$20="yes")*ISNUMBER(F40:F48)),"n/a") -> 8.93 | G51: =IFERROR(SUMPRODUCT(($C$12:$C$20="Core")*($P$12:$P$20="yes")*ISNUMBER(G40:G48),G40:G48)/SUMPRODUCT(($C$12:$C$20="Core")*($P$12:$P$20="yes")*ISNUMBER(G40:G48)),"n/a") -> 0.2303774 | H51: =IFERROR(SUMPRODUCT(($C$12:$C$20="Core")*($P$12:$P$20="yes")*ISNUMBER(H40:H48),H40:H48)/SUMPRODUCT(($C$12:$C$20="Core")*($P$12:$P$20="yes")*ISNUMBER(H40:H48)),"n/a") -> 2.4206612 | I51: =IFERROR(SUMPRODUCT(($C$12:$C$20="Core")*($P$12:$P$20="yes")*ISNUMBER(I40:I48),I40:I48)/SUMPRODUCT(($C$12:$C$20="Core")*($P$12:$P$20="yes")*ISNUMBER(I40:I48)),"n/a") -> 0.1406892
A52: Core: number of eligible peers | B52: =SUMPRODUCT(($C$12:$C$20="Core")*($P$12:$P$20="yes")*ISNUMBER(B40:B48)) -> 2 | C52: =SUMPRODUCT(($C$12:$C$20="Core")*($P$12:$P$20="yes")*ISNUMBER(C40:C48)) -> 1 | D52: =SUMPRODUCT(($C$12:$C$20="Core")*($P$12:$P$20="yes")*ISNUMBER(D40:D48)) -> 2 | E52: =SUMPRODUCT(($C$12:$C$20="Core")*($Q$12:$Q$20="yes")*ISNUMBER(E40:E48)) -> 1 | F52: =SUMPRODUCT(($C$12:$C$20="Core")*($Q$12:$Q$20="yes")*ISNUMBER(F40:F48)) -> 1 | G52: =SUMPRODUCT(($C$12:$C$20="Core")*($P$12:$P$20="yes")*ISNUMBER(G40:G48)) -> 1 | H52: =SUMPRODUCT(($C$12:$C$20="Core")*($P$12:$P$20="yes")*ISNUMBER(H40:H48)) -> 2 | I52: =SUMPRODUCT(($C$12:$C$20="Core")*($P$12:$P$20="yes")*ISNUMBER(I40:I48)) -> 2
A53: All-peer median (eligible peers) | B53: =IFERROR(_xlfn.AGGREGATE(16,6,B40:B48/(($P$12:$P$20="yes")*ISNUMBER(B40:B48)),0.5),"n/a") -> 8.2693232 | C53: =IFERROR(_xlfn.AGGREGATE(16,6,C40:C48/(($P$12:$P$20="yes")*ISNUMBER(C40:C48)),0.5),"n/a") -> 9.2157465 | D53: =IFERROR(_xlfn.AGGREGATE(16,6,D40:D48/(($P$12:$P$20="yes")*ISNUMBER(D40:D48)),0.5),"n/a") -> 1.8017436 | E53: =IFERROR(_xlfn.AGGREGATE(16,6,E40:E48/(($Q$12:$Q$20="yes")*ISNUMBER(E40:E48)),0.5),"n/a") -> 19.625 | F53: =IFERROR(_xlfn.AGGREGATE(16,6,F40:F48/(($Q$12:$Q$20="yes")*ISNUMBER(F40:F48)),0.5),"n/a") -> 13.625 | G53: =IFERROR(_xlfn.AGGREGATE(16,6,G40:G48/(($P$12:$P$20="yes")*ISNUMBER(G40:G48)),0.5),"n/a") -> 0.10707234 | H53: =IFERROR(_xlfn.AGGREGATE(16,6,H40:H48/(($P$12:$P$20="yes")*ISNUMBER(H40:H48)),0.5),"n/a") -> 3.1044175 | I53: =IFERROR(_xlfn.AGGREGATE(16,6,I40:I48/(($P$12:$P$20="yes")*ISNUMBER(I40:I48)),0.5),"n/a") -> 0.17427652
A54: All-peer mean (eligible peers) | B54: =IFERROR(SUMPRODUCT(($P$12:$P$20="yes")*ISNUMBER(B40:B48),B40:B48)/SUMPRODUCT(($P$12:$P$20="yes")*ISNUMBER(B40:B48)),"n/a") -> 9.1889603 | C54: =IFERROR(SUMPRODUCT(($P$12:$P$20="yes")*ISNUMBER(C40:C48),C40:C48)/SUMPRODUCT(($P$12:$P$20="yes")*ISNUMBER(C40:C48)),"n/a") -> 9.7056385 | D54: =IFERROR(SUMPRODUCT(($P$12:$P$20="yes")*ISNUMBER(D40:D48),D40:D48)/SUMPRODUCT(($P$12:$P$20="yes")*ISNUMBER(D40:D48)),"n/a") -> 1.674575 | E54: =IFERROR(SUMPRODUCT(($Q$12:$Q$20="yes")*ISNUMBER(E40:E48),E40:E48)/SUMPRODUCT(($Q$12:$Q$20="yes")*ISNUMBER(E40:E48)),"n/a") -> 19.4525 | F54: =IFERROR(SUMPRODUCT(($Q$12:$Q$20="yes")*ISNUMBER(F40:F48),F40:F48)/SUMPRODUCT(($Q$12:$Q$20="yes")*ISNUMBER(F40:F48)),"n/a") -> 14.0025 | G54: =IFERROR(SUMPRODUCT(($P$12:$P$20="yes")*ISNUMBER(G40:G48),G40:G48)/SUMPRODUCT(($P$12:$P$20="yes")*ISNUMBER(G40:G48)),"n/a") -> 0.10462076 | H54: =IFERROR(SUMPRODUCT(($P$12:$P$20="yes")*ISNUMBER(H40:H48),H40:H48)/SUMPRODUCT(($P$12:$P$20="yes")*ISNUMBER(H40:H48)),"n/a") -> 2.9254046 | I54: =IFERROR(SUMPRODUCT(($P$12:$P$20="yes")*ISNUMBER(I40:I48),I40:I48)/SUMPRODUCT(($P$12:$P$20="yes")*ISNUMBER(I40:I48)),"n/a") -> 0.17920597
A55: All-peer: number of eligible peers | B55: =SUMPRODUCT(($P$12:$P$20="yes")*ISNUMBER(B40:B48)) -> 6 | C55: =SUMPRODUCT(($P$12:$P$20="yes")*ISNUMBER(C40:C48)) -> 5 | D55: =SUMPRODUCT(($P$12:$P$20="yes")*ISNUMBER(D40:D48)) -> 6 | E55: =SUMPRODUCT(($Q$12:$Q$20="yes")*ISNUMBER(E40:E48)) -> 4 | F55: =SUMPRODUCT(($Q$12:$Q$20="yes")*ISNUMBER(F40:F48)) -> 4 | G55: =SUMPRODUCT(($P$12:$P$20="yes")*ISNUMBER(G40:G48)) -> 5 | H55: =SUMPRODUCT(($P$12:$P$20="yes")*ISNUMBER(H40:H48)) -> 6 | I55: =SUMPRODUCT(($P$12:$P$20="yes")*ISNUMBER(I40:I48)) -> 6
A58: D. Calendarisation to NTM from 16-Oct-2026 (local currency; weights from fiscal year-end dates)
A59: Company | B59: FY1 year end (contains pricing date) | C59: Days from pricing date to FY1 end (incl.) | D59: Weight FY1 | E59: Weight FY2 | F59: EBITDA FY1 (local m) | G59: EBITDA FY2 (local m) | H59: EBITDA NTM (local m) | I59: Revenue FY1 (local m) | J59: Revenue FY2 (local m) | K59: Revenue NTM (local m) | L59: EPS FY1 (local) | M59: EPS FY2 (local) | N59: EPS NTM (local) | O59: Notes
A60: Grupo Bimbo (MXN) | B60: =Inputs_Sources!$D$327 -> 46387 | C60: =B60-Inputs_Sources!$D$6+1 -> 77 | D60: =MIN(1,MAX(0,C60/365)) -> 0.2109589 | E60: =1-D60 -> 0.7890411 | F60: =TearSheet!$H$19 -> 62117 | G60: =TearSheet!$I$19 -> 64891 | H60: =IFERROR(D60*F60+E60*G60,"n/a") -> 64305.8 | I60: =TearSheet!$H$7 -> 426274.7 | J60: =TearSheet!$I$7 -> 445288 | K60: =IFERROR(D60*I60+E60*J60,"n/a") -> 441276.98 | L60: =TearSheet!$H$24 -> 3.07 | M60: =TearSheet!$I$24 -> 3.35 | N60: =IFERROR(D60*L60+E60*M60,"n/a") -> 3.2909315 | O60: FY1 = FY2026E, FY2 = FY2027E (CIQ consensus mean, MXN, 20-Sep-2026)
A61: Flowers Foods, Inc. | B61: =Inputs_Sources!$D$242 -> 46389 | C61: =B61-Inputs_Sources!$D$6+1 -> 79 | D61: =MIN(1,MAX(0,C61/365)) -> 0.21643836 | E61: =1-D61 -> 0.78356164 | F61: =Inputs_Sources!$D$243 -> 458.6 | G61: =Inputs_Sources!$D$245 -> 430.1 | H61: =IFERROR(D61*F61+E61*G61,"n/a") -> 436.26849 | I61: =Inputs_Sources!$D$244 -> 5075.8 | J61: =Inputs_Sources!$D$246 -> 5058.3 | K61: =IFERROR(D61*I61+E61*J61,"n/a") -> 5062.0877 | L61: n/a | M61: n/a | N61: n/a | O61: CIQ consensus in USD; CIQ conversion basis not stated
A62: Gruma, S.A.B. de C.V. | B62: =Inputs_Sources!$D$282 -> 46387 | C62: =B62-Inputs_Sources!$D$6+1 -> 77 | D62: =MIN(1,MAX(0,C62/365)) -> 0.2109589 | E62: =1-D62 -> 0.7890411 | F62: n/a | G62: n/a | H62: =IFERROR(D62*F62+E62*G62,"n/a") -> n/a | I62: n/a | J62: n/a | K62: =IFERROR(D62*I62+E62*J62,"n/a") -> n/a | L62: n/a | M62: n/a | N62: n/a | O62: No EBITDA consensus found (pending)
A63: Yamazaki Baking Co., Ltd. | B63: =Inputs_Sources!$D$247 -> 46387 | C63: =B63-Inputs_Sources!$D$6+1 -> 77 | D63: =MIN(1,MAX(0,C63/365)) -> 0.2109589 | E63: =1-D63 -> 0.7890411 | F63: =Inputs_Sources!$D$248 -> 700.1 | G63: =Inputs_Sources!$D$250 -> 741.5 | H63: =IFERROR(D63*F63+E63*G63,"n/a") -> 732.7663 | I63: =Inputs_Sources!$D$249 -> 8564.4 | J63: =Inputs_Sources!$D$251 -> 8795 | K63: =IFERROR(D63*I63+E63*J63,"n/a") -> 8746.3529 | L63: n/a | M63: n/a | N63: n/a | O63: CIQ consensus in USD; CIQ conversion basis not stated
A64: ARYZTA AG | B64: =Inputs_Sources!$D$252 -> 46387 | C64: =B64-Inputs_Sources!$D$6+1 -> 77 | D64: =MIN(1,MAX(0,C64/365)) -> 0.2109589 | E64: =1-D64 -> 0.7890411 | F64: =Inputs_Sources!$D$253 -> 354.7 | G64: =Inputs_Sources!$D$255 -> 363.6 | H64: =IFERROR(D64*F64+E64*G64,"n/a") -> 361.72247 | I64: =Inputs_Sources!$D$254 -> 2594.7 | J64: =Inputs_Sources!$D$256 -> 2562.6 | K64: =IFERROR(D64*I64+E64*J64,"n/a") -> 2569.3718 | L64: n/a | M64: n/a | N64: n/a | O64: CIQ consensus in USD; CIQ conversion basis not stated
A65: The J. M. Smucker Company | B65: =Inputs_Sources!$D$257 -> 46507 | C65: =B65-Inputs_Sources!$D$6+1 -> 197 | D65: =MIN(1,MAX(0,C65/365)) -> 0.53972603 | E65: =1-D65 -> 0.46027397 | F65: =Inputs_Sources!$D$258 -> 2181.3 | G65: =Inputs_Sources!$D$260 -> 2175.4 | H65: =IFERROR(D65*F65+E65*G65,"n/a") -> 2178.5844 | I65: =Inputs_Sources!$D$259 -> 8930.3 | J65: =Inputs_Sources!$D$261 -> 9037.5 | K65: =IFERROR(D65*I65+E65*J65,"n/a") -> 8979.6414 | L65: n/a | M65: n/a | N65: n/a | O65: CIQ consensus (USD); FY1 for SJM and CPB is FY27E (FY26 closed)
A66: The Campbell's Company | B66: =Inputs_Sources!$D$262 -> 46600 | C66: =B66-Inputs_Sources!$D$6+1 -> 290 | D66: =MIN(1,MAX(0,C66/365)) -> 0.79452055 | E66: =1-D66 -> 0.20547945 | F66: =Inputs_Sources!$D$263 -> 1464.6 | G66: =Inputs_Sources!$D$265 -> 1519.8 | H66: =IFERROR(D66*F66+E66*G66,"n/a") -> 1475.9425 | I66: =Inputs_Sources!$D$264 -> 9496.6 | J66: =Inputs_Sources!$D$266 -> 9469.4 | K66: =IFERROR(D66*I66+E66*J66,"n/a") -> 9491.011 | L66: n/a | M66: n/a | N66: n/a | O66: CIQ consensus (USD); FY1 for SJM and CPB is FY27E (FY26 closed)
A67: Mondelez International, Inc. | B67: =Inputs_Sources!$D$267 -> 46387 | C67: =B67-Inputs_Sources!$D$6+1 -> 77 | D67: =MIN(1,MAX(0,C67/365)) -> 0.2109589 | E67: =1-D67 -> 0.7890411 | F67: =Inputs_Sources!$D$268 -> 6735.2 | G67: =Inputs_Sources!$D$270 -> 7265 | H67: =IFERROR(D67*F67+E67*G67,"n/a") -> 7153.234 | I67: =Inputs_Sources!$D$269 -> 40101.2 | J67: =Inputs_Sources!$D$271 -> 41232.9 | K67: =IFERROR(D67*I67+E67*J67,"n/a") -> 40994.158 | L67: n/a | M67: n/a | N67: n/a | O67: CIQ consensus in USD; CIQ conversion basis not stated
A68: Arca Continental, S.A.B. de C.V. | B68: =Inputs_Sources!$D$272 -> 46387 | C68: =B68-Inputs_Sources!$D$6+1 -> 77 | D68: =MIN(1,MAX(0,C68/365)) -> 0.2109589 | E68: =1-D68 -> 0.7890411 | F68: =Inputs_Sources!$D$273 -> 2930.2 | G68: =Inputs_Sources!$D$275 -> 3006.3 | H68: =IFERROR(D68*F68+E68*G68,"n/a") -> 2990.246 | I68: =Inputs_Sources!$D$274 -> 14453.8 | J68: =Inputs_Sources!$D$276 -> 14628.6 | K68: =IFERROR(D68*I68+E68*J68,"n/a") -> 14591.724 | L68: n/a | M68: n/a | N68: n/a | O68: CIQ consensus in USD; CIQ conversion basis not stated
A69: PepsiCo, Inc. | B69: =Inputs_Sources!$D$277 -> 46387 | C69: =B69-Inputs_Sources!$D$6+1 -> 77 | D69: =MIN(1,MAX(0,C69/365)) -> 0.2109589 | E69: =1-D69 -> 0.7890411 | F69: =Inputs_Sources!$D$278 -> 19050.5 | G69: =Inputs_Sources!$D$280 -> 19587.1 | H69: =IFERROR(D69*F69+E69*G69,"n/a") -> 19473.899 | I69: =Inputs_Sources!$D$279 -> 99300.5 | J69: =Inputs_Sources!$D$281 -> 101773.1 | K69: =IFERROR(D69*I69+E69*J69,"n/a") -> 101251.48 | L69: n/a | M69: n/a | N69: n/a | O69: CIQ consensus in USD; CIQ conversion basis not stated
A72: Memo: Grupo Bimbo on the same claim basis (MXN m unless stated)
A73: Market cap = price x shares (MXN m) | B73: =F11*G11 -> 251681.14
A74: Net debt, claim basis = financial debt + leases + NCI - cash (MXN m) | B74: =N11/H11 -> 171180
A75: Enterprise value, claim basis (MXN m) | B75: =O11/H11 -> 422861.14
A76: LTM EBITDA, company IFRS 16 Adjusted (MXN m) | B76: =J25/H11 -> 60919
A77: LTM EBITDA, model basis = operating income + D&A (MXN m; 35,666 + 24,660) | B77: =Inputs_Sources!$D$20+Inputs_Sources!$D$21 -> 60326
A78: EV/EBITDA LTM, company IFRS 16 basis (x) | B78: =IFERROR(O11/J25,"n/a") -> 6.9413671
A79: EV/EBITDA LTM, model basis EBIT + D&A (x) | B79: =IFERROR(O11/((Inputs_Sources!$D$20+Inputs_Sources!$D$21)*H11),"n/a") -> 7.0096002
A80: EV/EBITDA NTM, calendarised, company IFRS 16 basis (x) | B80: =IFERROR(O11/L25,"n/a") -> 6.5757854

Sheet Inputs_Sources
A1: Inputs and sources: every number used in PeerAnalysis and Checks
A2: Tags: sourced (filing or CIQ), guidance, assumption, calc, unverified, pending (not found: shown as n/a). Blue = hard-coded input.
A4: Key | B4: Entity | C4: Item | D4: Value | E4: Unit | F4: Currency | G4: Tag | H4: Source (document, section/metric/period, URL) | I4: As-of | J4: Note
A5: A. General
A6: pricing_date | B6: All | C6: Pricing / valuation date | D6: 46311 | E6: date | G6: sourced | H6: CIQ pricing 15/16-Oct-2026 (data/capitaliq/capiq-ai-prompt1_2026-10-16.md) | I6: 2026-10-16
A7: fx_cic_jpy | B7: All | C7: CIQ conversion JPY to USD (Yamazaki LTM figures) | D7: 0.006482 | E7: USD per JPY | F7: USD | G7: sourced | H7: data/capitaliq/capiq-ai-prompt1_2026-10-16.md Task 1A (market data, LTM balance sheet) note: TSE:2212 converted at 0.006482 USD/JPY | I7: 2026-10-16
A8: fx_cic_eur | B8: All | C8: CIQ conversion EUR to USD (Aryzta) | D8: 1.166559 | E8: USD per EUR | F8: USD | G8: sourced | H8: data/capitaliq/capiq-ai-prompt1_2026-10-16.md Task 1A (market data, LTM balance sheet) note: ARYN converted at 1.166559 USD/EUR | I8: 2026-10-16
A9: fx_cic_mxn_old | B9: All | C9: CIQ note MXN to USD (memo: implies 17.96 MXN/USD, not used) | D9: 0.05569 | E9: USD per MXN | F9: USD | G9: sourced | H9: data/capitaliq/capiq-ai-prompt1_2026-10-16.md Task 1A (market data, LTM balance sheet) note: AC converted at 0.055690; inconsistent with the 17.46 spot used for market values (see Checks) | I9: 2026-10-16
A10: fx_mxn_spot | B10: All | C10: MXN per USD, spot used for all MXN market values (Bimbo display, Gruma and Arca prices) | D10: 17.46 | E10: MXN per USD | F10: MXN | G10: calc | H10: wiki/Valuation/bimbo-consensus-dashboard-capiq-2026-10.md section 1: Ps. 17.46 per US$ (CIQ Oct-2026 spot implied) | I10: 2026-10-17 | J10: Single spot for market values; balance-sheet and LTM figures are taken in USD from the filings or CIQ
A11: fx_bmv_disp | B11: Grupo Bimbo | C11: MXN per USD used for USD display of Bimbo | D11: 17.46 | E11: MXN per USD | F11: MXN | G11: calc | H11: Same spot as above (17.46) | I11: 2026-10-17 | J11: Display only: Bimbo multiples are computed in MXN and do not depend on this rate
A12: B. Grupo Bimbo market data and balance sheet (MXN m unless stated)
A13: bmv_price | B13: Grupo Bimbo | C13: Share price (BMV:BIMBO A), MXN | D13: 58.6 | E13: MXN per share | F13: MXN | G13: unverified | H13: Coordinator-supplied price MXN 58.60 (BMV close per coordinator message, 17-Oct-2026); not independently verified in this session. Supersedes the derived 55.35 placeholder (US$3.1701 x 17.46) | I13: 2026-10-16 | J13: Confirm against the BMV close before the report; MXN 1 per share = about 0.07x on EV/EBITDA
A14: bmv_shares | B14: Grupo Bimbo | C14: Shares outstanding (coordinator-supplied) | D14: 4294.9 | E14: m shares | F14: shares | G14: unverified | H14: Coordinator-supplied 4,294.9m (market cap MXN 251,684m = 58.60 x 4,294.9m). CIQ balance sheet 2026 FQ2 shows 4,296.3m (filing 2026-07-24) | I14: 2026-07-24 | J14: Difference to CIQ 2Q26 is 0.03%; dashboard register 4,304.7m is 0.2% higher
A15: bmv_td | B15: Grupo Bimbo | C15: Total debt incl. IFRS 16 leases, 30-Jun-2026 | D15: 189679.4 | E15: MXN m | F15: MXN | G15: sourced | H15: data/capitaliq/balance_sheet.csv 'Total Debt' 2026 FQ2 (= long-term debt 150,019.5 + current portion 6,299.0 + leases 33,361) | I15: 2026-06-30 | J15: CIQ basis; company ex-IFRS 16 total debt is 153,663 (wiki/Valuation/bimbo-capital-structure-and-debt.md)
A16: bmv_cash | B16: Grupo Bimbo | C16: Cash, 30-Jun-2026 (claim basis) | D16: 16563 | E16: MXN m | F16: MXN | G16: sourced | H16: data/capitaliq/balance_sheet.csv 'Cash & Short-term Investments' 2026 FQ2 (company ~16.6bn; coordinator value 16,563) | I16: 2026-06-30
A17: bmv_nci | B17: Grupo Bimbo | C17: Non-controlling interest at book, 30-Jun-2026 (claim basis) | D17: 722 | E17: MXN m | F17: MXN | G17: sourced | H17: Company 2Q26 p.8: NCI 722 (CIQ 721.7); coordinator value 722. Book value understates the economic claim if IO profit is attributed to NCI (see Checks) | I17: 2026-06-30
A18: bmv_fin_debt | B18: Grupo Bimbo | C18: Financial debt excluding leases, 30-Jun-2026 (claim basis) | D18: 153660 | E18: MXN m | F18: MXN | G18: sourced | H18: Company total debt 153,660 (coordinator; wiki/Valuation/bimbo-capital-structure-and-debt.md: 153,663 at Jun-26) | I18: 2026-06-30 | J18: CIQ financial debt is 156,319 (LTD 150,019.5 + CPLTD 6,299.0); the 2,659 difference is not added
A19: bmv_leases | B19: Grupo Bimbo | C19: IFRS 16 lease liabilities, 30-Jun-2026 (claim basis) | D19: 33361 | E19: MXN m | F19: MXN | G19: sourced | H19: data/capitaliq/balance_sheet.csv 'Current Portion of Leases' 7,112.9 + 'Long-term Leases' 26,248.0 (2026 FQ2) | I19: 2026-06-30
A20: bmv_ltm_ebit | B20: Grupo Bimbo | C20: Operating income, LTM to 30-Jun-2026 (model basis) | D20: 35666 | E20: MXN m | F20: MXN | G20: sourced | H20: BMV Jun-26 p.27 via wiki/Financials/bimbo-quarterly-trend-4q21-2q26.md line 62 | I20: 2026-06-30
A21: bmv_ltm_da | B21: Grupo Bimbo | C21: D&A, LTM to 30-Jun-2026 (model basis; includes IFRS 16 right-of-use depreciation) | D21: 24660 | E21: MXN m | F21: MXN | G21: sourced | H21: BMV Jun-26 p.27 via wiki/Financials/bimbo-quarterly-trend-4q21-2q26.md line 62 | I21: 2026-06-30
A22: bmv_lease_cur | B22: Grupo Bimbo | C22: IFRS 16 lease liabilities, current (memo) | D22: 7112.9 | E22: MXN m | F22: MXN | G22: sourced | H22: data/capitaliq/balance_sheet.csv 'Current Portion of Leases' 2026 FQ2 | I22: 2026-06-30
A23: bmv_lease_nc | B23: Grupo Bimbo | C23: IFRS 16 lease liabilities, non-current (memo) | D23: 26248 | E23: MXN m | F23: MXN | G23: sourced | H23: data/capitaliq/balance_sheet.csv 'Long-term Leases' 2026 FQ2 | I23: 2026-06-30
A24: bmv_netdebt_co | B24: Grupo Bimbo | C24: Company net debt ex-IFRS 16, 30-Jun-2026 (memo) | D24: 137100 | E24: MXN m | F24: MXN | G24: sourced | H24: 2Q26 release p.6 via wiki/Valuation/bimbo-capital-structure-and-debt.md (137.1bn; excludes leases) | I24: 2026-06-30 | J24: Not used for EV: excludes IFRS 16 leases while EBITDA is IFRS 16
A25: bmv_ebitda_3Q25 | B25: Grupo Bimbo | C25: Adj. EBITDA (IFRS 16), quarter 3Q25 | D25: 15776 | E25: MXN m | F25: MXN | G25: sourced | H25: Company quarterly release via wiki/Financials/bimbo-quarterly-trend-4q21-2q26.md; wiki/Financials/bimbo-balance-sheet-and-leverage.md line 83 | I25: 2026-06-30
A26: bmv_ebitda_4Q25 | B26: Grupo Bimbo | C26: Adj. EBITDA (IFRS 16), quarter 4Q25 | D26: 15994 | E26: MXN m | F26: MXN | G26: sourced | H26: Company quarterly release via wiki/Financials/bimbo-quarterly-trend-4q21-2q26.md; wiki/Financials/bimbo-balance-sheet-and-leverage.md line 83 | I26: 2026-06-30
A27: bmv_ebitda_1Q26 | B27: Grupo Bimbo | C27: Adj. EBITDA (IFRS 16), quarter 1Q26 | D27: 14036 | E27: MXN m | F27: MXN | G27: sourced | H27: Company quarterly release via wiki/Financials/bimbo-quarterly-trend-4q21-2q26.md; wiki/Financials/bimbo-balance-sheet-and-leverage.md line 83 | I27: 2026-06-30
A28: bmv_ebitda_2Q26 | B28: Grupo Bimbo | C28: Adj. EBITDA (IFRS 16), quarter 2Q26 | D28: 15113 | E28: MXN m | F28: MXN | G28: sourced | H28: Company quarterly release via wiki/Financials/bimbo-quarterly-trend-4q21-2q26.md; wiki/Financials/bimbo-balance-sheet-and-leverage.md line 83 | I28: 2026-06-30
A29: bmv_rev_ltm | B29: Grupo Bimbo | C29: Net sales, LTM to 30-Jun-2026 | D29: 421423 | E29: MXN m | F29: MXN | G29: sourced | H29: BMV Jun-26 p.27 via wiki/Financials/bimbo-quarterly-trend-4q21-2q26.md line 62 (CIQ quarterly sum 421,435 differs by 0.1%) | I29: 2026-06-30
A30: bmv_eps_3Q25 | B30: Grupo Bimbo | C30: Normalized diluted EPS, quarter 3Q25 | D30: 0.782 | E30: MXN per share | F30: MXN | G30: sourced | H30: data/capitaliq/income_statement.csv 'Normalized Diluted EPS' 3Q25 | I30: 2026-06-30
A31: bmv_eps_4Q25 | B31: Grupo Bimbo | C31: Normalized diluted EPS, quarter 4Q25 | D31: 0.866 | E31: MXN per share | F31: MXN | G31: sourced | H31: data/capitaliq/income_statement.csv 'Normalized Diluted EPS' 4Q25 | I31: 2026-06-30
A32: bmv_eps_1Q26 | B32: Grupo Bimbo | C32: Normalized diluted EPS, quarter 1Q26 | D32: 0.853 | E32: MXN per share | F32: MXN | G32: sourced | H32: data/capitaliq/income_statement.csv 'Normalized Diluted EPS' 1Q26 | I32: 2026-06-30
A33: bmv_eps_2Q26 | B33: Grupo Bimbo | C33: Normalized diluted EPS, quarter 2Q26 | D33: 0.674 | E33: MXN per share | F33: MXN | G33: sourced | H33: data/capitaliq/income_statement.csv 'Normalized Diluted EPS' 2Q26 | I33: 2026-06-30
A34: bmv_gp_ltm | B34: Grupo Bimbo | C34: Gross profit, LTM to 30-Jun-2026 (CIQ basis) | D34: 221490.26 | E34: MXN m | F34: MXN | G34: sourced | H34: data/capitaliq/income_statement.csv 'Gross Profit', 3Q25 to 2Q26 (sum of quarters, MXN thousands / 1,000) | I34: 2026-06-30
A35: bmv_lfcf_ltm | B35: Grupo Bimbo | C35: Levered free cash flow, LTM to 30-Jun-2026 (CIQ basis) | D35: 25433.349 | E35: MXN m | F35: MXN | G35: sourced | H35: data/capitaliq/cash_flow.csv 'Levered Free Cash Flow', 3Q25 to 2Q26 (sum of quarters, MXN thousands / 1,000) | I35: 2026-06-30
A36: C. Peers: market data, net debt, LTM and history (USD m unless stated)
A37: FLO.mc | B37: Flowers Foods, Inc. | C37: Market capitalisation (CIQ, LTM date) | D37: 1295.7 | E37: USD m | F37: USD | G37: sourced | H37: data/capitaliq/capiq-ai-prompt1_2026-10-16.md Task 1A (market data, LTM balance sheet) | I37: 2026-10-16
A38: FLO.shares | B38: Flowers Foods, Inc. | C38: Diluted shares (CIQ) | D38: 212.1 | E38: m shares | F38: shares | G38: sourced | H38: data/capitaliq/capiq-ai-prompt1_2026-10-16.md Task 1A (market data, LTM balance sheet) | I38: 2026-10-16
A39: FLO.ev_ciq | B39: Flowers Foods, Inc. | C39: Enterprise value (CIQ table) | D39: 3250.7 | E39: USD m | F39: USD | G39: sourced | H39: data/capitaliq/capiq-ai-prompt1_2026-10-16.md Task 1A (market data, LTM balance sheet) | I39: 2026-10-16
A40: FLO.nci_filings | B40: Flowers Foods, Inc. | C40: NCI and redeemable NCI from filings (memo, USD m) | D40: 0 | E40: USD m | F40: USD | G40: sourced | H40: SEC XBRL MinorityInterest and balance sheet (research: see Checks section 1) | I40: 2026-10-16 | J40: 0.0 (no NCI)
A41: FLO.nd | B41: Flowers Foods, Inc. | C41: Net debt incl. leases (USD m) | D41: 1955 | E41: USD m | F41: USD | G41: sourced | H41: data/capitaliq/capiq-ai-prompt1_2026-10-16.md Task 1A (market data, LTM balance sheet) | I41: 2026-10-16
A42: FLO.ebitda_ltm | B42: Flowers Foods, Inc. | C42: EBITDA, LTM (reported basis, USD m) | D42: 486.9 | E42: USD m | F42: USD | G42: sourced | H42: data/capitaliq/capiq-ai-prompt1_2026-10-16.md Task 1A (market data, LTM balance sheet) | I42: 2026-10-16
A43: FLO.rev_ltm | B43: Flowers Foods, Inc. | C43: Revenue, LTM (USD m) | D43: 5223.9 | E43: USD m | F43: USD | G43: sourced | H43: data/capitaliq/capiq-ai-prompt1_2026-10-16.md Task 2B (revenue, levered FCF, consensus) | I43: 2026-10-16
A44: FLO.rev_fy24 | B44: Flowers Foods, Inc. | C44: Revenue, FY2024 (fiscal label per CIQ / company) | D44: 5103.5 | E44: USD m | F44: USD | G44: sourced | H44: data/capitaliq/capiq-ai-prompt1_2026-10-16.md Task 2B (revenue, levered FCF, consensus) | I44: FY2024
A45: FLO.rev_fy25 | B45: Flowers Foods, Inc. | C45: Revenue, FY2025 (fiscal label per CIQ / company) | D45: 5256.5 | E45: USD m | F45: USD | G45: sourced | H45: data/capitaliq/capiq-ai-prompt1_2026-10-16.md Task 2B (revenue, levered FCF, consensus) | I45: FY2025
A46: FLO.ebitda_fy24 | B46: Flowers Foods, Inc. | C46: EBITDA, FY2024 (reported basis) | D46: 520.7 | E46: USD m | F46: USD | G46: sourced | H46: data/capitaliq/capiq-ai-prompt1_2026-10-16.md Task 1B (annual leverage history, EBITDA) | I46: FY2024
A47: FLO.ebitda_fy25 | B47: Flowers Foods, Inc. | C47: EBITDA, FY2025 (reported basis) | D47: 514.8 | E47: USD m | F47: USD | G47: sourced | H47: data/capitaliq/capiq-ai-prompt1_2026-10-16.md Task 1B (annual leverage history, EBITDA) | I47: FY2025
A48: FLO.gp_ltm | B48: Flowers Foods, Inc. | C48: Gross profit, LTM (USD m) | D48: n/a | E48: USD m | F48: USD | G48: pending | H48: Not in the CIQ pull; SEC research did not find it | I48: 2026-10-16
A49: FLO.lfcf_ltm | B49: Flowers Foods, Inc. | C49: Levered free cash flow, LTM (CIQ basis) | D49: 298.5 | E49: USD m | F49: USD | G49: sourced | H49: data/capitaliq/capiq-ai-prompt1_2026-10-16.md Task 2B (revenue, levered FCF, consensus) | I49: 2026-10-16
A50: FLO.pe_ltm | B50: Flowers Foods, Inc. | C50: P/E LTM (CIQ multiples tool) | D50: 23.45 | E50: x | G50: sourced | H50: data/capitaliq/capiq-ai-prompt1_2026-10-16.md Task 2A (CIQ multiples tool) | I50: 2026-10-16
A51: FLO.pe_ntm | B51: Flowers Foods, Inc. | C51: P/E NTM (CIQ multiples tool) | D51: 8.93 | E51: x | G51: sourced | H51: data/capitaliq/capiq-ai-prompt1_2026-10-16.md Task 2A (CIQ multiples tool) | I51: 2026-10-16 | J51: Tool value; EPS NTM is derived as price / this P/E [calc]
A52: FLO.ev_ebitda_ltm_tool | B52: Flowers Foods, Inc. | C52: EV/EBITDA LTM, CIQ multiples tool (audit only) | D52: 5.15 | E52: x | G52: sourced | H52: data/capitaliq/capiq-ai-prompt1_2026-10-16.md Task 2A (CIQ multiples tool) | I52: 2026-10-16 | J52: Not used: tool EV differs from the table EV (wiki discrepancy #7)
A53: FLO.ev_ebitda_ntm_tool | B53: Flowers Foods, Inc. | C53: EV/EBITDA NTM, CIQ multiples tool (audit only) | D53: 7.55 | E53: x | G53: sourced | H53: data/capitaliq/capiq-ai-prompt1_2026-10-16.md Task 2A (CIQ multiples tool) | I53: 2026-10-16 | J53: Audit only
A54: GRUMA.price_local | B54: Gruma, S.A.B. de C.V. | C54: Share price, local currency (pricing date) | D54: 242.02 | E54: MXN per share | F54: MXN | G54: unverified | H54: Delayed quote (Yahoo Finance 16-Oct-2026 1:59 PM CST); no official BMV close found | I54: 2026-10-16 | J54: Delayed quote (Yahoo Finance, 16-Oct-2026 1:59 PM CST); StockAnalysis 242.71; no official BMV close found
A55: GRUMA.shares | B55: Gruma, S.A.B. de C.V. | C55: Shares outstanding | D55: 336.20799 | E55: m shares | F55: shares | G55: sourced | H55: Company filings (see note) | I55: 2026-06-30 | J55: Outstanding Series B shares at 30-Jun-2026 (2Q26 BMV report p.53); treasury 6,463,051 excluded
A56: GRUMA.fx | B56: Gruma, S.A.B. de C.V. | C56: Local currency to USD for market values | D56: 0.057273769 | E56: USD per MXN | F56: USD | G56: calc | H56: Local to USD rate (see note) | I56: 2026-10-17 | J56: MXN per USD 17.46 = CIQ consensus dashboard spot (Oct-2026); CIQ's 0.055690 (17.96) is not used
A57: GRUMA.nci_usd | B57: Gruma, S.A.B. de C.V. | C57: Non-controlling interest, USD m (filings) | D57: 2.8 | E57: USD m | F57: USD | G57: sourced | H57: Company filings (see note) | I57: 2026-06-30 | J57: Non-controlling interest 30-Jun-2026, USD m (2Q26 BMV report p.20)
A58: GRUMA.nd | B58: Gruma, S.A.B. de C.V. | C58: Net debt incl. leases (USD m) | D58: 1628.2 | E58: USD m | F58: USD | G58: calc | H58: Calc from Gruma 2Q26 BMV report (USD): total debt incl. leases 2,111.8 (ST 365.2 p.35; LT 1,333.4 p.20; leases 413.2 p.19-20) less cash 483.6 (p.19) | I58: 2026-06-30 | J58: Calc: total debt incl. leases 2,111.8 (ST bank loans 365.2 + LT debt 1,333.4 + leases 413.2, carrying; 2Q26 report p.19-20, p.35) less cash 483.6 (p.19)
A59: GRUMA.ebitda_ltm | B59: Gruma, S.A.B. de C.V. | C59: EBITDA, LTM (reported basis, USD m) | D59: 1108.9 | E59: USD m | F59: USD | G59: calc | H59: Calc from Gruma FY25 release (S3 p.11, EBITDA 1,136.0) + 1H26 538.5 - 1H25 565.6 (2Q26 BMV report p.12 and p.33) | I59: 2026-06-30 | J59: Calc: FY25 1,136.0 + 1H26 538.5 - 1H25 565.6 (company EBITDA = operating income + D&A + impairment, before lease costs under IFRS 16)
A60: GRUMA.rev_ltm | B60: Gruma, S.A.B. de C.V. | C60: Revenue, LTM (USD m) | D60: 6500.1 | E60: USD m | F60: USD | G60: calc | H60: Calc from Gruma FY25 release (S3 p.11, net sales 6,374.6) + 1H26 3,274.7 - 1H25 3,149.2 (2Q26 BMV report p.34 cross-check 6,500.057) | I60: 2026-06-30
A61: GRUMA.rev_fy24 | B61: Gruma, S.A.B. de C.V. | C61: Revenue, FY2024 (fiscal label per CIQ / company) | D61: 6486.9 | E61: USD m | F61: USD | G61: sourced | H61: Gruma FY25 release, FY24 comparative (S3 p.11) | I61: FY2024
A62: GRUMA.rev_fy25 | B62: Gruma, S.A.B. de C.V. | C62: Revenue, FY2025 (fiscal label per CIQ / company) | D62: 6374.6 | E62: USD m | F62: USD | G62: sourced | H62: Gruma FY25 release (S3 p.11) | I62: FY2025
A63: GRUMA.ebitda_fy24 | B63: Gruma, S.A.B. de C.V. | C63: EBITDA, FY2024 (reported basis) | D63: 1131.1 | E63: USD m | F63: USD | G63: sourced | H63: Gruma FY25 release, FY24 comparative (S3 p.11) EBITDA UAFIRDA | I63: FY2024
A64: GRUMA.ebitda_fy25 | B64: Gruma, S.A.B. de C.V. | C64: EBITDA, FY2025 (reported basis) | D64: 1136 | E64: USD m | F64: USD | G64: sourced | H64: Gruma FY25 release (S3 p.11) EBITDA UAFIRDA | I64: FY2025
A65: GRUMA.gp_ltm | B65: Gruma, S.A.B. de C.V. | C65: Gross profit, LTM (USD m) | D65: 2522.2 | E65: USD m | F65: USD | G65: sourced | H65: Calc from Gruma FY25 gross profit 2,492.7 (S3 p.11) + 1H26 1,276.1 - 1H25 1,246.6 (S1 p.12) | I65: 2026-06-30
A66: GRUMA.lfcf_ltm | B66: Gruma, S.A.B. de C.V. | C66: Levered free cash flow, LTM (CIQ basis) | D66: n/a | E66: USD m | F66: USD | G66: pending | H66: Not retrieved (pending) | I66: 2026-10-16
A67: GRUMA.pe_ltm | B67: Gruma, S.A.B. de C.V. | C67: P/E LTM (CIQ multiples tool) | D67: n/a | E67: x | G67: pending | H67: not in CIQ pull | I67: 2026-10-16
A68: GRUMA.pe_ntm | B68: Gruma, S.A.B. de C.V. | C68: P/E NTM (CIQ multiples tool) | D68: n/a | E68: x | G68: pending | H68: not in CIQ pull | I68: 2026-10-16 | J68: Tool value; EPS NTM is derived as price / this P/E [calc]
A69: GRUMA.ev_ebitda_ltm_tool | B69: Gruma, S.A.B. de C.V. | C69: EV/EBITDA LTM, CIQ multiples tool (audit only) | D69: n/a | E69: x | G69: sourced | H69: not in CIQ pull | I69: 2026-10-16 | J69: Not used: tool EV differs from the table EV (wiki discrepancy #7)
A70: GRUMA.ev_ebitda_ntm_tool | B70: Gruma, S.A.B. de C.V. | C70: EV/EBITDA NTM, CIQ multiples tool (audit only) | D70: n/a | E70: x | G70: sourced | H70: not in CIQ pull | I70: 2026-10-16 | J70: Audit only
A71: YMZ.price_local | B71: Yamazaki Baking Co., Ltd. | C71: Share price, local currency (pricing date) | D71: 3816 | E71: JPY per share | F71: JPY | G71: unverified | H71: Aggregator quote (see note); official exchange close not found | I71: 2026-10-16 | J71: TSE Prime close 16-Oct-2026 (Yahoo Finance Japan history, aggregator, not JPX primary)
A72: YMZ.shares | B72: Yamazaki Baking Co., Ltd. | C72: Shares outstanding | D72: n/a | E72: m shares | F72: shares | G72: pending | H72: Public source (research did not find it) | I72: 2026-06-30 | J72: Not found
A73: YMZ.fx | B73: Yamazaki Baking Co., Ltd. | C73: Local currency to USD for market values | D73: 0.006482 | E73: USD per JPY | F73: USD | G73: calc | H73: Local to USD rate (see note) | I73: 2026-10-17 | J73: CIQ conversion 0.006482 USD per JPY
A74: YMZ.nci_usd | B74: Yamazaki Baking Co., Ltd. | C74: Non-controlling interest, USD m (filings) | D74: n/a | E74: USD m | F74: USD | G74: pending | H74: Not found in research | I74: 2026-06-30 | J74: Not found
A75: YMZ.nd | B75: Yamazaki Baking Co., Ltd. | C75: Net debt incl. leases (USD m) | D75: -473.5 | E75: USD m | F75: USD | G75: sourced | H75: data/capitaliq/capiq-ai-prompt1_2026-10-16.md Task 1A (market data, LTM balance sheet) | I75: 2026-10-16
A76: YMZ.ebitda_ltm | B76: Yamazaki Baking Co., Ltd. | C76: EBITDA, LTM (reported basis, USD m) | D76: 706.7 | E76: USD m | F76: USD | G76: sourced | H76: data/capitaliq/capiq-ai-prompt1_2026-10-16.md Task 1A (market data, LTM balance sheet) | I76: 2026-10-16
A77: YMZ.rev_ltm | B77: Yamazaki Baking Co., Ltd. | C77: Revenue, LTM (USD m) | D77: 8669.9 | E77: USD m | F77: USD | G77: sourced | H77: data/capitaliq/capiq-ai-prompt1_2026-10-16.md Task 2B (revenue, levered FCF, consensus) | I77: 2026-10-16
A78: YMZ.rev_fy24 | B78: Yamazaki Baking Co., Ltd. | C78: Revenue, FY2024 (fiscal label per CIQ / company) | D78: 8224.6 | E78: USD m | F78: USD | G78: sourced | H78: data/capitaliq/capiq-ai-prompt1_2026-10-16.md Task 2B (revenue, levered FCF, consensus) | I78: FY2024
A79: YMZ.rev_fy25 | B79: Yamazaki Baking Co., Ltd. | C79: Revenue, FY2025 (fiscal label per CIQ / company) | D79: n/a | E79: USD m | F79: USD | G79: unverified | H79: data/capitaliq/capiq-ai-prompt1_2026-10-16.md Task 2B (revenue, levered FCF, consensus) | I79: FY2025 | J79: Not used: CIQ value equals the FY2021 figure (wiki discrepancy #11)
A80: YMZ.ebitda_fy24 | B80: Yamazaki Baking Co., Ltd. | C80: EBITDA, FY2024 (reported basis) | D80: 630.3 | E80: USD m | F80: USD | G80: sourced | H80: data/capitaliq/capiq-ai-prompt1_2026-10-16.md Task 1B (annual leverage history, EBITDA) | I80: FY2024
A81: YMZ.ebitda_fy25 | B81: Yamazaki Baking Co., Ltd. | C81: EBITDA, FY2025 (reported basis) | D81: 712 | E81: USD m | F81: USD | G81: sourced | H81: data/capitaliq/capiq-ai-prompt1_2026-10-16.md Task 1B (annual leverage history, EBITDA) | I81: FY2025
A82: YMZ.gp_ltm | B82: Yamazaki Baking Co., Ltd. | C82: Gross profit, LTM (USD m) | D82: n/a | E82: USD m | F82: USD | G82: pending | H82: Not in the CIQ pull | I82: 2026-10-16
A83: YMZ.lfcf_ltm | B83: Yamazaki Baking Co., Ltd. | C83: Levered free cash flow, LTM (CIQ basis) | D83: 113.4 | E83: USD m | F83: USD | G83: sourced | H83: data/capitaliq/capiq-ai-prompt1_2026-10-16.md Task 2B (revenue, levered FCF, consensus) | I83: 2026-10-16
A84: YMZ.pe_ltm | B84: Yamazaki Baking Co., Ltd. | C84: P/E LTM (CIQ multiples tool) | D84: 17.74 | E84: x | G84: sourced | H84: data/capitaliq/capiq-ai-prompt1_2026-10-16.md Task 2A (CIQ multiples tool) | I84: 2026-10-16
A85: YMZ.pe_ntm | B85: Yamazaki Baking Co., Ltd. | C85: P/E NTM (CIQ multiples tool) | D85: 16.84 | E85: x | G85: sourced | H85: data/capitaliq/capiq-ai-prompt1_2026-10-16.md Task 2A (CIQ multiples tool) | I85: 2026-10-16 | J85: Tool value; EPS NTM is derived as price / this P/E [calc]
A86: YMZ.ev_ebitda_ltm_tool | B86: Yamazaki Baking Co., Ltd. | C86: EV/EBITDA LTM, CIQ multiples tool (audit only) | D86: 6.58 | E86: x | G86: sourced | H86: data/capitaliq/capiq-ai-prompt1_2026-10-16.md Task 2A (CIQ multiples tool) | I86: 2026-10-16 | J86: Not used: tool EV differs from the table EV (wiki discrepancy #7)
A87: YMZ.ev_ebitda_ntm_tool | B87: Yamazaki Baking Co., Ltd. | C87: EV/EBITDA NTM, CIQ multiples tool (audit only) | D87: 6.37 | E87: x | G87: sourced | H87: data/capitaliq/capiq-ai-prompt1_2026-10-16.md Task 2A (CIQ multiples tool) | I87: 2026-10-16 | J87: Audit only
A88: ARYN.mc | B88: ARYZTA AG | C88: Market capitalisation (CIQ, LTM date) | D88: 1218.8 | E88: USD m | F88: USD | G88: sourced | H88: data/capitaliq/capiq-ai-prompt1_2026-10-16.md Task 1A (market data, LTM balance sheet) | I88: 2026-10-16
A89: ARYN.shares | B89: ARYZTA AG | C89: Diluted shares (CIQ) | D89: 24.8 | E89: m shares | F89: shares | G89: sourced | H89: data/capitaliq/capiq-ai-prompt1_2026-10-16.md Task 1A (market data, LTM balance sheet) | I89: 2026-10-16 | J89: CIQ share count 24.8m not verified (Aryzta H1-26 report not read)
A90: ARYN.ev_ciq | B90: ARYZTA AG | C90: Enterprise value (CIQ table) | D90: 2103.3 | E90: USD m | F90: USD | G90: sourced | H90: data/capitaliq/capiq-ai-prompt1_2026-10-16.md Task 1A (market data, LTM balance sheet) | I90: 2026-10-16
A91: ARYN.nci_filings | B91: ARYZTA AG | C91: NCI and redeemable NCI from filings (memo, USD m) | D91: n/a | E91: USD m | F91: USD | G91: pending | H91: SEC XBRL MinorityInterest and balance sheet (research: see Checks section 1) | I91: 2026-10-16 | J91: CIQ residual -17.4 unexplained (NCI not found in research)
A92: ARYN.nd | B92: ARYZTA AG | C92: Net debt incl. leases (USD m) | D92: 901.9 | E92: USD m | F92: USD | G92: sourced | H92: data/capitaliq/capiq-ai-prompt1_2026-10-16.md Task 1A (market data, LTM balance sheet) | I92: 2026-10-16
A93: ARYN.ebitda_ltm | B93: ARYZTA AG | C93: EBITDA, LTM (reported basis, USD m) | D93: 252.4 | E93: USD m | F93: USD | G93: sourced | H93: data/capitaliq/capiq-ai-prompt1_2026-10-16.md Task 1A (market data, LTM balance sheet) | I93: 2026-10-16
A94: ARYN.rev_ltm | B94: ARYZTA AG | C94: Revenue, LTM (USD m) | D94: 2567.4 | E94: USD m | F94: USD | G94: sourced | H94: data/capitaliq/capiq-ai-prompt1_2026-10-16.md Task 2B (revenue, levered FCF, consensus) | I94: 2026-10-16
A95: ARYN.rev_fy24 | B95: ARYZTA AG | C95: Revenue, FY2024 (fiscal label per CIQ / company) | D95: 2374.1 | E95: USD m | F95: USD | G95: sourced | H95: data/capitaliq/capiq-ai-prompt1_2026-10-16.md Task 2B (revenue, levered FCF, consensus) | I95: FY2024
A96: ARYN.rev_fy25 | B96: ARYZTA AG | C96: Revenue, FY2025 (fiscal label per CIQ / company) | D96: 2513.7 | E96: USD m | F96: USD | G96: sourced | H96: data/capitaliq/capiq-ai-prompt1_2026-10-16.md Task 2B (revenue, levered FCF, consensus) | I96: FY2025
A97: ARYN.ebitda_fy24 | B97: ARYZTA AG | C97: EBITDA, FY2024 (reported basis) | D97: 295.3 | E97: USD m | F97: USD | G97: sourced | H97: data/capitaliq/capiq-ai-prompt1_2026-10-16.md Task 1B (annual leverage history, EBITDA) | I97: FY2024
A98: ARYN.ebitda_fy25 | B98: ARYZTA AG | C98: EBITDA, FY2025 (reported basis) | D98: 287.4 | E98: USD m | F98: USD | G98: sourced | H98: data/capitaliq/capiq-ai-prompt1_2026-10-16.md Task 1B (annual leverage history, EBITDA) | I98: FY2025
A99: ARYN.gp_ltm | B99: ARYZTA AG | C99: Gross profit, LTM (USD m) | D99: n/a | E99: USD m | F99: USD | G99: pending | H99: Not in the CIQ pull | I99: 2026-10-16
A100: ARYN.lfcf_ltm | B100: ARYZTA AG | C100: Levered free cash flow, LTM (CIQ basis) | D100: 138.1 | E100: USD m | F100: USD | G100: sourced | H100: data/capitaliq/capiq-ai-prompt1_2026-10-16.md Task 2B (revenue, levered FCF, consensus) | I100: 2026-10-16
A101: ARYN.pe_ltm | B101: ARYZTA AG | C101: P/E LTM (CIQ multiples tool) | D101: 10.21 | E101: x | G101: sourced | H101: data/capitaliq/capiq-ai-prompt1_2026-10-16.md Task 2A (CIQ multiples tool) | I101: 2026-10-16
...

Sheet Checks
A1: Checks (formulas; flags shown as FLAG when a test fails)
A3: 1. Enterprise value: CIQ table EV vs our EV on the claim basis (CIQ-quoted peers)
A4: Company | B4: CIQ EV (USD m) | C4: Our EV, claim basis (USD m) | D4: Difference | E4: Difference % of CIQ EV | F4: Flag (>0.5%) | G4: Explanation
A5: Flowers Foods, Inc. | B5: =Inputs_Sources!$D$39 -> 3250.7 | C5: =PeerAnalysis!O12 -> 3246.236 | D5: =C5-B5 -> -4.464 | E5: =IFERROR(D5/B5,"n/a") -> -0.0013732427 | F5: =IF(ABS(E5)>0.005,"FLAG","ok") -> ok | G5: Components 2,003.3 (debt 1,686.2 + operating leases 317.1) vs CIQ total debt 2,007.8: 4.5 unreconciled; NCI nil
A6: The J. M. Smucker Company | B6: =Inputs_Sources!$D$107 -> 20509.5 | C6: =PeerAnalysis!O16 -> 20509.5 | D6: =C6-B6 -> 0 | E6: =IFERROR(D6/B6,"n/a") -> 0 | F6: =IF(ABS(E6)>0.005,"FLAG","ok") -> ok | G6: Exact: financial debt + finance leases + operating leases - cash = CIQ net debt
A7: The Campbell's Company | B7: =Inputs_Sources!$D$124 -> 13287.9 | C7: =PeerAnalysis!O17 -> 13287.9 | D7: =C7-B7 -> 0 | E7: =IFERROR(D7/B7,"n/a") -> 0 | F7: =IF(ABS(E7)>0.005,"FLAG","ok") -> ok | G7: Exact: redeemable NCI 304 + NCI 2 is the CIQ residual of 306
A8: Mondelez International, Inc. | B8: =Inputs_Sources!$D$141 -> 101964.8 | C8: =PeerAnalysis!O18 -> 101964.8 | D8: =C8-B8 -> 0 | E8: =IFERROR(D8/B8,"n/a") -> 0 | F8: =IF(ABS(E8)>0.005,"FLAG","ok") -> ok | G8: Exact: NCI 53 is the CIQ residual; current operating lease portion (164 at FY25) not added
A9: PepsiCo, Inc. | B9: =Inputs_Sources!$D$175 -> 220113.5 | C9: =PeerAnalysis!O20 -> 224447.5 | D9: =C9-B9 -> 4334 | E9: =IFERROR(D9/B9,"n/a") -> 0.019689842 | F9: =IF(ABS(E9)>0.005,"FLAG","ok") -> FLAG | G9: Our EV adds operating leases 3,846 (CIQ excludes them) and deducts cash 10,675 only (CIQ deducts 488 more)
A10: ARYZTA AG | B10: =Inputs_Sources!$D$90 -> 2103.3 | C10: =PeerAnalysis!O15 -> 2103.3 | D10: =C10-B10 -> 0 | E10: =IFERROR(D10/B10,"n/a") -> 0 | F10: =IF(ABS(E10)>0.005,"FLAG","ok") -> ok | G10: Carried as the CIQ residual (-17.4, unexplained); components not verified
A12: 2. Calendarisation weights sum to 1
A13: Weights check: BIMBO | B13: =IFERROR(PeerAnalysis!D60+PeerAnalysis!E60,"n/a") -> 1 | C13: =IF(ISNUMBER(B13),IF(ABS(B13-1)<0.000001,"ok","FLAG"),"n/a") -> ok
A14: Weights check: FLO | B14: =IFERROR(PeerAnalysis!D61+PeerAnalysis!E61,"n/a") -> 1 | C14: =IF(ISNUMBER(B14),IF(ABS(B14-1)<0.000001,"ok","FLAG"),"n/a") -> ok
A15: Weights check: GRUMA | B15: =IFERROR(PeerAnalysis!D62+PeerAnalysis!E62,"n/a") -> 1 | C15: =IF(ISNUMBER(B15),IF(ABS(B15-1)<0.000001,"ok","FLAG"),"n/a") -> ok
A16: Weights check: YMZ | B16: =IFERROR(PeerAnalysis!D63+PeerAnalysis!E63,"n/a") -> 1 | C16: =IF(ISNUMBER(B16),IF(ABS(B16-1)<0.000001,"ok","FLAG"),"n/a") -> ok
A17: Weights check: ARYN | B17: =IFERROR(PeerAnalysis!D64+PeerAnalysis!E64,"n/a") -> 1 | C17: =IF(ISNUMBER(B17),IF(ABS(B17-1)<0.000001,"ok","FLAG"),"n/a") -> ok
A18: Weights check: SJM | B18: =IFERROR(PeerAnalysis!D65+PeerAnalysis!E65,"n/a") -> 1 | C18: =IF(ISNUMBER(B18),IF(ABS(B18-1)<0.000001,"ok","FLAG"),"n/a") -> ok
A19: Weights check: CPB | B19: =IFERROR(PeerAnalysis!D66+PeerAnalysis!E66,"n/a") -> 1 | C19: =IF(ISNUMBER(B19),IF(ABS(B19-1)<0.000001,"ok","FLAG"),"n/a") -> ok
A20: Weights check: MDLZ | B20: =IFERROR(PeerAnalysis!D67+PeerAnalysis!E67,"n/a") -> 1 | C20: =IF(ISNUMBER(B20),IF(ABS(B20-1)<0.000001,"ok","FLAG"),"n/a") -> ok
A21: Weights check: AC | B21: =IFERROR(PeerAnalysis!D68+PeerAnalysis!E68,"n/a") -> 1 | C21: =IF(ISNUMBER(B21),IF(ABS(B21-1)<0.000001,"ok","FLAG"),"n/a") -> ok
A22: Weights check: PEP | B22: =IFERROR(PeerAnalysis!D69+PeerAnalysis!E69,"n/a") -> 1 | C22: =IF(ISNUMBER(B22),IF(ABS(B22-1)<0.000001,"ok","FLAG"),"n/a") -> ok
A24: 3. Bimbo LTM Adjusted EBITDA: sum of four quarters vs company LTM (60,919)
A25: Sum of quarters 3Q25 to 2Q26 (MXN m) | B25: =Inputs_Sources!$D$25+Inputs_Sources!$D$26+Inputs_Sources!$D$27+Inputs_Sources!$D$28 -> 60919 | C25: =IF(ABS(B25-60919)<0.5,"ok","FLAG") -> ok
A27: 4. TearSheet identities and cross-checks
A28: Test | B28: FY2021 | C28: FY2022 | D28: FY2023 | E28: FY2024 | F28: FY2025
A29: Balance sheet identity: total assets - total liabilities - equity (should be 0) | B29: =TearSheet!C30-TearSheet!C33-TearSheet!C35 -> 0 | C29: =TearSheet!D30-TearSheet!D33-TearSheet!D35 -> 0 | D29: =TearSheet!E30-TearSheet!E33-TearSheet!E35 -> 0 | E29: =TearSheet!F30-TearSheet!F33-TearSheet!F35 -> 0 | F29: =TearSheet!G30-TearSheet!G33-TearSheet!G35 -> 0
A30: Net debt CIQ incl. leases minus (total debt incl. leases minus cash) (should be 0) | B30: =TearSheet!C37-(TearSheet!C36-TearSheet!C28) -> 0 | C30: =TearSheet!D37-(TearSheet!D36-TearSheet!D28) -> 0 | D30: =TearSheet!E37-(TearSheet!E36-TearSheet!E28) -> 0 | E30: =TearSheet!F37-(TearSheet!F36-TearSheet!F28) -> 0 | F30: =TearSheet!G37-(TearSheet!G36-TearSheet!G28) -> 0
A31: Revenue CIQ sum of quarters minus company annual (MXN m; FY2025 company 426,952; FY2021-23 restated company) | B31: =TearSheet!C7-338792 -> 0 | C31: =TearSheet!D7-398706 -> 0 | D31: =TearSheet!E7-399879 -> 0 | F31: =TearSheet!G7-426952 -> 11
A32: Consensus FY2026E EBITDA in USD at 17.46 minus CIQ dashboard US$3,558.4m (should be about 0) | B32: =TearSheet!H19/Inputs_Sources!$D$11-3558.4 -> -0.72531501
A34: 5. Error scan (count of error values in formula areas; must be 0)
A35: PeerAnalysis error cells | B35: =SUMPRODUCT(--ISERROR(PeerAnalysis!A1:T90)) -> 0
A36: TearSheet error cells | B36: =SUMPRODUCT(--ISERROR(TearSheet!A1:L80)) -> 0
A37: Checks sheet error cells | B37: =SUMPRODUCT(--ISERROR(A1:H36)) -> 0
A39: 6. Known gaps and memo items (no value is invented; blank = not found)
A40: CIQ dividend and CFO actuals differ from company values in some years (TearSheet memo rows); company values used where stated.
A41: Gross profit: SEC for US peers (Flowers not found; Smucker LTM not used; Campbell's calculated), Gruma from its report; not in the CIQ pull. Price performance not retrieved.
A42: Arca and Yamazaki: shares and NCI not found (aggregator prices only), excluded from medians. Aryzta: H1-26 report unreadable; CIQ values shown descriptively.
A43: Gruma price is a delayed quote (no official BMV close found); replace with the BMV close before the report.
A44: Bimbo price MXN 58.60 and shares 4,294.9m are coordinator-supplied and not independently verified; each MXN 1 per share moves EV/EBITDA by about 0.07x.
A45: Bimbo NCI at book (722) is small against the FY25 NCI profit share (1,813) because consolidated IO profit is attributed to NCI (coordinator statement); on an economic NCI claim EV would be higher.
A46: CIQ NTM multiples tool values are audit only; they differ from the table-based NTM multiples by up to about 0.5x.
A48: 7. Lease normalisation: CIQ total debt vs reconciled debt (US GAAP peers; values from SEC research)
A49: Company | B49: CIQ total debt (USD m) | C49: (A) financial debt (USD m) | D49: (A) vs CIQ | E49: (B) financial debt + op. lease liabilities (USD m) | F49: (B) vs CIQ | G49: CIQ includes op. leases? | H49: Basis note
A50: Flowers Foods, Inc. | B50: 2007.8 | C50: 1686.2 | D50: =C50/B50-1 -> -0.16017532 | E50: 2003.3 | F50: =E50/B50-1 -> -0.0022412591 | G50: yes | H50: 18-Jul-2026: financial debt 1,686.2 + op. lease liabilities 317.1 (75.2 + 241.9)
A51: The J. M. Smucker Company | B51: 6940.2 | C51: 6737.8 | D51: =C51/B51-1 -> -0.029163425 | E51: 6930.6 | F51: =E51/B51-1 -> -0.0013832454 | G51: yes | H51: 31-Jul-2026: (B) with finance leases 9.6 = 6,940.2 exact
A52: The Campbell's Company | B52: 7450 | C52: 7137 | D52: =C52/B52-1 -> -0.042013423 | E52: 7450 | F52: =E52/B52-1 -> 0 | G52: yes | H52: 2-Aug-2026 (FY26 10-K): 7,137 + op. lease liabilities 313 = 7,450 exact
A53: Mondelez International, Inc. | B53: 22059 | C53: 21450 | D53: =C53/B53-1 -> -0.027607779 | E53: 22059 | F53: =E53/B53-1 -> 0 | G53: yes | H53: 30-Jun-2026: noncurrent op. lease 609 ties exactly; current portion not found
A54: PepsiCo, Inc. | B54: 51881 | C54: 51881 | D54: =C54/B54-1 -> 0 | E54: 55727 | F54: =E54/B54-1 -> 0.074131185 | G54: no | H54: 5-Sep-2026: (A) exact, so CIQ excludes leases; (B) uses 27-Dec-2025 liabilities 3,846
A56: 8. FX and basis memo
A57: MXN per USD 17.46 (CIQ dashboard, Oct-2026) is used for every MXN market value (Gruma and Arca prices; Bimbo USD display).
A58: CIQ's note of 0.055690 USD per MXN (17.96) for Arca conflicts with Gruma's 30-Jun-2026 rate of 17.47 and is not used.
A59: CIQ's USD net debt for Bimbo (9,907) implies 17.47 MXN per USD (173,116 / 9,907), consistent with the spot rate used here.
A60: Bimbo multiples are computed in MXN and do not depend on FX; the USD columns are for size only.
A61: Gruma reports in USD: its balance-sheet items are USD at historical rates; its market cap uses the spot rate.
A62: Consensus for peers is in USD (CIQ); CIQ does not state its conversion rate, so NTM figures may differ from LTM by a few percent.
A64: 9. EV claim basis: categories included and excluded (one basis for all eligible peers and Bimbo)
A65: Included: financial debt (incl. finance leases where separated), operating or IFRS 16 lease liabilities, NCI at book including redeemable NCI, less cash and equivalents.
A66: Excluded for every company: pensions and OPEB, Bimbo's MEPP, derivative assets and liabilities, equity-method investments, short-term investments (except as CIQ deducts them, flagged for PepsiCo).
A67: Reason: these claims are not sourced for every eligible peer (Gruma, Flowers, Smucker, Campbell's, Mondelez, PepsiCo); adding them would change the basis by company.
