Workbook

Sheet TearSheet
B2: Financials & Peer Analysis
B4: Company set-up (static values: the CIQ Excel plugin is not used)
B5: Step 1. Company identifier | E5: BMV:BIMBO A | H5: Notes:
H6: Layout after the S&P Capital IQ Pro 'Financials & Peer Analysis' template. Numbers are static and tagged; detail and sources are in Detail_TearSheet and Inputs_Sources.
H7: A = actual (CIQ quarterly sums or company filings); E = consensus mean (CIQ, 20-Sep-2026). Shaded blank = not in the local data; pending a CIQ refresh.
B8: Step 2. Latest completed year | E8: FY2025
B11: Step 3. As-of date | E11: 2026-10-16
B14: Step 4. Currency | E14: Mexican peso (MXN)
B16: Step 5. Magnitude | E16: Millions
B18: Step 6. Source | E18: Company filings and CIQ (A); S&P Capital IQ consensus mean (E)
B21: Step 7. Refresh | E21: Not linked to CIQ: re-run valuation/build/build_peer_workbook.py
B25: Grupo Bimbo, S.A.B. de C.V. | K25: Data in (MXN m), except per share
E26: A | F26: A | G26: A | H26: E | I26: E | J26: E | K26: E
B27: Income Statement | E27: FY2023 | F27: FY2024 | G27: FY2025 | H27: FY2026 | I27: FY2027 | J27: FY2028 | K27: FY2029 | L27: Tag / source
B28: Sales | C28: Total revenue | E28: =IF(ISNUMBER(Detail_TearSheet!E7),Detail_TearSheet!E7,"n/a") -> 399879 | F28: =IF(ISNUMBER(Detail_TearSheet!F7),Detail_TearSheet!F7,"n/a") -> 408335 | G28: =IF(ISNUMBER(Detail_TearSheet!G7),Detail_TearSheet!G7,"n/a") -> 426963 | H28: =IF(ISNUMBER(Detail_TearSheet!H7),Detail_TearSheet!H7,"n/a") -> 426274.7 | I28: =IF(ISNUMBER(Detail_TearSheet!I7),Detail_TearSheet!I7,"n/a") -> 445288 | J28: =IF(ISNUMBER(Detail_TearSheet!J7),Detail_TearSheet!J7,"n/a") -> 468430.9 | K28: =Inputs_Sources!$D$705 -> 477018 | L28: [sourced] A: Detail_TearSheet (CIQ / filings); E: CIQ consensus mean
B29: - growth YoY | E29: =IFERROR(E28/Detail_TearSheet!D7-1,"n/a") -> 0.0029420174 | F29: =IFERROR(F28/E28-1,"n/a") -> 0.021146397 | G29: =IFERROR(G28/F28-1,"n/a") -> 0.045619406 | H29: =IFERROR(H28/G28-1,"n/a") -> -0.0016120835 | I29: =IFERROR(I28/H28-1,"n/a") -> 0.044603398 | J29: =IFERROR(J28/I28-1,"n/a") -> 0.05197288 | K29: =IFERROR(K28/J28-1,"n/a") -> 0.018331626 | L29: [calc]
B30: Gross Profit | C30: Gross Profit / (loss) | E30: =IF(ISNUMBER(Detail_TearSheet!E9),Detail_TearSheet!E9,"n/a") -> 206159.5 | F30: =IF(ISNUMBER(Detail_TearSheet!F9),Detail_TearSheet!F9,"n/a") -> 214928 | G30: =IF(ISNUMBER(Detail_TearSheet!G9),Detail_TearSheet!G9,"n/a") -> 224241.7 | H30: =IFERROR(H28*Detail_TearSheet!H11/100,"n/a") -> 222941.67 | I30: =IFERROR(I28*Detail_TearSheet!I11/100,"n/a") -> 231549.76 | J30: =IFERROR(J28*Detail_TearSheet!J11/100,"n/a") -> 243818.28 | K30: =IFERROR(K28*Inputs_Sources!$D$715/100,"n/a") -> 248526.38 | L30: [sourced] A: Detail_TearSheet (CIQ / filings); E: CIQ consensus mean; E = revenue x consensus gross margin [calc]
B31: SG&A | C31: Selling, general and administrative expenses | E31: =IF(ISNUMBER(Detail_TearSheet!E12),Detail_TearSheet!E12,"n/a") -> 165748 | F31: =IF(ISNUMBER(Detail_TearSheet!F12),Detail_TearSheet!F12,"n/a") -> 175164 | G31: =IF(ISNUMBER(Detail_TearSheet!G12),Detail_TearSheet!G12,"n/a") -> 184186 | H31: =IF(ISNUMBER(Detail_TearSheet!H12),Detail_TearSheet!H12,"n/a") -> 177262 | I31: =IF(ISNUMBER(Detail_TearSheet!I12),Detail_TearSheet!I12,"n/a") -> 189938 | J31: =IF(ISNUMBER(Detail_TearSheet!J12),Detail_TearSheet!J12,"n/a") -> 197030 | K31: =Inputs_Sources!$D$716 -> 216662 | L31: [sourced] A: Detail_TearSheet (CIQ / filings); E: CIQ consensus mean
B32: Operating Expenses | C32: Total operating expenses | E32: =IF(ISNUMBER(Detail_TearSheet!E14),Detail_TearSheet!E14,"n/a") -> 168704.7 | F32: =IF(ISNUMBER(Detail_TearSheet!F14),Detail_TearSheet!F14,"n/a") -> 181779 | G32: =IF(ISNUMBER(Detail_TearSheet!G14),Detail_TearSheet!G14,"n/a") -> 187970.1 | H32: =IFERROR(H30-H33,"n/a") -> 185495.67 | I32: =IFERROR(I30-I33,"n/a") -> 192770.76 | J32: =IFERROR(J30-J33,"n/a") -> 201892.28 | K32: =IFERROR(K30-K33,"n/a") -> 208504.38 | L32: [sourced] A: Detail_TearSheet (CIQ / filings); E: CIQ consensus mean; E = gross profit - EBIT [calc]
B33: EBIT | C33: Operating income/(loss), company basis | E33: =IF(ISNUMBER(Detail_TearSheet!E16),Detail_TearSheet!E16,"n/a") -> 35455 | F33: =IF(ISNUMBER(Detail_TearSheet!F16),Detail_TearSheet!F16,"n/a") -> 33149 | G33: =IF(ISNUMBER(Detail_TearSheet!G16),Detail_TearSheet!G16,"n/a") -> 34146 | H33: =IF(ISNUMBER(Detail_TearSheet!H16),Detail_TearSheet!H16,"n/a") -> 37446 | I33: =IF(ISNUMBER(Detail_TearSheet!I16),Detail_TearSheet!I16,"n/a") -> 38779 | J33: =IF(ISNUMBER(Detail_TearSheet!J16),Detail_TearSheet!J16,"n/a") -> 41926 | K33: =Inputs_Sources!$D$707 -> 40022 | L33: [sourced] A: Detail_TearSheet (CIQ / filings); E: CIQ consensus mean
B34: EBITDA | C34: Adjusted EBITDA, company (IFRS 16) | E34: =IF(ISNUMBER(Detail_TearSheet!E19),Detail_TearSheet!E19,"n/a") -> 54942 | F34: =IF(ISNUMBER(Detail_TearSheet!F19),Detail_TearSheet!F19,"n/a") -> 55473 | G34: =IF(ISNUMBER(Detail_TearSheet!G19),Detail_TearSheet!G19,"n/a") -> 59456 | H34: =IF(ISNUMBER(Detail_TearSheet!H19),Detail_TearSheet!H19,"n/a") -> 62117 | I34: =IF(ISNUMBER(Detail_TearSheet!I19),Detail_TearSheet!I19,"n/a") -> 64891 | J34: =IF(ISNUMBER(Detail_TearSheet!J19),Detail_TearSheet!J19,"n/a") -> 68999 | K34: =Inputs_Sources!$D$706 -> 70667.5 | L34: [sourced] A: Detail_TearSheet (CIQ / filings); E: CIQ consensus mean
B35: Pre tax profit | C35: Income from continuing operations before taxes | E35: =IF(ISNUMBER(Detail_TearSheet!E21),Detail_TearSheet!E21,"n/a") -> 25324 | F35: =IF(ISNUMBER(Detail_TearSheet!F21),Detail_TearSheet!F21,"n/a") -> 21034 | G35: =IF(ISNUMBER(Detail_TearSheet!G21),Detail_TearSheet!G21,"n/a") -> 20143 | H35: =IF(ISNUMBER(Detail_TearSheet!H21),Detail_TearSheet!H21,"n/a") -> 23597 | I35: =IF(ISNUMBER(Detail_TearSheet!I21),Detail_TearSheet!I21,"n/a") -> 25677 | J35: =IF(ISNUMBER(Detail_TearSheet!J21),Detail_TearSheet!J21,"n/a") -> 30308 | L35: [sourced] A: Detail_TearSheet (CIQ / filings); E: CIQ consensus mean; E: not in CIQ consensus
B36: NPAT | C36: Net income to majority | E36: =IF(ISNUMBER(Detail_TearSheet!E22),Detail_TearSheet!E22,"n/a") -> 15477 | F36: =IF(ISNUMBER(Detail_TearSheet!F22),Detail_TearSheet!F22,"n/a") -> 12544 | G36: =IF(ISNUMBER(Detail_TearSheet!G22),Detail_TearSheet!G22,"n/a") -> 11133 | H36: =IF(ISNUMBER(Detail_TearSheet!H22),Detail_TearSheet!H22,"n/a") -> 13688 | I36: =IF(ISNUMBER(Detail_TearSheet!I22),Detail_TearSheet!I22,"n/a") -> 15011 | J36: =IF(ISNUMBER(Detail_TearSheet!J22),Detail_TearSheet!J22,"n/a") -> 17371 | K36: =Inputs_Sources!$D$708 -> 16735 | L36: [sourced] A: Detail_TearSheet (CIQ / filings); E: CIQ consensus mean
B37: EPS | C37: EPS, basic, total (E: normalised) | E37: =IF(ISNUMBER(Detail_TearSheet!E24),Detail_TearSheet!E24,"n/a") -> 3.5 | F37: =IF(ISNUMBER(Detail_TearSheet!F24),Detail_TearSheet!F24,"n/a") -> 2.88 | G37: =IF(ISNUMBER(Detail_TearSheet!G24),Detail_TearSheet!G24,"n/a") -> 2.58 | H37: =IF(ISNUMBER(Detail_TearSheet!H24),Detail_TearSheet!H24,"n/a") -> 3.07 | I37: =IF(ISNUMBER(Detail_TearSheet!I24),Detail_TearSheet!I24,"n/a") -> 3.35 | J37: =IF(ISNUMBER(Detail_TearSheet!J24),Detail_TearSheet!J24,"n/a") -> 3.8 | K37: =Inputs_Sources!$D$709 -> 4.02 | L37: [sourced] A: Detail_TearSheet (CIQ / filings); E: CIQ consensus mean
B38: - growth YoY | E38: =IFERROR(E37/Detail_TearSheet!D24-1,"n/a") -> -0.66793169 | F38: =IFERROR(F37/E37-1,"n/a") -> -0.17714286 | G38: =IFERROR(G37/F37-1,"n/a") -> -0.10416667 | H38: =IFERROR(H37/G37-1,"n/a") -> 0.18992248 | I38: =IFERROR(I37/H37-1,"n/a") -> 0.091205212 | J38: =IFERROR(J37/I37-1,"n/a") -> 0.13432836 | K38: =IFERROR(K37/J37-1,"n/a") -> 0.057894737 | L38: [calc]
B39: DPS | C39: Dividend per share | E39: =IF(ISNUMBER(Detail_TearSheet!E25),Detail_TearSheet!E25,"n/a") -> 0.78 | F39: =IF(ISNUMBER(Detail_TearSheet!F25),Detail_TearSheet!F25,"n/a") -> 0.94 | G39: =IF(ISNUMBER(Detail_TearSheet!G25),Detail_TearSheet!G25,"n/a") -> 1 | H39: =IF(ISNUMBER(Detail_TearSheet!H25),Detail_TearSheet!H25,"n/a") -> 1.01 | I39: =IF(ISNUMBER(Detail_TearSheet!I25),Detail_TearSheet!I25,"n/a") -> 1.05 | J39: =IF(ISNUMBER(Detail_TearSheet!J25),Detail_TearSheet!J25,"n/a") -> 1.24 | K39: =Inputs_Sources!$D$710 -> 1.24 | L39: [sourced] A: Detail_TearSheet (CIQ / filings); E: CIQ consensus mean
B41: Balance Sheet
B42: Cash and Equivalents | C42: Cash and short-term investments | E42: =IF(ISNUMBER(Detail_TearSheet!E28),Detail_TearSheet!E28,"n/a") -> 6353 | F42: =IF(ISNUMBER(Detail_TearSheet!F28),Detail_TearSheet!F28,"n/a") -> 8057 | G42: =IF(ISNUMBER(Detail_TearSheet!G28),Detail_TearSheet!G28,"n/a") -> 8535 | L42: [sourced] A: Detail_TearSheet (CIQ / filings); E: CIQ consensus mean; E: not in CIQ consensus
B43: Current Assets | C43: Total current assets | E43: =IF(ISNUMBER(Detail_TearSheet!E29),Detail_TearSheet!E29,"n/a") -> 58914 | F43: =IF(ISNUMBER(Detail_TearSheet!F29),Detail_TearSheet!F29,"n/a") -> 67180 | G43: =IF(ISNUMBER(Detail_TearSheet!G29),Detail_TearSheet!G29,"n/a") -> 64671 | L43: [sourced] A: Detail_TearSheet (CIQ / filings); E: CIQ consensus mean; E: not in CIQ consensus
B44: Non-Current Assets | C44: Total non-current assets | E44: =IF(ISNUMBER(Detail_TearSheet!E31),Detail_TearSheet!E31,"n/a") -> 289188 | F44: =IF(ISNUMBER(Detail_TearSheet!F31),Detail_TearSheet!F31,"n/a") -> 349624 | G44: =IF(ISNUMBER(Detail_TearSheet!G31),Detail_TearSheet!G31,"n/a") -> 345134 | L44: [sourced] A: Detail_TearSheet (CIQ / filings); E: CIQ consensus mean; E: not in CIQ consensus
B45: Current Liabilities | C45: Total current liabilities | E45: =IF(ISNUMBER(Detail_TearSheet!E32),Detail_TearSheet!E32,"n/a") -> 87192 | F45: =IF(ISNUMBER(Detail_TearSheet!F32),Detail_TearSheet!F32,"n/a") -> 85155 | G45: =IF(ISNUMBER(Detail_TearSheet!G32),Detail_TearSheet!G32,"n/a") -> 90573 | L45: [sourced] A: Detail_TearSheet (CIQ / filings); E: CIQ consensus mean; E: not in CIQ consensus
B46: Non-Current Liabilities | C46: Total non-current liabilities | E46: =IF(ISNUMBER(Detail_TearSheet!E34),Detail_TearSheet!E34,"n/a") -> 149282 | F46: =IF(ISNUMBER(Detail_TearSheet!F34),Detail_TearSheet!F34,"n/a") -> 203951 | G46: =IF(ISNUMBER(Detail_TearSheet!G34),Detail_TearSheet!G34,"n/a") -> 198977 | L46: [sourced] A: Detail_TearSheet (CIQ / filings); E: CIQ consensus mean; E: not in CIQ consensus
B47: Net Debt | C47: Net debt (A: CIQ incl. IFRS 16 leases; E: consensus) | E47: =IF(ISNUMBER(Detail_TearSheet!E37),Detail_TearSheet!E37,"n/a") -> 133186 | F47: =IF(ISNUMBER(Detail_TearSheet!F37),Detail_TearSheet!F37,"n/a") -> 179338 | G47: =IF(ISNUMBER(Detail_TearSheet!G37),Detail_TearSheet!G37,"n/a") -> 182232 | H47: =Inputs_Sources!$D$678 -> 146911.02 | I47: =Inputs_Sources!$D$690 -> 133766.76 | J47: =Inputs_Sources!$D$702 -> 119433.54 | K47: =Inputs_Sources!$D$714 -> 109707 | L47: [sourced] A: Detail_TearSheet (CIQ / filings); E: CIQ consensus mean; E = consensus net debt (broker definition; FY25A 149,031 vs 182,232 incl. leases)
B49: Cash Flow
B50: Capex | C50: Capital expenditures | E50: =IF(ISNUMBER(Detail_TearSheet!E42),Detail_TearSheet!E42,"n/a") -> -34754 | F50: =IF(ISNUMBER(Detail_TearSheet!F42),Detail_TearSheet!F42,"n/a") -> -29402 | G50: =IF(ISNUMBER(Detail_TearSheet!G42),Detail_TearSheet!G42,"n/a") -> -22530 | H50: =IF(ISNUMBER(Detail_TearSheet!H42),Detail_TearSheet!H42,"n/a") -> -21978.8 | I50: =IF(ISNUMBER(Detail_TearSheet!I42),Detail_TearSheet!I42,"n/a") -> -22341.3 | J50: =IF(ISNUMBER(Detail_TearSheet!J42),Detail_TearSheet!J42,"n/a") -> -22933.5 | K50: =-Inputs_Sources!$D$711 -> -19308 | L50: [sourced] A: Detail_TearSheet (CIQ / filings); E: CIQ consensus mean
B51: Change in working capital | C51: (Increase)/decrease in working capital | E51: =IF(ISNUMBER(Detail_TearSheet!E46),Detail_TearSheet!E46,"n/a") -> 11165 | F51: =IF(ISNUMBER(Detail_TearSheet!F46),Detail_TearSheet!F46,"n/a") -> 1017 | G51: =IF(ISNUMBER(Detail_TearSheet!G46),Detail_TearSheet!G46,"n/a") -> -696 | L51: [sourced] A: Detail_TearSheet (CIQ / filings); E: CIQ consensus mean; E: not in CIQ consensus
B52: Net cash flow from operations | C52: Net cash flows from operating activities | E52: =IF(ISNUMBER(Detail_TearSheet!E41),Detail_TearSheet!E41,"n/a") -> 31411 | F52: =IF(ISNUMBER(Detail_TearSheet!F41),Detail_TearSheet!F41,"n/a") -> 39907 | G52: =IF(ISNUMBER(Detail_TearSheet!G41),Detail_TearSheet!G41,"n/a") -> 47753 | H52: =Inputs_Sources!$D$676 -> 35594.5 | I52: =Inputs_Sources!$D$688 -> 38165 | J52: =Inputs_Sources!$D$700 -> 43566 | L52: [sourced] A: Detail_TearSheet (CIQ / filings); E: CIQ consensus mean
B53: Net cash flow from investing activities | C53: Net cash flows from investing activities | E53: =IF(ISNUMBER(Detail_TearSheet!E44),Detail_TearSheet!E44,"n/a") -> -42440 | F53: =IF(ISNUMBER(Detail_TearSheet!F44),Detail_TearSheet!F44,"n/a") -> -36138 | G53: =IF(ISNUMBER(Detail_TearSheet!G44),Detail_TearSheet!G44,"n/a") -> -34652 | L53: [sourced] A: Detail_TearSheet (CIQ / filings); E: CIQ consensus mean; E: not in CIQ consensus
B54: Net cash flow from financing activities | C54: Net cash flows from financing activities | E54: =IF(ISNUMBER(Detail_TearSheet!E45),Detail_TearSheet!E45,"n/a") -> 5904 | F54: =IF(ISNUMBER(Detail_TearSheet!F45),Detail_TearSheet!F45,"n/a") -> n/a | G54: =IF(ISNUMBER(Detail_TearSheet!G45),Detail_TearSheet!G45,"n/a") -> -11908 | L54: [sourced] A: Detail_TearSheet (CIQ / filings); E: CIQ consensus mean; E: not in CIQ consensus
B56: Margins / Ratios
B57: Gross margin | C57: Gross margin | E57: =IFERROR(E30/E28,"n/a") -> 0.51555471 | F57: =IFERROR(F30/F28,"n/a") -> 0.52635214 | G57: =IFERROR(G30/G28,"n/a") -> 0.52520172 | H57: =IFERROR(H30/H28,"n/a") -> 0.523 | I57: =IFERROR(I30/I28,"n/a") -> 0.52 | J57: =IFERROR(J30/J28,"n/a") -> 0.5205 | K57: =IFERROR(K30/K28,"n/a") -> 0.521 | L57: [calc]
B58: SG&A / Sales | C58: SG&A / Sales | E58: =IFERROR(E31/E28,"n/a") -> 0.41449538 | F58: =IFERROR(F31/F28,"n/a") -> 0.42897131 | G58: =IFERROR(G31/G28,"n/a") -> 0.43138633 | H58: =IFERROR(H31/H28,"n/a") -> 0.41583983 | I58: =IFERROR(I31/I28,"n/a") -> 0.42655091 | J58: =IFERROR(J31/J28,"n/a") -> 0.420617 | K58: =IFERROR(K31/K28,"n/a") -> 0.45420089 | L58: [calc]
B59: Operating margin | C59: Operating margin | E59: =IFERROR(E33/E28,"n/a") -> 0.088664321 | F59: =IFERROR(F33/F28,"n/a") -> 0.081180893 | G59: =IFERROR(G33/G28,"n/a") -> 0.079974143 | H59: =IFERROR(H33/H28,"n/a") -> 0.087844763 | I59: =IFERROR(I33/I28,"n/a") -> 0.087087458 | J59: =IFERROR(J33/J28,"n/a") -> 0.089503062 | K59: =IFERROR(K33/K28,"n/a") -> 0.083900398 | L59: [calc]
B60: EBITDA margin | C60: EBITDA margin | E60: =IFERROR(E34/E28,"n/a") -> 0.13739656 | F60: =IFERROR(F34/F28,"n/a") -> 0.13585169 | G60: =IFERROR(G34/G28,"n/a") -> 0.13925328 | H60: =IFERROR(H34/H28,"n/a") -> 0.14572059 | I60: =IFERROR(I34/I28,"n/a") -> 0.14572816 | J60: =IFERROR(J34/J28,"n/a") -> 0.14729814 | K60: =IFERROR(K34/K28,"n/a") -> 0.1481443 | L60: [calc]
B61: Net margin | C61: Net margin | E61: =IFERROR(E36/E28,"n/a") -> 0.038704208 | F61: =IFERROR(F36/F28,"n/a") -> 0.030719875 | G61: =IFERROR(G36/G28,"n/a") -> 0.026074859 | H61: =IFERROR(H36/H28,"n/a") -> 0.032110749 | I61: =IFERROR(I36/I28,"n/a") -> 0.033710767 | J61: =IFERROR(J36/J28,"n/a") -> 0.037083378 | K61: =IFERROR(K36/K28,"n/a") -> 0.035082534 | L61: [calc]
B63: Source: S&P Capital IQ Pro (CIQ CSV exports and consensus, 19/20-Sep-2026) and Grupo Bimbo filings; compiled in Inputs_Sources and Detail_TearSheet.

Sheet PeerAnalysis
B2: Performance Valuation - Grupo Bimbo and peers
B4: Notes:
B5: Pricing date 16-Oct-2026. USD m; MXN figures converted at the pricing-date rate, MXN 18.479 per USD (Bimbo's own multiples are computed in MXN).
B6: Enterprise value on one claim basis for every company: financial debt + lease liabilities + NCI at book - cash (pensions, MEPP and derivatives excluded); US GAAP EBITDA + operating lease cost.
B7: Shaded blank = not available (peers' 52-week range and 1-day change were not returned by Capital IQ). Price changes over 1, 2, 3 and 5 years are month-end approximations (base 31-Oct); QTD and YTD are exact.
B8: NTM and STM: CIQ consensus calendarised from the pricing date with fiscal-year day weights (STM = the 12 months after NTM).
B9: Data in ($M)
F10: Market Data
F11: Share Price ($) | G11: Price High ($) | H11: Price Low ($) | I11: Market Cap. ($M) | J11: Enterprise Value ($M) | K11: Price Performance (%) | R11: Dividends per share
B12: Company Name | D12: Group | E12: Exchange:Ticker | G12: 52W | H12: 52W | K12: 1D | L12: 1Y | M12: 2Y | N12: 3Y | O12: 5Y | P12: QTD | Q12: YTD
B13: =Detail_PeerAnalysis!A12 -> Flowers Foods, Inc. | D13: Core | E13: =Detail_PeerAnalysis!B12 -> NYSE:FLO | F13: =IFERROR(Detail_PeerAnalysis!F12*Detail_PeerAnalysis!H12,"n/a") -> 6.1089109 | L13: =IF(AND(ISNUMBER(Inputs_Sources!$D$346),ISNUMBER(Inputs_Sources!$D$349)),Inputs_Sources!$D$346/Inputs_Sources!$D$349-1,"n/a") -> -0.48784577 | M13: =IF(AND(ISNUMBER(Inputs_Sources!$D$346),ISNUMBER(Inputs_Sources!$D$350)),Inputs_Sources!$D$346/Inputs_Sources!$D$350-1,"n/a") -> -0.7251462 | N13: =IF(AND(ISNUMBER(Inputs_Sources!$D$346),ISNUMBER(Inputs_Sources!$D$351)),Inputs_Sources!$D$346/Inputs_Sources!$D$351-1,"n/a") -> -0.72138623 | O13: =IF(AND(ISNUMBER(Inputs_Sources!$D$346),ISNUMBER(Inputs_Sources!$D$352)),Inputs_Sources!$D$346/Inputs_Sources!$D$352-1,"n/a") -> -0.75313131 | P13: =IF(AND(ISNUMBER(Inputs_Sources!$D$346),ISNUMBER(Inputs_Sources!$D$347)),Inputs_Sources!$D$346/Inputs_Sources!$D$347-1,"n/a") -> 0.1009009 | Q13: =IF(AND(ISNUMBER(Inputs_Sources!$D$346),ISNUMBER(Inputs_Sources!$D$348)),Inputs_Sources!$D$346/Inputs_Sources!$D$348-1,"n/a") -> -0.43841912 | R13: =IF(ISNUMBER(Inputs_Sources!$D$353),Inputs_Sources!$D$353,"n/a") -> 0.87
B14: =Detail_PeerAnalysis!A13 -> Gruma, S.A.B. de C.V. | D14: Core | E14: =Detail_PeerAnalysis!B13 -> BMV:GRUMA B | F14: =IFERROR(Detail_PeerAnalysis!F13*Detail_PeerAnalysis!H13,"n/a") -> 13.097029 | L14: =IF(AND(ISNUMBER(Inputs_Sources!$D$383),ISNUMBER(Inputs_Sources!$D$386)),Inputs_Sources!$D$383/Inputs_Sources!$D$386-1,"n/a") -> -0.22954679 | M14: =IF(AND(ISNUMBER(Inputs_Sources!$D$383),ISNUMBER(Inputs_Sources!$D$387)),Inputs_Sources!$D$383/Inputs_Sources!$D$387-1,"n/a") -> -0.24071926 | N14: =IF(AND(ISNUMBER(Inputs_Sources!$D$383),ISNUMBER(Inputs_Sources!$D$388)),Inputs_Sources!$D$383/Inputs_Sources!$D$388-1,"n/a") -> -0.24553314 | O14: =IF(AND(ISNUMBER(Inputs_Sources!$D$383),ISNUMBER(Inputs_Sources!$D$389)),Inputs_Sources!$D$383/Inputs_Sources!$D$389-1,"n/a") -> 0.11309524 | P14: =IF(AND(ISNUMBER(Inputs_Sources!$D$383),ISNUMBER(Inputs_Sources!$D$384)),Inputs_Sources!$D$383/Inputs_Sources!$D$384-1,"n/a") -> 0.0046047583 | Q14: =IF(AND(ISNUMBER(Inputs_Sources!$D$383),ISNUMBER(Inputs_Sources!$D$385)),Inputs_Sources!$D$383/Inputs_Sources!$D$385-1,"n/a") -> -0.24027858 | R14: =IF(ISNUMBER(Inputs_Sources!$D$390),Inputs_Sources!$D$390,"n/a") -> 0.32
B15: =Detail_PeerAnalysis!A14 -> Yamazaki Baking Co., Ltd. | D15: Core | E15: =Detail_PeerAnalysis!B14 -> TSE:2212 | F15: =IFERROR(Detail_PeerAnalysis!F14*Detail_PeerAnalysis!H14,"n/a") -> 24.153886 | L15: =IF(AND(ISNUMBER(Inputs_Sources!$D$420),ISNUMBER(Inputs_Sources!$D$423)),Inputs_Sources!$D$420/Inputs_Sources!$D$423-1,"n/a") -> 0.23379275 | M15: =IF(AND(ISNUMBER(Inputs_Sources!$D$420),ISNUMBER(Inputs_Sources!$D$424)),Inputs_Sources!$D$420/Inputs_Sources!$D$424-1,"n/a") -> 0.18364349 | N15: =IF(AND(ISNUMBER(Inputs_Sources!$D$420),ISNUMBER(Inputs_Sources!$D$425)),Inputs_Sources!$D$420/Inputs_Sources!$D$425-1,"n/a") -> 0.1427896 | O15: =IF(AND(ISNUMBER(Inputs_Sources!$D$420),ISNUMBER(Inputs_Sources!$D$426)),Inputs_Sources!$D$420/Inputs_Sources!$D$426-1,"n/a") -> 0.5932762 | P15: =IF(AND(ISNUMBER(Inputs_Sources!$D$420),ISNUMBER(Inputs_Sources!$D$421)),Inputs_Sources!$D$420/Inputs_Sources!$D$421-1,"n/a") -> 0.053159041 | Q15: =IF(AND(ISNUMBER(Inputs_Sources!$D$420),ISNUMBER(Inputs_Sources!$D$422)),Inputs_Sources!$D$420/Inputs_Sources!$D$422-1,"n/a") -> 0.14712862 | R15: =IF(ISNUMBER(Inputs_Sources!$D$427),Inputs_Sources!$D$427,"n/a") -> 0.39
B16: =Detail_PeerAnalysis!A15 -> ARYZTA AG | D16: Core | E16: =Detail_PeerAnalysis!B15 -> SWX:ARYN | F16: =IFERROR(Detail_PeerAnalysis!F15*Detail_PeerAnalysis!H15,"n/a") -> 49.145161 | L16: =IF(AND(ISNUMBER(Inputs_Sources!$D$457),ISNUMBER(Inputs_Sources!$D$460)),Inputs_Sources!$D$457/Inputs_Sources!$D$460-1,"n/a") -> -0.23412884 | M16: =IF(AND(ISNUMBER(Inputs_Sources!$D$457),ISNUMBER(Inputs_Sources!$D$461)),Inputs_Sources!$D$457/Inputs_Sources!$D$461-1,"n/a") -> -0.30423693 | N16: =IF(AND(ISNUMBER(Inputs_Sources!$D$457),ISNUMBER(Inputs_Sources!$D$462)),Inputs_Sources!$D$457/Inputs_Sources!$D$462-1,"n/a") -> -0.32850109 | O16: =IF(AND(ISNUMBER(Inputs_Sources!$D$457),ISNUMBER(Inputs_Sources!$D$463)),Inputs_Sources!$D$457/Inputs_Sources!$D$463-1,"n/a") -> -0.059747223 | P16: =IF(AND(ISNUMBER(Inputs_Sources!$D$457),ISNUMBER(Inputs_Sources!$D$458)),Inputs_Sources!$D$457/Inputs_Sources!$D$458-1,"n/a") -> 0.079358101 | Q16: =IF(AND(ISNUMBER(Inputs_Sources!$D$457),ISNUMBER(Inputs_Sources!$D$459)),Inputs_Sources!$D$457/Inputs_Sources!$D$459-1,"n/a") -> -0.24693252 | R16: =IF(ISNUMBER(Inputs_Sources!$D$464),Inputs_Sources!$D$464,"n/a") -> 0
B17: =Detail_PeerAnalysis!A16 -> The J. M. Smucker Company | D17: Secondary | E17: =Detail_PeerAnalysis!B16 -> NYSE:SJM | F17: =IFERROR(Detail_PeerAnalysis!F16*Detail_PeerAnalysis!H16,"n/a") -> 127.45787 | L17: =IF(AND(ISNUMBER(Inputs_Sources!$D$494),ISNUMBER(Inputs_Sources!$D$497)),Inputs_Sources!$D$494/Inputs_Sources!$D$497-1,"n/a") -> 0.23061323 | M17: =IF(AND(ISNUMBER(Inputs_Sources!$D$494),ISNUMBER(Inputs_Sources!$D$498)),Inputs_Sources!$D$494/Inputs_Sources!$D$498-1,"n/a") -> 0.12263237 | N17: =IF(AND(ISNUMBER(Inputs_Sources!$D$494),ISNUMBER(Inputs_Sources!$D$499)),Inputs_Sources!$D$494/Inputs_Sources!$D$499-1,"n/a") -> 0.11937807 | O17: =IF(AND(ISNUMBER(Inputs_Sources!$D$494),ISNUMBER(Inputs_Sources!$D$500)),Inputs_Sources!$D$494/Inputs_Sources!$D$500-1,"n/a") -> 0.037196809 | P17: =IF(AND(ISNUMBER(Inputs_Sources!$D$494),ISNUMBER(Inputs_Sources!$D$495)),Inputs_Sources!$D$494/Inputs_Sources!$D$495-1,"n/a") -> 0.071650828 | Q17: =IF(AND(ISNUMBER(Inputs_Sources!$D$494),ISNUMBER(Inputs_Sources!$D$496)),Inputs_Sources!$D$494/Inputs_Sources!$D$496-1,"n/a") -> 0.30283202 | R17: =IF(ISNUMBER(Inputs_Sources!$D$501),Inputs_Sources!$D$501,"n/a") -> 4.42
B18: =Detail_PeerAnalysis!A17 -> The Campbell's Company | D18: Secondary | E18: =Detail_PeerAnalysis!B17 -> NasdaqGS:CPB | F18: =IFERROR(Detail_PeerAnalysis!F17*Detail_PeerAnalysis!H17,"n/a") -> 19.872233 | L18: =IF(AND(ISNUMBER(Inputs_Sources!$D$531),ISNUMBER(Inputs_Sources!$D$534)),Inputs_Sources!$D$531/Inputs_Sources!$D$534-1,"n/a") -> -0.34052439 | M18: =IF(AND(ISNUMBER(Inputs_Sources!$D$531),ISNUMBER(Inputs_Sources!$D$535)),Inputs_Sources!$D$531/Inputs_Sources!$D$535-1,"n/a") -> -0.57406217 | N18: =IF(AND(ISNUMBER(Inputs_Sources!$D$531),ISNUMBER(Inputs_Sources!$D$536)),Inputs_Sources!$D$531/Inputs_Sources!$D$536-1,"n/a") -> -0.50829003 | O18: =IF(AND(ISNUMBER(Inputs_Sources!$D$531),ISNUMBER(Inputs_Sources!$D$537)),Inputs_Sources!$D$531/Inputs_Sources!$D$537-1,"n/a") -> -0.50262829 | P18: =IF(AND(ISNUMBER(Inputs_Sources!$D$531),ISNUMBER(Inputs_Sources!$D$532)),Inputs_Sources!$D$531/Inputs_Sources!$D$532-1,"n/a") -> 0.0020171457 | Q18: =IF(AND(ISNUMBER(Inputs_Sources!$D$531),ISNUMBER(Inputs_Sources!$D$533)),Inputs_Sources!$D$531/Inputs_Sources!$D$533-1,"n/a") -> -0.287047 | R18: =IF(ISNUMBER(Inputs_Sources!$D$538),Inputs_Sources!$D$538,"n/a") -> 1.56
B19: =Detail_PeerAnalysis!A18 -> Mondelez International, Inc. | D19: Secondary | E19: =Detail_PeerAnalysis!B18 -> NasdaqGS:MDLZ | F19: =IFERROR(Detail_PeerAnalysis!F18*Detail_PeerAnalysis!H18,"n/a") -> 63.910366 | L19: =IF(AND(ISNUMBER(Inputs_Sources!$D$568),ISNUMBER(Inputs_Sources!$D$571)),Inputs_Sources!$D$568/Inputs_Sources!$D$571-1,"n/a") -> 0.112252 | M19: =IF(AND(ISNUMBER(Inputs_Sources!$D$568),ISNUMBER(Inputs_Sources!$D$572)),Inputs_Sources!$D$568/Inputs_Sources!$D$572-1,"n/a") -> -0.066734813 | N19: =IF(AND(ISNUMBER(Inputs_Sources!$D$568),ISNUMBER(Inputs_Sources!$D$573)),Inputs_Sources!$D$568/Inputs_Sources!$D$573-1,"n/a") -> -0.034737955 | O19: =IF(AND(ISNUMBER(Inputs_Sources!$D$568),ISNUMBER(Inputs_Sources!$D$574)),Inputs_Sources!$D$568/Inputs_Sources!$D$574-1,"n/a") -> 0.052189661 | P19: =IF(AND(ISNUMBER(Inputs_Sources!$D$568),ISNUMBER(Inputs_Sources!$D$569)),Inputs_Sources!$D$568/Inputs_Sources!$D$569-1,"n/a") -> 0.10532688 | Q19: =IF(AND(ISNUMBER(Inputs_Sources!$D$568),ISNUMBER(Inputs_Sources!$D$570)),Inputs_Sources!$D$568/Inputs_Sources!$D$570-1,"n/a") -> 0.18725618 | R19: =IF(ISNUMBER(Inputs_Sources!$D$575),Inputs_Sources!$D$575,"n/a") -> 2
B20: =Detail_PeerAnalysis!A19 -> Arca Continental, S.A.B. de C.V. | D20: Secondary | E20: =Detail_PeerAnalysis!B19 -> BMV:AC | F20: =IFERROR(Detail_PeerAnalysis!F19*Detail_PeerAnalysis!H19,"n/a") -> 11.345852 | L20: =IF(AND(ISNUMBER(Inputs_Sources!$D$605),ISNUMBER(Inputs_Sources!$D$608)),Inputs_Sources!$D$605/Inputs_Sources!$D$608-1,"n/a") -> 0.17027864 | M20: =IF(AND(ISNUMBER(Inputs_Sources!$D$605),ISNUMBER(Inputs_Sources!$D$609)),Inputs_Sources!$D$605/Inputs_Sources!$D$609-1,"n/a") -> 0.32631579 | N20: =IF(AND(ISNUMBER(Inputs_Sources!$D$605),ISNUMBER(Inputs_Sources!$D$610)),Inputs_Sources!$D$605/Inputs_Sources!$D$610-1,"n/a") -> 0.26845638 | O20: =IF(AND(ISNUMBER(Inputs_Sources!$D$605),ISNUMBER(Inputs_Sources!$D$611)),Inputs_Sources!$D$605/Inputs_Sources!$D$611-1,"n/a") -> 0.85597381 | P20: =IF(AND(ISNUMBER(Inputs_Sources!$D$605),ISNUMBER(Inputs_Sources!$D$606)),Inputs_Sources!$D$605/Inputs_Sources!$D$606-1,"n/a") -> 0.055865922 | Q20: =IF(AND(ISNUMBER(Inputs_Sources!$D$605),ISNUMBER(Inputs_Sources!$D$607)),Inputs_Sources!$D$605/Inputs_Sources!$D$607-1,"n/a") -> 0.04805915 | R20: =IF(ISNUMBER(Inputs_Sources!$D$612),Inputs_Sources!$D$612,"n/a") -> 0.24
B21: =Detail_PeerAnalysis!A20 -> PepsiCo, Inc. | D21: Secondary | E21: =Detail_PeerAnalysis!B20 -> NasdaqGS:PEP | F21: =IFERROR(Detail_PeerAnalysis!F20*Detail_PeerAnalysis!H20,"n/a") -> 131.504 | L21: =IF(AND(ISNUMBER(Inputs_Sources!$D$642),ISNUMBER(Inputs_Sources!$D$645)),Inputs_Sources!$D$642/Inputs_Sources!$D$645-1,"n/a") -> -0.099938394 | M21: =IF(AND(ISNUMBER(Inputs_Sources!$D$642),ISNUMBER(Inputs_Sources!$D$646)),Inputs_Sources!$D$642/Inputs_Sources!$D$646-1,"n/a") -> -0.20827312 | N21: =IF(AND(ISNUMBER(Inputs_Sources!$D$642),ISNUMBER(Inputs_Sources!$D$647)),Inputs_Sources!$D$642/Inputs_Sources!$D$647-1,"n/a") -> -0.19469623 | O21: =IF(AND(ISNUMBER(Inputs_Sources!$D$642),ISNUMBER(Inputs_Sources!$D$648)),Inputs_Sources!$D$642/Inputs_Sources!$D$648-1,"n/a") -> -0.18632426 | P21: =IF(AND(ISNUMBER(Inputs_Sources!$D$642),ISNUMBER(Inputs_Sources!$D$643)),Inputs_Sources!$D$642/Inputs_Sources!$D$643-1,"n/a") -> 0.037642045 | Q21: =IF(AND(ISNUMBER(Inputs_Sources!$D$642),ISNUMBER(Inputs_Sources!$D$644)),Inputs_Sources!$D$642/Inputs_Sources!$D$644-1,"n/a") -> -0.08382107 | R21: =IF(ISNUMBER(Inputs_Sources!$D$649),Inputs_Sources!$D$649,"n/a") -> 5.81
B22: =Detail_PeerAnalysis!A11 -> Grupo Bimbo, S.A.B. de C.V. (subject) | D22: Subject Company >> | E22: =Detail_PeerAnalysis!B11 -> BMV:BIMBO A | F22: =IFERROR(Detail_PeerAnalysis!F11*Detail_PeerAnalysis!H11,"n/a") -> 3.1711673 | G22: =Inputs_Sources!$D$717/Inputs_Sources!$D$10 -> 3.7161102 | H22: =Inputs_Sources!$D$718/Inputs_Sources!$D$10 -> 2.869744 | K22: =IF(ISNUMBER(Inputs_Sources!$D$719),Inputs_Sources!$D$719,"n/a") -> 0.010868 | L22: =IF(AND(ISNUMBER(Inputs_Sources!$D$720),ISNUMBER(Inputs_Sources!$D$723)),Inputs_Sources!$D$720/Inputs_Sources!$D$723-1,"n/a") -> -0.086658354 | M22: =IF(AND(ISNUMBER(Inputs_Sources!$D$720),ISNUMBER(Inputs_Sources!$D$724)),Inputs_Sources!$D$720/Inputs_Sources!$D$724-1,"n/a") -> -0.054381152 | N22: =IF(AND(ISNUMBER(Inputs_Sources!$D$720),ISNUMBER(Inputs_Sources!$D$725)),Inputs_Sources!$D$720/Inputs_Sources!$D$725-1,"n/a") -> -0.19923476 | O22: =IF(AND(ISNUMBER(Inputs_Sources!$D$720),ISNUMBER(Inputs_Sources!$D$726)),Inputs_Sources!$D$720/Inputs_Sources!$D$726-1,"n/a") -> -0.038398425 | P22: =IF(AND(ISNUMBER(Inputs_Sources!$D$720),ISNUMBER(Inputs_Sources!$D$721)),Inputs_Sources!$D$720/Inputs_Sources!$D$721-1,"n/a") -> 0.067395264 | Q22: =IF(AND(ISNUMBER(Inputs_Sources!$D$720),ISNUMBER(Inputs_Sources!$D$722)),Inputs_Sources!$D$720/Inputs_Sources!$D$722-1,"n/a") -> -0.006779661 | R22: =Inputs_Sources!$D$727/Inputs_Sources!$D$10 -> 0.058174144
R27: EBITDA, YoY (%)
F28: Financials ($M) | R28: Ratios & Margins
F29: FY2024 | G29: FY2025 | H29: FY2026 | I29: LTM | J29: NTM | K29: STM | L29: FY2024 | M29: FY2025 | N29: FY2026 | O29: LTM | P29: NTM | Q29: STM | R29: FY2024 | S29: FY2025 | T29: FY2026 | U29: LTM | V29: NTM | W29: STM
B30: Company Name | D30: Group | E30: Exchange:Ticker | F30: Total revenue | L30: Gross Profit / (loss) | R30: EBITDA, YoY (%)
B31: =Detail_PeerAnalysis!A12 -> Flowers Foods, Inc. | D31: Core | E31: =Detail_PeerAnalysis!B12 -> NYSE:FLO | F31: =Detail_PeerAnalysis!B26 -> 5103.5 | G31: =Detail_PeerAnalysis!C26 -> 5256.5 | H31: =IF(ISNUMBER(Inputs_Sources!$D$337),Inputs_Sources!$D$337,"n/a") -> 5075.8 | I31: =Detail_PeerAnalysis!D26 -> 5223.9 | J31: =IF(ISNUMBER(Detail_PeerAnalysis!E26),Detail_PeerAnalysis!E26,"n/a") -> 5062.0877 | K31: =IF(AND(ISNUMBER(Inputs_Sources!$D$246),ISNUMBER(Inputs_Sources!$D$339)),Detail_PeerAnalysis!D61*Inputs_Sources!$D$246+Detail_PeerAnalysis!E61*Inputs_Sources!$D$339,"n/a") -> 5038.1625 | L31: =IF(ISNUMBER(Inputs_Sources!$D$356),Inputs_Sources!$D$356,"n/a") -> 2526.3 | M31: =IF(ISNUMBER(Inputs_Sources!$D$357),Inputs_Sources!$D$357,"n/a") -> 2568.9 | N31: =IF(AND(ISNUMBER(Inputs_Sources!$D$337),ISNUMBER(Inputs_Sources!$D$358)),Inputs_Sources!$D$337*Inputs_Sources!$D$358/100,"n/a") -> 2424.7097 | O31: =IF(ISNUMBER(Detail_PeerAnalysis!M26),Detail_PeerAnalysis!M26,"n/a") -> 2540.4 | P31: =IF(AND(ISNUMBER(Inputs_Sources!$D$244),ISNUMBER(Inputs_Sources!$D$246),ISNUMBER(Inputs_Sources!$D$358),ISNUMBER(Inputs_Sources!$D$359)),(Detail_PeerAnalysis!D61*Inputs_Sources!$D$244*Inputs_Sources!$D$358+Detail_PeerAnalysis!E61*Inputs_Sources!$D$246*Inputs_Sources!$D$359)/100,"n/a") -> 2394.3783 | Q31: =IF(AND(ISNUMBER(Inputs_Sources!$D$246),ISNUMBER(Inputs_Sources!$D$339),ISNUMBER(Inputs_Sources!$D$359),ISNUMBER(Inputs_Sources!$D$360)),(Detail_PeerAnalysis!D61*Inputs_Sources!$D$246*Inputs_Sources!$D$359+Detail_PeerAnalysis!E61*Inputs_Sources!$D$339*Inputs_Sources!$D$360)/100,"n/a") -> 2413.1744 | R31: =IF(ISNUMBER(Inputs_Sources!$D$336),IFERROR(Detail_PeerAnalysis!F26/Inputs_Sources!$D$336-1,"n/a"),"n/a") -> 0.065479844 | S31: =IFERROR(Detail_PeerAnalysis!G26/Detail_PeerAnalysis!F26-1,"n/a") -> -0.011330901 | T31: =IF(ISNUMBER(Inputs_Sources!$D$338),IFERROR(Inputs_Sources!$D$338/Detail_PeerAnalysis!G26-1,"n/a"),"n/a") -> -0.10916861 | V31: =IFERROR(Detail_PeerAnalysis!K26/Detail_PeerAnalysis!H26-1,"n/a") -> -0.10398749 | W31: =IF(AND(ISNUMBER(Inputs_Sources!$D$245),ISNUMBER(Inputs_Sources!$D$340)),IFERROR((Detail_PeerAnalysis!D61*Inputs_Sources!$D$245+Detail_PeerAnalysis!E61*Inputs_Sources!$D$340)/Detail_PeerAnalysis!K26-1,"n/a"),"n/a") -> -0.010008289
B32: =Detail_PeerAnalysis!A13 -> Gruma, S.A.B. de C.V. | D32: Core | E32: =Detail_PeerAnalysis!B13 -> BMV:GRUMA B | F32: =Detail_PeerAnalysis!B27 -> 6486.9 | G32: =Detail_PeerAnalysis!C27 -> 6374.6 | H32: =IF(ISNUMBER(Inputs_Sources!$D$374),Inputs_Sources!$D$374,"n/a") -> 6648.35 | I32: =Detail_PeerAnalysis!D27 -> 6500.1 | J32: =IF(ISNUMBER(Detail_PeerAnalysis!E27),Detail_PeerAnalysis!E27,"n/a") -> 6487.4487 | K32: =IF(AND(ISNUMBER(Inputs_Sources!$D$331),ISNUMBER(Inputs_Sources!$D$376)),Detail_PeerAnalysis!D62*Inputs_Sources!$D$331+Detail_PeerAnalysis!E62*Inputs_Sources!$D$376,"n/a") -> 6579.5375 | L32: =IF(ISNUMBER(Inputs_Sources!$D$393),Inputs_Sources!$D$393,"n/a") -> 2498.6 | M32: =IF(ISNUMBER(Inputs_Sources!$D$394),Inputs_Sources!$D$394,"n/a") -> 2492.7 | N32: =IF(AND(ISNUMBER(Inputs_Sources!$D$374),ISNUMBER(Inputs_Sources!$D$395)),Inputs_Sources!$D$374*Inputs_Sources!$D$395/100,"n/a") -> 2562.9389 | O32: =IF(ISNUMBER(Detail_PeerAnalysis!M27),Detail_PeerAnalysis!M27,"n/a") -> 2522.2 | P32: =IF(AND(ISNUMBER(Inputs_Sources!$D$330),ISNUMBER(Inputs_Sources!$D$331),ISNUMBER(Inputs_Sources!$D$395),ISNUMBER(Inputs_Sources!$D$396)),(Detail_PeerAnalysis!D62*Inputs_Sources!$D$330*Inputs_Sources!$D$395+Detail_PeerAnalysis!E62*Inputs_Sources!$D$331*Inputs_Sources!$D$396)/100,"n/a") -> 2500.9115 | Q32: =IF(AND(ISNUMBER(Inputs_Sources!$D$331),ISNUMBER(Inputs_Sources!$D$376),ISNUMBER(Inputs_Sources!$D$396),ISNUMBER(Inputs_Sources!$D$397)),(Detail_PeerAnalysis!D62*Inputs_Sources!$D$331*Inputs_Sources!$D$396+Detail_PeerAnalysis!E62*Inputs_Sources!$D$376*Inputs_Sources!$D$397)/100,"n/a") -> 2539.0217 | R32: =IF(ISNUMBER(Inputs_Sources!$D$373),IFERROR(Detail_PeerAnalysis!F27/Inputs_Sources!$D$373-1,"n/a"),"n/a") -> n/a | S32: =IFERROR(Detail_PeerAnalysis!G27/Detail_PeerAnalysis!F27-1,"n/a") -> 0.0043320661 | T32: =IF(ISNUMBER(Inputs_Sources!$D$375),IFERROR(Inputs_Sources!$D$375/Detail_PeerAnalysis!G27-1,"n/a"),"n/a") -> -0.021681338 | V32: =IFERROR(Detail_PeerAnalysis!K27/Detail_PeerAnalysis!H27-1,"n/a") -> -0.034908517 | W32: =IF(AND(ISNUMBER(Inputs_Sources!$D$332),ISNUMBER(Inputs_Sources!$D$377)),IFERROR((Detail_PeerAnalysis!D62*Inputs_Sources!$D$332+Detail_PeerAnalysis!E62*Inputs_Sources!$D$377)/Detail_PeerAnalysis!K27-1,"n/a"),"n/a") -> 0.020722605
B33: =Detail_PeerAnalysis!A14 -> Yamazaki Baking Co., Ltd. | D33: Core | E33: =Detail_PeerAnalysis!B14 -> TSE:2212 | F33: =Detail_PeerAnalysis!B28 -> 8224.6 | G33: =Detail_PeerAnalysis!C28 -> 8773.2 | H33: =IF(ISNUMBER(Inputs_Sources!$D$411),Inputs_Sources!$D$411,"n/a") -> 8564.4 | I33: =Detail_PeerAnalysis!D28 -> 8669.9 | J33: =IF(ISNUMBER(Detail_PeerAnalysis!E28),Detail_PeerAnalysis!E28,"n/a") -> 8746.3529 | K33: =IF(AND(ISNUMBER(Inputs_Sources!$D$251),ISNUMBER(Inputs_Sources!$D$413)),Detail_PeerAnalysis!D63*Inputs_Sources!$D$251+Detail_PeerAnalysis!E63*Inputs_Sources!$D$413,"n/a") -> 8925.6652 | L33: =IF(ISNUMBER(Inputs_Sources!$D$430),Inputs_Sources!$D$430,"n/a") -> 2678.3 | M33: =IF(ISNUMBER(Inputs_Sources!$D$431),Inputs_Sources!$D$431,"n/a") -> 2865.9 | N33: =IF(AND(ISNUMBER(Inputs_Sources!$D$411),ISNUMBER(Inputs_Sources!$D$432)),Inputs_Sources!$D$411*Inputs_Sources!$D$432/100,"n/a") -> 2835.6728 | O33: =IF(ISNUMBER(Detail_PeerAnalysis!M28),Detail_PeerAnalysis!M28,"n/a") -> 2834.9 | P33: =IF(AND(ISNUMBER(Inputs_Sources!$D$249),ISNUMBER(Inputs_Sources!$D$251),ISNUMBER(Inputs_Sources!$D$432),ISNUMBER(Inputs_Sources!$D$433)),(Detail_PeerAnalysis!D63*Inputs_Sources!$D$249*Inputs_Sources!$D$432+Detail_PeerAnalysis!E63*Inputs_Sources!$D$251*Inputs_Sources!$D$433)/100,"n/a") -> 2898.6933 | Q33: =IF(AND(ISNUMBER(Inputs_Sources!$D$251),ISNUMBER(Inputs_Sources!$D$413),ISNUMBER(Inputs_Sources!$D$433),ISNUMBER(Inputs_Sources!$D$434)),(Detail_PeerAnalysis!D63*Inputs_Sources!$D$251*Inputs_Sources!$D$433+Detail_PeerAnalysis!E63*Inputs_Sources!$D$413*Inputs_Sources!$D$434)/100,"n/a") -> 2967.3424 | R33: =IF(ISNUMBER(Inputs_Sources!$D$410),IFERROR(Detail_PeerAnalysis!F28/Inputs_Sources!$D$410-1,"n/a"),"n/a") -> 0.058971774 | S33: =IFERROR(Detail_PeerAnalysis!G28/Detail_PeerAnalysis!F28-1,"n/a") -> 0.12962082 | T33: =IF(ISNUMBER(Inputs_Sources!$D$412),IFERROR(Inputs_Sources!$D$412/Detail_PeerAnalysis!G28-1,"n/a"),"n/a") -> -0.016713483 | V33: =IFERROR(Detail_PeerAnalysis!K28/Detail_PeerAnalysis!H28-1,"n/a") -> 0.036884536 | W33: =IF(AND(ISNUMBER(Inputs_Sources!$D$250),ISNUMBER(Inputs_Sources!$D$414)),IFERROR((Detail_PeerAnalysis!D63*Inputs_Sources!$D$250+Detail_PeerAnalysis!E63*Inputs_Sources!$D$414)/Detail_PeerAnalysis!K28-1,"n/a"),"n/a") -> 0.03819267
B34: =Detail_PeerAnalysis!A15 -> ARYZTA AG | D34: Core | E34: =Detail_PeerAnalysis!B15 -> SWX:ARYN | F34: =Detail_PeerAnalysis!B29 -> 2374.1 | G34: =Detail_PeerAnalysis!C29 -> 2513.7 | H34: =IF(ISNUMBER(Inputs_Sources!$D$448),Inputs_Sources!$D$448,"n/a") -> 2594.7 | I34: =Detail_PeerAnalysis!D29 -> 2567.4 | J34: =IF(ISNUMBER(Detail_PeerAnalysis!E29),Detail_PeerAnalysis!E29,"n/a") -> 2569.3718 | K34: =IF(AND(ISNUMBER(Inputs_Sources!$D$256),ISNUMBER(Inputs_Sources!$D$450)),Detail_PeerAnalysis!D64*Inputs_Sources!$D$256+Detail_PeerAnalysis!E64*Inputs_Sources!$D$450,"n/a") -> 2599.2904 | L34: =IF(ISNUMBER(Inputs_Sources!$D$467),Inputs_Sources!$D$467,"n/a") -> 507.6 | M34: =IF(ISNUMBER(Inputs_Sources!$D$468),Inputs_Sources!$D$468,"n/a") -> 506.5 | N34: =IF(AND(ISNUMBER(Inputs_Sources!$D$448),ISNUMBER(Inputs_Sources!$D$469)),Inputs_Sources!$D$448*Inputs_Sources!$D$469/100,"n/a") -> 679.03299 | O34: =IF(ISNUMBER(Detail_PeerAnalysis!M29),Detail_PeerAnalysis!M29,"n/a") -> 514.8 | P34: =IF(AND(ISNUMBER(Inputs_Sources!$D$254),ISNUMBER(Inputs_Sources!$D$256),ISNUMBER(Inputs_Sources!$D$469),ISNUMBER(Inputs_Sources!$D$470)),(Detail_PeerAnalysis!D64*Inputs_Sources!$D$254*Inputs_Sources!$D$469+Detail_PeerAnalysis!E64*Inputs_Sources!$D$256*Inputs_Sources!$D$470)/100,"n/a") -> 676.04419 | Q34: =IF(AND(ISNUMBER(Inputs_Sources!$D$256),ISNUMBER(Inputs_Sources!$D$450),ISNUMBER(Inputs_Sources!$D$470),ISNUMBER(Inputs_Sources!$D$471)),(Detail_PeerAnalysis!D64*Inputs_Sources!$D$256*Inputs_Sources!$D$470+Detail_PeerAnalysis!E64*Inputs_Sources!$D$450*Inputs_Sources!$D$471)/100,"n/a") -> 690.88322 | R34: =IF(ISNUMBER(Inputs_Sources!$D$447),IFERROR(Detail_PeerAnalysis!F29/Inputs_Sources!$D$447-1,"n/a"),"n/a") -> 0.24441635 | S34: =IFERROR(Detail_PeerAnalysis!G29/Detail_PeerAnalysis!F29-1,"n/a") -> -0.026752455 | T34: =IF(ISNUMBER(Inputs_Sources!$D$449),IFERROR(Inputs_Sources!$D$449/Detail_PeerAnalysis!G29-1,"n/a"),"n/a") -> 0.23416841 | V34: =IFERROR(Detail_PeerAnalysis!K29/Detail_PeerAnalysis!H29-1,"n/a") -> 0.4331318 | W34: =IF(AND(ISNUMBER(Inputs_Sources!$D$255),ISNUMBER(Inputs_Sources!$D$451)),IFERROR((Detail_PeerAnalysis!D64*Inputs_Sources!$D$255+Detail_PeerAnalysis!E64*Inputs_Sources!$D$451)/Detail_PeerAnalysis!K29-1,"n/a"),"n/a") -> 0.043364056
B35: =Detail_PeerAnalysis!A16 -> The J. M. Smucker Company | D35: Secondary | E35: =Detail_PeerAnalysis!B16 -> NYSE:SJM | F35: =Detail_PeerAnalysis!B30 -> 8178.7 | G35: =Detail_PeerAnalysis!C30 -> 8726.1 | H35: =IF(ISNUMBER(Inputs_Sources!$D$485),Inputs_Sources!$D$485,"n/a") -> 9050.9 | I35: =Detail_PeerAnalysis!D30 -> 9156.9 | J35: =IF(ISNUMBER(Detail_PeerAnalysis!E30),Detail_PeerAnalysis!E30,"n/a") -> 8979.6414 | K35: =IF(AND(ISNUMBER(Inputs_Sources!$D$261),ISNUMBER(Inputs_Sources!$D$487)),Detail_PeerAnalysis!D65*Inputs_Sources!$D$261+Detail_PeerAnalysis!E65*Inputs_Sources!$D$487,"n/a") -> 9108.083 | L35: =IF(ISNUMBER(Inputs_Sources!$D$504),Inputs_Sources!$D$504,"n/a") -> 3118.3 | M35: =IF(ISNUMBER(Inputs_Sources!$D$505),Inputs_Sources!$D$505,"n/a") -> 3393.8 | O35: =IF(ISNUMBER(Detail_PeerAnalysis!M30),Detail_PeerAnalysis!M30,"n/a") -> 3475.1 | P35: =IF(AND(ISNUMBER(Inputs_Sources!$D$259),ISNUMBER(Inputs_Sources!$D$261),ISNUMBER(Inputs_Sources!$D$506),ISNUMBER(Inputs_Sources!$D$507)),(Detail_PeerAnalysis!D65*Inputs_Sources!$D$259*Inputs_Sources!$D$506+Detail_PeerAnalysis!E65*Inputs_Sources!$D$261*Inputs_Sources!$D$507)/100,"n/a") -> 3457.1684 | Q35: =IF(AND(ISNUMBER(Inputs_Sources!$D$261),ISNUMBER(Inputs_Sources!$D$487),ISNUMBER(Inputs_Sources!$D$507),ISNUMBER(Inputs_Sources!$D$508)),(Detail_PeerAnalysis!D65*Inputs_Sources!$D$261*Inputs_Sources!$D$507+Detail_PeerAnalysis!E65*Inputs_Sources!$D$487*Inputs_Sources!$D$508)/100,"n/a") -> 3508.5718 | R35: =IF(ISNUMBER(Inputs_Sources!$D$484),IFERROR(Detail_PeerAnalysis!F30/Inputs_Sources!$D$484-1,"n/a"),"n/a") -> 0.16875585 | S35: =IFERROR(Detail_PeerAnalysis!G30/Detail_PeerAnalysis!F30-1,"n/a") -> 0.15052559 | T35: =IF(ISNUMBER(Inputs_Sources!$D$486),IFERROR(Inputs_Sources!$D$486/Detail_PeerAnalysis!G30-1,"n/a"),"n/a") -> -0.060986921 | V35: =IFERROR(Detail_PeerAnalysis!K30/Detail_PeerAnalysis!H30-1,"n/a") -> -0.037685241 | W35: =IF(AND(ISNUMBER(Inputs_Sources!$D$260),ISNUMBER(Inputs_Sources!$D$488)),IFERROR((Detail_PeerAnalysis!D65*Inputs_Sources!$D$260+Detail_PeerAnalysis!E65*Inputs_Sources!$D$488)/Detail_PeerAnalysis!K30-1,"n/a"),"n/a") -> n/a
B36: =Detail_PeerAnalysis!A17 -> The Campbell's Company | D36: Secondary | E36: =Detail_PeerAnalysis!B17 -> NasdaqGS:CPB | F36: =Detail_PeerAnalysis!B31 -> 9636 | G36: =Detail_PeerAnalysis!C31 -> 10253 | H36: =IF(ISNUMBER(Inputs_Sources!$D$522),Inputs_Sources!$D$522,"n/a") -> 9744 | I36: =Detail_PeerAnalysis!D31 -> 9744 | J36: =IF(ISNUMBER(Detail_PeerAnalysis!E31),Detail_PeerAnalysis!E31,"n/a") -> 9491.011 | K36: =IF(AND(ISNUMBER(Inputs_Sources!$D$266),ISNUMBER(Inputs_Sources!$D$524)),Detail_PeerAnalysis!D66*Inputs_Sources!$D$266+Detail_PeerAnalysis!E66*Inputs_Sources!$D$524,"n/a") -> 9487.1781 | L36: =IF(ISNUMBER(Inputs_Sources!$D$541),Inputs_Sources!$D$541,"n/a") -> 3017 | M36: =IF(ISNUMBER(Inputs_Sources!$D$542),Inputs_Sources!$D$542,"n/a") -> 3151 | O36: =IF(ISNUMBER(Detail_PeerAnalysis!M31),Detail_PeerAnalysis!M31,"n/a") -> 2781 | P36: =IF(AND(ISNUMBER(Inputs_Sources!$D$264),ISNUMBER(Inputs_Sources!$D$266),ISNUMBER(Inputs_Sources!$D$543),ISNUMBER(Inputs_Sources!$D$544)),(Detail_PeerAnalysis!D66*Inputs_Sources!$D$264*Inputs_Sources!$D$543+Detail_PeerAnalysis!E66*Inputs_Sources!$D$266*Inputs_Sources!$D$544)/100,"n/a") -> 2646.0614 | Q36: =IF(AND(ISNUMBER(Inputs_Sources!$D$266),ISNUMBER(Inputs_Sources!$D$524),ISNUMBER(Inputs_Sources!$D$544),ISNUMBER(Inputs_Sources!$D$545)),(Detail_PeerAnalysis!D66*Inputs_Sources!$D$266*Inputs_Sources!$D$544+Detail_PeerAnalysis!E66*Inputs_Sources!$D$524*Inputs_Sources!$D$545)/100,"n/a") -> 2704.567 | R36: =IF(ISNUMBER(Inputs_Sources!$D$521),IFERROR(Detail_PeerAnalysis!F31/Inputs_Sources!$D$521-1,"n/a"),"n/a") -> -0.0023500448 | S36: =IFERROR(Detail_PeerAnalysis!G31/Detail_PeerAnalysis!F31-1,"n/a") -> 0.058889512 | T36: =IF(ISNUMBER(Inputs_Sources!$D$523),IFERROR(Inputs_Sources!$D$523/Detail_PeerAnalysis!G31-1,"n/a"),"n/a") -> -0.15572034 | V36: =IFERROR(Detail_PeerAnalysis!K31/Detail_PeerAnalysis!H31-1,"n/a") -> -0.088924404 | W36: =IF(AND(ISNUMBER(Inputs_Sources!$D$265),ISNUMBER(Inputs_Sources!$D$525)),IFERROR((Detail_PeerAnalysis!D66*Inputs_Sources!$D$265+Detail_PeerAnalysis!E66*Inputs_Sources!$D$525)/Detail_PeerAnalysis!K31-1,"n/a"),"n/a") -> n/a
B37: =Detail_PeerAnalysis!A18 -> Mondelez International, Inc. | D37: Secondary | E37: =Detail_PeerAnalysis!B18 -> NasdaqGS:MDLZ | F37: =Detail_PeerAnalysis!B32 -> 36441 | G37: =Detail_PeerAnalysis!C32 -> 38537 | H37: =IF(ISNUMBER(Inputs_Sources!$D$559),Inputs_Sources!$D$559,"n/a") -> 40101.2 | I37: =Detail_PeerAnalysis!D32 -> 39675 | J37: =IF(ISNUMBER(Detail_PeerAnalysis!E32),Detail_PeerAnalysis!E32,"n/a") -> 40994.158 | K37: =IF(AND(ISNUMBER(Inputs_Sources!$D$271),ISNUMBER(Inputs_Sources!$D$561)),Detail_PeerAnalysis!D67*Inputs_Sources!$D$271+Detail_PeerAnalysis!E67*Inputs_Sources!$D$561,"n/a") -> 42355.863 | L37: =IF(ISNUMBER(Inputs_Sources!$D$578),Inputs_Sources!$D$578,"n/a") -> 14257 | M37: =IF(ISNUMBER(Inputs_Sources!$D$579),Inputs_Sources!$D$579,"n/a") -> 10935 | N37: =IF(AND(ISNUMBER(Inputs_Sources!$D$559),ISNUMBER(Inputs_Sources!$D$580)),Inputs_Sources!$D$559*Inputs_Sources!$D$580/100,"n/a") -> 13269.487 | O37: =IF(ISNUMBER(Detail_PeerAnalysis!M32),Detail_PeerAnalysis!M32,"n/a") -> 12357 | P37: =IF(AND(ISNUMBER(Inputs_Sources!$D$269),ISNUMBER(Inputs_Sources!$D$271),ISNUMBER(Inputs_Sources!$D$580),ISNUMBER(Inputs_Sources!$D$581)),(Detail_PeerAnalysis!D67*Inputs_Sources!$D$269*Inputs_Sources!$D$580+Detail_PeerAnalysis!E67*Inputs_Sources!$D$271*Inputs_Sources!$D$581)/100,"n/a") -> 14137.573 | Q37: =IF(AND(ISNUMBER(Inputs_Sources!$D$271),ISNUMBER(Inputs_Sources!$D$561),ISNUMBER(Inputs_Sources!$D$581),ISNUMBER(Inputs_Sources!$D$582)),(Detail_PeerAnalysis!D67*Inputs_Sources!$D$271*Inputs_Sources!$D$581+Detail_PeerAnalysis!E67*Inputs_Sources!$D$561*Inputs_Sources!$D$582)/100,"n/a") -> 14882.185 | R37: =IF(ISNUMBER(Inputs_Sources!$D$558),IFERROR(Detail_PeerAnalysis!F32/Inputs_Sources!$D$558-1,"n/a"),"n/a") -> 0.11928967 | S37: =IFERROR(Detail_PeerAnalysis!G32/Detail_PeerAnalysis!F32-1,"n/a") -> -0.35529716 | T37: =IF(ISNUMBER(Inputs_Sources!$D$560),IFERROR(Inputs_Sources!$D$560/Detail_PeerAnalysis!G32-1,"n/a"),"n/a") -> 0.34973948 | V37: =IFERROR(Detail_PeerAnalysis!K32/Detail_PeerAnalysis!H32-1,"n/a") -> 0.17651875 | W37: =IF(AND(ISNUMBER(Inputs_Sources!$D$270),ISNUMBER(Inputs_Sources!$D$562)),IFERROR((Detail_PeerAnalysis!D67*Inputs_Sources!$D$270+Detail_PeerAnalysis!E67*Inputs_Sources!$D$562)/Detail_PeerAnalysis!K32-1,"n/a"),"n/a") -> 0.063640532
B38: =Detail_PeerAnalysis!A19 -> Arca Continental, S.A.B. de C.V. | D38: Secondary | E38: =Detail_PeerAnalysis!B19 -> BMV:AC | F38: =Detail_PeerAnalysis!B33 -> 13149.5 | G38: =Detail_PeerAnalysis!C33 -> 13058.3 | H38: =IF(ISNUMBER(Inputs_Sources!$D$596),Inputs_Sources!$D$596,"n/a") -> 14453.8 | I38: =Detail_PeerAnalysis!D33 -> 13945.2 | J38: =IF(ISNUMBER(Detail_PeerAnalysis!E33),Detail_PeerAnalysis!E33,"n/a") -> 14591.724 | K38: =IF(AND(ISNUMBER(Inputs_Sources!$D$276),ISNUMBER(Inputs_Sources!$D$598)),Detail_PeerAnalysis!D68*Inputs_Sources!$D$276+Detail_PeerAnalysis!E68*Inputs_Sources!$D$598,"n/a") -> 15424.9 | L38: =IF(ISNUMBER(Inputs_Sources!$D$615),Inputs_Sources!$D$615,"n/a") -> 6131.3 | M38: =IF(ISNUMBER(Inputs_Sources!$D$616),Inputs_Sources!$D$616,"n/a") -> 6074.7 | N38: =IF(AND(ISNUMBER(Inputs_Sources!$D$596),ISNUMBER(Inputs_Sources!$D$617)),Inputs_Sources!$D$596*Inputs_Sources!$D$617/100,"n/a") -> 6855.4373 | O38: =IF(ISNUMBER(Detail_PeerAnalysis!M33),Detail_PeerAnalysis!M33,"n/a") -> 6537.9 | P38: =IF(AND(ISNUMBER(Inputs_Sources!$D$274),ISNUMBER(Inputs_Sources!$D$276),ISNUMBER(Inputs_Sources!$D$617),ISNUMBER(Inputs_Sources!$D$618)),(Detail_PeerAnalysis!D68*Inputs_Sources!$D$274*Inputs_Sources!$D$617+Detail_PeerAnalysis!E68*Inputs_Sources!$D$276*Inputs_Sources!$D$618)/100,"n/a") -> 6933.5517 | Q38: =IF(AND(ISNUMBER(Inputs_Sources!$D$276),ISNUMBER(Inputs_Sources!$D$598),ISNUMBER(Inputs_Sources!$D$618),ISNUMBER(Inputs_Sources!$D$619)),(Detail_PeerAnalysis!D68*Inputs_Sources!$D$276*Inputs_Sources!$D$618+Detail_PeerAnalysis!E68*Inputs_Sources!$D$598*Inputs_Sources!$D$619)/100,"n/a") -> 7337.9331 | R38: =IF(ISNUMBER(Inputs_Sources!$D$595),IFERROR(Detail_PeerAnalysis!F33/Inputs_Sources!$D$595-1,"n/a"),"n/a") -> 0.10567515 | S38: =IFERROR(Detail_PeerAnalysis!G33/Detail_PeerAnalysis!F33-1,"n/a") -> -0.022470181 | T38: =IF(ISNUMBER(Inputs_Sources!$D$597),IFERROR(Inputs_Sources!$D$597/Detail_PeerAnalysis!G33-1,"n/a"),"n/a") -> 0.1533496 | V38: =IFERROR(Detail_PeerAnalysis!K33/Detail_PeerAnalysis!H33-1,"n/a") -> 0.10463466 | W38: =IF(AND(ISNUMBER(Inputs_Sources!$D$275),ISNUMBER(Inputs_Sources!$D$599)),IFERROR((Detail_PeerAnalysis!D68*Inputs_Sources!$D$275+Detail_PeerAnalysis!E68*Inputs_Sources!$D$599)/Detail_PeerAnalysis!K33-1,"n/a"),"n/a") -> 0.065505125
B39: =Detail_PeerAnalysis!A20 -> PepsiCo, Inc. | D39: Secondary | E39: =Detail_PeerAnalysis!B20 -> NasdaqGS:PEP | F39: =Detail_PeerAnalysis!B34 -> 91854 | G39: =Detail_PeerAnalysis!C34 -> 93925 | H39: =IF(ISNUMBER(Inputs_Sources!$D$633),Inputs_Sources!$D$633,"n/a") -> 99300.5 | I39: =Detail_PeerAnalysis!D34 -> 98241 | J39: =IF(ISNUMBER(Detail_PeerAnalysis!E34),Detail_PeerAnalysis!E34,"n/a") -> 101251.48 | K39: =IF(AND(ISNUMBER(Inputs_Sources!$D$281),ISNUMBER(Inputs_Sources!$D$635)),Detail_PeerAnalysis!D69*Inputs_Sources!$D$281+Detail_PeerAnalysis!E69*Inputs_Sources!$D$635,"n/a") -> 104438.72 | L39: =IF(ISNUMBER(Inputs_Sources!$D$652),Inputs_Sources!$D$652,"n/a") -> 50419 | M39: =IF(ISNUMBER(Inputs_Sources!$D$653),Inputs_Sources!$D$653,"n/a") -> 51152 | N39: =IF(AND(ISNUMBER(Inputs_Sources!$D$633),ISNUMBER(Inputs_Sources!$D$654)),Inputs_Sources!$D$633*Inputs_Sources!$D$654/100,"n/a") -> 53711.64 | O39: =IF(ISNUMBER(Detail_PeerAnalysis!M34),Detail_PeerAnalysis!M34,"n/a") -> 53371 | P39: =IF(AND(ISNUMBER(Inputs_Sources!$D$279),ISNUMBER(Inputs_Sources!$D$281),ISNUMBER(Inputs_Sources!$D$654),ISNUMBER(Inputs_Sources!$D$655)),(Detail_PeerAnalysis!D69*Inputs_Sources!$D$279*Inputs_Sources!$D$654+Detail_PeerAnalysis!E69*Inputs_Sources!$D$281*Inputs_Sources!$D$655)/100,"n/a") -> 54694.654 | Q39: =IF(AND(ISNUMBER(Inputs_Sources!$D$281),ISNUMBER(Inputs_Sources!$D$635),ISNUMBER(Inputs_Sources!$D$655),ISNUMBER(Inputs_Sources!$D$656)),(Detail_PeerAnalysis!D69*Inputs_Sources!$D$281*Inputs_Sources!$D$655+Detail_PeerAnalysis!E69*Inputs_Sources!$D$635*Inputs_Sources!$D$656)/100,"n/a") -> 56454.986 | R39: =IF(ISNUMBER(Inputs_Sources!$D$632),IFERROR(Detail_PeerAnalysis!F34/Inputs_Sources!$D$632-1,"n/a"),"n/a") -> 0.060086627 | S39: =IFERROR(Detail_PeerAnalysis!G34/Detail_PeerAnalysis!F34-1,"n/a") -> 0.018607779 | T39: =IF(ISNUMBER(Inputs_Sources!$D$634),IFERROR(Inputs_Sources!$D$634/Detail_PeerAnalysis!G34-1,"n/a"),"n/a") -> 0.048228238 | V39: =IFERROR(Detail_PeerAnalysis!K34/Detail_PeerAnalysis!H34-1,"n/a") -> 0.015799878 | W39: =IF(AND(ISNUMBER(Inputs_Sources!$D$280),ISNUMBER(Inputs_Sources!$D$636)),IFERROR((Detail_PeerAnalysis!D69*Inputs_Sources!$D$280+Detail_PeerAnalysis!E69*Inputs_Sources!$D$636)/Detail_PeerAnalysis!K34-1,"n/a"),"n/a") -> 0.04643211
B40: =Detail_PeerAnalysis!A11 -> Grupo Bimbo, S.A.B. de C.V. (subject) | D40: Subject Company >> | E40: =Detail_PeerAnalysis!B11 -> BMV:BIMBO A | F40: =Detail_PeerAnalysis!B25 -> 22097.246 | G40: =Detail_PeerAnalysis!C25 -> 23105.309 | H40: =Inputs_Sources!$D$669/Inputs_Sources!$D$10 -> 23068.063 | I40: =Detail_PeerAnalysis!D25 -> 22805.509 | J40: =Detail_PeerAnalysis!E25 -> 23879.916 | K40: =(Detail_PeerAnalysis!D60*Inputs_Sources!$D$681+Detail_PeerAnalysis!E60*Inputs_Sources!$D$693)/Inputs_Sources!$D$10 -> 25085.161 | L40: =Detail_TearSheet!F9/Inputs_Sources!$D$10 -> 11630.932 | M40: =Detail_TearSheet!G9/Inputs_Sources!$D$10 -> 12134.948 | N40: =Inputs_Sources!$D$669*Inputs_Sources!$D$679/100/Inputs_Sources!$D$10 -> 12064.597 | O40: =Detail_PeerAnalysis!M25 -> 11986.052 | P40: =(Detail_PeerAnalysis!D60*Inputs_Sources!$D$669*Inputs_Sources!$D$679+Detail_PeerAnalysis!E60*Inputs_Sources!$D$681*Inputs_Sources!$D$691)/100/Inputs_Sources!$D$10 -> 12432.155 | Q40: =(Detail_PeerAnalysis!D60*Inputs_Sources!$D$681*Inputs_Sources!$D$691+Detail_PeerAnalysis!E60*Inputs_Sources!$D$693*Inputs_Sources!$D$703)/100/Inputs_Sources!$D$10 -> 13054.285 | R40: =IFERROR(Detail_TearSheet!F19/Detail_TearSheet!E19-1,"n/a") -> 0.0096647374 | S40: =IFERROR(Detail_TearSheet!G19/Detail_TearSheet!F19-1,"n/a") -> 0.071800696 | T40: =IFERROR(Inputs_Sources!$D$670/Detail_TearSheet!G19-1,"n/a") -> 0.044753864 | V40: =IFERROR(Detail_PeerAnalysis!K25/Detail_PeerAnalysis!H25-1,"n/a") -> 0.055595135 | W40: =IFERROR((Detail_PeerAnalysis!D60*Inputs_Sources!$D$682+Detail_PeerAnalysis!E60*Inputs_Sources!$D$694)/(Detail_PeerAnalysis!H60)-1,"n/a") -> 0.059500621
F45: Free Cash Flow Yield (%) | L45: Price / Sales (x) | R45: Price / Free Cash Flow (x)
F47: Performance Valuations
F48: FY2024 | G48: FY2025 | H48: FY2026 | I48: LTM | J48: NTM | K48: STM | L48: FY2024 | M48: FY2025 | N48: FY2026 | O48: LTM | P48: NTM | Q48: STM | R48: FY2024 | S48: FY2025 | T48: FY2026 | U48: LTM | V48: NTM | W48: STM
B49: Company Name | D49: Group | E49: Exchange:Ticker
B50: =Detail_PeerAnalysis!A12 -> Flowers Foods, Inc. | D50: Core | E50: =Detail_PeerAnalysis!B12 -> NYSE:FLO | F50: =IFERROR(IF(ISNUMBER(Inputs_Sources!$D$341),(Inputs_Sources!$D$341)/Detail_PeerAnalysis!I12,"n/a"),"n/a") -> 0.12117002 | G50: =IFERROR(IF(ISNUMBER(Inputs_Sources!$D$342),(Inputs_Sources!$D$342)/Detail_PeerAnalysis!I12,"n/a"),"n/a") -> 0.17064135 | H50: =IFERROR(IF(ISNUMBER(Inputs_Sources!$D$361),(Inputs_Sources!$D$361)/Detail_PeerAnalysis!I12,"n/a"),"n/a") -> 0.17038666 | I50: =IFERROR(IF(ISNUMBER(Detail_PeerAnalysis!N26),(Detail_PeerAnalysis!N26)/Detail_PeerAnalysis!I12,"n/a"),"n/a") -> 0.2303774 | J50: =IFERROR(IF(ISNUMBER((Detail_PeerAnalysis!D61*Inputs_Sources!$D$361+Detail_PeerAnalysis!E61*Inputs_Sources!$D$362)),((Detail_PeerAnalysis!D61*Inputs_Sources!$D$361+Detail_PeerAnalysis!E61*Inputs_Sources!$D$362))/Detail_PeerAnalysis!I12,"n/a"),"n/a") -> 0.14567094 | K50: =IFERROR(IF(ISNUMBER((Detail_PeerAnalysis!D61*Inputs_Sources!$D$362+Detail_PeerAnalysis!E61*Inputs_Sources!$D$363)),((Detail_PeerAnalysis!D61*Inputs_Sources!$D$362+Detail_PeerAnalysis!E61*Inputs_Sources!$D$363))/Detail_PeerAnalysis!I12,"n/a"),"n/a") -> 0.13709012 | L50: =IFERROR(Detail_PeerAnalysis!I12/F31,"n/a") -> 0.25388459 | M50: =IFERROR(Detail_PeerAnalysis!I12/G31,"n/a") -> 0.24649482 | N50: =IFERROR(Detail_PeerAnalysis!I12/H31,"n/a") -> 0.25527011 | O50: =IFERROR(Detail_PeerAnalysis!I12/I31,"n/a") -> 0.24803308 | P50: =IFERROR(Detail_PeerAnalysis!I12/J31,"n/a") -> 0.25596159 | Q50: =IFERROR(Detail_PeerAnalysis!I12/K31,"n/a") -> 0.2571771 | R50: =IFERROR(IF(ISNUMBER(Inputs_Sources!$D$341),IF((Inputs_Sources!$D$341)>0,Detail_PeerAnalysis!I12/(Inputs_Sources!$D$341),"n.m."),"n/a"),"n/a") -> 8.2528662 | S50: =IFERROR(IF(ISNUMBER(Inputs_Sources!$D$342),IF((Inputs_Sources!$D$342)>0,Detail_PeerAnalysis!I12/(Inputs_Sources!$D$342),"n.m."),"n/a"),"n/a") -> 5.8602442 | T50: =IFERROR(IF(ISNUMBER(Inputs_Sources!$D$361),IF((Inputs_Sources!$D$361)>0,Detail_PeerAnalysis!I12/(Inputs_Sources!$D$361),"n.m."),"n/a"),"n/a") -> 5.8690039 | U50: =IFERROR(IF(ISNUMBER(Detail_PeerAnalysis!N26),IF((Detail_PeerAnalysis!N26)>0,Detail_PeerAnalysis!I12/(Detail_PeerAnalysis!N26),"n.m."),"n/a"),"n/a") -> 4.3407035 | V50: =IFERROR(IF(ISNUMBER((Detail_PeerAnalysis!D61*Inputs_Sources!$D$361+Detail_PeerAnalysis!E61*Inputs_Sources!$D$362)),IF(((Detail_PeerAnalysis!D61*Inputs_Sources!$D$361+Detail_PeerAnalysis!E61*Inputs_Sources!$D$362))>0,Detail_PeerAnalysis!I12/((Detail_PeerAnalysis!D61*Inputs_Sources!$D$361+Detail_PeerAnalysis!E61*Inputs_Sources!$D$362)),"n.m."),"n/a"),"n/a") -> 6.8647872 | W50: =IFERROR(IF(ISNUMBER((Detail_PeerAnalysis!D61*Inputs_Sources!$D$362+Detail_PeerAnalysis!E61*Inputs_Sources!$D$363)),IF(((Detail_PeerAnalysis!D61*Inputs_Sources!$D$362+Detail_PeerAnalysis!E61*Inputs_Sources!$D$363))>0,Detail_PeerAnalysis!I12/((Detail_PeerAnalysis!D61*Inputs_Sources!$D$362+Detail_PeerAnalysis!E61*Inputs_Sources!$D$363)),"n.m."),"n/a"),"n/a") -> 7.2944716
B51: =Detail_PeerAnalysis!A13 -> Gruma, S.A.B. de C.V. | D51: Core | E51: =Detail_PeerAnalysis!B13 -> BMV:GRUMA B | F51: =IFERROR(IF(ISNUMBER(Inputs_Sources!$D$378),(Inputs_Sources!$D$378)/Detail_PeerAnalysis!I13,"n/a"),"n/a") -> n/a | G51: =IFERROR(IF(ISNUMBER(Inputs_Sources!$D$379),(Inputs_Sources!$D$379)/Detail_PeerAnalysis!I13,"n/a"),"n/a") -> n/a | H51: =IFERROR(IF(ISNUMBER(Inputs_Sources!$D$398),(Inputs_Sources!$D$398)/Detail_PeerAnalysis!I13,"n/a"),"n/a") -> 0.039749501 | I51: =IFERROR(IF(ISNUMBER(Detail_PeerAnalysis!N27),(Detail_PeerAnalysis!N27)/Detail_PeerAnalysis!I13,"n/a"),"n/a") -> n/a | J51: =IFERROR(IF(ISNUMBER((Detail_PeerAnalysis!D62*Inputs_Sources!$D$398+Detail_PeerAnalysis!E62*Inputs_Sources!$D$399)),((Detail_PeerAnalysis!D62*Inputs_Sources!$D$398+Detail_PeerAnalysis!E62*Inputs_Sources!$D$399))/Detail_PeerAnalysis!I13,"n/a"),"n/a") -> 0.10393969 | K51: =IFERROR(IF(ISNUMBER((Detail_PeerAnalysis!D62*Inputs_Sources!$D$399+Detail_PeerAnalysis!E62*Inputs_Sources!$D$400)),((Detail_PeerAnalysis!D62*Inputs_Sources!$D$399+Detail_PeerAnalysis!E62*Inputs_Sources!$D$400))/Detail_PeerAnalysis!I13,"n/a"),"n/a") -> 0.12068771 | L51: =IFERROR(Detail_PeerAnalysis!I13/F32,"n/a") -> 0.67880278 | M51: =IFERROR(Detail_PeerAnalysis!I13/G32,"n/a") -> 0.69076111 | N51: =IFERROR(Detail_PeerAnalysis!I13/H32,"n/a") -> 0.66231858 | O51: =IFERROR(Detail_PeerAnalysis!I13/I32,"n/a") -> 0.67742431 | P51: =IFERROR(Detail_PeerAnalysis!I13/J32,"n/a") -> 0.67874536 | Q51: =IFERROR(Detail_PeerAnalysis!I13/K32,"n/a") -> 0.66924548 | R51: =IFERROR(IF(ISNUMBER(Inputs_Sources!$D$378),IF((Inputs_Sources!$D$378)>0,Detail_PeerAnalysis!I13/(Inputs_Sources!$D$378),"n.m."),"n/a"),"n/a") -> n/a | S51: =IFERROR(IF(ISNUMBER(Inputs_Sources!$D$379),IF((Inputs_Sources!$D$379)>0,Detail_PeerAnalysis!I13/(Inputs_Sources!$D$379),"n.m."),"n/a"),"n/a") -> n/a | T51: =IFERROR(IF(ISNUMBER(Inputs_Sources!$D$398),IF((Inputs_Sources!$D$398)>0,Detail_PeerAnalysis!I13/(Inputs_Sources!$D$398),"n.m."),"n/a"),"n/a") -> 25.157549 | U51: =IFERROR(IF(ISNUMBER(Detail_PeerAnalysis!N27),IF((Detail_PeerAnalysis!N27)>0,Detail_PeerAnalysis!I13/(Detail_PeerAnalysis!N27),"n.m."),"n/a"),"n/a") -> n/a | V51: =IFERROR(IF(ISNUMBER((Detail_PeerAnalysis!D62*Inputs_Sources!$D$398+Detail_PeerAnalysis!E62*Inputs_Sources!$D$399)),IF(((Detail_PeerAnalysis!D62*Inputs_Sources!$D$398+Detail_PeerAnalysis!E62*Inputs_Sources!$D$399))>0,Detail_PeerAnalysis!I13/((Detail_PeerAnalysis!D62*Inputs_Sources!$D$398+Detail_PeerAnalysis!E62*Inputs_Sources!$D$399)),"n.m."),"n/a"),"n/a") -> 9.6209641 | W51: =IFERROR(IF(ISNUMBER((Detail_PeerAnalysis!D62*Inputs_Sources!$D$399+Detail_PeerAnalysis!E62*Inputs_Sources!$D$400)),IF(((Detail_PeerAnalysis!D62*Inputs_Sources!$D$399+Detail_PeerAnalysis!E62*Inputs_Sources!$D$400))>0,Detail_PeerAnalysis!I13/((Detail_PeerAnalysis!D62*Inputs_Sources!$D$399+Detail_PeerAnalysis!E62*Inputs_Sources!$D$400)),"n.m."),"n/a"),"n/a") -> 8.2858476
B52: =Detail_PeerAnalysis!A14 -> Yamazaki Baking Co., Ltd. | D52: Core | E52: =Detail_PeerAnalysis!B14 -> TSE:2212 | F52: =IFERROR(IF(ISNUMBER(Inputs_Sources!$D$415),(Inputs_Sources!$D$415)/Detail_PeerAnalysis!I14,"n/a"),"n/a") -> 0.038709812 | G52: =IFERROR(IF(ISNUMBER(Inputs_Sources!$D$416),(Inputs_Sources!$D$416)/Detail_PeerAnalysis!I14,"n/a"),"n/a") -> 0.035513782 | H52: =IFERROR(IF(ISNUMBER(Inputs_Sources!$D$435),(Inputs_Sources!$D$435)/Detail_PeerAnalysis!I14,"n/a"),"n/a") -> 0.038772891 | I52: =IFERROR(IF(ISNUMBER(Detail_PeerAnalysis!N28),(Detail_PeerAnalysis!N28)/Detail_PeerAnalysis!I14,"n/a"),"n/a") -> 0.023844067 | J52: =IFERROR(IF(ISNUMBER((Detail_PeerAnalysis!D63*Inputs_Sources!$D$435+Detail_PeerAnalysis!E63*Inputs_Sources!$D$436)),((Detail_PeerAnalysis!D63*Inputs_Sources!$D$435+Detail_PeerAnalysis!E63*Inputs_Sources!$D$436))/Detail_PeerAnalysis!I14,"n/a"),"n/a") -> 0.046072836 | K52: =IFERROR(IF(ISNUMBER((Detail_PeerAnalysis!D63*Inputs_Sources!$D$436+Detail_PeerAnalysis!E63*Inputs_Sources!$D$437)),((Detail_PeerAnalysis!D63*Inputs_Sources!$D$436+Detail_PeerAnalysis!E63*Inputs_Sources!$D$437))/Detail_PeerAnalysis!I14,"n/a"),"n/a") -> 0.053950785 | L52: =IFERROR(Detail_PeerAnalysis!I14/F33,"n/a") -> 0.57825307 | M52: =IFERROR(Detail_PeerAnalysis!I14/G33,"n/a") -> 0.54209412 | N52: =IFERROR(Detail_PeerAnalysis!I14/H33,"n/a") -> 0.55531037 | O52: =IFERROR(Detail_PeerAnalysis!I14/I33,"n/a") -> 0.54855306 | P52: =IFERROR(Detail_PeerAnalysis!I14/J33,"n/a") -> 0.54375809 | Q52: =IFERROR(Detail_PeerAnalysis!I14/K33,"n/a") -> 0.53283425 | R52: =IFERROR(IF(ISNUMBER(Inputs_Sources!$D$415),IF((Inputs_Sources!$D$415)>0,Detail_PeerAnalysis!I14/(Inputs_Sources!$D$415),"n.m."),"n/a"),"n/a") -> 25.833244 | S52: =IFERROR(IF(ISNUMBER(Inputs_Sources!$D$416),IF((Inputs_Sources!$D$416)>0,Detail_PeerAnalysis!I14/(Inputs_Sources!$D$416),"n.m."),"n/a"),"n/a") -> 28.158083 | T52: =IFERROR(IF(ISNUMBER(Inputs_Sources!$D$435),IF((Inputs_Sources!$D$435)>0,Detail_PeerAnalysis!I14/(Inputs_Sources!$D$435),"n.m."),"n/a"),"n/a") -> 25.791216 | U52: =IFERROR(IF(ISNUMBER(Detail_PeerAnalysis!N28),IF((Detail_PeerAnalysis!N28)>0,Detail_PeerAnalysis!I14/(Detail_PeerAnalysis!N28),"n.m."),"n/a"),"n/a") -> 41.939155 | V52: =IFERROR(IF(ISNUMBER((Detail_PeerAnalysis!D63*Inputs_Sources!$D$435+Detail_PeerAnalysis!E63*Inputs_Sources!$D$436)),IF(((Detail_PeerAnalysis!D63*Inputs_Sources!$D$435+Detail_PeerAnalysis!E63*Inputs_Sources!$D$436))>0,Detail_PeerAnalysis!I14/((Detail_PeerAnalysis!D63*Inputs_Sources!$D$435+Detail_PeerAnalysis!E63*Inputs_Sources!$D$436)),"n.m."),"n/a"),"n/a") -> 21.704763 | W52: =IFERROR(IF(ISNUMBER((Detail_PeerAnalysis!D63*Inputs_Sources!$D$436+Detail_PeerAnalysis!E63*Inputs_Sources!$D$437)),IF(((Detail_PeerAnalysis!D63*Inputs_Sources!$D$436+Detail_PeerAnalysis!E63*Inputs_Sources!$D$437))>0,Detail_PeerAnalysis!I14/((Detail_PeerAnalysis!D63*Inputs_Sources!$D$436+Detail_PeerAnalysis!E63*Inputs_Sources!$D$437)),"n.m."),"n/a"),"n/a") -> 18.535411
B53: =Detail_PeerAnalysis!A15 -> ARYZTA AG | D53: Core | E53: =Detail_PeerAnalysis!B15 -> SWX:ARYN | F53: =IFERROR(IF(ISNUMBER(Inputs_Sources!$D$452),(Inputs_Sources!$D$452)/Detail_PeerAnalysis!I15,"n/a"),"n/a") -> 0.13258943 | G53: =IFERROR(IF(ISNUMBER(Inputs_Sources!$D$453),(Inputs_Sources!$D$453)/Detail_PeerAnalysis!I15,"n/a"),"n/a") -> 0.12709222 | H53: =IFERROR(IF(ISNUMBER(Inputs_Sources!$D$472),(Inputs_Sources!$D$472)/Detail_PeerAnalysis!I15,"n/a"),"n/a") -> 0.114383 | I53: =IFERROR(IF(ISNUMBER(Detail_PeerAnalysis!N29),(Detail_PeerAnalysis!N29)/Detail_PeerAnalysis!I15,"n/a"),"n/a") -> 0.11330817 | J53: =IFERROR(IF(ISNUMBER((Detail_PeerAnalysis!D64*Inputs_Sources!$D$472+Detail_PeerAnalysis!E64*Inputs_Sources!$D$473)),((Detail_PeerAnalysis!D64*Inputs_Sources!$D$472+Detail_PeerAnalysis!E64*Inputs_Sources!$D$473))/Detail_PeerAnalysis!I15,"n/a"),"n/a") -> 0.14033046 | K53: =IFERROR(IF(ISNUMBER((Detail_PeerAnalysis!D64*Inputs_Sources!$D$473+Detail_PeerAnalysis!E64*Inputs_Sources!$D$474)),((Detail_PeerAnalysis!D64*Inputs_Sources!$D$473+Detail_PeerAnalysis!E64*Inputs_Sources!$D$474))/Detail_PeerAnalysis!I15,"n/a"),"n/a") -> 0.16114141 | L53: =IFERROR(Detail_PeerAnalysis!I15/F34,"n/a") -> 0.51337349 | M53: =IFERROR(Detail_PeerAnalysis!I15/G34,"n/a") -> 0.48486295 | N53: =IFERROR(Detail_PeerAnalysis!I15/H34,"n/a") -> 0.46972675 | O53: =IFERROR(Detail_PeerAnalysis!I15/I34,"n/a") -> 0.47472151 | P53: =IFERROR(Detail_PeerAnalysis!I15/J34,"n/a") -> 0.4743572 | Q53: =IFERROR(Detail_PeerAnalysis!I15/K34,"n/a") -> 0.4688972 | R53: =IFERROR(IF(ISNUMBER(Inputs_Sources!$D$452),IF((Inputs_Sources!$D$452)>0,Detail_PeerAnalysis!I15/(Inputs_Sources!$D$452),"n.m."),"n/a"),"n/a") -> 7.5420792 | S53: =IFERROR(IF(ISNUMBER(Inputs_Sources!$D$453),IF((Inputs_Sources!$D$453)>0,Detail_PeerAnalysis!I15/(Inputs_Sources!$D$453),"n.m."),"n/a"),"n/a") -> 7.8683021 | T53: =IFERROR(IF(ISNUMBER(Inputs_Sources!$D$472),IF((Inputs_Sources!$D$472)>0,Detail_PeerAnalysis!I15/(Inputs_Sources!$D$472),"n.m."),"n/a"),"n/a") -> 8.7425579 | U53: =IFERROR(IF(ISNUMBER(Detail_PeerAnalysis!N29),IF((Detail_PeerAnalysis!N29)>0,Detail_PeerAnalysis!I15/(Detail_PeerAnalysis!N29),"n.m."),"n/a"),"n/a") -> 8.8254888 | V53: =IFERROR(IF(ISNUMBER((Detail_PeerAnalysis!D64*Inputs_Sources!$D$472+Detail_PeerAnalysis!E64*Inputs_Sources!$D$473)),IF(((Detail_PeerAnalysis!D64*Inputs_Sources!$D$472+Detail_PeerAnalysis!E64*Inputs_Sources!$D$473))>0,Detail_PeerAnalysis!I15/((Detail_PeerAnalysis!D64*Inputs_Sources!$D$472+Detail_PeerAnalysis!E64*Inputs_Sources!$D$473)),"n.m."),"n/a"),"n/a") -> 7.1260365 | W53: =IFERROR(IF(ISNUMBER((Detail_PeerAnalysis!D64*Inputs_Sources!$D$473+Detail_PeerAnalysis!E64*Inputs_Sources!$D$474)),IF(((Detail_PeerAnalysis!D64*Inputs_Sources!$D$473+Detail_PeerAnalysis!E64*Inputs_Sources!$D$474))>0,Detail_PeerAnalysis!I15/((Detail_PeerAnalysis!D64*Inputs_Sources!$D$473+Detail_PeerAnalysis!E64*Inputs_Sources!$D$474)),"n.m."),"n/a"),"n/a") -> 6.2057295
B54: =Detail_PeerAnalysis!A16 -> The J. M. Smucker Company | D54: Secondary | E54: =Detail_PeerAnalysis!B16 -> NYSE:SJM | F54: =IFERROR(IF(ISNUMBER(Inputs_Sources!$D$489),(Inputs_Sources!$D$489)/Detail_PeerAnalysis!I16,"n/a"),"n/a") -> 0.043379247 | G54: =IFERROR(IF(ISNUMBER(Inputs_Sources!$D$490),(Inputs_Sources!$D$490)/Detail_PeerAnalysis!I16,"n/a"),"n/a") -> 0.044099174 | I54: =IFERROR(IF(ISNUMBER(Detail_PeerAnalysis!N30),(Detail_PeerAnalysis!N30)/Detail_PeerAnalysis!I16,"n/a"),"n/a") -> 0.10757025 | J54: =IFERROR(IF(ISNUMBER((Detail_PeerAnalysis!D65*Inputs_Sources!$D$509+Detail_PeerAnalysis!E65*Inputs_Sources!$D$510)),((Detail_PeerAnalysis!D65*Inputs_Sources!$D$509+Detail_PeerAnalysis!E65*Inputs_Sources!$D$510))/Detail_PeerAnalysis!I16,"n/a"),"n/a") -> 0.08977847 | K54: =IFERROR(IF(ISNUMBER((Detail_PeerAnalysis!D65*Inputs_Sources!$D$510+Detail_PeerAnalysis!E65*Inputs_Sources!$D$511)),((Detail_PeerAnalysis!D65*Inputs_Sources!$D$510+Detail_PeerAnalysis!E65*Inputs_Sources!$D$511))/Detail_PeerAnalysis!I16,"n/a"),"n/a") -> 0.094103266 | L54: =IFERROR(Detail_PeerAnalysis!I16/F35,"n/a") -> 1.6643843 | M54: =IFERROR(Detail_PeerAnalysis!I16/G35,"n/a") -> 1.5599752 | N54: =IFERROR(Detail_PeerAnalysis!I16/H35,"n/a") -> 1.5039941 | O54: =IFERROR(Detail_PeerAnalysis!I16/I35,"n/a") -> 1.4865839 | P54: =IFERROR(Detail_PeerAnalysis!I16/J35,"n/a") -> 1.5159291 | Q54: =IFERROR(Detail_PeerAnalysis!I16/K35,"n/a") -> 1.4945516 | R54: =IFERROR(IF(ISNUMBER(Inputs_Sources!$D$489),IF((Inputs_Sources!$D$489)>0,Detail_PeerAnalysis!I16/(Inputs_Sources!$D$489),"n.m."),"n/a"),"n/a") -> 23.052498 | S54: =IFERROR(IF(ISNUMBER(Inputs_Sources!$D$490),IF((Inputs_Sources!$D$490)>0,Detail_PeerAnalysis!I16/(Inputs_Sources!$D$490),"n.m."),"n/a"),"n/a") -> 22.676162 | U54: =IFERROR(IF(ISNUMBER(Detail_PeerAnalysis!N30),IF((Detail_PeerAnalysis!N30)>0,Detail_PeerAnalysis!I16/(Detail_PeerAnalysis!N30),"n.m."),"n/a"),"n/a") -> 9.2962508 | V54: =IFERROR(IF(ISNUMBER((Detail_PeerAnalysis!D65*Inputs_Sources!$D$509+Detail_PeerAnalysis!E65*Inputs_Sources!$D$510)),IF(((Detail_PeerAnalysis!D65*Inputs_Sources!$D$509+Detail_PeerAnalysis!E65*Inputs_Sources!$D$510))>0,Detail_PeerAnalysis!I16/((Detail_PeerAnalysis!D65*Inputs_Sources!$D$509+Detail_PeerAnalysis!E65*Inputs_Sources!$D$510)),"n.m."),"n/a"),"n/a") -> 11.138528 | W54: =IFERROR(IF(ISNUMBER((Detail_PeerAnalysis!D65*Inputs_Sources!$D$510+Detail_PeerAnalysis!E65*Inputs_Sources!$D$511)),IF(((Detail_PeerAnalysis!D65*Inputs_Sources!$D$510+Detail_PeerAnalysis!E65*Inputs_Sources!$D$511))>0,Detail_PeerAnalysis!I16/((Detail_PeerAnalysis!D65*Inputs_Sources!$D$510+Detail_PeerAnalysis!E65*Inputs_Sources!$D$511)),"n.m."),"n/a"),"n/a") -> 10.626624
B55: =Detail_PeerAnalysis!A17 -> The Campbell's Company | D55: Secondary | E55: =Detail_PeerAnalysis!B17 -> NasdaqGS:CPB | F55: =IFERROR(IF(ISNUMBER(Inputs_Sources!$D$526),(Inputs_Sources!$D$526)/Detail_PeerAnalysis!I17,"n/a"),"n/a") -> 0.097335426 | G55: =IFERROR(IF(ISNUMBER(Inputs_Sources!$D$527),(Inputs_Sources!$D$527)/Detail_PeerAnalysis!I17,"n/a"),"n/a") -> 0.12109553 | I55: =IFERROR(IF(ISNUMBER(Detail_PeerAnalysis!N31),(Detail_PeerAnalysis!N31)/Detail_PeerAnalysis!I17,"n/a"),"n/a") -> 0.10707234 | J55: =IFERROR(IF(ISNUMBER((Detail_PeerAnalysis!D66*Inputs_Sources!$D$546+Detail_PeerAnalysis!E66*Inputs_Sources!$D$547)),((Detail_PeerAnalysis!D66*Inputs_Sources!$D$546+Detail_PeerAnalysis!E66*Inputs_Sources!$D$547))/Detail_PeerAnalysis!I17,"n/a"),"n/a") -> 0.12757708 | K55: =IFERROR(IF(ISNUMBER((Detail_PeerAnalysis!D66*Inputs_Sources!$D$547+Detail_PeerAnalysis!E66*Inputs_Sources!$D$548)),((Detail_PeerAnalysis!D66*Inputs_Sources!$D$547+Detail_PeerAnalysis!E66*Inputs_Sources!$D$548))/Detail_PeerAnalysis!I17,"n/a"),"n/a") -> 0.11792473 | L55: =IFERROR(Detail_PeerAnalysis!I17/F36,"n/a") -> 0.61497509 | M55: =IFERROR(Detail_PeerAnalysis!I17/G36,"n/a") -> 0.57796742 | N55: =IFERROR(Detail_PeerAnalysis!I17/H36,"n/a") -> 0.60815887 | O55: =IFERROR(Detail_PeerAnalysis!I17/I36,"n/a") -> 0.60815887 | P55: =IFERROR(Detail_PeerAnalysis!I17/J36,"n/a") -> 0.62436974 | Q55: =IFERROR(Detail_PeerAnalysis!I17/K36,"n/a") -> 0.62462198 | R55: =IFERROR(IF(ISNUMBER(Inputs_Sources!$D$526),IF((Inputs_Sources!$D$526)>0,Detail_PeerAnalysis!I17/(Inputs_Sources!$D$526),"n.m."),"n/a"),"n/a") -> 10.273752 | S55: =IFERROR(IF(ISNUMBER(Inputs_Sources!$D$527),IF((Inputs_Sources!$D$527)>0,Detail_PeerAnalysis!I17/(Inputs_Sources!$D$527),"n.m."),"n/a"),"n/a") -> 8.2579431 | U55: =IFERROR(IF(ISNUMBER(Detail_PeerAnalysis!N31),IF((Detail_PeerAnalysis!N31)>0,Detail_PeerAnalysis!I17/(Detail_PeerAnalysis!N31),"n.m."),"n/a"),"n/a") -> 9.3394799 | V55: =IFERROR(IF(ISNUMBER((Detail_PeerAnalysis!D66*Inputs_Sources!$D$546+Detail_PeerAnalysis!E66*Inputs_Sources!$D$547)),IF(((Detail_PeerAnalysis!D66*Inputs_Sources!$D$546+Detail_PeerAnalysis!E66*Inputs_Sources!$D$547))>0,Detail_PeerAnalysis!I17/((Detail_PeerAnalysis!D66*Inputs_Sources!$D$546+Detail_PeerAnalysis!E66*Inputs_Sources!$D$547)),"n.m."),"n/a"),"n/a") -> 7.8383983 | W55: =IFERROR(IF(ISNUMBER((Detail_PeerAnalysis!D66*Inputs_Sources!$D$547+Detail_PeerAnalysis!E66*Inputs_Sources!$D$548)),IF(((Detail_PeerAnalysis!D66*Inputs_Sources!$D$547+Detail_PeerAnalysis!E66*Inputs_Sources!$D$548))>0,Detail_PeerAnalysis!I17/((Detail_PeerAnalysis!D66*Inputs_Sources!$D$547+Detail_PeerAnalysis!E66*Inputs_Sources!$D$548)),"n.m."),"n/a"),"n/a") -> 8.4799857
B56: =Detail_PeerAnalysis!A18 -> Mondelez International, Inc. | D56: Secondary | E56: =Detail_PeerAnalysis!B18 -> NasdaqGS:MDLZ | F56: =IFERROR(IF(ISNUMBER(Inputs_Sources!$D$563),(Inputs_Sources!$D$563)/Detail_PeerAnalysis!I18,"n/a"),"n/a") -> 0.0336869 | G56: =IFERROR(IF(ISNUMBER(Inputs_Sources!$D$564),(Inputs_Sources!$D$564)/Detail_PeerAnalysis!I18,"n/a"),"n/a") -> 0.043987407 | H56: =IFERROR(IF(ISNUMBER(Inputs_Sources!$D$583),(Inputs_Sources!$D$583)/Detail_PeerAnalysis!I18,"n/a"),"n/a") -> 0.040162047 | I56: =IFERROR(IF(ISNUMBER(Detail_PeerAnalysis!N32),(Detail_PeerAnalysis!N32)/Detail_PeerAnalysis!I18,"n/a"),"n/a") -> 0.027613499 | J56: =IFERROR(IF(ISNUMBER((Detail_PeerAnalysis!D67*Inputs_Sources!$D$583+Detail_PeerAnalysis!E67*Inputs_Sources!$D$584)),((Detail_PeerAnalysis!D67*Inputs_Sources!$D$583+Detail_PeerAnalysis!E67*Inputs_Sources!$D$584))/Detail_PeerAnalysis!I18,"n/a"),"n/a") -> 0.04972248 | K56: =IFERROR(IF(ISNUMBER((Detail_PeerAnalysis!D67*Inputs_Sources!$D$584+Detail_PeerAnalysis!E67*Inputs_Sources!$D$585)),((Detail_PeerAnalysis!D67*Inputs_Sources!$D$584+Detail_PeerAnalysis!E67*Inputs_Sources!$D$585))/Detail_PeerAnalysis!I18,"n/a"),"n/a") -> 0.057849916 | L56: =IFERROR(Detail_PeerAnalysis!I18/F37,"n/a") -> 2.2383798 | M56: =IFERROR(Detail_PeerAnalysis!I18/G37,"n/a") -> 2.116636 | N56: =IFERROR(Detail_PeerAnalysis!I18/H37,"n/a") -> 2.0340738 | O56: =IFERROR(Detail_PeerAnalysis!I18/I37,"n/a") -> 2.0559244 | P56: =IFERROR(Detail_PeerAnalysis!I18/J37,"n/a") -> 1.9897665 | Q56: =IFERROR(Detail_PeerAnalysis!I18/K37,"n/a") -> 1.9257971 | R56: =IFERROR(IF(ISNUMBER(Inputs_Sources!$D$563),IF((Inputs_Sources!$D$563)>0,Detail_PeerAnalysis!I18/(Inputs_Sources!$D$563),"n.m."),"n/a"),"n/a") -> 29.68513 | S56: =IFERROR(IF(ISNUMBER(Inputs_Sources!$D$564),IF((Inputs_Sources!$D$564)>0,Detail_PeerAnalysis!I18/(Inputs_Sources!$D$564),"n.m."),"n/a"),"n/a") -> 22.733779 | T56: =IFERROR(IF(ISNUMBER(Inputs_Sources!$D$583),IF((Inputs_Sources!$D$583)>0,Detail_PeerAnalysis!I18/(Inputs_Sources!$D$583),"n.m."),"n/a"),"n/a") -> 24.899129 | U56: =IFERROR(IF(ISNUMBER(Detail_PeerAnalysis!N32),IF((Detail_PeerAnalysis!N32)>0,Detail_PeerAnalysis!I18/(Detail_PeerAnalysis!N32),"n.m."),"n/a"),"n/a") -> 36.214172 | V56: =IFERROR(IF(ISNUMBER((Detail_PeerAnalysis!D67*Inputs_Sources!$D$583+Detail_PeerAnalysis!E67*Inputs_Sources!$D$584)),IF(((Detail_PeerAnalysis!D67*Inputs_Sources!$D$583+Detail_PeerAnalysis!E67*Inputs_Sources!$D$584))>0,Detail_PeerAnalysis!I18/((Detail_PeerAnalysis!D67*Inputs_Sources!$D$583+Detail_PeerAnalysis!E67*Inputs_Sources!$D$584)),"n.m."),"n/a"),"n/a") -> 20.111628 | W56: =IFERROR(IF(ISNUMBER((Detail_PeerAnalysis!D67*Inputs_Sources!$D$584+Detail_PeerAnalysis!E67*Inputs_Sources!$D$585)),IF(((Detail_PeerAnalysis!D67*Inputs_Sources!$D$584+Detail_PeerAnalysis!E67*Inputs_Sources!$D$585))>0,Detail_PeerAnalysis!I18/((Detail_PeerAnalysis!D67*Inputs_Sources!$D$584+Detail_PeerAnalysis!E67*Inputs_Sources!$D$585)),"n.m."),"n/a"),"n/a") -> 17.28611
B57: =Detail_PeerAnalysis!A19 -> Arca Continental, S.A.B. de C.V. | D57: Secondary | E57: =Detail_PeerAnalysis!B19 -> BMV:AC | F57: =IFERROR(IF(ISNUMBER(Inputs_Sources!$D$600),(Inputs_Sources!$D$600)/Detail_PeerAnalysis!I19,"n/a"),"n/a") -> 0.044905557 | G57: =IFERROR(IF(ISNUMBER(Inputs_Sources!$D$601),(Inputs_Sources!$D$601)/Detail_PeerAnalysis!I19,"n/a"),"n/a") -> 0.027493092 | H57: =IFERROR(IF(ISNUMBER(Inputs_Sources!$D$620),(Inputs_Sources!$D$620)/Detail_PeerAnalysis!I19,"n/a"),"n/a") -> 0.063849861 | I57: =IFERROR(IF(ISNUMBER(Detail_PeerAnalysis!N33),(Detail_PeerAnalysis!N33)/Detail_PeerAnalysis!I19,"n/a"),"n/a") -> 0.03967818 | J57: =IFERROR(IF(ISNUMBER((Detail_PeerAnalysis!D68*Inputs_Sources!$D$620+Detail_PeerAnalysis!E68*Inputs_Sources!$D$621)),((Detail_PeerAnalysis!D68*Inputs_Sources!$D$620+Detail_PeerAnalysis!E68*Inputs_Sources!$D$621))/Detail_PeerAnalysis!I19,"n/a"),"n/a") -> 0.069947814 | K57: =IFERROR(IF(ISNUMBER((Detail_PeerAnalysis!D68*Inputs_Sources!$D$621+Detail_PeerAnalysis!E68*Inputs_Sources!$D$622)),((Detail_PeerAnalysis!D68*Inputs_Sources!$D$621+Detail_PeerAnalysis!E68*Inputs_Sources!$D$622))/Detail_PeerAnalysis!I19,"n/a"),"n/a") -> 0.078987716 | L57: =IFERROR(Detail_PeerAnalysis!I19/F38,"n/a") -> 1.4635411 | M57: =IFERROR(Detail_PeerAnalysis!I19/G38,"n/a") -> 1.4737626 | N57: =IFERROR(Detail_PeerAnalysis!I19/H38,"n/a") -> 1.3314723 | O57: =IFERROR(Detail_PeerAnalysis!I19/I38,"n/a") -> 1.3800329 | P57: =IFERROR(Detail_PeerAnalysis!I19/J38,"n/a") -> 1.3188869 | Q57: =IFERROR(Detail_PeerAnalysis!I19/K38,"n/a") -> 1.2476472 | R57: =IFERROR(IF(ISNUMBER(Inputs_Sources!$D$600),IF((Inputs_Sources!$D$600)>0,Detail_PeerAnalysis!I19/(Inputs_Sources!$D$600),"n.m."),"n/a"),"n/a") -> 22.268959 | S57: =IFERROR(IF(ISNUMBER(Inputs_Sources!$D$601),IF((Inputs_Sources!$D$601)>0,Detail_PeerAnalysis!I19/(Inputs_Sources!$D$601),"n.m."),"n/a"),"n/a") -> 36.372773 | T57: =IFERROR(IF(ISNUMBER(Inputs_Sources!$D$620),IF((Inputs_Sources!$D$620)>0,Detail_PeerAnalysis!I19/(Inputs_Sources!$D$620),"n.m."),"n/a"),"n/a") -> 15.661741 | U57: =IFERROR(IF(ISNUMBER(Detail_PeerAnalysis!N33),IF((Detail_PeerAnalysis!N33)>0,Detail_PeerAnalysis!I19/(Detail_PeerAnalysis!N33),"n.m."),"n/a"),"n/a") -> 25.202769 | V57: =IFERROR(IF(ISNUMBER((Detail_PeerAnalysis!D68*Inputs_Sources!$D$620+Detail_PeerAnalysis!E68*Inputs_Sources!$D$621)),IF(((Detail_PeerAnalysis!D68*Inputs_Sources!$D$620+Detail_PeerAnalysis!E68*Inputs_Sources!$D$621))>0,Detail_PeerAnalysis!I19/((Detail_PeerAnalysis!D68*Inputs_Sources!$D$620+Detail_PeerAnalysis!E68*Inputs_Sources!$D$621)),"n.m."),"n/a"),"n/a") -> 14.296372 | W57: =IFERROR(IF(ISNUMBER((Detail_PeerAnalysis!D68*Inputs_Sources!$D$621+Detail_PeerAnalysis!E68*Inputs_Sources!$D$622)),IF(((Detail_PeerAnalysis!D68*Inputs_Sources!$D$621+Detail_PeerAnalysis!E68*Inputs_Sources!$D$622))>0,Detail_PeerAnalysis!I19/((Detail_PeerAnalysis!D68*Inputs_Sources!$D$621+Detail_PeerAnalysis!E68*Inputs_Sources!$D$622)),"n.m."),"n/a"),"n/a") -> 12.660196
B58: =Detail_PeerAnalysis!A20 -> PepsiCo, Inc. | D58: Secondary | E58: =Detail_PeerAnalysis!B20 -> NasdaqGS:PEP | F58: =IFERROR(IF(ISNUMBER(Inputs_Sources!$D$637),(Inputs_Sources!$D$637)/Detail_PeerAnalysis!I20,"n/a"),"n/a") -> 0.040183482 | G58: =IFERROR(IF(ISNUMBER(Inputs_Sources!$D$638),(Inputs_Sources!$D$638)/Detail_PeerAnalysis!I20,"n/a"),"n/a") -> 0.045941836 | H58: =IFERROR(IF(ISNUMBER(Inputs_Sources!$D$657),(Inputs_Sources!$D$657)/Detail_PeerAnalysis!I20,"n/a"),"n/a") -> 0.058559435 | I58: =IFERROR(IF(ISNUMBER(Detail_PeerAnalysis!N34),(Detail_PeerAnalysis!N34)/Detail_PeerAnalysis!I20,"n/a"),"n/a") -> 0.050470283 | J58: =IFERROR(IF(ISNUMBER((Detail_PeerAnalysis!D69*Inputs_Sources!$D$657+Detail_PeerAnalysis!E69*Inputs_Sources!$D$658)),((Detail_PeerAnalysis!D69*Inputs_Sources!$D$657+Detail_PeerAnalysis!E69*Inputs_Sources!$D$658))/Detail_PeerAnalysis!I20,"n/a"),"n/a") -> 0.06466546 | K58: =IFERROR(IF(ISNUMBER((Detail_PeerAnalysis!D69*Inputs_Sources!$D$658+Detail_PeerAnalysis!E69*Inputs_Sources!$D$659)),((Detail_PeerAnalysis!D69*Inputs_Sources!$D$658+Detail_PeerAnalysis!E69*Inputs_Sources!$D$659))/Detail_PeerAnalysis!I20,"n/a"),"n/a") -> 0.070468696 | L58: =IFERROR(Detail_PeerAnalysis!I20/F39,"n/a") -> 1.9509276 | M58: =IFERROR(Detail_PeerAnalysis!I20/G39,"n/a") -> 1.9079106 | N58: =IFERROR(Detail_PeerAnalysis!I20/H39,"n/a") -> 1.8046284 | O58: =IFERROR(Detail_PeerAnalysis!I20/I39,"n/a") -> 1.8240908 | P58: =IFERROR(Detail_PeerAnalysis!I20/J39,"n/a") -> 1.7698556 | Q58: =IFERROR(Detail_PeerAnalysis!I20/K39,"n/a") -> 1.7158436 | R58: =IFERROR(IF(ISNUMBER(Inputs_Sources!$D$637),IF((Inputs_Sources!$D$637)>0,Detail_PeerAnalysis!I20/(Inputs_Sources!$D$637),"n.m."),"n/a"),"n/a") -> 24.885848 | S58: =IFERROR(IF(ISNUMBER(Inputs_Sources!$D$638),IF((Inputs_Sources!$D$638)>0,Detail_PeerAnalysis!I20/(Inputs_Sources!$D$638),"n.m."),"n/a"),"n/a") -> 21.766653 | T58: =IFERROR(IF(ISNUMBER(Inputs_Sources!$D$657),IF((Inputs_Sources!$D$657)>0,Detail_PeerAnalysis!I20/(Inputs_Sources!$D$657),"n.m."),"n/a"),"n/a") -> 17.076668 | U58: =IFERROR(IF(ISNUMBER(Detail_PeerAnalysis!N34),IF((Detail_PeerAnalysis!N34)>0,Detail_PeerAnalysis!I20/(Detail_PeerAnalysis!N34),"n.m."),"n/a"),"n/a") -> 19.81364 | V58: =IFERROR(IF(ISNUMBER((Detail_PeerAnalysis!D69*Inputs_Sources!$D$657+Detail_PeerAnalysis!E69*Inputs_Sources!$D$658)),IF(((Detail_PeerAnalysis!D69*Inputs_Sources!$D$657+Detail_PeerAnalysis!E69*Inputs_Sources!$D$658))>0,Detail_PeerAnalysis!I20/((Detail_PeerAnalysis!D69*Inputs_Sources!$D$657+Detail_PeerAnalysis!E69*Inputs_Sources!$D$658)),"n.m."),"n/a"),"n/a") -> 15.464206 | W58: =IFERROR(IF(ISNUMBER((Detail_PeerAnalysis!D69*Inputs_Sources!$D$658+Detail_PeerAnalysis!E69*Inputs_Sources!$D$659)),IF(((Detail_PeerAnalysis!D69*Inputs_Sources!$D$658+Detail_PeerAnalysis!E69*Inputs_Sources!$D$659))>0,Detail_PeerAnalysis!I20/((Detail_PeerAnalysis!D69*Inputs_Sources!$D$658+Detail_PeerAnalysis!E69*Inputs_Sources!$D$659)),"n.m."),"n/a"),"n/a") -> 14.190698
B59: =Detail_PeerAnalysis!A11 -> Grupo Bimbo, S.A.B. de C.V. (subject) | D59: Subject Company >> | E59: =Detail_PeerAnalysis!B11 -> BMV:BIMBO A | G59: =IFERROR(IF(ISNUMBER(Detail_TearSheet!G48),(Detail_TearSheet!G48)/(Inputs_Sources!$D$13*Inputs_Sources!$D$14),"n/a"),"n/a") -> 0.065005268 | H59: =IFERROR(IF(ISNUMBER(Inputs_Sources!$D$677),(Inputs_Sources!$D$677)/(Inputs_Sources!$D$13*Inputs_Sources!$D$14),"n/a"),"n/a") -> 0.075465859 | I59: =IFERROR(IF(ISNUMBER(Detail_PeerAnalysis!N25*Inputs_Sources!$D$10),(Detail_PeerAnalysis!N25*Inputs_Sources!$D$10)/(Inputs_Sources!$D$13*Inputs_Sources!$D$14),"n/a"),"n/a") -> 0.10105385 | J59: =IFERROR(IF(ISNUMBER((Detail_PeerAnalysis!D60*Inputs_Sources!$D$677+Detail_PeerAnalysis!E60*Inputs_Sources!$D$689)),((Detail_PeerAnalysis!D60*Inputs_Sources!$D$677+Detail_PeerAnalysis!E60*Inputs_Sources!$D$689))/(Inputs_Sources!$D$13*Inputs_Sources!$D$14),"n/a"),"n/a") -> 0.084325601 | K59: =IFERROR(IF(ISNUMBER((Detail_PeerAnalysis!D60*Inputs_Sources!$D$689+Detail_PeerAnalysis!E60*Inputs_Sources!$D$701)),((Detail_PeerAnalysis!D60*Inputs_Sources!$D$689+Detail_PeerAnalysis!E60*Inputs_Sources!$D$701))/(Inputs_Sources!$D$13*Inputs_Sources!$D$14),"n/a"),"n/a") -> 0.10141565 | L59: =IFERROR(Detail_PeerAnalysis!I11/F40,"n/a") -> 0.61635946 | M59: =IFERROR(Detail_PeerAnalysis!I11/G40,"n/a") -> 0.58946827 | N59: =IFERROR(Detail_PeerAnalysis!I11/H40,"n/a") -> 0.59042003 | O59: =IFERROR(Detail_PeerAnalysis!I11/I40,"n/a") -> 0.59721738 | P59: =IFERROR(Detail_PeerAnalysis!I11/J40,"n/a") -> 0.57034732 | Q59: =IFERROR(Detail_PeerAnalysis!I11/K40,"n/a") -> 0.54294434 | S59: =IFERROR(IF(ISNUMBER(Detail_TearSheet!G48),IF((Detail_TearSheet!G48)>0,(Inputs_Sources!$D$13*Inputs_Sources!$D$14)/(Detail_TearSheet!G48),"n.m."),"n/a"),"n/a") -> 15.383369 | T59: =IFERROR(IF(ISNUMBER(Inputs_Sources!$D$677),IF((Inputs_Sources!$D$677)>0,(Inputs_Sources!$D$13*Inputs_Sources!$D$14)/(Inputs_Sources!$D$677),"n.m."),"n/a"),"n/a") -> 13.251025 | U59: =IFERROR(IF(ISNUMBER(Detail_PeerAnalysis!N25*Inputs_Sources!$D$10),IF((Detail_PeerAnalysis!N25*Inputs_Sources!$D$10)>0,(Inputs_Sources!$D$13*Inputs_Sources!$D$14)/(Detail_PeerAnalysis!N25*Inputs_Sources!$D$10),"n.m."),"n/a"),"n/a") -> 9.8957135 | V59: =IFERROR(IF(ISNUMBER((Detail_PeerAnalysis!D60*Inputs_Sources!$D$677+Detail_PeerAnalysis!E60*Inputs_Sources!$D$689)),IF(((Detail_PeerAnalysis!D60*Inputs_Sources!$D$677+Detail_PeerAnalysis!E60*Inputs_Sources!$D$689))>0,(Inputs_Sources!$D$13*Inputs_Sources!$D$14)/((Detail_PeerAnalysis!D60*Inputs_Sources!$D$677+Detail_PeerAnalysis!E60*Inputs_Sources!$D$689)),"n.m."),"n/a"),"n/a") -> 11.858795 | W59: =IFERROR(IF(ISNUMBER((Detail_PeerAnalysis!D60*Inputs_Sources!$D$689+Detail_PeerAnalysis!E60*Inputs_Sources!$D$701)),IF(((Detail_PeerAnalysis!D60*Inputs_Sources!$D$689+Detail_PeerAnalysis!E60*Inputs_Sources!$D$701))>0,(Inputs_Sources!$D$13*Inputs_Sources!$D$14)/((Detail_PeerAnalysis!D60*Inputs_Sources!$D$689+Detail_PeerAnalysis!E60*Inputs_Sources!$D$701)),"n.m."),"n/a"),"n/a") -> 9.8604107
F62: Valuation on the claim basis (lease-normalised; drives the exit multiple in the DCF)
F63: EV/EBITDA LTM (x) | G63: EV/EBITDA NTM (x) | H63: EV/Sales LTM (x) | I63: P/E LTM (x) | J63: P/E NTM (x) | K63: Net debt / EBITDA LTM (x) | L63: EBITDA margin LTM | M63: In median: valuation | N63: In median: P/E
B64: =Detail_PeerAnalysis!A12 -> Flowers Foods, Inc. | D64: Core | E64: =Detail_PeerAnalysis!B12 -> NYSE:FLO | F64: =Detail_PeerAnalysis!B40 -> 5.6094445 | G64: =Detail_PeerAnalysis!C40 -> 6.147272 | H64: =Detail_PeerAnalysis!D40 -> 0.62142001 | I64: =Detail_PeerAnalysis!E40 -> 23.45 | J64: =Detail_PeerAnalysis!F40 -> 8.93 | K64: =Detail_PeerAnalysis!H40 -> 3.3704954 | L64: =Detail_PeerAnalysis!I40 -> 0.11078103 | M64: =Detail_PeerAnalysis!P12 -> yes | N64: =Detail_PeerAnalysis!Q12 -> yes
B65: =Detail_PeerAnalysis!A13 -> Gruma, S.A.B. de C.V. | D65: Core | E65: =Detail_PeerAnalysis!B13 -> BMV:GRUMA B | F65: =Detail_PeerAnalysis!B41 -> 5.4417222 | G65: =Detail_PeerAnalysis!C41 -> 5.6385558 | H65: =Detail_PeerAnalysis!D41 -> 0.92834353 | I65: =Detail_PeerAnalysis!E41 -> 9.3550208 | J65: =Detail_PeerAnalysis!F41 -> 9.7392544 | K65: =Detail_PeerAnalysis!H41 -> 1.4708269 | L65: =Detail_PeerAnalysis!I41 -> 0.17059738 | M65: =Detail_PeerAnalysis!P13 -> yes | N65: =Detail_PeerAnalysis!Q13 -> yes
B66: =Detail_PeerAnalysis!A14 -> Yamazaki Baking Co., Ltd. | D66: Core | E66: =Detail_PeerAnalysis!B14 -> TSE:2212 | F66: =Detail_PeerAnalysis!B42 -> 6.0597144 | G66: =Detail_PeerAnalysis!C42 -> 5.8441554 | H66: =Detail_PeerAnalysis!D42 -> 0.49393882 | I66: =Detail_PeerAnalysis!E42 -> 17.74 | J66: =Detail_PeerAnalysis!F42 -> 16.84 | K66: =Detail_PeerAnalysis!H42 -> -0.67001557 | L66: =Detail_PeerAnalysis!I42 -> 0.081511897 | M66: =Detail_PeerAnalysis!P14 -> no | N66: =Detail_PeerAnalysis!Q14 -> no
B67: =Detail_PeerAnalysis!A15 -> ARYZTA AG | D67: Core | E67: =Detail_PeerAnalysis!B15 -> SWX:ARYN | F67: =Detail_PeerAnalysis!B43 -> 8.3332366 | G67: =Detail_PeerAnalysis!C43 -> 5.8147036 | H67: =Detail_PeerAnalysis!D43 -> 0.81923694 | I67: =Detail_PeerAnalysis!E43 -> 10.21 | J67: =Detail_PeerAnalysis!F43 -> 9.01 | K67: =Detail_PeerAnalysis!H43 -> 3.5043935 | L67: =Detail_PeerAnalysis!I43 -> 0.098309574 | M67: =Detail_PeerAnalysis!P15 -> no | N67: =Detail_PeerAnalysis!Q15 -> no
B68: =Detail_PeerAnalysis!A16 -> The J. M. Smucker Company | D68: Secondary | E68: =Detail_PeerAnalysis!B16 -> NYSE:SJM | F68: =Detail_PeerAnalysis!B44 -> 8.8754977 | G68: =Detail_PeerAnalysis!C44 -> 9.2157465 | H68: =Detail_PeerAnalysis!D44 -> 2.2397864 | I68: =Detail_PeerAnalysis!E44 -> 58.63 | J68: =Detail_PeerAnalysis!F44 -> 12.6 | K68: =Detail_PeerAnalysis!H44 -> 2.9846806 | L68: =Detail_PeerAnalysis!I44 -> 0.25235615 | M68: =Detail_PeerAnalysis!P16 -> yes | N68: =Detail_PeerAnalysis!Q16 -> no
B69: =Detail_PeerAnalysis!A17 -> The Campbell's Company | D69: Secondary | E69: =Detail_PeerAnalysis!B17 -> NasdaqGS:CPB | F69: =Detail_PeerAnalysis!B45 -> 7.6631488 | G69: =Detail_PeerAnalysis!C45 -> 8.3574722 | H69: =Detail_PeerAnalysis!D45 -> 1.3637007 | I69: =Detail_PeerAnalysis!E45 -> 15.11 | J69: =Detail_PeerAnalysis!F45 -> 11.72 | K69: =Detail_PeerAnalysis!H45 -> 4.2456747 | L69: =Detail_PeerAnalysis!I45 -> 0.17795567 | M69: =Detail_PeerAnalysis!P17 -> yes | N69: =Detail_PeerAnalysis!Q17 -> yes
B70: =Detail_PeerAnalysis!A18 -> Mondelez International, Inc. | D70: Secondary | E70: =Detail_PeerAnalysis!B18 -> NasdaqGS:MDLZ | F70: =Detail_PeerAnalysis!B46 -> 16.144293 | G70: =Detail_PeerAnalysis!C46 -> 13.802618 | H70: =Detail_PeerAnalysis!D46 -> 2.5741348 | I70: =Detail_PeerAnalysis!E46 -> 23.1 | J70: =Detail_PeerAnalysis!F46 -> 19.83 | K70: =Detail_PeerAnalysis!H46 -> 3.250079 | L70: =Detail_PeerAnalysis!I46 -> 0.15944549 | M70: =Detail_PeerAnalysis!P18 -> yes | N70: =Detail_PeerAnalysis!Q18 -> yes
B71: =Detail_PeerAnalysis!A19 -> Arca Continental, S.A.B. de C.V. | D71: Secondary | E71: =Detail_PeerAnalysis!B19 -> BMV:AC | F71: =Detail_PeerAnalysis!B47 -> 7.8537991 | G71: =Detail_PeerAnalysis!C47 -> 7.1098612 | H71: =Detail_PeerAnalysis!D47 -> 1.5245557 | I71: =Detail_PeerAnalysis!E47 -> 18.71 | J71: =Detail_PeerAnalysis!F47 -> 16.5 | K71: =Detail_PeerAnalysis!H47 -> 0.74451422 | L71: =Detail_PeerAnalysis!I47 -> 0.19411697 | M71: =Detail_PeerAnalysis!P19 -> no | N71: =Detail_PeerAnalysis!Q19 -> no
B72: =Detail_PeerAnalysis!A20 -> PepsiCo, Inc. | D72: Secondary | E72: =Detail_PeerAnalysis!B20 -> NasdaqGS:PEP | F72: =Detail_PeerAnalysis!B48 -> 11.193831 | G72: =Detail_PeerAnalysis!C48 -> 11.027248 | H72: =Detail_PeerAnalysis!D48 -> 2.2846622 | I72: =Detail_PeerAnalysis!E48 -> 16.15 | J72: =Detail_PeerAnalysis!F48 -> 15.53 | K72: =Detail_PeerAnalysis!H48 -> 2.2565957 | L72: =Detail_PeerAnalysis!I48 -> 0.20410012 | M72: =Detail_PeerAnalysis!P20 -> yes | N72: =Detail_PeerAnalysis!Q20 -> yes
B73: =Detail_PeerAnalysis!A11 -> Grupo Bimbo, S.A.B. de C.V. (subject) | D73: Subject Company >> | E73: =Detail_PeerAnalysis!B11 -> BMV:BIMBO A | F73: =Detail_PeerAnalysis!B39 -> 6.9413671 | G73: =Detail_PeerAnalysis!C39 -> 6.5757854 | H73: =Detail_PeerAnalysis!D39 -> 1.0034126 | I73: =Detail_PeerAnalysis!E39 -> 18.456693 | J73: =Detail_PeerAnalysis!F39 -> 17.806509 | K73: =Detail_PeerAnalysis!H39 -> 2.8099608 | L73: =Detail_PeerAnalysis!I39 -> 0.14455547 | M73: =Detail_PeerAnalysis!P11 -> subject | N73: =Detail_PeerAnalysis!Q11 -> subject
B74: Core median (eligible) | F74: =Detail_PeerAnalysis!B50 -> 5.5255833 | G74: =Detail_PeerAnalysis!C50 -> 5.8929139 | H74: =Detail_PeerAnalysis!D50 -> 0.77488177 | I74: =Detail_PeerAnalysis!E50 -> 16.40251 | J74: =Detail_PeerAnalysis!F50 -> 9.3346272 | K74: =Detail_PeerAnalysis!H50 -> 2.4206612 | L74: =Detail_PeerAnalysis!I50 -> 0.1406892
B75: All-peer median (eligible) | F75: =Detail_PeerAnalysis!B53 -> 8.2693232 | G75: =Detail_PeerAnalysis!C53 -> 8.7866094 | H75: =Detail_PeerAnalysis!D53 -> 1.8017436 | I75: =Detail_PeerAnalysis!E53 -> 16.15 | J75: =Detail_PeerAnalysis!F53 -> 11.72 | K75: =Detail_PeerAnalysis!H53 -> 3.1173798 | L75: =Detail_PeerAnalysis!I53 -> 0.17427652
B76: All-peer mean (eligible) | F76: =Detail_PeerAnalysis!B54 -> 9.1546562 | G76: =Detail_PeerAnalysis!C54 -> 9.0314855 | H76: =Detail_PeerAnalysis!D54 -> 1.6686746 | I76: =Detail_PeerAnalysis!E54 -> 17.433004 | J76: =Detail_PeerAnalysis!F54 -> 13.149851 | K76: =Detail_PeerAnalysis!H54 -> 2.9297254 | L76: =Detail_PeerAnalysis!I54 -> 0.17920597
B77: All-peer: number eligible | F77: =Detail_PeerAnalysis!B55 -> 6 | G77: =Detail_PeerAnalysis!C55 -> 6 | H77: =Detail_PeerAnalysis!D55 -> 6 | I77: =Detail_PeerAnalysis!E55 -> 5 | J77: =Detail_PeerAnalysis!F55 -> 5 | K77: =Detail_PeerAnalysis!H55 -> 6 | L77: =Detail_PeerAnalysis!I55 -> 6
F79: Capital intensity: consensus capex / consensus revenue (Capital IQ, FY1-FY3)
F80: FY1 | G80: FY2 | H80: FY3
B81: =Detail_PeerAnalysis!A12 -> Flowers Foods, Inc. | D81: Core | E81: =Detail_PeerAnalysis!B12 -> NYSE:FLO | F81: =IF(AND(ISNUMBER(Inputs_Sources!$D$367),ISNUMBER(Inputs_Sources!$D$370)),Inputs_Sources!$D$367/Inputs_Sources!$D$370,"n/a") -> 0.023604207 | G81: =IF(AND(ISNUMBER(Inputs_Sources!$D$368),ISNUMBER(Inputs_Sources!$D$371)),Inputs_Sources!$D$368/Inputs_Sources!$D$371,"n/a") -> 0.024510453 | H81: =IF(AND(ISNUMBER(Inputs_Sources!$D$369),ISNUMBER(Inputs_Sources!$D$372)),Inputs_Sources!$D$369/Inputs_Sources!$D$372,"n/a") -> 0.024611533
B82: =Detail_PeerAnalysis!A13 -> Gruma, S.A.B. de C.V. | D82: Core | E82: =Detail_PeerAnalysis!B13 -> BMV:GRUMA B | F82: =IF(AND(ISNUMBER(Inputs_Sources!$D$404),ISNUMBER(Inputs_Sources!$D$407)),Inputs_Sources!$D$404/Inputs_Sources!$D$407,"n/a") -> 0.033059331 | G82: =IF(AND(ISNUMBER(Inputs_Sources!$D$405),ISNUMBER(Inputs_Sources!$D$408)),Inputs_Sources!$D$405/Inputs_Sources!$D$408,"n/a") -> 0.036656461 | H82: =IF(AND(ISNUMBER(Inputs_Sources!$D$406),ISNUMBER(Inputs_Sources!$D$409)),Inputs_Sources!$D$406/Inputs_Sources!$D$409,"n/a") -> 0.037547274
B83: =Detail_PeerAnalysis!A14 -> Yamazaki Baking Co., Ltd. | D83: Core | E83: =Detail_PeerAnalysis!B14 -> TSE:2212 | F83: =IF(AND(ISNUMBER(Inputs_Sources!$D$441),ISNUMBER(Inputs_Sources!$D$444)),Inputs_Sources!$D$441/Inputs_Sources!$D$444,"n/a") -> 0.044692992 | G83: =IF(AND(ISNUMBER(Inputs_Sources!$D$442),ISNUMBER(Inputs_Sources!$D$445)),Inputs_Sources!$D$442/Inputs_Sources!$D$445,"n/a") -> 0.042575521 | H83: =IF(AND(ISNUMBER(Inputs_Sources!$D$443),ISNUMBER(Inputs_Sources!$D$446)),Inputs_Sources!$D$443/Inputs_Sources!$D$446,"n/a") -> 0.040658037
B84: =Detail_PeerAnalysis!A15 -> ARYZTA AG | D84: Core | E84: =Detail_PeerAnalysis!B15 -> SWX:ARYN | F84: =IF(AND(ISNUMBER(Inputs_Sources!$D$478),ISNUMBER(Inputs_Sources!$D$481)),Inputs_Sources!$D$478/Inputs_Sources!$D$481,"n/a") -> 0.041981247 | G84: =IF(AND(ISNUMBER(Inputs_Sources!$D$479),ISNUMBER(Inputs_Sources!$D$482)),Inputs_Sources!$D$479/Inputs_Sources!$D$482,"n/a") -> 0.039362827 | H84: =IF(AND(ISNUMBER(Inputs_Sources!$D$480),ISNUMBER(Inputs_Sources!$D$483)),Inputs_Sources!$D$480/Inputs_Sources!$D$483,"n/a") -> 0.038189268
B85: =Detail_PeerAnalysis!A16 -> The J. M. Smucker Company | D85: Secondary | E85: =Detail_PeerAnalysis!B16 -> NYSE:SJM | F85: =IF(AND(ISNUMBER(Inputs_Sources!$D$515),ISNUMBER(Inputs_Sources!$D$518)),Inputs_Sources!$D$515/Inputs_Sources!$D$518,"n/a") -> 0.036560758 | G85: =IF(AND(ISNUMBER(Inputs_Sources!$D$516),ISNUMBER(Inputs_Sources!$D$519)),Inputs_Sources!$D$516/Inputs_Sources!$D$519,"n/a") -> 0.038153124 | H85: =IF(AND(ISNUMBER(Inputs_Sources!$D$517),ISNUMBER(Inputs_Sources!$D$520)),Inputs_Sources!$D$517/Inputs_Sources!$D$520,"n/a") -> 0.037851776
B86: =Detail_PeerAnalysis!A17 -> The Campbell's Company | D86: Secondary | E86: =Detail_PeerAnalysis!B17 -> NasdaqGS:CPB | F86: =IF(AND(ISNUMBER(Inputs_Sources!$D$552),ISNUMBER(Inputs_Sources!$D$555)),Inputs_Sources!$D$552/Inputs_Sources!$D$555,"n/a") -> 0.034197646 | G86: =IF(AND(ISNUMBER(Inputs_Sources!$D$553),ISNUMBER(Inputs_Sources!$D$556)),Inputs_Sources!$D$553/Inputs_Sources!$D$556,"n/a") -> 0.035820719 | H86: =IF(AND(ISNUMBER(Inputs_Sources!$D$554),ISNUMBER(Inputs_Sources!$D$557)),Inputs_Sources!$D$554/Inputs_Sources!$D$557,"n/a") -> 0.036676741
B87: =Detail_PeerAnalysis!A18 -> Mondelez International, Inc. | D87: Secondary | E87: =Detail_PeerAnalysis!B18 -> NasdaqGS:MDLZ | F87: =IF(AND(ISNUMBER(Inputs_Sources!$D$589),ISNUMBER(Inputs_Sources!$D$592)),Inputs_Sources!$D$589/Inputs_Sources!$D$592,"n/a") -> 0.035667778 | G87: =IF(AND(ISNUMBER(Inputs_Sources!$D$590),ISNUMBER(Inputs_Sources!$D$593)),Inputs_Sources!$D$590/Inputs_Sources!$D$593,"n/a") -> 0.035780175 | H87: =IF(AND(ISNUMBER(Inputs_Sources!$D$591),ISNUMBER(Inputs_Sources!$D$594)),Inputs_Sources!$D$591/Inputs_Sources!$D$594,"n/a") -> 0.035712343
B88: =Detail_PeerAnalysis!A19 -> Arca Continental, S.A.B. de C.V. | D88: Secondary | E88: =Detail_PeerAnalysis!B19 -> BMV:AC | F88: =IF(AND(ISNUMBER(Inputs_Sources!$D$626),ISNUMBER(Inputs_Sources!$D$629)),Inputs_Sources!$D$626/Inputs_Sources!$D$629,"n/a") -> 0.068803264 | G88: =IF(AND(ISNUMBER(Inputs_Sources!$D$627),ISNUMBER(Inputs_Sources!$D$630)),Inputs_Sources!$D$627/Inputs_Sources!$D$630,"n/a") -> 0.066707044 | H88: =IF(AND(ISNUMBER(Inputs_Sources!$D$628),ISNUMBER(Inputs_Sources!$D$631)),Inputs_Sources!$D$628/Inputs_Sources!$D$631,"n/a") -> 0.063765567
B89: =Detail_PeerAnalysis!A20 -> PepsiCo, Inc. | D89: Secondary | E89: =Detail_PeerAnalysis!B20 -> NasdaqGS:PEP | F89: =IF(AND(ISNUMBER(Inputs_Sources!$D$663),ISNUMBER(Inputs_Sources!$D$666)),Inputs_Sources!$D$663/Inputs_Sources!$D$666,"n/a") -> 0.044320907 | G89: =IF(AND(ISNUMBER(Inputs_Sources!$D$664),ISNUMBER(Inputs_Sources!$D$667)),Inputs_Sources!$D$664/Inputs_Sources!$D$667,"n/a") -> 0.04284669 | H89: =IF(AND(ISNUMBER(Inputs_Sources!$D$665),ISNUMBER(Inputs_Sources!$D$668)),Inputs_Sources!$D$665/Inputs_Sources!$D$668,"n/a") -> 0.043246326
B90: Peer median (excluding Bimbo) | F90: =MEDIAN(F81:F89) -> 0.036560758 | G90: =MEDIAN(G81:G89) -> 0.038153124 | H90: =MEDIAN(H81:H89) -> 0.037851776
B91: =Detail_PeerAnalysis!A11 -> Grupo Bimbo, S.A.B. de C.V. (subject) | D91: Subject Company >> | E91: =Detail_PeerAnalysis!B11 -> BMV:BIMBO A | F91: =IF(AND(ISNUMBER(Inputs_Sources!$D$675),ISNUMBER(Inputs_Sources!$D$669)),Inputs_Sources!$D$675/Inputs_Sources!$D$669,"n/a") -> 0.051560095 | G91: =IF(AND(ISNUMBER(Inputs_Sources!$D$687),ISNUMBER(Inputs_Sources!$D$681)),Inputs_Sources!$D$687/Inputs_Sources!$D$681,"n/a") -> 0.050172716 | H91: =IF(AND(ISNUMBER(Inputs_Sources!$D$699),ISNUMBER(Inputs_Sources!$D$693)),Inputs_Sources!$D$699/Inputs_Sources!$D$693,"n/a") -> 0.04895812
B92: FY1-FY3 = FY2026E-FY2028E; Smucker FY2027E-FY2029E (April year-end); Campbell's FY2027E-FY2029E (July year-end). The DCF terminal capex is a team decision: compare it with this benchmark.
B94: Source: S&P Capital IQ Pro (Task 1A/2A/2B pulls, 15/16-Oct-2026), SEC XBRL filings and company reports; compiled in Inputs_Sources and Detail_PeerAnalysis.

Sheet Detail_TearSheet
A1: TearSheet: Grupo Bimbo, S.A.B. de C.V. (BMV:BIMBO A), MXN millions unless stated
A2: Actuals: CIQ quarterly CSVs (sum of quarters; FY2021 restated) with company annual values where the CSV lacks Q4 2024 (flagged). FY2026E-FY2028E: CIQ consensus mean (20-Sep-2026). Adjusted EBITDA is the company IFRS 16 figure; CIQ EBITDA is standardised and sits after lease depreciation.
A3: Tags: sourced = CIQ CSV or company filing; calc = computed here; consensus = CIQ mean estimate; memo rows are not used in valuation except where stated.
A5: Line item | B5: Unit | C5: FY2021A | D5: FY2022A | E5: FY2023A | F5: FY2024A | G5: FY2025A | H5: FY2026E | I5: FY2027E | J5: FY2028E | K5: Tag | L5: Source / note
A6: Income statement
A7: Total revenue | B7: MXN m | C7: 338792 | D7: 398706 | E7: 399879 | F7: 408335 | G7: 426963 | H7: 426274.7 | I7: 445288 | J7: 468430.9 | K7: sourced / consensus | L7: CSV income_statement 'Total Revenue' (FY2021 restated = 338,792); FY2024 company annual (4Q24 missing in CSV; wiki/Financials/bimbo-income-statement-fy21-fy25.md s.1); FY26E-28E consensus.csv Revenue mean
A8: Revenue growth YoY | B8: % | D8: =IFERROR(D7/C7-1,"n/a") -> 0.17684597 | E8: =IFERROR(E7/D7-1,"n/a") -> 0.0029420174 | F8: =IFERROR(F7/E7-1,"n/a") -> 0.021146397 | G8: =IFERROR(G7/F7-1,"n/a") -> 0.045619406 | H8: =IFERROR(H7/G7-1,"n/a") -> -0.0016120835 | I8: =IFERROR(I7/H7-1,"n/a") -> 0.044603398 | J8: =IFERROR(J7/I7-1,"n/a") -> 0.05197288 | K8: calc | L8: calc
A9: Gross profit | B9: MXN m | C9: 181789.4 | D9: 205974.4 | E9: 206159.5 | F9: 214928 | G9: 224241.7 | K9: sourced | L9: CSV 'Gross Profit' (CIQ basis; company FY24 214,928; company FY25 223,487 differs by 0.3%)
A10: Gross margin | B10: % | C10: =IFERROR(C9/C7,"n/a") -> 0.53658115 | D10: =IFERROR(D9/D7,"n/a") -> 0.51660722 | E10: =IFERROR(E9/E7,"n/a") -> 0.51555471 | F10: =IFERROR(F9/F7,"n/a") -> 0.52635214 | G10: =IFERROR(G9/G7,"n/a") -> 0.52520172 | K10: calc | L10: calc
A11: Gross margin, consensus mean | B11: % | H11: 52.3 | I11: 52 | J11: 52.05 | K11: consensus | L11: consensus.csv Gross Margin (%) mean
A12: SG&A (selling, general and administrative) | B12: MXN m | C12: 147963 | D12: 167254 | E12: 165748 | F12: 175164 | G12: 184186 | H12: 177262 | I12: 189938 | J12: 197030 | K12: sourced / consensus | L12: CSV 'Selling General & Admin Exp.' (CIQ basis); FY2024 company general expenses 175,164; FY26E-28E consensus mean
A13: SG&A / sales | B13: % | C13: =IFERROR(C12/C7,"n/a") -> 0.43673699 | D13: =IFERROR(D12/D7,"n/a") -> 0.41949206 | E13: =IFERROR(E12/E7,"n/a") -> 0.41449538 | F13: =IFERROR(F12/F7,"n/a") -> 0.42897131 | G13: =IFERROR(G12/G7,"n/a") -> 0.43138633 | H13: =IFERROR(H12/H7,"n/a") -> 0.41583983 | I13: =IFERROR(I12/I7,"n/a") -> 0.42655091 | J13: =IFERROR(J12/J7,"n/a") -> 0.420617 | K13: calc | L13: calc
A14: Total operating expenses, CIQ basis | B14: MXN m | C14: 148200.4 | D14: 169510.4 | E14: 168704.7 | F14: 181779 | G14: 187970.1 | K14: sourced | L14: CSV 'Other Operating Exp., Total'; FY2024 company total operating expenses (wiki s.1)
A15: EBIT, CIQ standardised | B15: MXN m | C15: 33588.9 | D15: 36464.1 | E15: 37454.8 | G15: 36271.6 | K15: sourced | L15: CSV 'Operating Income' (sum of quarters); not like-for-like with company operating income (see next row); FY2024 CSV Q4 missing
A16: Operating income, company basis (FY26E-28E: consensus EBIT) | B16: MXN m | C16: 32580 | D16: 53696 | E16: 35455 | F16: 33149 | G16: 34146 | H16: 37446 | I16: 38779 | J16: 41926 | K16: sourced / consensus | L16: Company FY21 restated 32,580 and FY22 53,696 incl. MEPP/Ricolino one-offs (wiki s.1); consensus.csv EBIT is company basis (FY25A 34,146)
A17: Operating margin, company basis | B17: % | C17: =IFERROR(C16/C7,"n/a") -> 0.096165199 | D17: =IFERROR(D16/D7,"n/a") -> 0.13467568 | E17: =IFERROR(E16/E7,"n/a") -> 0.088664321 | F17: =IFERROR(F16/F7,"n/a") -> 0.081180893 | G17: =IFERROR(G16/G7,"n/a") -> 0.079974143 | H17: =IFERROR(H16/H7,"n/a") -> 0.087844763 | I17: =IFERROR(I16/I7,"n/a") -> 0.087087458 | J17: =IFERROR(J16/J7,"n/a") -> 0.089503062 | K17: calc | L17: calc
A18: EBITDA, CIQ standardised (after lease depreciation) | B18: MXN m | C18: 45540.9 | D18: 50087.1 | E18: 51987.8 | G18: 54815.1 | K18: sourced | L18: CSV 'EBITDA' (sum of quarters); about 6 bn below company Adj. EBITDA (ROU depreciation); not the valuation basis
A19: Adjusted EBITDA, company, IFRS 16 (valuation basis) | B19: MXN m | C19: 47372 | D19: 53446 | E19: 54942 | F19: 55473 | G19: 59456 | H19: 62117 | I19: 64891 | J19: 68999 | K19: sourced / consensus | L19: Company Adj. EBITDA FY21 restated, FY22-25 (wiki s.1; FY24 55,473 vs 55,474 in releases); FY26E-28E consensus EBITDA mean (same definition, FY25A 59,456)
A20: Adjusted EBITDA margin | B20: % | C20: =IFERROR(C19/C7,"n/a") -> 0.13982621 | D20: =IFERROR(D19/D7,"n/a") -> 0.13404865 | E20: =IFERROR(E19/E7,"n/a") -> 0.13739656 | F20: =IFERROR(F19/F7,"n/a") -> 0.13585169 | G20: =IFERROR(G19/G7,"n/a") -> 0.13925328 | H20: =IFERROR(H19/H7,"n/a") -> 0.14572059 | I20: =IFERROR(I19/I7,"n/a") -> 0.14572816 | J20: =IFERROR(J19/J7,"n/a") -> 0.14729814 | K20: calc | L20: calc
A21: Pre-tax profit (continuing) | B21: MXN m | C21: 24854 | D21: 45878 | E21: 25324 | F21: 21034 | G21: 20143 | H21: 23597 | I21: 25677 | J21: 30308 | K21: sourced / consensus | L21: CSV 'EBT Incl. Unusual Items' (FY2024 company 21,034); FY26E-28E consensus EBT normalised mean
A22: Net income to majority | B22: MXN m | C22: 15916 | D22: 46910 | E22: 15477 | F22: 12544 | G22: 11133 | H22: 13688 | I22: 15011 | J22: 17371 | K22: sourced / consensus | L22: CSV 'NI to Common Incl Extra Items' (FY2024 company 12,544); FY26E-28E consensus net income normalised mean
A23: Net margin | B23: % | C23: =IFERROR(C22/C7,"n/a") -> 0.046978677 | D23: =IFERROR(D22/D7,"n/a") -> 0.11765562 | E23: =IFERROR(E22/E7,"n/a") -> 0.038704208 | F23: =IFERROR(F22/F7,"n/a") -> 0.030719875 | G23: =IFERROR(G22/G7,"n/a") -> 0.026074859 | H23: =IFERROR(H22/H7,"n/a") -> 0.032110749 | I23: =IFERROR(I22/I7,"n/a") -> 0.033710767 | J23: =IFERROR(J22/J7,"n/a") -> 0.037083378 | K23: calc | L23: calc
A24: EPS, basic, total (E = consensus normalised EPS mean) | B24: MXN/share | C24: 3.55 | D24: 10.54 | E24: 3.5 | F24: 2.88 | G24: 2.58 | H24: 3.07 | I24: 3.35 | J24: 3.8 | K24: sourced / consensus | L24: Company basic EPS total (wiki s.1); consensus.csv 'EPS Normalized' mean FY26E-28E (3.07 / 3.35 / 3.80)
A25: DPS declared for the fiscal year (E = consensus mean) | B25: MXN/share | C25: 1 | D25: 0.65 | E25: 0.78 | F25: 0.94 | G25: 1 | H25: 1.01 | I25: 1.05 | J25: 1.24 | K25: sourced / consensus | L25: Company declared DPS (wiki s.1). CIQ actual DPS differs for FY21-FY23 (memo row below)
A26: DPS, CIQ actual (memo; timing differs) | B26: MXN/share | C26: 0 | D26: 1.3 | E26: 0.94 | F26: 0.94 | G26: 1 | K26: sourced | L26: consensus.csv 'Dividend per share' Actual (A); see Checks
A27: Balance sheet (fiscal year-end; CSV Q4)
A28: Cash and short-term investments | B28: MXN m | C28: 8748 | D28: 12313 | E28: 6353 | F28: 8057 | G28: 8535 | K28: sourced | L28: CSV balance_sheet 'Cash & Short-term Investments' Q4
A29: Total current assets | B29: MXN m | C29: 53411 | D29: 63470 | E29: 58914 | F29: 67180 | G29: 64671 | K29: sourced | L29: CSV 'Total Current Assets' Q4
A30: Total assets | B30: MXN m | C30: 337640 | D30: 347764 | E30: 348102 | F30: 416804 | G30: 409805 | K30: sourced | L30: CSV 'Total Assets' Q4
A31: Non-current assets (total assets less current assets) | B31: MXN m | C31: =IFERROR(C30-C29,"n/a") -> 284229 | D31: =IFERROR(D30-D29,"n/a") -> 284294 | E31: =IFERROR(E30-E29,"n/a") -> 289188 | F31: =IFERROR(F30-F29,"n/a") -> 349624 | G31: =IFERROR(G30-G29,"n/a") -> 345134 | K31: calc | L31: calc
A32: Total current liabilities | B32: MXN m | C32: 80760 | D32: 89734 | E32: 87192 | F32: 85155 | G32: 90573 | K32: sourced | L32: CSV 'Total Current Liabilities' Q4
A33: Total liabilities (excl. NCI) | B33: MXN m | C33: 236034 | D33: 220162 | E33: 236474 | F33: 289106 | G33: 289550 | K33: sourced | L33: CSV 'Total Liabilities' Q4
A34: Non-current liabilities (total liabilities less current) | B34: MXN m | C34: =IFERROR(C33-C32,"n/a") -> 155274 | D34: =IFERROR(D33-D32,"n/a") -> 130428 | E34: =IFERROR(E33-E32,"n/a") -> 149282 | F34: =IFERROR(F33-F32,"n/a") -> 203951 | G34: =IFERROR(G33-G32,"n/a") -> 198977 | K34: calc | L34: calc
A35: Total equity incl. NCI | B35: MXN m | C35: 101606 | D35: 127602 | E35: 111628 | F35: 127698 | G35: 120255 | K35: sourced | L35: CSV 'Total Equity' Q4
A36: Total debt incl. IFRS 16 leases (CIQ) | B36: MXN m | C36: 124071 | D36: 113829 | E36: 139539 | F36: 187395 | G36: 190767 | K36: sourced | L36: CSV 'Total Debt' Q4 (= financial debt + lease liabilities)
A37: Net debt incl. IFRS 16 leases (CIQ) | B37: MXN m | C37: 115323 | D37: 101516 | E37: 133186 | F37: 179338 | G37: 182232 | K37: sourced | L37: CSV 'Net Debt' Q4
A38: Net debt ex-IFRS 16 (company; memo) | B38: MXN m | C38: 84107 | D38: 71741 | E38: 103582 | F38: 142848 | G38: 145128 | K38: sourced | L38: Company, RA25 p.299 and wiki; FY21 84,107 (wiki cross-source); FY22 71,741 from consensus.csv 'Net Debt' actual (basis unconfirmed)
A39: Net debt incl. leases / Adjusted EBITDA | B39: x | C39: =IFERROR(C37/C19,"n/a") -> 2.4344127 | D39: =IFERROR(D37/D19,"n/a") -> 1.8994125 | E39: =IFERROR(E37/E19,"n/a") -> 2.42412 | F39: =IFERROR(F37/F19,"n/a") -> 3.2328881 | G39: =IFERROR(G37/G19,"n/a") -> 3.0649892 | K39: calc | L39: calc
A40: Cash flow
A41: Cash from operations | B41: MXN m | C41: 45776 | D41: 38851 | E41: 31411 | F41: 39907 | G41: 47753 | K41: sourced | L41: CSV 'Cash from Ops.' FY22, FY23, FY25; FY21 and FY24 from company (wiki cash-flow article; CSV quarter missing). Consensus CFO actuals differ for FY23/FY24 (see Checks)
A42: Capital expenditure | B42: MXN m | C42: -20671 | D42: -28669 | E42: -34754 | F42: -29402 | G42: -22530 | H42: -21978.8 | I42: -22341.3 | J42: -22933.5 | K42: sourced / consensus | L42: CSV 'Capital Expenditure' FY22, FY23, FY25; FY21 and FY24 company (wiki); FY26E-28E consensus mean (sign flipped)
A43: Capex / sales | B43: % | C43: =IFERROR(-C42/C7,"n/a") -> 0.061013837 | D43: =IFERROR(-D42/D7,"n/a") -> 0.071905113 | E43: =IFERROR(-E42/E7,"n/a") -> 0.086911291 | F43: =IFERROR(-F42/F7,"n/a") -> 0.072004604 | G43: =IFERROR(-G42/G7,"n/a") -> 0.052768038 | H43: =IFERROR(-H42/H7,"n/a") -> 0.051560179 | I43: =IFERROR(-I42/I7,"n/a") -> 0.050172697 | J43: =IFERROR(-J42/J7,"n/a") -> 0.048958128 | K43: calc | L43: calc
A44: Cash from investing | B44: MXN m | D44: -9122 | E44: -42440 | F44: -36138 | G44: -34652 | K44: sourced / calc | L44: CSV 'Cash from Investing' FY22, FY23, FY25; FY24 = sum of company investing lines (wiki cash-flow article, incl. residual that ties to CFI) [calc]
A45: Cash from financing | B45: MXN m | D45: -25692 | E45: 5904 | G45: -11908 | K45: sourced | L45: CSV 'Cash from Financing'; FY21 and FY24 not available (CSV quarter missing; company totals not in wiki)
A46: Change in working capital, CIQ basis | B46: MXN m | C46: -5502 | D46: -6533 | E46: 11165 | F46: 1017 | G46: -696 | K46: sourced | L46: CSV 'Change in Net Working Capital' (CIQ definition; sign and size differ from company lines, see memo)
A47: Change in working capital, company lines (memo) | B47: MXN m | C47: 5451 | D47: -2737 | E47: -6542 | F47: -7733 | G47: -655 | K47: sourced | L47: wiki/Financials/bimbo-cash-flow-and-fcf.md (six working-capital lines); not used in valuation
A48: Levered free cash flow, CIQ (memo) | B48: MXN m | D48: 13502.3 | E48: -10624.6 | G48: 16360.6 | K48: sourced | L48: CSV 'Levered Free Cash Flow' (CIQ definition; memo only)
A49: Margins and ratios (calc from the rows above)
A50: EBITDA margin, CIQ standardised | B50: % | C50: =IFERROR(C18/C7,"n/a") -> 0.13442141 | D50: =IFERROR(D18/D7,"n/a") -> 0.12562414 | E50: =IFERROR(E18/E7,"n/a") -> 0.13000883 | G50: =IFERROR(G18/G7,"n/a") -> 0.12838372 | K50: calc | L50: calc

Sheet Detail_PeerAnalysis
A1: PeerAnalysis: Grupo Bimbo vs bakery and packaged-food peers (USD m unless stated)
A2: Pricing date 16-Oct-2026 (CIQ 15/16-Oct-2026). Forward horizon: NTM from 16-Oct-2026, calendarised from each company's fiscal-year consensus by day weights (block D).
A3: EV claim basis (one basis for all eligible peers and for Bimbo): EV = market cap + financial debt (incl. finance leases) + lease liabilities (operating or IFRS 16) + NCI at book incl. redeemable NCI - cash. Pensions/OPEB, MEPP and derivatives are excluded for every company (not sourced for all eligible peers).
A4: Lease basis: IFRS 16-equivalent. EBITDA is before operating lease cost: US GAAP peers add back operating lease cost (LTM; held flat for NTM) because EV includes their operating lease liabilities. Peers without a reconciled basis are shown but excluded from medians.
A5: Bimbo: company Adjusted EBITDA (IFRS 16, 60,919) includes consolidated BBU independent-operator earnings (profit to NCI per coordinator); NCI is taken at book (722), which understates the NCI claim if that profit is attributed to NCI. Model-basis EBIT + D&A is shown as a memo (block D).
A6: Bimbo price MXN 58.60 (BMV official close 16-Oct-2026) and shares 4,294.9m (BMV notice 29-Jul-2026: 4,294,943,715). USD columns convert at the pricing-date rate (Inputs_Sources fx_bmv_disp = fx_mxn_spot, MXN 18.479 per USD on 16-Oct-2026) for size only; multiples are computed in MXN.
A7: P/E for peers = CIQ multiples tool (NTM / LTM), EPS derived as price / P/E; Gruma = price / EPS (Capital IQ prompt 4: diluted EPS LTM and consensus FY2026E-FY2027E, day-weighted). Gross profit, dividends and price performance are on the front sheets (Capital IQ prompts 5-6); blank = not retrieved, never zero.
A8: Medians and means use only peers with in-median flag = yes (AGGREGATE / SUMPRODUCT formulas; n/a cells are ignored). Core = Flowers, Gruma, Yamazaki, Aryzta; at present Yamazaki (lease basis) and Aryzta (NCI not verified) are excluded.
A9: A. Market data and enterprise value on the claim basis
A10: Company | B10: Ticker | C10: Group | D10: Price currency | E10: Reporting currency | F10: Price (local) | G10: Shares (m) | H10: FX local to USD | I10: Market cap (USD m) | J10: Financial debt incl. finance leases (USD m) | K10: Lease liabilities, operating / IFRS 16 (USD m) | L10: NCI at book incl. redeemable (USD m) | M10: Cash (USD m) | N10: Net debt, claim basis (USD m) | O10: EV, claim basis (USD m) | P10: In median: valuation (yes/no) | Q10: In median: P/E (yes/no) | R10: EV claim basis (categories included and excluded) | S10: Distributor / IO earnings in EBITDA? | T10: Eligibility notes
A11: Grupo Bimbo, S.A.B. de C.V. (subject) | B11: BMV:BIMBO A | C11: Subject | D11: MXN | E11: MXN | F11: =Inputs_Sources!$D$13 -> 58.6 | G11: =Inputs_Sources!$D$14 -> 4294.9 | H11: =1/Inputs_Sources!$D$11 -> 0.054115482 | I11: =IFERROR(F11*G11*H11,"n/a") -> 13619.846 | J11: =IFERROR(Inputs_Sources!$D$18*H11,"n/a") -> 8315.385 | K11: =IFERROR(Inputs_Sources!$D$19*H11,"n/a") -> 1805.3466 | L11: =IFERROR(Inputs_Sources!$D$17*H11,0) -> 39.071378 | M11: =IFERROR(Inputs_Sources!$D$16*H11,"n/a") -> 896.31474 | N11: =IFERROR(J11+K11+L11-M11,"n/a") -> 9263.4883 | O11: =IFERROR(I11+N11,"n/a") -> 22883.335 | P11: subject | Q11: subject | R11: Financial debt 153,660 + IFRS 16 lease liabilities 33,361 + NCI at book 722 - cash 16,563 (MXN m, 30-Jun-2026). Excludes MEPP, pensions/OPEB and derivatives. | S11: Yes: BBU independent operators (US route partners) are consolidated structured entities (RA25 p.249-250); their profit to NCI is the coordinator's statement, not confirmed in the wiki (FY25 NCI profit share 1,813). | T11: Subject. Price: BMV official close 16-Oct-2026; shares: BMV notice 29-Jul-2026. EBITDA includes consolidated IO earnings.
A12: Flowers Foods, Inc. | B12: NYSE:FLO | C12: Core | D12: USD | E12: USD | F12: =IFERROR(Inputs_Sources!$D$37/Inputs_Sources!$D$38,"n/a") -> 6.1089109 | G12: =Inputs_Sources!$D$38 -> 212.1 | H12: 1 | I12: =IFERROR(F12*G12*H12,"n/a") -> 1295.7 | J12: =Inputs_Sources!$D$191+Inputs_Sources!$D$192 -> 1686.2 | K12: =Inputs_Sources!$D$193 -> 317.102 | L12: =Inputs_Sources!$D$194 -> 0 | M12: =Inputs_Sources!$D$195 -> 52.766 | N12: =IFERROR(J12+K12+L12-M12,"n/a") -> 1950.536 | O12: =IFERROR(I12+N12,"n/a") -> 3246.236 | P12: yes | Q12: yes | R12: Financial debt 1,686.2 (current 399.9, non-current 1,286.4; no finance leases tagged) + operating lease liabilities 317.1 (75.2 + 241.9) + NCI nil (no minority interest reported) - cash 52.8. CIQ total debt is 2,007.8, 4.5 above these components (not added). | S12: No: independent distributors not consolidated (coordinator statement; not re-verified in this session) | T12: US GAAP, lease basis reconciled: CIQ total debt 2,007.8 vs financial debt 1,686.2 + operating leases 317.1 (-0.2%); EBITDA + LTM operating lease cost 91.8; NCI nil (filings). P/E available (23.45x / 8.93x) and not distorted. Unchanged.
A13: Gruma, S.A.B. de C.V. | B13: BMV:GRUMA B | C13: Core | D13: MXN | E13: USD | F13: =Inputs_Sources!$D$54 -> 242.02 | G13: =Inputs_Sources!$D$55 -> 336.20799 | H13: =Inputs_Sources!$D$56 -> 0.054115482 | I13: =IFERROR(F13*G13*H13,"n/a") -> 4403.3257 | J13: =Inputs_Sources!$D$226+Inputs_Sources!$D$227 -> 1698.6 | K13: =Inputs_Sources!$D$228 -> 413.2 | L13: =Inputs_Sources!$D$229 -> 2.8 | M13: =Inputs_Sources!$D$230 -> 483.6 | N13: =IFERROR(J13+K13+L13-M13,"n/a") -> 1631 | O13: =IFERROR(I13+N13,"n/a") -> 6034.3257 | P13: yes | Q13: yes | R13: Bank loans, carrying (ST 365.2 + LT 1,333.4) + IFRS 16 lease liabilities 413.2 (current 52.8, non-current 360.4) + NCI 2.8 - cash 483.6. Reports in USD. | S13: Not checked | T13: IFRS 16, USD statements: debt + IFRS 16 leases reconcile to CIQ total debt 2,111.8; EBITDA before lease costs (company UAFIRDA); NCI 2.8 from filings. Consensus FY2026E-FY2028E is now available on the same company basis (FY26E 1,111.37 vs LTM 1,108.9), so Gruma enters the NTM medians. P/E now available: price USD 13.10 / diluted EPS LTM 1.40 = 9.36x, NTM 9.74x; earnings not depressed, so P/E-eligible (it was 'no' only for lack of data).
A14: Yamazaki Baking Co., Ltd. | B14: TSE:2212 | C14: Core | D14: JPY | E14: JPY | F14: =Inputs_Sources!$D$71 -> 3816 | G14: =Inputs_Sources!$D$72 -> 196.9 | H14: =Inputs_Sources!$D$73 -> 0.0063296347 | I14: =IFERROR(F14*G14*H14,"n/a") -> 4755.9002 | J14: n/a | K14: n/a | L14: n/a | M14: n/a | N14: =Inputs_Sources!$D$75 -> -473.5 | O14: =IFERROR(I14+N14,"n/a") -> 4282.4002 | P14: no | Q14: no | R14: Descriptive only, not the claim basis: EV = market cap + Capital IQ net debt -473.5 (includes J-GAAP finance-lease obligations, JPY 7,853m; operating leases are off balance sheet; NCI not returned). Excluded from medians. | S14: Not checked | T14: Fails the lease test. Under J-GAAP operating leases are off balance sheet (CIQ's JPY 7,853m are finance-lease obligations) and no operating lease cost is available to add back, so EBITDA is after operating lease costs: neither 'debt includes leases' nor 'EBITDA before lease costs' holds. NCI not returned (CIQ N/A). Peers without a reconciled basis are excluded from all medians, P/E included. Unchanged.
A15: ARYZTA AG | B15: SWX:ARYN | C15: Core | D15: USD | E15: EUR | F15: =IFERROR(Inputs_Sources!$D$88/Inputs_Sources!$D$89,"n/a") -> 49.145161 | G15: =Inputs_Sources!$D$89 -> 24.8 | H15: 1 | I15: =IFERROR(F15*G15*H15,"n/a") -> 1218.8 | J15: =Inputs_Sources!$D$233+Inputs_Sources!$D$234 -> 791.16031 | K15: =Inputs_Sources!$D$235 -> 195.7486 | L15: =Inputs_Sources!$D$236 -> -17.4 | M15: =Inputs_Sources!$D$237 -> 85 | N15: =IFERROR(J15+K15+L15-M15,"n/a") -> 884.50891 | O15: =IFERROR(I15+N15,"n/a") -> 2103.3089 | P15: no | Q15: no | R15: Long-term debt 791.2 (EUR 678.2) + IFRS 16 lease liabilities 195.7 (EUR 167.8: current 35.5 + non-current 132.3) = CIQ total debt 986.9; + CIQ TEV residual -17.4 (unexplained, not a book NCI) - cash 85.0 (EUR 72.9). USD at Capital IQ's 1.166559. Lease basis reconciled; NCI not verified, so descriptive only. | S15: Not checked | T15: Lease basis now passes: CIQ total debt EUR 845.9m = long-term debt 678.2 + IFRS 16 leases 167.8 (35.5 + 132.3); IFRS 16 EBITDA is before lease costs; shares 24.8m in three CIQ pulls. Fails the claim basis on NCI: Capital IQ returns minority interest as N/A for every company, including CPB (306), MDLZ (53), PEP (195) and Gruma (2.8), whose filings show NCI, so N/A is not zero, and the CIQ TEV residual (-17.4) is unexplained. NCI not verified, so excluded from all medians. Unchanged.
A16: The J. M. Smucker Company | B16: NYSE:SJM | C16: Secondary | D16: USD | E16: USD | F16: =IFERROR(Inputs_Sources!$D$105/Inputs_Sources!$D$106,"n/a") -> 127.45787 | G16: =Inputs_Sources!$D$106 -> 106.8 | H16: 1 | I16: =IFERROR(F16*G16*H16,"n/a") -> 13612.5 | J16: =Inputs_Sources!$D$198+Inputs_Sources!$D$199 -> 6747.4 | K16: =Inputs_Sources!$D$200 -> 192.8 | L16: =Inputs_Sources!$D$201 -> 0 | M16: =Inputs_Sources!$D$202 -> 43.2 | N16: =IFERROR(J16+K16+L16-M16,"n/a") -> 6897 | O16: =IFERROR(I16+N16,"n/a") -> 20509.5 | P16: yes | Q16: no | R16: Financial debt 6,737.8 (ST borrowings 193.5, current LTD 150.0, LTD 6,394.3) + finance leases 9.6 + operating lease liabilities 192.8 + NCI nil (not reported) - cash 43.2. Ties exactly to CIQ EV. | S16: Not checked | T16: US GAAP, lease basis reconciled (exact tie incl. finance leases 9.6); EBITDA + operating lease cost 46.9; in EV medians. P/E excluded: LTM 58.6x reflects depressed earnings [assumption]. Unchanged.
A17: The Campbell's Company | B17: NasdaqGS:CPB | C17: Secondary | D17: USD | E17: USD | F17: =IFERROR(Inputs_Sources!$D$122/Inputs_Sources!$D$123,"n/a") -> 19.872233 | G17: =Inputs_Sources!$D$123 -> 298.2 | H17: 1 | I17: =IFERROR(F17*G17*H17,"n/a") -> 5925.9 | J17: =Inputs_Sources!$D$205+Inputs_Sources!$D$206 -> 7137 | K17: =Inputs_Sources!$D$207 -> 313 | L17: =Inputs_Sources!$D$208 -> 306 | M17: =Inputs_Sources!$D$209 -> 394 | N17: =IFERROR(J17+K17+L17-M17,"n/a") -> 7362 | O17: =IFERROR(I17+N17,"n/a") -> 13287.9 | P17: yes | Q17: yes | R17: Financial debt 7,053.0 + finance leases 84.0 + operating lease liabilities 313.0 + NCI 2.0 + redeemable NCI (mezzanine) 304.0 - cash 394.0. Ties to CIQ EV including the 306 residual. | S17: Not checked | T17: US GAAP, lease basis reconciled (exact tie); EBITDA + operating lease cost 114.0; EV includes redeemable NCI 304 and NCI 2. P/E 15.11x / 11.72x. Unchanged.
A18: Mondelez International, Inc. | B18: NasdaqGS:MDLZ | C18: Secondary | D18: USD | E18: USD | F18: =IFERROR(Inputs_Sources!$D$139/Inputs_Sources!$D$140,"n/a") -> 63.910366 | G18: =Inputs_Sources!$D$140 -> 1276.3 | H18: 1 | I18: =IFERROR(F18*G18*H18,"n/a") -> 81568.8 | J18: =Inputs_Sources!$D$212+Inputs_Sources!$D$213 -> 21450 | K18: =Inputs_Sources!$D$214 -> 773 | L18: =Inputs_Sources!$D$215 -> 53 | M18: =Inputs_Sources!$D$216 -> 1716 | N18: =IFERROR(J18+K18+L18-M18,"n/a") -> 20560 | O18: =IFERROR(I18+N18,"n/a") -> 102128.8 | P18: yes | Q18: yes | R18: Financial debt 21,450 (includes finance leases, not separated at 30-Jun-26; 423 at 31-Dec-25) + noncurrent operating lease liabilities 609 (current portion not found; 164 at 31-Dec-25) + NCI 53 - cash 1,716. Ties to CIQ EV. | S18: Not checked | T18: US GAAP, lease basis reconciled on noncurrent leases (exact tie) + current leases 164 (Dec-25 proxy) [assumption]; EBITDA + FY25 operating lease cost 246 [assumption]; NCI 53. P/E 23.1x / 19.8x. Unchanged.
A19: Arca Continental, S.A.B. de C.V. | B19: BMV:AC | C19: Secondary | D19: MXN | E19: MXN | F19: =Inputs_Sources!$D$156 -> 209.66 | G19: =Inputs_Sources!$D$157 -> 1696.2 | H19: =Inputs_Sources!$D$158 -> 0.054115482 | I19: =IFERROR(F19*G19*H19,"n/a") -> 19244.834 | J19: n/a | K19: n/a | L19: n/a | M19: n/a | N19: =Inputs_Sources!$D$160 -> 2015.4 | O19: =IFERROR(I19+N19,"n/a") -> 21260.234 | P19: no | Q19: no | R19: Descriptive only, not the claim basis: EV = market cap + Capital IQ net debt 2,015.4 (includes IFRS 16 leases, MXN 1,832.2m; NCI not returned: the CIQ tool's 8.47x implies about MXN 19.9bn of claims missing from this EV). Excluded from medians. | S19: Not checked | T19: Lease basis now passes: CIQ total debt MXN 65,427m includes IFRS 16 leases 1,832.2 (reconciles within 3.7 once two derivation slips in the output are corrected); IFRS 16 EBITDA; shares 1,696.2m; price corroborated by the CIQ chart. Fails the claim basis on NCI: CIQ N/A, and the CIQ tool's 8.47x vs 8.06x ex-NCI implies about MXN 19.9bn of claims missing from our EV, consistent with a material NCI. Excluded from all medians. Unchanged.
A20: PepsiCo, Inc. | B20: NasdaqGS:PEP | C20: Secondary | D20: USD | E20: USD | F20: =IFERROR(Inputs_Sources!$D$173/Inputs_Sources!$D$174,"n/a") -> 131.504 | G20: =Inputs_Sources!$D$174 -> 1362.7 | H20: 1 | I20: =IFERROR(F20*G20*H20,"n/a") -> 179200.5 | J20: =Inputs_Sources!$D$219+Inputs_Sources!$D$220 -> 51881 | K20: =Inputs_Sources!$D$221 -> 3846 | L20: =Inputs_Sources!$D$222 -> 195 | M20: =Inputs_Sources!$D$223 -> 10675 | N20: =IFERROR(J20+K20+L20-M20,"n/a") -> 45247 | O20: =IFERROR(I20+N20,"n/a") -> 224447.5 | P20: yes | Q20: yes | R20: Financial debt 51,881 (= CIQ total debt; finance leases not separated) + operating lease liabilities 3,846 (27-Dec-2025 10-K; Sep-2026 not found; CIQ excludes leases) + NCI 195 - cash 10,675. CIQ net debt (40,718) deducts a further 488 that is not cash and is not used. | S20: Not checked (franchise bottler consolidation not verified) | T20: US GAAP: CIQ debt excludes operating leases, so EV adds 3,846 (27-Dec-2025 10-K) [assumption]; EBITDA + FY25 operating lease cost 880 [assumption]; NCI 195. P/E 16.15x / 15.53x. Unchanged.
A23: B. Financials (USD m; Bimbo converted at the MXN display rate)
A24: Company | B24: Revenue FY2024 | C24: Revenue FY2025 | D24: Revenue LTM | E24: Revenue NTM (calendarised) | F24: EBITDA FY2024 (reported) | G24: EBITDA FY2025 (reported) | H24: EBITDA LTM (reported) | I24: Operating lease cost add-back, LTM | J24: EBITDA LTM, IFRS 16-equivalent | K24: EBITDA NTM (reported, calendarised) | L24: EBITDA NTM, IFRS 16-equivalent | M24: Gross profit LTM | N24: Levered FCF LTM | O24: EBITDA margin LTM (IFRS 16-eq.) | P24: Gross margin LTM | Q24: EPS LTM (local) | R24: EPS NTM (local)
A25: Grupo Bimbo (subject) | B25: =IFERROR(Detail_TearSheet!$F$7*$H$11,"n/a") -> 22097.246 | C25: =IFERROR(Detail_TearSheet!$G$7*$H$11,"n/a") -> 23105.309 | D25: =IFERROR(Inputs_Sources!$D$29*$H$11,"n/a") -> 22805.509 | E25: =IFERROR(K60*$H$11,"n/a") -> 23879.916 | F25: =IFERROR(Detail_TearSheet!$F$19*$H$11,"n/a") -> 3001.9482 | G25: =IFERROR(Detail_TearSheet!$G$19*$H$11,"n/a") -> 3217.4901 | H25: =IFERROR((Inputs_Sources!$D$25+Inputs_Sources!$D$26+Inputs_Sources!$D$27+Inputs_Sources!$D$28)*$H$11,"n/a") -> 3296.6611 | I25: 0 | J25: =IFERROR(H25+I25,"n/a") -> 3296.6611 | K25: =IFERROR(H60*$H$11,"n/a") -> 3479.9394 | L25: =IFERROR(K25+I25,"n/a") -> 3479.9394 | M25: =IFERROR(Inputs_Sources!$D$34*$H$11,"n/a") -> 11986.052 | N25: =IFERROR(Inputs_Sources!$D$35*$H$11,"n/a") -> 1376.338 | O25: =IFERROR(J25/D25,"n/a") -> 0.14455547 | P25: =IFERROR(M25/D25,"n/a") -> 0.52557706 | Q25: =IFERROR(Inputs_Sources!$D$30+Inputs_Sources!$D$31+Inputs_Sources!$D$32+Inputs_Sources!$D$33,"n/a") -> 3.175 | R25: =N60 -> 3.2909315
A26: Flowers Foods, Inc. | B26: =Inputs_Sources!$D$44 -> 5103.5 | C26: =Inputs_Sources!$D$45 -> 5256.5 | D26: =Inputs_Sources!$D$43 -> 5223.9 | E26: =K61 -> 5062.0877 | F26: =Inputs_Sources!$D$46 -> 520.7 | G26: =Inputs_Sources!$D$47 -> 514.8 | H26: =Inputs_Sources!$D$42 -> 486.9 | I26: =IF(ISNUMBER(Inputs_Sources!$D$289),Inputs_Sources!$D$289,0) -> 91.809 | J26: =IFERROR(H26+I26,"n/a") -> 578.709 | K26: =H61 -> 436.26849 | L26: =IFERROR(K26+I26,"n/a") -> 528.07749 | M26: =Inputs_Sources!$D$48 -> 2540.4 | N26: =Inputs_Sources!$D$49 -> 298.5 | O26: =IFERROR(J26/D26,"n/a") -> 0.11078103 | P26: =IFERROR(M26/D26,"n/a") -> 0.48630334 | Q26: =IFERROR(F12/Inputs_Sources!$D$50,"n/a") -> 0.26050793 | R26: =IFERROR(F12/Inputs_Sources!$D$51,"n/a") -> 0.68408857
A27: Gruma, S.A.B. de C.V. | B27: =Inputs_Sources!$D$61 -> 6486.9 | C27: =Inputs_Sources!$D$62 -> 6374.6 | D27: =Inputs_Sources!$D$60 -> 6500.1 | E27: =K62 -> 6487.4487 | F27: =Inputs_Sources!$D$63 -> 1131.1 | G27: =Inputs_Sources!$D$64 -> 1136 | H27: =Inputs_Sources!$D$59 -> 1108.9 | I27: =IF(ISNUMBER(Inputs_Sources!$D$313),Inputs_Sources!$D$313,0) -> 0 | J27: =IFERROR(H27+I27,"n/a") -> 1108.9 | K27: =H62 -> 1070.1899 | L27: =IFERROR(K27+I27,"n/a") -> 1070.1899 | M27: =Inputs_Sources!$D$65 -> 2522.2 | N27: =Inputs_Sources!$D$66 -> n/a | O27: =IFERROR(J27/D27,"n/a") -> 0.17059738 | P27: =IFERROR(M27/D27,"n/a") -> 0.3880248 | Q27: =IFERROR(F13/Inputs_Sources!$D$67,"n/a") -> 25.8706 | R27: =IFERROR(F13/Inputs_Sources!$D$68,"n/a") -> 24.849952
A28: Yamazaki Baking Co., Ltd. | B28: =Inputs_Sources!$D$78 -> 8224.6 | C28: =Inputs_Sources!$D$79 -> 8773.2 | D28: =Inputs_Sources!$D$77 -> 8669.9 | E28: =K63 -> 8746.3529 | F28: =Inputs_Sources!$D$80 -> 630.3 | G28: =Inputs_Sources!$D$81 -> 712 | H28: =Inputs_Sources!$D$76 -> 706.7 | I28: 0 | J28: =IFERROR(H28+I28,"n/a") -> 706.7 | K28: =H63 -> 732.7663 | L28: =IFERROR(K28+I28,"n/a") -> 732.7663 | M28: =Inputs_Sources!$D$82 -> 2834.9 | N28: =Inputs_Sources!$D$83 -> 113.4 | O28: =IFERROR(J28/D28,"n/a") -> 0.081511897 | P28: =IFERROR(M28/D28,"n/a") -> 0.32698186 | Q28: =IFERROR(F14/Inputs_Sources!$D$84,"n/a") -> 215.1071 | R28: =IFERROR(F14/Inputs_Sources!$D$85,"n/a") -> 226.60333
A29: ARYZTA AG | B29: =Inputs_Sources!$D$95 -> 2374.1 | C29: =Inputs_Sources!$D$96 -> 2513.7 | D29: =Inputs_Sources!$D$94 -> 2567.4 | E29: =K64 -> 2569.3718 | F29: =Inputs_Sources!$D$97 -> 295.3 | G29: =Inputs_Sources!$D$98 -> 287.4 | H29: =Inputs_Sources!$D$93 -> 252.4 | I29: =IF(ISNUMBER(Inputs_Sources!$D$317),Inputs_Sources!$D$317,0) -> 0 | J29: =IFERROR(H29+I29,"n/a") -> 252.4 | K29: =H64 -> 361.72247 | L29: =IFERROR(K29+I29,"n/a") -> 361.72247 | M29: =Inputs_Sources!$D$99 -> 514.8 | N29: =Inputs_Sources!$D$100 -> 138.1 | O29: =IFERROR(J29/D29,"n/a") -> 0.098309574 | P29: =IFERROR(M29/D29,"n/a") -> 0.20051414 | Q29: =IFERROR(F15/Inputs_Sources!$D$101,"n/a") -> 4.813434 | R29: =IFERROR(F15/Inputs_Sources!$D$102,"n/a") -> 5.4545129
A30: The J. M. Smucker Company | B30: =Inputs_Sources!$D$112 -> 8178.7 | C30: =Inputs_Sources!$D$113 -> 8726.1 | D30: =Inputs_Sources!$D$111 -> 9156.9 | E30: =K65 -> 8979.6414 | F30: =Inputs_Sources!$D$114 -> 1874.1 | G30: =Inputs_Sources!$D$115 -> 2156.2 | H30: =Inputs_Sources!$D$110 -> 2263.9 | I30: =IF(ISNUMBER(Inputs_Sources!$D$294),Inputs_Sources!$D$294,0) -> 46.9 | J30: =IFERROR(H30+I30,"n/a") -> 2310.8 | K30: =H65 -> 2178.5844 | L30: =IFERROR(K30+I30,"n/a") -> 2225.4844 | M30: =Inputs_Sources!$D$116 -> 3475.1 | N30: =Inputs_Sources!$D$117 -> 1464.3 | O30: =IFERROR(J30/D30,"n/a") -> 0.25235615 | P30: =IFERROR(M30/D30,"n/a") -> 0.37950616 | Q30: =IFERROR(F16/Inputs_Sources!$D$118,"n/a") -> 2.173936 | R30: =IFERROR(F16/Inputs_Sources!$D$119,"n/a") -> 10.115704
A31: The Campbell's Company | B31: =Inputs_Sources!$D$129 -> 9636 | C31: =Inputs_Sources!$D$130 -> 10253 | D31: =Inputs_Sources!$D$128 -> 9744 | E31: =K66 -> 9491.011 | F31: =Inputs_Sources!$D$131 -> 1783 | G31: =Inputs_Sources!$D$132 -> 1888 | H31: =Inputs_Sources!$D$127 -> 1620 | I31: =IF(ISNUMBER(Inputs_Sources!$D$299),Inputs_Sources!$D$299,0) -> 114 | J31: =IFERROR(H31+I31,"n/a") -> 1734 | K31: =H66 -> 1475.9425 | L31: =IFERROR(K31+I31,"n/a") -> 1589.9425 | M31: =Inputs_Sources!$D$133 -> 2781 | N31: =Inputs_Sources!$D$134 -> 634.5 | O31: =IFERROR(J31/D31,"n/a") -> 0.17795567 | P31: =IFERROR(M31/D31,"n/a") -> 0.2854064 | Q31: =IFERROR(F17/Inputs_Sources!$D$135,"n/a") -> 1.315171 | R31: =IFERROR(F17/Inputs_Sources!$D$136,"n/a") -> 1.6955831
A32: Mondelez International, Inc. | B32: =Inputs_Sources!$D$146 -> 36441 | C32: =Inputs_Sources!$D$147 -> 38537 | D32: =Inputs_Sources!$D$145 -> 39675 | E32: =K67 -> 40994.158 | F32: =Inputs_Sources!$D$148 -> 7740 | G32: =Inputs_Sources!$D$149 -> 4990 | H32: =Inputs_Sources!$D$144 -> 6080 | I32: =IF(ISNUMBER(Inputs_Sources!$D$304),Inputs_Sources!$D$304,0) -> 246 | J32: =IFERROR(H32+I32,"n/a") -> 6326 | K32: =H67 -> 7153.234 | L32: =IFERROR(K32+I32,"n/a") -> 7399.234 | M32: =Inputs_Sources!$D$150 -> 12357 | N32: =Inputs_Sources!$D$151 -> 2252.4 | O32: =IFERROR(J32/D32,"n/a") -> 0.15944549 | P32: =IFERROR(M32/D32,"n/a") -> 0.31145558 | Q32: =IFERROR(F18/Inputs_Sources!$D$152,"n/a") -> 2.7666825 | R32: =IFERROR(F18/Inputs_Sources!$D$153,"n/a") -> 3.2229131
A33: Arca Continental, S.A.B. de C.V. | B33: =Inputs_Sources!$D$163 -> 13149.5 | C33: =Inputs_Sources!$D$164 -> 13058.3 | D33: =Inputs_Sources!$D$162 -> 13945.2 | E33: =K68 -> 14591.724 | F33: =Inputs_Sources!$D$165 -> 2599 | G33: =Inputs_Sources!$D$166 -> 2540.6 | H33: =Inputs_Sources!$D$161 -> 2707 | I33: =IF(ISNUMBER(Inputs_Sources!$D$321),Inputs_Sources!$D$321,0) -> 0 | J33: =IFERROR(H33+I33,"n/a") -> 2707 | K33: =H68 -> 2990.246 | L33: =IFERROR(K33+I33,"n/a") -> 2990.246 | M33: =Inputs_Sources!$D$167 -> 6537.9 | N33: =Inputs_Sources!$D$168 -> 763.6 | O33: =IFERROR(J33/D33,"n/a") -> 0.19411697 | P33: =IFERROR(M33/D33,"n/a") -> 0.46882798 | Q33: =IFERROR(F19/Inputs_Sources!$D$169,"n/a") -> 11.205772 | R33: =IFERROR(F19/Inputs_Sources!$D$170,"n/a") -> 12.706667
A34: PepsiCo, Inc. | B34: =Inputs_Sources!$D$180 -> 91854 | C34: =Inputs_Sources!$D$181 -> 93925 | D34: =Inputs_Sources!$D$179 -> 98241 | E34: =K69 -> 101251.48 | F34: =Inputs_Sources!$D$182 -> 17842 | G34: =Inputs_Sources!$D$183 -> 18174 | H34: =Inputs_Sources!$D$178 -> 19171 | I34: =IF(ISNUMBER(Inputs_Sources!$D$309),Inputs_Sources!$D$309,0) -> 880 | J34: =IFERROR(H34+I34,"n/a") -> 20051 | K34: =H69 -> 19473.899 | L34: =IFERROR(K34+I34,"n/a") -> 20353.899 | M34: =Inputs_Sources!$D$184 -> 53371 | N34: =Inputs_Sources!$D$185 -> 9044.3 | O34: =IFERROR(J34/D34,"n/a") -> 0.20410012 | P34: =IFERROR(M34/D34,"n/a") -> 0.54326605 | Q34: =IFERROR(F20/Inputs_Sources!$D$186,"n/a") -> 8.1426625 | R34: =IFERROR(F20/Inputs_Sources!$D$187,"n/a") -> 8.4677398
A37: C. Valuation (EV on the claim basis; IFRS 16-equivalent EBITDA; medians over eligible peers)
A38: Company | B38: EV/EBITDA LTM (x) | C38: EV/EBITDA NTM (x) | D38: EV/Sales LTM (x) | E38: P/E LTM (x) | F38: P/E NTM (x) | G38: FCF yield LTM (levered, %) | H38: Net debt / EBITDA LTM (x, claim basis) | I38: EBITDA margin LTM (%) | J38: CIQ tool EV/EBITDA LTM (audit) | K38: CIQ tool EV/EBITDA NTM (audit) | L38: CIQ tool P/E LTM (audit) | M38: CIQ tool P/E NTM (audit) | N38: Notes
A39: Grupo Bimbo (subject) | B39: =IFERROR(O11/J25,"n/a") -> 6.9413671 | C39: =IFERROR(O11/L25,"n/a") -> 6.5757854 | D39: =IFERROR(O11/D25,"n/a") -> 1.0034126 | E39: =IFERROR(F11/Q25,"n/a") -> 18.456693 | F39: =IFERROR(F11/R25,"n/a") -> 17.806509 | G39: =IFERROR(N25/I11,"n/a") -> 0.10105385 | H39: =IFERROR(N11/J25,"n/a") -> 2.8099608 | I39: =O25 -> 0.14455547 | J39: n/a | K39: n/a | L39: n/a | M39: n/a | N39: Bimbo on the same claim basis (block D memo gives the model-basis EBIT + D&A multiple)
A40: Flowers Foods, Inc. | B40: =IFERROR(O12/J26,"n/a") -> 5.6094445 | C40: =IFERROR(O12/L26,"n/a") -> 6.147272 | D40: =IFERROR(O12/D26,"n/a") -> 0.62142001 | E40: =Inputs_Sources!$D$50 -> 23.45 | F40: =Inputs_Sources!$D$51 -> 8.93 | G40: =IFERROR(N26/I12,"n/a") -> 0.2303774 | H40: =IFERROR(N12/J26,"n/a") -> 3.3704954 | I40: =O26 -> 0.11078103 | J40: =Inputs_Sources!$D$52 -> 5.15 | K40: =Inputs_Sources!$D$53 -> 7.55 | L40: =Inputs_Sources!$D$50 -> 23.45 | M40: =Inputs_Sources!$D$51 -> 8.93 | N40: CIQ tool values are audit only; EV-based multiples use the claim-basis EV
A41: Gruma, S.A.B. de C.V. | B41: =IFERROR(O13/J27,"n/a") -> 5.4417222 | C41: =IFERROR(O13/L27,"n/a") -> 5.6385558 | D41: =IFERROR(O13/D27,"n/a") -> 0.92834353 | E41: =Inputs_Sources!$D$67 -> 9.3550208 | F41: =Inputs_Sources!$D$68 -> 9.7392544 | G41: =IFERROR(N27/I13,"n/a") -> n/a | H41: =IFERROR(N13/J27,"n/a") -> 1.4708269 | I41: =O27 -> 0.17059738 | J41: =Inputs_Sources!$D$69 -> n/a | K41: =Inputs_Sources!$D$70 -> n/a | L41: =Inputs_Sources!$D$67 -> 9.3550208 | M41: =Inputs_Sources!$D$68 -> 9.7392544 | N41: CIQ tool values are audit only; EV-based multiples use the claim-basis EV
A42: Yamazaki Baking Co., Ltd. | B42: =IFERROR(O14/J28,"n/a") -> 6.0597144 | C42: =IFERROR(O14/L28,"n/a") -> 5.8441554 | D42: =IFERROR(O14/D28,"n/a") -> 0.49393882 | E42: =Inputs_Sources!$D$84 -> 17.74 | F42: =Inputs_Sources!$D$85 -> 16.84 | G42: =IFERROR(N28/I14,"n/a") -> 0.023844067 | H42: =IFERROR(N14/J28,"n/a") -> -0.67001557 | I42: =O28 -> 0.081511897 | J42: =Inputs_Sources!$D$86 -> 6.58 | K42: =Inputs_Sources!$D$87 -> 6.37 | L42: =Inputs_Sources!$D$84 -> 17.74 | M42: =Inputs_Sources!$D$85 -> 16.84 | N42: CIQ tool values are audit only; EV-based multiples use the claim-basis EV
A43: ARYZTA AG | B43: =IFERROR(O15/J29,"n/a") -> 8.3332366 | C43: =IFERROR(O15/L29,"n/a") -> 5.8147036 | D43: =IFERROR(O15/D29,"n/a") -> 0.81923694 | E43: =Inputs_Sources!$D$101 -> 10.21 | F43: =Inputs_Sources!$D$102 -> 9.01 | G43: =IFERROR(N29/I15,"n/a") -> 0.11330817 | H43: =IFERROR(N15/J29,"n/a") -> 3.5043935 | I43: =O29 -> 0.098309574 | J43: =Inputs_Sources!$D$103 -> 7.31 | K43: =Inputs_Sources!$D$104 -> 5.94 | L43: =Inputs_Sources!$D$101 -> 10.21 | M43: =Inputs_Sources!$D$102 -> 9.01 | N43: CIQ tool values are audit only; EV-based multiples use the claim-basis EV
A44: The J. M. Smucker Company | B44: =IFERROR(O16/J30,"n/a") -> 8.8754977 | C44: =IFERROR(O16/L30,"n/a") -> 9.2157465 | D44: =IFERROR(O16/D30,"n/a") -> 2.2397864 | E44: =Inputs_Sources!$D$118 -> 58.63 | F44: =Inputs_Sources!$D$119 -> 12.6 | G44: =IFERROR(N30/I16,"n/a") -> 0.10757025 | H44: =IFERROR(N16/J30,"n/a") -> 2.9846806 | I44: =O30 -> 0.25235615 | J44: =Inputs_Sources!$D$120 -> 8.57 | K44: =Inputs_Sources!$D$121 -> 9.86 | L44: =Inputs_Sources!$D$118 -> 58.63 | M44: =Inputs_Sources!$D$119 -> 12.6 | N44: CIQ tool values are audit only; EV-based multiples use the claim-basis EV
A45: The Campbell's Company | B45: =IFERROR(O17/J31,"n/a") -> 7.6631488 | C45: =IFERROR(O17/L31,"n/a") -> 8.3574722 | D45: =IFERROR(O17/D31,"n/a") -> 1.3637007 | E45: =Inputs_Sources!$D$135 -> 15.11 | F45: =Inputs_Sources!$D$136 -> 11.72 | G45: =IFERROR(N31/I17,"n/a") -> 0.10707234 | H45: =IFERROR(N17/J31,"n/a") -> 4.2456747 | I45: =O31 -> 0.17795567 | J45: =Inputs_Sources!$D$137 -> 6.47 | K45: =Inputs_Sources!$D$138 -> 9.07 | L45: =Inputs_Sources!$D$135 -> 15.11 | M45: =Inputs_Sources!$D$136 -> 11.72 | N45: CIQ tool values are audit only; EV-based multiples use the claim-basis EV
A46: Mondelez International, Inc. | B46: =IFERROR(O18/J32,"n/a") -> 16.144293 | C46: =IFERROR(O18/L32,"n/a") -> 13.802618 | D46: =IFERROR(O18/D32,"n/a") -> 2.5741348 | E46: =Inputs_Sources!$D$152 -> 23.1 | F46: =Inputs_Sources!$D$153 -> 19.83 | G46: =IFERROR(N32/I18,"n/a") -> 0.027613499 | H46: =IFERROR(N18/J32,"n/a") -> 3.250079 | I46: =O32 -> 0.15944549 | J46: =Inputs_Sources!$D$154 -> 14.48 | K46: =Inputs_Sources!$D$155 -> 14.13 | L46: =Inputs_Sources!$D$152 -> 23.1 | M46: =Inputs_Sources!$D$153 -> 19.83 | N46: CIQ tool values are audit only; EV-based multiples use the claim-basis EV
A47: Arca Continental, S.A.B. de C.V. | B47: =IFERROR(O19/J33,"n/a") -> 7.8537991 | C47: =IFERROR(O19/L33,"n/a") -> 7.1098612 | D47: =IFERROR(O19/D33,"n/a") -> 1.5245557 | E47: =Inputs_Sources!$D$169 -> 18.71 | F47: =Inputs_Sources!$D$170 -> 16.5 | G47: =IFERROR(N33/I19,"n/a") -> 0.03967818 | H47: =IFERROR(N19/J33,"n/a") -> 0.74451422 | I47: =O33 -> 0.19411697 | J47: =Inputs_Sources!$D$171 -> 8.47 | K47: =Inputs_Sources!$D$172 -> 7.87 | L47: =Inputs_Sources!$D$169 -> 18.71 | M47: =Inputs_Sources!$D$170 -> 16.5 | N47: CIQ tool values are audit only; EV-based multiples use the claim-basis EV
A48: PepsiCo, Inc. | B48: =IFERROR(O20/J34,"n/a") -> 11.193831 | C48: =IFERROR(O20/L34,"n/a") -> 11.027248 | D48: =IFERROR(O20/D34,"n/a") -> 2.2846622 | E48: =Inputs_Sources!$D$186 -> 16.15 | F48: =Inputs_Sources!$D$187 -> 15.53 | G48: =IFERROR(N34/I20,"n/a") -> 0.050470283 | H48: =IFERROR(N20/J34,"n/a") -> 2.2565957 | I48: =O34 -> 0.20410012 | J48: =Inputs_Sources!$D$188 -> 10.35 | K48: =Inputs_Sources!$D$189 -> 11.24 | L48: =Inputs_Sources!$D$186 -> 16.15 | M48: =Inputs_Sources!$D$187 -> 15.53 | N48: CIQ tool values are audit only; EV-based multiples use the claim-basis EV
A49: Statistics (valuation metrics)
A50: Core median (eligible peers) | B50: =IFERROR(_xlfn.AGGREGATE(16,6,B40:B48/(($C$12:$C$20="Core")*($P$12:$P$20="yes")*ISNUMBER(B40:B48)),0.5),"n/a") -> 5.5255833 | C50: =IFERROR(_xlfn.AGGREGATE(16,6,C40:C48/(($C$12:$C$20="Core")*($P$12:$P$20="yes")*ISNUMBER(C40:C48)),0.5),"n/a") -> 5.8929139 | D50: =IFERROR(_xlfn.AGGREGATE(16,6,D40:D48/(($C$12:$C$20="Core")*($P$12:$P$20="yes")*ISNUMBER(D40:D48)),0.5),"n/a") -> 0.77488177 | E50: =IFERROR(_xlfn.AGGREGATE(16,6,E40:E48/(($C$12:$C$20="Core")*($Q$12:$Q$20="yes")*ISNUMBER(E40:E48)),0.5),"n/a") -> 16.40251 | F50: =IFERROR(_xlfn.AGGREGATE(16,6,F40:F48/(($C$12:$C$20="Core")*($Q$12:$Q$20="yes")*ISNUMBER(F40:F48)),0.5),"n/a") -> 9.3346272 | G50: =IFERROR(_xlfn.AGGREGATE(16,6,G40:G48/(($C$12:$C$20="Core")*($P$12:$P$20="yes")*ISNUMBER(G40:G48)),0.5),"n/a") -> 0.2303774 | H50: =IFERROR(_xlfn.AGGREGATE(16,6,H40:H48/(($C$12:$C$20="Core")*($P$12:$P$20="yes")*ISNUMBER(H40:H48)),0.5),"n/a") -> 2.4206612 | I50: =IFERROR(_xlfn.AGGREGATE(16,6,I40:I48/(($C$12:$C$20="Core")*($P$12:$P$20="yes")*ISNUMBER(I40:I48)),0.5),"n/a") -> 0.1406892
A51: Core mean (eligible peers) | B51: =IFERROR(SUMPRODUCT(($C$12:$C$20="Core")*($P$12:$P$20="yes")*ISNUMBER(B40:B48),B40:B48)/SUMPRODUCT(($C$12:$C$20="Core")*($P$12:$P$20="yes")*ISNUMBER(B40:B48)),"n/a") -> 5.5255833 | C51: =IFERROR(SUMPRODUCT(($C$12:$C$20="Core")*($P$12:$P$20="yes")*ISNUMBER(C40:C48),C40:C48)/SUMPRODUCT(($C$12:$C$20="Core")*($P$12:$P$20="yes")*ISNUMBER(C40:C48)),"n/a") -> 5.8929139 | D51: =IFERROR(SUMPRODUCT(($C$12:$C$20="Core")*($P$12:$P$20="yes")*ISNUMBER(D40:D48),D40:D48)/SUMPRODUCT(($C$12:$C$20="Core")*($P$12:$P$20="yes")*ISNUMBER(D40:D48)),"n/a") -> 0.77488177 | E51: =IFERROR(SUMPRODUCT(($C$12:$C$20="Core")*($Q$12:$Q$20="yes")*ISNUMBER(E40:E48),E40:E48)/SUMPRODUCT(($C$12:$C$20="Core")*($Q$12:$Q$20="yes")*ISNUMBER(E40:E48)),"n/a") -> 16.40251 | F51: =IFERROR(SUMPRODUCT(($C$12:$C$20="Core")*($Q$12:$Q$20="yes")*ISNUMBER(F40:F48),F40:F48)/SUMPRODUCT(($C$12:$C$20="Core")*($Q$12:$Q$20="yes")*ISNUMBER(F40:F48)),"n/a") -> 9.3346272 | G51: =IFERROR(SUMPRODUCT(($C$12:$C$20="Core")*($P$12:$P$20="yes")*ISNUMBER(G40:G48),G40:G48)/SUMPRODUCT(($C$12:$C$20="Core")*($P$12:$P$20="yes")*ISNUMBER(G40:G48)),"n/a") -> 0.2303774 | H51: =IFERROR(SUMPRODUCT(($C$12:$C$20="Core")*($P$12:$P$20="yes")*ISNUMBER(H40:H48),H40:H48)/SUMPRODUCT(($C$12:$C$20="Core")*($P$12:$P$20="yes")*ISNUMBER(H40:H48)),"n/a") -> 2.4206612 | I51: =IFERROR(SUMPRODUCT(($C$12:$C$20="Core")*($P$12:$P$20="yes")*ISNUMBER(I40:I48),I40:I48)/SUMPRODUCT(($C$12:$C$20="Core")*($P$12:$P$20="yes")*ISNUMBER(I40:I48)),"n/a") -> 0.1406892
A52: Core: number of eligible peers | B52: =SUMPRODUCT(($C$12:$C$20="Core")*($P$12:$P$20="yes")*ISNUMBER(B40:B48)) -> 2 | C52: =SUMPRODUCT(($C$12:$C$20="Core")*($P$12:$P$20="yes")*ISNUMBER(C40:C48)) -> 2 | D52: =SUMPRODUCT(($C$12:$C$20="Core")*($P$12:$P$20="yes")*ISNUMBER(D40:D48)) -> 2 | E52: =SUMPRODUCT(($C$12:$C$20="Core")*($Q$12:$Q$20="yes")*ISNUMBER(E40:E48)) -> 2 | F52: =SUMPRODUCT(($C$12:$C$20="Core")*($Q$12:$Q$20="yes")*ISNUMBER(F40:F48)) -> 2 | G52: =SUMPRODUCT(($C$12:$C$20="Core")*($P$12:$P$20="yes")*ISNUMBER(G40:G48)) -> 1 | H52: =SUMPRODUCT(($C$12:$C$20="Core")*($P$12:$P$20="yes")*ISNUMBER(H40:H48)) -> 2 | I52: =SUMPRODUCT(($C$12:$C$20="Core")*($P$12:$P$20="yes")*ISNUMBER(I40:I48)) -> 2
A53: All-peer median (eligible peers) | B53: =IFERROR(_xlfn.AGGREGATE(16,6,B40:B48/(($P$12:$P$20="yes")*ISNUMBER(B40:B48)),0.5),"n/a") -> 8.2693232 | C53: =IFERROR(_xlfn.AGGREGATE(16,6,C40:C48/(($P$12:$P$20="yes")*ISNUMBER(C40:C48)),0.5),"n/a") -> 8.7866094 | D53: =IFERROR(_xlfn.AGGREGATE(16,6,D40:D48/(($P$12:$P$20="yes")*ISNUMBER(D40:D48)),0.5),"n/a") -> 1.8017436 | E53: =IFERROR(_xlfn.AGGREGATE(16,6,E40:E48/(($Q$12:$Q$20="yes")*ISNUMBER(E40:E48)),0.5),"n/a") -> 16.15 | F53: =IFERROR(_xlfn.AGGREGATE(16,6,F40:F48/(($Q$12:$Q$20="yes")*ISNUMBER(F40:F48)),0.5),"n/a") -> 11.72 | G53: =IFERROR(_xlfn.AGGREGATE(16,6,G40:G48/(($P$12:$P$20="yes")*ISNUMBER(G40:G48)),0.5),"n/a") -> 0.10707234 | H53: =IFERROR(_xlfn.AGGREGATE(16,6,H40:H48/(($P$12:$P$20="yes")*ISNUMBER(H40:H48)),0.5),"n/a") -> 3.1173798 | I53: =IFERROR(_xlfn.AGGREGATE(16,6,I40:I48/(($P$12:$P$20="yes")*ISNUMBER(I40:I48)),0.5),"n/a") -> 0.17427652
A54: All-peer mean (eligible peers) | B54: =IFERROR(SUMPRODUCT(($P$12:$P$20="yes")*ISNUMBER(B40:B48),B40:B48)/SUMPRODUCT(($P$12:$P$20="yes")*ISNUMBER(B40:B48)),"n/a") -> 9.1546562 | C54: =IFERROR(SUMPRODUCT(($P$12:$P$20="yes")*ISNUMBER(C40:C48),C40:C48)/SUMPRODUCT(($P$12:$P$20="yes")*ISNUMBER(C40:C48)),"n/a") -> 9.0314855 | D54: =IFERROR(SUMPRODUCT(($P$12:$P$20="yes")*ISNUMBER(D40:D48),D40:D48)/SUMPRODUCT(($P$12:$P$20="yes")*ISNUMBER(D40:D48)),"n/a") -> 1.6686746 | E54: =IFERROR(SUMPRODUCT(($Q$12:$Q$20="yes")*ISNUMBER(E40:E48),E40:E48)/SUMPRODUCT(($Q$12:$Q$20="yes")*ISNUMBER(E40:E48)),"n/a") -> 17.433004 | F54: =IFERROR(SUMPRODUCT(($Q$12:$Q$20="yes")*ISNUMBER(F40:F48),F40:F48)/SUMPRODUCT(($Q$12:$Q$20="yes")*ISNUMBER(F40:F48)),"n/a") -> 13.149851 | G54: =IFERROR(SUMPRODUCT(($P$12:$P$20="yes")*ISNUMBER(G40:G48),G40:G48)/SUMPRODUCT(($P$12:$P$20="yes")*ISNUMBER(G40:G48)),"n/a") -> 0.10462076 | H54: =IFERROR(SUMPRODUCT(($P$12:$P$20="yes")*ISNUMBER(H40:H48),H40:H48)/SUMPRODUCT(($P$12:$P$20="yes")*ISNUMBER(H40:H48)),"n/a") -> 2.9297254 | I54: =IFERROR(SUMPRODUCT(($P$12:$P$20="yes")*ISNUMBER(I40:I48),I40:I48)/SUMPRODUCT(($P$12:$P$20="yes")*ISNUMBER(I40:I48)),"n/a") -> 0.17920597
A55: All-peer: number of eligible peers | B55: =SUMPRODUCT(($P$12:$P$20="yes")*ISNUMBER(B40:B48)) -> 6 | C55: =SUMPRODUCT(($P$12:$P$20="yes")*ISNUMBER(C40:C48)) -> 6 | D55: =SUMPRODUCT(($P$12:$P$20="yes")*ISNUMBER(D40:D48)) -> 6 | E55: =SUMPRODUCT(($Q$12:$Q$20="yes")*ISNUMBER(E40:E48)) -> 5 | F55: =SUMPRODUCT(($Q$12:$Q$20="yes")*ISNUMBER(F40:F48)) -> 5 | G55: =SUMPRODUCT(($P$12:$P$20="yes")*ISNUMBER(G40:G48)) -> 5 | H55: =SUMPRODUCT(($P$12:$P$20="yes")*ISNUMBER(H40:H48)) -> 6 | I55: =SUMPRODUCT(($P$12:$P$20="yes")*ISNUMBER(I40:I48)) -> 6
A58: D. Calendarisation to NTM from 16-Oct-2026 (local currency; weights from fiscal year-end dates)
A59: Company | B59: FY1 year end (contains pricing date) | C59: Days from pricing date to FY1 end (incl.) | D59: Weight FY1 | E59: Weight FY2 | F59: EBITDA FY1 (local m) | G59: EBITDA FY2 (local m) | H59: EBITDA NTM (local m) | I59: Revenue FY1 (local m) | J59: Revenue FY2 (local m) | K59: Revenue NTM (local m) | L59: EPS FY1 (local) | M59: EPS FY2 (local) | N59: EPS NTM (local) | O59: Notes
A60: Grupo Bimbo (MXN) | B60: =Inputs_Sources!$D$327 -> 46387 | C60: =B60-Inputs_Sources!$D$6+1 -> 77 | D60: =MIN(1,MAX(0,C60/365)) -> 0.2109589 | E60: =1-D60 -> 0.7890411 | F60: =Detail_TearSheet!$H$19 -> 62117 | G60: =Detail_TearSheet!$I$19 -> 64891 | H60: =IFERROR(D60*F60+E60*G60,"n/a") -> 64305.8 | I60: =Detail_TearSheet!$H$7 -> 426274.7 | J60: =Detail_TearSheet!$I$7 -> 445288 | K60: =IFERROR(D60*I60+E60*J60,"n/a") -> 441276.98 | L60: =Detail_TearSheet!$H$24 -> 3.07 | M60: =Detail_TearSheet!$I$24 -> 3.35 | N60: =IFERROR(D60*L60+E60*M60,"n/a") -> 3.2909315 | O60: FY1 = FY2026E, FY2 = FY2027E (CIQ consensus mean, MXN, 20-Sep-2026)
A61: Flowers Foods, Inc. | B61: =Inputs_Sources!$D$242 -> 46389 | C61: =B61-Inputs_Sources!$D$6+1 -> 79 | D61: =MIN(1,MAX(0,C61/365)) -> 0.21643836 | E61: =1-D61 -> 0.78356164 | F61: =Inputs_Sources!$D$243 -> 458.6 | G61: =Inputs_Sources!$D$245 -> 430.1 | H61: =IFERROR(D61*F61+E61*G61,"n/a") -> 436.26849 | I61: =Inputs_Sources!$D$244 -> 5075.8 | J61: =Inputs_Sources!$D$246 -> 5058.3 | K61: =IFERROR(D61*I61+E61*J61,"n/a") -> 5062.0877 | L61: n/a | M61: n/a | N61: n/a | O61: CIQ consensus in USD; CIQ conversion basis not stated
A62: Gruma, S.A.B. de C.V. | B62: =Inputs_Sources!$D$282 -> 46387 | C62: =B62-Inputs_Sources!$D$6+1 -> 77 | D62: =MIN(1,MAX(0,C62/365)) -> 0.2109589 | E62: =1-D62 -> 0.7890411 | F62: =Inputs_Sources!$D$283 -> 1111.37 | G62: =Inputs_Sources!$D$332 -> 1059.18 | H62: =IFERROR(D62*F62+E62*G62,"n/a") -> 1070.1899 | I62: =Inputs_Sources!$D$330 -> 6648.35 | J62: =Inputs_Sources!$D$331 -> 6444.43 | K62: =IFERROR(D62*I62+E62*J62,"n/a") -> 6487.4487 | L62: =Inputs_Sources!$D$333 -> 1.4 | M62: =Inputs_Sources!$D$334 -> 1.33 | N62: =IFERROR(D62*L62+E62*M62,"n/a") -> 1.3447671 | O62: CIQ consensus (prompt 4C, company EBITDA basis), USD as converted by Capital IQ at the query-date rate
A63: Yamazaki Baking Co., Ltd. | B63: =Inputs_Sources!$D$247 -> 46387 | C63: =B63-Inputs_Sources!$D$6+1 -> 77 | D63: =MIN(1,MAX(0,C63/365)) -> 0.2109589 | E63: =1-D63 -> 0.7890411 | F63: =Inputs_Sources!$D$248 -> 700.1 | G63: =Inputs_Sources!$D$250 -> 741.5 | H63: =IFERROR(D63*F63+E63*G63,"n/a") -> 732.7663 | I63: =Inputs_Sources!$D$249 -> 8564.4 | J63: =Inputs_Sources!$D$251 -> 8795 | K63: =IFERROR(D63*I63+E63*J63,"n/a") -> 8746.3529 | L63: n/a | M63: n/a | N63: n/a | O63: CIQ consensus in USD; CIQ conversion basis not stated
A64: ARYZTA AG | B64: =Inputs_Sources!$D$252 -> 46387 | C64: =B64-Inputs_Sources!$D$6+1 -> 77 | D64: =MIN(1,MAX(0,C64/365)) -> 0.2109589 | E64: =1-D64 -> 0.7890411 | F64: =Inputs_Sources!$D$253 -> 354.7 | G64: =Inputs_Sources!$D$255 -> 363.6 | H64: =IFERROR(D64*F64+E64*G64,"n/a") -> 361.72247 | I64: =Inputs_Sources!$D$254 -> 2594.7 | J64: =Inputs_Sources!$D$256 -> 2562.6 | K64: =IFERROR(D64*I64+E64*J64,"n/a") -> 2569.3718 | L64: n/a | M64: n/a | N64: n/a | O64: CIQ consensus in USD; CIQ conversion basis not stated
A65: The J. M. Smucker Company | B65: =Inputs_Sources!$D$257 -> 46507 | C65: =B65-Inputs_Sources!$D$6+1 -> 197 | D65: =MIN(1,MAX(0,C65/365)) -> 0.53972603 | E65: =1-D65 -> 0.46027397 | F65: =Inputs_Sources!$D$258 -> 2181.3 | G65: =Inputs_Sources!$D$260 -> 2175.4 | H65: =IFERROR(D65*F65+E65*G65,"n/a") -> 2178.5844 | I65: =Inputs_Sources!$D$259 -> 8930.3 | J65: =Inputs_Sources!$D$261 -> 9037.5 | K65: =IFERROR(D65*I65+E65*J65,"n/a") -> 8979.6414 | L65: n/a | M65: n/a | N65: n/a | O65: CIQ consensus (USD); FY1 for SJM and CPB is FY27E (FY26 closed)
A66: The Campbell's Company | B66: =Inputs_Sources!$D$262 -> 46600 | C66: =B66-Inputs_Sources!$D$6+1 -> 290 | D66: =MIN(1,MAX(0,C66/365)) -> 0.79452055 | E66: =1-D66 -> 0.20547945 | F66: =Inputs_Sources!$D$263 -> 1464.6 | G66: =Inputs_Sources!$D$265 -> 1519.8 | H66: =IFERROR(D66*F66+E66*G66,"n/a") -> 1475.9425 | I66: =Inputs_Sources!$D$264 -> 9496.6 | J66: =Inputs_Sources!$D$266 -> 9469.4 | K66: =IFERROR(D66*I66+E66*J66,"n/a") -> 9491.011 | L66: n/a | M66: n/a | N66: n/a | O66: CIQ consensus (USD); FY1 for SJM and CPB is FY27E (FY26 closed)
A67: Mondelez International, Inc. | B67: =Inputs_Sources!$D$267 -> 46387 | C67: =B67-Inputs_Sources!$D$6+1 -> 77 | D67: =MIN(1,MAX(0,C67/365)) -> 0.2109589 | E67: =1-D67 -> 0.7890411 | F67: =Inputs_Sources!$D$268 -> 6735.2 | G67: =Inputs_Sources!$D$270 -> 7265 | H67: =IFERROR(D67*F67+E67*G67,"n/a") -> 7153.234 | I67: =Inputs_Sources!$D$269 -> 40101.2 | J67: =Inputs_Sources!$D$271 -> 41232.9 | K67: =IFERROR(D67*I67+E67*J67,"n/a") -> 40994.158 | L67: n/a | M67: n/a | N67: n/a | O67: CIQ consensus in USD; CIQ conversion basis not stated
A68: Arca Continental, S.A.B. de C.V. | B68: =Inputs_Sources!$D$272 -> 46387 | C68: =B68-Inputs_Sources!$D$6+1 -> 77 | D68: =MIN(1,MAX(0,C68/365)) -> 0.2109589 | E68: =1-D68 -> 0.7890411 | F68: =Inputs_Sources!$D$273 -> 2930.2 | G68: =Inputs_Sources!$D$275 -> 3006.3 | H68: =IFERROR(D68*F68+E68*G68,"n/a") -> 2990.246 | I68: =Inputs_Sources!$D$274 -> 14453.8 | J68: =Inputs_Sources!$D$276 -> 14628.6 | K68: =IFERROR(D68*I68+E68*J68,"n/a") -> 14591.724 | L68: n/a | M68: n/a | N68: n/a | O68: CIQ consensus in USD; CIQ conversion basis not stated
A69: PepsiCo, Inc. | B69: =Inputs_Sources!$D$277 -> 46387 | C69: =B69-Inputs_Sources!$D$6+1 -> 77 | D69: =MIN(1,MAX(0,C69/365)) -> 0.2109589 | E69: =1-D69 -> 0.7890411 | F69: =Inputs_Sources!$D$278 -> 19050.5 | G69: =Inputs_Sources!$D$280 -> 19587.1 | H69: =IFERROR(D69*F69+E69*G69,"n/a") -> 19473.899 | I69: =Inputs_Sources!$D$279 -> 99300.5 | J69: =Inputs_Sources!$D$281 -> 101773.1 | K69: =IFERROR(D69*I69+E69*J69,"n/a") -> 101251.48 | L69: n/a | M69: n/a | N69: n/a | O69: CIQ consensus in USD; CIQ conversion basis not stated
A72: Memo: Grupo Bimbo on the same claim basis (MXN m unless stated)
A73: Market cap = price x shares (MXN m) | B73: =F11*G11 -> 251681.14
A74: Net debt, claim basis = financial debt + leases + NCI - cash (MXN m) | B74: =N11/H11 -> 171180
A75: Enterprise value, claim basis (MXN m) | B75: =O11/H11 -> 422861.14
A76: LTM EBITDA, company IFRS 16 Adjusted (MXN m) | B76: =J25/H11 -> 60919
A77: LTM EBITDA, model basis = operating income + D&A (MXN m; 35,666 + 24,660) | B77: =Inputs_Sources!$D$20+Inputs_Sources!$D$21 -> 60326
A78: EV/EBITDA LTM, company IFRS 16 basis (x) | B78: =IFERROR(O11/J25,"n/a") -> 6.9413671
A79: EV/EBITDA LTM, model basis EBIT + D&A (x) | B79: =IFERROR(O11/((Inputs_Sources!$D$20+Inputs_Sources!$D$21)*H11),"n/a") -> 7.0096002
A80: EV/EBITDA NTM, calendarised, company IFRS 16 basis (x) | B80: =IFERROR(O11/L25,"n/a") -> 6.5757854

Sheet Inputs_Sources
A1: Inputs and sources: every number used in PeerAnalysis and Checks
A2: Tags: sourced (filing or CIQ), guidance, assumption, calc, unverified, pending (not found: shown as n/a). Blue = hard-coded input.
A4: Key | B4: Entity | C4: Item | D4: Value | E4: Unit | F4: Currency | G4: Tag | H4: Source (document, section/metric/period, URL) | I4: As-of | J4: Note
A5: A. General
A6: pricing_date | B6: All | C6: Pricing / valuation date | D6: 46311 | E6: date | G6: sourced | H6: CIQ pricing 15/16-Oct-2026 (data/capitaliq/capiq-ai-prompt1_2026-10-16.md) | I6: 2026-10-16
A7: fx_cic_jpy | B7: All | C7: CIQ conversion JPY to USD (Yamazaki LTM figures) | D7: 0.006482 | E7: USD per JPY | F7: USD | G7: sourced | H7: data/capitaliq/capiq-ai-prompt1_2026-10-16.md Task 1A (market data, LTM balance sheet) note: TSE:2212 converted at 0.006482 USD/JPY | I7: 2026-10-16
A8: fx_cic_eur | B8: All | C8: CIQ conversion EUR to USD (Aryzta) | D8: 1.166559 | E8: USD per EUR | F8: USD | G8: sourced | H8: data/capitaliq/capiq-ai-prompt1_2026-10-16.md Task 1A (market data, LTM balance sheet) note: ARYN converted at 1.166559 USD/EUR | I8: 2026-10-16
A9: fx_cic_mxn_old | B9: All | C9: CIQ note MXN to USD (memo: implies 17.96 MXN/USD, not used) | D9: 0.05569 | E9: USD per MXN | F9: USD | G9: sourced | H9: Memo, not used. The Capital IQ AI says it converted the LTM 06/30/2026 figures at 0.055690 USD per MXN (17.957) (data/capitaliq/capiq-ai-prompt1_2026-10-16.md Task 1A; data/capitaliq/capiq-ai-model-gaps-4_2026-10-17.md). It is not the 30-Jun-2026 closing rate (17.47 per the company, 2Q26 release p.6 note 12; Capital IQ's own USD figures for Bimbo's 30-Jun debt also imply 17.47 = 189,679.4 / 10,855) nor the 16-Oct-2026 rate (18.479); probably an LTM average used for income-statement items [unverified]. | I9: 2026-10-16
A10: fx_mxn_spot | B10: All | C10: MXN per USD, spot used for all MXN market values (Bimbo display, Gruma and Arca prices) | D10: 18.479 | E10: MXN per USD | F10: MXN | G10: sourced | H10: USD/MXN close 16-Oct-2026 = 18.479 (Yahoo Finance MXN=X, last bar 2026-10-16T21:00:38Z; data/market/usdmxn_daily_2026-09-15_2026-10-16.csv). Capital IQ chart cross-check (data/capitaliq/capiq-ai-model-gaps-5_2026-10-17.md and data/capitaliq/capiq-ai-model-gaps-1_2026-10-17.md): Gruma USD 13.09 vs MXN 242.02, BIMBO A USD 3.17 vs MXN 58.60 and Arca USD 11.34 vs MXN 209.66 each imply about 18.49. Replaces the 17.46 of v1/v2, which was the rate implied in the Capital IQ consensus dashboard (wiki/Valuation/bimbo-consensus-dashboard-capiq-2026-10.md: MXN 426,275m revenue / USD 24,418.7m), not a pricing-date rate. | I10: 2026-10-17 | J10: Single spot for market values; balance-sheet and LTM figures are taken in USD from the filings or CIQ
A11: fx_bmv_disp | B11: Grupo Bimbo | C11: MXN per USD used for USD display of Bimbo | D11: =$D$10 -> 18.479 | E11: MXN per USD | F11: MXN | G11: calc | H11: Same rate as fx_mxn_spot (link) | I11: 2026-10-17 | J11: Display only: Bimbo multiples are computed in MXN and do not depend on this rate
A12: B. Grupo Bimbo market data and balance sheet (MXN m unless stated)
A13: bmv_price | B13: Grupo Bimbo | C13: Share price (BMV:BIMBO A), MXN | D13: 58.6 | E13: MXN per share | F13: MXN | G13: sourced | H13: BMV official close 16-Oct-2026 = PPP 58.60 (last trade 58.62), bmv.com.mx/es/emisoras/estadisticas/BIMBO-5163 | I13: 2026-10-16 | J13: Confirm against the BMV close before the report; MXN 1 per share = about 0.07x on EV/EBITDA
A14: bmv_shares | B14: Grupo Bimbo | C14: Shares outstanding (m) | D14: 4294.9 | E14: m shares | F14: shares | G14: sourced | H14: BMV notice 29-Jul-2026: 4,294,943,715 shares (valuation/inputs/spg_inputs.yaml shares_out); 4,294.9m used here (market cap -0.001% vs full precision). CIQ balance sheet 2026 FQ2 shows 4,296.3m (filing 2026-07-24) | I14: 2026-07-24 | J14: Difference to CIQ 2Q26 is 0.03%; dashboard register 4,304.7m is 0.2% higher
A15: bmv_td | B15: Grupo Bimbo | C15: Total debt incl. IFRS 16 leases, 30-Jun-2026 | D15: 189679.4 | E15: MXN m | F15: MXN | G15: sourced | H15: data/capitaliq/balance_sheet.csv 'Total Debt' 2026 FQ2 (= long-term debt 150,019.5 + current portion 6,299.0 + leases 33,361) | I15: 2026-06-30 | J15: CIQ basis; company ex-IFRS 16 total debt is 153,663 (wiki/Valuation/bimbo-capital-structure-and-debt.md)
A16: bmv_cash | B16: Grupo Bimbo | C16: Cash, 30-Jun-2026 (claim basis) | D16: 16563 | E16: MXN m | F16: MXN | G16: sourced | H16: data/capitaliq/balance_sheet.csv 'Cash & Short-term Investments' 2026 FQ2 (company ~16.6bn; coordinator value 16,563) | I16: 2026-06-30
A17: bmv_nci | B17: Grupo Bimbo | C17: Non-controlling interest at book, 30-Jun-2026 (claim basis) | D17: 722 | E17: MXN m | F17: MXN | G17: sourced | H17: Company 2Q26 p.8: NCI 722 (CIQ 721.7); coordinator value 722. Book value understates the economic claim if IO profit is attributed to NCI (see Checks) | I17: 2026-06-30
A18: bmv_fin_debt | B18: Grupo Bimbo | C18: Financial debt excluding leases, 30-Jun-2026 (claim basis) | D18: 153660 | E18: MXN m | F18: MXN | G18: sourced | H18: Company total debt 153,660 (coordinator; wiki/Valuation/bimbo-capital-structure-and-debt.md: 153,663 at Jun-26) | I18: 2026-06-30 | J18: CIQ financial debt is 156,319 (LTD 150,019.5 + CPLTD 6,299.0); the 2,659 difference is not added
A19: bmv_leases | B19: Grupo Bimbo | C19: IFRS 16 lease liabilities, 30-Jun-2026 (claim basis) | D19: 33361 | E19: MXN m | F19: MXN | G19: sourced | H19: data/capitaliq/balance_sheet.csv 'Current Portion of Leases' 7,112.9 + 'Long-term Leases' 26,248.0 (2026 FQ2) | I19: 2026-06-30
A20: bmv_ltm_ebit | B20: Grupo Bimbo | C20: Operating income, LTM to 30-Jun-2026 (model basis) | D20: 35666 | E20: MXN m | F20: MXN | G20: sourced | H20: BMV Jun-26 p.27 via wiki/Financials/bimbo-quarterly-trend-4q21-2q26.md line 62 | I20: 2026-06-30
A21: bmv_ltm_da | B21: Grupo Bimbo | C21: D&A, LTM to 30-Jun-2026 (model basis; includes IFRS 16 right-of-use depreciation) | D21: 24660 | E21: MXN m | F21: MXN | G21: sourced | H21: BMV Jun-26 p.27 via wiki/Financials/bimbo-quarterly-trend-4q21-2q26.md line 62 | I21: 2026-06-30
A22: bmv_lease_cur | B22: Grupo Bimbo | C22: IFRS 16 lease liabilities, current (memo) | D22: 7112.9 | E22: MXN m | F22: MXN | G22: sourced | H22: data/capitaliq/balance_sheet.csv 'Current Portion of Leases' 2026 FQ2 | I22: 2026-06-30
A23: bmv_lease_nc | B23: Grupo Bimbo | C23: IFRS 16 lease liabilities, non-current (memo) | D23: 26248 | E23: MXN m | F23: MXN | G23: sourced | H23: data/capitaliq/balance_sheet.csv 'Long-term Leases' 2026 FQ2 | I23: 2026-06-30
A24: bmv_netdebt_co | B24: Grupo Bimbo | C24: Company net debt ex-IFRS 16, 30-Jun-2026 (memo) | D24: 137100 | E24: MXN m | F24: MXN | G24: sourced | H24: 2Q26 release p.6 via wiki/Valuation/bimbo-capital-structure-and-debt.md (137.1bn; excludes leases) | I24: 2026-06-30 | J24: Not used for EV: excludes IFRS 16 leases while EBITDA is IFRS 16
A25: bmv_ebitda_3Q25 | B25: Grupo Bimbo | C25: Adj. EBITDA (IFRS 16), quarter 3Q25 | D25: 15776 | E25: MXN m | F25: MXN | G25: sourced | H25: Company quarterly release via wiki/Financials/bimbo-quarterly-trend-4q21-2q26.md; wiki/Financials/bimbo-balance-sheet-and-leverage.md line 83 | I25: 2026-06-30
A26: bmv_ebitda_4Q25 | B26: Grupo Bimbo | C26: Adj. EBITDA (IFRS 16), quarter 4Q25 | D26: 15994 | E26: MXN m | F26: MXN | G26: sourced | H26: Company quarterly release via wiki/Financials/bimbo-quarterly-trend-4q21-2q26.md; wiki/Financials/bimbo-balance-sheet-and-leverage.md line 83 | I26: 2026-06-30
A27: bmv_ebitda_1Q26 | B27: Grupo Bimbo | C27: Adj. EBITDA (IFRS 16), quarter 1Q26 | D27: 14036 | E27: MXN m | F27: MXN | G27: sourced | H27: Company quarterly release via wiki/Financials/bimbo-quarterly-trend-4q21-2q26.md; wiki/Financials/bimbo-balance-sheet-and-leverage.md line 83 | I27: 2026-06-30
A28: bmv_ebitda_2Q26 | B28: Grupo Bimbo | C28: Adj. EBITDA (IFRS 16), quarter 2Q26 | D28: 15113 | E28: MXN m | F28: MXN | G28: sourced | H28: Company quarterly release via wiki/Financials/bimbo-quarterly-trend-4q21-2q26.md; wiki/Financials/bimbo-balance-sheet-and-leverage.md line 83 | I28: 2026-06-30
A29: bmv_rev_ltm | B29: Grupo Bimbo | C29: Net sales, LTM to 30-Jun-2026 | D29: 421423 | E29: MXN m | F29: MXN | G29: sourced | H29: BMV Jun-26 p.27 via wiki/Financials/bimbo-quarterly-trend-4q21-2q26.md line 62 (CIQ quarterly sum 421,435 differs by 0.1%) | I29: 2026-06-30
A30: bmv_eps_3Q25 | B30: Grupo Bimbo | C30: Normalized diluted EPS, quarter 3Q25 | D30: 0.782 | E30: MXN per share | F30: MXN | G30: sourced | H30: data/capitaliq/income_statement.csv 'Normalized Diluted EPS' 3Q25 | I30: 2026-06-30
A31: bmv_eps_4Q25 | B31: Grupo Bimbo | C31: Normalized diluted EPS, quarter 4Q25 | D31: 0.866 | E31: MXN per share | F31: MXN | G31: sourced | H31: data/capitaliq/income_statement.csv 'Normalized Diluted EPS' 4Q25 | I31: 2026-06-30
A32: bmv_eps_1Q26 | B32: Grupo Bimbo | C32: Normalized diluted EPS, quarter 1Q26 | D32: 0.853 | E32: MXN per share | F32: MXN | G32: sourced | H32: data/capitaliq/income_statement.csv 'Normalized Diluted EPS' 1Q26 | I32: 2026-06-30
A33: bmv_eps_2Q26 | B33: Grupo Bimbo | C33: Normalized diluted EPS, quarter 2Q26 | D33: 0.674 | E33: MXN per share | F33: MXN | G33: sourced | H33: data/capitaliq/income_statement.csv 'Normalized Diluted EPS' 2Q26 | I33: 2026-06-30
A34: bmv_gp_ltm | B34: Grupo Bimbo | C34: Gross profit, LTM to 30-Jun-2026 (CIQ basis) | D34: 221490.26 | E34: MXN m | F34: MXN | G34: sourced | H34: data/capitaliq/income_statement.csv 'Gross Profit', 3Q25 to 2Q26 (sum of quarters, MXN thousands / 1,000) | I34: 2026-06-30
A35: bmv_lfcf_ltm | B35: Grupo Bimbo | C35: Levered free cash flow, LTM to 30-Jun-2026 (CIQ basis) | D35: 25433.349 | E35: MXN m | F35: MXN | G35: sourced | H35: data/capitaliq/cash_flow.csv 'Levered Free Cash Flow', 3Q25 to 2Q26 (sum of quarters, MXN thousands / 1,000) | I35: 2026-06-30
A36: C. Peers: market data, net debt, LTM and history (USD m unless stated)
A37: FLO.mc | B37: Flowers Foods, Inc. | C37: Market capitalisation (CIQ, LTM date) | D37: 1295.7 | E37: USD m | F37: USD | G37: sourced | H37: data/capitaliq/capiq-ai-prompt1_2026-10-16.md Task 1A (market data, LTM balance sheet) | I37: 2026-10-16
A38: FLO.shares | B38: Flowers Foods, Inc. | C38: Diluted shares (CIQ) | D38: 212.1 | E38: m shares | F38: shares | G38: sourced | H38: data/capitaliq/capiq-ai-prompt1_2026-10-16.md Task 1A (market data, LTM balance sheet) | I38: 2026-10-16
A39: FLO.ev_ciq | B39: Flowers Foods, Inc. | C39: Enterprise value (CIQ table) | D39: 3250.7 | E39: USD m | F39: USD | G39: sourced | H39: data/capitaliq/capiq-ai-prompt1_2026-10-16.md Task 1A (market data, LTM balance sheet) | I39: 2026-10-16
A40: FLO.nci_filings | B40: Flowers Foods, Inc. | C40: NCI and redeemable NCI from filings (memo, USD m) | D40: 0 | E40: USD m | F40: USD | G40: sourced | H40: SEC XBRL MinorityInterest and balance sheet (research: see Checks section 1) | I40: 2026-10-16 | J40: 0.0 (no NCI)
A41: FLO.nd | B41: Flowers Foods, Inc. | C41: Net debt incl. leases (USD m) | D41: 1955 | E41: USD m | F41: USD | G41: sourced | H41: data/capitaliq/capiq-ai-prompt1_2026-10-16.md Task 1A (market data, LTM balance sheet) | I41: 2026-10-16
A42: FLO.ebitda_ltm | B42: Flowers Foods, Inc. | C42: EBITDA, LTM (reported basis, USD m) | D42: 486.9 | E42: USD m | F42: USD | G42: sourced | H42: data/capitaliq/capiq-ai-prompt1_2026-10-16.md Task 1A (market data, LTM balance sheet) | I42: 2026-10-16
A43: FLO.rev_ltm | B43: Flowers Foods, Inc. | C43: Revenue, LTM (USD m) | D43: 5223.9 | E43: USD m | F43: USD | G43: sourced | H43: data/capitaliq/capiq-ai-prompt1_2026-10-16.md Task 2B (revenue, levered FCF, consensus) | I43: 2026-10-16
A44: FLO.rev_fy24 | B44: Flowers Foods, Inc. | C44: Revenue, FY2024 (fiscal label per CIQ / company) | D44: 5103.5 | E44: USD m | F44: USD | G44: sourced | H44: data/capitaliq/capiq-ai-prompt1_2026-10-16.md Task 2B (revenue, levered FCF, consensus) | I44: FY2024
A45: FLO.rev_fy25 | B45: Flowers Foods, Inc. | C45: Revenue, FY2025 (fiscal label per CIQ / company) | D45: 5256.5 | E45: USD m | F45: USD | G45: sourced | H45: data/capitaliq/capiq-ai-prompt1_2026-10-16.md Task 2B (revenue, levered FCF, consensus) | I45: FY2025
A46: FLO.ebitda_fy24 | B46: Flowers Foods, Inc. | C46: EBITDA, FY2024 (reported basis) | D46: 520.7 | E46: USD m | F46: USD | G46: sourced | H46: data/capitaliq/capiq-ai-prompt1_2026-10-16.md Task 1B (annual leverage history, EBITDA) | I46: FY2024
A47: FLO.ebitda_fy25 | B47: Flowers Foods, Inc. | C47: EBITDA, FY2025 (reported basis) | D47: 514.8 | E47: USD m | F47: USD | G47: sourced | H47: data/capitaliq/capiq-ai-prompt1_2026-10-16.md Task 1B (annual leverage history, EBITDA) | I47: FY2025
A48: FLO.gp_ltm | B48: Flowers Foods, Inc. | C48: Gross profit, LTM (USD m) | D48: 2540.4 | E48: USD m | F48: USD | G48: sourced | H48: CIQ LTM gross profit to 18-Jul-2026 (data/capitaliq/capiq-ai-model-gaps-6_2026-10-17.md Task 6A, USD m). | I48: 2026-10-16
A49: FLO.lfcf_ltm | B49: Flowers Foods, Inc. | C49: Levered free cash flow, LTM (CIQ basis) | D49: 298.5 | E49: USD m | F49: USD | G49: sourced | H49: data/capitaliq/capiq-ai-prompt1_2026-10-16.md Task 2B (revenue, levered FCF, consensus) | I49: 2026-10-16
A50: FLO.pe_ltm | B50: Flowers Foods, Inc. | C50: P/E LTM (CIQ multiples tool) | D50: 23.45 | E50: x | G50: sourced | H50: data/capitaliq/capiq-ai-prompt1_2026-10-16.md Task 2A (CIQ multiples tool) | I50: 2026-10-16
A51: FLO.pe_ntm | B51: Flowers Foods, Inc. | C51: P/E NTM (CIQ multiples tool) | D51: 8.93 | E51: x | G51: sourced | H51: data/capitaliq/capiq-ai-prompt1_2026-10-16.md Task 2A (CIQ multiples tool) | I51: 2026-10-16 | J51: Tool value; EPS NTM is derived as price / this P/E [calc]
A52: FLO.ev_ebitda_ltm_tool | B52: Flowers Foods, Inc. | C52: EV/EBITDA LTM, CIQ multiples tool (audit only) | D52: 5.15 | E52: x | G52: sourced | H52: data/capitaliq/capiq-ai-prompt1_2026-10-16.md Task 2A (CIQ multiples tool) | I52: 2026-10-16 | J52: Not used: tool EV differs from the table EV (wiki discrepancy #7)
A53: FLO.ev_ebitda_ntm_tool | B53: Flowers Foods, Inc. | C53: EV/EBITDA NTM, CIQ multiples tool (audit only) | D53: 7.55 | E53: x | G53: sourced | H53: data/capitaliq/capiq-ai-prompt1_2026-10-16.md Task 2A (CIQ multiples tool) | I53: 2026-10-16 | J53: Audit only
A54: GRUMA.price_local | B54: Gruma, S.A.B. de C.V. | C54: Share price, local currency (pricing date) | D54: 242.02 | E54: MXN per share | F54: MXN | G54: sourced | H54: Delayed quote MXN 242.02 (Yahoo Finance, 16-Oct-2026 1:59 PM CST; no official BMV close found). Corroborated by the Capital IQ chart close USD 13.09 x 18.479 = MXN 241.89 (-0.05%) (data/capitaliq/capiq-ai-model-gaps-5_2026-10-17.md chart table). | I54: 2026-10-16 | J54: Delayed quote (Yahoo Finance, 16-Oct-2026 1:59 PM CST); StockAnalysis 242.71; no official BMV close found
A55: GRUMA.shares | B55: Gruma, S.A.B. de C.V. | C55: Shares outstanding | D55: 336.20799 | E55: m shares | F55: shares | G55: sourced | H55: Company filings (see note) | I55: 2026-06-30 | J55: Outstanding Series B shares at 30-Jun-2026 (2Q26 BMV report p.53); treasury 6,463,051 excluded
A56: GRUMA.fx | B56: Gruma, S.A.B. de C.V. | C56: Local currency to USD for market values | D56: =1/$D$10 -> 0.054115482 | E56: USD per MXN | F56: USD | G56: calc | H56: USD per MXN = 1 / fx_mxn_spot (link) | I56: 2026-10-17 | J56: Linked: 1 / fx_mxn_spot (USD/MXN 18.479 on 16-Oct-2026); v1/v2 used 17.46
A57: GRUMA.nci_usd | B57: Gruma, S.A.B. de C.V. | C57: Non-controlling interest, USD m (filings) | D57: 2.8 | E57: USD m | F57: USD | G57: sourced | H57: Company filings (see note) | I57: 2026-06-30 | J57: Non-controlling interest 30-Jun-2026, USD m (2Q26 BMV report p.20)
A58: GRUMA.nd | B58: Gruma, S.A.B. de C.V. | C58: Net debt incl. leases (USD m) | D58: 1628.2 | E58: USD m | F58: USD | G58: calc | H58: Calc from Gruma 2Q26 BMV report (USD): total debt incl. leases 2,111.8 (ST 365.2 p.35; LT 1,333.4 p.20; leases 413.2 p.19-20) less cash 483.6 (p.19) | I58: 2026-06-30 | J58: Calc: total debt incl. leases 2,111.8 (ST bank loans 365.2 + LT debt 1,333.4 + leases 413.2, carrying; 2Q26 report p.19-20, p.35) less cash 483.6 (p.19)
A59: GRUMA.ebitda_ltm | B59: Gruma, S.A.B. de C.V. | C59: EBITDA, LTM (reported basis, USD m) | D59: 1108.9 | E59: USD m | F59: USD | G59: calc | H59: Calc from Gruma FY25 release (S3 p.11, EBITDA 1,136.0) + 1H26 538.5 - 1H25 565.6 (2Q26 BMV report p.12 and p.33) | I59: 2026-06-30 | J59: Calc: FY25 1,136.0 + 1H26 538.5 - 1H25 565.6 (company EBITDA = operating income + D&A + impairment, before lease costs under IFRS 16)
A60: GRUMA.rev_ltm | B60: Gruma, S.A.B. de C.V. | C60: Revenue, LTM (USD m) | D60: 6500.1 | E60: USD m | F60: USD | G60: calc | H60: Calc from Gruma FY25 release (S3 p.11, net sales 6,374.6) + 1H26 3,274.7 - 1H25 3,149.2 (2Q26 BMV report p.34 cross-check 6,500.057) | I60: 2026-06-30
A61: GRUMA.rev_fy24 | B61: Gruma, S.A.B. de C.V. | C61: Revenue, FY2024 (fiscal label per CIQ / company) | D61: 6486.9 | E61: USD m | F61: USD | G61: sourced | H61: Gruma FY25 release, FY24 comparative (S3 p.11) | I61: FY2024
A62: GRUMA.rev_fy25 | B62: Gruma, S.A.B. de C.V. | C62: Revenue, FY2025 (fiscal label per CIQ / company) | D62: 6374.6 | E62: USD m | F62: USD | G62: sourced | H62: Gruma FY25 release (S3 p.11) | I62: FY2025
A63: GRUMA.ebitda_fy24 | B63: Gruma, S.A.B. de C.V. | C63: EBITDA, FY2024 (reported basis) | D63: 1131.1 | E63: USD m | F63: USD | G63: sourced | H63: Gruma FY25 release, FY24 comparative (S3 p.11) EBITDA UAFIRDA | I63: FY2024
A64: GRUMA.ebitda_fy25 | B64: Gruma, S.A.B. de C.V. | C64: EBITDA, FY2025 (reported basis) | D64: 1136 | E64: USD m | F64: USD | G64: sourced | H64: Gruma FY25 release (S3 p.11) EBITDA UAFIRDA | I64: FY2025
A65: GRUMA.gp_ltm | B65: Gruma, S.A.B. de C.V. | C65: Gross profit, LTM (USD m) | D65: 2522.2 | E65: USD m | F65: USD | G65: sourced | H65: Calc from Gruma FY25 gross profit 2,492.7 (S3 p.11) + 1H26 1,276.1 - 1H25 1,246.6 (S1 p.12) | I65: 2026-06-30
A66: GRUMA.lfcf_ltm | B66: Gruma, S.A.B. de C.V. | C66: Levered free cash flow, LTM (CIQ basis) | D66: n/a | E66: USD m | F66: USD | G66: pending | H66: Not retrieved (pending) | I66: 2026-10-16
A67: GRUMA.pe_ltm | B67: Gruma, S.A.B. de C.V. | C67: P/E LTM (CIQ multiples tool) | D67: =IFERROR($D$54*$D$56/$D$335,"n/a") -> 9.3550208 | E67: x | G67: calc | H67: calc: price in USD / diluted EPS LTM USD 1.40 (Capital IQ, prompt 4B) | I67: 2026-10-16
A68: GRUMA.pe_ntm | B68: Gruma, S.A.B. de C.V. | C68: P/E NTM (CIQ multiples tool) | D68: =IFERROR($D$54*$D$56/(Detail_PeerAnalysis!$D$62*$D$333+Detail_PeerAnalysis!$E$62*$D$334),"n/a") -> 9.7392544 | E68: x | G68: calc | H68: calc: price in USD / NTM EPS (FY2026E 1.40 and FY2027E 1.33 consensus, day-weighted; Capital IQ, prompt 4C) | I68: 2026-10-16 | J68: Tool value; EPS NTM is derived as price / this P/E [calc]
A69: GRUMA.ev_ebitda_ltm_tool | B69: Gruma, S.A.B. de C.V. | C69: EV/EBITDA LTM, CIQ multiples tool (audit only) | D69: n/a | E69: x | G69: sourced | H69: not in CIQ pull | I69: 2026-10-16 | J69: Not used: tool EV differs from the table EV (wiki discrepancy #7)
A70: GRUMA.ev_ebitda_ntm_tool | B70: Gruma, S.A.B. de C.V. | C70: EV/EBITDA NTM, CIQ multiples tool (audit only) | D70: n/a | E70: x | G70: sourced | H70: not in CIQ pull | I70: 2026-10-16 | J70: Audit only
A71: YMZ.price_local | B71: Yamazaki Baking Co., Ltd. | C71: Share price, local currency (pricing date) | D71: 3816 | E71: JPY per share | F71: JPY | G71: sourced | H71: TSE close JPY 3,816 on 16-Oct-2026 (Yahoo Finance Japan history, aggregator). Corroborated by the Capital IQ chart close USD 24.17 x 157.987 = JPY 3,818.5 (+0.07%) (data/capitaliq/capiq-ai-model-gaps-5_2026-10-17.md). | I71: 2026-10-16 | J71: TSE close 16-Oct-2026 (Yahoo Finance Japan, aggregator); CIQ chart within 0.07%
A72: YMZ.shares | B72: Yamazaki Baking Co., Ltd. | C72: Shares outstanding | D72: 196.9 | E72: m shares | F72: shares | G72: sourced | H72: Basic shares outstanding 196.9m at 30-Jun-2026 (data/capitaliq/capiq-ai-model-gaps-4_2026-10-17.md Task 4A; diluted returned N/A). | I72: 2026-06-30 | J72: Not found
A73: YMZ.fx | B73: Yamazaki Baking Co., Ltd. | C73: Local currency to USD for market values | D73: =1/157.987 -> 0.0063296347 | E73: USD per JPY | F73: USD | G73: calc | H73: USD per JPY = 1 / 157.987 (Yahoo Finance JPY=X close 16-Oct-2026, see fx.usd_per_jpy). v2 used Capital IQ's 0.006482 (LTM 30-Jun-2026 conversion). | I73: 2026-10-17 | J73: CIQ conversion 0.006482 USD per JPY
A74: YMZ.nci_usd | B74: Yamazaki Baking Co., Ltd. | C74: Non-controlling interest, USD m (filings) | D74: n/a | E74: USD m | F74: USD | G74: pending | H74: Not found in research | I74: 2026-06-30 | J74: Not found
A75: YMZ.nd | B75: Yamazaki Baking Co., Ltd. | C75: Net debt incl. leases (USD m) | D75: -473.5 | E75: USD m | F75: USD | G75: sourced | H75: data/capitaliq/capiq-ai-prompt1_2026-10-16.md Task 1A (market data, LTM balance sheet) | I75: 2026-10-16
A76: YMZ.ebitda_ltm | B76: Yamazaki Baking Co., Ltd. | C76: EBITDA, LTM (reported basis, USD m) | D76: 706.7 | E76: USD m | F76: USD | G76: sourced | H76: data/capitaliq/capiq-ai-prompt1_2026-10-16.md Task 1A (market data, LTM balance sheet) | I76: 2026-10-16
A77: YMZ.rev_ltm | B77: Yamazaki Baking Co., Ltd. | C77: Revenue, LTM (USD m) | D77: 8669.9 | E77: USD m | F77: USD | G77: sourced | H77: data/capitaliq/capiq-ai-prompt1_2026-10-16.md Task 2B (revenue, levered FCF, consensus) | I77: 2026-10-16
A78: YMZ.rev_fy24 | B78: Yamazaki Baking Co., Ltd. | C78: Revenue, FY2024 (fiscal label per CIQ / company) | D78: 8224.6 | E78: USD m | F78: USD | G78: sourced | H78: data/capitaliq/capiq-ai-prompt1_2026-10-16.md Task 2B (revenue, levered FCF, consensus) | I78: FY2024
A79: YMZ.rev_fy25 | B79: Yamazaki Baking Co., Ltd. | C79: Revenue, FY2025 (fiscal label per CIQ / company) | D79: 8773.2 | E79: USD m | F79: USD | G79: sourced | H79: data/capitaliq/capiq-ai-model-gaps-7_2026-10-17.md Task 7A corrected revenue table: FY2025 USD 8,773.2m = JPY 1,353,459m (data/capitaliq/capiq-ai-model-gaps-4_2026-10-17.md Task 4B) x 0.006482. Resolves wiki discrepancy #11: the copy error was the Prompt 1 FY2021 value (FY2021 is 9,592.8). | I79: FY2025 | J79: Not used: CIQ value equals the FY2021 figure (wiki discrepancy #11)
A80: YMZ.ebitda_fy24 | B80: Yamazaki Baking Co., Ltd. | C80: EBITDA, FY2024 (reported basis) | D80: 630.3 | E80: USD m | F80: USD | G80: sourced | H80: data/capitaliq/capiq-ai-prompt1_2026-10-16.md Task 1B (annual leverage history, EBITDA) | I80: FY2024
A81: YMZ.ebitda_fy25 | B81: Yamazaki Baking Co., Ltd. | C81: EBITDA, FY2025 (reported basis) | D81: 712 | E81: USD m | F81: USD | G81: sourced | H81: data/capitaliq/capiq-ai-prompt1_2026-10-16.md Task 1B (annual leverage history, EBITDA) | I81: FY2025
A82: YMZ.gp_ltm | B82: Yamazaki Baking Co., Ltd. | C82: Gross profit, LTM (USD m) | D82: 2834.9 | E82: USD m | F82: USD | G82: sourced | H82: CIQ LTM gross profit to 30-Jun-2026 (data/capitaliq/capiq-ai-model-gaps-6_2026-10-17.md Task 6A, USD m). | I82: 2026-10-16
A83: YMZ.lfcf_ltm | B83: Yamazaki Baking Co., Ltd. | C83: Levered free cash flow, LTM (CIQ basis) | D83: 113.4 | E83: USD m | F83: USD | G83: sourced | H83: data/capitaliq/capiq-ai-prompt1_2026-10-16.md Task 2B (revenue, levered FCF, consensus) | I83: 2026-10-16
A84: YMZ.pe_ltm | B84: Yamazaki Baking Co., Ltd. | C84: P/E LTM (CIQ multiples tool) | D84: 17.74 | E84: x | G84: sourced | H84: data/capitaliq/capiq-ai-prompt1_2026-10-16.md Task 2A (CIQ multiples tool) | I84: 2026-10-16
A85: YMZ.pe_ntm | B85: Yamazaki Baking Co., Ltd. | C85: P/E NTM (CIQ multiples tool) | D85: 16.84 | E85: x | G85: sourced | H85: data/capitaliq/capiq-ai-prompt1_2026-10-16.md Task 2A (CIQ multiples tool) | I85: 2026-10-16 | J85: Tool value; EPS NTM is derived as price / this P/E [calc]
A86: YMZ.ev_ebitda_ltm_tool | B86: Yamazaki Baking Co., Ltd. | C86: EV/EBITDA LTM, CIQ multiples tool (audit only) | D86: 6.58 | E86: x | G86: sourced | H86: data/capitaliq/capiq-ai-prompt1_2026-10-16.md Task 2A (CIQ multiples tool) | I86: 2026-10-16 | J86: Not used: tool EV differs from the table EV (wiki discrepancy #7)
A87: YMZ.ev_ebitda_ntm_tool | B87: Yamazaki Baking Co., Ltd. | C87: EV/EBITDA NTM, CIQ multiples tool (audit only) | D87: 6.37 | E87: x | G87: sourced | H87: data/capitaliq/capiq-ai-prompt1_2026-10-16.md Task 2A (CIQ multiples tool) | I87: 2026-10-16 | J87: Audit only
A88: ARYN.mc | B88: ARYZTA AG | C88: Market capitalisation (CIQ, LTM date) | D88: 1218.8 | E88: USD m | F88: USD | G88: sourced | H88: data/capitaliq/capiq-ai-prompt1_2026-10-16.md Task 1A (market data, LTM balance sheet) | I88: 2026-10-16
A89: ARYN.shares | B89: ARYZTA AG | C89: Diluted shares (CIQ) | D89: 24.8 | E89: m shares | F89: shares | G89: sourced | H89: 24.8m in three Capital IQ pulls: Task 1A diluted (data/capitaliq/capiq-ai-prompt1_2026-10-16.md), basic at 30-Jun-2026 (data/capitaliq/capiq-ai-model-gaps-4_2026-10-17.md Task 4A) and latest (data/capitaliq/capiq-ai-model-gaps-5_2026-10-17.md). | I89: 2026-10-16 | J89: CIQ share count 24.8m not verified (Aryzta H1-26 report not read)
A90: ARYN.ev_ciq | B90: ARYZTA AG | C90: Enterprise value (CIQ table) | D90: 2103.3 | E90: USD m | F90: USD | G90: sourced | H90: data/capitaliq/capiq-ai-prompt1_2026-10-16.md Task 1A (market data, LTM balance sheet) | I90: 2026-10-16
A91: ARYN.nci_filings | B91: ARYZTA AG | C91: NCI and redeemable NCI from filings (memo, USD m) | D91: n/a | E91: USD m | F91: USD | G91: pending | H91: SEC XBRL MinorityInterest and balance sheet (research: see Checks section 1) | I91: 2026-10-16 | J91: CIQ residual -17.4 unexplained (NCI not found in research)
A92: ARYN.nd | B92: ARYZTA AG | C92: Net debt incl. leases (USD m) | D92: 901.9 | E92: USD m | F92: USD | G92: sourced | H92: data/capitaliq/capiq-ai-prompt1_2026-10-16.md Task 1A (market data, LTM balance sheet) | I92: 2026-10-16
A93: ARYN.ebitda_ltm | B93: ARYZTA AG | C93: EBITDA, LTM (reported basis, USD m) | D93: 252.4 | E93: USD m | F93: USD | G93: sourced | H93: data/capitaliq/capiq-ai-prompt1_2026-10-16.md Task 1A (market data, LTM balance sheet) | I93: 2026-10-16
A94: ARYN.rev_ltm | B94: ARYZTA AG | C94: Revenue, LTM (USD m) | D94: 2567.4 | E94: USD m | F94: USD | G94: sourced | H94: data/capitaliq/capiq-ai-prompt1_2026-10-16.md Task 2B (revenue, levered FCF, consensus) | I94: 2026-10-16
A95: ARYN.rev_fy24 | B95: ARYZTA AG | C95: Revenue, FY2024 (fiscal label per CIQ / company) | D95: 2374.1 | E95: USD m | F95: USD | G95: sourced | H95: data/capitaliq/capiq-ai-prompt1_2026-10-16.md Task 2B (revenue, levered FCF, consensus) | I95: FY2024
A96: ARYN.rev_fy25 | B96: ARYZTA AG | C96: Revenue, FY2025 (fiscal label per CIQ / company) | D96: 2513.7 | E96: USD m | F96: USD | G96: sourced | H96: data/capitaliq/capiq-ai-prompt1_2026-10-16.md Task 2B (revenue, levered FCF, consensus) | I96: FY2025
A97: ARYN.ebitda_fy24 | B97: ARYZTA AG | C97: EBITDA, FY2024 (reported basis) | D97: 295.3 | E97: USD m | F97: USD | G97: sourced | H97: data/capitaliq/capiq-ai-prompt1_2026-10-16.md Task 1B (annual leverage history, EBITDA) | I97: FY2024
A98: ARYN.ebitda_fy25 | B98: ARYZTA AG | C98: EBITDA, FY2025 (reported basis) | D98: 287.4 | E98: USD m | F98: USD | G98: sourced | H98: data/capitaliq/capiq-ai-prompt1_2026-10-16.md Task 1B (annual leverage history, EBITDA) | I98: FY2025
A99: ARYN.gp_ltm | B99: ARYZTA AG | C99: Gross profit, LTM (USD m) | D99: 514.8 | E99: USD m | F99: USD | G99: sourced | H99: CIQ LTM gross profit to 30-Jun-2026 (data/capitaliq/capiq-ai-model-gaps-6_2026-10-17.md Task 6A, USD m). | I99: 2026-10-16
A100: ARYN.lfcf_ltm | B100: ARYZTA AG | C100: Levered free cash flow, LTM (CIQ basis) | D100: 138.1 | E100: USD m | F100: USD | G100: sourced | H100: data/capitaliq/capiq-ai-prompt1_2026-10-16.md Task 2B (revenue, levered FCF, consensus) | I100: 2026-10-16
A101: ARYN.pe_ltm | B101: ARYZTA AG | C101: P/E LTM (CIQ multiples tool) | D101: 10.21 | E101: x | G101: sourced | H101: data/capitaliq/capiq-ai-prompt1_2026-10-16.md Task 2A (CIQ multiples tool) | I101: 2026-10-16
...

Sheet Checks
A1: Checks (formulas; flags shown as FLAG when a test fails)
A3: 1. Enterprise value: CIQ table EV vs our EV on the claim basis (CIQ-quoted peers)
A4: Company | B4: CIQ EV (USD m) | C4: Our EV, claim basis (USD m) | D4: Difference | E4: Difference % of CIQ EV | F4: Flag (>0.5%) | G4: Explanation
A5: Flowers Foods, Inc. | B5: =Inputs_Sources!$D$39 -> 3250.7 | C5: =Detail_PeerAnalysis!O12 -> 3246.236 | D5: =C5-B5 -> -4.464 | E5: =IFERROR(D5/B5,"n/a") -> -0.0013732427 | F5: =IF(ABS(E5)>0.005,"FLAG","ok") -> ok | G5: Components 2,003.3 (debt 1,686.2 + operating leases 317.1) vs CIQ total debt 2,007.8: 4.5 unreconciled; NCI nil
A6: The J. M. Smucker Company | B6: =Inputs_Sources!$D$107 -> 20509.5 | C6: =Detail_PeerAnalysis!O16 -> 20509.5 | D6: =C6-B6 -> 0 | E6: =IFERROR(D6/B6,"n/a") -> 0 | F6: =IF(ABS(E6)>0.005,"FLAG","ok") -> ok | G6: Exact: financial debt + finance leases + operating leases - cash = CIQ net debt
A7: The Campbell's Company | B7: =Inputs_Sources!$D$124 -> 13287.9 | C7: =Detail_PeerAnalysis!O17 -> 13287.9 | D7: =C7-B7 -> 0 | E7: =IFERROR(D7/B7,"n/a") -> 0 | F7: =IF(ABS(E7)>0.005,"FLAG","ok") -> ok | G7: Exact: redeemable NCI 304 + NCI 2 is the CIQ residual of 306
A8: Mondelez International, Inc. | B8: =Inputs_Sources!$D$141 -> 101964.8 | C8: =Detail_PeerAnalysis!O18 -> 102128.8 | D8: =C8-B8 -> 164 | E8: =IFERROR(D8/B8,"n/a") -> 0.0016083982 | F8: =IF(ABS(E8)>0.005,"FLAG","ok") -> ok | G8: Exact except the current operating lease portion (164, 31-Dec-2025 proxy), which our claim basis adds (v2); NCI 53 is the CIQ residual
A9: PepsiCo, Inc. | B9: =Inputs_Sources!$D$175 -> 220113.5 | C9: =Detail_PeerAnalysis!O20 -> 224447.5 | D9: =C9-B9 -> 4334 | E9: =IFERROR(D9/B9,"n/a") -> 0.019689842 | F9: =IF(ABS(E9)>0.005,"FLAG","ok") -> FLAG | G9: Our EV adds operating leases 3,846 (CIQ excludes them) and deducts cash 10,675 only (CIQ deducts 488 more)
A10: ARYZTA AG | B10: =Inputs_Sources!$D$90 -> 2103.3 | C10: =Detail_PeerAnalysis!O15 -> 2103.3089 | D10: =C10-B10 -> 0.008914 | E10: =IFERROR(D10/B10,"n/a") -> 4.238102e-06 | F10: =IF(ABS(E10)>0.005,"FLAG","ok") -> ok | G10: Lease split reconciled to CIQ total debt (791.2 + 195.7 = 986.9); the CIQ TEV residual -17.4 is kept (unexplained, not a book NCI); the 0.01 gap is the EUR conversion of the components
A12: 2. Calendarisation weights sum to 1
A13: Weights check: BIMBO | B13: =IFERROR(Detail_PeerAnalysis!D60+Detail_PeerAnalysis!E60,"n/a") -> 1 | C13: =IF(ISNUMBER(B13),IF(ABS(B13-1)<0.000001,"ok","FLAG"),"n/a") -> ok
A14: Weights check: FLO | B14: =IFERROR(Detail_PeerAnalysis!D61+Detail_PeerAnalysis!E61,"n/a") -> 1 | C14: =IF(ISNUMBER(B14),IF(ABS(B14-1)<0.000001,"ok","FLAG"),"n/a") -> ok
A15: Weights check: GRUMA | B15: =IFERROR(Detail_PeerAnalysis!D62+Detail_PeerAnalysis!E62,"n/a") -> 1 | C15: =IF(ISNUMBER(B15),IF(ABS(B15-1)<0.000001,"ok","FLAG"),"n/a") -> ok
A16: Weights check: YMZ | B16: =IFERROR(Detail_PeerAnalysis!D63+Detail_PeerAnalysis!E63,"n/a") -> 1 | C16: =IF(ISNUMBER(B16),IF(ABS(B16-1)<0.000001,"ok","FLAG"),"n/a") -> ok
A17: Weights check: ARYN | B17: =IFERROR(Detail_PeerAnalysis!D64+Detail_PeerAnalysis!E64,"n/a") -> 1 | C17: =IF(ISNUMBER(B17),IF(ABS(B17-1)<0.000001,"ok","FLAG"),"n/a") -> ok
A18: Weights check: SJM | B18: =IFERROR(Detail_PeerAnalysis!D65+Detail_PeerAnalysis!E65,"n/a") -> 1 | C18: =IF(ISNUMBER(B18),IF(ABS(B18-1)<0.000001,"ok","FLAG"),"n/a") -> ok
A19: Weights check: CPB | B19: =IFERROR(Detail_PeerAnalysis!D66+Detail_PeerAnalysis!E66,"n/a") -> 1 | C19: =IF(ISNUMBER(B19),IF(ABS(B19-1)<0.000001,"ok","FLAG"),"n/a") -> ok
A20: Weights check: MDLZ | B20: =IFERROR(Detail_PeerAnalysis!D67+Detail_PeerAnalysis!E67,"n/a") -> 1 | C20: =IF(ISNUMBER(B20),IF(ABS(B20-1)<0.000001,"ok","FLAG"),"n/a") -> ok
A21: Weights check: AC | B21: =IFERROR(Detail_PeerAnalysis!D68+Detail_PeerAnalysis!E68,"n/a") -> 1 | C21: =IF(ISNUMBER(B21),IF(ABS(B21-1)<0.000001,"ok","FLAG"),"n/a") -> ok
A22: Weights check: PEP | B22: =IFERROR(Detail_PeerAnalysis!D69+Detail_PeerAnalysis!E69,"n/a") -> 1 | C22: =IF(ISNUMBER(B22),IF(ABS(B22-1)<0.000001,"ok","FLAG"),"n/a") -> ok
A24: 3. Bimbo LTM Adjusted EBITDA: sum of four quarters vs company LTM (60,919)
A25: Sum of quarters 3Q25 to 2Q26 (MXN m) | B25: =Inputs_Sources!$D$25+Inputs_Sources!$D$26+Inputs_Sources!$D$27+Inputs_Sources!$D$28 -> 60919 | C25: =IF(ABS(B25-60919)<0.5,"ok","FLAG") -> ok
A27: 4. TearSheet identities and cross-checks
A28: Test | B28: FY2021 | C28: FY2022 | D28: FY2023 | E28: FY2024 | F28: FY2025
A29: Balance sheet identity: total assets - total liabilities - equity (should be 0) | B29: =Detail_TearSheet!C30-Detail_TearSheet!C33-Detail_TearSheet!C35 -> 0 | C29: =Detail_TearSheet!D30-Detail_TearSheet!D33-Detail_TearSheet!D35 -> 0 | D29: =Detail_TearSheet!E30-Detail_TearSheet!E33-Detail_TearSheet!E35 -> 0 | E29: =Detail_TearSheet!F30-Detail_TearSheet!F33-Detail_TearSheet!F35 -> 0 | F29: =Detail_TearSheet!G30-Detail_TearSheet!G33-Detail_TearSheet!G35 -> 0
A30: Net debt CIQ incl. leases minus (total debt incl. leases minus cash) (should be 0) | B30: =Detail_TearSheet!C37-(Detail_TearSheet!C36-Detail_TearSheet!C28) -> 0 | C30: =Detail_TearSheet!D37-(Detail_TearSheet!D36-Detail_TearSheet!D28) -> 0 | D30: =Detail_TearSheet!E37-(Detail_TearSheet!E36-Detail_TearSheet!E28) -> 0 | E30: =Detail_TearSheet!F37-(Detail_TearSheet!F36-Detail_TearSheet!F28) -> 0 | F30: =Detail_TearSheet!G37-(Detail_TearSheet!G36-Detail_TearSheet!G28) -> 0
A31: Revenue CIQ sum of quarters minus company annual (MXN m; FY2025 company 426,952; FY2021-23 restated company) | B31: =Detail_TearSheet!C7-338792 -> 0 | C31: =Detail_TearSheet!D7-398706 -> 0 | D31: =Detail_TearSheet!E7-399879 -> 0 | F31: =Detail_TearSheet!G7-426952 -> 11
A32: Consensus FY2026E EBITDA in USD at 17.46 (the rate implied in the CIQ dashboard, not the pricing-date rate) minus CIQ dashboard US$3,558.4m (should be about 0) | B32: =Detail_TearSheet!H19/17.46-3558.4 -> -0.72531501
A34: 5. Error scan (count of error values in formula areas; must be 0)
A35: PeerAnalysis error cells | B35: =SUMPRODUCT(--ISERROR(Detail_PeerAnalysis!A1:T90)) -> 0
A36: TearSheet error cells | B36: =SUMPRODUCT(--ISERROR(Detail_TearSheet!A1:L80)) -> 0
A37: Checks sheet error cells | B37: =SUMPRODUCT(--ISERROR(A1:H36)) -> 0
A39: 6. Known gaps and memo items (no value is invented; blank = not found)
A40: CIQ dividend and CFO actuals differ from company values in some years (TearSheet memo rows); company values used where stated.
A41: Gross profit LTM: Capital IQ (prompt 6) for seven peers; Gruma (company report) and Mondelez (SEC) unchanged and equal to CIQ; Campbell's and PepsiCo moved from the SEC calculations (2,742 and 53,216) to the CIQ basis. Price performance: CIQ chart (prompt 5).
A42: Yamazaki (lease basis fails under J-GAAP), Aryzta and Arca (NCI not verified) are excluded from medians; their EVs are descriptive (Detail rows 14, 15 and 19). Shares and prices are now sourced from Capital IQ (prompts 4-5).
A43: Gruma price is a delayed quote (Yahoo, 16-Oct-2026), corroborated by the CIQ chart within 0.05%; replace it with the BMV official close before the report.
A44: Bimbo price MXN 58.60 (BMV official close 16-Oct-2026) and shares 4,294.9m (BMV notice 29-Jul-2026) are sourced; each MXN 1 per share moves EV/EBITDA by about 0.07x.
A45: Bimbo NCI at book (722) is small against the FY25 NCI profit share (1,813) because consolidated IO profit is attributed to NCI (coordinator statement); on an economic NCI claim EV would be higher.
A46: CIQ NTM multiples tool values are audit only; they differ from the table-based NTM multiples by up to about 0.5x.
A48: 7. Lease normalisation: CIQ total debt vs reconciled debt (US GAAP peers; values from SEC research)
A49: Company | B49: CIQ total debt (USD m) | C49: (A) financial debt (USD m) | D49: (A) vs CIQ | E49: (B) financial debt + op. lease liabilities (USD m) | F49: (B) vs CIQ | G49: CIQ includes op. leases? | H49: Basis note
A50: Flowers Foods, Inc. | B50: 2007.8 | C50: 1686.2 | D50: =C50/B50-1 -> -0.16017532 | E50: 2003.3 | F50: =E50/B50-1 -> -0.0022412591 | G50: yes | H50: 18-Jul-2026: financial debt 1,686.2 + op. lease liabilities 317.1 (75.2 + 241.9)
A51: The J. M. Smucker Company | B51: 6940.2 | C51: 6737.8 | D51: =C51/B51-1 -> -0.029163425 | E51: 6930.6 | F51: =E51/B51-1 -> -0.0013832454 | G51: yes | H51: 31-Jul-2026: (B) with finance leases 9.6 = 6,940.2 exact
A52: The Campbell's Company | B52: 7450 | C52: 7137 | D52: =C52/B52-1 -> -0.042013423 | E52: 7450 | F52: =E52/B52-1 -> 0 | G52: yes | H52: 2-Aug-2026 (FY26 10-K): 7,137 + op. lease liabilities 313 = 7,450 exact
A53: Mondelez International, Inc. | B53: 22059 | C53: 21450 | D53: =C53/B53-1 -> -0.027607779 | E53: 22059 | F53: =E53/B53-1 -> 0 | G53: yes | H53: 30-Jun-2026: noncurrent op. lease 609 ties exactly; current portion not found
A54: PepsiCo, Inc. | B54: 51881 | C54: 51881 | D54: =C54/B54-1 -> 0 | E54: 55727 | F54: =E54/B54-1 -> 0.074131185 | G54: no | H54: 5-Sep-2026: (A) exact, so CIQ excludes leases; (B) uses 27-Dec-2025 liabilities 3,846
A56: 8. FX and basis memo
A57: MXN per USD 18.479 (USD/MXN close 16-Oct-2026, Yahoo Finance MXN=X; the CIQ chart implies about 18.49) is used for every MXN market value (Gruma and Arca prices; Bimbo USD display). v1/v2 used 17.46, the rate implied in the CIQ consensus dashboard, not a pricing-date rate.
A58: CIQ's 0.055690 USD per MXN (17.957), stated for its LTM USD figures, is neither the 30-Jun-2026 closing rate (17.47, company 2Q26 release) nor the 16-Oct rate (18.479); it is used only to put Arca's MXN lease figure on CIQ's USD basis.
A59: CIQ's USD net debt for Bimbo (9,907) implies 17.47 MXN per USD (173,116 / 9,907): the 30-Jun-2026 balance-sheet rate, not the pricing-date rate.
A60: Bimbo multiples are computed in MXN and do not depend on FX; the USD columns are for size only.
A61: Gruma reports in USD: its balance-sheet items are USD at historical rates; its market cap uses the spot rate.
A62: Consensus for peers is in USD as converted by CIQ; Bimbo's MXN consensus against CIQ's USD values implies 17.46 for FY1 and about 18.50 for FY2-FY3, so NTM figures may differ from LTM by a few percent (Gruma: judgment_calls in valuation/inputs/peer_extras_v3.yaml).
A64: 9. EV claim basis: categories included and excluded (one basis for all eligible peers and Bimbo)
A65: Included: financial debt (incl. finance leases where separated), operating or IFRS 16 lease liabilities, NCI at book including redeemable NCI, less cash and equivalents.
A66: Excluded for every company: pensions and OPEB, Bimbo's MEPP, derivative assets and liabilities, equity-method investments, short-term investments (except as CIQ deducts them, flagged for PepsiCo).
A67: Reason: these claims are not sourced for every eligible peer (Gruma, Flowers, Smucker, Campbell's, Mondelez, PepsiCo); adding them would change the basis by company.
A69: 10. v3: results against the independent calculation's expected values, and v2 -> v3 changes
A70: Item | B70: Workbook | C70: Expected (spec) | D70: Flag | E70: v2
A71: Core median EV/EBITDA LTM | B71: =Detail_PeerAnalysis!B50 -> 5.5255833 | C71: 5.525583 | D71: =IF(ISNUMBER(B71),IF(ABS(B71-C71)<=0.000001*MAX(1,ABS(C71)),"ok","FLAG"),"FLAG") -> ok | E71: 5.641458
A72: Core median EV/EBITDA NTM | B72: =Detail_PeerAnalysis!C50 -> 5.8929139 | C72: 5.892914 | D72: =IF(ISNUMBER(B72),IF(ABS(B72-C72)<=0.000001*MAX(1,ABS(C72)),"ok","FLAG"),"FLAG") -> ok | E72: 6.147272
A73: All-peer median EV/EBITDA LTM | B73: =Detail_PeerAnalysis!B53 -> 8.2693232 | C73: 8.269323 | D73: =IF(ISNUMBER(B73),IF(ABS(B73-C73)<=0.000001*MAX(1,ABS(C73)),"ok","FLAG"),"FLAG") -> ok | E73: 8.269323
A74: All-peer median EV/EBITDA NTM | B74: =Detail_PeerAnalysis!C53 -> 8.7866094 | C74: 8.786609 | D74: =IF(ISNUMBER(B74),IF(ABS(B74-C74)<=0.000001*MAX(1,ABS(C74)),"ok","FLAG"),"FLAG") -> ok | E74: 9.215747
A75: All-peer median P/E LTM | B75: =Detail_PeerAnalysis!E53 -> 16.15 | C75: 16.15 | D75: =IF(ISNUMBER(B75),IF(ABS(B75-C75)<=0.000001*MAX(1,ABS(C75)),"ok","FLAG"),"FLAG") -> ok | E75: 19.625
A76: All-peer median P/E NTM | B76: =Detail_PeerAnalysis!F53 -> 11.72 | C76: 11.72 | D76: =IF(ISNUMBER(B76),IF(ABS(B76-C76)<=0.000001*MAX(1,ABS(C76)),"ok","FLAG"),"FLAG") -> ok | E76: 13.625
A77: FLO ev_ebitda_ltm | B77: =Detail_PeerAnalysis!B40 -> 5.6094445 | C77: 5.609444 | D77: =IF(ISNUMBER(B77),IF(ABS(B77-C77)<=0.000001*MAX(1,ABS(C77)),"ok","FLAG"),"FLAG") -> ok
A78: FLO ev_ebitda_ntm | B78: =Detail_PeerAnalysis!C40 -> 6.147272 | C78: 6.147272 | D78: =IF(ISNUMBER(B78),IF(ABS(B78-C78)<=0.000001*MAX(1,ABS(C78)),"ok","FLAG"),"FLAG") -> ok
A79: FLO pe_ltm | B79: =Detail_PeerAnalysis!E40 -> 23.45 | C79: 23.45 | D79: =IF(ISNUMBER(B79),IF(ABS(B79-C79)<=0.000001*MAX(1,ABS(C79)),"ok","FLAG"),"FLAG") -> ok
A80: FLO pe_ntm | B80: =Detail_PeerAnalysis!F40 -> 8.93 | C80: 8.93 | D80: =IF(ISNUMBER(B80),IF(ABS(B80-C80)<=0.000001*MAX(1,ABS(C80)),"ok","FLAG"),"FLAG") -> ok
A81: GRUMA ev_ebitda_ltm | B81: =Detail_PeerAnalysis!B41 -> 5.4417222 | C81: 5.441722 | D81: =IF(ISNUMBER(B81),IF(ABS(B81-C81)<=0.000001*MAX(1,ABS(C81)),"ok","FLAG"),"FLAG") -> ok
A82: GRUMA ev_ebitda_ntm | B82: =Detail_PeerAnalysis!C41 -> 5.6385558 | C82: 5.638556 | D82: =IF(ISNUMBER(B82),IF(ABS(B82-C82)<=0.000001*MAX(1,ABS(C82)),"ok","FLAG"),"FLAG") -> ok
A83: GRUMA pe_ltm | B83: =Detail_PeerAnalysis!E41 -> 9.3550208 | C83: 9.355021 | D83: =IF(ISNUMBER(B83),IF(ABS(B83-C83)<=0.000001*MAX(1,ABS(C83)),"ok","FLAG"),"FLAG") -> ok
A84: GRUMA pe_ntm | B84: =Detail_PeerAnalysis!F41 -> 9.7392544 | C84: 9.739254 | D84: =IF(ISNUMBER(B84),IF(ABS(B84-C84)<=0.000001*MAX(1,ABS(C84)),"ok","FLAG"),"FLAG") -> ok
A85: YMZ ev_ebitda_ltm | B85: =Detail_PeerAnalysis!B42 -> 6.0597144 | C85: 6.059714 | D85: =IF(ISNUMBER(B85),IF(ABS(B85-C85)<=0.000001*MAX(1,ABS(C85)),"ok","FLAG"),"FLAG") -> ok
A86: YMZ ev_ebitda_ntm | B86: =Detail_PeerAnalysis!C42 -> 5.8441554 | C86: 5.844155 | D86: =IF(ISNUMBER(B86),IF(ABS(B86-C86)<=0.000001*MAX(1,ABS(C86)),"ok","FLAG"),"FLAG") -> ok
A87: YMZ pe_ltm | B87: =Detail_PeerAnalysis!E42 -> 17.74 | C87: 17.74 | D87: =IF(ISNUMBER(B87),IF(ABS(B87-C87)<=0.000001*MAX(1,ABS(C87)),"ok","FLAG"),"FLAG") -> ok
A88: YMZ pe_ntm | B88: =Detail_PeerAnalysis!F42 -> 16.84 | C88: 16.84 | D88: =IF(ISNUMBER(B88),IF(ABS(B88-C88)<=0.000001*MAX(1,ABS(C88)),"ok","FLAG"),"FLAG") -> ok
A89: ARYN ev_ebitda_ltm | B89: =Detail_PeerAnalysis!B43 -> 8.3332366 | C89: 8.333237 | D89: =IF(ISNUMBER(B89),IF(ABS(B89-C89)<=0.000001*MAX(1,ABS(C89)),"ok","FLAG"),"FLAG") -> ok
A90: ARYN ev_ebitda_ntm | B90: =Detail_PeerAnalysis!C43 -> 5.8147036 | C90: 5.814704 | D90: =IF(ISNUMBER(B90),IF(ABS(B90-C90)<=0.000001*MAX(1,ABS(C90)),"ok","FLAG"),"FLAG") -> ok
A91: ARYN pe_ltm | B91: =Detail_PeerAnalysis!E43 -> 10.21 | C91: 10.21 | D91: =IF(ISNUMBER(B91),IF(ABS(B91-C91)<=0.000001*MAX(1,ABS(C91)),"ok","FLAG"),"FLAG") -> ok
A92: ARYN pe_ntm | B92: =Detail_PeerAnalysis!F43 -> 9.01 | C92: 9.01 | D92: =IF(ISNUMBER(B92),IF(ABS(B92-C92)<=0.000001*MAX(1,ABS(C92)),"ok","FLAG"),"FLAG") -> ok
A93: SJM ev_ebitda_ltm | B93: =Detail_PeerAnalysis!B44 -> 8.8754977 | C93: 8.875498 | D93: =IF(ISNUMBER(B93),IF(ABS(B93-C93)<=0.000001*MAX(1,ABS(C93)),"ok","FLAG"),"FLAG") -> ok
A94: SJM ev_ebitda_ntm | B94: =Detail_PeerAnalysis!C44 -> 9.2157465 | C94: 9.215747 | D94: =IF(ISNUMBER(B94),IF(ABS(B94-C94)<=0.000001*MAX(1,ABS(C94)),"ok","FLAG"),"FLAG") -> ok
A95: SJM pe_ltm | B95: =Detail_PeerAnalysis!E44 -> 58.63 | C95: 58.63 | D95: =IF(ISNUMBER(B95),IF(ABS(B95-C95)<=0.000001*MAX(1,ABS(C95)),"ok","FLAG"),"FLAG") -> ok
A96: SJM pe_ntm | B96: =Detail_PeerAnalysis!F44 -> 12.6 | C96: 12.6 | D96: =IF(ISNUMBER(B96),IF(ABS(B96-C96)<=0.000001*MAX(1,ABS(C96)),"ok","FLAG"),"FLAG") -> ok
A97: CPB ev_ebitda_ltm | B97: =Detail_PeerAnalysis!B45 -> 7.6631488 | C97: 7.663149 | D97: =IF(ISNUMBER(B97),IF(ABS(B97-C97)<=0.000001*MAX(1,ABS(C97)),"ok","FLAG"),"FLAG") -> ok
A98: CPB ev_ebitda_ntm | B98: =Detail_PeerAnalysis!C45 -> 8.3574722 | C98: 8.357472 | D98: =IF(ISNUMBER(B98),IF(ABS(B98-C98)<=0.000001*MAX(1,ABS(C98)),"ok","FLAG"),"FLAG") -> ok
A99: CPB pe_ltm | B99: =Detail_PeerAnalysis!E45 -> 15.11 | C99: 15.11 | D99: =IF(ISNUMBER(B99),IF(ABS(B99-C99)<=0.000001*MAX(1,ABS(C99)),"ok","FLAG"),"FLAG") -> ok
A100: CPB pe_ntm | B100: =Detail_PeerAnalysis!F45 -> 11.72 | C100: 11.72 | D100: =IF(ISNUMBER(B100),IF(ABS(B100-C100)<=0.000001*MAX(1,ABS(C100)),"ok","FLAG"),"FLAG") -> ok
A101: MDLZ ev_ebitda_ltm | B101: =Detail_PeerAnalysis!B46 -> 16.144293 | C101: 16.144293 | D101: =IF(ISNUMBER(B101),IF(ABS(B101-C101)<=0.000001*MAX(1,ABS(C101)),"ok","FLAG"),"FLAG") -> ok
A102: MDLZ ev_ebitda_ntm | B102: =Detail_PeerAnalysis!C46 -> 13.802618 | C102: 13.802618 | D102: =IF(ISNUMBER(B102),IF(ABS(B102-C102)<=0.000001*MAX(1,ABS(C102)),"ok","FLAG"),"FLAG") -> ok
A103: MDLZ pe_ltm | B103: =Detail_PeerAnalysis!E46 -> 23.1 | C103: 23.1 | D103: =IF(ISNUMBER(B103),IF(ABS(B103-C103)<=0.000001*MAX(1,ABS(C103)),"ok","FLAG"),"FLAG") -> ok
A104: MDLZ pe_ntm | B104: =Detail_PeerAnalysis!F46 -> 19.83 | C104: 19.83 | D104: =IF(ISNUMBER(B104),IF(ABS(B104-C104)<=0.000001*MAX(1,ABS(C104)),"ok","FLAG"),"FLAG") -> ok
A105: AC ev_ebitda_ltm | B105: =Detail_PeerAnalysis!B47 -> 7.8537991 | C105: 7.853799 | D105: =IF(ISNUMBER(B105),IF(ABS(B105-C105)<=0.000001*MAX(1,ABS(C105)),"ok","FLAG"),"FLAG") -> ok
A106: AC ev_ebitda_ntm | B106: =Detail_PeerAnalysis!C47 -> 7.1098612 | C106: 7.109861 | D106: =IF(ISNUMBER(B106),IF(ABS(B106-C106)<=0.000001*MAX(1,ABS(C106)),"ok","FLAG"),"FLAG") -> ok
A107: AC pe_ltm | B107: =Detail_PeerAnalysis!E47 -> 18.71 | C107: 18.71 | D107: =IF(ISNUMBER(B107),IF(ABS(B107-C107)<=0.000001*MAX(1,ABS(C107)),"ok","FLAG"),"FLAG") -> ok
A108: AC pe_ntm | B108: =Detail_PeerAnalysis!F47 -> 16.5 | C108: 16.5 | D108: =IF(ISNUMBER(B108),IF(ABS(B108-C108)<=0.000001*MAX(1,ABS(C108)),"ok","FLAG"),"FLAG") -> ok
A109: PEP ev_ebitda_ltm | B109: =Detail_PeerAnalysis!B48 -> 11.193831 | C109: 11.193831 | D109: =IF(ISNUMBER(B109),IF(ABS(B109-C109)<=0.000001*MAX(1,ABS(C109)),"ok","FLAG"),"FLAG") -> ok
A110: PEP ev_ebitda_ntm | B110: =Detail_PeerAnalysis!C48 -> 11.027248 | C110: 11.027248 | D110: =IF(ISNUMBER(B110),IF(ABS(B110-C110)<=0.000001*MAX(1,ABS(C110)),"ok","FLAG"),"FLAG") -> ok
...
