Workbook

Sheet LEEME
A1: Grupo Bimbo (BIMBOA) - Estados financieros consolidados 2021R-2030E
A2: Millones de MXN. Generado el 2026-10-19 con model/build/build_statements_workbook.py --lang es. Versión de trabajo en español; la oficial es la inglesa.
A4: Qué contiene
A5: ER, ORI, BG, FE y Capital: todos los renglones de los estados auditados, 2021R-2025R.
A6: Cuadres: vínculos entre estados y cada subtotal contra el reporte. Historia: todo en 0.
A7: Regiones: historia por región (nota de segmentos auditada), referencia para calibrar las tesis.
A8: La proyección es consolidada: no se proyecta ni se cuadra nada por región.
A9: Supuestos: 2026E = 9M26 real + 4T26, sobre la guía de Bimbo. El ER 2026E hasta la utilidad neta y la UPA se vincula aquí.
A10: FY2026E y FY2027E: ER, BG, FE, capital y ORI ligados a Supuestos; Cuadres debe mostrar OK en ambos. FY2028E-FY2030E siguen vacíos.
A12: Fuentes (número de página del PDF)
A13: 2023-2025: filings/annual/IA25_GB_EEFF_V10.pdf - BG p.12, ER p.13, ORI p.14, capital p.15, FE p.16.
A14: 2021-2022: filings/bmv/Reporte Anual 2023_XBRL_VF.PDF - BG p.256, ER p.257, ORI p.258, capital p.259, FE p.260.
... A34: Los insumos condensados del modelo (data/financials.csv) agrupan estos renglones; los totales coinciden con este libro.

Sheet ER
A1: Grupo Bimbo - Estado consolidado de resultados
A2: Operaciones continuas; 2021 reformulado por Ricolino (operación discontinuada desde 2022). Costos por función, como se reportan.
B3: Real (auditado) | G3: Proyección - el equipo proyecta y cuadra
A4: Millones de MXN | B4: 2021R | C4: 2022R | D4: 2023R | E4: 2024R | F4: 2025R | G4: 2026E | H4: 2027E | I4: 2028E | J4: 2029E | K4: 2030E | L4: Etiqueta | M4: Fuente / nota
A5: Operaciones continuas
A6: Ventas netas | B6: 338792 | C6: 398706 | D6: 399879 | E6: 408335 | F6: 426952 | G6: =Supuestos!B43 | H6: =Supuestos!B142 | L6: [sourced] | M6: RA23 p.257 (2021-22); IA25 p.13 (2023-25)
A7: Costo de ventas | B7: 157703 | C7: 193325 | D7: 194369 | E7: 193407 | F7: 203465 | G7: =Supuestos!B54 | H7: =Supuestos!B174 | L7: [sourced] | M7: RA23 p.257 (2021-22); IA25 p.13 (2023-25); Positivo = gasto
A8: Utilidad bruta | B8: =B6-B7 | C8: =C6-C7 | D8: =D6-D7 | E8: =E6-E7 | F8: =F6-F7 | G8: =G6-G7 | H8: =H6-H7 | I8: =I6-I7 | ... K8: =K6-K7 | L8: [calc]
A9: Gastos de distribución y venta | B9: 124422 | C9: 140455 | D9: 139477 | E9: 147628 | F9: 154866 | G9: =Supuestos!B60 | H9: =Supuestos!B237 | L9: [sourced] | M9: RA23 p.257 (2021-22); IA25 p.13 (2023-25)
A10: Gastos de administración | B10: 23147 | C10: 26172 | D10: 25860 | E10: 27536 | F10: 29023 | G10: =Supuestos!B61 | H10: =Supuestos!B238 | L10: [sourced] | M10: RA23 p.257 (2021-22); IA25 p.13 (2023-25)
A11: Gastos de integración | B11: 724 | C11: 367 | D11: 288 | E11: 317 | F11: 541 | G11: =Supuestos!B62 | H11: =Supuestos!B236 | L11: [sourced] | M11: RA23 p.257 (2021-22); IA25 p.13 (2023-25)
A12: Otros (ingresos) gastos, neto | B12: 216 | C12: -15309 | D12: 4430 | E12: 6298 | F12: 4911 | G12: =Supuestos!B56 | H12: =Supuestos!B235 | L12: [sourced] | M12: RA23 p.257 (2021-22); IA25 p.13 (2023-25); 2022 incluye la ganancia sin flujo de los planes de pensiones multipatronales (MEPP)
A13: Total de gastos generales | B13: =SUM(B9:B12) | C13: =SUM(C9:C12) | D13: =SUM(D9:D12) | E13: =SUM(E9:E12) | F13: =SUM(F9:F12) | G13: =SUM(G9:G12) | H13: =SUM(H9:H12) | I13: =SUM(I9:I12) | ... K13: =SUM(K9:K12) | L13: [calc]
A14: Utilidad de operación (EBIT) | B14: =B8-B13 | C14: =C8-C13 | D14: =D8-D13 | E14: =E8-E13 | F14: =F8-F13 | G14: =G8-G13 | H14: =H8-H13 | I14: =I8-I13 | ... K14: =K8-K13 | L14: [calc]
A16: Costo integral de financiamiento
A17: Intereses a cargo | B17: 7823 | C17: 8049 | D17: 10006 | E17: 13100 | F17: 14464 | G17: =Supuestos!B65 | H17: =Supuestos!B257 | L17: [sourced] | M17: RA23 p.257 (2021-22); IA25 p.13 (2023-25); Incluye intereses de arrendamientos (IFRS 16)
A18: Intereses ganados | B18: -363 | C18: -740 | D18: -809 | E18: -924 | F18: -897 | G18: 0 | H18: 0 | L18: [sourced] | M18: RA23 p.257 (2021-22); IA25 p.13 (2023-25); Negativo = ingreso (como en el reporte)
A19: Pérdida cambiaria, neta | B19: 538 | C19: 995 | D19: 1323 | E19: 506 | F19: 384 | G19: =Supuestos!B66 | H19: 0 | L19: [sourced] | M19: RA23 p.257 (2021-22); IA25 p.13 (2023-25)
A20: Pérdida (ganancia) por posición monetaria | B20: -25 | C20: -34 | D20: -73 | E20: -103 | F20: 50 | G20: =Supuestos!B67 | H20: =Supuestos!B258 | L20: [sourced] | M20: RA23 p.257 (2021-22); IA25 p.13 (2023-25)
A21: Total del costo integral de financiamiento | B21: =SUM(B17:B20) | C21: =SUM(C17:C20) | D21: =SUM(D17:D20) | E21: =SUM(E17:E20) | F21: =SUM(F17:F20) | G21: =SUM(G17:G20) | H21: =SUM(H17:H20) | I21: =SUM(I17:I20) | ... K21: =SUM(K17:K20) | L21: [calc]
A22: Participación en los resultados de compañías asociadas | B22: 247 | C22: 452 | D22: 316 | E22: 464 | F22: -2 | G22: =Supuestos!B68 | H22: =Supuestos!B259 | L22: [sourced] | M22: RA23 p.257 (2021-22); IA25 p.13 (2023-25)
A23: Utilidad antes de impuestos de operaciones continuas | B23: =B14-B21+B22 | C23: =C14-C21+C22 | D23: =D14-D21+D22 | E23: =E14-E21+E22 | F23: =F14-F21+F22 | G23: =G14-G21+G22 | H23: =H14-H21+H22 | I23: =I14-I21+I22 | ... K23: =K14-K21+K22 | L23: [calc]
A24: Impuestos a las ganancias | B24: 8726 | C24: 14381 | D24: 8386 | E24: 6797 | F24: 7197 | G24: =G23*Supuestos!B69 | H24: =H23*Supuestos!B260 | L24: [sourced] | M24: RA23 p.257 (2021-22); IA25 p.13 (2023-25)
A25: Utilidad neta de operaciones continuas | B25: =B23-B24 | C25: =C23-C24 | D25: =D23-D24 | E25: =E23-E24 | F25: =F23-F24 | G25: =G23-G24 | H25: =H23-H24 | I25: =I23-I24 | ... K25: =K23-K24 | L25: [calc]
A26: Utilidad neta de la operación discontinuada, después de impuestos | B26: 1254 | C26: 16988 | D26: -16 | E26: -194 | F26: 0 | G26: 0 | H26: 0 | L26: [sourced] | M26: RA23 p.257 (2021-22); IA25 p.13 (2023-25); Ricolino (vendida el 1-nov-2022)
A27: Utilidad neta consolidada | B27: =B25+B26 | C27: =C25+C26 | D27: =D25+D26 | E27: =E25+E26 | F27: =F25+F26 | G27: =G25+G26 | H27: =H25+H26 | I27: =I25+I26 | ... K27: =K25+K26 | L27: [calc]
A29: Atribución
A30: Participación no controladora | B30: 1466 | C30: 1575 | D30: 1445 | E30: 1499 | F30: 1813 | G30: =Supuestos!B70 | H30: =Supuestos!B261 | L30: [sourced] | M30: RA23 p.257 (2021-22); IA25 p.13 (2023-25); 2021-22 incluyen la participación no controladora discontinuada (30; 402)
A31: Participación controladora | B31: =B27-B30 | C31: =C27-C30 | D31: =D27-D30 | E31: =E27-E30 | F31: =F27-F30 | G31: =G27-G30 | H31: =H27-H30 | I31: =I27-I30 | ... K31: =K27-K30 | L31: [calc]
A32: Promedio ponderado de acciones (millones) | B32: 4487.268 | C32: 4448.693 | D32: 4418.137 | E32: 4357.25 | F32: 4310.531 | G32: =Supuestos!B71 | H32: =Supuestos!B71 | L32: [sourced] | M32: RA23 p.257 (2021-22); IA25 p.13 (2023-25); El reporte las presenta en miles; básica = diluida
A33: Utilidad básica por acción (MXN) | B33: =IFERROR(B31/B32,0) | C33: =IFERROR(C31/C32,0) | D33: =IFERROR(D31/D32,0) | E33: =IFERROR(E31/E32,0) | F33: =IFERROR(F31/F32,0) | G33: =IFERROR(G31/G32,0) | H33: =IFERROR(H31/H32,0) | I33: =IFERROR(I31/I32,0) | ... K33: =IFERROR(K31/K32,0) | L33: [calc]
A35: Memorándum
A36: Depreciación y amortización, operaciones continuas (nota de segmentos) | B36: 16126 | C36: 18038 | D36: 18929 | E36: 23051 | F36: 24838 | G36: =Supuestos!B55 | H36: =Supuestos!B239 | L36: [sourced] | M36: RA23 p.358-359; IA25 p.85-86 (data/financials.csv)
A37: EBITDA (EBIT + depreciación y amortización) | B37: =B14+B36 | C37: =C14+C36 | D37: =D14+D36 | E37: =E14+E36 | F37: =F14+F36 | G37: =G14+G36 | H37: =H14+H36 | I37: =I14+I36 | ... K37: =K14+K36 | L37: [calc]
A38: Deterioro y otras partidas que no generan flujo (nota de segmentos) | B38: =Regiones!B42+Regiones!B50 | C38: =Regiones!C42+Regiones!C50 | D38: =Regiones!D42+Regiones!D50 | E38: =Regiones!E42+Regiones!E50 | F38: =Regiones!F42+Regiones!F50 | G38: 0 | H38: 0 | L38: [calc] | M38: Principalmente ajustes de planes de pensiones multipatronales (MEPP)
A39: UAFIDA Ajustada (definición de la empresa) | B39: =B14+B36+B38 | C39: =C14+C36+C38 | D39: =D14+D36+D38 | E39: =E14+E36+E38 | F39: =F14+F36+F38 | G39: =G14+G36+G38 | H39: =H14+H36+H38 | I39: =I14+I36+I38 | ... K39: =K14+K36+K38 | L39: [calc] | M39: Definición de la empresa; en la historia cuadra con la nota de segmentos

Sheet Supuestos
A1: Grupo Bimbo - Supuestos 2026E
A2: 2026 = 9M26 real + estimación del 4T26, anclado en la guía 2026 de Bimbo. La opción A alimenta el ER; la opción B es la comprobación.
A4: Millones de MXN | B4: 1T26 | C4: 2T26 | D4: 3T26 | E4: 9M26 | F4: Etiqueta | G4: Fuente / nota
A5: 2026 real por trimestre (reportes trimestrales)
A6: Ventas netas | B6: 100319 | C6: 105026 | D6: 106061 | E6: =SUM(B6:D6) | F6: [sourced] | G6: Reportes trimestrales, filings/quarterly: 1T26 p.9, 2T26 p.8, 3T26 p.8 (estado de resultados)
A7: Costo de ventas | B7: 47662 | C7: 49771 | D7: 49762 | E7: =SUM(B7:D7) | F7: [sourced] | G7: Reportes trimestrales, filings/quarterly: 1T26 p.9, 2T26 p.8, 3T26 p.8 (estado de resultados)
A8: Utilidad bruta | B8: =B6-B7 | C8: =C6-C7 | D8: =D6-D7 | E8: =E6-E7 | F8: [calc]
A9: Gastos generales | B9: 44282 | C9: 45378 | D9: 45052 | E9: =SUM(B9:D9) | F9: [sourced] | G9: Reportes trimestrales, filings/quarterly: 1T26 p.9, 2T26 p.8, 3T26 p.8 (estado de resultados); distribución y venta + administración + integración
A10: Otros (ingresos) gastos, neto | B10: 463 | C10: 1049 | D10: 857 | E10: =SUM(B10:D10) | F10: [sourced] | G10: Reportes trimestrales, filings/quarterly: 1T26 p.9, 2T26 p.8, 3T26 p.8 (estado de resultados)
A11: Utilidad de operación | B11: =B8-B9-B10 | C11: =C8-C9-C10 | D11: =D8-D9-D10 | E11: =E8-E9-E10 | F11: [calc] | G11: Suma de renglones; los reportes imprimen 7,911 / 8,827 / 10,390 (redondeo)
A12: UAFIDA Ajustada | B12: 14036 | C12: 15113 | D12: 16644 | E12: =SUM(B12:D12) | F12: [sourced] | G12: Reportes trimestrales, filings/quarterly: 1T26 p.9, 2T26 p.8, 3T26 p.8 (estado de resultados)
A13: Depreciación, amortización, deterioro y partidas sin flujo (UAFIDA - EBIT) | B13: =B12-B11 | C13: =C12-C11 | D13: =D12-D11 | E13: =E12-E11 | F13: [calc]
A14: Ventas netas, mismo trimestre de 2025 | B14: 103448 | C14: 107389 | D14: 107427 | E14: =SUM(B14:D14) | F14: [sourced] | G14: Comparativos: 1T26 p.3, 2T26 p.3, 3T26 p.3 (3T25 reexpresado desde 107,421)
A15: UAFIDA Ajustada, mismo trimestre de 2025 | B15: 12797 | C15: 14890 | D15: 15776 | E15: =SUM(B15:D15) | F15: [sourced] | G15: Comparativos en los reportes de 2026 (página del estado de resultados)
A16: Margen bruto | B16: =B8/B6 | C16: =C8/C6 | D16: =D8/D6 | E16: =E8/E6 | F16: [calc]
A17: Gastos generales / ventas netas | B17: =B9/B6 | C17: =C9/C6 | D17: =D9/D6 | E17: =E9/E6 | F17: [calc]
A18: Otros gastos / ventas netas | B18: =B10/B6 | C18: =C10/C6 | D18: =D10/D6 | E18: =E10/E6 | F18: [calc]
A19: Depreciación y partidas sin flujo / ventas netas | B19: =B13/B6 | C19: =C13/C6 | D19: =D13/D6 | E19: =E13/E6 | F19: [calc]
A20: Margen UAFIDA Ajustada | B20: =B12/B6 | C20: =C12/C6 | D20: =D12/D6 | E20: =E12/E6 | F20: [calc]
A21: Crecimiento de ventas netas en MXN | B21: =B6/B14-1 | C21: =C6/C14-1 | D21: =D6/D14-1 | E21: =E6/E14-1 | F21: [calc]
A22: Intereses pagados netos | B22: 3273 | C22: 3292 | D22: 2829 | E22: =SUM(B22:D22) | F22: [sourced] | G22: Reportes trimestrales, filings/quarterly: 1T26 p.9, 2T26 p.8, 3T26 p.8 (estado de resultados)
A23: Pérdida (ganancia) cambiaria, neta | B23: 189 | C23: 227 | D23: 194 | E23: =SUM(B23:D23) | F23: [sourced] | G23: Reportes trimestrales, filings/quarterly: 1T26 p.9, 2T26 p.8, 3T26 p.8 (estado de resultados)
A24: Pérdida (ganancia) por posición monetaria | B24: 0 | C24: -56 | D24: 119 | E24: =SUM(B24:D24) | F24: [sourced] | G24: Reportes trimestrales, filings/quarterly: 1T26 p.9, 2T26 p.8, 3T26 p.8 (estado de resultados)
A25: Participación en los resultados de compañías asociadas | B25: -7 | C25: 42 | D25: 1 | E25: =SUM(B25:D25) | F25: [sourced] | G25: Reportes trimestrales, filings/quarterly: 1T26 p.9, 2T26 p.8, 3T26 p.8 (estado de resultados)
A26: Utilidad antes de impuestos (según el reporte) | B26: 4443 | C26: 5406 | D26: 7249 | E26: =SUM(B26:D26) | F26: [sourced] | G26: Reportes trimestrales, filings/quarterly: 1T26 p.9, 2T26 p.8, 3T26 p.8 (estado de resultados)
A27: Utilidad antes de impuestos, suma de renglones | B27: =B11-B22-B23-B24+B25 | C27: =C11-C22-C23-C24+C25 | D27: =D11-D22-D23-D24+D25 | E27: =E11-E22-E23-E24+E25 | F27: [calc] | G27: Difiere del reporte por redondeo
A28: Impuestos a las ganancias | B28: 1644 | C28: 2000 | D28: 2682 | E28: =SUM(B28:D28) | F28: [sourced] | G28: Reportes trimestrales, filings/quarterly: 1T26 p.9, 2T26 p.8, 3T26 p.8 (estado de resultados)
A29: Tasa efectiva de impuestos | B29: =B28/B26 | C29: =C28/C26 | D29: =D28/D26 | E29: =E28/E26 | F29: [calc]
A30: Participación no controladora | B30: 437 | C30: 471 | D30: 458 | E30: =SUM(B30:D30) | F30: [sourced] | G30: Reportes trimestrales, filings/quarterly: 1T26 p.9, 2T26 p.8, 3T26 p.8 (estado de resultados)
A32: Supuestos 2026E (valor en la columna B)
A33: Ventas netas 2025 | B33: =ER!F6 | F33: [sourced] | G33: Estado de resultados
A34: Ventas netas 4T25 | B34: 108688 | F34: [sourced] | G34: Reporte 4T25 p.4
A35: UAFIDA Ajustada 4T25 | B35: =ER!F39-E15 | F35: [calc] | G35: 2025 menos 9M25
A36: Crecimiento de ventas 4T26 sin efecto cambiario | B36: 0.05 | F36: [assumption] | G36: Equipo: guía de 'un dígito medio' tomada literal para el último trimestre (presentación 3T26 p.26)
A37: Ventas netas México 2025 (después de eliminaciones entre segmentos) | B37: 140360 | F37: [sourced] | G37: Nota de segmentos, IA25 p.85
A38: Participación de México en ventas netas | B38: =B37/B33 | F38: [calc] | G38: Se genera en pesos; el resto se convierte (cerca de 2/3 en el extranjero, llamada 2026-02-25 p.7)
A39: Tipo de cambio USD/MXN promedio 4T25 | B39: 18.3041 | F39: [calc] | G39: Promedio de cierres diarios oct-dic 2025, data/market/usdmxn_daily_2025-01_2026-10.csv
A40: Tipo de cambio USD/MXN promedio 4T26 | B40: 18.5769 | F40: [assumption] | G40: Cierres de octubre 2026 al 23-oct más la cotización del 23-oct fija para los días hábiles restantes (tipo de cambio de mercado, decisión del equipo)
A41: Factor de conversión cambiaria 4T26 vs 4T25 | B41: =B38+(1-B38)*B40/B39 | F41: [calc] | G41: USD/MXN como aproximación de todas las monedas extranjeras, igual que en la guía de Bimbo
A42: Ventas netas 4T26 | B42: =B34*(1+B36)*B41 | F42: [calc]
A43: Ventas netas 2026E | B43: =E6+B42 | F43: [calc] | G43: 9M26 real + 4T26
A44: Crecimiento de ventas netas 2026E en MXN | B44: =B43/B33-1 | F44: [calc] | G44: Guía: entre plano y caída de un dígito bajo en MXN
A45: Margen UAFIDA Ajustada 2025 | B45: =ER!F39/ER!F6 | F45: [calc]
A46: Expansión de margen, punto medio de la guía | B46: 0.01025 | F46: [guidance] | G46: +85 a +120 pb; filings/quarterly/GB_Investor_PPT_3Q26.pdf p.26
A47: Menos ganancia extraordinaria por la participación en La Moderna | B47: -0.00115 | F47: [guidance] | G47: 10-13 pb del margen 2026, punto medio; llamada 2026-04-29 p.7 (excluida por decisión del equipo)
A48: Margen UAFIDA Ajustada 2026E | B48: =B45+B46+B47 | F48: [calc]
A49: UAFIDA Ajustada 2026E | B49: =B43*B48 | F49: [calc]
A50: Margen UAFIDA Ajustada implícito 4T26 | B50: =(B49-E12)/B42 | F50: [calc] | G50: Comparar con 4T25
A51: Margen UAFIDA Ajustada 4T25 | B51: =B35/B34 | F51: [calc]
A53: Opción A: ER 2026E (margen bruto 9M26; gastos generales cuadran hacia la guía)
A54: Costo de ventas | B54: =B43*(1-E16) | F54: [calc] | G54: Margen bruto 9M26
A55: Depreciación, amortización y partidas sin flujo | B55: =B43*E19 | F55: [calc] | G55: Proporción 9M26 de (UAFIDA - EBIT); va al renglón de depreciación del memorándum del ER
A56: Otros (ingresos) gastos, neto | B56: =B43*E18 | F56: [calc] | G56: Proporción 9M26
A57: Utilidad de operación | B57: =B49-B55 | F57: [calc]
A58: Gastos generales (renglón de cuadre) | B58: =B43-B54-B56-B57 | F58: [calc]
A59: Gastos generales / ventas netas | B59: =B58/B43 | F59: [calc] | G59: Comparar con 9M26
A60: Distribución y venta | B60: =B58*ER!F9/(ER!F9+ER!F10+ER!F11) | F60: [calc] | G60: Reparto 2025 de los gastos generales
A61: Administración | B61: =B58*ER!F10/(ER!F9+ER!F10+ER!F11) | F61: [calc] | G61: Reparto 2025 de los gastos generales
A62: Integración | B62: =B58*ER!F11/(ER!F9+ER!F10+ER!F11) | F62: [calc] | G62: Reparto 2025 de los gastos generales
A64: 2026E abajo de la utilidad de operación (decisiones del equipo 2026-10-23)
A65: Intereses pagados netos | B65: =E22+D22 | F65: [assumption] | G65: 9M26 real + 4T26 = 3T26; el director de finanzas dijo que el nivel del 3T26 quizá no se mantenga (llamada 3T26). Los reportes solo dan intereses netos: intereses ganados del ER 2026E = 0
A66: Pérdida (ganancia) cambiaria, neta | B66: =E23*4/3 | F66: [assumption] | G66: 9M26 real + 4T26 al promedio trimestral de 9M26
A67: Pérdida (ganancia) por posición monetaria | B67: =E24*4/3 | F67: [assumption] | G67: 9M26 real + 4T26 al promedio trimestral de 9M26
A68: Participación en los resultados de compañías asociadas | B68: =E25*4/3 | F68: [assumption] | G68: 9M26 real + 4T26 al promedio trimestral de 9M26
A69: Tasa efectiva de impuestos | B69: 0.37 | F69: [assumption] | G69: 9M26 = 37.0%, la estimación de Bimbo de su tasa anual (NIC 34); no se proyecta la tasa más baja del 4T de 2024-25
A70: Participación no controladora | B70: =E30*4/3 | F70: [assumption] | G70: 9M26 real + 4T26 al promedio trimestral de 9M26
A71: Promedio ponderado de acciones (millones) | B71: 4304.7441 | F71: [assumption] | G71: Acciones en circulación al 31-dic-2025, 4,304,744,119 (EEFF25 p.80): el punto de partida de 2026; no se restan las recompras de 2026 (20 millones de acciones en el 3T26, llamada 3T26)
A73: Balance y flujo 2026E (decisiones del equipo 2026-10-23)
A74: USD/MXN promedio 9M26 | B74: 17.4031 | F74: [calc] | G74: Promedio de cierres diarios ene-sep 2026, data/market/usdmxn_daily_2025-01_2026-10.csv
A75: USD/MXN promedio 2026E | B75: =(3*B74+B40)/4 | F75: [calc] | G75: Tres trimestres al promedio 9M26 y uno al 4T26
A76: Capex 2026E (millones de US$) | B76: 1050 | F76: [guidance] | G76: Punto medio de US$1.0-1.1 mil millones del director de finanzas (llamada 3T26); presentación US$1.0-1.2 mil millones (GB_Investor_PPT_3Q26 p.26)
A77: Capex 2026E | B77: =B76*B75 | F77: [calc] | G77: Compras de propiedades, planta y equipo en el FE
A78: Depreciación de derechos de uso | B78: 6142 | F78: [assumption] | G78: 2025 (EEFF25 p.41); derechos de uso y pasivo por arrendamiento al nivel de 2025: los contratos nuevos reemplazan a los que vencen
A79: Intereses por arrendamiento | B79: 2137 | F79: [assumption] | G79: 2025 (EEFF25 p.43); se pagan dentro de los pagos de arrendamiento
A80: Amortización de intangibles | B80: 2175 | F80: [assumption] | G80: 2025 (EEFF25 p.45); sin compras de intangibles
A81: Depreciación de propiedades, planta y equipo y otras partidas sin flujo | B81: =B55-B78-B80 | F81: [calc] | G81: Depreciación del ER menos depreciación de derechos de uso y amortización
A82: Días de cobro (promedio FY2021-FY2025, sobre ventas netas) | B82: =AVERAGE(BG!B7/ER!B6*365,BG!C7/ER!C6*365,BG!D7/ER!D6*365,BG!E7/ER!E6*365,BG!F7/ER!F6*365) | F82: [calc] | G82: Equipo 2026-10-25: estables en 29-33 días en FY2021-FY2025, se usa el promedio
A83: Días de inventario (2025, sobre costo de ventas) | B83: =BG!F8/ER!F7*365 | F83: [calc] | G83: Igual que en 2025
A84: Días de proveedores (2025, sobre costo de ventas) | B84: =BG!F26/ER!F7*365 | F84: [calc] | G84: Igual que en 2025
A85: Deuda a corto plazo al 30-sep-2026 | B85: 13636 | F85: [sourced] | G85: Reporte 3T26 p.8
A86: Deuda a largo plazo al 30-sep-2026 | B86: 139166 | F86: [sourced] | G86: Reporte 3T26 p.8
A87: Préstamos bancarios que vencen en el resto de 2026 (millones de US$) | B87: 87 | F87: [sourced] | G87: Perfil de amortización, reporte 3T26 p.6
A88: USD/MXN del perfil de amortización | B88: 17.84 | F88: [sourced] | G88: Reporte 3T26 p.6, nota 11
A89: Vencimiento 2026 pagado en el 4T26 | B89: =B87*B88 | F89: [assumption] | G89: Solo el vencimiento contractual; sin prepagos ni deuda nueva; el efectivo es el resultado
A90: Dividendo por acción 2026 (MXN) | B90: 1.075 | F90: [sourced] | G90: Aviso BMV 30-abr-2026 (bmv.com.mx/docs-pub/derechos/derechos_1554405_1.pdf), pagado el 13-may-2026
A91: Dividendos decretados, controladora | B91: =B90*B71 | F91: [calc] | G91: Sobre las acciones en circulación al 31-dic-2025
A92: Dividendos a la participación no controladora | B92: 135 | F92: [assumption] | G92: 2025 (estado de variaciones en el capital)
A93: Devuelto a los accionistas 9M26 (dividendos + recompras) | B93: 6000 | F93: [guidance] | G93: Director de finanzas: 'devolver 6 mil millones de pesos' (llamada 3T26, aproximado)
A94: Recompra de acciones 3T26 | B94: 1200 | F94: [guidance] | G94: CFO: 20 millones de acciones, cerca de 1,200 millones de pesos en el trimestre (llamada 3T26)
A95: Recompra de acciones 2026E | B95: =B93-B91+B94 | F95: [assumption] | G95: Equipo 2026-10-25: implícito 9M26 + 4T26 al ritmo del 3T26 (CFO: el programa continúa, llamada 3T26)
A97: Comprobación opción B: todas las proporciones de 9M26
A98: Utilidad de operación | B98: =B43*(E16-E17-E18) | F98: [calc]
A99: UAFIDA Ajustada | B99: =B98+B55 | F99: [calc]
A100: Margen UAFIDA Ajustada | B100: =B99/B43 | F100: [calc]
A101: Diferencia B - A | B101: =B99-B49 | F101: [calc]
A102: Diferencia B - A (pb de ventas netas) | B102: =B101/B43*10000 | F102: [calc] | G102: Una diferencia pequeña indica que la guía es consistente con 9M26
A104: Ventas netas FY2027E por región: crecimiento orgánico = ratio x crecimiento del PIB nominal (decisiones del equipo 2026-10-25)
A105: Ventas netas por trimestre, Norteamérica | B105: 40533 | C105: 44368 | D105: 44241 | E105: =SUM(B105:D105) | F105: [sourced] | G105: Rep. 1T26 p.3, 2T26 p.3, 3T26 p.3 (antes de eliminaciones entre regiones)
A106: Ventas netas por trimestre, México | B106: 39726 | C106: 40279 | D106: 40905 | E106: =SUM(B106:D106) | F106: [sourced] | G106: Rep. 1T26 p.3, 2T26 p.3, 3T26 p.3 (antes de eliminaciones entre regiones)
A107: Ventas netas por trimestre, Latinoamérica | B107: 11545 | C107: 11620 | D107: 12047 | E107: =SUM(B107:D107) | F107: [sourced] | G107: Rep. 1T26 p.3, 2T26 p.3, 3T26 p.3 (antes de eliminaciones entre regiones)
...

Sheet Regiones
A1: Grupo Bimbo - Ventas netas y UAFIDA Ajustada por región (historia)
A2: Nota de segmentos auditada, solo como referencia para calibrar las tesis. No se proyecta ni se cuadra por región.
B3: Real (auditado) | G3: Proyección - el equipo proyecta y cuadra
A4: Millones de MXN | B4: 2021R | C4: 2022R | D4: 2023R | E4: 2024R | F4: 2025R | G4: 2026E | H4: 2027E | I4: 2028E | J4: 2029E | K4: 2030E | L4: Etiqueta | M4: Fuente / nota
A5: Ventas netas por región (antes de eliminaciones entre segmentos)
A6: México | B6: 109089 | C6: 130401 | D6: 145387 | E6: 151164 | F6: 154809 | L6: [sourced] | M6: Nota de segmentos: RA23 p.359 (2021), p.358 (2022); IA25 p.86 (2023-24), p.85 (2025)
A7: Norteamérica | B7: 175369 | C7: 205674 | D7: 192534 | E7: 189330 | F7: 190211 | L7: [sourced] | M7: Nota de segmentos: RA23 p.359 (2021), p.358 (2022); IA25 p.86 (2023-24), p.85 (2025)
A8: Latinoamérica | B8: 31109 | C8: 38411 | D8: 36647 | E8: 39879 | F8: 44120 | L8: [sourced] | M8: Nota de segmentos: RA23 p.359 (2021), p.358 (2022); IA25 p.86 (2023-24), p.85 (2025)
A9: Europa, Asia y África (EAA) | B9: 34195 | C9: 37536 | D9: 40545 | E9: 45044 | F9: 54214 | L9: [sourced] | M9: Nota de segmentos: RA23 p.359 (2021), p.358 (2022); IA25 p.86 (2023-24), p.85 (2025)
A10: Eliminaciones entre segmentos | B10: -10970 | C10: -13316 | D10: -15234 | E10: -17082 | F10: -16402 | L10: [sourced] | M10: Nota de segmentos: RA23 p.359 (2021), p.358 (2022); IA25 p.86 (2023-24), p.85 (2025)
A11: Ventas netas consolidadas | B11: =SUM(B6:B10) | C11: =SUM(C6:C10) | D11: =SUM(D6:D10) | E11: =SUM(E6:E10) | F11: =SUM(F6:F10) | L11: [calc] | M11: Igual a las ventas netas del ER
A13: Crecimiento de ventas netas (en MXN, incluye efecto cambiario)
A14: México | C14: =IFERROR(C6/B6-1,0) | D14: =IFERROR(D6/C6-1,0) | E14: =IFERROR(E6/D6-1,0) | F14: =IFERROR(F6/E6-1,0) | L14: [calc]
A15: Norteamérica | C15: =IFERROR(C7/B7-1,0) | D15: =IFERROR(D7/C7-1,0) | E15: =IFERROR(E7/D7-1,0) | F15: =IFERROR(F7/E7-1,0) | L15: [calc]
A16: Latinoamérica | C16: =IFERROR(C8/B8-1,0) | D16: =IFERROR(D8/C8-1,0) | E16: =IFERROR(E8/D8-1,0) | F16: =IFERROR(F8/E8-1,0) | L16: [calc]
A17: Europa, Asia y África (EAA) | C17: =IFERROR(C9/B9-1,0) | D17: =IFERROR(D9/C9-1,0) | E17: =IFERROR(E9/D9-1,0) | F17: =IFERROR(F9/E9-1,0) | L17: [calc]
A18: Ventas netas consolidadas | C18: =IFERROR(C11/B11-1,0) | D18: =IFERROR(D11/C11-1,0) | E18: =IFERROR(E11/D11-1,0) | F18: =IFERROR(F11/E11-1,0) | L18: [calc]
A20: Utilidad de operación por región
A21: México | B21: 16731 | C21: 18824 | D21: 21882 | E21: 23726 | F21: 23442 | L21: [sourced] | M21: Nota de segmentos: RA23 p.359 (2021), p.358 (2022); IA25 p.86 (2023-24), p.85 (2025)
A22: Norteamérica | B22: 15171 | C22: 33263 | D22: 11175 | E22: 5920 | F22: 6272 | L22: [sourced] | M22: Nota de segmentos: RA23 p.359 (2021), p.358 (2022); IA25 p.86 (2023-24), p.85 (2025)
A23: Latinoamérica | B23: 78 | C23: 1087 | D23: 1294 | E23: 1191 | F23: 607 | L23: [sourced] | M23: Nota de segmentos: RA23 p.359 (2021), p.358 (2022); IA25 p.86 (2023-24), p.85 (2025)
A24: Europa, Asia y África (EAA) | B24: 292 | C24: -486 | D24: 326 | E24: 1227 | F24: 2498 | L24: [sourced] | M24: Nota de segmentos: RA23 p.359 (2021), p.358 (2022); IA25 p.86 (2023-24), p.85 (2025)
A25: Eliminaciones (regalías intercompañía) | B25: 308 | C25: 1008 | D25: 778 | E25: 1085 | F25: 1327 | L25: [sourced] | M25: Nota de segmentos: RA23 p.359 (2021), p.358 (2022); IA25 p.86 (2023-24), p.85 (2025)
A26: Total | B26: =SUM(B21:B25) | C26: =SUM(C21:C25) | D26: =SUM(D21:D25) | E26: =SUM(E21:E25) | F26: =SUM(F21:F25) | L26: [calc] | M26: Igual a la utilidad de operación del ER
A28: Depreciación y amortización por región
A29: México | B29: 3907 | C29: 4424 | D29: 5524 | E29: 6895 | F29: 7859 | L29: [sourced] | M29: Nota de segmentos: RA23 p.359 (2021), p.358 (2022); IA25 p.86 (2023-24), p.85 (2025)
A30: Norteamérica | B30: 8470 | C30: 9248 | D30: 8946 | E30: 10878 | F30: 10793 | L30: [sourced] | M30: Nota de segmentos: RA23 p.359 (2021), p.358 (2022); IA25 p.86 (2023-24), p.85 (2025)
A31: Latinoamérica | B31: 1687 | C31: 2278 | D31: 2215 | E31: 2507 | F31: 2945 | L31: [sourced] | M31: Nota de segmentos: RA23 p.359 (2021), p.358 (2022); IA25 p.86 (2023-24), p.85 (2025)
A32: Europa, Asia y África (EAA) | B32: 2062 | C32: 2088 | D32: 2244 | E32: 2772 | F32: 3241 | L32: [sourced] | M32: Nota de segmentos: RA23 p.359 (2021), p.358 (2022); IA25 p.86 (2023-24), p.85 (2025)
A33: Eliminaciones | B33: 0 | C33: 0 | D33: 0 | E33: -1 | F33: 0 | L33: [sourced] | M33: Nota de segmentos: RA23 p.359 (2021), p.358 (2022); IA25 p.86 (2023-24), p.85 (2025)
A34: Total | B34: =SUM(B29:B33) | C34: =SUM(C29:C33) | D34: =SUM(D29:D33) | E34: =SUM(E29:E33) | F34: =SUM(F29:F33) | L34: [calc] | M34: Igual a la depreciación y amortización del memorándum del ER
A36: Deterioro (reversión) de activos de larga duración por región
A37: México | B37: 133 | C37: 72 | D37: 78 | E37: 141 | F37: 329 | L37: [sourced] | M37: Nota de segmentos: RA23 p.359 (2021), p.358 (2022); IA25 p.86 (2023-24), p.85 (2025)
A38: Norteamérica | B38: 57 | C38: -890 | D38: -79 | E38: -4 | F38: 25 | L38: [sourced] | M38: Nota de segmentos: RA23 p.359 (2021), p.358 (2022); IA25 p.86 (2023-24), p.85 (2025)
A39: Latinoamérica | B39: 142 | C39: 46 | D39: 22 | E39: -101 | F39: 0 | L39: [sourced] | M39: Nota de segmentos: RA23 p.359 (2021), p.358 (2022); IA25 p.86 (2023-24), p.85 (2025)
A40: Europa, Asia y África (EAA) | B40: 350 | C40: 1024 | D40: 362 | E40: 213 | F40: 91 | L40: [sourced] | M40: Nota de segmentos: RA23 p.359 (2021), p.358 (2022); IA25 p.86 (2023-24), p.85 (2025)
A41: Eliminaciones | B41: 0 | C41: 0 | D41: 0 | E41: 0 | F41: 0 | L41: [sourced] | M41: Nota de segmentos: RA23 p.359 (2021), p.358 (2022); IA25 p.86 (2023-24), p.85 (2025)
A42: Total | B42: =SUM(B37:B41) | C42: =SUM(C37:C41) | D42: =SUM(D37:D41) | E42: =SUM(E37:E41) | F42: =SUM(F37:F41) | L42: [calc]
A44: Otras partidas que no generan flujo por región (principalmente MEPP)
A45: México | B45: 0 | C45: 0 | D45: 0 | E45: 0 | F45: 0 | L45: [sourced] | M45: Nota de segmentos: RA23 p.359 (2021), p.358 (2022); IA25 p.86 (2023-24), p.85 (2025)
A46: Norteamérica | B46: -2246 | C46: -19010 | D46: 175 | E46: -982 | F46: 27 | L46: [sourced] | M46: Nota de segmentos: RA23 p.359 (2021), p.358 (2022); IA25 p.86 (2023-24), p.85 (2025)
A47: Latinoamérica | B47: 19 | C47: 22 | D47: 0 | E47: 6 | F47: 0 | L47: [sourced] | M47: Nota de segmentos: RA23 p.359 (2021), p.358 (2022); IA25 p.86 (2023-24), p.85 (2025)
A48: Europa, Asia y África (EAA) | B48: 0 | C48: 0 | D48: 0 | E48: 0 | F48: 0 | L48: [sourced] | M48: Nota de segmentos: RA23 p.359 (2021), p.358 (2022); IA25 p.86 (2023-24), p.85 (2025)
A49: Eliminaciones | B49: 211 | C49: 448 | D49: 0 | E49: 0 | F49: 0 | L49: [sourced] | M49: Nota de segmentos: RA23 p.359 (2021), p.358 (2022); IA25 p.86 (2023-24), p.85 (2025)
A50: Total | B50: =SUM(B45:B49) | C50: =SUM(C45:C49) | D50: =SUM(D45:D49) | E50: =SUM(E45:E49) | F50: =SUM(F45:F49) | L50: [calc]
A52: UAFIDA Ajustada por región (utilidad de operación + depreciación y amortización + deterioro + partidas sin flujo)
A53: México | B53: =B21+B29+B37+B45 | C53: =C21+C29+C37+C45 | D53: =D21+D29+D37+D45 | E53: =E21+E29+E37+E45 | F53: =F21+F29+F37+F45 | L53: [calc]
A54: Norteamérica | B54: =B22+B30+B38+B46 | C54: =C22+C30+C38+C46 | D54: =D22+D30+D38+D46 | E54: =E22+E30+E38+E46 | F54: =F22+F30+F38+F46 | L54: [calc]
A55: Latinoamérica | B55: =B23+B31+B39+B47 | C55: =C23+C31+C39+C47 | D55: =D23+D31+D39+D47 | E55: =E23+E31+E39+E47 | F55: =F23+F31+F39+F47 | L55: [calc]
A56: Europa, Asia y África (EAA) | B56: =B24+B32+B40+B48 | C56: =C24+C32+C40+C48 | D56: =D24+D32+D40+D48 | E56: =E24+E32+E40+E48 | F56: =F24+F32+F40+F48 | L56: [calc]
A57: Eliminaciones (regalías intercompañía) | B57: =B25+B33+B41+B49 | C57: =C25+C33+C41+C49 | D57: =D25+D33+D41+D49 | E57: =E25+E33+E41+E49 | F57: =F25+F33+F41+F49 | L57: [calc]
A58: UAFIDA Ajustada total | B58: =SUM(B53:B57) | C58: =SUM(C53:C57) | D58: =SUM(D53:D57) | E58: =SUM(E53:E57) | F58: =SUM(F53:F57) | L58: [calc] | M58: Igual a la UAFIDA Ajustada del ER (EBIT + depreciación y amortización + partidas sin flujo)
A60: Margen de UAFIDA Ajustada sobre ventas netas de cada región
A61: México | B61: =IFERROR(B53/B6,0) | C61: =IFERROR(C53/C6,0) | D61: =IFERROR(D53/D6,0) | E61: =IFERROR(E53/E6,0) | F61: =IFERROR(F53/F6,0) | L61: [calc] | M61: Misma base que los reportes trimestrales
A62: Norteamérica | B62: =IFERROR(B54/B7,0) | C62: =IFERROR(C54/C7,0) | D62: =IFERROR(D54/D7,0) | E62: =IFERROR(E54/E7,0) | F62: =IFERROR(F54/F7,0) | L62: [calc] | M62: Misma base que los reportes trimestrales
A63: Latinoamérica | B63: =IFERROR(B55/B8,0) | C63: =IFERROR(C55/C8,0) | D63: =IFERROR(D55/D8,0) | E63: =IFERROR(E55/E8,0) | F63: =IFERROR(F55/F8,0) | L63: [calc] | M63: Misma base que los reportes trimestrales
A64: Europa, Asia y África (EAA) | B64: =IFERROR(B56/B9,0) | C64: =IFERROR(C56/C9,0) | D64: =IFERROR(D56/D9,0) | E64: =IFERROR(E56/E9,0) | F64: =IFERROR(F56/F9,0) | L64: [calc] | M64: Misma base que los reportes trimestrales
A65: Consolidado | B65: =IFERROR(B58/B11,0) | C65: =IFERROR(C58/C11,0) | D65: =IFERROR(D58/D11,0) | E65: =IFERROR(E58/E11,0) | F65: =IFERROR(F58/F11,0) | L65: [calc]

Sheet ORI
A1: Grupo Bimbo - Estado consolidado de otros resultados integrales
A2: Como se reporta. Positivo = utilidad.
B3: Real (auditado) | G3: Proyección - el equipo proyecta y cuadra
A4: Millones de MXN | B4: 2021R | C4: 2022R | D4: 2023R | E4: 2024R | F4: 2025R | G4: 2026E | H4: 2027E | I4: 2028E | J4: 2029E | K4: 2030E | L4: Etiqueta | M4: Fuente / nota
A5: Utilidad neta consolidada | B5: 17382 | C5: 48485 | D5: 16922 | E5: 14043 | F5: 12946 | G5: =ER!G27 | H5: =ER!H27 | L5: [sourced] | M5: RA23 p.258 (2021-22); IA25 p.14 (2023-25); Debe ser igual a la utilidad neta consolidada del ER
A7: Partidas que no se reclasificarán a resultados
A8: Valuación de instrumentos financieros de capital | B8: -112 | C8: -32 | D8: -236 | E8: -43 | F8: -118 | G8: 0 | H8: 0 | L8: [sourced] | M8: RA23 p.258 (2021-22); IA25 p.14 (2023-25)
A9: Utilidades (pérdidas) actuariales de planes de beneficios definidos | B9: 1543 | C9: 800 | D9: -349 | E9: 802 | F9: -433 | G9: 0 | H9: 0 | L9: [sourced] | M9: RA23 p.258 (2021-22); IA25 p.14 (2023-25)
A10: Impuesto a las ganancias | B10: -432 | C10: -207 | D10: 164 | E10: -540 | F10: 369 | G10: 0 | H10: 0 | L10: [sourced] | M10: RA23 p.258 (2021-22); IA25 p.14 (2023-25)
A11: Subtotal | B11: =SUM(B8:B10) | C11: =SUM(C8:C10) | D11: =SUM(D8:D10) | E11: =SUM(E8:E10) | F11: =SUM(F8:F10) | G11: =SUM(G8:G10) | H11: =SUM(H8:H10) | I11: =SUM(I8:I10) | ... K11: =SUM(K8:K10) | L11: [calc]
A12: Partidas que se reclasificarán a resultados
A13: Efectos de cobertura económica neta | B13: -723 | C13: 667 | D13: 1100 | E13: -3407 | F13: 2096 | G13: 0 | H13: 0 | L13: [sourced] | M13: RA23 p.258 (2021-22); IA25 p.14 (2023-25)
A14: Efectos de conversión de operaciones extranjeras | B14: 2114 | C14: -9862 | D14: -15635 | E14: 15551 | F14: -10811 | G14: 0 | H14: 0 | L14: [sourced] | M14: RA23 p.258 (2021-22); IA25 p.14 (2023-25)
A15: Variación neta de instrumentos de cobertura de flujos de efectivo | B15: 2988 | C15: -2213 | D15: 938 | E15: 287 | F15: -1800 | G15: 0 | H15: 0 | L15: [sourced] | M15: RA23 p.258 (2021-22); IA25 p.14 (2023-25)
A16: Impuesto a las ganancias | B16: -937 | C16: 142 | D16: -772 | E16: 1164 | F16: -348 | G16: 0 | H16: 0 | L16: [sourced] | M16: RA23 p.258 (2021-22); IA25 p.14 (2023-25)
A17: Subtotal | B17: =SUM(B13:B16) | C17: =SUM(C13:C16) | D17: =SUM(D13:D16) | E17: =SUM(E13:E16) | F17: =SUM(F13:F16) | G17: =SUM(G13:G16) | H17: =SUM(H13:H16) | I17: =SUM(I13:I16) | ... K17: =SUM(K13:K16) | L17: [calc]
A18: Total de otros resultados integrales | B18: =B11+B17 | C18: =C11+C17 | D18: =D11+D17 | E18: =E11+E17 | F18: =F11+F17 | G18: =G11+G17 | H18: =H11+H17 | I18: =I11+I17 | ... K18: =K11+K17 | L18: [calc]
A19: Resultado integral consolidado | B19: =B5+B18 | C19: =C5+C18 | D19: =D5+D18 | E19: =E5+E18 | F19: =F5+F18 | G19: =G5+G18 | H19: =H5+H18 | I19: =I5+I18 | ... K19: =K5+K18 | L19: [calc]
A20: Atribuible a la participación no controladora | B20: 1470 | C20: 1155 | D20: 1540 | E20: 1677 | F20: 2012 | G20: =ER!G30 | H20: =ER!H30 | L20: [sourced] | M20: RA23 p.258 (2021-22); IA25 p.14 (2023-25)
A21: Atribuible a la participación controladora | B21: =B19-B20 | C21: =C19-C20 | D21: =D19-D20 | E21: =E19-E20 | F21: =F19-F20 | G21: =G19-G20 | H21: =H19-H20 | I21: =I19-I20 | ... K21: =K19-K20 | L21: [calc]

Sheet BG
A1: Grupo Bimbo - Estado consolidado de situación financiera (balance general) al 31 de diciembre
A2: Como se reporta: todos los renglones del estado.
B3: Real (auditado) | G3: Proyección - el equipo proyecta y cuadra
A4: Millones de MXN | B4: 2021R | C4: 2022R | D4: 2023R | E4: 2024R | F4: 2025R | G4: 2026E | H4: 2027E | I4: 2028E | J4: 2029E | K4: 2030E | L4: Etiqueta | M4: Fuente / nota
A5: Activo circulante
A6: Efectivo y equivalentes de efectivo | B6: 8748 | C6: 12313 | D6: 6353 | E6: 8057 | F6: 8535 | G6: =FE!G68 | H6: =FE!H68 | L6: [sourced] | M6: RA23 p.256 (2021-22); IA25 p.12 (2023-25); Debe ser igual al efectivo final del FE
A7: Cuentas por cobrar a clientes y otras, neto | B7: 27170 | C7: 32185 | D7: 33269 | E7: 36659 | F7: 35782 | G7: =ER!G6*Supuestos!B82/365 | H7: =ER!H6*Supuestos!B82/365 | L7: [sourced] | M7: RA23 p.256 (2021-22); IA25 p.12 (2023-25)
A8: Inventarios | B8: 13710 | C8: 16989 | D8: 16120 | E8: 18832 | F8: 17151 | G8: =ER!G7*Supuestos!B83/365 | H8: =ER!H7*Supuestos!B83/365 | L8: [sourced] | M8: RA23 p.256 (2021-22); IA25 p.12 (2023-25)
A9: Pagos anticipados | B9: 2296 | C9: 928 | D9: 1378 | E9: 1371 | F9: 1798 | G9: =F9 | H9: =G9 | L9: [sourced] | M9: RA23 p.256 (2021-22); IA25 p.12 (2023-25)
A10: Instrumentos financieros derivados | B10: 1293 | C10: 38 | D10: 119 | E10: 1417 | F10: 60 | G10: =F10 | H10: =G10 | L10: [sourced] | M10: RA23 p.256 (2021-22); IA25 p.12 (2023-25)
A11: Depósitos en cuentas de garantía de instrumentos financieros derivados | B11: 0 | C11: 879 | D11: 1519 | E11: 577 | F11: 459 | G11: =F11 | H11: =G11 | L11: [sourced] | M11: RA23 p.256 (2021-22); IA25 p.12 (2023-25)
A12: Activos clasificados como mantenidos para su venta | B12: 194 | C12: 138 | D12: 156 | E12: 267 | F12: 886 | G12: =F12 | H12: =G12 | L12: [sourced] | M12: RA23 p.256 (2021-22); IA25 p.12 (2023-25)
A13: Total del activo circulante | B13: =SUM(B6:B12) | C13: =SUM(C6:C12) | D13: =SUM(D6:D12) | E13: =SUM(E6:E12) | F13: =SUM(F6:F12) | G13: =SUM(G6:G12) | H13: =SUM(H6:H12) | I13: =SUM(I6:I12) | ... K13: =SUM(K6:K12) | L13: [calc]
A14: Propiedades, planta y equipo, neto | B14: 103891 | C14: 113505 | D14: 129156 | E14: 155376 | F14: 157423 | G14: =F14+Supuestos!B77-Supuestos!B81 | H14: =G14+Supuestos!B182-(ER!H36-Supuestos!B78-Supuestos!B80) | L14: [sourced] | M14: RA23 p.256 (2021-22); IA25 p.12 (2023-25)
A15: Activos por derecho de uso, neto | B15: 30754 | C15: 28477 | D15: 25848 | E15: 34220 | F15: 32757 | G15: =F15 | H15: =G15 | L15: [sourced] | M15: RA23 p.256 (2021-22); IA25 p.12 (2023-25)
A16: Inversión en asociadas | B16: 3891 | C16: 4398 | D16: 5031 | E16: 7531 | F16: 7018 | G16: =F16+ER!G22 | H16: =G16+ER!H22 | L16: [sourced] | M16: RA23 p.256 (2021-22); IA25 p.12 (2023-25)
A17: Instrumentos financieros derivados | B17: 1962 | C17: 2005 | D17: 468 | E17: 784 | F17: 657 | G17: =F17 | H17: =G17 | L17: [sourced] | M17: RA23 p.256 (2021-22); IA25 p.12 (2023-25)
A18: Impuestos a las ganancias diferidos | B18: 7861 | C18: 3962 | D18: 7313 | E18: 6884 | F18: 6908 | G18: =F18 | H18: =G18 | L18: [sourced] | M18: RA23 p.256 (2021-22); IA25 p.12 (2023-25)
A19: Activos intangibles, neto | B19: 56965 | C19: 59062 | D19: 55101 | E19: 65808 | F19: 62947 | G19: =F19-Supuestos!B80 | H19: =G19-Supuestos!B80 | L19: [sourced] | M19: RA23 p.256 (2021-22); IA25 p.12 (2023-25)
A20: Crédito mercantil | B20: 74565 | C20: 68085 | D20: 62000 | E20: 75100 | F20: 72568 | G20: =F20 | H20: =G20 | L20: [sourced] | M20: RA23 p.256 (2021-22); IA25 p.12 (2023-25)
A21: Otros activos, neto | B21: 4340 | C21: 4800 | D21: 4271 | E21: 3921 | F21: 4856 | G21: =F21 | H21: =G21 | L21: [sourced] | M21: RA23 p.256 (2021-22); IA25 p.12 (2023-25)
A22: TOTAL DEL ACTIVO | B22: =B13+SUM(B14:B21) | C22: =C13+SUM(C14:C21) | D22: =D13+SUM(D14:D21) | E22: =E13+SUM(E14:E21) | F22: =F13+SUM(F14:F21) | G22: =G13+SUM(G14:G21) | H22: =H13+SUM(H14:H21) | I22: =I13+SUM(I14:I21) | ... K22: =K13+SUM(K14:K21) | L22: [calc]
A24: Pasivo a corto plazo
A25: Porción a corto plazo de la deuda a largo plazo | B25: 10625 | C25: 6435 | D25: 12932 | E25: 4862 | F25: 12635 | G25: =Supuestos!B85-Supuestos!B89 | H25: =Supuestos!B252 | L25: [sourced] | M25: RA23 p.256 (2021-22); IA25 p.12 (2023-25)
A26: Cuentas por pagar a proveedores | B26: 35752 | C26: 44058 | D26: 40409 | E26: 40815 | F26: 39074 | G26: =ER!G7*Supuestos!B84/365 | H26: =ER!H7*Supuestos!B84/365 | L26: [sourced] | M26: RA23 p.256 (2021-22); IA25 p.12 (2023-25)
A27: Otras cuentas por pagar y pasivos acumulados | B27: 24102 | C27: 24198 | D27: 22072 | E27: 27280 | F27: 26395 | G27: =F27 | H27: =G27 | L27: [sourced] | M27: RA23 p.256 (2021-22); IA25 p.12 (2023-25)
A28: Pasivo por arrendamientos | B28: 5793 | C28: 5930 | D28: 5751 | E28: 7140 | F28: 7076 | G28: =F28 | H28: =G28 | L28: [sourced] | M28: RA23 p.256 (2021-22); IA25 p.12 (2023-25)
A29: Cuentas por pagar a partes relacionadas | B29: 1527 | C29: 1240 | D29: 1412 | E29: 1260 | F29: 1154 | G29: =F29 | H29: =G29 | L29: [sourced] | M29: RA23 p.256 (2021-22); IA25 p.12 (2023-25)
A30: Impuesto a las ganancias por pagar | B30: 708 | C30: 4604 | D30: 665 | E30: 1535 | F30: 1059 | G30: =F30 | H30: =G30 | L30: [sourced] | M30: RA23 p.256 (2021-22); IA25 p.12 (2023-25)
A31: Participación de los trabajadores en las utilidades (PTU) | B31: 1692 | C31: 1811 | D31: 1787 | E31: 1752 | F31: 1592 | G31: =F31 | H31: =G31 | L31: [sourced] | M31: RA23 p.256 (2021-22); IA25 p.12 (2023-25)
A32: Instrumentos financieros derivados | B32: 169 | C32: 1458 | D32: 2164 | E32: 511 | F32: 1588 | G32: =F32 | H32: =G32 | L32: [sourced] | M32: RA23 p.256 (2021-22); IA25 p.12 (2023-25)
A33: Otros pasivos a corto plazo | B33: 392 | C33: 0 | D33: 0 | E33: 0 | F33: 0 | G33: =F33 | H33: =G33 | L33: [sourced] | M33: RA23 p.256 (2021-22); IA25 p.12 (2023-25)
A34: Total del pasivo a corto plazo | B34: =SUM(B25:B33) | C34: =SUM(C25:C33) | D34: =SUM(D25:D33) | E34: =SUM(E25:E33) | F34: =SUM(F25:F33) | G34: =SUM(G25:G33) | H34: =SUM(H25:H33) | I34: =SUM(I25:I33) | ... K34: =SUM(K25:K33) | L34: [calc]
A35: Deuda a largo plazo | B35: 82230 | C35: 77619 | D35: 97003 | E35: 146043 | F35: 141028 | G35: =Supuestos!B86 | H35: =G25+G35-Supuestos!B249+Supuestos!B250-Supuestos!B252 | L35: [sourced] | M35: RA23 p.256 (2021-22); IA25 p.12 (2023-25)
A36: Pasivo por arrendamientos | B36: 25356 | C36: 23255 | D36: 21064 | E36: 28661 | F36: 27714 | G36: =F36 | H36: =G36 | L36: [sourced] | M36: RA23 p.256 (2021-22); IA25 p.12 (2023-25)
A37: Instrumentos financieros derivados | B37: 67 | C37: 590 | D37: 1888 | E37: 689 | F37: 2314 | G37: =F37 | H37: =G37 | L37: [sourced] | M37: RA23 p.256 (2021-22); IA25 p.12 (2023-25)
A38: Beneficios a empleados | B38: 30712 | C38: 9382 | D38: 7217 | E38: 6635 | F38: 6507 | G38: =F38 | H38: =G38 | L38: [sourced] | M38: RA23 p.256 (2021-22); IA25 p.12 (2023-25); La caída de 2022 = liquidación de MEPP
A39: Impuestos a las ganancias diferidos | B39: 7087 | C39: 7575 | D39: 9224 | E39: 8891 | F39: 8415 | G39: =F39 | H39: =G39 | L39: [sourced] | M39: RA23 p.256 (2021-22); IA25 p.12 (2023-25)
A40: Otros pasivos a largo plazo | B40: 9822 | C40: 12007 | D40: 12886 | E40: 13032 | F40: 12999 | G40: =F40 | H40: =G40 | L40: [sourced] | M40: RA23 p.256 (2021-22); IA25 p.12 (2023-25)
A41: TOTAL DEL PASIVO | B41: =B34+SUM(B35:B40) | C41: =C34+SUM(C35:C40) | D41: =D34+SUM(D35:D40) | E41: =E34+SUM(E35:E40) | F41: =F34+SUM(F35:F40) | G41: =G34+SUM(G35:G40) | H41: =H34+SUM(H35:H40) | I41: =I34+SUM(I35:I40) | ... K41: =K34+SUM(K35:K40) | L41: [calc]
A43: Capital contable
A44: Capital social | B44: 4021 | C44: 3984 | D44: 3946 | E44: 3887 | F44: 3866 | G44: =F44 | H44: =G44 | L44: [sourced] | M44: RA23 p.256 (2021-22); IA25 p.12 (2023-25)
A45: Utilidades retenidas | B45: 73384 | C45: 111486 | D45: 118718 | E45: 122763 | F45: 127596 | G45: =F45+SUM(Capital!G7:Capital!G14) | H45: =G45+SUM(Capital!H7:Capital!H14) | L45: [sourced] | M45: RA23 p.256 (2021-22); IA25 p.12 (2023-25)
A46: Otro instrumento financiero de capital (bonos perpetuos) | B46: 8867 | C46: 8098 | D46: 0 | E46: 0 | F46: 0 | G46: =F46 | H46: =G46 | L46: [sourced] | M46: RA23 p.256 (2021-22); IA25 p.12 (2023-25); Reclasificado a deuda en 2023
A47: Efecto acumulado de conversión de operaciones extranjeras | B47: 10297 | C47: 1132 | D47: -13832 | E47: -868 | F47: -10377 | G47: =F47 | H47: =G47 | L47: [sourced] | M47: RA23 p.256 (2021-22); IA25 p.12 (2023-25)
A48: Utilidades actuariales de planes de beneficios definidos | B48: 696 | C48: 1152 | D48: 734 | E48: 1315 | F48: 1008 | G48: =F48 | H48: =G48 | L48: [sourced] | M48: RA23 p.256 (2021-22); IA25 p.12 (2023-25)
A49: Valuación de instrumentos financieros de capital | B49: -742 | C49: -690 | D49: -857 | E49: -1011 | F49: -1132 | G49: =F49 | H49: =G49 | L49: [sourced] | M49: RA23 p.256 (2021-22); IA25 p.12 (2023-25)
A50: (Pérdidas) utilidades por realizar de coberturas de flujos de efectivo | B50: 577 | C50: -1051 | D50: -387 | E50: -142 | F50: -1449 | G50: =F50 | H50: =G50 | L50: [sourced] | M50: RA23 p.256 (2021-22); IA25 p.12 (2023-25)
A51: Participación controladora | B51: =SUM(B44:B50) | C51: =SUM(C44:C50) | D51: =SUM(D44:D50) | E51: =SUM(E44:E50) | F51: =SUM(F44:F50) | G51: =SUM(G44:G50) | H51: =SUM(H44:H50) | I51: =SUM(I44:I50) | ... K51: =SUM(K44:K50) | L51: [calc]
A52: Participación no controladora | B52: 4506 | C52: 3491 | D52: 3306 | E52: 1754 | F52: 743 | G52: =Capital!G25 | H52: =Capital!H25 | L52: [sourced] | M52: RA23 p.256 (2021-22); IA25 p.12 (2023-25)
A53: TOTAL DEL CAPITAL CONTABLE | B53: =B51+B52 | C53: =C51+C52 | D53: =D51+D52 | E53: =E51+E52 | F53: =F51+F52 | G53: =G51+G52 | H53: =H51+H52 | I53: =I51+I52 | ... K53: =K51+K52 | L53: [calc]
A54: TOTAL PASIVO Y CAPITAL CONTABLE | B54: =B41+B53 | C54: =C41+C53 | D54: =D41+D53 | E54: =E41+E53 | F54: =F41+F53 | G54: =G41+G53 | H54: =H41+H53 | I54: =I41+I53 | ... K54: =K41+K53 | L54: [calc]
A56: Cuadre: activo total - (pasivo + capital) | B56: =B22-B54 | C56: =C22-C54 | D56: =D22-D54 | E56: =E22-E54 | F56: =F22-F54 | G56: =G22-G54 | H56: =H22-H54 | I56: =I22-I54 | ... K56: =K22-K54 | L56: [calc] | M56: Debe ser 0

Sheet FE
A1: Grupo Bimbo - Estado consolidado de flujos de efectivo
A2: Método indirecto, como se reporta. Signo como en el reporte: negativo = salida de efectivo. 2021-22 incluyen Ricolino hasta su venta.
B3: Real (auditado) | G3: Proyección - el equipo proyecta y cuadra
A4: Millones de MXN | B4: 2021R | C4: 2022R | D4: 2023R | E4: 2024R | F4: 2025R | G4: 2026E | H4: 2027E | I4: 2028E | J4: 2029E | K4: 2030E | L4: Etiqueta | M4: Fuente / nota
A5: Actividades de operación
A6: Utilidad antes de impuestos de operaciones continuas | B6: 24854 | C6: 45878 | D6: 25324 | E6: 21034 | F6: 20143 | G6: =ER!G23 | H6: =ER!H23 | L6: [sourced] | M6: RA23 p.260 (2021-22); IA25 p.16 (2023-25); Debe ser igual al ER
A7: Utilidad (pérdida) antes de impuestos de operaciones discontinuadas | B7: 1499 | C7: 23516 | D7: -23 | E7: -277 | F7: 0 | G7: 0 | H7: 0 | L7: [sourced] | M7: RA23 p.260 (2021-22); IA25 p.16 (2023-25)
A8: Utilidad antes de impuestos | B8: =B6+B7 | C8: =C6+C7 | D8: =D6+D7 | E8: =E6+E7 | F8: =F6+F7 | G8: =G6+G7 | H8: =H6+H7 | I8: =I6+I7 | ... K8: =K6+K7 | L8: [calc]
A9: Ajustes por:
A10: Depreciación y amortización | B10: 16375 | C10: 18282 | D10: 18929 | E10: 23051 | F10: 24838 | G10: =ER!G36 | H10: =ER!H36 | L10: [sourced] | M10: RA23 p.260 (2021-22); IA25 p.16 (2023-25); 2021-22 incluyen depreciación y amortización discontinuada (249; 244)
A11: Pérdida (ganancia) en venta de propiedades, planta y equipo | B11: -157 | C11: 650 | D11: 751 | E11: -192 | F11: 68 | G11: 0 | H11: 0 | L11: [sourced] | M11: RA23 p.260 (2021-22); IA25 p.16 (2023-25)
A12: Bajas de propiedades, planta y equipo por siniestro | B12: 379 | C12: 0 | D12: 0 | E12: 0 | F12: 0 | G12: 0 | H12: 0 | L12: [sourced] | M12: RA23 p.260 (2021-22); IA25 p.16 (2023-25)
A13: Participación en los resultados de compañías asociadas | B13: -247 | C13: -452 | D13: -316 | E13: -464 | F13: 2 | G13: =-ER!G22 | H13: =-ER!H22 | L13: [sourced] | M13: RA23 p.260 (2021-22); IA25 p.16 (2023-25)
A14: Deterioro de activos de larga duración | B14: 694 | C14: 1046 | D14: 383 | E14: 249 | F14: 445 | G14: 0 | H14: 0 | L14: [sourced] | M14: RA23 p.260 (2021-22); IA25 p.16 (2023-25)
A15: Ganancia en disposición de operación discontinuada | B15: 0 | C15: -22038 | D15: 0 | E15: 277 | F15: 0 | G15: 0 | H15: 0 | L15: [sourced] | M15: RA23 p.260 (2021-22); IA25 p.16 (2023-25)
A16: Planes de pensiones multipatronales y otros pasivos a largo plazo | B16: -2247 | C16: -19010 | D16: 0 | E16: -982 | F16: 27 | G16: 0 | H16: 0 | L16: [sourced] | M16: RA23 p.260 (2021-22); IA25 p.16 (2023-25)
A17: Costo laboral del servicio actual | B17: 1128 | C17: 1013 | D17: 837 | E17: 942 | F17: 909 | G17: 0 | H17: 0 | L17: [sourced] | M17: RA23 p.260 (2021-22); IA25 p.16 (2023-25)
A18: Intereses a cargo | B18: 7884 | C18: 8049 | D18: 10006 | E18: 13100 | F18: 14464 | G18: =ER!G17 | H18: =ER!H17 | L18: [sourced] | M18: RA23 p.260 (2021-22); IA25 p.16 (2023-25)
A19: Intereses ganados | B19: -373 | C19: -740 | D19: -809 | E19: -924 | F19: -897 | G19: =ER!G18 | H19: =ER!H18 | L19: [sourced] | M19: RA23 p.260 (2021-22); IA25 p.16 (2023-25)
A20: Gastos de arrendamientos de corto plazo y bajo valor | B20: 2183 | C20: 2519 | D20: 3968 | E20: 4526 | F20: 4964 | G20: 0 | H20: 0 | L20: [sourced] | M20: RA23 p.260 (2021-22); IA25 p.16 (2023-25)
A21: Cambios en activos y pasivos:
A22: Cuentas por cobrar a clientes y otras | B22: 666 | C22: -6647 | D22: -4206 | E22: -319 | F22: 601 | G22: =BG!F7-BG!G7 | H22: =BG!G7-BG!H7 | L22: [sourced] | M22: RA23 p.260 (2021-22); IA25 p.16 (2023-25)
A23: Inventarios | B23: -2320 | C23: -4163 | D23: -1078 | E23: -1104 | F23: 901 | G23: =BG!F8-BG!G8 | H23: =BG!G8-BG!H8 | L23: [sourced] | M23: RA23 p.260 (2021-22); IA25 p.16 (2023-25)
A24: Pagos anticipados | B24: -365 | C24: 1261 | D24: -625 | E24: 189 | F24: -594 | G24: 0 | H24: 0 | L24: [sourced] | M24: RA23 p.260 (2021-22); IA25 p.16 (2023-25)
A25: Cuentas por pagar a proveedores | B25: 8286 | C25: 9920 | D25: -851 | E25: -2825 | F25: -1108 | G25: =BG!G26-BG!F26 | H25: =BG!H26-BG!G26 | L25: [sourced] | M25: RA23 p.260 (2021-22); IA25 p.16 (2023-25)
A26: Otras cuentas por pagar y pasivos acumulados | B26: -1025 | C26: -3395 | D26: 390 | E26: -3827 | F26: -560 | G26: 0 | H26: 0 | L26: [sourced] | M26: RA23 p.260 (2021-22); IA25 p.16 (2023-25)
A27: Cuentas por pagar a partes relacionadas | B27: 209 | C27: 287 | D27: -172 | E27: 153 | F27: 105 | G27: 0 | H27: 0 | L27: [sourced] | M27: RA23 p.260 (2021-22); IA25 p.16 (2023-25)
A28: Impuestos a las ganancias pagados | B28: -7578 | C28: -11824 | D28: -13831 | E28: -6472 | F28: -8955 | G28: =-ER!G24 | H28: =-ER!H24 | L28: [sourced] | M28: RA23 p.260 (2021-22); IA25 p.16 (2023-25)
A29: Depósitos en cuentas de garantía de instrumentos financieros derivados | B29: 6 | C29: -1271 | D29: -640 | E29: 942 | F29: 118 | G29: 0 | H29: 0 | L29: [sourced] | M29: RA23 p.260 (2021-22); IA25 p.16 (2023-25)
A30: Participación de los trabajadores en las utilidades (PTU) | B30: 675 | C30: 122 | D30: -21 | E30: -36 | F30: -159 | G30: 0 | H30: 0 | L30: [sourced] | M30: RA23 p.260 (2021-22); IA25 p.16 (2023-25)
A31: Beneficios a empleados y previsión social | B31: -2567 | C31: -754 | D31: -2637 | E31: -2608 | F31: -2595 | G31: 0 | H31: 0 | L31: [sourced] | M31: RA23 p.260 (2021-22); IA25 p.16 (2023-25)
A32: Dividendos por cobrar a la operación discontinuada | B32: 0 | C32: -879 | D32: 0 | E32: 0 | F32: 0 | G32: 0 | H32: 0 | L32: [sourced] | M32: RA23 p.260 (2021-22); IA25 p.16 (2023-25)
A33: Pagos de arrendamientos de corto plazo y bajo valor | B33: -2183 | C33: -2519 | D33: -3968 | E33: -4526 | F33: -4964 | G33: 0 | H33: 0 | L33: [sourced] | M33: RA23 p.260 (2021-22); IA25 p.16 (2023-25)
A34: Flujos netos de efectivo de actividades de operación | B34: =SUM(B8:B33) | C34: =SUM(C8:C33) | D34: =SUM(D8:D33) | E34: =SUM(E8:E33) | F34: =SUM(F8:F33) | G34: =SUM(G8:G33) | H34: =SUM(H8:H33) | I34: =SUM(I8:I33) | ... K34: =SUM(K8:K33) | L34: [calc]
A36: Actividades de inversión
A37: Adquisición de propiedades, planta y equipo | B37: -20671 | C37: -28669 | D37: -34754 | E37: -29402 | F37: -22530 | G37: =-Supuestos!B77 | H37: =-Supuestos!B182 | L37: [sourced] | M37: RA23 p.260 (2021-22); IA25 p.16 (2023-25)
A38: Adquisiciones de negocios y participaciones no controladoras, neto de efectivo recibido | B38: -10637 | C38: -6520 | D38: -6548 | E38: -5988 | F38: -11294 | G38: 0 | H38: 0 | L38: [sourced] | M38: RA23 p.260 (2021-22); IA25 p.16 (2023-25)
A39: Precio cobrado por venta de operación discontinuada | B39: 0 | C39: 25797 | D39: 0 | E39: 0 | F39: 0 | G39: 0 | H39: 0 | L39: [sourced] | M39: RA23 p.260 (2021-22); IA25 p.16 (2023-25); Ricolino
A40: Cobros por venta de propiedades, planta y equipo | B40: 882 | C40: 20 | D40: 152 | E40: 984 | F40: 824 | G40: 0 | H40: 0 | L40: [sourced] | M40: RA23 p.260 (2021-22); IA25 p.16 (2023-25)
A41: Cobros por recuperación de seguro | B41: 201 | C41: 272 | D41: 0 | E41: 0 | F41: 0 | G41: 0 | H41: 0 | L41: [sourced] | M41: RA23 p.260 (2021-22); IA25 p.16 (2023-25)
A42: Adquisición de activos intangibles, neta de bajas | B42: -622 | C42: -798 | D42: -918 | E42: -772 | F42: -311 | G42: 0 | H42: 0 | L42: [sourced] | M42: RA23 p.260 (2021-22); IA25 p.16 (2023-25)
A43: Incremento de derechos de distribución en entidades estructuradas | B43: -77 | C43: 3 | D43: -129 | E43: -705 | F43: -52 | G43: 0 | H43: 0 | L43: [sourced] | M43: RA23 p.260 (2021-22); IA25 p.16 (2023-25)
A44: Otros activos | B44: -1433 | C44: -794 | D44: -577 | E44: 455 | F44: -860 | G44: 0 | H44: 0 | L44: [sourced] | M44: RA23 p.260 (2021-22); IA25 p.16 (2023-25)
A45: Dividendos cobrados a asociadas y terceros | B45: 59 | C45: 954 | D45: 86 | E45: 207 | F45: 158 | G45: 0 | H45: 0 | L45: [sourced] | M45: RA23 p.260 (2021-22); IA25 p.16 (2023-25)
A46: Intereses cobrados | B46: 373 | C46: 740 | D46: 809 | E46: 924 | F46: 897 | G46: =-ER!G18 | H46: =-ER!H18 | L46: [sourced] | M46: RA23 p.260 (2021-22); IA25 p.16 (2023-25)
A47: Compra de participación no controladora | B47: 0 | C47: 0 | D47: 0 | E47: 0 | F47: -1468 | G47: 0 | H47: 0 | L47: [sourced] | M47: RA23 p.260 (2021-22); IA25 p.16 (2023-25); Bimbo Colombia 40%
A48: Aportaciones netas de capital social en asociadas | B48: -534 | C48: -127 | D48: -561 | E48: -1841 | F48: -16 | G48: 0 | H48: 0 | L48: [sourced] | M48: RA23 p.260 (2021-22); IA25 p.16 (2023-25)
A49: Flujos netos de efectivo de actividades de inversión | B49: =SUM(B37:B48) | C49: =SUM(C37:C48) | D49: =SUM(D37:D48) | E49: =SUM(E37:E48) | F49: =SUM(F37:F48) | G49: =SUM(G37:G48) | H49: =SUM(H37:H48) | I49: =SUM(I37:I48) | ... K49: =SUM(K37:K48) | L49: [calc]
A51: Actividades de financiamiento
A52: Préstamos obtenidos, netos de gastos de emisión | B52: 38924 | C52: 51670 | D52: 136638 | E52: 79111 | F52: 69267 | G52: 0 | H52: =Supuestos!B250 | L52: [sourced] | M52: RA23 p.260 (2021-22); IA25 p.16 (2023-25)
A53: Pago de préstamos | B53: -33535 | C53: -55542 | D53: -109847 | E53: -56495 | F53: -55477 | G53: =BG!G25+BG!G35-BG!F25-BG!F35 | H53: =BG!H25+BG!H35-BG!G25-BG!G35-Supuestos!B250 | L53: [sourced] | M53: RA23 p.260 (2021-22); IA25 p.16 (2023-25)
A54: Intereses pagados | B54: -6781 | C54: -6407 | D54: -7436 | E54: -8376 | F54: -11533 | G54: =-(ER!G17-Supuestos!B79) | H54: =-(ER!H17-Supuestos!B79) | L54: [sourced] | M54: RA23 p.260 (2021-22); IA25 p.16 (2023-25); Intereses de deuda; los intereses de arrendamiento van dentro de pagos de arrendamiento
A55: Rendimientos del instrumento financiero de capital (bonos perpetuos) | B55: -621 | C55: -649 | D55: -395 | E55: 0 | F55: 0 | G55: 0 | H55: 0 | L55: [sourced] | M55: RA23 p.260 (2021-22); IA25 p.16 (2023-25)
A56: Recompra del instrumento financiero de capital (bonos perpetuos) | B56: 0 | C56: -344 | D56: -78 | E56: 0 | F56: 0 | G56: 0 | H56: 0 | L56: [sourced] | M56: RA23 p.260 (2021-22); IA25 p.16 (2023-25)
A57: Dividendos pagados | B57: -4636 | C57: -5885 | D57: -3549 | E57: -4234 | F57: -4451 | G57: =-(Supuestos!B91+Supuestos!B92) | H57: =-(Supuestos!B266+Supuestos!B267) | L57: [sourced] | M57: RA23 p.260 (2021-22); IA25 p.16 (2023-25); Controladora + no controladora
A58: Pagos a distribuidores de EUA, entidades estructuradas (no controladora) | B58: 0 | C58: 0 | D58: 0 | E58: 0 | F58: 0 | G58: =Capital!G20 | H58: =Capital!H20 | L58: [sourced] | M58: RA23 p.260 (2021-22); IA25 p.16 (2023-25); No se reporta por separado en la historia; proyección = 'efecto de consolidación de entidades estructuradas' del capital
A59: Pagos de arrendamiento | B59: -5372 | C59: -6385 | D59: -6278 | E59: -7072 | F59: -8060 | G59: =-(Supuestos!B78+Supuestos!B79) | H59: =-(Supuestos!B78+Supuestos!B79) | L59: [sourced] | M59: RA23 p.260 (2021-22); IA25 p.16 (2023-25); Capital + intereses
A60: Pagos de instrumentos financieros derivados | B60: -1690 | C60: 0 | D60: -1655 | E60: -1889 | F60: -1034 | G60: 0 | H60: 0 | L60: [sourced] | M60: RA23 p.260 (2021-22); IA25 p.16 (2023-25)
A61: Cobros de instrumentos financieros derivados | B61: 1496 | C61: 418 | D61: 2090 | E61: 692 | F61: 633 | G61: 0 | H61: 0 | L61: [sourced] | M61: RA23 p.260 (2021-22); IA25 p.16 (2023-25)
A62: Recompra de acciones | B62: -1901 | C62: -2568 | D62: -3586 | E62: -4433 | F62: -1253 | G62: =-Supuestos!B95 | H62: =-Supuestos!B268 | L62: [sourced] | M62: RA23 p.260 (2021-22); IA25 p.16 (2023-25)
A63: Flujos netos de efectivo de actividades de financiamiento | B63: =SUM(B52:B62) | C63: =SUM(C52:C62) | D63: =SUM(D52:D62) | E63: =SUM(E52:E62) | F63: =SUM(F52:F62) | G63: =SUM(G52:G62) | H63: =SUM(H52:H62) | I63: =SUM(I52:I62) | ... K63: =SUM(K52:K62) | L63: [calc]
A65: Ajuste al efectivo por tipo de cambio y efectos inflacionarios | B65: 279 | C65: -472 | D65: -835 | E65: 631 | F65: -715 | G65: 0 | H65: 0 | L65: [sourced] | M65: RA23 p.260 (2021-22); IA25 p.16 (2023-25)
A66: Incremento (disminución) neto de efectivo | B66: =B34+B49+B63+B65 | C66: =C34+C49+C63+C65 | D66: =D34+D49+D63+D65 | E66: =E34+E49+E63+E65 | F66: =F34+F49+F63+F65 | G66: =G34+G49+G63+G65 | H66: =H34+H49+H63+H65 | I66: =I34+I49+I63+I65 | ... K66: =K34+K49+K63+K65 | L66: [calc]
A67: Efectivo al principio del periodo | B67: 9268 | C67: =B68 | D67: =C68 | E67: =D68 | F67: =E68 | G67: =F68 | H67: =G68 | I67: =H68 | J67: =I68 | K67: =J68 | L67: [sourced] 2021; [calc] después | M67: RA23 p.260 (2021-22); IA25 p.16 (2023-25); 2021 capturado (cierre 2020); años siguientes = efectivo final del año anterior
A68: Efectivo al final del periodo | B68: =B67+B66 | C68: =C67+C66 | D68: =D67+D66 | E68: =E67+E66 | F68: =F67+F66 | G68: =G67+G66 | H68: =H67+H66 | I68: =I67+I66 | ... K68: =K67+K66 | L68: [calc] | M68: Debe ser igual al efectivo del BG

Sheet Capital
A1: Grupo Bimbo - Movimientos del capital contable (estado de cambios en el capital contable)
A2: Columnas del estado de cambios en el capital condensadas en participación controladora y no controladora.
B3: Real (auditado) | G3: Proyección - el equipo proyecta y cuadra
A4: Millones de MXN | B4: 2021R | C4: 2022R | D4: 2023R | E4: 2024R | F4: 2025R | G4: 2026E | H4: 2027E | I4: 2028E | J4: 2029E | K4: 2030E | L4: Etiqueta | M4: Fuente / nota
A5: Participación controladora
A6: Saldo inicial | B6: 83713 | C6: =B16 | D6: =C16 | E6: =D16 | F6: =E16 | G6: =F16 | H6: =G16 | I6: =H16 | J6: =I16 | K6: =J16 | L6: [sourced] 2021; [calc] después | M6: RA23 p.259 (2021-22); IA25 p.15 (2023-25); 2021 capturado (cierre 2020); años siguientes = saldo final del año anterior
A7: Rendimientos del instrumento financiero de capital | B7: -621 | C7: -649 | D7: -395 | E7: 0 | F7: 0 | G7: 0 | H7: 0 | L7: [sourced] | M7: RA23 p.259 (2021-22); IA25 p.15 (2023-25)
A8: Efecto de impuestos sobre el instrumento financiero de capital | B8: 58 | C8: -229 | D8: -20 | E8: 0 | F8: 0 | G8: 0 | H8: 0 | L8: [sourced] | M8: RA23 p.259 (2021-22); IA25 p.15 (2023-25)
A9: Recompra del instrumento financiero de capital (bonos perpetuos) | B9: 0 | C9: -377 | D9: -78 | E9: 0 | F9: 0 | G9: 0 | H9: 0 | L9: [sourced] | M9: RA23 p.259 (2021-22); IA25 p.15 (2023-25)
A10: Reclasificación del instrumento financiero de capital a deuda | B10: 0 | C10: 0 | D10: -8844 | E10: 0 | F10: 0 | G10: 0 | H10: 0 | L10: [sourced] | M10: RA23 p.259 (2021-22); IA25 p.15 (2023-25)
A11: Decreto de dividendos | B11: -4502 | C11: -5791 | D11: -3458 | E11: -4125 | F11: -4316 | G11: =-Supuestos!B91 | H11: =-Supuestos!B266 | L11: [sourced] | M11: RA23 p.259 (2021-22); IA25 p.15 (2023-25)
A12: Recompra de acciones | B12: -1901 | C12: -2568 | D12: -3586 | E12: -4433 | F12: -1253 | G12: =-Supuestos!B95 | H12: =-Supuestos!B268 | L12: [sourced] | M12: RA23 p.259 (2021-22); IA25 p.15 (2023-25)
A13: Cambios en la participación | B13: 0 | C13: 0 | D13: 0 | E13: 0 | F13: -752 | G13: 0 | H13: 0 | L13: [sourced] | M13: RA23 p.259 (2021-22); IA25 p.15 (2023-25); Compra de la participación no controladora de Colombia
A14: Utilidad neta (participación controladora) | B14: 15916 | C14: 46910 | D14: 15477 | E14: 12544 | F14: 11133 | G14: =ER!G31 | H14: =ER!H31 | L14: [sourced] | M14: RA23 p.259 (2021-22); IA25 p.15 (2023-25); Debe ser igual a la utilidad controladora del ER
A15: Otros resultados integrales (participación controladora) | B15: 4437 | C15: -10285 | D15: -14885 | E15: 13636 | F15: -11244 | G15: 0 | H15: 0 | L15: [sourced] | M15: RA23 p.259 (2021-22); IA25 p.15 (2023-25)
A16: Saldo final, participación controladora | B16: =SUM(B6:B15) | C16: =SUM(C6:C15) | D16: =SUM(D6:D15) | E16: =SUM(E6:E15) | F16: =SUM(F6:F15) | G16: =SUM(G6:G15) | H16: =SUM(H6:H15) | I16: =SUM(I6:I15) | ... K16: =SUM(K6:K15) | L16: [calc] | M16: Debe ser igual a la participación controladora del BG
A18: Participación no controladora
A19: Saldo inicial | B19: 4298 | C19: =B25 | D19: =C25 | E19: =D25 | F19: =E25 | G19: =F25 | H19: =G25 | I19: =H25 | J19: =I25 | K19: =J25 | L19: [sourced] 2021; [calc] después | M19: RA23 p.259 (2021-22); IA25 p.15 (2023-25); 2021 capturado (cierre 2020); años siguientes = saldo final del año anterior
A20: Efecto de consolidación de entidades estructuradas | B20: -1099 | C20: -2011 | D20: -1851 | E20: -3120 | F20: -2240 | G20: =-(G23+G21) | H20: =-(H23+H21) | L20: [sourced] | M20: RA23 p.259 (2021-22); IA25 p.15 (2023-25)
A21: Decreto de dividendos | B21: -163 | C21: -94 | D21: -91 | E21: -109 | F21: -135 | G21: =-Supuestos!B92 | H21: =-Supuestos!B267 | L21: [sourced] | M21: RA23 p.259 (2021-22); IA25 p.15 (2023-25)
A22: Adquisiciones, disposiciones y cambios en la participación | B22: 0 | C22: -65 | D22: 217 | E22: 0 | F22: -648 | G22: 0 | H22: 0 | L22: [sourced] | M22: RA23 p.259 (2021-22); IA25 p.15 (2023-25); 2022 operación discontinuada (-65); 2023 adquisiciones (+217); 2025 adquisiciones 68 menos disminución 716
A23: Utilidad neta (participación no controladora) | B23: 1466 | C23: 1575 | D23: 1445 | E23: 1499 | F23: 1813 | G23: =ER!G30 | H23: =ER!H30 | L23: [sourced] | M23: RA23 p.259 (2021-22); IA25 p.15 (2023-25); Debe ser igual a la participación no controladora del ER
A24: Otros resultados integrales (participación no controladora) | B24: 4 | C24: -420 | D24: 95 | E24: 178 | F24: 199 | G24: 0 | H24: 0 | L24: [sourced] | M24: RA23 p.259 (2021-22); IA25 p.15 (2023-25)
A25: Saldo final, participación no controladora | B25: =SUM(B19:B24) | C25: =SUM(C19:C24) | D25: =SUM(D19:D24) | E25: =SUM(E19:E24) | F25: =SUM(F19:F24) | G25: =SUM(G19:G24) | H25: =SUM(H19:H24) | I25: =SUM(I19:I24) | ... K25: =SUM(K19:K24) | L25: [calc] | M25: Debe ser igual a la participación no controladora del BG
A27: Total del capital contable, saldo final | B27: =B16+B25 | C27: =C16+C25 | D27: =D16+D25 | E27: =E16+E25 | F27: =F16+F25 | G27: =G16+G25 | H27: =H16+H25 | I27: =I16+I25 | ... K27: =K16+K25 | L27: [calc] | M27: Debe ser igual al capital contable total del BG

Sheet Cuadres
A1: Cuadres - cada renglón debe ser 0 en todos los años
A2: En la historia todo da 0. En la proyección, un valor distinto de 0 indica qué vínculo falta.
A4: Cuadre (diferencia, millones de MXN) | B4: 2021R | C4: 2022R | D4: 2023R | E4: 2024R | F4: 2025R | G4: 2026E | H4: 2027E | I4: 2028E | J4: 2029E | K4: 2030E
A5: Vínculos entre estados (todos los años)
A6: BG: activo total - (pasivo + capital) | B6: =BG!B22-BG!B54 | C6: =BG!C22-BG!C54 | D6: =BG!D22-BG!D54 | E6: =BG!E22-BG!E54 | F6: =BG!F22-BG!F54 | G6: =BG!G22-BG!G54 | H6: =BG!H22-BG!H54 | I6: =BG!I22-BG!I54 | ... K6: =BG!K22-BG!K54
A7: FE efectivo final - efectivo del BG | B7: =FE!B68-BG!B6 | C7: =FE!C68-BG!C6 | D7: =FE!D68-BG!D6 | E7: =FE!E68-BG!E6 | F7: =FE!F68-BG!F6 | G7: =FE!G68-BG!G6 | H7: =FE!H68-BG!H6 | I7: =FE!I68-BG!I6 | ... K7: =FE!K68-BG!K6
A8: FE utilidad antes de impuestos (continuas) - ER | B8: =FE!B6-ER!B23 | C8: =FE!C6-ER!C23 | D8: =FE!D6-ER!D23 | E8: =FE!E6-ER!E23 | F8: =FE!F6-ER!F23 | G8: =FE!G6-ER!G23 | H8: =FE!H6-ER!H23 | I8: =FE!I6-ER!I23 | ... K8: =FE!K6-ER!K23
A9: ORI utilidad neta - utilidad neta consolidada del ER | B9: =ORI!B5-ER!B27 | C9: =ORI!C5-ER!C27 | D9: =ORI!D5-ER!D27 | E9: =ORI!E5-ER!E27 | F9: =ORI!F5-ER!F27 | G9: =ORI!G5-ER!G27 | H9: =ORI!H5-ER!H27 | I9: =ORI!I5-ER!I27 | ... K9: =ORI!K5-ER!K27
A10: Capital: utilidad controladora - ER | B10: =Capital!B14-ER!B31 | C10: =Capital!C14-ER!C31 | D10: =Capital!D14-ER!D31 | E10: =Capital!E14-ER!E31 | F10: =Capital!F14-ER!F31 | G10: =Capital!G14-ER!G31 | H10: =Capital!H14-ER!H31 | I10: =Capital!I14-ER!I31 | ... K10: =Capital!K14-ER!K31
A11: Capital: utilidad no controladora - ER | B11: =Capital!B23-ER!B30 | C11: =Capital!C23-ER!C30 | D11: =Capital!D23-ER!D30 | E11: =Capital!E23-ER!E30 | F11: =Capital!F23-ER!F30 | G11: =Capital!G23-ER!G30 | H11: =Capital!H23-ER!H30 | I11: =Capital!I23-ER!I30 | ... K11: =Capital!K23-ER!K30
A12: Capital: ORI (controladora + no controladora) - estado de ORI | B12: =Capital!B15+Capital!B24-ORI!B18 | C12: =Capital!C15+Capital!C24-ORI!C18 | D12: =Capital!D15+Capital!D24-ORI!D18 | E12: =Capital!E15+Capital!E24-ORI!E18 | F12: =Capital!F15+Capital!F24-ORI!F18 | G12: =Capital!G15+Capital!G24-ORI!G18 | H12: =Capital!H15+Capital!H24-ORI!H18 | I12: =Capital!I15+Capital!I24-ORI!I18 | ... K12: =Capital!K15+Capital!K24-ORI!K18
A13: Capital: ORI no controladora - estado de ORI | B13: =Capital!B24-(ORI!B20-ER!B30) | C13: =Capital!C24-(ORI!C20-ER!C30) | D13: =Capital!D24-(ORI!D20-ER!D30) | E13: =Capital!E24-(ORI!E20-ER!E30) | F13: =Capital!F24-(ORI!F20-ER!F30) | G13: =Capital!G24-(ORI!G20-ER!G30) | H13: =Capital!H24-(ORI!H20-ER!H30) | I13: =Capital!I24-(ORI!I20-ER!I30) | ... K13: =Capital!K24-(ORI!K20-ER!K30)
A14: Capital: saldo final controladora - BG | B14: =Capital!B16-BG!B51 | C14: =Capital!C16-BG!C51 | D14: =Capital!D16-BG!D51 | E14: =Capital!E16-BG!E51 | F14: =Capital!F16-BG!F51 | G14: =Capital!G16-BG!G51 | H14: =Capital!H16-BG!H51 | I14: =Capital!I16-BG!I51 | ... K14: =Capital!K16-BG!K51
A15: Capital: saldo final no controladora - BG | B15: =Capital!B25-BG!B52 | C15: =Capital!C25-BG!C52 | D15: =Capital!D25-BG!D52 | E15: =Capital!E25-BG!E52 | F15: =Capital!F25-BG!F52 | G15: =Capital!G25-BG!G52 | H15: =Capital!H25-BG!H52 | I15: =Capital!I25-BG!I52 | ... K15: =Capital!K25-BG!K52
A16: Capital: recompra de acciones - FE | B16: =Capital!B12-FE!B62 | C16: =Capital!C12-FE!C62 | D16: =Capital!D12-FE!D62 | E16: =Capital!E12-FE!E62 | F16: =Capital!F12-FE!F62 | G16: =Capital!G12-FE!G62 | H16: =Capital!H12-FE!H62 | I16: =Capital!I12-FE!I62 | ... K16: =Capital!K12-FE!K62
A18: Subtotales contra el reporte auditado (solo historia)
A19: ER ventas netas vs reporte | B19: =ER!B6-338792 | C19: =ER!C6-398706 | D19: =ER!D6-399879 | E19: =ER!E6-408335 | F19: =ER!F6-426952
A20: ER utilidad bruta vs reporte | B20: =ER!B8-181089 | C20: =ER!C8-205381 | D20: =ER!D8-205510 | E20: =ER!E8-214928 | F20: =ER!F8-223487
A21: ER utilidad de operación vs reporte | B21: =ER!B14-32580 | C21: =ER!C14-53696 | D21: =ER!D14-35455 | E21: =ER!E14-33149 | F21: =ER!F14-34146
A22: ER utilidad antes de impuestos vs reporte | B22: =ER!B23-24854 | C22: =ER!C23-45878 | D22: =ER!D23-25324 | E22: =ER!E23-21034 | F22: =ER!F23-20143
A23: ER utilidad neta consolidada vs reporte | B23: =ER!B27-17382 | C23: =ER!C27-48485 | D23: =ER!D27-16922 | E23: =ER!E27-14043 | F23: =ER!F27-12946
A24: ER utilidad controladora vs reporte | B24: =ER!B31-15916 | C24: =ER!C31-46910 | D24: =ER!D31-15477 | E24: =ER!E31-12544 | F24: =ER!F31-11133
A25: BG activo circulante vs reporte | B25: =BG!B13-53411 | C25: =BG!C13-63470 | D25: =BG!D13-58914 | E25: =BG!E13-67180 | F25: =BG!F13-64671
A26: BG activo total vs reporte | B26: =BG!B22-337640 | C26: =BG!C22-347764 | D26: =BG!D22-348102 | E26: =BG!E22-416804 | F26: =BG!F22-409805
A27: BG pasivo a corto plazo vs reporte | B27: =BG!B34-80760 | C27: =BG!C34-89734 | D27: =BG!D34-87192 | E27: =BG!E34-85155 | F27: =BG!F34-90573
A28: BG pasivo total vs reporte | B28: =BG!B41-236034 | C28: =BG!C41-220162 | D28: =BG!D41-236474 | E28: =BG!E41-289106 | F28: =BG!F41-289550
A29: BG capital contable vs reporte | B29: =BG!B53-101606 | C29: =BG!C53-127602 | D29: =BG!D53-111628 | E29: =BG!E53-127698 | F29: =BG!F53-120255
A30: FE operación vs reporte | B30: =FE!B34-45776 | C30: =FE!C34-38851 | D30: =FE!D34-31411 | E30: =FE!E34-39907 | F30: =FE!F34-47753
A31: FE inversión vs reporte | B31: =FE!B49--32459 | C31: =FE!C49--9122 | D31: =FE!D49--42440 | E31: =FE!E49--36138 | F31: =FE!F49--34652
A32: FE financiamiento vs reporte | B32: =FE!B63--14116 | C32: =FE!C63--25692 | D32: =FE!D63-5904 | E32: =FE!E63--2696 | F32: =FE!F63--11908
A33: ORI total vs reporte | B33: =ORI!B18-4441 | C33: =ORI!C18--10705 | D33: =ORI!D18--14790 | E33: =ORI!E18-13814 | F33: =ORI!F18--11045
A35: Suma de diferencias absolutas | B35: =SUMPRODUCT(ABS(B6:B33)) | C35: =SUMPRODUCT(ABS(C6:C33)) | D35: =SUMPRODUCT(ABS(D6:D33)) | E35: =SUMPRODUCT(ABS(E6:E33)) | F35: =SUMPRODUCT(ABS(F6:F33)) | G35: =SUMPRODUCT(ABS(G6:G33)) | H35: =SUMPRODUCT(ABS(H6:H33)) | I35: =SUMPRODUCT(ABS(I6:I33)) | ... K35: =SUMPRODUCT(ABS(K6:K33))
A36: Estado | B36: =IF(ROUND(B35,0)=0,"OK","REVISAR") | C36: =IF(ROUND(C35,0)=0,"OK","REVISAR") | D36: =IF(ROUND(D35,0)=0,"OK","REVISAR") | E36: =IF(ROUND(E35,0)=0,"OK","REVISAR") | F36: =IF(ROUND(F35,0)=0,"OK","REVISAR") | G36: =IF(ROUND(G35,0)=0,"OK","REVISAR") | H36: =IF(ROUND(H35,0)=0,"OK","REVISAR") | I36: =IF(ROUND(I35,0)=0,"OK","REVISAR") | ... K36: =IF(ROUND(K35,0)=0,"OK","REVISAR")
