Workbook

Sheet Notes
A1: Nominal GDP growth, local currency, 2016-2030 (Grupo Bimbo regions)
A3: Built | B3: 2026-10-24 by the AI for the team (logged in docs/context/ai-use-log.md)
A4: Levels | B4: S&P Capital IQ nominalGDPLCU, entered as values exactly as stored [sourced]; file and line in Data columns H-I
A5: Sources | B5: data/capitaliq/capiq-sales-drivers-{M1..M5,X1,E1..E5}_2026-10-24.md; ESP/PRT/FRA/ITA from BIMBOA/research/Informacion_BIMBO_macro.txt (its "Derived" growth rows, computed by ChatIQ, are not used)
A6: Growth | B6: Live formula in Data column J: level_t / level_t-1 - 1 [calc]. Growth_view links to Data; nothing is pasted as a value
A7: Duplicates | B7: PER, URY, VEN 2015-2025 appear in M5 and X1 with identical values; the M5 row is cited
A8: [unverified] | B8: UKR 2027 (gap vs real GDP + CPI); VEN all years (unusable); SVN 2025 (flag conflict). Shaded orange
A9: H-02 fix | B9: KAZ, KOR, MAR and UKR 2026: the stored level step is a likely series break, so 2026 growth = (1 + real GDP growth) x (1 + CPI) - 1 (Data columns L-M; CPI from IAS29_test) [calc]; CPI is a proxy for the GDP deflator [assumption]. The 2026 levels stay as stored, so 2027-2030 growth is unchanged. Shaded green. Audit fix 2026-10-26
A10: Unit notes | B10: HRV labelled knB but euro-scale, one unit throughout so growth is unaffected; PRY 2026 flagged ACTUAL (label wrong, value plausible); India on calendar years
A11: FX | B11: Local currency per USD, annual average, as stored in BIMBOA/research/Informacion_BIMBO_macro.txt [sourced]; USD = 1; VES and MKD not in source
A12: Regional_agg | B12: Same logic as Bimbo ex-FX growth: each country grows in local currency; countries are added at the prior-year exchange rate, so weight_t = GDP USD t-1 / region total t-1 and region growth_t = sum(weight x growth) [calc]. All consolidated countries included (team decision 2026-10-25). VEN excluded because Bimbo has not consolidated it since 1-Jun-2017; MKD excluded for lack of FX (toggle column C). Weights are GDP, not Bimbo sales (Bimbo discloses sales by region only)
A13: IAS29_test | B13: IAS 29 para 3(e): one indicator of hyperinflation is cumulative inflation over three years approaching or exceeding 100%. Computed with live formulas from the Capital IQ CPI annual averages in the same blocks [calc]. Annual-average CPI is a proxy; IAS 29 practice uses index levels

Sheet Data
A1: iso3 | B1: region | C1: year | D1: nominal_gdp_lcu | E1: unit | F1: flag | G1: as_of | H1: source_file | I1: source_line | J1: growth | K1: tag | L1: real_gdp_growth (H-02) | M1: real GDP source (H-02)
A2: MEX | B2: Mexico | C2: 2015 | D2: 19228.61 | E2: Mex$B | F2: As reported ACTUAL | G2: 10/15/2026 | H2: capiq-sales-drivers-X1_2026-10-24.md | I2: 26 | K2: [sourced] level only
A3: MEX | B3: Mexico | C3: 2016 | D3: 20758.79 | E3: Mex$B | F3: As reported ACTUAL | G3: 10/15/2026 | H3: capiq-sales-drivers-X1_2026-10-24.md | I3: 27 | J3: =IF(D2=0,"",D3/D2-1) -> 0.079578295 | K3: [calc]
A4: MEX | B4: Mexico | C4: 2017 | D4: 22536.21 | E4: Mex$B | F4: As reported ACTUAL | G4: 10/15/2026 | H4: capiq-sales-drivers-X1_2026-10-24.md | I4: 28 | J4: =IF(D3=0,"",D4/D3-1) -> 0.085622524 | K4: [calc]
A5: MEX | B5: Mexico | C5: 2018 | D5: 24176.67 | E5: Mex$B | F5: As reported ACTUAL | G5: 10/15/2026 | H5: capiq-sales-drivers-X1_2026-10-24.md | I5: 29 | J5: =IF(D4=0,"",D5/D4-1) -> 0.072792186 | K5: [calc]
A6: MEX | B6: Mexico | C6: 2019 | D6: 25121.82 | E6: Mex$B | F6: As reported ACTUAL | G6: 10/15/2026 | H6: capiq-sales-drivers-X1_2026-10-24.md | I6: 30 | J6: =IF(D5=0,"",D6/D5-1) -> 0.039093473 | K6: [calc]
A7: MEX | B7: Mexico | C7: 2020 | D7: 24086.76 | E7: Mex$B | F7: As reported ACTUAL | G7: 10/15/2026 | H7: capiq-sales-drivers-X1_2026-10-24.md | I7: 31 | J7: =IF(D6=0,"",D7/D6-1) -> -0.041201633 | K7: [calc]
A8: MEX | B8: Mexico | C8: 2021 | D8: 26690.03 | E8: Mex$B | F8: As reported ACTUAL | G8: 10/15/2026 | H8: capiq-sales-drivers-X1_2026-10-24.md | I8: 32 | J8: =IF(D7=0,"",D8/D7-1) -> 0.10807888 | K8: [calc]
A9: MEX | B9: Mexico | C9: 2022 | D9: 29525.51 | E9: Mex$B | F9: As reported ACTUAL | G9: 10/15/2026 | H9: capiq-sales-drivers-X1_2026-10-24.md | I9: 33 | J9: =IF(D8=0,"",D9/D8-1) -> 0.10623742 | K9: [calc]
A10: MEX | B10: Mexico | C10: 2023 | D10: 31871.09 | E10: Mex$B | F10: As reported ACTUAL | G10: 10/15/2026 | H10: capiq-sales-drivers-X1_2026-10-24.md | I10: 34 | J10: =IF(D9=0,"",D10/D9-1) -> 0.079442489 | K10: [calc]
A11: MEX | B11: Mexico | C11: 2024 | D11: 33582.9 | E11: Mex$B | F11: As reported ACTUAL | G11: 10/15/2026 | H11: capiq-sales-drivers-X1_2026-10-24.md | I11: 35 | J11: =IF(D10=0,"",D11/D10-1) -> 0.053710432 | K11: [calc]
A12: MEX | B12: Mexico | C12: 2025 | D12: 35301.59 | E12: Mex$B | F12: As reported ACTUAL | G12: 10/15/2026 | H12: capiq-sales-drivers-X1_2026-10-24.md | I12: 36 | J12: =IF(D11=0,"",D12/D11-1) -> 0.051177534 | K12: [calc]
A13: MEX | B13: Mexico | C13: 2026 | D13: 37481.45 | E13: Mex$B | F13: Standardized FORECAST | G13: 10/15/2026 | H13: capiq-sales-drivers-M1_2026-10-24.md | I13: 24 | J13: =IF(D12=0,"",D13/D12-1) -> 0.061749627 | K13: [calc]
A14: MEX | B14: Mexico | C14: 2027 | D14: 39990.58 | E14: Mex$B | F14: Standardized FORECAST | G14: 10/15/2026 | H14: capiq-sales-drivers-M1_2026-10-24.md | I14: 25 | J14: =IF(D13=0,"",D14/D13-1) -> 0.066943248 | K14: [calc]
... A17: MEX | B17: Mexico | C17: 2030 | D17: 47039.53 | E17: Mex$B | F17: Standardized FORECAST | G17: 10/15/2026 | H17: capiq-sales-drivers-M1_2026-10-24.md | I17: 28 | J17: =IF(D16=0,"",D17/D16-1) -> 0.04875605 | K17: [calc]
A18: USA | B18: North America | C18: 2015 | D18: 18295.02 | E18: $B | F18: As reported ACTUAL | G18: 10/07/2026 | H18: capiq-sales-drivers-X1_2026-10-24.md | I18: 48 | K18: [sourced] level only
A19: USA | B19: North America | C19: 2016 | D19: 18804.91 | E19: $B | F19: As reported ACTUAL | G19: 10/07/2026 | H19: capiq-sales-drivers-X1_2026-10-24.md | I19: 49 | J19: =IF(D18=0,"",D19/D18-1) -> 0.027870426 | K19: [calc]
A20: USA | B20: North America | C20: 2017 | D20: 19612.1 | E20: $B | F20: As reported ACTUAL | G20: 10/07/2026 | H20: capiq-sales-drivers-X1_2026-10-24.md | I20: 50 | J20: =IF(D19=0,"",D20/D19-1) -> 0.042924428 | K20: [calc]
A21: USA | B21: North America | C21: 2018 | D21: 20656.52 | E21: $B | F21: As reported ACTUAL | G21: 10/07/2026 | H21: capiq-sales-drivers-X1_2026-10-24.md | I21: 51 | J21: =IF(D20=0,"",D21/D20-1) -> 0.053253859 | K21: [calc]
A22: USA | B22: North America | C22: 2019 | D22: 21539.98 | E22: $B | F22: As reported ACTUAL | G22: 10/07/2026 | H22: capiq-sales-drivers-X1_2026-10-24.md | I22: 52 | J22: =IF(D21=0,"",D22/D21-1) -> 0.042769063 | K22: [calc]
A23: USA | B23: North America | C23: 2020 | D23: 21375.28 | E23: $B | F23: As reported ACTUAL | G23: 10/15/2026 | H23: capiq-sales-drivers-X1_2026-10-24.md | I23: 53 | J23: =IF(D22=0,"",D23/D22-1) -> -0.0076462467 | K23: [calc]
A24: USA | B24: North America | C24: 2021 | D24: 23745.85 | E24: $B | F24: As reported ACTUAL | G24: 10/15/2026 | H24: capiq-sales-drivers-X1_2026-10-24.md | I24: 54 | J24: =IF(D23=0,"",D24/D23-1) -> 0.11090241 | K24: [calc]
A25: USA | B25: North America | C25: 2022 | D25: 26059.71 | E25: $B | F25: As reported ACTUAL | G25: 10/15/2026 | H25: capiq-sales-drivers-X1_2026-10-24.md | I25: 55 | J25: =IF(D24=0,"",D25/D24-1) -> 0.097442711 | K25: [calc]
A26: USA | B26: North America | C26: 2023 | D26: 27825.89 | E26: $B | F26: As reported ACTUAL | G26: 10/15/2026 | H26: capiq-sales-drivers-X1_2026-10-24.md | I26: 56 | J26: =IF(D25=0,"",D26/D25-1) -> 0.067774354 | K26: [calc]
A27: USA | B27: North America | C27: 2024 | D27: 29380.99 | E27: $B | F27: As reported ACTUAL | G27: 10/15/2026 | H27: capiq-sales-drivers-X1_2026-10-24.md | I27: 57 | J27: =IF(D26=0,"",D27/D26-1) -> 0.055886802 | K27: [calc]
A28: USA | B28: North America | C28: 2025 | D28: 30861.29 | E28: $B | F28: As reported ACTUAL | G28: 10/15/2026 | H28: capiq-sales-drivers-X1_2026-10-24.md | I28: 58 | J28: =IF(D27=0,"",D28/D27-1) -> 0.050382918 | K28: [calc]
A29: USA | B29: North America | C29: 2026 | D29: 32710.81 | E29: $B | F29: Standardized FORECAST | G29: 10/15/2026 | H29: capiq-sales-drivers-M1_2026-10-24.md | I29: 39 | J29: =IF(D28=0,"",D29/D28-1) -> 0.059930094 | K29: [calc]
A30: USA | B30: North America | C30: 2027 | D30: 34488.98 | E30: $B | F30: Standardized FORECAST | G30: 10/15/2026 | H30: capiq-sales-drivers-M1_2026-10-24.md | I30: 40 | J30: =IF(D29=0,"",D30/D29-1) -> 0.054360317 | K30: [calc]
... A33: USA | B33: North America | C33: 2030 | D33: 39193.65 | E33: $B | F33: Standardized FORECAST | G33: 10/15/2026 | H33: capiq-sales-drivers-M1_2026-10-24.md | I33: 43 | J33: =IF(D32=0,"",D33/D32-1) -> 0.041287357 | K33: [calc]
A34: CAN | B34: North America | C34: 2015 | D34: 1990.44 | E34: C$B | F34: As reported ACTUAL | G34: 07/15/2026 | H34: capiq-sales-drivers-X1_2026-10-24.md | I34: 70 | K34: [sourced] level only
A35: CAN | B35: North America | C35: 2016 | D35: 2025.54 | E35: C$B | F35: As reported ACTUAL | G35: 07/15/2026 | H35: capiq-sales-drivers-X1_2026-10-24.md | I35: 71 | J35: =IF(D34=0,"",D35/D34-1) -> 0.017634292 | K35: [calc]
A36: CAN | B36: North America | C36: 2017 | D36: 2140.64 | E36: C$B | F36: As reported ACTUAL | G36: 07/15/2026 | H36: capiq-sales-drivers-X1_2026-10-24.md | I36: 72 | J36: =IF(D35=0,"",D36/D35-1) -> 0.056824353 | K36: [calc]
A37: CAN | B37: North America | C37: 2018 | D37: 2235.68 | E37: C$B | F37: As reported ACTUAL | G37: 07/15/2026 | H37: capiq-sales-drivers-X1_2026-10-24.md | I37: 73 | J37: =IF(D36=0,"",D37/D36-1) -> 0.044397937 | K37: [calc]
A38: CAN | B38: North America | C38: 2019 | D38: 2313.56 | E38: C$B | F38: As reported ACTUAL | G38: 07/15/2026 | H38: capiq-sales-drivers-X1_2026-10-24.md | I38: 74 | J38: =IF(D37=0,"",D38/D37-1) -> 0.034835039 | K38: [calc]
A39: CAN | B39: North America | C39: 2020 | D39: 2220.53 | E39: C$B | F39: As reported ACTUAL | G39: 07/15/2026 | H39: capiq-sales-drivers-X1_2026-10-24.md | I39: 75 | J39: =IF(D38=0,"",D39/D38-1) -> -0.040210757 | K39: [calc]
A40: CAN | B40: North America | C40: 2021 | D40: 2535.82 | E40: C$B | F40: As reported ACTUAL | G40: 07/15/2026 | H40: capiq-sales-drivers-X1_2026-10-24.md | I40: 76 | J40: =IF(D39=0,"",D40/D39-1) -> 0.14198862 | K40: [calc]
A41: CAN | B41: North America | C41: 2022 | D41: 2864.16 | E41: C$B | F41: As reported ACTUAL | G41: 07/15/2026 | H41: capiq-sales-drivers-X1_2026-10-24.md | I41: 77 | J41: =IF(D40=0,"",D41/D40-1) -> 0.1294808 | K41: [calc]
A42: CAN | B42: North America | C42: 2023 | D42: 2965.2 | E42: C$B | F42: As reported ACTUAL | G42: 07/15/2026 | H42: capiq-sales-drivers-X1_2026-10-24.md | I42: 78 | J42: =IF(D41=0,"",D42/D41-1) -> 0.035277359 | K42: [calc]
A43: CAN | B43: North America | C43: 2024 | D43: 3108.55 | E43: C$B | F43: As reported ACTUAL | G43: 07/15/2026 | H43: capiq-sales-drivers-X1_2026-10-24.md | I43: 79 | J43: =IF(D42=0,"",D43/D42-1) -> 0.048344125 | K43: [calc]
A44: CAN | B44: North America | C44: 2025 | D44: 3245.26 | E44: C$B | F44: As reported ACTUAL | G44: 07/15/2026 | H44: capiq-sales-drivers-X1_2026-10-24.md | I44: 80 | J44: =IF(D43=0,"",D44/D43-1) -> 0.043978704 | K44: [calc]
A45: CAN | B45: North America | C45: 2026 | D45: 3428.37 | E45: C$B | F45: Standardized FORECAST | G45: 10/15/2026 | H45: capiq-sales-drivers-M1_2026-10-24.md | I45: 54 | J45: =IF(D44=0,"",D45/D44-1) -> 0.05642383 | K45: [calc]
A46: CAN | B46: North America | C46: 2027 | D46: 3650.48 | E46: C$B | F46: Standardized FORECAST | G46: 10/15/2026 | H46: capiq-sales-drivers-M1_2026-10-24.md | I46: 55 | J46: =IF(D45=0,"",D46/D45-1) -> 0.06478589 | K46: [calc]
... A49: CAN | B49: North America | C49: 2030 | D49: 4123.68 | E49: C$B | F49: Standardized FORECAST | G49: 10/15/2026 | H49: capiq-sales-drivers-M1_2026-10-24.md | I49: 58 | J49: =IF(D48=0,"",D49/D48-1) -> 0.040860215 | K49: [calc]
A50: ARG | B50: Latin America | C50: 2015 | D50: 5954.51 | E50: AR$B | F50: As reported ACTUAL | G50: 10/15/2026 | H50: capiq-sales-drivers-X1_2026-10-24.md | I50: 92 | K50: [sourced] level only
A51: ARG | B51: Latin America | C51: 2016 | D51: 8228.16 | E51: AR$B | F51: As reported ACTUAL | G51: 10/15/2026 | H51: capiq-sales-drivers-X1_2026-10-24.md | I51: 93 | J51: =IF(D50=0,"",D51/D50-1) -> 0.38183662 | K51: [calc]
A52: ARG | B52: Latin America | C52: 2017 | D52: 10660.23 | E52: AR$B | F52: As reported ACTUAL | G52: 10/15/2026 | H52: capiq-sales-drivers-X1_2026-10-24.md | I52: 94 | J52: =IF(D51=0,"",D52/D51-1) -> 0.29557884 | K52: [calc]
A53: ARG | B53: Latin America | C53: 2018 | D53: 14744.81 | E53: AR$B | F53: As reported ACTUAL | G53: 10/15/2026 | H53: capiq-sales-drivers-X1_2026-10-24.md | I53: 95 | J53: =IF(D52=0,"",D53/D52-1) -> 0.38316059 | K53: [calc]
A54: ARG | B54: Latin America | C54: 2019 | D54: 21558.44 | E54: AR$B | F54: As reported ACTUAL | G54: 10/15/2026 | H54: capiq-sales-drivers-X1_2026-10-24.md | I54: 96 | J54: =IF(D53=0,"",D54/D53-1) -> 0.46210361 | K54: [calc]
A55: ARG | B55: Latin America | C55: 2020 | D55: 27209.81 | E55: AR$B | F55: As reported ACTUAL | G55: 10/15/2026 | H55: capiq-sales-drivers-X1_2026-10-24.md | I55: 97 | J55: =IF(D54=0,"",D55/D54-1) -> 0.26214188 | K55: [calc]
A56: ARG | B56: Latin America | C56: 2021 | D56: 46219.08 | E56: AR$B | F56: As reported ACTUAL | G56: 10/15/2026 | H56: capiq-sales-drivers-X1_2026-10-24.md | I56: 98 | J56: =IF(D55=0,"",D56/D55-1) -> 0.69861826 | K56: [calc]
A57: ARG | B57: Latin America | C57: 2022 | D57: 82810.05 | E57: AR$B | F57: As reported ACTUAL | G57: 10/15/2026 | H57: capiq-sales-drivers-X1_2026-10-24.md | I57: 99 | J57: =IF(D56=0,"",D57/D56-1) -> 0.79168538 | K57: [calc]
A58: ARG | B58: Latin America | C58: 2023 | D58: 193946.18 | E58: AR$B | F58: As reported ACTUAL | G58: 10/15/2026 | H58: capiq-sales-drivers-X1_2026-10-24.md | I58: 100 | J58: =IF(D57=0,"",D58/D57-1) -> 1.3420609 | K58: [calc]
A59: ARG | B59: Latin America | C59: 2024 | D59: 584377.01 | E59: AR$B | F59: As reported ACTUAL | G59: 10/15/2026 | H59: capiq-sales-drivers-X1_2026-10-24.md | I59: 101 | J59: =IF(D58=0,"",D59/D58-1) -> 2.0130885 | K59: [calc]
A60: ARG | B60: Latin America | C60: 2025 | D60: 850239.8 | E60: AR$B | F60: As reported ACTUAL | G60: 10/15/2026 | H60: capiq-sales-drivers-X1_2026-10-24.md | I60: 102 | J60: =IF(D59=0,"",D60/D59-1) -> 0.4549508 | K60: [calc]
A61: ARG | B61: Latin America | C61: 2026 | D61: 1135307.1 | E61: AR$B | F61: Standardized FORECAST | G61: 10/15/2026 | H61: capiq-sales-drivers-M2_2026-10-24.md | I61: 27 | J61: =IF(D60=0,"",D61/D60-1) -> 0.33527866 | K61: [calc]
A62: ARG | B62: Latin America | C62: 2027 | D62: 1341238.9 | E62: AR$B | F62: Standardized FORECAST | G62: 10/15/2026 | H62: capiq-sales-drivers-M2_2026-10-24.md | I62: 28 | J62: =IF(D61=0,"",D62/D61-1) -> 0.18138872 | K62: [calc]
... A65: ARG | B65: Latin America | C65: 2030 | D65: 1719120.6 | E65: AR$B | F65: Standardized FORECAST | G65: 10/15/2026 | H65: capiq-sales-drivers-M2_2026-10-24.md | I65: 31 | J65: =IF(D64=0,"",D65/D64-1) -> 0.077944282 | K65: [calc]
A66: BRA | B66: Latin America | C66: 2015 | D66: 5995.79 | E66: R$B | F66: As reported ACTUAL | G66: 06/15/2026 | H66: capiq-sales-drivers-X1_2026-10-24.md | I66: 114 | K66: [sourced] level only
A67: BRA | B67: Latin America | C67: 2016 | D67: 6269.33 | E67: R$B | F67: As reported ACTUAL | G67: 10/15/2026 | H67: capiq-sales-drivers-X1_2026-10-24.md | I67: 115 | J67: =IF(D66=0,"",D67/D66-1) -> 0.045622011 | K67: [calc]
A68: BRA | B68: Latin America | C68: 2017 | D68: 6585.48 | E68: R$B | F68: As reported ACTUAL | G68: 10/15/2026 | H68: capiq-sales-drivers-X1_2026-10-24.md | I68: 116 | J68: =IF(D67=0,"",D68/D67-1) -> 0.050428036 | K68: [calc]
A69: BRA | B69: Latin America | C69: 2018 | D69: 7004.14 | E69: R$B | F69: As reported ACTUAL | G69: 10/15/2026 | H69: capiq-sales-drivers-X1_2026-10-24.md | I69: 117 | J69: =IF(D68=0,"",D69/D68-1) -> 0.063573194 | K69: [calc]
A70: BRA | B70: Latin America | C70: 2019 | D70: 7389.13 | E70: R$B | F70: As reported ACTUAL | G70: 10/15/2026 | H70: capiq-sales-drivers-X1_2026-10-24.md | I70: 118 | J70: =IF(D69=0,"",D70/D69-1) -> 0.054966063 | K70: [calc]
A71: BRA | B71: Latin America | C71: 2020 | D71: 7609.6 | E71: R$B | F71: As reported ACTUAL | G71: 10/15/2026 | H71: capiq-sales-drivers-X1_2026-10-24.md | I71: 119 | J71: =IF(D70=0,"",D71/D70-1) -> 0.029837071 | K71: [calc]
A72: BRA | B72: Latin America | C72: 2021 | D72: 9012.14 | E72: R$B | F72: As reported ACTUAL | G72: 10/15/2026 | H72: capiq-sales-drivers-X1_2026-10-24.md | I72: 120 | J72: =IF(D71=0,"",D72/D71-1) -> 0.18431192 | K72: [calc]
A73: BRA | B73: Latin America | C73: 2022 | D73: 10079.68 | E73: R$B | F73: As reported ACTUAL | G73: 10/15/2026 | H73: capiq-sales-drivers-X1_2026-10-24.md | I73: 121 | J73: =IF(D72=0,"",D73/D72-1) -> 0.11845577 | K73: [calc]
A74: BRA | B74: Latin America | C74: 2023 | D74: 10943.34 | E74: R$B | F74: As reported ACTUAL | G74: 10/15/2026 | H74: capiq-sales-drivers-X1_2026-10-24.md | I74: 122 | J74: =IF(D73=0,"",D74/D73-1) -> 0.085683276 | K74: [calc]
A75: BRA | B75: Latin America | C75: 2024 | D75: 11779.25 | E75: R$B | F75: As reported ACTUAL | G75: 10/15/2026 | H75: capiq-sales-drivers-X1_2026-10-24.md | I75: 123 | J75: =IF(D74=0,"",D75/D74-1) -> 0.076385272 | K75: [calc]
A76: BRA | B76: Latin America | C76: 2025 | D76: 12738.57 | E76: R$B | F76: As reported ACTUAL | G76: 10/15/2026 | H76: capiq-sales-drivers-X1_2026-10-24.md | I76: 124 | J76: =IF(D75=0,"",D76/D75-1) -> 0.081441518 | K76: [calc]
A77: BRA | B77: Latin America | C77: 2026 | D77: 13657.02 | E77: R$B | F77: Standardized FORECAST | G77: 10/15/2026 | H77: capiq-sales-drivers-M2_2026-10-24.md | I77: 42 | J77: =IF(D76=0,"",D77/D76-1) -> 0.07209993 | K77: [calc]
A78: BRA | B78: Latin America | C78: 2027 | D78: 14425.98 | E78: R$B | F78: Standardized FORECAST | G78: 10/15/2026 | H78: capiq-sales-drivers-M2_2026-10-24.md | I78: 43 | J78: =IF(D77=0,"",D78/D77-1) -> 0.056305109 | K78: [calc]
... A81: BRA | B81: Latin America | C81: 2030 | D81: 17294.03 | E81: R$B | F81: Standardized FORECAST | G81: 10/15/2026 | H81: capiq-sales-drivers-M2_2026-10-24.md | I81: 46 | J81: =IF(D80=0,"",D81/D80-1) -> 0.07117272 | K81: [calc]
A82: CHL | B82: Latin America | C82: 2015 | D82: 158.62 | E82: CL$T | F82: As reported ACTUAL | G82: 06/15/2026 | H82: capiq-sales-drivers-X1_2026-10-24.md | I82: 136 | K82: [sourced] level only
A83: CHL | B83: Latin America | C83: 2016 | D83: 168.76 | E83: CL$T | F83: As reported ACTUAL | G83: 06/15/2026 | H83: capiq-sales-drivers-X1_2026-10-24.md | I83: 137 | J83: =IF(D82=0,"",D83/D82-1) -> 0.063926365 | K83: [calc]
A84: CHL | B84: Latin America | C84: 2017 | D84: 179.31 | E84: CL$T | F84: As reported ACTUAL | G84: 06/15/2026 | H84: capiq-sales-drivers-X1_2026-10-24.md | I84: 138 | J84: =IF(D83=0,"",D84/D83-1) -> 0.062514814 | K84: [calc]
A85: CHL | B85: Latin America | C85: 2018 | D85: 189.43 | E85: CL$T | F85: As reported ACTUAL | G85: 06/15/2026 | H85: capiq-sales-drivers-X1_2026-10-24.md | I85: 139 | J85: =IF(D84=0,"",D85/D84-1) -> 0.05643857 | K85: [calc]
A86: CHL | B86: Latin America | C86: 2019 | D86: 195.55 | E86: CL$T | F86: As reported ACTUAL | G86: 06/15/2026 | H86: capiq-sales-drivers-X1_2026-10-24.md | I86: 140 | J86: =IF(D85=0,"",D86/D85-1) -> 0.032307449 | K86: [calc]
A87: CHL | B87: Latin America | C87: 2020 | D87: 201.31 | E87: CL$T | F87: As reported ACTUAL | G87: 09/15/2026 | H87: capiq-sales-drivers-X1_2026-10-24.md | I87: 141 | J87: =IF(D86=0,"",D87/D86-1) -> 0.029455382 | K87: [calc]
A88: CHL | B88: Latin America | C88: 2021 | D88: 239.56 | E88: CL$T | F88: As reported ACTUAL | G88: 06/15/2026 | H88: capiq-sales-drivers-X1_2026-10-24.md | I88: 142 | J88: =IF(D87=0,"",D88/D87-1) -> 0.19000546 | K88: [calc]
A89: CHL | B89: Latin America | C89: 2022 | D89: 262.95 | E89: CL$T | F89: As reported ACTUAL | G89: 06/15/2026 | H89: capiq-sales-drivers-X1_2026-10-24.md | I89: 143 | J89: =IF(D88=0,"",D89/D88-1) -> 0.097637335 | K89: [calc]
A90: CHL | B90: Latin America | C90: 2023 | D90: 282.1 | E90: CL$T | F90: As reported ACTUAL | G90: 06/15/2026 | H90: capiq-sales-drivers-X1_2026-10-24.md | I90: 144 | J90: =IF(D89=0,"",D90/D89-1) -> 0.072827534 | K90: [calc]
A91: CHL | B91: Latin America | C91: 2024 | D91: 310.68 | E91: CL$T | F91: As reported ACTUAL | G91: 09/15/2026 | H91: capiq-sales-drivers-X1_2026-10-24.md | I91: 145 | J91: =IF(D90=0,"",D91/D90-1) -> 0.10131159 | K91: [calc]
A92: CHL | B92: Latin America | C92: 2025 | D92: 339.98 | E92: CL$T | F92: As reported ACTUAL | G92: 09/15/2026 | H92: capiq-sales-drivers-X1_2026-10-24.md | I92: 146 | J92: =IF(D91=0,"",D92/D91-1) -> 0.094309257 | K92: [calc]
A93: CHL | B93: Latin America | C93: 2026 | D93: 364.88 | E93: CL$T | F93: Standardized FORECAST | G93: 10/15/2026 | H93: capiq-sales-drivers-M2_2026-10-24.md | I93: 57 | J93: =IF(D92=0,"",D93/D92-1) -> 0.073239602 | K93: [calc]
A94: CHL | B94: Latin America | C94: 2027 | D94: 392.69 | E94: CL$T | F94: Standardized FORECAST | G94: 10/15/2026 | H94: capiq-sales-drivers-M2_2026-10-24.md | I94: 58 | J94: =IF(D93=0,"",D94/D93-1) -> 0.076216838 | K94: [calc]
... A97: CHL | B97: Latin America | C97: 2030 | D97: 485.25 | E97: CL$T | F97: Standardized FORECAST | G97: 10/15/2026 | H97: capiq-sales-drivers-M2_2026-10-24.md | I97: 61 | J97: =IF(D96=0,"",D97/D96-1) -> 0.080566504 | K97: [calc]
A98: COL | B98: Latin America | C98: 2015 | D98: 804.69 | E98: Col$T | F98: As reported ACTUAL | G98: 10/15/2026 | H98: capiq-sales-drivers-X1_2026-10-24.md | I98: 158 | K98: [sourced] level only
A99: COL | B99: Latin America | C99: 2016 | D99: 863.78 | E99: Col$T | F99: As reported ACTUAL | G99: 10/15/2026 | H99: capiq-sales-drivers-X1_2026-10-24.md | I99: 159 | J99: =IF(D98=0,"",D99/D98-1) -> 0.073432005 | K99: [calc]
A100: COL | B100: Latin America | C100: 2017 | D100: 920.47 | E100: Col$T | F100: As reported ACTUAL | G100: 10/15/2026 | H100: capiq-sales-drivers-X1_2026-10-24.md | I100: 160 | J100: =IF(D99=0,"",D100/D99-1) -> 0.065630137 | K100: [calc]
A101: COL | B101: Latin America | C101: 2018 | D101: 987.79 | E101: Col$T | F101: As reported ACTUAL | G101: 10/15/2026 | H101: capiq-sales-drivers-X1_2026-10-24.md | I101: 161 | J101: =IF(D100=0,"",D101/D100-1) -> 0.07313655 | K101: [calc]
A102: COL | B102: Latin America | C102: 2019 | D102: 1060.07 | E102: Col$T | F102: As reported ACTUAL | G102: 10/15/2026 | H102: capiq-sales-drivers-X1_2026-10-24.md | I102: 162 | J102: =IF(D101=0,"",D102/D101-1) -> 0.073173448 | K102: [calc]
A103: COL | B103: Latin America | C103: 2020 | D103: 998.47 | E103: Col$T | F103: As reported ACTUAL | G103: 09/15/2026 | H103: capiq-sales-drivers-X1_2026-10-24.md | I103: 163 | J103: =IF(D102=0,"",D103/D102-1) -> -0.05810937 | K103: [calc]
A104: COL | B104: Latin America | C104: 2021 | D104: 1192.63 | E104: Col$T | F104: As reported ACTUAL | G104: 08/18/2026 | H104: capiq-sales-drivers-X1_2026-10-24.md | I104: 164 | J104: =IF(D103=0,"",D104/D103-1) -> 0.19445752 | K104: [calc]
A105: COL | B105: Latin America | C105: 2022 | D105: 1471.08 | E105: Col$T | F105: As reported ACTUAL | G105: 08/18/2026 | H105: capiq-sales-drivers-X1_2026-10-24.md | I105: 165 | J105: =IF(D104=0,"",D105/D104-1) -> 0.2334756 | K105: [calc]
A106: COL | B106: Latin America | C106: 2023 | D106: 1587.2 | E106: Col$T | F106: As reported ACTUAL | G106: 09/15/2026 | H106: capiq-sales-drivers-X1_2026-10-24.md | I106: 166 | J106: =IF(D105=0,"",D106/D105-1) -> 0.078935204 | K106: [calc]
A107: COL | B107: Latin America | C107: 2024 | D107: 1713.32 | E107: Col$T | F107: As reported ACTUAL | G107: 09/15/2026 | H107: capiq-sales-drivers-X1_2026-10-24.md | I107: 167 | J107: =IF(D106=0,"",D107/D106-1) -> 0.079460685 | K107: [calc]
A108: COL | B108: Latin America | C108: 2025 | D108: 1852.67 | E108: Col$T | F108: As reported ACTUAL | G108: 09/15/2026 | H108: capiq-sales-drivers-X1_2026-10-24.md | I108: 168 | J108: =IF(D107=0,"",D108/D107-1) -> 0.081333318 | K108: [calc]
A109: COL | B109: Latin America | C109: 2026 | D109: 2020.92 | E109: Col$T | F109: Standardized FORECAST | G109: 10/15/2026 | H109: capiq-sales-drivers-M2_2026-10-24.md | I109: 72 | J109: =IF(D108=0,"",D109/D108-1) -> 0.090814878 | K109: [calc]
A110: COL | B110: Latin America | C110: 2027 | D110: 2191.5 | E110: Col$T | F110: Standardized FORECAST | G110: 10/15/2026 | H110: capiq-sales-drivers-M2_2026-10-24.md | I110: 73 | J110: =IF(D109=0,"",D110/D109-1) -> 0.084407102 | K110: [calc]
... A113: COL | B113: Latin America | C113: 2030 | D113: 2684.83 | E113: Col$T | F113: Standardized FORECAST | G113: 10/15/2026 | H113: capiq-sales-drivers-M2_2026-10-24.md | I113: 76 | J113: =IF(D112=0,"",D113/D112-1) -> 0.070425287 | K113: [calc]
A114: CRI | B114: Latin America | C114: 2015 | D114: 30171.92 | E114: ¢B | F114: As reported ACTUAL | G114: 03/17/2026 | H114: capiq-sales-drivers-X1_2026-10-24.md | I114: 180 | K114: [sourced] level only
...

Sheet Growth_view
A1: iso3 | B1: region | C1: 2016 | D1: 2017 | E1: 2018 | F1: 2019 | G1: 2020 | H1: 2021 | I1: 2022 | J1: 2023 | K1: 2024 | L1: 2025 | M1: 2026 | N1: 2027 | O1: 2028 | P1: 2029 | Q1: 2030
A2: MEX | B2: Mexico | C2: =Data!J3 -> 0.079578295 | D2: =Data!J4 -> 0.085622524 | E2: =Data!J5 -> 0.072792186 | F2: =Data!J6 -> 0.039093473 | G2: =Data!J7 -> -0.041201633 | H2: =Data!J8 -> 0.10807888 | I2: =Data!J9 -> 0.10623742 | J2: =Data!J10 -> 0.079442489 | K2: =Data!J11 -> 0.053710432 | L2: =Data!J12 -> 0.051177534 | M2: =Data!J13 -> 0.061749627 | N2: =Data!J14 -> 0.066943248 | O2: =Data!J15 -> 0.060058894 | P2: =Data!J16 -> 0.058036859 | Q2: =Data!J17 -> 0.04875605
A3: USA | B3: North America | C3: =Data!J19 -> 0.027870426 | D3: =Data!J20 -> 0.042924428 | E3: =Data!J21 -> 0.053253859 | F3: =Data!J22 -> 0.042769063 | G3: =Data!J23 -> -0.0076462467 | H3: =Data!J24 -> 0.11090241 | I3: =Data!J25 -> 0.097442711 | J3: =Data!J26 -> 0.067774354 | K3: =Data!J27 -> 0.055886802 | L3: =Data!J28 -> 0.050382918 | M3: =Data!J29 -> 0.059930094 | N3: =Data!J30 -> 0.054360317 | O3: =Data!J31 -> 0.047543882 | P3: =Data!J32 -> 0.041819638 | Q3: =Data!J33 -> 0.041287357
A4: CAN | B4: North America | C4: =Data!J35 -> 0.017634292 | D4: =Data!J36 -> 0.056824353 | E4: =Data!J37 -> 0.044397937 | F4: =Data!J38 -> 0.034835039 | G4: =Data!J39 -> -0.040210757 | H4: =Data!J40 -> 0.14198862 | I4: =Data!J41 -> 0.1294808 | J4: =Data!J42 -> 0.035277359 | K4: =Data!J43 -> 0.048344125 | L4: =Data!J44 -> 0.043978704 | M4: =Data!J45 -> 0.05642383 | N4: =Data!J46 -> 0.06478589 | O4: =Data!J47 -> 0.047215709 | P4: =Data!J48 -> 0.036349939 | Q4: =Data!J49 -> 0.040860215
A5: ARG | B5: Latin America | C5: =Data!J51 -> 0.38183662 | D5: =Data!J52 -> 0.29557884 | E5: =Data!J53 -> 0.38316059 | F5: =Data!J54 -> 0.46210361 | G5: =Data!J55 -> 0.26214188 | H5: =Data!J56 -> 0.69861826 | I5: =Data!J57 -> 0.79168538 | J5: =Data!J58 -> 1.3420609 | K5: =Data!J59 -> 2.0130885 | L5: =Data!J60 -> 0.4549508 | M5: =Data!J61 -> 0.33527866 | N5: =Data!J62 -> 0.18138872 | O5: =Data!J63 -> 0.10103969 | P5: =Data!J64 -> 0.079943169 | Q5: =Data!J65 -> 0.077944282
A6: BRA | B6: Latin America | C6: =Data!J67 -> 0.045622011 | D6: =Data!J68 -> 0.050428036 | E6: =Data!J69 -> 0.063573194 | F6: =Data!J70 -> 0.054966063 | G6: =Data!J71 -> 0.029837071 | H6: =Data!J72 -> 0.18431192 | I6: =Data!J73 -> 0.11845577 | J6: =Data!J74 -> 0.085683276 | K6: =Data!J75 -> 0.076385272 | L6: =Data!J76 -> 0.081441518 | M6: =Data!J77 -> 0.07209993 | N6: =Data!J78 -> 0.056305109 | O6: =Data!J79 -> 0.052576671 | P6: =Data!J80 -> 0.063255502 | Q6: =Data!J81 -> 0.07117272
A7: CHL | B7: Latin America | C7: =Data!J83 -> 0.063926365 | D7: =Data!J84 -> 0.062514814 | E7: =Data!J85 -> 0.05643857 | F7: =Data!J86 -> 0.032307449 | G7: =Data!J87 -> 0.029455382 | H7: =Data!J88 -> 0.19000546 | I7: =Data!J89 -> 0.097637335 | J7: =Data!J90 -> 0.072827534 | K7: =Data!J91 -> 0.10131159 | L7: =Data!J92 -> 0.094309257 | M7: =Data!J93 -> 0.073239602 | N7: =Data!J94 -> 0.076216838 | O7: =Data!J95 -> 0.0593598 | P7: =Data!J96 -> 0.079495192 | Q7: =Data!J97 -> 0.080566504
A8: COL | B8: Latin America | C8: =Data!J99 -> 0.073432005 | D8: =Data!J100 -> 0.065630137 | E8: =Data!J101 -> 0.07313655 | F8: =Data!J102 -> 0.073173448 | G8: =Data!J103 -> -0.05810937 | H8: =Data!J104 -> 0.19445752 | I8: =Data!J105 -> 0.2334756 | J8: =Data!J106 -> 0.078935204 | K8: =Data!J107 -> 0.079460685 | L8: =Data!J108 -> 0.081333318 | M8: =Data!J109 -> 0.090814878 | N8: =Data!J110 -> 0.084407102 | O8: =Data!J111 -> 0.071371207 | P8: =Data!J112 -> 0.068264968 | Q8: =Data!J113 -> 0.070425287
A9: CRI | B9: Latin America | C9: =Data!J115 -> 0.062454428 | D9: =Data!J116 -> 0.071354483 | E9: =Data!J117 -> 0.051136964 | F9: =Data!J118 -> 0.053448931 | G9: =Data!J119 -> -0.03401975 | H9: =Data!J120 -> 0.10836836 | I9: =Data!J121 -> 0.12846919 | J9: =Data!J122 -> 0.036212681 | K9: =Data!J123 -> 0.046372375 | L9: =Data!J124 -> 0.04000729 | M9: =Data!J125 -> 0.0244027 | N9: =Data!J126 -> 0.049777247 | O9: =Data!J127 -> 0.051734185 | P9: =Data!J128 -> 0.051594139 | Q9: =Data!J129 -> 0.052014525
A10: ECU | B10: Latin America | C10: =Data!J131 -> 0.0047320235 | D10: =Data!J132 -> 0.069622197 | E10: =Data!J133 -> 0.028812099 | F10: =Data!J134 -> 0.0011164868 | G10: =Data!J135 -> -0.10901487 | H10: =Data!J136 -> 0.11797225 | I10: =Data!J137 -> 0.083504385 | J10: =Data!J138 -> 0.040127443 | K10: =Data!J139 -> 0.024919281 | L10: =Data!J140 -> 0.05266559 | M10: =Data!J141 -> 0.056169429 | N10: =Data!J142 -> 0.053327521 | O10: =Data!J143 -> 0.045868396 | P10: =Data!J144 -> 0.042471806 | Q10: =Data!J145 -> 0.042576074
A11: SLV | B11: Latin America | C11: =Data!J147 -> 0.031996587 | D11: =Data!J148 -> 0.032658123 | E11: =Data!J149 -> 0.041633307 | F11: =Data!J150 -> 0.033051499 | G11: =Data!J151 -> -0.072916667 | H11: =Data!J152 -> 0.16532905 | I11: =Data!J153 -> 0.097451791 | J11: =Data!J154 -> 0.053341701 | K11: =Data!J155 -> 0.039022937 | L11: =Data!J156 -> 0.052465596 | M11: =Data!J157 -> 0.045219286 | N11: =Data!J158 -> 0.043262966 | O11: =Data!J159 -> 0.039220585 | P11: =Data!J160 -> 0.038461538 | Q11: =Data!J161 -> 0.038657407
A12: GTM | B12: Latin America | C12: =Data!J163 -> 0.054577539 | D12: =Data!J164 -> 0.048824701 | E12: =Data!J165 -> 0.047216577 | F12: =Data!J166 -> 0.077262093 | G12: =Data!J167 -> 0.010354058 | H12: =Data!J168 -> 0.11424382 | I12: =Data!J169 -> 0.10786923 | J12: =Data!J170 -> 0.1026579 | K12: =Data!J171 -> 0.075325025 | L12: =Data!J172 -> 0.078120197 | M12: =Data!J173 -> 0.07308265 | N12: =Data!J174 -> 0.10540041 | O12: =Data!J175 -> 0.0981813 | P12: =Data!J176 -> 0.1002821 | Q12: =Data!J177 -> 0.099784135
A13: HND | B13: Latin America | C13: =Data!J179 -> 0.077126909 | D13: =Data!J180 -> 0.095741249 | E13: =Data!J181 -> 0.058667648 | F13: =Data!J182 -> 0.060057711 | G13: =Data!J183 -> -0.058688487 | H13: =Data!J184 -> 0.17749634 | I13: =Data!J185 -> 0.1384167 | J13: =Data!J186 -> 0.098402838 | K13: =Data!J187 -> 0.085032122 | L13: =Data!J188 -> 0.1206874 | M13: =Data!J189 -> 0.092054565 | N13: =Data!J190 -> 0.081229897 | O13: =Data!J191 -> 0.073479243 | P13: =Data!J192 -> 0.069209571 | Q13: =Data!J193 -> 0.067680401
A14: NIC | B14: Latin America | C14: =Data!J195 -> 0.093612493 | D14: =Data!J196 -> 0.089465103 | E14: =Data!J197 -> -0.0079414888 | F14: =Data!J198 -> 0.023406896 | G14: =Data!J199 -> 0.039086089 | H14: =Data!J200 -> 0.14346185 | I14: =Data!J201 -> 0.12232116 | J14: =Data!J202 -> 0.15687848 | K14: =Data!J203 -> 0.11171729 | L14: =Data!J204 -> 0.12900632 | M14: =Data!J205 -> 0.070651507 | N14: =Data!J206 -> 0.065966329 | O14: =Data!J207 -> 0.074794509 | P14: =Data!J208 -> 0.065915916 | Q14: =Data!J209 -> 0.0632953
A15: PAN | B15: Latin America | C15: =Data!J211 -> 0.070623036 | D15: =Data!J212 -> 0.07408047 | E15: =Data!J213 -> 0.082315113 | F15: =Data!J214 -> 0.036541889 | G15: =Data!J215 -> -0.18228719 | H15: =Data!J216 -> 0.18121276 | I15: =Data!J217 -> 0.1347181 | J15: =Data!J218 -> 0.095972803 | K15: =Data!J219 -> 0.032689096 | L15: =Data!J220 -> 0.047828096 | M15: =Data!J221 -> 0.065159868 | N15: =Data!J222 -> 0.054031674 | O15: =Data!J223 -> 0.04998527 | P15: =Data!J224 -> 0.050224467 | Q15: =Data!J225 -> 0.05004898
A16: PRY | B16: Latin America | C16: =Data!J227 -> 0.085791596 | D16: =Data!J228 -> 0.070706084 | E16: =Data!J229 -> 0.05230011 | F16: =Data!J230 -> 0.026455026 | G16: =Data!J231 -> 0.013647118 | H16: =Data!J232 -> 0.12767288 | I16: =Data!J233 -> 0.079951209 | J16: =Data!J234 -> 0.076256974 | K16: =Data!J235 -> 0.075655907 | L16: =Data!J236 -> 0.099308184 | M16: =Data!J237 -> 0.078933921 | N16: =Data!J238 -> 0.055760507 | O16: =Data!J239 -> 0.075622713 | P16: =Data!J240 -> 0.067276878 | Q16: =Data!J241 -> 0.065421714
A17: PER | B17: Latin America | C17: =Data!J243 -> 0.084403107 | D17: =Data!J244 -> 0.065980702 | E17: =Data!J245 -> 0.055317306 | F17: =Data!J246 -> 0.044263836 | G17: =Data!J247 -> -0.069627714 | H17: =Data!J248 -> 0.21563258 | I17: =Data!J249 -> 0.067413841 | J17: =Data!J250 -> 0.06901512 | K17: =Data!J251 -> 0.089467946 | L17: =Data!J252 -> 0.094372622 | M17: =Data!J253 -> 0.10654914 | N17: =Data!J254 -> 0.059237366 | O17: =Data!J255 -> 0.051995699 | P17: =Data!J256 -> 0.05032102 | Q17: =Data!J257 -> 0.05512973
A18: URY | B18: Latin America | C18: =Data!J259 -> 0.070182153 | D18: =Data!J260 -> 0.075194518 | E18: =Data!J261 -> 0.077027476 | F18: =Data!J262 -> 0.092612054 | G18: =Data!J263 -> 0.025769601 | H18: =Data!J264 -> 0.1756555 | I18: =Data!J265 -> 0.10871455 | J18: =Data!J266 -> 0.048457924 | K18: =Data!J267 -> 0.076496086 | L18: =Data!J268 -> 0.061952677 | M18: =Data!J269 -> 0.049119334 | N18: =Data!J270 -> 0.063581151 | O18: =Data!J271 -> 0.073304102 | P18: =Data!J272 -> 0.074442135 | Q18: =Data!J273 -> 0.073155204
A19: VEN | B19: Latin America | C19: =Data!J275 -> 2.5 | D19: =Data!J276 -> 6.1785714 | E19: =Data!J277 -> -1 | F19: =Data!J278 | G19: =Data!J279 -> 40.83871 | H19: =Data!J280 -> 15.444102 | I19: =Data!J281 -> 2.437922 | J19: =Data!J282 -> 1.9624816 | K19: =Data!J283 -> 1.0148052 | L19: =Data!J284 -> 2.8092597 | M19: =Data!J285 -> 3.7878125 | N19: =Data!J286 -> 0.82465683 | O19: =Data!J287 -> 0.38505682 | P19: =Data!J288 -> 0.25573277 | Q19: =Data!J289 -> 0.17196854
A20: GBR | B20: EAA | C20: =Data!J291 -> 0.039716525 | D20: =Data!J292 -> 0.048306433 | E20: =Data!J293 -> 0.036001541 | F20: =Data!J294 -> 0.039176346 | G20: =Data!J295 -> -0.058186027 | H20: =Data!J296 -> 0.094345907 | I20: =Data!J297 -> 0.11055576 | J20: =Data!J298 -> 0.067814078 | K20: =Data!J299 -> 0.050064162 | L20: =Data!J300 -> 0.048069674 | M20: =Data!J301 -> 0.039154697 | N20: =Data!J302 -> 0.035052785 | O20: =Data!J303 -> 0.03943262 | P20: =Data!J304 -> 0.041174207 | Q20: =Data!J305 -> 0.040762081
A21: CHE | B21: EAA | C21: =Data!J307 -> 0.01290408 | D21: =Data!J308 -> 0.01080767 | E21: =Data!J309 -> 0.041015176 | F21: =Data!J310 -> 0.010243242 | G21: =Data!J311 -> -0.029994534 | H21: =Data!J312 -> 0.082313165 | I21: =Data!J313 -> 0.066928724 | J21: =Data!J314 -> 0.021300476 | K21: =Data!J315 -> 0.028393617 | L21: =Data!J316 -> 0.023974075 | M21: =Data!J317 -> 0.019272434 | N21: =Data!J318 -> 0.025919249 | O21: =Data!J319 -> 0.027509899 | P21: =Data!J320 -> 0.025506487 | Q21: =Data!J321 -> 0.021093919
A22: ROU | B22: EAA | C22: =Data!J323 -> 0.055546979 | D22: =Data!J324 -> 0.13227766 | E22: =Data!J325 -> 0.11832742 | F22: =Data!J326 -> 0.10583899 | G22: =Data!J327 -> 0.0029529335 | H22: =Data!J328 -> 0.11694594 | I22: =Data!J329 -> 0.16835476 | J22: =Data!J330 -> 0.1519812 | K22: =Data!J331 -> 0.1130759 | L22: =Data!J332 -> 0.091885806 | M22: =Data!J333 -> 0.086386553 | N22: =Data!J334 -> 0.075806644 | O22: =Data!J335 -> 0.057013908 | P22: =Data!J336 -> 0.073798649 | Q22: =Data!J337 -> 0.071714828
A23: SRB | B23: EAA | C23: =Data!J339 -> 0.045649063 | D23: =Data!J340 -> 0.054316458 | E23: =Data!J341 -> 0.067422557 | F23: =Data!J342 -> 0.072097338 | G23: =Data!J343 -> 0.016741221 | H23: =Data!J344 -> 0.14084817 | I23: =Data!J345 -> 0.13444606 | J23: =Data!J346 -> 0.18200329 | K23: =Data!J347 -> 0.10550686 | L23: =Data!J348 -> 0.066107182 | M23: =Data!J349 -> 0.075674344 | N23: =Data!J350 -> 0.050056579 | O23: =Data!J351 -> 0.054625113 | P23: =Data!J352 -> 0.049093011 | Q23: =Data!J353 -> 0.0343062
A24: SVN | B24: EAA | C24: =Data!J355 -> 0.039490777 | D24: =Data!J356 -> 0.065483629 | E24: =Data!J357 -> 0.066385175 | F24: =Data!J358 -> 0.059392873 | G24: =Data!J359 -> -0.02948505 | H24: =Data!J360 -> 0.11317929 | I24: =Data!J361 -> 0.093599846 | J24: =Data!J362 -> 0.12688928 | K24: =Data!J363 -> 0.052401747 | L24: =Data!J364 -> 0.054682869 | M24: =Data!J365 -> 0.050442602 | N24: =Data!J366 -> 0.065676833 | O24: =Data!J367 -> 0.052089871 | P24: =Data!J368 -> 0.051419709 | Q24: =Data!J369 -> 0.051174401
A25: HRV | B25: EAA | C25: =Data!J371 -> 0.034805308 | D25: =Data!J372 -> 0.045406769 | E25: =Data!J373 -> 0.05007038 | F25: =Data!J374 -> 0.05151283 | G25: =Data!J375 -> -0.075942451 | H25: =Data!J376 -> 0.14978321 | I25: =Data!J377 -> 0.15889613 | J25: =Data!J378 -> 0.17127644 | K25: =Data!J379 -> 0.084859199 | L25: =Data!J380 -> 0.082295425 | M25: =Data!J381 -> 0.065497957 | N25: =Data!J382 -> 0.056121934 | O25: =Data!J383 -> 0.051323712 | P25: =Data!J384 -> 0.051909091 | Q25: =Data!J385 -> 0.047878316
A26: MNE | B26: EAA | C26: =Data!J387 -> 0.091412742 | D26: =Data!J388 -> 0.078680203 | E26: =Data!J389 -> 0.082352941 | F26: =Data!J390 -> 0.065217391 | G26: =Data!J391 -> -0.15510204 | H26: =Data!J392 -> 0.1884058 | I26: =Data!J393 -> 0.20731707 | J26: =Data!J394 -> 0.19023569 | K26: =Data!J395 -> 0.080622348 | L26: =Data!J396 -> 0.082460733 | M26: =Data!J397 -> 0.054413543 | N26: =Data!J398 -> 0.064220183 | O26: =Data!J399 -> 0.061422414 | P26: =Data!J400 -> 0.059898477 | Q26: =Data!J401 -> 0.058429119
A27: MKD | B27: EAA | C27: =Data!J403 -> 0.064120225 | D27: =Data!J404 -> 0.039207115 | E27: =Data!J405 -> 0.069194804 | F27: =Data!J406 -> 0.048117661 | G27: =Data!J407 -> -0.033781833 | H27: =Data!J408 -> 0.08988764 | I27: =Data!J409 -> 0.11877605 | J27: =Data!J410 -> 0.10639888 | K27: =Data!J411 -> 0.067758691 | L27: =Data!J412 -> 0.082761983 | M27: =Data!J413 -> 0.072565812 | N27: =Data!J414 -> 0.069531899 | O27: =Data!J415 -> 0.055140796 | P27: =Data!J416 -> 0.053873733 | Q27: =Data!J417 -> 0.051420117
A28: RUS | B28: EAA | C28: =Data!J419 -> 0.030434473 | D28: =Data!J420 -> 0.072732482 | E28: =Data!J421 -> 0.13085897 | F28: =Data!J422 -> 0.055329951 | G28: =Data!J423 -> -0.017792264 | H28: =Data!J424 -> 0.25143795 | I28: =Data!J425 -> 0.16532575 | J28: =Data!J426 -> 0.10996298 | K28: =Data!J427 -> 0.16098822 | L28: =Data!J428 -> 0.059018055 | M28: =Data!J429 -> 0.10087252 | N28: =Data!J430 -> 0.07246744 | O28: =Data!J431 -> 0.04676368 | P28: =Data!J432 -> 0.070421773 | Q28: =Data!J433 -> 0.074451036
A29: UKR | B29: EAA | C29: =Data!J435 -> 0.19955847 | D29: =Data!J436 -> 0.24979773 | E29: =Data!J437 -> 0.19423862 | F29: =Data!J438 -> 0.11709687 | G29: =Data!J439 -> 0.061558383 | H29: =Data!J440 -> 0.29104957 | I29: =Data!J441 -> -0.038845318 | J29: =Data!J442 -> 0.26509274 | K29: =Data!J443 -> 0.15606914 | L29: =Data!J444 -> 0.16558954 | M29: =Data!J445 -> 0.0962395 | N29: =Data!J446 -> 0.18650762 | O29: =Data!J447 -> 0.1972805 | P29: =Data!J448 -> 0.20549831 | Q29: =Data!J449 -> 0.18495488
A30: TUR | B30: EAA | C30: =Data!J451 -> 0.11721451 | D30: =Data!J452 -> 0.19830494 | E30: =Data!J453 -> 0.20781969 | F30: =Data!J454 -> 0.15646214 | G30: =Data!J455 -> 0.16802626 | H30: =Data!J456 -> 0.4457836 | I30: =Data!J457 -> 1.0616455 | J30: =Data!J458 -> 0.76769656 | K30: =Data!J459 -> 0.64907884 | L30: =Data!J460 -> 0.4155377 | M30: =Data!J461 -> 0.30665276 | N30: =Data!J462 -> 0.20545857 | O30: =Data!J463 -> 0.15906133 | P30: =Data!J464 -> 0.13635358 | Q30: =Data!J465 -> 0.1350944
A31: KAZ | B31: EAA | C31: =Data!J467 -> 0.14888467 | D31: =Data!J468 -> 0.15770766 | E31: =Data!J469 -> 0.13683038 | F31: =Data!J470 -> 0.12476783 | G31: =Data!J471 -> 0.016055771 | H31: =Data!J472 -> 0.18829077 | I31: =Data!J473 -> 0.23601614 | J31: =Data!J474 -> 0.1510788 | K31: =Data!J475 -> 0.14442983 | L31: =Data!J476 -> 0.16763972 | M31: =Data!J477 -> 0.15262336 | N31: =Data!J478 -> 0.12378759 | O31: =Data!J479 -> 0.12436113 | P31: =Data!J480 -> 0.11494272 | Q31: =Data!J481 -> 0.10755211
A32: CHN | B32: EAA | C32: =Data!J483 -> 0.083531017 | D32: =Data!J484 -> 0.11323002 | E32: =Data!J485 -> 0.10458932 | F32: =Data!J486 -> 0.074638404 | G32: =Data!J487 -> 0.028825923 | H32: =Data!J488 -> 0.1342736 | I32: =Data!J489 -> 0.051290868 | J32: =Data!J490 -> 0.048817557 | K32: =Data!J491 -> 0.04156353 | L32: =Data!J492 -> 0.039918663 | M32: =Data!J493 -> 0.05812819 | N32: =Data!J494 -> 0.056284419 | O32: =Data!J495 -> 0.055110723 | P32: =Data!J496 -> 0.05559696 | Q32: =Data!J497 -> 0.056332149
A33: IND | B33: EAA | C33: =Data!J499 -> 0.11754291 | D33: =Data!J500 -> 0.11115583 | E33: =Data!J501 -> 0.12358235 | F33: =Data!J502 -> 0.057435636 | G33: =Data!J503 -> -0.025866181 | H33: =Data!J504 -> 0.18635267 | I33: =Data!J505 -> 0.11774009 | J33: =Data!J506 -> 0.10745392 | K33: =Data!J507 -> 0.10105933 | L33: =Data!J508 -> 0.084341894 | M33: =Data!J509 -> 0.13607713 | N33: =Data!J510 -> 0.1289866 | O33: =Data!J511 -> 0.13175973 | P33: =Data!J512 -> 0.12188021 | Q33: =Data!J513 -> 0.11020998
A34: KOR | B34: EAA | C34: =Data!J515 -> 0.052993486 | D34: =Data!J516 -> 0.055209135 | E34: =Data!J517 -> 0.037606696 | F34: =Data!J518 -> 0.016751621 | G34: =Data!J519 -> 0.0087621717 | H34: =Data!J520 -> 0.080278071 | I34: =Data!J521 -> 0.046970842 | J34: =Data!J522 -> 0.034108334 | K34: =Data!J523 -> 0.065052875 | L34: =Data!J524 -> 0.043861633 | M34: =Data!J525 -> 0.05955636 | N34: =Data!J526 -> 0.048119645 | O34: =Data!J527 -> 0.039327691 | P34: =Data!J528 -> 0.035685373 | Q34: =Data!J529 -> 0.034515309
A35: ZAF | B35: EAA | C35: =Data!J531 -> 0.076628838 | D35: =Data!J532 -> 0.066947506 | E35: =Data!J533 -> 0.056122359 | F35: =Data!J534 -> 0.048855252 | G35: =Data!J535 -> -0.011101808 | H35: =Data!J536 -> 0.11578425 | I35: =Data!J537 -> 0.074069897 | J35: =Data!J538 -> 0.055664224 | K35: =Data!J539 -> 0.044727872 | L35: =Data!J540 -> 0.039352869 | M35: =Data!J541 -> 0.057182938 | N35: =Data!J542 -> 0.052561219 | O35: =Data!J543 -> 0.056710257 | P35: =Data!J544 -> 0.064822389 | Q35: =Data!J545 -> 0.068074121
A36: MAR | B36: EAA | C36: =Data!J547 -> 0.014961229 | D36: =Data!J548 -> 0.049942883 | E36: =Data!J549 -> 0.040334233 | F36: =Data!J550 -> 0.037314682 | G36: =Data!J551 -> -0.070460705 | H36: =Data!J552 -> 0.10766347 | I36: =Data!J553 -> 0.044635583 | J36: =Data!J554 -> 0.11405732 | K36: =Data!J555 -> 0.086784147 | L36: =Data!J556 -> 0.065422992 | M36: =Data!J557 -> 0.0531814 | N36: =Data!J558 -> 0.047821902 | O36: =Data!J559 -> 0.052349977 | P36: =Data!J560 -> 0.053499375 | Q36: =Data!J561 -> 0.074016561
A37: TUN | B37: EAA | C37: =Data!J563 -> 0.061135857 | D37: =Data!J564 -> 0.070521566 | E37: =Data!J565 -> 0.10763651 | F37: =Data!J566 -> 0.088326401 | G37: =Data!J567 -> -0.028218265 | H37: =Data!J568 -> 0.10075314 | I37: =Data!J569 -> 0.060057777 | J37: =Data!J570 -> 0.074225473 | K37: =Data!J571 -> 0.067160692 | L37: =Data!J572 -> 0.073756647 | M37: =Data!J573 -> 0.057620601 | N37: =Data!J574 -> 0.091995813 | O37: =Data!J575 -> 0.082278162 | P37: =Data!J576 -> 0.066654237 | Q37: =Data!J577 -> 0.048898794
A38: ESP | B38: EAA | C38: =Data!J579 -> 0.032986542 | D38: =Data!J580 -> 0.041897825 | E38: =Data!J581 -> 0.036119041 | F38: =Data!J582 -> 0.034175273 | G38: =Data!J583 -> -0.099305262 | H38: =Data!J584 -> 0.094101186 | I38: =Data!J585 -> 0.11363287 | J38: =Data!J586 -> 0.08752344 | K38: =Data!J587 -> 0.06837624 | L38: =Data!J588 -> 0.057187897 | M38: =Data!J589 -> 0.052638742 | N38: =Data!J590 -> 0.041400361 | O38: =Data!J591 -> 0.037314722 | P38: =Data!J592 -> 0.038537791 | Q38: =Data!J593 -> 0.039272275
A39: PRT | B39: EAA | C39: =Data!J595 -> 0.038965383 | D39: =Data!J596 -> 0.048985943 | E39: =Data!J597 -> 0.048539717 | F39: =Data!J598 -> 0.046292683 | G39: =Data!J599 -> -0.062753508 | H39: =Data!J600 -> 0.076903945 | I39: =Data!J601 -> 0.12688808 | J39: =Data!J602 -> 0.10817347 | K39: =Data!J603 -> 0.076937303 | L39: =Data!J604 -> 0.059728662 | M39: =Data!J605 -> 0.045407403 | N39: =Data!J606 -> 0.037389552 | O39: =Data!J607 -> 0.038612116 | P39: =Data!J608 -> 0.04379478 | Q39: =Data!J609 -> 0.039641626
A40: FRA | B40: EAA | C40: =Data!J611 -> 0.013818479 | D40: =Data!J612 -> 0.026821159 | E40: =Data!J613 -> 0.027787475 | F40: =Data!J614 -> 0.032627709 | G40: =Data!J615 -> -0.046842172 | H40: =Data!J616 -> 0.081879669 | I40: =Data!J617 -> 0.058171524 | J40: =Data!J618 -> 0.067758101 | K40: =Data!J619 -> 0.035785492 | L40: =Data!J620 -> 0.019017184 | M40: =Data!J621 -> 0.026117831 | N40: =Data!J622 -> 0.027932542 | O40: =Data!J623 -> 0.029915275 | P40: =Data!J624 -> 0.033828929 | Q40: =Data!J625 -> 0.033067299
A41: ITA | B41: EAA | C41: =Data!J627 -> 0.024998798 | D41: =Data!J628 -> 0.02324531 | E41: =Data!J629 -> 0.019060012 | F41: =Data!J630 -> 0.01481094 | G41: =Data!J631 -> -0.074309755 | H41: =Data!J632 -> 0.10329279 | I41: =Data!J633 -> 0.084428307 | J41: =Data!J634 -> 0.072404871 | K41: =Data!J635 -> 0.027670179 | L41: =Data!J636 -> 0.025440162 | M41: =Data!J637 -> 0.020606275 | N41: =Data!J638 -> 0.016775291 | O41: =Data!J639 -> 0.021389188 | P41: =Data!J640 -> 0.025800548 | Q41: =Data!J641 -> 0.026764585

Sheet IAS29_test
A1: CPI annual average [sourced]: Capital IQ consumerPriceInflation, % stored / 100. Source lines in column S
A2: iso3 | B2: region | C2: 2015 | D2: 2016 | E2: 2017 | F2: 2018 | G2: 2019 | H2: 2020 | I2: 2021 | J2: 2022 | K2: 2023 | L2: 2024 | M2: 2025 | N2: 2026 | O2: 2027 | P2: 2028 | Q2: 2029 | R2: 2030 | S2: source
A3: MEX | B3: Mexico | C3: 0.0272 | D3: 0.0282 | E3: 0.0604 | F3: 0.049 | G3: 0.0364 | H3: 0.034 | I3: 0.0569 | J3: 0.079 | K3: 0.0553 | L3: 0.0472 | M3: 0.0381 | N3: 0.0376 | O3: 0.039 | P3: 0.0372 | Q3: 0.0321 | R3: 0.0255 | S3: capiq-sales-drivers-M1_2026-10-24.md; capiq-sales-drivers-X1_2026-10-24.md L29-L47
A4: USA | B4: North America | C4: 0.0012 | D4: 0.0126 | E4: 0.0213 | F4: 0.0244 | G4: 0.0181 | H4: 0.0123 | I4: 0.047 | J4: 0.08 | K4: 0.0412 | L4: 0.0295 | M4: 0.0271 | N4: 0.0336 | O4: 0.0242 | P4: 0.0208 | Q4: 0.02 | R4: 0.0206 | S4: capiq-sales-drivers-M1_2026-10-24.md; capiq-sales-drivers-X1_2026-10-24.md L44-L69
A5: CAN | B5: North America | C5: 0.0113 | D5: 0.0143 | E5: 0.016 | F5: 0.0227 | G5: 0.0195 | H5: 0.0072 | I5: 0.034 | J5: 0.068 | K5: 0.0388 | L5: 0.0238 | M5: 0.0207 | N5: 0.0278 | O5: 0.0279 | P5: 0.0206 | Q5: 0.0182 | R5: 0.0186 | S5: capiq-sales-drivers-M1_2026-10-24.md; capiq-sales-drivers-X1_2026-10-24.md L59-L91
A6: ARG | B6: Latin America | C6: 0.1636 | D6: 0.3752 | E6: 0.2528 | F6: 0.3428 | G6: 0.5355 | H6: 0.4202 | I6: 0.4841 | J6: 0.7243 | K6: 1.3349 | L6: 2.1988 | M6: 0.4192 | N6: 0.327 | O6: 0.1779 | P6: 0.083 | Q6: 0.0667 | R6: 0.0709 | S6: capiq-sales-drivers-M2_2026-10-24.md; capiq-sales-drivers-X1_2026-10-24.md L32-L113
A7: BRA | B7: Latin America | C7: 0.0903 | D7: 0.0874 | E7: 0.0345 | F7: 0.0366 | G7: 0.0373 | H7: 0.0321 | I7: 0.083 | J7: 0.0928 | K7: 0.0459 | L7: 0.0437 | M7: 0.0502 | N7: 0.0459 | O7: 0.0487 | P7: 0.0351 | Q7: 0.0362 | R7: 0.0321 | S7: capiq-sales-drivers-M2_2026-10-24.md; capiq-sales-drivers-X1_2026-10-24.md L47-L135
A8: CHL | B8: Latin America | C8: 0.0435 | D8: 0.0378 | E8: 0.0218 | F8: 0.0244 | G8: 0.0256 | H8: 0.0305 | I8: 0.0452 | J8: 0.1164 | K8: 0.0758 | L8: 0.0427 | M8: 0.0421 | N8: 0.0375 | O8: 0.0366 | P8: 0.0289 | Q8: 0.0271 | R8: 0.0309 | S8: capiq-sales-drivers-M2_2026-10-24.md; capiq-sales-drivers-X1_2026-10-24.md L62-L157
A9: COL | B9: Latin America | C9: 0.0499 | D9: 0.0751 | E9: 0.0432 | F9: 0.0324 | G9: 0.0352 | H9: 0.0253 | I9: 0.035 | J9: 0.1018 | K9: 0.1174 | L9: 0.0661 | M9: 0.0514 | N9: 0.06 | O9: 0.0605 | P9: 0.0382 | Q9: 0.0344 | R9: 0.033 | S9: capiq-sales-drivers-M2_2026-10-24.md; capiq-sales-drivers-X1_2026-10-24.md L77-L179
A10: CRI | B10: Latin America | C10: 0.008 | D10: -0.0002 | E10: 0.0163 | F10: 0.0222 | G10: 0.021 | H10: 0.0072 | I10: 0.0173 | J10: 0.0827 | K10: 0.0053 | L10: -0.0041 | M10: -0.0007 | N10: -0.0056 | O10: 0.0344 | P10: 0.0195 | Q10: 0.0171 | R10: 0.0218 | S10: capiq-sales-drivers-M3_2026-10-24.md; capiq-sales-drivers-X1_2026-10-24.md L32-L201
A11: ECU | B11: Latin America | C11: 0.0397 | D11: 0.0173 | E11: 0.0042 | F11: -0.0022 | G11: 0.0027 | H11: -0.0034 | I11: 0.0013 | J11: 0.0347 | K11: 0.0222 | L11: 0.0155 | M11: 0.0071 | N11: 0.0237 | O11: 0.0269 | P11: 0.0218 | Q11: 0.0209 | R11: 0.0207 | S11: capiq-sales-drivers-M3_2026-10-24.md; capiq-sales-drivers-X1_2026-10-24.md L47-L223
A12: SLV | B12: Latin America | C12: -0.0073 | D12: 0.006 | E12: 0.0101 | F12: 0.0109 | G12: 0.0007 | H12: -0.0037 | I12: 0.0347 | J12: 0.072 | K12: 0.0405 | L12: 0.0085 | M12: 0.0026 | N12: 0.0242 | O12: 0.0262 | P12: 0.0246 | Q12: 0.0256 | R12: 0.0265 | S12: capiq-sales-drivers-M3_2026-10-24.md; capiq-sales-drivers-X1_2026-10-24.md L62-L245
A13: GTM | B13: Latin America | C13: 0.0239 | D13: 0.0445 | E13: 0.0442 | F13: 0.0375 | G13: 0.037 | H13: 0.0321 | I13: 0.0426 | J13: 0.0689 | K13: 0.0621 | L13: 0.0287 | M13: 0.0158 | N13: 0.031 | O13: 0.0354 | P13: 0.0355 | Q13: 0.0313 | R13: 0.0304 | S13: capiq-sales-drivers-M3_2026-10-24.md L77-L93
... A42: ITA | B42: EAA | C42: 0.0016 | D42: -0.0006 | E42: 0.0133 | F42: 0.0124 | G42: 0.0066 | H42: -0.0017 | I42: 0.0195 | J42: 0.0875 | K42: 0.0591 | L42: 0.0108 | M42: 0.0163 | N42: 0.0299 | O42: 0.0261 | P42: 0.0151 | Q42: 0.0177 | R42: 0.0183 | S42: Informacion_BIMBO_macro.txt L948-L963
A44: Cumulative 3-year inflation ending in each year [calc] = (1+CPI t-2)(1+CPI t-1)(1+CPI t) - 1; orange = 100% or more (IAS 29 para 3(e))
A45: iso3 | B45: region | E45: 2017 | F45: 2018 | G45: 2019 | H45: 2020 | I45: 2021 | J45: 2022 | K45: 2023 | L45: 2024 | M45: 2025 | N45: 2026 | O45: 2027 | P45: 2028 | Q45: 2029 | R45: 2030
A46: MEX | B46: Mexico | E46: =IF(COUNT(C3:E3)<3,"",(1+C3)*(1+D3)*(1+E3)-1) -> 0.11995953 | F46: =IF(COUNT(D3:F3)<3,"",(1+D3)*(1+E3)*(1+F3)-1) -> 0.14372814 | G46: =IF(COUNT(E3:G3)<3,"",(1+E3)*(1+F3)*(1+G3)-1) -> 0.15284949 | H46: =IF(COUNT(F3:H3)<3,"",(1+F3)*(1+G3)*(1+H3)-1) -> 0.12414784 | I46: =IF(COUNT(G3:I3)<3,"",(1+G3)*(1+H3)*(1+I3)-1) -> 0.13261378 | J46: =IF(COUNT(H3:J3)<3,"",(1+H3)*(1+I3)*(1+J3)-1) -> 0.17916853 | K46: =IF(COUNT(I3:K3)<3,"",(1+I3)*(1+J3)*(1+K3)-1) -> 0.20345895 | L46: =IF(COUNT(J3:L3)<3,"",(1+J3)*(1+K3)*(1+L3)-1) -> 0.19241386 | ... R46: =IF(COUNT(P3:R3)<3,"",(1+P3)*(1+Q3)*(1+R3)-1) -> 0.09779172
A47: USA | B47: North America | E47: =IF(COUNT(C4:E4)<3,"",(1+C4)*(1+D4)*(1+E4)-1) -> 0.035409382 | F47: =IF(COUNT(D4:F4)<3,"",(1+D4)*(1+E4)*(1+F4)-1) -> 0.059402088 | G47: =IF(COUNT(E4:G4)<3,"",(1+E4)*(1+F4)*(1+G4)-1) -> 0.065156297 | H47: =IF(COUNT(F4:H4)<3,"",(1+F4)*(1+G4)*(1+H4)-1) -> 0.055769822 | I47: =IF(COUNT(G4:I4)<3,"",(1+G4)*(1+H4)*(1+I4)-1) -> 0.079061894 | J47: =IF(COUNT(H4:J4)<3,"",(1+H4)*(1+I4)*(1+J4)-1) -> 0.14466835 | K47: =IF(COUNT(I4:K4)<3,"",(1+I4)*(1+J4)*(1+K4)-1) -> 0.17734731 | L47: =IF(COUNT(J4:L4)<3,"",(1+J4)*(1+K4)*(1+L4)-1) -> 0.15766863 | ... R47: =IF(COUNT(P4:R4)<3,"",(1+P4)*(1+Q4)*(1+R4)-1) -> 0.06266505
A48: CAN | B48: North America | E48: =IF(COUNT(C5:E5)<3,"",(1+C5)*(1+D5)*(1+E5)-1) -> 0.042173775 | F48: =IF(COUNT(D5:F5)<3,"",(1+D5)*(1+E5)*(1+F5)-1) -> 0.053921804 | G48: =IF(COUNT(E5:G5)<3,"",(1+E5)*(1+F5)*(1+G5)-1) -> 0.059324932 | H48: =IF(COUNT(F5:H5)<3,"",(1+F5)*(1+G5)*(1+H5)-1) -> 0.050149677 | I48: =IF(COUNT(G5:I5)<3,"",(1+G5)*(1+H5)*(1+I5)-1) -> 0.061752974 | J48: =IF(COUNT(H5:J5)<3,"",(1+H5)*(1+I5)*(1+J5)-1) -> 0.11226305 | K48: =IF(COUNT(I5:K5)<3,"",(1+I5)*(1+J5)*(1+K5)-1) -> 0.14715931 | L48: =IF(COUNT(J5:L5)<3,"",(1+J5)*(1+K5)*(1+L5)-1) -> 0.13584303 | ... R48: =IF(COUNT(P5:R5)<3,"",(1+P5)*(1+Q5)*(1+R5)-1) -> 0.058503574
A49: ARG | B49: Latin America | E49: =IF(COUNT(C6:E6)<3,"",(1+C6)*(1+D6)*(1+E6)-1) -> 1.0047089 | F49: =IF(COUNT(D6:F6)<3,"",(1+D6)*(1+E6)*(1+F6)-1) -> 1.3134437 | G49: =IF(COUNT(E6:G6)<3,"",(1+E6)*(1+F6)*(1+G6)-1) -> 1.58311 | H49: =IF(COUNT(F6:H6)<3,"",(1+F6)*(1+G6)*(1+H6)-1) -> 1.9282669 | I49: =IF(COUNT(G6:I6)<3,"",(1+G6)*(1+H6)*(1+I6)-1) -> 2.2364022 | J49: =IF(COUNT(H6:J6)<3,"",(1+H6)*(1+I6)*(1+J6)-1) -> 2.6343396 | K49: =IF(COUNT(I6:K6)<3,"",(1+I6)*(1+J6)*(1+K6)-1) -> 4.9750876 | L49: =IF(COUNT(J6:L6)<3,"",(1+J6)*(1+K6)*(1+L6)-1) -> 11.878587 | ... R49: =IF(COUNT(P6:R6)<3,"",(1+P6)*(1+Q6)*(1+R6)-1) -> 0.23714234
A50: BRA | B50: Latin America | E50: =IF(COUNT(C7:E7)<3,"",(1+C7)*(1+D7)*(1+E7)-1) -> 0.22649515 | F50: =IF(COUNT(D7:F7)<3,"",(1+D7)*(1+E7)*(1+F7)-1) -> 0.1660872 | G50: =IF(COUNT(E7:G7)<3,"",(1+E7)*(1+F7)*(1+G7)-1) -> 0.11236183 | H50: =IF(COUNT(F7:H7)<3,"",(1+F7)*(1+G7)*(1+H7)-1) -> 0.10978119 | I50: =IF(COUNT(G7:I7)<3,"",(1+G7)*(1+H7)*(1+I7)-1) -> 0.15945691 | J50: =IF(COUNT(H7:J7)<3,"",(1+H7)*(1+I7)*(1+J7)-1) -> 0.22149283 | K50: =IF(COUNT(I7:K7)<3,"",(1+I7)*(1+J7)*(1+K7)-1) -> 0.23782516 | L50: =IF(COUNT(J7:L7)<3,"",(1+J7)*(1+K7)*(1+L7)-1) -> 0.19290685 | ... R50: =IF(COUNT(P7:R7)<3,"",(1+P7)*(1+Q7)*(1+R7)-1) -> 0.10700014
A51: CHL | B51: Latin America | E51: =IF(COUNT(C8:E8)<3,"",(1+C8)*(1+D8)*(1+E8)-1) -> 0.10655249 | F51: =IF(COUNT(D8:F8)<3,"",(1+D8)*(1+E8)*(1+F8)-1) -> 0.086298387 | G51: =IF(COUNT(E8:G8)<3,"",(1+E8)*(1+F8)*(1+G8)-1) -> 0.073528257 | H51: =IF(COUNT(F8:H8)<3,"",(1+F8)*(1+G8)*(1+H8)-1) -> 0.082668692 | I51: =IF(COUNT(G8:I8)<3,"",(1+G8)*(1+H8)*(1+I8)-1) -> 0.10465181 | J51: =IF(COUNT(H8:J8)<3,"",(1+H8)*(1+I8)*(1+J8)-1) -> 0.20245055 | K51: =IF(COUNT(I8:K8)<3,"",(1+I8)*(1+J8)*(1+K8)-1) -> 0.25530937 | L51: =IF(COUNT(J8:L8)<3,"",(1+J8)*(1+K8)*(1+L8)-1) -> 0.25230681 | ... R51: =IF(COUNT(P8:R8)<3,"",(1+P8)*(1+Q8)*(1+R8)-1) -> 0.089437791
A52: COL | B52: Latin America | E52: =IF(COUNT(C9:E9)<3,"",(1+C9)*(1+D9)*(1+E9)-1) -> 0.17750938 | F52: =IF(COUNT(D9:F9)<3,"",(1+D9)*(1+E9)*(1+F9)-1) -> 0.15788236 | G52: =IF(COUNT(E9:G9)<3,"",(1+E9)*(1+F9)*(1+G9)-1) -> 0.11491007 | H52: =IF(COUNT(F9:H9)<3,"",(1+F9)*(1+G9)*(1+H9)-1) -> 0.095779614 | I52: =IF(COUNT(G9:I9)<3,"",(1+G9)*(1+H9)*(1+I9)-1) -> 0.09853923 | J52: =IF(COUNT(H9:J9)<3,"",(1+H9)*(1+I9)*(1+J9)-1) -> 0.16921418 | K52: =IF(COUNT(I9:K9)<3,"",(1+I9)*(1+J9)*(1+K9)-1) -> 0.27424162 | L52: =IF(COUNT(J9:L9)<3,"",(1+J9)*(1+K9)*(1+L9)-1) -> 0.31253042 | ... R52: =IF(COUNT(P9:R9)<3,"",(1+P9)*(1+Q9)*(1+R9)-1) -> 0.10935324
A53: CRI | B53: Latin America | E53: =IF(COUNT(C10:E10)<3,"",(1+C10)*(1+D10)*(1+E10)-1) -> 0.024225514 | F53: =IF(COUNT(D10:F10)<3,"",(1+D10)*(1+E10)*(1+F10)-1) -> 0.038654088 | G53: =IF(COUNT(E10:G10)<3,"",(1+E10)*(1+F10)*(1+G10)-1) -> 0.060677959 | H53: =IF(COUNT(F10:H10)<3,"",(1+F10)*(1+G10)*(1+H10)-1) -> 0.051180597 | I53: =IF(COUNT(G10:I10)<3,"",(1+G10)*(1+H10)*(1+I10)-1) -> 0.046141676 | J53: =IF(COUNT(H10:J10)<3,"",(1+H10)*(1+I10)*(1+J10)-1) -> 0.10936101 | K53: =IF(COUNT(I10:K10)<3,"",(1+I10)*(1+J10)*(1+K10)-1) -> 0.10726829 | L53: =IF(COUNT(J10:L10)<3,"",(1+J10)*(1+K10)*(1+L10)-1) -> 0.083975713 | ... R53: =IF(COUNT(P10:R10)<3,"",(1+P10)*(1+Q10)*(1+R10)-1) -> 0.059538599
A54: ECU | B54: Latin America | E54: =IF(COUNT(C11:E11)<3,"",(1+C11)*(1+D11)*(1+E11)-1) -> 0.062129095 | F54: =IF(COUNT(D11:F11)<3,"",(1+D11)*(1+E11)*(1+F11)-1) -> 0.0193252 | G54: =IF(COUNT(E11:G11)<3,"",(1+E11)*(1+F11)*(1+G11)-1) -> 0.0046961351 | H54: =IF(COUNT(F11:H11)<3,"",(1+F11)*(1+G11)*(1+H11)-1) -> -0.0029076198 | I54: =IF(COUNT(G11:I11)<3,"",(1+G11)*(1+H11)*(1+I11)-1) -> 0.00058989807 | J54: =IF(COUNT(H11:J11)<3,"",(1+H11)*(1+I11)*(1+J11)-1) -> 0.032522557 | K54: =IF(COUNT(I11:K11)<3,"",(1+I11)*(1+J11)*(1+K11)-1) -> 0.059045311 | L54: =IF(COUNT(J11:L11)<3,"",(1+J11)*(1+K11)*(1+L11)-1) -> 0.07406423 | ... R54: =IF(COUNT(P11:R11)<3,"",(1+P11)*(1+Q11)*(1+R11)-1) -> 0.064748941
A55: SLV | B55: Latin America | E55: =IF(COUNT(C12:E12)<3,"",(1+C12)*(1+D12)*(1+E12)-1) -> 0.0087426276 | F55: =IF(COUNT(D12:F12)<3,"",(1+D12)*(1+E12)*(1+F12)-1) -> 0.027236751 | G55: =IF(COUNT(E12:G12)<3,"",(1+E12)*(1+F12)*(1+G12)-1) -> 0.021824867 | H55: =IF(COUNT(F12:H12)<3,"",(1+F12)*(1+G12)*(1+H12)-1) -> 0.0078646818 | I55: =IF(COUNT(G12:I12)<3,"",(1+G12)*(1+H12)*(1+I12)-1) -> 0.03159322 | J55: =IF(COUNT(H12:J12)<3,"",(1+H12)*(1+I12)*(1+J12)-1) -> 0.10509437 | K55: =IF(COUNT(I12:K12)<3,"",(1+I12)*(1+J12)*(1+K12)-1) -> 0.15412094 | L55: =IF(COUNT(J12:L12)<3,"",(1+J12)*(1+K12)*(1+L12)-1) -> 0.12489704 | ... R55: =IF(COUNT(P12:R12)<3,"",(1+P12)*(1+Q12)*(1+R12)-1) -> 0.078676749
A56: GTM | B56: Latin America | E56: =IF(COUNT(C13:E13)<3,"",(1+C13)*(1+D13)*(1+E13)-1) -> 0.11673384 | F56: =IF(COUNT(D13:F13)<3,"",(1+D13)*(1+E13)*(1+F13)-1) -> 0.13156691 | G56: =IF(COUNT(E13:G13)<3,"",(1+E13)*(1+F13)*(1+G13)-1) -> 0.12344173 | H56: =IF(COUNT(F13:H13)<3,"",(1+F13)*(1+G13)*(1+H13)-1) -> 0.11042349 | I56: =IF(COUNT(G13:I13)<3,"",(1+G13)*(1+H13)*(1+I13)-1) -> 0.11588196 | J56: =IF(COUNT(H13:J13)<3,"",(1+H13)*(1+I13)*(1+J13)-1) -> 0.15020851 | K56: =IF(COUNT(I13:K13)<3,"",(1+I13)*(1+J13)*(1+K13)-1) -> 0.18364156 | L56: =IF(COUNT(J13:L13)<3,"",(1+J13)*(1+K13)*(1+L13)-1) -> 0.16786119 | ... R56: =IF(COUNT(P13:R13)<3,"",(1+P13)*(1+Q13)*(1+R13)-1) -> 0.10037565
A57: HND | B57: Latin America | E57: =IF(COUNT(C14:E14)<3,"",(1+C14)*(1+D14)*(1+E14)-1) -> 0.10130414 | F57: =IF(COUNT(D14:F14)<3,"",(1+D14)*(1+E14)*(1+F14)-1) -> 0.11400821 | G57: =IF(COUNT(E14:G14)<3,"",(1+E14)*(1+F14)*(1+G14)-1) -> 0.13190262 | H57: =IF(COUNT(F14:H14)<3,"",(1+F14)*(1+G14)*(1+H14)-1) -> 0.12689275 | I57: =IF(COUNT(G14:I14)<3,"",(1+G14)*(1+H14)*(1+I14)-1) -> 0.12829664 | J57: =IF(COUNT(H14:J14)<3,"",(1+H14)*(1+I14)*(1+J14)-1) -> 0.17932242 | K57: =IF(COUNT(I14:K14)<3,"",(1+I14)*(1+J14)*(1+K14)-1) -> 0.21568116 | L57: =IF(COUNT(J14:L14)<3,"",(1+J14)*(1+K14)*(1+L14)-1) -> 0.21719378 | ... R57: =IF(COUNT(P14:R14)<3,"",(1+P14)*(1+Q14)*(1+R14)-1) -> 0.12247912
... A85: ITA | B85: EAA | E85: =IF(COUNT(C42:E42)<3,"",(1+C42)*(1+D42)*(1+E42)-1) -> 0.014312327 | F85: =IF(COUNT(D42:F42)<3,"",(1+D42)*(1+E42)*(1+F42)-1) -> 0.025249401 | G85: =IF(COUNT(E42:G42)<3,"",(1+E42)*(1+F42)*(1+G42)-1) -> 0.032635628 | H85: =IF(COUNT(F42:H42)<3,"",(1+F42)*(1+G42)*(1+H42)-1) -> 0.017349401 | I85: =IF(COUNT(G42:I42)<3,"",(1+G42)*(1+H42)*(1+I42)-1) -> 0.024484111 | J85: =IF(COUNT(H42:J42)<3,"",(1+H42)*(1+I42)*(1+J42)-1) -> 0.10682145 | K85: =IF(COUNT(I42:K42)<3,"",(1+I42)*(1+J42)*(1+K42)-1) -> 0.17423079 | L85: =IF(COUNT(J42:L42)<3,"",(1+J42)*(1+K42)*(1+L42)-1) -> 0.16421038 | ... R85: =IF(COUNT(P42:R42)<3,"",(1+P42)*(1+Q42)*(1+R42)-1) -> 0.051972401

Sheet FX
A1: Local currency per USD, annual average [sourced]: BIMBOA/research/Informacion_BIMBO_macro.txt (2015-2025 Banxico FIX for MXN, and CAD/GBP/EUR from 2019, else Capital IQ; 2026-2030 Capital IQ forecast). USD = 1 by definition
A2: currency | B2: 2015 | C2: 2016 | D2: 2017 | E2: 2018 | F2: 2019 | G2: 2020 | H2: 2021 | I2: 2022 | J2: 2023 | K2: 2024 | L2: 2025 | M2: 2026 | N2: 2027 | O2: 2028 | P2: 2029 | Q2: 2030 | R2: source lines
A3: ARS | B3: 9.23 | C3: 14.76 | D3: 16.56 | E3: 28.09 | F3: 48.25 | G3: 70.64 | H3: 95.09 | I3: 130.71 | J3: 296.52 | K3: 916.32 | L3: 1243.79 | M3: 1472.34 | N3: 1695.69 | O3: 1851.17 | P3: 1907.4 | Q3: 1974.33 | R3: L1028 (2015-2025), L1131 (2026-2030)
A4: BRL | B4: 3.33 | C4: 3.49 | D4: 3.19 | E4: 3.65 | F4: 3.94 | G4: 5.15 | H4: 5.39 | I4: 5.16 | J4: 5 | K4: 5.39 | L4: 5.59 | M4: 5.14 | N4: 5.18 | O4: 5.3 | P4: 5.42 | Q4: 5.54 | R4: L1027 (2015-2025), L1130 (2026-2030)
A5: CAD | B5: 1.28 | C5: 1.33 | D5: 1.3 | E5: 1.3 | F5: 1.3269 | G5: 1.3413 | H5: 1.2534 | I5: 1.3011 | J5: 1.3494 | K5: 1.3698 | L5: 1.3975 | M5: 1.39 | N5: 1.36 | O5: 1.33 | P5: 1.29 | Q5: 1.26 | R5: L1026 (2015-2025), L1129 (2026-2030)
A6: CHF | B6: 0.96 | C6: 0.99 | D6: 0.98 | E6: 0.98 | F6: 0.99 | G6: 0.94 | H6: 0.91 | I6: 0.95 | J6: 0.9 | K6: 0.88 | L6: 0.83 | M6: 0.8 | N6: 0.81 | O6: 0.81 | P6: 0.8 | Q6: 0.79 | R6: L1039 (2015-2025), L1142 (2026-2030)
A7: CLP | B7: 650 | C7: 680 | D7: 650 | E7: 640 | F7: 700 | G7: 790 | H7: 760 | I7: 870 | J7: 840 | K7: 940 | L7: 950 | M7: 917 | N7: 931.8 | O7: 901.75 | P7: 906.75 | Q7: 914.72 | R7: L1029 (2015-2025), L1132 (2026-2030)
A8: CNY | B8: 6.28 | C8: 6.64 | D8: 6.76 | E8: 6.62 | F8: 6.91 | G8: 6.9 | H8: 6.45 | I8: 6.73 | J8: 7.08 | K8: 7.2 | L8: 7.19 | M8: 6.79 | N8: 6.66 | O8: 6.62 | P8: 6.59 | Q8: 6.59 | R8: L1045 (2015-2025), L1148 (2026-2030)
A9: COP | B9: 2740 | C9: 3050 | D9: 2950 | E9: 2960 | F9: 3280 | G9: 3690 | H9: 3740 | I9: 4250 | J9: 4330 | K9: 4070 | L9: 4050 | M9: 3484.23 | N9: 3445.24 | O9: 3657.07 | P9: 3715.25 | Q9: 3714.47 | R9: L1030 (2015-2025), L1133 (2026-2030)
A10: CRC | B10: 534.57 | C10: 544.74 | D10: 567.51 | E10: 576.97 | F10: 584.01 | G10: 581.67 | H10: 617.56 | I10: 643.65 | J10: 540.7 | K10: 511.97 | L10: 500.58 | M10: 459.37 | N10: 465.17 | O10: 476.92 | P10: 486.67 | Q10: 500.07 | R10: L1036 (2015-2025), L1139 (2026-2030)
A11: EUR | B11: 0.9 | C11: 0.9 | D11: 0.89 | E11: 0.85 | F11: 0.8934 | G11: 0.8773 | H11: 0.8458 | I11: 0.9515 | J11: 0.9249 | K11: 0.9241 | L11: 0.8863 | M11: 0.87 | N11: 0.89 | O11: 0.89 | P11: 0.86 | Q11: 0.84 | R11: L1052 (2015-2025), L1155 (2026-2030)
A12: GBP | B12: 0.65 | C12: 0.74 | D12: 0.78 | E12: 0.75 | F12: 0.7844 | G12: 0.7798 | H12: 0.7269 | I12: 0.8118 | J12: 0.8041 | K12: 0.7824 | L12: 0.7589 | M12: 0.75 | N12: 0.75 | O12: 0.75 | P12: 0.75 | Q12: 0.75 | R12: L1038 (2015-2025), L1141 (2026-2030)
A13: GTQ | B13: 7.65 | C13: 7.6 | D13: 7.35 | E13: 7.52 | F13: 7.7 | G13: 7.72 | H13: 7.74 | I13: 7.75 | J13: 7.83 | K13: 7.76 | L13: 7.68 | M13: 7.64 | N13: 7.71 | O13: 7.76 | P13: 7.83 | Q13: 7.9 | R13: L1034 (2015-2025), L1137 (2026-2030)
... A18: MAD | B18: 9.76 | C18: 9.81 | D18: 9.69 | E18: 9.39 | F18: 9.62 | G18: 9.49 | H18: 8.99 | I18: 10.16 | J18: 10.13 | K18: 9.94 | L18: 9.35 | M18: 9.32 | N18: 9.62 | O18: 9.75 | P18: 9.65 | Q18: 9.69 | R18: L1050 (2015-2025), L1153 (2026-2030)
A19: MKD | R19: not in source: no FX
A20: MXN | B20: 15.881 | C20: 18.689 | D20: 18.907 | E20: 19.237 | F20: 19.257 | G20: 21.498 | H20: 20.282 | I20: 20.12 | J20: 17.734 | K20: 18.326 | L20: 19.2 | M20: 17.54 | N20: 18.21 | O20: 18.67 | P20: 19.03 | Q20: 19.24 | R20: L1025 (2015-2025), L1128 (2026-2030)
A21: NIO | B21: 27.26 | C21: 28.62 | D21: 30.05 | E21: 31.55 | F21: 33.12 | G21: 34.34 | H21: 35.17 | I21: 35.87 | J21: 36.44 | K21: 36.62 | L21: 36.62 | M21: 36.62 | N21: 36.67 | O21: 38.53 | P21: 40.17 | Q21: 41.89 | R21: L1037 (2015-2025), L1140 (2026-2030)
A22: PEN | B22: 3.18 | C22: 3.38 | D22: 3.26 | E22: 3.29 | F22: 3.34 | G22: 3.5 | H22: 3.88 | I22: 3.83 | J22: 3.74 | K22: 3.75 | L22: 3.57 | M22: 3.41 | N22: 3.42 | O22: 3.44 | P22: 3.45 | Q22: 3.45 | R22: L1031 (2015-2025), L1134 (2026-2030)
A23: PYG | B23: 5200 | C23: 5670 | D23: 5620 | E23: 5730 | F23: 6240 | G23: 6770 | H23: 6770 | I23: 6980 | J23: 7290 | K23: 7560 | L23: 7540 | M23: 6134.11 | N23: 5972.76 | O23: 6224.53 | P23: 6445.97 | Q23: 6660.27 | R23: L1033 (2015-2025), L1136 (2026-2030)
A24: RON | B24: 4.01 | C24: 4.06 | D24: 4.05 | E24: 3.94 | F24: 4.24 | G24: 4.24 | H24: 4.16 | I24: 4.69 | J24: 4.57 | K24: 4.6 | L24: 4.47 | M24: 4.52 | N24: 4.75 | O24: 4.73 | P24: 4.58 | Q24: 4.49 | R24: L1040 (2015-2025), L1143 (2026-2030)
A25: RSD | B25: 108.81 | C25: 111.28 | D25: 107.76 | E25: 100.18 | F25: 105.25 | G25: 103.16 | H25: 99.4 | I25: 111.66 | J25: 108.4 | K25: 108.21 | L25: 103.97 | M25: 102.61 | N25: 102.82 | O25: 100.67 | P25: 99.92 | Q25: 99.68 | R25: L1041 (2015-2025), L1144 (2026-2030)
A26: RUB | B26: 61.11 | C26: 67.03 | D26: 58.31 | E26: 62.74 | F26: 64.72 | G26: 72.21 | H26: 73.66 | I26: 68.57 | J26: 85.29 | K26: 92.6 | L26: 83.55 | M26: 79.93 | N26: 87.56 | O26: 95.88 | P26: 100.67 | Q26: 100.45 | R26: L1043 (2015-2025), L1146 (2026-2030)
A27: TND | B27: 1.96 | C27: 2.15 | D27: 2.42 | E27: 2.65 | F27: 2.93 | G27: 2.81 | H27: 2.79 | I27: 3.1 | J27: 3.11 | K27: 3.11 | L27: 3 | M27: 2.95 | N27: 3.15 | O27: 3.29 | P27: 3.38 | Q27: 3.45 | R27: L1051 (2015-2025), L1154 (2026-2030)
A28: TRY | B28: 2.72 | C28: 3.02 | D28: 3.65 | E28: 4.83 | F28: 5.68 | G28: 7.02 | H28: 8.86 | I28: 16.57 | J28: 23.79 | K28: 32.83 | L28: 39.49 | M28: 46.74 | N28: 54.83 | O28: 60.56 | P28: 64.5 | Q28: 68.7 | R28: L1042 (2015-2025), L1145 (2026-2030)
A29: UAH | B29: 21.84 | C29: 25.55 | D29: 26.6 | E29: 27.2 | F29: 25.83 | G29: 26.96 | H29: 27.28 | I29: 32.3 | J29: 36.57 | K29: 40.16 | L29: 41.69 | M29: 44.25 | N29: 46.55 | O29: 46.98 | P29: 46.43 | Q29: 43.9 | R29: L1044 (2015-2025), L1147 (2026-2030)
A30: USD | B30: 1 | C30: 1 | D30: 1 | E30: 1 | F30: 1 | G30: 1 | H30: 1 | I30: 1 | J30: 1 | K30: 1 | L30: 1 | M30: 1 | N30: 1 | O30: 1 | P30: 1 | Q30: 1
A31: UYU | B31: 27.33 | C31: 30.16 | D31: 28.68 | E31: 30.73 | F31: 35.25 | G31: 42.01 | H31: 43.56 | I31: 41.18 | J31: 38.83 | K31: 40.21 | L31: 41.09 | M31: 40.09 | N31: 42.63 | O31: 44.28 | P31: 45.82 | Q31: 47.29 | R31: L1032 (2015-2025), L1135 (2026-2030)
A32: VES | R32: not in source: no FX
A33: ZAR | B33: 12.76 | C33: 14.71 | D33: 13.33 | E33: 13.24 | F33: 14.45 | G33: 16.47 | H33: 14.78 | I33: 16.36 | J33: 18.45 | K33: 18.33 | L33: 17.89 | M33: 16.39 | N33: 16.61 | O33: 16.77 | P33: 17.05 | Q33: 17.37 | R33: L1049 (2015-2025), L1152 (2026-2030)

Sheet Regional_agg
A1: Regional nominal GDP growth, local currency, constant prior-year FX (same logic as Bimbo ex-FX growth) [calc]. include = 1/0 (team can toggle). GDP USD bn = level (x1000 when stored in trillions: CHL, COL, PRY, KOR) / FX
A2: iso3 | B2: region | C2: include | D2: note | E2: GDP USD bn 2015 | F2: GDP USD bn 2016 | G2: GDP USD bn 2017 | H2: GDP USD bn 2018 | I2: GDP USD bn 2019 | J2: GDP USD bn 2020 | K2: GDP USD bn 2021 | L2: GDP USD bn 2022 | M2: GDP USD bn 2023 | N2: GDP USD bn 2024 | O2: GDP USD bn 2025 | P2: GDP USD bn 2026 | Q2: GDP USD bn 2027 | R2: GDP USD bn 2028 | S2: GDP USD bn 2029 | T2: GDP USD bn 2030
A3: MEX | B3: Mexico | C3: 1 | E3: =IF(N(FX!B20)=0,"",Data!D2/FX!B20) -> 1210.7934 | F3: =IF(N(FX!C20)=0,"",Data!D3/FX!C20) -> 1110.7491 | G3: =IF(N(FX!D20)=0,"",Data!D4/FX!D20) -> 1191.9506 | H3: =IF(N(FX!E20)=0,"",Data!D5/FX!E20) -> 1256.7796 | I3: =IF(N(FX!F20)=0,"",Data!D6/FX!F20) -> 1304.5552 | J3: =IF(N(FX!G20)=0,"",Data!D7/FX!G20) -> 1120.4186 | K3: =IF(N(FX!H20)=0,"",Data!D8/FX!H20) -> 1315.9467 | L3: =IF(N(FX!I20)=0,"",Data!D9/FX!I20) -> 1467.4707 | M3: =IF(N(FX!J20)=0,"",Data!D10/FX!J20) -> 1797.1744 | N3: =IF(N(FX!K20)=0,"",Data!D11/FX!K20) -> 1832.5276 | O3: =IF(N(FX!L20)=0,"",Data!D12/FX!L20) -> 1838.6245 | P3: =IF(N(FX!M20)=0,"",Data!D13/FX!M20) -> 2136.9128 | Q3: =IF(N(FX!N20)=0,"",Data!D14/FX!N20) -> 2196.078 | R3: =IF(N(FX!O20)=0,"",Data!D15/FX!O20) -> 2270.6144 | S3: =IF(N(FX!P20)=0,"",Data!D16/FX!P20) -> 2356.9464 | T3: =IF(N(FX!Q20)=0,"",Data!D17/FX!Q20) -> 2444.882
A4: USA | B4: North America | C4: 1 | E4: =IF(N(FX!B30)=0,"",Data!D18/FX!B30) -> 18295.02 | F4: =IF(N(FX!C30)=0,"",Data!D19/FX!C30) -> 18804.91 | G4: =IF(N(FX!D30)=0,"",Data!D20/FX!D30) -> 19612.1 | H4: =IF(N(FX!E30)=0,"",Data!D21/FX!E30) -> 20656.52 | I4: =IF(N(FX!F30)=0,"",Data!D22/FX!F30) -> 21539.98 | J4: =IF(N(FX!G30)=0,"",Data!D23/FX!G30) -> 21375.28 | K4: =IF(N(FX!H30)=0,"",Data!D24/FX!H30) -> 23745.85 | L4: =IF(N(FX!I30)=0,"",Data!D25/FX!I30) -> 26059.71 | M4: =IF(N(FX!J30)=0,"",Data!D26/FX!J30) -> 27825.89 | N4: =IF(N(FX!K30)=0,"",Data!D27/FX!K30) -> 29380.99 | O4: =IF(N(FX!L30)=0,"",Data!D28/FX!L30) -> 30861.29 | P4: =IF(N(FX!M30)=0,"",Data!D29/FX!M30) -> 32710.81 | Q4: =IF(N(FX!N30)=0,"",Data!D30/FX!N30) -> 34488.98 | R4: =IF(N(FX!O30)=0,"",Data!D31/FX!O30) -> 36128.72 | S4: =IF(N(FX!P30)=0,"",Data!D32/FX!P30) -> 37639.61 | T4: =IF(N(FX!Q30)=0,"",Data!D33/FX!Q30) -> 39193.65
A5: CAN | B5: North America | C5: 1 | E5: =IF(N(FX!B5)=0,"",Data!D34/FX!B5) -> 1555.0312 | F5: =IF(N(FX!C5)=0,"",Data!D35/FX!C5) -> 1522.9624 | G5: =IF(N(FX!D5)=0,"",Data!D36/FX!D5) -> 1646.6462 | H5: =IF(N(FX!E5)=0,"",Data!D37/FX!E5) -> 1719.7538 | I5: =IF(N(FX!F5)=0,"",Data!D38/FX!F5) -> 1743.5828 | J5: =IF(N(FX!G5)=0,"",Data!D39/FX!G5) -> 1655.5059 | K5: =IF(N(FX!H5)=0,"",Data!D40/FX!H5) -> 2023.153 | L5: =IF(N(FX!I5)=0,"",Data!D41/FX!I5) -> 2201.3373 | M5: =IF(N(FX!J5)=0,"",Data!D42/FX!J5) -> 2197.4211 | N5: =IF(N(FX!K5)=0,"",Data!D43/FX!K5) -> 2269.3459 | O5: =IF(N(FX!L5)=0,"",Data!D44/FX!L5) -> 2322.1896 | P5: =IF(N(FX!M5)=0,"",Data!D45/FX!M5) -> 2466.4532 | Q5: =IF(N(FX!N5)=0,"",Data!D46/FX!N5) -> 2684.1765 | R5: =IF(N(FX!O5)=0,"",Data!D47/FX!O5) -> 2874.3158 | S5: =IF(N(FX!P5)=0,"",Data!D48/FX!P5) -> 3071.1628 | T5: =IF(N(FX!Q5)=0,"",Data!D49/FX!Q5) -> 3272.7619
A6: ARG | B6: Latin America | C6: 1 | E6: =IF(N(FX!B3)=0,"",Data!D50/FX!B3) -> 645.12568 | F6: =IF(N(FX!C3)=0,"",Data!D51/FX!C3) -> 557.46341 | G6: =IF(N(FX!D3)=0,"",Data!D52/FX!D3) -> 643.7337 | H6: =IF(N(FX!E3)=0,"",Data!D53/FX!E3) -> 524.91314 | I6: =IF(N(FX!F3)=0,"",Data!D54/FX!F3) -> 446.80705 | J6: =IF(N(FX!G3)=0,"",Data!D55/FX!G3) -> 385.18984 | K6: =IF(N(FX!H3)=0,"",Data!D56/FX!H3) -> 486.05616 | L6: =IF(N(FX!I3)=0,"",Data!D57/FX!I3) -> 633.54028 | M6: =IF(N(FX!J3)=0,"",Data!D58/FX!J3) -> 654.07453 | N6: =IF(N(FX!K3)=0,"",Data!D59/FX!K3) -> 637.74338 | O6: =IF(N(FX!L3)=0,"",Data!D60/FX!L3) -> 683.5879 | P6: =IF(N(FX!M3)=0,"",Data!D61/FX!M3) -> 771.09028 | Q6: =IF(N(FX!N3)=0,"",Data!D62/FX!N3) -> 790.96943 | R6: =IF(N(FX!O3)=0,"",Data!D63/FX!O3) -> 797.74268 | S6: =IF(N(FX!P3)=0,"",Data!D64/FX!P3) -> 836.11931 | T6: =IF(N(FX!Q3)=0,"",Data!D65/FX!Q3) -> 870.7362
A7: BRA | B7: Latin America | C7: 1 | E7: =IF(N(FX!B4)=0,"",Data!D66/FX!B4) -> 1800.5375 | F7: =IF(N(FX!C4)=0,"",Data!D67/FX!C4) -> 1796.3696 | G7: =IF(N(FX!D4)=0,"",Data!D68/FX!D4) -> 2064.4138 | H7: =IF(N(FX!E4)=0,"",Data!D69/FX!E4) -> 1918.9425 | I7: =IF(N(FX!F4)=0,"",Data!D70/FX!F4) -> 1875.4137 | J7: =IF(N(FX!G4)=0,"",Data!D71/FX!G4) -> 1477.5922 | K7: =IF(N(FX!H4)=0,"",Data!D72/FX!H4) -> 1672.0111 | L7: =IF(N(FX!I4)=0,"",Data!D73/FX!I4) -> 1953.4264 | M7: =IF(N(FX!J4)=0,"",Data!D74/FX!J4) -> 2188.668 | N7: =IF(N(FX!K4)=0,"",Data!D75/FX!K4) -> 2185.3896 | O7: =IF(N(FX!L4)=0,"",Data!D76/FX!L4) -> 2278.814 | P7: =IF(N(FX!M4)=0,"",Data!D77/FX!M4) -> 2657.0078 | Q7: =IF(N(FX!N4)=0,"",Data!D78/FX!N4) -> 2784.9382 | R7: =IF(N(FX!O4)=0,"",Data!D79/FX!O4) -> 2864.9906 | S7: =IF(N(FX!P4)=0,"",Data!D80/FX!P4) -> 2978.7731 | T7: =IF(N(FX!Q4)=0,"",Data!D81/FX!Q4) -> 3121.6661
A8: CHL | B8: Latin America | C8: 1 | E8: =IF(N(FX!B7)=0,"",Data!D82*1000/FX!B7) -> 244.03077 | F8: =IF(N(FX!C7)=0,"",Data!D83*1000/FX!C7) -> 248.17647 | G8: =IF(N(FX!D7)=0,"",Data!D84*1000/FX!D7) -> 275.86154 | H8: =IF(N(FX!E7)=0,"",Data!D85*1000/FX!E7) -> 295.98438 | I8: =IF(N(FX!F7)=0,"",Data!D86*1000/FX!F7) -> 279.35714 | J8: =IF(N(FX!G7)=0,"",Data!D87*1000/FX!G7) -> 254.82278 | K8: =IF(N(FX!H7)=0,"",Data!D88*1000/FX!H7) -> 315.21053 | L8: =IF(N(FX!I7)=0,"",Data!D89*1000/FX!I7) -> 302.24138 | M8: =IF(N(FX!J7)=0,"",Data!D90*1000/FX!J7) -> 335.83333 | N8: =IF(N(FX!K7)=0,"",Data!D91*1000/FX!K7) -> 330.51064 | O8: =IF(N(FX!L7)=0,"",Data!D92*1000/FX!L7) -> 357.87368 | P8: =IF(N(FX!M7)=0,"",Data!D93*1000/FX!M7) -> 397.90622 | Q8: =IF(N(FX!N7)=0,"",Data!D94*1000/FX!N7) -> 421.43164 | R8: =IF(N(FX!O7)=0,"",Data!D95*1000/FX!O7) -> 461.3252 | S8: =IF(N(FX!P7)=0,"",Data!D96*1000/FX!P7) -> 495.25227 | T8: =IF(N(FX!Q7)=0,"",Data!D97*1000/FX!Q7) -> 530.4902
A9: COL | B9: Latin America | C9: 1 | E9: =IF(N(FX!B9)=0,"",Data!D98*1000/FX!B9) -> 293.68248 | F9: =IF(N(FX!C9)=0,"",Data!D99*1000/FX!C9) -> 283.20656 | G9: =IF(N(FX!D9)=0,"",Data!D100*1000/FX!D9) -> 312.02373 | H9: =IF(N(FX!E9)=0,"",Data!D101*1000/FX!E9) -> 333.71284 | I9: =IF(N(FX!F9)=0,"",Data!D102*1000/FX!F9) -> 323.19207 | J9: =IF(N(FX!G9)=0,"",Data!D103*1000/FX!G9) -> 270.58808 | K9: =IF(N(FX!H9)=0,"",Data!D104*1000/FX!H9) -> 318.88503 | L9: =IF(N(FX!I9)=0,"",Data!D105*1000/FX!I9) -> 346.13647 | M9: =IF(N(FX!J9)=0,"",Data!D106*1000/FX!J9) -> 366.55889 | N9: =IF(N(FX!K9)=0,"",Data!D107*1000/FX!K9) -> 420.96314 | O9: =IF(N(FX!L9)=0,"",Data!D108*1000/FX!L9) -> 457.44938 | P9: =IF(N(FX!M9)=0,"",Data!D109*1000/FX!M9) -> 580.01911 | Q9: =IF(N(FX!N9)=0,"",Data!D110*1000/FX!N9) -> 636.09502 | R9: =IF(N(FX!O9)=0,"",Data!D111*1000/FX!O9) -> 642.01943 | S9: =IF(N(FX!P9)=0,"",Data!D112*1000/FX!P9) -> 675.10666 | T9: =IF(N(FX!Q9)=0,"",Data!D113*1000/FX!Q9) -> 722.80298
A10: CRI | B10: Latin America | C10: 1 | E10: =IF(N(FX!B10)=0,"",Data!D114/FX!B10) -> 56.441476 | F10: =IF(N(FX!C10)=0,"",Data!D115/FX!C10) -> 58.846955 | G10: =IF(N(FX!D10)=0,"",Data!D116/FX!D10) -> 60.516379 | H10: =IF(N(FX!E10)=0,"",Data!D117/FX!E10) -> 62.568036 | I10: =IF(N(FX!F10)=0,"",Data!D118/FX!F10) -> 65.117686 | J10: =IF(N(FX!G10)=0,"",Data!D119/FX!G10) -> 63.155449 | K10: =IF(N(FX!H10)=0,"",Data!D120/FX!H10) -> 65.931424 | L10: =IF(N(FX!I10)=0,"",Data!D121/FX!I10) -> 71.385753 | M10: =IF(N(FX!J10)=0,"",Data!D122/FX!J10) -> 88.054966 | N10: =IF(N(FX!K10)=0,"",Data!D123/FX!K10) -> 97.308768 | O10: =IF(N(FX!L10)=0,"",Data!D124/FX!L10) -> 103.50453 | P10: =IF(N(FX!M10)=0,"",Data!D125/FX!M10) -> 115.54229 | Q10: =IF(N(FX!N10)=0,"",Data!D126/FX!N10) -> 119.78131 | R10: =IF(N(FX!O10)=0,"",Data!D127/FX!O10) -> 122.87434 | S10: =IF(N(FX!P10)=0,"",Data!D128/FX!P10) -> 126.62525 | T10: =IF(N(FX!Q10)=0,"",Data!D129/FX!Q10) -> 129.64203
A11: ECU | B11: Latin America | C11: 1 | E11: =IF(N(FX!B30)=0,"",Data!D130/FX!B30) -> 97.21 | F11: =IF(N(FX!C30)=0,"",Data!D131/FX!C30) -> 97.67 | G11: =IF(N(FX!D30)=0,"",Data!D132/FX!D30) -> 104.47 | H11: =IF(N(FX!E30)=0,"",Data!D133/FX!E30) -> 107.48 | I11: =IF(N(FX!F30)=0,"",Data!D134/FX!F30) -> 107.6 | J11: =IF(N(FX!G30)=0,"",Data!D135/FX!G30) -> 95.87 | K11: =IF(N(FX!H30)=0,"",Data!D136/FX!H30) -> 107.18 | L11: =IF(N(FX!I30)=0,"",Data!D137/FX!I30) -> 116.13 | M11: =IF(N(FX!J30)=0,"",Data!D138/FX!J30) -> 120.79 | N11: =IF(N(FX!K30)=0,"",Data!D139/FX!K30) -> 123.8 | O11: =IF(N(FX!L30)=0,"",Data!D140/FX!L30) -> 130.32 | P11: =IF(N(FX!M30)=0,"",Data!D141/FX!M30) -> 137.64 | Q11: =IF(N(FX!N30)=0,"",Data!D142/FX!N30) -> 144.98 | R11: =IF(N(FX!O30)=0,"",Data!D143/FX!O30) -> 151.63 | S11: =IF(N(FX!P30)=0,"",Data!D144/FX!P30) -> 158.07 | T11: =IF(N(FX!Q30)=0,"",Data!D145/FX!Q30) -> 164.8
A12: SLV | B12: Latin America | C12: 1 | E12: =IF(N(FX!B30)=0,"",Data!D146/FX!B30) -> 23.44 | F12: =IF(N(FX!C30)=0,"",Data!D147/FX!C30) -> 24.19 | G12: =IF(N(FX!D30)=0,"",Data!D148/FX!D30) -> 24.98 | H12: =IF(N(FX!E30)=0,"",Data!D149/FX!E30) -> 26.02 | I12: =IF(N(FX!F30)=0,"",Data!D150/FX!F30) -> 26.88 | J12: =IF(N(FX!G30)=0,"",Data!D151/FX!G30) -> 24.92 | K12: =IF(N(FX!H30)=0,"",Data!D152/FX!H30) -> 29.04 | L12: =IF(N(FX!I30)=0,"",Data!D153/FX!I30) -> 31.87 | M12: =IF(N(FX!J30)=0,"",Data!D154/FX!J30) -> 33.57 | N12: =IF(N(FX!K30)=0,"",Data!D155/FX!K30) -> 34.88 | O12: =IF(N(FX!L30)=0,"",Data!D156/FX!L30) -> 36.71 | P12: =IF(N(FX!M30)=0,"",Data!D157/FX!M30) -> 38.37 | Q12: =IF(N(FX!N30)=0,"",Data!D158/FX!N30) -> 40.03 | R12: =IF(N(FX!O30)=0,"",Data!D159/FX!O30) -> 41.6 | S12: =IF(N(FX!P30)=0,"",Data!D160/FX!P30) -> 43.2 | T12: =IF(N(FX!Q30)=0,"",Data!D161/FX!Q30) -> 44.87
A13: GTM | B13: Latin America | C13: 1 | E13: =IF(N(FX!B13)=0,"",Data!D162/FX!B13) -> 62.224837 | F13: =IF(N(FX!C13)=0,"",Data!D163/FX!C13) -> 66.052632 | G13: =IF(N(FX!D13)=0,"",Data!D164/FX!D13) -> 71.634014 | H13: =IF(N(FX!E13)=0,"",Data!D165/FX!E13) -> 73.320479 | I13: =IF(N(FX!F13)=0,"",Data!D166/FX!F13) -> 77.138961 | J13: =IF(N(FX!G13)=0,"",Data!D167/FX!G13) -> 77.735751 | K13: =IF(N(FX!H13)=0,"",Data!D168/FX!H13) -> 86.392765 | L13: =IF(N(FX!I13)=0,"",Data!D169/FX!I13) -> 95.588387 | M13: =IF(N(FX!J13)=0,"",Data!D170/FX!J13) -> 104.32439 | N13: =IF(N(FX!K13)=0,"",Data!D171/FX!K13) -> 113.19459 | O13: =IF(N(FX!L13)=0,"",Data!D172/FX!L13) -> 123.30859 | P13: =IF(N(FX!M13)=0,"",Data!D173/FX!M13) -> 133.01309 | Q13: =IF(N(FX!N13)=0,"",Data!D174/FX!N13) -> 145.6978 | R13: =IF(N(FX!O13)=0,"",Data!D175/FX!O13) -> 158.97165 | S13: =IF(N(FX!P13)=0,"",Data!D176/FX!P13) -> 173.34994 | T13: =IF(N(FX!Q13)=0,"",Data!D177/FX!Q13) -> 188.95823
A14: HND | B14: Latin America | C14: 1 | E14: =IF(N(FX!B14)=0,"",Data!D178/FX!B14) -> 20.975399 | F14: =IF(N(FX!C14)=0,"",Data!D179/FX!C14) -> 21.712785 | G14: =IF(N(FX!D14)=0,"",Data!D180/FX!D14) -> 23.133248 | H14: =IF(N(FX!E14)=0,"",Data!D181/FX!E14) -> 24.070293 | I14: =IF(N(FX!F14)=0,"",Data!D182/FX!F14) -> 24.799919 | J14: =IF(N(FX!G14)=0,"",Data!D183/FX!G14) -> 23.268747 | K14: =IF(N(FX!H14)=0,"",Data!D184/FX!H14) -> 28.046888 | L14: =IF(N(FX!I14)=0,"",Data!D185/FX!I14) -> 31.331026 | M14: =IF(N(FX!J14)=0,"",Data!D186/FX!J14) -> 34.274534 | N14: =IF(N(FX!K14)=0,"",Data!D187/FX!K14) -> 36.889783 | O14: =IF(N(FX!L14)=0,"",Data!D188/FX!L14) -> 39.498847 | P14: =IF(N(FX!M14)=0,"",Data!D189/FX!M14) -> 41.89511 | Q14: =IF(N(FX!N14)=0,"",Data!D190/FX!N14) -> 44.193008 | R14: =IF(N(FX!O14)=0,"",Data!D191/FX!O14) -> 46.310345 | S14: =IF(N(FX!P14)=0,"",Data!D192/FX!P14) -> 48.346755 | T14: =IF(N(FX!Q14)=0,"",Data!D193/FX!Q14) -> 50.394443
A15: NIC | B15: Latin America | C15: 1 | E15: =IF(N(FX!B21)=0,"",Data!D194/FX!B21) -> 12.755319 | F15: =IF(N(FX!C21)=0,"",Data!D195/FX!C21) -> 13.286513 | G15: =IF(N(FX!D21)=0,"",Data!D196/FX!D21) -> 13.786356 | H15: =IF(N(FX!E21)=0,"",Data!D197/FX!E21) -> 13.026624 | I15: =IF(N(FX!F21)=0,"",Data!D198/FX!F21) -> 12.699577 | J15: =IF(N(FX!G21)=0,"",Data!D199/FX!G21) -> 12.72714 | K15: =IF(N(FX!H21)=0,"",Data!D200/FX!H21) -> 14.209554 | L15: =IF(N(FX!I21)=0,"",Data!D201/FX!I21) -> 15.636465 | M15: =IF(N(FX!J21)=0,"",Data!D202/FX!J21) -> 17.806531 | N15: =IF(N(FX!K21)=0,"",Data!D203/FX!K21) -> 19.698525 | O15: =IF(N(FX!L21)=0,"",Data!D204/FX!L21) -> 22.23976 | P15: =IF(N(FX!M21)=0,"",Data!D205/FX!M21) -> 23.811032 | Q15: =IF(N(FX!N21)=0,"",Data!D206/FX!N21) -> 25.34715 | R15: =IF(N(FX!O21)=0,"",Data!D207/FX!O21) -> 25.927848 | S15: =IF(N(FX!P21)=0,"",Data!D208/FX!P21) -> 26.508588 | T15: =IF(N(FX!Q21)=0,"",Data!D209/FX!Q21) -> 27.029124
A16: PAN | B16: Latin America | C16: 1 | E16: =IF(N(FX!B30)=0,"",Data!D210/FX!B30) -> 54.09 | F16: =IF(N(FX!C30)=0,"",Data!D211/FX!C30) -> 57.91 | G16: =IF(N(FX!D30)=0,"",Data!D212/FX!D30) -> 62.2 | H16: =IF(N(FX!E30)=0,"",Data!D213/FX!E30) -> 67.32 | I16: =IF(N(FX!F30)=0,"",Data!D214/FX!F30) -> 69.78 | J16: =IF(N(FX!G30)=0,"",Data!D215/FX!G30) -> 57.06 | K16: =IF(N(FX!H30)=0,"",Data!D216/FX!H30) -> 67.4 | L16: =IF(N(FX!I30)=0,"",Data!D217/FX!I30) -> 76.48 | M16: =IF(N(FX!J30)=0,"",Data!D218/FX!J30) -> 83.82 | N16: =IF(N(FX!K30)=0,"",Data!D219/FX!K30) -> 86.56 | O16: =IF(N(FX!L30)=0,"",Data!D220/FX!L30) -> 90.7 | P16: =IF(N(FX!M30)=0,"",Data!D221/FX!M30) -> 96.61 | Q16: =IF(N(FX!N30)=0,"",Data!D222/FX!N30) -> 101.83 | R16: =IF(N(FX!O30)=0,"",Data!D223/FX!O30) -> 106.92 | S16: =IF(N(FX!P30)=0,"",Data!D224/FX!P30) -> 112.29 | T16: =IF(N(FX!Q30)=0,"",Data!D225/FX!Q30) -> 117.91
A17: PRY | B17: Latin America | C17: 1 | E17: =IF(N(FX!B23)=0,"",Data!D226*1000/FX!B23) -> 36.246154 | F17: =IF(N(FX!C23)=0,"",Data!D227*1000/FX!C23) -> 36.093474 | G17: =IF(N(FX!D23)=0,"",Data!D228*1000/FX!D23) -> 38.989324 | H17: =IF(N(FX!E23)=0,"",Data!D229*1000/FX!E23) -> 40.240838 | I17: =IF(N(FX!F23)=0,"",Data!D230*1000/FX!F23) -> 37.929487 | J17: =IF(N(FX!G23)=0,"",Data!D231*1000/FX!G23) -> 35.437223 | K17: =IF(N(FX!H23)=0,"",Data!D232*1000/FX!H23) -> 39.961595 | L17: =IF(N(FX!I23)=0,"",Data!D233*1000/FX!I23) -> 41.858166 | M17: =IF(N(FX!J23)=0,"",Data!D234*1000/FX!J23) -> 43.134431 | N17: =IF(N(FX!K23)=0,"",Data!D235*1000/FX!K23) -> 44.740741 | O17: =IF(N(FX!L23)=0,"",Data!D236*1000/FX!L23) -> 49.314324 | P17: =IF(N(FX!M23)=0,"",Data!D237*1000/FX!M23) -> 65.401501 | Q17: =IF(N(FX!N23)=0,"",Data!D238*1000/FX!N23) -> 70.913614 | R17: =IF(N(FX!O23)=0,"",Data!D239*1000/FX!O23) -> 73.191068 | S17: =IF(N(FX!P23)=0,"",Data!D240*1000/FX!P23) -> 75.431626 | T17: =IF(N(FX!Q23)=0,"",Data!D241*1000/FX!Q23) -> 77.780631
A18: PER | B18: Latin America | C18: 1 | E18: =IF(N(FX!B22)=0,"",Data!D242/FX!B22) -> 194.74528 | F18: =IF(N(FX!C22)=0,"",Data!D243/FX!C22) -> 198.68639 | G18: =IF(N(FX!D22)=0,"",Data!D244/FX!D22) -> 219.59202 | H18: =IF(N(FX!E22)=0,"",Data!D245/FX!E22) -> 229.62614 | I18: =IF(N(FX!F22)=0,"",Data!D246/FX!F22) -> 236.2006 | J18: =IF(N(FX!G22)=0,"",Data!D247/FX!G22) -> 209.70857 | K18: =IF(N(FX!H22)=0,"",Data!D248/FX!H22) -> 229.96134 | L18: =IF(N(FX!I22)=0,"",Data!D249/FX!I22) -> 248.66841 | M18: =IF(N(FX!J22)=0,"",Data!D250/FX!J22) -> 272.22727 | N18: =IF(N(FX!K22)=0,"",Data!D251/FX!K22) -> 295.792 | O18: =IF(N(FX!L22)=0,"",Data!D252/FX!L22) -> 340.02801 | P18: =IF(N(FX!M22)=0,"",Data!D253/FX!M22) -> 393.91202 | Q18: =IF(N(FX!N22)=0,"",Data!D254/FX!N22) -> 416.02632 | R18: =IF(N(FX!O22)=0,"",Data!D255/FX!O22) -> 435.11337 | S18: =IF(N(FX!P22)=0,"",Data!D256/FX!P22) -> 455.68406 | T18: =IF(N(FX!Q22)=0,"",Data!D257/FX!Q22) -> 480.8058
A19: URY | B19: Latin America | C19: 1 | E19: =IF(N(FX!B31)=0,"",Data!D258/FX!B31) -> 59.278083 | F19: =IF(N(FX!C31)=0,"",Data!D259/FX!C31) -> 57.485743 | G19: =IF(N(FX!D31)=0,"",Data!D260/FX!D31) -> 64.997908 | H19: =IF(N(FX!E31)=0,"",Data!D261/FX!E31) -> 65.334527 | I19: =IF(N(FX!F31)=0,"",Data!D262/FX!F31) -> 62.231773 | J19: =IF(N(FX!G31)=0,"",Data!D263/FX!G31) -> 53.563437 | K19: =IF(N(FX!H31)=0,"",Data!D264/FX!H31) -> 60.731405 | L19: =IF(N(FX!I31)=0,"",Data!D265/FX!I31) -> 71.225352 | M19: =IF(N(FX!J31)=0,"",Data!D266/FX!J31) -> 79.19624 | N19: =IF(N(FX!K31)=0,"",Data!D267/FX!K31) -> 82.328525 | O19: =IF(N(FX!L31)=0,"",Data!D268/FX!L31) -> 85.556583 | P19: =IF(N(FX!M31)=0,"",Data!D269/FX!M31) -> 91.998004 | Q19: =IF(N(FX!N31)=0,"",Data!D270/FX!N31) -> 92.017359 | R19: =IF(N(FX!O31)=0,"",Data!D271/FX!O31) -> 95.08243 | S19: =IF(N(FX!P31)=0,"",Data!D272/FX!P31) -> 98.726975 | T19: =IF(N(FX!Q31)=0,"",Data!D273/FX!Q31) -> 102.65595
A20: VEN | B20: Latin America | C20: 0 | D20: excluded: not consolidated by Bimbo since 1-Jun-2017 (fair-value instrument) [sourced] wiki bimbo-history-2014-2020; GDP also unusable | E20: =IF(N(FX!B32)=0,"",Data!D274/FX!B32) | F20: =IF(N(FX!C32)=0,"",Data!D275/FX!C32) | G20: =IF(N(FX!D32)=0,"",Data!D276/FX!D32) | H20: =IF(N(FX!E32)=0,"",Data!D277/FX!E32) | I20: =IF(N(FX!F32)=0,"",Data!D278/FX!F32) | J20: =IF(N(FX!G32)=0,"",Data!D279/FX!G32) | K20: =IF(N(FX!H32)=0,"",Data!D280/FX!H32) | L20: =IF(N(FX!I32)=0,"",Data!D281/FX!I32) | M20: =IF(N(FX!J32)=0,"",Data!D282/FX!J32) | N20: =IF(N(FX!K32)=0,"",Data!D283/FX!K32) | O20: =IF(N(FX!L32)=0,"",Data!D284/FX!L32) | P20: =IF(N(FX!M32)=0,"",Data!D285/FX!M32) | Q20: =IF(N(FX!N32)=0,"",Data!D286/FX!N32) | R20: =IF(N(FX!O32)=0,"",Data!D287/FX!O32) | S20: =IF(N(FX!P32)=0,"",Data!D288/FX!P32) | T20: =IF(N(FX!Q32)=0,"",Data!D289/FX!Q32)
A21: GBR | B21: EAA | C21: 1 | E21: =IF(N(FX!B12)=0,"",Data!D290/FX!B12) -> 2967.5692 | F21: =IF(N(FX!C12)=0,"",Data!D291/FX!C12) -> 2710.1757 | G21: =IF(N(FX!D12)=0,"",Data!D292/FX!D12) -> 2695.3974 | H21: =IF(N(FX!E12)=0,"",Data!D293/FX!E12) -> 2904.1333 | I21: =IF(N(FX!F12)=0,"",Data!D294/FX!F12) -> 2885.5558 | J21: =IF(N(FX!G12)=0,"",Data!D295/FX!G12) -> 2733.6881 | K21: =IF(N(FX!H12)=0,"",Data!D296/FX!H12) -> 3209.3135 | L21: =IF(N(FX!I12)=0,"",Data!D297/FX!I12) -> 3191.3772 | M21: =IF(N(FX!J12)=0,"",Data!D298/FX!J12) -> 3440.4303 | N21: =IF(N(FX!K12)=0,"",Data!D299/FX!K12) -> 3712.8707 | O21: =IF(N(FX!L12)=0,"",Data!D300/FX!L12) -> 4011.8461 | P21: =IF(N(FX!M12)=0,"",Data!D301/FX!M12) -> 4218.4 | Q21: =IF(N(FX!N12)=0,"",Data!D302/FX!N12) -> 4366.2667 | R21: =IF(N(FX!O12)=0,"",Data!D303/FX!O12) -> 4538.44 | S21: =IF(N(FX!P12)=0,"",Data!D304/FX!P12) -> 4725.3067 | T21: =IF(N(FX!Q12)=0,"",Data!D305/FX!Q12) -> 4917.92
A22: CHE | B22: EAA | C22: 1 | E22: =IF(N(FX!B6)=0,"",Data!D306/FX!B6) -> 707.94792 | F22: =IF(N(FX!C6)=0,"",Data!D307/FX!C6) -> 695.35354 | G22: =IF(N(FX!D6)=0,"",Data!D308/FX!D6) -> 710.04082 | H22: =IF(N(FX!E6)=0,"",Data!D309/FX!E6) -> 739.16327 | I22: =IF(N(FX!F6)=0,"",Data!D310/FX!F6) -> 739.19192 | J22: =IF(N(FX!G6)=0,"",Data!D311/FX!G6) -> 755.15957 | K22: =IF(N(FX!H6)=0,"",Data!D312/FX!H6) -> 844.26374 | L22: =IF(N(FX!I6)=0,"",Data!D313/FX!I6) -> 862.84211 | M22: =IF(N(FX!J6)=0,"",Data!D314/FX!J6) -> 930.17778 | N22: =IF(N(FX!K6)=0,"",Data!D315/FX!K6) -> 978.32955 | O22: =IF(N(FX!L6)=0,"",Data!D316/FX!L6) -> 1062.1325 | P22: =IF(N(FX!M6)=0,"",Data!D317/FX!M6) -> 1123.2 | Q22: =IF(N(FX!N6)=0,"",Data!D318/FX!N6) -> 1138.0864 | R22: =IF(N(FX!O6)=0,"",Data!D319/FX!O6) -> 1169.3951 | S22: =IF(N(FX!P6)=0,"",Data!D320/FX!P6) -> 1214.2125 | T22: =IF(N(FX!Q6)=0,"",Data!D321/FX!Q6) -> 1255.519
A23: ROU | B23: EAA | C23: 1 | E23: =IF(N(FX!B24)=0,"",Data!D322/FX!B24) -> 177.69327 | F23: =IF(N(FX!C24)=0,"",Data!D323/FX!C24) -> 185.25369 | G23: =IF(N(FX!D24)=0,"",Data!D324/FX!D24) -> 210.27654 | H23: =IF(N(FX!E24)=0,"",Data!D325/FX!E24) -> 241.72335 | I23: =IF(N(FX!F24)=0,"",Data!D326/FX!F24) -> 248.39387 | J23: =IF(N(FX!G24)=0,"",Data!D327/FX!G24) -> 249.12736 | K23: =IF(N(FX!H24)=0,"",Data!D328/FX!H24) -> 283.61298 | L23: =IF(N(FX!I24)=0,"",Data!D329/FX!I24) -> 293.91471 | M23: =IF(N(FX!J24)=0,"",Data!D330/FX!J24) -> 347.47484 | N23: =IF(N(FX!K24)=0,"",Data!D331/FX!K24) -> 384.24348 | O23: =IF(N(FX!L24)=0,"",Data!D332/FX!L24) -> 431.75168 | P23: =IF(N(FX!M24)=0,"",Data!D333/FX!M24) -> 463.86062 | Q23: =IF(N(FX!N24)=0,"",Data!D334/FX!N24) -> 474.86105 | R23: =IF(N(FX!O24)=0,"",Data!D335/FX!O24) -> 504.05708 | S23: =IF(N(FX!P24)=0,"",Data!D336/FX!P24) -> 558.98253 | T23: =IF(N(FX!Q24)=0,"",Data!D337/FX!Q24) -> 611.07795
A24: SRB | B24: EAA | C24: 1 | E24: =IF(N(FX!B25)=0,"",Data!D338/FX!B25) -> 41.297951 | F24: =IF(N(FX!C25)=0,"",Data!D339/FX!C25) -> 42.224659 | G24: =IF(N(FX!D25)=0,"",Data!D340/FX!D25) -> 45.972346 | H24: =IF(N(FX!E25)=0,"",Data!D341/FX!E25) -> 52.784887 | I24: =IF(N(FX!F25)=0,"",Data!D342/FX!F25) -> 53.864513 | J24: =IF(N(FX!G25)=0,"",Data!D343/FX!G25) -> 55.875824 | K24: =IF(N(FX!H25)=0,"",Data!D344/FX!H25) -> 66.157143 | L24: =IF(N(FX!I25)=0,"",Data!D345/FX!I25) -> 66.811213 | M24: =IF(N(FX!J25)=0,"",Data!D346/FX!J25) -> 81.346033 | N24: =IF(N(FX!K25)=0,"",Data!D347/FX!K25) -> 90.086498 | O24: =IF(N(FX!L25)=0,"",Data!D348/FX!L25) -> 99.958546 | P24: =IF(N(FX!M25)=0,"",Data!D349/FX!M25) -> 108.94796 | Q24: =IF(N(FX!N25)=0,"",Data!D350/FX!N25) -> 114.16787 | R24: =IF(N(FX!O25)=0,"",Data!D351/FX!O25) -> 122.97576 | S24: =IF(N(FX!P25)=0,"",Data!D352/FX!P25) -> 129.98139 | T24: =IF(N(FX!Q25)=0,"",Data!D353/FX!Q25) -> 134.76425
A25: SVN | B25: EAA | C25: 1 | E25: =IF(N(FX!B11)=0,"",Data!D354/FX!B11) -> 42.766667 | F25: =IF(N(FX!C11)=0,"",Data!D355/FX!C11) -> 44.455556 | G25: =IF(N(FX!D11)=0,"",Data!D356/FX!D11) -> 47.898876 | H25: =IF(N(FX!E11)=0,"",Data!D357/FX!E11) -> 53.482353 | I25: =IF(N(FX!F11)=0,"",Data!D358/FX!F11) -> 53.906425 | J25: =IF(N(FX!G11)=0,"",Data!D359/FX!G11) -> 53.2771 | K25: =IF(N(FX!H11)=0,"",Data!D360/FX!H11) -> 61.515725 | L25: =IF(N(FX!I11)=0,"",Data!D361/FX!I11) -> 59.800315 | M25: =IF(N(FX!J11)=0,"",Data!D362/FX!J11) -> 69.326414 | N25: =IF(N(FX!K11)=0,"",Data!D363/FX!K11) -> 73.0224 | O25: =IF(N(FX!L11)=0,"",Data!D364/FX!L11) -> 80.300124 | P25: =IF(N(FX!M11)=0,"",Data!D365/FX!M11) -> 85.931034 | Q25: =IF(N(FX!N11)=0,"",Data!D366/FX!N11) -> 89.516854 | R25: =IF(N(FX!O11)=0,"",Data!D367/FX!O11) -> 94.179775 | S25: =IF(N(FX!P11)=0,"",Data!D368/FX!P11) -> 102.47674 | T25: =IF(N(FX!Q11)=0,"",Data!D369/FX!Q11) -> 110.28571
A26: HRV | B26: EAA | C26: 1 | E26: =IF(N(FX!B11)=0,"",Data!D370/FX!B11) -> 51.077778 | F26: =IF(N(FX!C11)=0,"",Data!D371/FX!C11) -> 52.855556 | G26: =IF(N(FX!D11)=0,"",Data!D372/FX!D11) -> 55.876404 | H26: =IF(N(FX!E11)=0,"",Data!D373/FX!E11) -> 61.435294 | I26: =IF(N(FX!F11)=0,"",Data!D374/FX!F11) -> 61.461831 | J26: =IF(N(FX!G11)=0,"",Data!D375/FX!G11) -> 57.836544 | K26: =IF(N(FX!H11)=0,"",Data!D376/FX!H11) -> 68.976117 | L26: =IF(N(FX!I11)=0,"",Data!D377/FX!I11) -> 71.056227 | M26: =IF(N(FX!J11)=0,"",Data!D378/FX!J11) -> 85.620067 | N26: =IF(N(FX!K11)=0,"",Data!D379/FX!K11) -> 92.966129 | O26: =IF(N(FX!L11)=0,"",Data!D380/FX!L11) -> 104.90804 | P26: =IF(N(FX!M11)=0,"",Data!D381/FX!M11) -> 113.87356 | Q26: =IF(N(FX!N11)=0,"",Data!D382/FX!N11) -> 117.5618 | R26: =IF(N(FX!O11)=0,"",Data!D383/FX!O11) -> 123.59551 | S26: =IF(N(FX!P11)=0,"",Data!D384/FX!P11) -> 134.54651 | T26: =IF(N(FX!Q11)=0,"",Data!D385/FX!Q11) -> 144.34524
A27: MNE | B27: EAA | C27: 1 | E27: =IF(N(FX!B11)=0,"",Data!D386/FX!B11) -> 4.0111111 | F27: =IF(N(FX!C11)=0,"",Data!D387/FX!C11) -> 4.3777778 | G27: =IF(N(FX!D11)=0,"",Data!D388/FX!D11) -> 4.7752809 | H27: =IF(N(FX!E11)=0,"",Data!D389/FX!E11) -> 5.4117647 | I27: =IF(N(FX!F11)=0,"",Data!D390/FX!F11) -> 5.4846653 | J27: =IF(N(FX!G11)=0,"",Data!D391/FX!G11) -> 4.7190243 | K27: =IF(N(FX!H11)=0,"",Data!D392/FX!H11) -> 5.816978 | L27: =IF(N(FX!I11)=0,"",Data!D393/FX!I11) -> 6.2427746 | M27: =IF(N(FX!J11)=0,"",Data!D394/FX!J11) -> 7.6440696 | N27: =IF(N(FX!K11)=0,"",Data!D395/FX!K11) -> 8.2675035 | O27: =IF(N(FX!L11)=0,"",Data!D396/FX!L11) -> 9.3309263 | P27: =IF(N(FX!M11)=0,"",Data!D397/FX!M11) -> 10.022989 | Q27: =IF(N(FX!N11)=0,"",Data!D398/FX!N11) -> 10.426966 | R27: =IF(N(FX!O11)=0,"",Data!D399/FX!O11) -> 11.067416 | S27: =IF(N(FX!P11)=0,"",Data!D400/FX!P11) -> 12.139535 | T27: =IF(N(FX!Q11)=0,"",Data!D401/FX!Q11) -> 13.154762
A28: MKD | B28: EAA | C28: 0 | D28: excluded: no MKD FX in source, cannot weight [unverified] | E28: =IF(N(FX!B19)=0,"",Data!D402/FX!B19) | F28: =IF(N(FX!C19)=0,"",Data!D403/FX!C19) | G28: =IF(N(FX!D19)=0,"",Data!D404/FX!D19) | H28: =IF(N(FX!E19)=0,"",Data!D405/FX!E19) | I28: =IF(N(FX!F19)=0,"",Data!D406/FX!F19) | J28: =IF(N(FX!G19)=0,"",Data!D407/FX!G19) | K28: =IF(N(FX!H19)=0,"",Data!D408/FX!H19) | L28: =IF(N(FX!I19)=0,"",Data!D409/FX!I19) | M28: =IF(N(FX!J19)=0,"",Data!D410/FX!J19) | N28: =IF(N(FX!K19)=0,"",Data!D411/FX!K19) | O28: =IF(N(FX!L19)=0,"",Data!D412/FX!L19) | P28: =IF(N(FX!M19)=0,"",Data!D413/FX!M19) | Q28: =IF(N(FX!N19)=0,"",Data!D414/FX!N19) | R28: =IF(N(FX!O19)=0,"",Data!D415/FX!O19) | S28: =IF(N(FX!P19)=0,"",Data!D416/FX!P19) | T28: =IF(N(FX!Q19)=0,"",Data!D417/FX!Q19)
A29: RUS | B29: EAA | C29: 1 | E29: =IF(N(FX!B26)=0,"",Data!D418/FX!B26) -> 1359.6361 | F29: =IF(N(FX!C26)=0,"",Data!D419/FX!C26) -> 1277.28 | G29: =IF(N(FX!D26)=0,"",Data!D420/FX!D26) -> 1575.084 | H29: =IF(N(FX!E26)=0,"",Data!D421/FX!E26) -> 1655.4296 | I29: =IF(N(FX!F26)=0,"",Data!D422/FX!F26) -> 1693.5771 | J29: =IF(N(FX!G26)=0,"",Data!D423/FX!G26) -> 1490.9033 | K29: =IF(N(FX!H26)=0,"",Data!D424/FX!H26) -> 1829.0452 | L29: =IF(N(FX!I26)=0,"",Data!D425/FX!I26) -> 2289.6513 | M29: =IF(N(FX!J26)=0,"",Data!D426/FX!J26) -> 2043.2141 | N29: =IF(N(FX!K26)=0,"",Data!D427/FX!K26) -> 2184.8862 | O29: =IF(N(FX!L26)=0,"",Data!D428/FX!L26) -> 2564.4646 | P29: =IF(N(FX!M26)=0,"",Data!D429/FX!M26) -> 2951.008 | Q29: =IF(N(FX!N26)=0,"",Data!D430/FX!N26) -> 2889.0733 | R29: =IF(N(FX!O26)=0,"",Data!D431/FX!O26) -> 2761.7537 | S29: =IF(N(FX!P26)=0,"",Data!D432/FX!P26) -> 2815.5797 | T29: =IF(N(FX!Q26)=0,"",Data!D433/FX!Q26) -> 3031.8282
A30: UKR | B30: EAA | C30: 1 | E30: =IF(N(FX!B29)=0,"",Data!D434/FX!B29) -> 91.050366 | F30: =IF(N(FX!C29)=0,"",Data!D435/FX!C29) -> 93.360861 | G30: =IF(N(FX!D29)=0,"",Data!D436/FX!D29) -> 112.07632 | H30: =IF(N(FX!E29)=0,"",Data!D437/FX!E29) -> 130.89338 | I30: =IF(N(FX!F29)=0,"",Data!D438/FX!F29) -> 153.976 | J30: =IF(N(FX!G29)=0,"",Data!D439/FX!G29) -> 156.60349 | K30: =IF(N(FX!H29)=0,"",Data!D440/FX!H29) -> 199.81122 | L30: =IF(N(FX!I29)=0,"",Data!D441/FX!I29) -> 162.20155 | M30: =IF(N(FX!J29)=0,"",Data!D442/FX!J29) -> 181.24036 | N30: =IF(N(FX!K29)=0,"",Data!D443/FX!K29) -> 190.79631 | O30: =IF(N(FX!L29)=0,"",Data!D444/FX!L29) -> 214.22859 | P30: =IF(N(FX!M29)=0,"",Data!D445/FX!M29) -> 246.76836 | Q30: =IF(N(FX!N29)=0,"",Data!D446/FX!N29) -> 278.32589 | R30: =IF(N(FX!O29)=0,"",Data!D447/FX!O29) -> 330.18412 | S30: =IF(N(FX!P29)=0,"",Data!D448/FX!P29) -> 402.75145 | T30: =IF(N(FX!Q29)=0,"",Data!D449/FX!Q29) -> 504.74624
A31: TUR | B31: EAA | C31: 1 | E31: =IF(N(FX!B28)=0,"",Data!D450/FX!B28) -> 865.46324 | F31: =IF(N(FX!C28)=0,"",Data!D451/FX!C28) -> 870.85762 | G31: =IF(N(FX!D28)=0,"",Data!D452/FX!D28) -> 863.43288 | H31: =IF(N(FX!E28)=0,"",Data!D453/FX!E28) -> 788.0911 | I31: =IF(N(FX!F28)=0,"",Data!D454/FX!F28) -> 775.0088 | J31: =IF(N(FX!G28)=0,"",Data!D455/FX!G28) -> 732.43732 | K31: =IF(N(FX!H28)=0,"",Data!D456/FX!H28) -> 839.02935 | L31: =IF(N(FX!I28)=0,"",Data!D457/FX!I28) -> 924.91611 | M31: =IF(N(FX!J28)=0,"",Data!D458/FX!J28) -> 1138.7755 | N31: =IF(N(FX!K28)=0,"",Data!D459/FX!K28) -> 1360.8276 | O31: =IF(N(FX!L28)=0,"",Data!D460/FX!L28) -> 1601.4312 | P31: =IF(N(FX!M28)=0,"",Data!D461/FX!M28) -> 1767.9375 | Q31: =IF(N(FX!N28)=0,"",Data!D462/FX!N28) -> 1816.727 | R31: =IF(N(FX!O28)=0,"",Data!D463/FX!O28) -> 1906.4633 | S31: =IF(N(FX!P28)=0,"",Data!D464/FX!P28) -> 2034.0803 | T31: =IF(N(FX!Q28)=0,"",Data!D465/FX!Q28) -> 2167.7194
A32: KAZ | B32: EAA | C32: 1 | E32: =IF(N(FX!B17)=0,"",Data!D466/FX!B17) -> 184.387 | F32: =IF(N(FX!C17)=0,"",Data!D467/FX!C17) -> 137.40281 | G32: =IF(N(FX!D17)=0,"",Data!D468/FX!D17) -> 166.80632 | H32: =IF(N(FX!E17)=0,"",Data!D469/FX!E17) -> 179.32221 | I32: =IF(N(FX!F17)=0,"",Data!D470/FX!F17) -> 181.65168 | J32: =IF(N(FX!G17)=0,"",Data!D471/FX!G17) -> 170.89751 | K32: =IF(N(FX!H17)=0,"",Data!D472/FX!H17) -> 197.10185 | L32: =IF(N(FX!I17)=0,"",Data!D473/FX!I17) -> 225.4351 | M32: =IF(N(FX!J17)=0,"",Data!D474/FX!J17) -> 261.78558 | N32: =IF(N(FX!K17)=0,"",Data!D475/FX!K17) -> 291.47562 | O32: =IF(N(FX!L17)=0,"",Data!D476/FX!L17) -> 306.30335 | P32: =IF(N(FX!M17)=0,"",Data!D477/FX!M17) -> 435.73905 | Q32: =IF(N(FX!N17)=0,"",Data!D478/FX!N17) -> 479.19321 | R32: =IF(N(FX!O17)=0,"",Data!D479/FX!O17) -> 506.84178 | S32: =IF(N(FX!P17)=0,"",Data!D480/FX!P17) -> 563.64035 | T32: =IF(N(FX!Q17)=0,"",Data!D481/FX!Q17) -> 621.36809
A33: CHN | B33: EAA | C33: 1 | E33: =IF(N(FX!B8)=0,"",Data!D482/FX!B8) -> 11186.489 | F33: =IF(N(FX!C8)=0,"",Data!D483/FX!C8) -> 11463.75 | G33: =IF(N(FX!D8)=0,"",Data!D484/FX!D8) -> 12535.25 | H33: =IF(N(FX!E8)=0,"",Data!D485/FX!E8) -> 14139.125 | I33: =IF(N(FX!F8)=0,"",Data!D486/FX!F8) -> 14556.764 | J33: =IF(N(FX!G8)=0,"",Data!D487/FX!G8) -> 14998.081 | K33: =IF(N(FX!H8)=0,"",Data!D488/FX!H8) -> 18198.806 | L33: =IF(N(FX!I8)=0,"",Data!D489/FX!I8) -> 18336.247 | M33: =IF(N(FX!J8)=0,"",Data!D490/FX!J8) -> 18280.674 | N33: =IF(N(FX!K8)=0,"",Data!D491/FX!K8) -> 18723.142 | O33: =IF(N(FX!L8)=0,"",Data!D492/FX!L8) -> 19497.624 | P33: =IF(N(FX!M8)=0,"",Data!D493/FX!M8) -> 21846.361 | Q33: =IF(N(FX!N8)=0,"",Data!D494/FX!N8) -> 23526.402 | R33: =IF(N(FX!O8)=0,"",Data!D495/FX!O8) -> 24972.947 | S33: =IF(N(FX!P8)=0,"",Data!D496/FX!P8) -> 26481.373 | T33: =IF(N(FX!Q8)=0,"",Data!D497/FX!Q8) -> 27973.126
A34: IND | B34: EAA | C34: 1 | E34: =IF(N(FX!B15)=0,"",Data!D498/FX!B15) -> 2087.4087 | F34: =IF(N(FX!C15)=0,"",Data!D499/FX!C15) -> 2226.8917 | G34: =IF(N(FX!D15)=0,"",Data!D500/FX!D15) -> 2553.4593 | H34: =IF(N(FX!E15)=0,"",Data!D501/FX!E15) -> 2731.8424 | I34: =IF(N(FX!F15)=0,"",Data!D502/FX!F15) -> 2805.0751 | J34: =IF(N(FX!G15)=0,"",Data!D503/FX!G15) -> 2597.1833 | K34: =IF(N(FX!H15)=0,"",Data!D504/FX!H15) -> 3088.6782 | L34: =IF(N(FX!I15)=0,"",Data!D505/FX!I15) -> 3246.7803 | M34: =IF(N(FX!J15)=0,"",Data!D506/FX!J15) -> 3421.5356 | N34: =IF(N(FX!K15)=0,"",Data!D507/FX!K15) -> 3719.136 | O34: =IF(N(FX!L15)=0,"",Data!D508/FX!L15) -> 3871.3358 | P34: =IF(N(FX!M15)=0,"",Data!D509/FX!M15) -> 4053.9503 | Q34: =IF(N(FX!N15)=0,"",Data!D510/FX!N15) -> 4443.4031 | R34: =IF(N(FX!O15)=0,"",Data!D511/FX!O15) -> 5058.9901 | S34: =IF(N(FX!P15)=0,"",Data!D512/FX!P15) -> 5632.5312 | T34: =IF(N(FX!Q15)=0,"",Data!D513/FX!Q15) -> 6153.6332
A35: KOR | B35: EAA | C35: 1 | E35: =IF(N(FX!B16)=0,"",Data!D514*1000/FX!B16) -> 1540.5133 | F35: =IF(N(FX!C16)=0,"",Data!D515*1000/FX!C16) -> 1580.1983 | G35: =IF(N(FX!D16)=0,"",Data!D516*1000/FX!D16) -> 1711.708 | H35: =IF(N(FX!E16)=0,"",Data!D517*1000/FX!E16) -> 1824.5182 | I35: =IF(N(FX!F16)=0,"",Data!D518*1000/FX!F16) -> 1744.094 | J35: =IF(N(FX!G16)=0,"",Data!D519*1000/FX!G16) -> 1744.4661 | K35: =IF(N(FX!H16)=0,"",Data!D520*1000/FX!H16) -> 1950.6316 | L35: =IF(N(FX!I16)=0,"",Data!D521*1000/FX!I16) -> 1804.7829 | M35: =IF(N(FX!J16)=0,"",Data!D522*1000/FX!J16) -> 1837.8473 | N35: =IF(N(FX!K16)=0,"",Data!D523*1000/FX!K16) -> 1885.4412 | O35: =IF(N(FX!L16)=0,"",Data!D524*1000/FX!L16) -> 1884.9789 | P35: =IF(N(FX!M16)=0,"",Data!D525*1000/FX!M16) -> 2282.9516 | Q35: =IF(N(FX!N16)=0,"",Data!D526*1000/FX!N16) -> 2518.4813 | R35: =IF(N(FX!O16)=0,"",Data!D527*1000/FX!O16) -> 2641.8184 | S35: =IF(N(FX!P16)=0,"",Data!D528*1000/FX!P16) -> 2779.8496 | T35: =IF(N(FX!Q16)=0,"",Data!D529*1000/FX!Q16) -> 2902.8172
A36: ZAF | B36: EAA | C36: 1 | E36: =IF(N(FX!B33)=0,"",Data!D530/FX!B33) -> 346.4569 | F36: =IF(N(FX!C33)=0,"",Data!D531/FX!C33) -> 323.5588 | G36: =IF(N(FX!D33)=0,"",Data!D532/FX!D33) -> 380.95949 | H36: =IF(N(FX!E33)=0,"",Data!D533/FX!E33) -> 405.07477 | I36: =IF(N(FX!F33)=0,"",Data!D534/FX!F33) -> 389.28789 | J36: =IF(N(FX!G33)=0,"",Data!D535/FX!G33) -> 337.75106 | K36: =IF(N(FX!H33)=0,"",Data!D536/FX!H33) -> 419.94858 | L36: =IF(N(FX!I33)=0,"",Data!D537/FX!I33) -> 407.49267 | M36: =IF(N(FX!J33)=0,"",Data!D538/FX!J33) -> 381.44553 | N36: =IF(N(FX!K33)=0,"",Data!D539/FX!K33) -> 401.11566 | O36: =IF(N(FX!L33)=0,"",Data!D540/FX!L33) -> 427.15428 | P36: =IF(N(FX!M33)=0,"",Data!D541/FX!M33) -> 492.90848 | Q36: =IF(N(FX!N33)=0,"",Data!D542/FX!N33) -> 511.94461 | R36: =IF(N(FX!O33)=0,"",Data!D543/FX!O33) -> 535.81574 | S36: =IF(N(FX!P33)=0,"",Data!D544/FX!P33) -> 561.17889 | T36: =IF(N(FX!Q33)=0,"",Data!D545/FX!Q33) -> 588.33851
A37: MAR | B37: EAA | C37: 1 | E37: =IF(N(FX!B18)=0,"",Data!D546/FX!B18) -> 110.46311 | F37: =IF(N(FX!C18)=0,"",Data!D547/FX!C18) -> 111.54434 | G37: =IF(N(FX!D18)=0,"",Data!D548/FX!D18) -> 118.56553 | H37: =IF(N(FX!E18)=0,"",Data!D549/FX!E18) -> 127.2886 | I37: =IF(N(FX!F18)=0,"",Data!D550/FX!F18) -> 128.8815 | J37: =IF(N(FX!G18)=0,"",Data!D551/FX!G18) -> 121.44152 | K37: =IF(N(FX!H18)=0,"",Data!D552/FX!H18) -> 141.99778 | L37: =IF(N(FX!I18)=0,"",Data!D553/FX!I18) -> 131.25394 | M37: =IF(N(FX!J18)=0,"",Data!D554/FX!J18) -> 146.65745 | N37: =IF(N(FX!K18)=0,"",Data!D555/FX!K18) -> 162.43159 | O37: =IF(N(FX!L18)=0,"",Data!D556/FX!L18) -> 183.97861 | P37: =IF(N(FX!M18)=0,"",Data!D557/FX!M18) -> 204.01609 | Q37: =IF(N(FX!N18)=0,"",Data!D558/FX!N18) -> 207.10603 | R37: =IF(N(FX!O18)=0,"",Data!D559/FX!O18) -> 215.04205 | S37: =IF(N(FX!P18)=0,"",Data!D560/FX!P18) -> 228.8943 | T37: =IF(N(FX!Q18)=0,"",Data!D561/FX!Q18) -> 244.82147
A38: TUN | B38: EAA | C38: 1 | E38: =IF(N(FX!B27)=0,"",Data!D562/FX!B27) -> 45.816327 | F38: =IF(N(FX!C27)=0,"",Data!D563/FX!C27) -> 44.32093 | G38: =IF(N(FX!D27)=0,"",Data!D564/FX!D27) -> 42.152893 | H38: =IF(N(FX!E27)=0,"",Data!D565/FX!E27) -> 42.637736 | I38: =IF(N(FX!F27)=0,"",Data!D566/FX!F27) -> 41.969283 | J38: =IF(N(FX!G27)=0,"",Data!D567/FX!G27) -> 42.52669 | K38: =IF(N(FX!H27)=0,"",Data!D568/FX!H27) -> 47.146953 | L38: =IF(N(FX!I27)=0,"",Data!D569/FX!I27) -> 44.980645 | M38: =IF(N(FX!J27)=0,"",Data!D570/FX!J27) -> 48.163987 | N38: =IF(N(FX!K27)=0,"",Data!D571/FX!K27) -> 51.398714 | O38: =IF(N(FX!L27)=0,"",Data!D572/FX!L27) -> 57.213333 | P38: =IF(N(FX!M27)=0,"",Data!D573/FX!M27) -> 61.535593 | Q38: =IF(N(FX!N27)=0,"",Data!D574/FX!N27) -> 62.930159 | R38: =IF(N(FX!O27)=0,"",Data!D575/FX!O27) -> 65.209726 | S38: =IF(N(FX!P27)=0,"",Data!D576/FX!P27) -> 67.704142 | T38: =IF(N(FX!Q27)=0,"",Data!D577/FX!Q27) -> 69.573913
A39: ESP | B39: EAA | C39: 1 | E39: =IF(N(FX!B11)=0,"",Data!D578/FX!B11) -> 1207.9 | F39: =IF(N(FX!C11)=0,"",Data!D579/FX!C11) -> 1247.7444 | G39: =IF(N(FX!D11)=0,"",Data!D580/FX!D11) -> 1314.6292 | H39: =IF(N(FX!E11)=0,"",Data!D581/FX!E11) -> 1426.2118 | I39: =IF(N(FX!F11)=0,"",Data!D582/FX!F11) -> 1403.302 | J39: =IF(N(FX!G11)=0,"",Data!D583/FX!G11) -> 1287.1424 | K39: =IF(N(FX!H11)=0,"",Data!D584/FX!H11) -> 1460.7118 | L39: =IF(N(FX!I11)=0,"",Data!D585/FX!I11) -> 1445.9905 | M39: =IF(N(FX!J11)=0,"",Data!D586/FX!J11) -> 1617.7749 | N39: =IF(N(FX!K11)=0,"",Data!D587/FX!K11) -> 1729.8885 | O39: =IF(N(FX!L11)=0,"",Data!D588/FX!L11) -> 1906.8148 | P39: =IF(N(FX!M11)=0,"",Data!D589/FX!M11) -> 2044.7931 | Q39: =IF(N(FX!N11)=0,"",Data!D590/FX!N11) -> 2081.5955 | R39: =IF(N(FX!O11)=0,"",Data!D591/FX!O11) -> 2159.2697 | S39: =IF(N(FX!P11)=0,"",Data!D592/FX!P11) -> 2320.7093 | T39: =IF(N(FX!Q11)=0,"",Data!D593/FX!Q11) -> 2469.2738
A40: PRT | B40: EAA | C40: 1 | E40: =IF(N(FX!B11)=0,"",Data!D594/FX!B11) -> 199.32222 | F40: =IF(N(FX!C11)=0,"",Data!D595/FX!C11) -> 207.08889 | G40: =IF(N(FX!D11)=0,"",Data!D596/FX!D11) -> 219.67416 | H40: =IF(N(FX!E11)=0,"",Data!D597/FX!E11) -> 241.17647 | I40: =IF(N(FX!F11)=0,"",Data!D598/FX!F11) -> 240.08283 | J40: =IF(N(FX!G11)=0,"",Data!D599/FX!G11) -> 229.14624 | K40: =IF(N(FX!H11)=0,"",Data!D600/FX!H11) -> 255.95886 | L40: =IF(N(FX!I11)=0,"",Data!D601/FX!I11) -> 256.39517 | M40: =IF(N(FX!J11)=0,"",Data!D602/FX!J11) -> 292.30187 | N40: =IF(N(FX!K11)=0,"",Data!D603/FX!K11) -> 315.0633 | O40: =IF(N(FX!L11)=0,"",Data!D604/FX!L11) -> 348.1214 | P40: =IF(N(FX!M11)=0,"",Data!D605/FX!M11) -> 370.74713 | Q40: =IF(N(FX!N11)=0,"",Data!D606/FX!N11) -> 375.96629 | R40: =IF(N(FX!O11)=0,"",Data!D607/FX!O11) -> 390.48315 | S40: =IF(N(FX!P11)=0,"",Data!D608/FX!P11) -> 421.80233 | T40: =IF(N(FX!Q11)=0,"",Data!D609/FX!Q11) -> 448.96429
A41: FRA | B41: EAA | C41: 1 | E41: =IF(N(FX!B11)=0,"",Data!D610/FX!B11) -> 2446 | F41: =IF(N(FX!C11)=0,"",Data!D611/FX!C11) -> 2479.8 | G41: =IF(N(FX!D11)=0,"",Data!D612/FX!D11) -> 2574.9213 | H41: =IF(N(FX!E11)=0,"",Data!D613/FX!E11) -> 2771.0118 | I41: =IF(N(FX!F11)=0,"",Data!D614/FX!F11) -> 2722.42 | J41: =IF(N(FX!G11)=0,"",Data!D615/FX!G11) -> 2642.5168 | K41: =IF(N(FX!H11)=0,"",Data!D616/FX!H11) -> 2965.3582 | L41: =IF(N(FX!I11)=0,"",Data!D617/FX!I11) -> 2789.2801 | M41: =IF(N(FX!J11)=0,"",Data!D618/FX!J11) -> 3063.9312 | N41: =IF(N(FX!K11)=0,"",Data!D619/FX!K11) -> 3176.3229 | O41: =IF(N(FX!L11)=0,"",Data!D620/FX!L11) -> 3374.7715 | P41: =IF(N(FX!M11)=0,"",Data!D621/FX!M11) -> 3527.7931 | Q41: =IF(N(FX!N11)=0,"",Data!D622/FX!N11) -> 3544.8427 | R41: =IF(N(FX!O11)=0,"",Data!D623/FX!O11) -> 3650.8876 | S41: =IF(N(FX!P11)=0,"",Data!D624/FX!P11) -> 3906.0581 | T41: =IF(N(FX!Q11)=0,"",Data!D625/FX!Q11) -> 4131.2976
A42: ITA | B42: EAA | C42: 1 | E42: =IF(N(FX!B11)=0,"",Data!D626/FX!B11) -> 1848.0889 | F42: =IF(N(FX!C11)=0,"",Data!D627/FX!C11) -> 1894.2889 | G42: =IF(N(FX!D11)=0,"",Data!D628/FX!D11) -> 1960.1011 | H42: =IF(N(FX!E11)=0,"",Data!D629/FX!E11) -> 2091.4588 | I42: =IF(N(FX!F11)=0,"",Data!D630/FX!F11) -> 2019.3306 | J42: =IF(N(FX!G11)=0,"",Data!D631/FX!G11) -> 1903.5792 | K42: =IF(N(FX!H11)=0,"",Data!D632/FX!H11) -> 2178.4228 | L42: =IF(N(FX!I11)=0,"",Data!D633/FX!I11) -> 2099.9159 | M42: =IF(N(FX!J11)=0,"",Data!D634/FX!J11) -> 2316.7261 | N42: =IF(N(FX!K11)=0,"",Data!D635/FX!K11) -> 2382.8915 | O42: =IF(N(FX!L11)=0,"",Data!D636/FX!L11) -> 2547.7265 | P42: =IF(N(FX!M11)=0,"",Data!D637/FX!M11) -> 2648.9425 | Q42: =IF(N(FX!N11)=0,"",Data!D638/FX!N11) -> 2632.8539 | R42: =IF(N(FX!O11)=0,"",Data!D639/FX!O11) -> 2689.1685 | S42: =IF(N(FX!P11)=0,"",Data!D640/FX!P11) -> 2854.7791 | T42: =IF(N(FX!Q11)=0,"",Data!D641/FX!Q11) -> 3000.9762
A44: Weight inside its region used for year t = included GDP USD t-1 / region total t-1 [calc]
A45: iso3 | E45: 2016 | F45: 2017 | G45: 2018 | H45: 2019 | I45: 2020 | J45: 2021 | K45: 2022 | L45: 2023 | M45: 2024 | N45: 2025 | O45: 2026 | P45: 2027 | Q45: 2028 | R45: 2029 | S45: 2030
A46: MEX | B46: Mexico | E46: =IF($C3=0,0,N(E3)/SUMPRODUCT($C$3:$C$3,E$3:E$3)) -> 1 | F46: =IF($C3=0,0,N(F3)/SUMPRODUCT($C$3:$C$3,F$3:F$3)) -> 1 | G46: =IF($C3=0,0,N(G3)/SUMPRODUCT($C$3:$C$3,G$3:G$3)) -> 1 | H46: =IF($C3=0,0,N(H3)/SUMPRODUCT($C$3:$C$3,H$3:H$3)) -> 1 | I46: =IF($C3=0,0,N(I3)/SUMPRODUCT($C$3:$C$3,I$3:I$3)) -> 1 | J46: =IF($C3=0,0,N(J3)/SUMPRODUCT($C$3:$C$3,J$3:J$3)) -> 1 | K46: =IF($C3=0,0,N(K3)/SUMPRODUCT($C$3:$C$3,K$3:K$3)) -> 1 | L46: =IF($C3=0,0,N(L3)/SUMPRODUCT($C$3:$C$3,L$3:L$3)) -> 1 | ... S46: =IF($C3=0,0,N(S3)/SUMPRODUCT($C$3:$C$3,S$3:S$3)) -> 1
A47: USA | B47: North America | E47: =IF($C4=0,0,N(E4)/SUMPRODUCT($C$4:$C$5,E$4:E$5)) -> 0.9216611 | F47: =IF($C4=0,0,N(F4)/SUMPRODUCT($C$4:$C$5,F$4:F$5)) -> 0.92508009 | G47: =IF($C4=0,0,N(G4)/SUMPRODUCT($C$4:$C$5,G$4:G$5)) -> 0.92254265 | H47: =IF($C4=0,0,N(H4)/SUMPRODUCT($C$4:$C$5,H$4:H$5)) -> 0.92314387 | I47: =IF($C4=0,0,N(I4)/SUMPRODUCT($C$4:$C$5,I$4:I$5)) -> 0.92511529 | J47: =IF($C4=0,0,N(J4)/SUMPRODUCT($C$4:$C$5,J$4:J$5)) -> 0.9281177 | K47: =IF($C4=0,0,N(K4)/SUMPRODUCT($C$4:$C$5,K$4:K$5)) -> 0.92148889 | L47: =IF($C4=0,0,N(L4)/SUMPRODUCT($C$4:$C$5,L$4:L$5)) -> 0.92210702 | ... S47: =IF($C4=0,0,N(S4)/SUMPRODUCT($C$4:$C$5,S$4:S$5)) -> 0.92456142
A48: CAN | B48: North America | E48: =IF($C5=0,0,N(E5)/SUMPRODUCT($C$4:$C$5,E$4:E$5)) -> 0.078338904 | F48: =IF($C5=0,0,N(F5)/SUMPRODUCT($C$4:$C$5,F$4:F$5)) -> 0.074919912 | G48: =IF($C5=0,0,N(G5)/SUMPRODUCT($C$4:$C$5,G$4:G$5)) -> 0.077457351 | H48: =IF($C5=0,0,N(H5)/SUMPRODUCT($C$4:$C$5,H$4:H$5)) -> 0.076856132 | I48: =IF($C5=0,0,N(I5)/SUMPRODUCT($C$4:$C$5,I$4:I$5)) -> 0.074884707 | J48: =IF($C5=0,0,N(J5)/SUMPRODUCT($C$4:$C$5,J$4:J$5)) -> 0.0718823 | K48: =IF($C5=0,0,N(K5)/SUMPRODUCT($C$4:$C$5,K$4:K$5)) -> 0.07851111 | L48: =IF($C5=0,0,N(L5)/SUMPRODUCT($C$4:$C$5,L$4:L$5)) -> 0.077892985 | ... S48: =IF($C5=0,0,N(S5)/SUMPRODUCT($C$4:$C$5,S$4:S$5)) -> 0.075438578
A49: ARG | B49: Latin America | E49: =IF($C6=0,0,N(E6)/SUMPRODUCT($C$6:$C$20,E$6:E$20)) -> 0.17916261 | F49: =IF($C6=0,0,N(F6)/SUMPRODUCT($C$6:$C$20,F$6:F$20)) -> 0.15849859 | G49: =IF($C6=0,0,N(G6)/SUMPRODUCT($C$6:$C$20,G$6:G$20)) -> 0.16172864 | H49: =IF($C6=0,0,N(H6)/SUMPRODUCT($C$6:$C$20,H$6:H$20)) -> 0.13877194 | I49: =IF($C6=0,0,N(I6)/SUMPRODUCT($C$6:$C$20,I$6:I$20)) -> 0.12257583 | J49: =IF($C6=0,0,N(J6)/SUMPRODUCT($C$6:$C$20,J$6:J$20)) -> 0.1266389 | K49: =IF($C6=0,0,N(K6)/SUMPRODUCT($C$6:$C$20,K$6:K$20)) -> 0.13804422 | L49: =IF($C6=0,0,N(L6)/SUMPRODUCT($C$6:$C$20,L$6:L$20)) -> 0.15699107 | ... S49: =IF($C6=0,0,N(S6)/SUMPRODUCT($C$6:$C$20,S$6:S$20)) -> 0.13264399
A50: BRA | B50: Latin America | E50: =IF($C7=0,0,N(E7)/SUMPRODUCT($C$6:$C$20,E$6:E$20)) -> 0.50004055 | F50: =IF($C7=0,0,N(F7)/SUMPRODUCT($C$6:$C$20,F$6:F$20)) -> 0.51074573 | G50: =IF($C7=0,0,N(G7)/SUMPRODUCT($C$6:$C$20,G$6:G$20)) -> 0.51865367 | H50: =IF($C7=0,0,N(H7)/SUMPRODUCT($C$6:$C$20,H$6:H$20)) -> 0.50731319 | I50: =IF($C7=0,0,N(I7)/SUMPRODUCT($C$6:$C$20,I$6:I$20)) -> 0.51449591 | J50: =IF($C7=0,0,N(J7)/SUMPRODUCT($C$6:$C$20,J$6:J$20)) -> 0.48578813 | K50: =IF($C7=0,0,N(K7)/SUMPRODUCT($C$6:$C$20,K$6:K$20)) -> 0.47486585 | L50: =IF($C7=0,0,N(L7)/SUMPRODUCT($C$6:$C$20,L$6:L$20)) -> 0.48405839 | ... S50: =IF($C7=0,0,N(S7)/SUMPRODUCT($C$6:$C$20,S$6:S$20)) -> 0.47255975
A51: CHL | B51: Latin America | E51: =IF($C8=0,0,N(E8)/SUMPRODUCT($C$6:$C$20,E$6:E$20)) -> 0.067771584 | F51: =IF($C8=0,0,N(F8)/SUMPRODUCT($C$6:$C$20,F$6:F$20)) -> 0.070561799 | G51: =IF($C8=0,0,N(G8)/SUMPRODUCT($C$6:$C$20,G$6:G$20)) -> 0.069306163 | H51: =IF($C8=0,0,N(H8)/SUMPRODUCT($C$6:$C$20,H$6:H$20)) -> 0.078249755 | I51: =IF($C8=0,0,N(I8)/SUMPRODUCT($C$6:$C$20,I$6:I$20)) -> 0.07663808 | J51: =IF($C8=0,0,N(J8)/SUMPRODUCT($C$6:$C$20,J$6:J$20)) -> 0.083778109 | K51: =IF($C8=0,0,N(K8)/SUMPRODUCT($C$6:$C$20,K$6:K$20)) -> 0.089522559 | L51: =IF($C8=0,0,N(L8)/SUMPRODUCT($C$6:$C$20,L$6:L$20)) -> 0.074895311 | ... S51: =IF($C8=0,0,N(S8)/SUMPRODUCT($C$6:$C$20,S$6:S$20)) -> 0.078568017
A52: COL | B52: Latin America | E52: =IF($C9=0,0,N(E9)/SUMPRODUCT($C$6:$C$20,E$6:E$20)) -> 0.081560727 | F52: =IF($C9=0,0,N(F9)/SUMPRODUCT($C$6:$C$20,F$6:F$20)) -> 0.080521591 | G52: =IF($C9=0,0,N(G9)/SUMPRODUCT($C$6:$C$20,G$6:G$20)) -> 0.078391382 | H52: =IF($C9=0,0,N(H9)/SUMPRODUCT($C$6:$C$20,H$6:H$20)) -> 0.088224076 | I52: =IF($C9=0,0,N(I9)/SUMPRODUCT($C$6:$C$20,I$6:I$20)) -> 0.088663636 | J52: =IF($C9=0,0,N(J9)/SUMPRODUCT($C$6:$C$20,J$6:J$20)) -> 0.088961265 | K52: =IF($C9=0,0,N(K9)/SUMPRODUCT($C$6:$C$20,K$6:K$20)) -> 0.09056615 | L52: =IF($C9=0,0,N(L9)/SUMPRODUCT($C$6:$C$20,L$6:L$20)) -> 0.0857725 | ... S52: =IF($C9=0,0,N(S9)/SUMPRODUCT($C$6:$C$20,S$6:S$20)) -> 0.10710055
A53: CRI | B53: Latin America | E53: =IF($C10=0,0,N(E10)/SUMPRODUCT($C$6:$C$20,E$6:E$20)) -> 0.015674779 | F53: =IF($C10=0,0,N(F10)/SUMPRODUCT($C$6:$C$20,F$6:F$20)) -> 0.016731429 | G53: =IF($C10=0,0,N(G10)/SUMPRODUCT($C$6:$C$20,G$6:G$20)) -> 0.015203852 | H53: =IF($C10=0,0,N(H10)/SUMPRODUCT($C$6:$C$20,H$6:H$20)) -> 0.016541189 | I53: =IF($C10=0,0,N(I10)/SUMPRODUCT($C$6:$C$20,I$6:I$20)) -> 0.017864209 | J53: =IF($C10=0,0,N(J10)/SUMPRODUCT($C$6:$C$20,J$6:J$20)) -> 0.020763622 | K53: =IF($C10=0,0,N(K10)/SUMPRODUCT($C$6:$C$20,K$6:K$20)) -> 0.018725104 | L53: =IF($C10=0,0,N(L10)/SUMPRODUCT($C$6:$C$20,L$6:L$20)) -> 0.017689365 | ... S53: =IF($C10=0,0,N(S10)/SUMPRODUCT($C$6:$C$20,S$6:S$20)) -> 0.020088135
A54: ECU | B54: Latin America | E54: =IF($C11=0,0,N(E11)/SUMPRODUCT($C$6:$C$20,E$6:E$20)) -> 0.026996906 | F54: =IF($C11=0,0,N(F11)/SUMPRODUCT($C$6:$C$20,F$6:F$20)) -> 0.027769639 | G54: =IF($C11=0,0,N(G11)/SUMPRODUCT($C$6:$C$20,G$6:G$20)) -> 0.026246554 | H54: =IF($C11=0,0,N(H11)/SUMPRODUCT($C$6:$C$20,H$6:H$20)) -> 0.028414621 | I54: =IF($C11=0,0,N(I11)/SUMPRODUCT($C$6:$C$20,I$6:I$20)) -> 0.029518692 | J54: =IF($C11=0,0,N(J11)/SUMPRODUCT($C$6:$C$20,J$6:J$20)) -> 0.031519188 | K54: =IF($C11=0,0,N(K11)/SUMPRODUCT($C$6:$C$20,K$6:K$20)) -> 0.030440062 | L54: =IF($C11=0,0,N(L11)/SUMPRODUCT($C$6:$C$20,L$6:L$20)) -> 0.028776975 | ... S54: =IF($C11=0,0,N(S11)/SUMPRODUCT($C$6:$C$20,S$6:S$20)) -> 0.025076606
A55: SLV | B55: Latin America | E55: =IF($C12=0,0,N(E12)/SUMPRODUCT($C$6:$C$20,E$6:E$20)) -> 0.0065096952 | F55: =IF($C12=0,0,N(F12)/SUMPRODUCT($C$6:$C$20,F$6:F$20)) -> 0.0068777266 | G55: =IF($C12=0,0,N(G12)/SUMPRODUCT($C$6:$C$20,G$6:G$20)) -> 0.0062758584 | H55: =IF($C12=0,0,N(H12)/SUMPRODUCT($C$6:$C$20,H$6:H$20)) -> 0.0068789396 | I55: =IF($C12=0,0,N(I12)/SUMPRODUCT($C$6:$C$20,I$6:I$20)) -> 0.0073741862 | J55: =IF($C12=0,0,N(J12)/SUMPRODUCT($C$6:$C$20,J$6:J$20)) -> 0.0081929506 | K55: =IF($C12=0,0,N(K12)/SUMPRODUCT($C$6:$C$20,K$6:K$20)) -> 0.0082476152 | L55: =IF($C12=0,0,N(L12)/SUMPRODUCT($C$6:$C$20,L$6:L$20)) -> 0.0078973752 | ... S55: =IF($C12=0,0,N(S12)/SUMPRODUCT($C$6:$C$20,S$6:S$20)) -> 0.0068533523
A56: GTM | B56: Latin America | E56: =IF($C13=0,0,N(E13)/SUMPRODUCT($C$6:$C$20,E$6:E$20)) -> 0.017280918 | F56: =IF($C13=0,0,N(F13)/SUMPRODUCT($C$6:$C$20,F$6:F$20)) -> 0.018780155 | G56: =IF($C13=0,0,N(G13)/SUMPRODUCT($C$6:$C$20,G$6:G$20)) -> 0.017996995 | H56: =IF($C13=0,0,N(H13)/SUMPRODUCT($C$6:$C$20,H$6:H$20)) -> 0.019383826 | I56: =IF($C13=0,0,N(I13)/SUMPRODUCT($C$6:$C$20,I$6:I$20)) -> 0.021162093 | J56: =IF($C13=0,0,N(J13)/SUMPRODUCT($C$6:$C$20,J$6:J$20)) -> 0.02555719 | K56: =IF($C13=0,0,N(K13)/SUMPRODUCT($C$6:$C$20,K$6:K$20)) -> 0.024536304 | L56: =IF($C13=0,0,N(L13)/SUMPRODUCT($C$6:$C$20,L$6:L$20)) -> 0.02368677 | ... S56: =IF($C13=0,0,N(S13)/SUMPRODUCT($C$6:$C$20,S$6:S$20)) -> 0.027500652
A57: HND | B57: Latin America | E57: =IF($C14=0,0,N(E14)/SUMPRODUCT($C$6:$C$20,E$6:E$20)) -> 0.0058252326 | F57: =IF($C14=0,0,N(F14)/SUMPRODUCT($C$6:$C$20,F$6:F$20)) -> 0.0061734021 | G57: =IF($C14=0,0,N(G14)/SUMPRODUCT($C$6:$C$20,G$6:G$20)) -> 0.0058118891 | H57: =IF($C14=0,0,N(H14)/SUMPRODUCT($C$6:$C$20,H$6:H$20)) -> 0.0063634931 | I57: =IF($C14=0,0,N(I14)/SUMPRODUCT($C$6:$C$20,I$6:I$20)) -> 0.0068035424 | J57: =IF($C14=0,0,N(J14)/SUMPRODUCT($C$6:$C$20,J$6:J$20)) -> 0.0076500681 | K57: =IF($C14=0,0,N(K14)/SUMPRODUCT($C$6:$C$20,K$6:K$20)) -> 0.0079655626 | L57: =IF($C14=0,0,N(L14)/SUMPRODUCT($C$6:$C$20,L$6:L$20)) -> 0.0077638176 | ... S57: =IF($C14=0,0,N(S14)/SUMPRODUCT($C$6:$C$20,S$6:S$20)) -> 0.0076698459
A58: NIC | B58: Latin America | E58: =IF($C15=0,0,N(E15)/SUMPRODUCT($C$6:$C$20,E$6:E$20)) -> 0.0035423737 | F58: =IF($C15=0,0,N(F15)/SUMPRODUCT($C$6:$C$20,F$6:F$20)) -> 0.0037776355 | G58: =IF($C15=0,0,N(G15)/SUMPRODUCT($C$6:$C$20,G$6:G$20)) -> 0.0034636196 | H58: =IF($C15=0,0,N(H15)/SUMPRODUCT($C$6:$C$20,H$6:H$20)) -> 0.0034438648 | I58: =IF($C15=0,0,N(I15)/SUMPRODUCT($C$6:$C$20,I$6:I$20)) -> 0.0034839676 | J58: =IF($C15=0,0,N(J15)/SUMPRODUCT($C$6:$C$20,J$6:J$20)) -> 0.004184303 | K58: =IF($C15=0,0,N(K15)/SUMPRODUCT($C$6:$C$20,K$6:K$20)) -> 0.0040356381 | L58: =IF($C15=0,0,N(L15)/SUMPRODUCT($C$6:$C$20,L$6:L$20)) -> 0.0038747107 | ... S58: =IF($C15=0,0,N(S15)/SUMPRODUCT($C$6:$C$20,S$6:S$20)) -> 0.0042053865
A59: PAN | B59: Latin America | E59: =IF($C16=0,0,N(E16)/SUMPRODUCT($C$6:$C$20,E$6:E$20)) -> 0.015021733 | F59: =IF($C16=0,0,N(F16)/SUMPRODUCT($C$6:$C$20,F$6:F$20)) -> 0.016465033 | G59: =IF($C16=0,0,N(G16)/SUMPRODUCT($C$6:$C$20,G$6:G$20)) -> 0.015626837 | H59: =IF($C16=0,0,N(H16)/SUMPRODUCT($C$6:$C$20,H$6:H$20)) -> 0.017797472 | I59: =IF($C16=0,0,N(I16)/SUMPRODUCT($C$6:$C$20,I$6:I$20)) -> 0.019143256 | J59: =IF($C16=0,0,N(J16)/SUMPRODUCT($C$6:$C$20,J$6:J$20)) -> 0.018759621 | K59: =IF($C16=0,0,N(K16)/SUMPRODUCT($C$6:$C$20,K$6:K$20)) -> 0.019142192 | L59: =IF($C16=0,0,N(L16)/SUMPRODUCT($C$6:$C$20,L$6:L$20)) -> 0.018951718 | ... S59: =IF($C16=0,0,N(S16)/SUMPRODUCT($C$6:$C$20,S$6:S$20)) -> 0.017813957
A60: PRY | B60: Latin America | E60: =IF($C17=0,0,N(E17)/SUMPRODUCT($C$6:$C$20,E$6:E$20)) -> 0.010066187 | F60: =IF($C17=0,0,N(F17)/SUMPRODUCT($C$6:$C$20,F$6:F$20)) -> 0.010262135 | G60: =IF($C17=0,0,N(G17)/SUMPRODUCT($C$6:$C$20,G$6:G$20)) -> 0.0097954954 | H60: =IF($C17=0,0,N(H17)/SUMPRODUCT($C$6:$C$20,H$6:H$20)) -> 0.01063852 | I60: =IF($C17=0,0,N(I17)/SUMPRODUCT($C$6:$C$20,I$6:I$20)) -> 0.010405473 | J60: =IF($C17=0,0,N(J17)/SUMPRODUCT($C$6:$C$20,J$6:J$20)) -> 0.011650699 | K60: =IF($C17=0,0,N(K17)/SUMPRODUCT($C$6:$C$20,K$6:K$20)) -> 0.011349444 | L60: =IF($C17=0,0,N(L17)/SUMPRODUCT($C$6:$C$20,L$6:L$20)) -> 0.010372439 | ... S60: =IF($C17=0,0,N(S17)/SUMPRODUCT($C$6:$C$20,S$6:S$20)) -> 0.011966655
... A63: VEN | B63: Latin America | E63: =IF($C20=0,0,N(E20)/SUMPRODUCT($C$6:$C$20,E$6:E$20)) -> 0 | F63: =IF($C20=0,0,N(F20)/SUMPRODUCT($C$6:$C$20,F$6:F$20)) -> 0 | G63: =IF($C20=0,0,N(G20)/SUMPRODUCT($C$6:$C$20,G$6:G$20)) -> 0 | H63: =IF($C20=0,0,N(H20)/SUMPRODUCT($C$6:$C$20,H$6:H$20)) -> 0 | I63: =IF($C20=0,0,N(I20)/SUMPRODUCT($C$6:$C$20,I$6:I$20)) -> 0 | J63: =IF($C20=0,0,N(J20)/SUMPRODUCT($C$6:$C$20,J$6:J$20)) -> 0 | K63: =IF($C20=0,0,N(K20)/SUMPRODUCT($C$6:$C$20,K$6:K$20)) -> 0 | L63: =IF($C20=0,0,N(L20)/SUMPRODUCT($C$6:$C$20,L$6:L$20)) -> 0 | ... S63: =IF($C20=0,0,N(S20)/SUMPRODUCT($C$6:$C$20,S$6:S$20)) -> 0
A64: GBR | B64: EAA | E64: =IF($C21=0,0,N(E21)/SUMPRODUCT($C$21:$C$42,E$21:E$42)) -> 0.10786705 | F64: =IF($C21=0,0,N(F21)/SUMPRODUCT($C$21:$C$42,F$21:F$42)) -> 0.097865772 | G64: =IF($C21=0,0,N(G21)/SUMPRODUCT($C$21:$C$42,G$21:G$42)) -> 0.090149911 | H64: =IF($C21=0,0,N(H21)/SUMPRODUCT($C$21:$C$42,H$21:H$42)) -> 0.089050474 | I64: =IF($C21=0,0,N(I21)/SUMPRODUCT($C$21:$C$42,I$21:I$42)) -> 0.087698121 | J64: =IF($C21=0,0,N(J21)/SUMPRODUCT($C$21:$C$42,J$21:J$42)) -> 0.084466004 | K64: =IF($C21=0,0,N(K21)/SUMPRODUCT($C$21:$C$42,K$21:K$42)) -> 0.083767175 | L64: =IF($C21=0,0,N(L21)/SUMPRODUCT($C$21:$C$42,L$21:L$42)) -> 0.082427536 | ... S64: =IF($C21=0,0,N(S21)/SUMPRODUCT($C$21:$C$42,S$21:S$42)) -> 0.0815431
A65: CHE | B65: EAA | E65: =IF($C22=0,0,N(E22)/SUMPRODUCT($C$21:$C$42,E$21:E$42)) -> 0.025732932 | F65: =IF($C22=0,0,N(F22)/SUMPRODUCT($C$21:$C$42,F$21:F$42)) -> 0.025109557 | G65: =IF($C22=0,0,N(G22)/SUMPRODUCT($C$21:$C$42,G$21:G$42)) -> 0.023747932 | H65: =IF($C22=0,0,N(H22)/SUMPRODUCT($C$21:$C$42,H$21:H$42)) -> 0.022665226 | I65: =IF($C22=0,0,N(I22)/SUMPRODUCT($C$21:$C$42,I$21:I$42)) -> 0.0224656 | J65: =IF($C22=0,0,N(J22)/SUMPRODUCT($C$21:$C$42,J$21:J$42)) -> 0.023333061 | K65: =IF($C22=0,0,N(K22)/SUMPRODUCT($C$21:$C$42,K$21:K$42)) -> 0.02203636 | L65: =IF($C22=0,0,N(L22)/SUMPRODUCT($C$21:$C$42,L$21:L$42)) -> 0.02228566 | ... S65: =IF($C22=0,0,N(S22)/SUMPRODUCT($C$21:$C$42,S$21:S$42)) -> 0.020953275
A66: ROU | B66: EAA | E66: =IF($C23=0,0,N(E23)/SUMPRODUCT($C$21:$C$42,E$21:E$42)) -> 0.0064589055 | F66: =IF($C23=0,0,N(F23)/SUMPRODUCT($C$21:$C$42,F$21:F$42)) -> 0.0066896017 | G66: =IF($C23=0,0,N(G23)/SUMPRODUCT($C$21:$C$42,G$21:G$42)) -> 0.0070328818 | H66: =IF($C23=0,0,N(H23)/SUMPRODUCT($C$21:$C$42,H$21:H$42)) -> 0.0074120491 | I66: =IF($C23=0,0,N(I23)/SUMPRODUCT($C$21:$C$42,I$21:I$42)) -> 0.007549213 | J66: =IF($C23=0,0,N(J23)/SUMPRODUCT($C$21:$C$42,J$21:J$42)) -> 0.0076975834 | K66: =IF($C23=0,0,N(K23)/SUMPRODUCT($C$21:$C$42,K$21:K$42)) -> 0.0074026604 | L66: =IF($C23=0,0,N(L23)/SUMPRODUCT($C$21:$C$42,L$21:L$42)) -> 0.0075912887 | ... S66: =IF($C23=0,0,N(S23)/SUMPRODUCT($C$21:$C$42,S$21:S$42)) -> 0.0096461821
A67: SRB | B67: EAA | E67: =IF($C24=0,0,N(E24)/SUMPRODUCT($C$21:$C$42,E$21:E$42)) -> 0.0015011236 | F67: =IF($C24=0,0,N(F24)/SUMPRODUCT($C$21:$C$42,F$21:F$42)) -> 0.0015247531 | G67: =IF($C24=0,0,N(G24)/SUMPRODUCT($C$21:$C$42,G$21:G$42)) -> 0.0015375851 | H67: =IF($C24=0,0,N(H24)/SUMPRODUCT($C$21:$C$42,H$21:H$42)) -> 0.0016185618 | I67: =IF($C24=0,0,N(I24)/SUMPRODUCT($C$21:$C$42,I$21:I$42)) -> 0.001637056 | J67: =IF($C24=0,0,N(J24)/SUMPRODUCT($C$21:$C$42,J$21:J$42)) -> 0.0017264616 | K67: =IF($C24=0,0,N(K24)/SUMPRODUCT($C$21:$C$42,K$21:K$42)) -> 0.0017267858 | L67: =IF($C24=0,0,N(L24)/SUMPRODUCT($C$21:$C$42,L$21:L$42)) -> 0.0017256135 | ... S67: =IF($C24=0,0,N(S24)/SUMPRODUCT($C$21:$C$42,S$21:S$42)) -> 0.002243047
A68: SVN | B68: EAA | E68: =IF($C25=0,0,N(E25)/SUMPRODUCT($C$21:$C$42,E$21:E$42)) -> 0.0015545094 | F68: =IF($C25=0,0,N(F25)/SUMPRODUCT($C$21:$C$42,F$21:F$42)) -> 0.0016053119 | G68: =IF($C25=0,0,N(G25)/SUMPRODUCT($C$21:$C$42,G$21:G$42)) -> 0.0016020196 | H68: =IF($C25=0,0,N(H25)/SUMPRODUCT($C$21:$C$42,H$21:H$42)) -> 0.0016399484 | I68: =IF($C25=0,0,N(I25)/SUMPRODUCT($C$21:$C$42,I$21:I$42)) -> 0.0016383298 | J68: =IF($C25=0,0,N(J25)/SUMPRODUCT($C$21:$C$42,J$21:J$42)) -> 0.0016461657 | K68: =IF($C25=0,0,N(K25)/SUMPRODUCT($C$21:$C$42,K$21:K$42)) -> 0.0016056388 | L68: =IF($C25=0,0,N(L25)/SUMPRODUCT($C$21:$C$42,L$21:L$42)) -> 0.0015445346 | ... S68: =IF($C25=0,0,N(S25)/SUMPRODUCT($C$21:$C$42,S$21:S$42)) -> 0.0017684083
A69: HRV | B69: EAA | E69: =IF($C26=0,0,N(E26)/SUMPRODUCT($C$21:$C$42,E$21:E$42)) -> 0.0018566069 | F69: =IF($C26=0,0,N(F26)/SUMPRODUCT($C$21:$C$42,F$21:F$42)) -> 0.00190864 | G69: =IF($C26=0,0,N(G26)/SUMPRODUCT($C$21:$C$42,G$21:G$42)) -> 0.0018688349 | H69: =IF($C26=0,0,N(H26)/SUMPRODUCT($C$21:$C$42,H$21:H$42)) -> 0.0018838123 | I69: =IF($C26=0,0,N(I26)/SUMPRODUCT($C$21:$C$42,I$21:I$42)) -> 0.0018679545 | J69: =IF($C26=0,0,N(J26)/SUMPRODUCT($C$21:$C$42,J$21:J$42)) -> 0.0017870443 | K69: =IF($C26=0,0,N(K26)/SUMPRODUCT($C$21:$C$42,K$21:K$42)) -> 0.0018003646 | L69: =IF($C26=0,0,N(L26)/SUMPRODUCT($C$21:$C$42,L$21:L$42)) -> 0.0018352546 | ... S69: =IF($C26=0,0,N(S26)/SUMPRODUCT($C$21:$C$42,S$21:S$42)) -> 0.0023218259
A70: MNE | B70: EAA | E70: =IF($C27=0,0,N(E27)/SUMPRODUCT($C$21:$C$42,E$21:E$42)) -> 0.00014579836 | F70: =IF($C27=0,0,N(F27)/SUMPRODUCT($C$21:$C$42,F$21:F$42)) -> 0.0001580837 | G70: =IF($C27=0,0,N(G27)/SUMPRODUCT($C$21:$C$42,G$21:G$42)) -> 0.00015971342 | H70: =IF($C27=0,0,N(H27)/SUMPRODUCT($C$21:$C$42,H$21:H$42)) -> 0.00016594287 | I70: =IF($C27=0,0,N(I27)/SUMPRODUCT($C$21:$C$42,I$21:I$42)) -> 0.00016669053 | J70: =IF($C27=0,0,N(J27)/SUMPRODUCT($C$21:$C$42,J$21:J$42)) -> 0.00014580929 | K70: =IF($C27=0,0,N(K27)/SUMPRODUCT($C$21:$C$42,K$21:K$42)) -> 0.00015183054 | L70: =IF($C27=0,0,N(L27)/SUMPRODUCT($C$21:$C$42,L$21:L$42)) -> 0.00016123964 | ... S70: =IF($C27=0,0,N(S27)/SUMPRODUCT($C$21:$C$42,S$21:S$42)) -> 0.00020948805
A71: MKD | B71: EAA | E71: =IF($C28=0,0,N(E28)/SUMPRODUCT($C$21:$C$42,E$21:E$42)) -> 0 | F71: =IF($C28=0,0,N(F28)/SUMPRODUCT($C$21:$C$42,F$21:F$42)) -> 0 | G71: =IF($C28=0,0,N(G28)/SUMPRODUCT($C$21:$C$42,G$21:G$42)) -> 0 | H71: =IF($C28=0,0,N(H28)/SUMPRODUCT($C$21:$C$42,H$21:H$42)) -> 0 | I71: =IF($C28=0,0,N(I28)/SUMPRODUCT($C$21:$C$42,I$21:I$42)) -> 0 | J71: =IF($C28=0,0,N(J28)/SUMPRODUCT($C$21:$C$42,J$21:J$42)) -> 0 | K71: =IF($C28=0,0,N(K28)/SUMPRODUCT($C$21:$C$42,K$21:K$42)) -> 0 | L71: =IF($C28=0,0,N(L28)/SUMPRODUCT($C$21:$C$42,L$21:L$42)) -> 0 | ... S71: =IF($C28=0,0,N(S28)/SUMPRODUCT($C$21:$C$42,S$21:S$42)) -> 0
A72: RUS | B72: EAA | E72: =IF($C29=0,0,N(E29)/SUMPRODUCT($C$21:$C$42,E$21:E$42)) -> 0.049420898 | F72: =IF($C29=0,0,N(F29)/SUMPRODUCT($C$21:$C$42,F$21:F$42)) -> 0.046123208 | G72: =IF($C29=0,0,N(G29)/SUMPRODUCT($C$21:$C$42,G$21:G$42)) -> 0.052680055 | H72: =IF($C29=0,0,N(H29)/SUMPRODUCT($C$21:$C$42,H$21:H$42)) -> 0.050761026 | I72: =IF($C29=0,0,N(I29)/SUMPRODUCT($C$21:$C$42,I$21:I$42)) -> 0.051471376 | J72: =IF($C29=0,0,N(J29)/SUMPRODUCT($C$21:$C$42,J$21:J$42)) -> 0.046066209 | K72: =IF($C29=0,0,N(K29)/SUMPRODUCT($C$21:$C$42,K$21:K$42)) -> 0.047740412 | L72: =IF($C29=0,0,N(L29)/SUMPRODUCT($C$21:$C$42,L$21:L$42)) -> 0.059137577 | ... S72: =IF($C29=0,0,N(S29)/SUMPRODUCT($C$21:$C$42,S$21:S$42)) -> 0.048587555
A73: UKR | B73: EAA | E73: =IF($C30=0,0,N(E30)/SUMPRODUCT($C$21:$C$42,E$21:E$42)) -> 0.0033095554 | F73: =IF($C30=0,0,N(F30)/SUMPRODUCT($C$21:$C$42,F$21:F$42)) -> 0.0033713064 | G73: =IF($C30=0,0,N(G30)/SUMPRODUCT($C$21:$C$42,G$21:G$42)) -> 0.0037484898 | H73: =IF($C30=0,0,N(H30)/SUMPRODUCT($C$21:$C$42,H$21:H$42)) -> 0.0040136304 | I73: =IF($C30=0,0,N(I30)/SUMPRODUCT($C$21:$C$42,I$21:I$42)) -> 0.0046796549 | J73: =IF($C30=0,0,N(J30)/SUMPRODUCT($C$21:$C$42,J$21:J$42)) -> 0.0048387636 | K73: =IF($C30=0,0,N(K30)/SUMPRODUCT($C$21:$C$42,K$21:K$42)) -> 0.0052153275 | L73: =IF($C30=0,0,N(L30)/SUMPRODUCT($C$21:$C$42,L$21:L$42)) -> 0.0041893744 | ... S73: =IF($C30=0,0,N(S30)/SUMPRODUCT($C$21:$C$42,S$21:S$42)) -> 0.0069501525
A74: TUR | B74: EAA | E74: =IF($C31=0,0,N(E31)/SUMPRODUCT($C$21:$C$42,E$21:E$42)) -> 0.031458396 | F74: =IF($C31=0,0,N(F31)/SUMPRODUCT($C$21:$C$42,F$21:F$42)) -> 0.031447095 | G74: =IF($C31=0,0,N(G31)/SUMPRODUCT($C$21:$C$42,G$21:G$42)) -> 0.028878263 | H74: =IF($C31=0,0,N(H31)/SUMPRODUCT($C$21:$C$42,H$21:H$42)) -> 0.024165518 | I74: =IF($C31=0,0,N(I31)/SUMPRODUCT($C$21:$C$42,I$21:I$42)) -> 0.02355415 | J74: =IF($C31=0,0,N(J31)/SUMPRODUCT($C$21:$C$42,J$21:J$42)) -> 0.022630985 | K74: =IF($C31=0,0,N(K31)/SUMPRODUCT($C$21:$C$42,K$21:K$42)) -> 0.021899736 | L74: =IF($C31=0,0,N(L31)/SUMPRODUCT($C$21:$C$42,L$21:L$42)) -> 0.023888921 | ... S74: =IF($C31=0,0,N(S31)/SUMPRODUCT($C$21:$C$42,S$21:S$42)) -> 0.035101471
A75: KAZ | B75: EAA | E75: =IF($C32=0,0,N(E32)/SUMPRODUCT($C$21:$C$42,E$21:E$42)) -> 0.0067022135 | F75: =IF($C32=0,0,N(F32)/SUMPRODUCT($C$21:$C$42,F$21:F$42)) -> 0.0049616827 | G75: =IF($C32=0,0,N(G32)/SUMPRODUCT($C$21:$C$42,G$21:G$42)) -> 0.0055789824 | H75: =IF($C32=0,0,N(H32)/SUMPRODUCT($C$21:$C$42,H$21:H$42)) -> 0.0054986209 | I75: =IF($C32=0,0,N(I32)/SUMPRODUCT($C$21:$C$42,I$21:I$42)) -> 0.0055207773 | J75: =IF($C32=0,0,N(J32)/SUMPRODUCT($C$21:$C$42,J$21:J$42)) -> 0.005280423 | K75: =IF($C32=0,0,N(K32)/SUMPRODUCT($C$21:$C$42,K$21:K$42)) -> 0.0051446095 | L75: =IF($C32=0,0,N(L32)/SUMPRODUCT($C$21:$C$42,L$21:L$42)) -> 0.0058225833 | ... S75: =IF($C32=0,0,N(S32)/SUMPRODUCT($C$21:$C$42,S$21:S$42)) -> 0.0097265605
... A85: ITA | B85: EAA | E85: =IF($C42=0,0,N(E42)/SUMPRODUCT($C$21:$C$42,E$21:E$42)) -> 0.067175485 | F85: =IF($C42=0,0,N(F42)/SUMPRODUCT($C$21:$C$42,F$21:F$42)) -> 0.0684037 | G85: =IF($C42=0,0,N(G42)/SUMPRODUCT($C$21:$C$42,G$21:G$42)) -> 0.065557286 | H85: =IF($C42=0,0,N(H42)/SUMPRODUCT($C$21:$C$42,H$21:H$42)) -> 0.064131146 | I85: =IF($C42=0,0,N(I42)/SUMPRODUCT($C$21:$C$42,I$21:I$42)) -> 0.061371713 | J85: =IF($C42=0,0,N(J42)/SUMPRODUCT($C$21:$C$42,J$21:J$42)) -> 0.058817143 | K85: =IF($C42=0,0,N(K42)/SUMPRODUCT($C$21:$C$42,K$21:K$42)) -> 0.056859612 | L85: =IF($C42=0,0,N(L42)/SUMPRODUCT($C$21:$C$42,L$21:L$42)) -> 0.054237053 | ... S85: =IF($C42=0,0,N(S42)/SUMPRODUCT($C$21:$C$42,S$21:S$42)) -> 0.049264006
A87: Regional nominal GDP growth, local currency, constant FX [calc] = sum(weight x Data growth)
A88: region | E88: 2016 | F88: 2017 | G88: 2018 | H88: 2019 | I88: 2020 | J88: 2021 | K88: 2022 | L88: 2023 | M88: 2024 | N88: 2025 | O88: 2026 | P88: 2027 | Q88: 2028 | R88: 2029 | S88: 2030
A89: Mexico | E89: =E46*N(Data!J3) -> 0.079578295 | F89: =F46*N(Data!J4) -> 0.085622524 | G89: =G46*N(Data!J5) -> 0.072792186 | H89: =H46*N(Data!J6) -> 0.039093473 | I89: =I46*N(Data!J7) -> -0.041201633 | J89: =J46*N(Data!J8) -> 0.10807888 | K89: =K46*N(Data!J9) -> 0.10623742 | L89: =L46*N(Data!J10) -> 0.079442489 | M89: =M46*N(Data!J11) -> 0.053710432 | N89: =N46*N(Data!J12) -> 0.051177534 | O89: =O46*N(Data!J13) -> 0.061749627 | P89: =P46*N(Data!J14) -> 0.066943248 | Q89: =Q46*N(Data!J15) -> 0.060058894 | R89: =R46*N(Data!J16) -> 0.058036859 | S89: =S46*N(Data!J17) -> 0.04875605
A90: North America | E90: =E47*N(Data!J19)+E48*N(Data!J35) -> 0.027068538 | F90: =F47*N(Data!J20)+F48*N(Data!J36) -> 0.043965809 | G90: =G47*N(Data!J21)+G48*N(Data!J37) -> 0.052567902 | H90: =H47*N(Data!J22)+H48*N(Data!J38) -> 0.042159284 | I90: =I47*N(Data!J23)+I48*N(Data!J39) -> -0.010084831 | J90: =J47*N(Data!J24)+J48*N(Data!J40) -> 0.11313696 | K90: =K47*N(Data!J25)+K48*N(Data!J41) -> 0.099958057 | L90: =L47*N(Data!J26)+L48*N(Data!J42) -> 0.065243066 | M90: =M47*N(Data!J27)+M48*N(Data!J43) -> 0.05533475 | N90: =N47*N(Data!J28)+N48*N(Data!J44) -> 0.049923732 | O90: =O47*N(Data!J29)+O48*N(Data!J45) -> 0.059684724 | P90: =P47*N(Data!J30)+P48*N(Data!J46) -> 0.055091306 | Q90: =Q47*N(Data!J31)+Q48*N(Data!J47) -> 0.047520186 | R90: =R47*N(Data!J32)+R48*N(Data!J48) -> 0.041416551 | S90: =S47*N(Data!J33)+S48*N(Data!J49) -> 0.041255134
A91: Latin America | E91: =E49*N(Data!J51)+E50*N(Data!J67)+E51*N(Data!J83)+E52*N(Data!J99)+E53*N(Data!J115)+E54*N(Data!J131)+E55*N(Data!J147)+E56*N(Data!J163)+E57*N(Data!J179)+E58*N(Data!J195)+E59*N(Data!J211)+E60*N(Data!J227)+E61*N(Data!J243)+E62*N(Data!J259)+E63*N(Data!J275) -> 0.11222902 | F91: =F49*N(Data!J52)+F50*N(Data!J68)+F51*N(Data!J84)+F52*N(Data!J100)+F53*N(Data!J116)+F54*N(Data!J132)+F55*N(Data!J148)+F56*N(Data!J164)+F57*N(Data!J180)+F58*N(Data!J196)+F59*N(Data!J212)+F60*N(Data!J228)+F61*N(Data!J244)+F62*N(Data!J260)+F63*N(Data!J276) -> 0.094399986 | G91: =G49*N(Data!J53)+G50*N(Data!J69)+G51*N(Data!J85)+G52*N(Data!J101)+G53*N(Data!J117)+G54*N(Data!J133)+G55*N(Data!J149)+G56*N(Data!J165)+G57*N(Data!J181)+G58*N(Data!J197)+G59*N(Data!J213)+G60*N(Data!J229)+G61*N(Data!J245)+G62*N(Data!J261)+G63*N(Data!J277) -> 0.11365182 | H91: =H49*N(Data!J54)+H50*N(Data!J70)+H51*N(Data!J86)+H52*N(Data!J102)+H53*N(Data!J118)+H54*N(Data!J134)+H55*N(Data!J150)+H56*N(Data!J166)+H57*N(Data!J182)+H58*N(Data!J198)+H59*N(Data!J214)+H60*N(Data!J230)+H61*N(Data!J246)+H62*N(Data!J262)+H63*N(Data!J278) -> 0.10931789 | I91: =I49*N(Data!J55)+I50*N(Data!J71)+I51*N(Data!J87)+I52*N(Data!J103)+I53*N(Data!J119)+I54*N(Data!J135)+I55*N(Data!J151)+I56*N(Data!J167)+I57*N(Data!J183)+I58*N(Data!J199)+I59*N(Data!J215)+I60*N(Data!J231)+I61*N(Data!J247)+I62*N(Data!J263)+I63*N(Data!J279) -> 0.032761717 | J91: =J49*N(Data!J56)+J50*N(Data!J72)+J51*N(Data!J88)+J52*N(Data!J104)+J53*N(Data!J120)+J54*N(Data!J136)+J55*N(Data!J152)+J56*N(Data!J168)+J57*N(Data!J184)+J58*N(Data!J200)+J59*N(Data!J216)+J60*N(Data!J232)+J61*N(Data!J248)+J62*N(Data!J264)+J63*N(Data!J280) -> 0.24627446 | K91: =K49*N(Data!J57)+K50*N(Data!J73)+K51*N(Data!J89)+K52*N(Data!J105)+K53*N(Data!J121)+K54*N(Data!J137)+K55*N(Data!J153)+K56*N(Data!J169)+K57*N(Data!J185)+K58*N(Data!J201)+K59*N(Data!J217)+K60*N(Data!J233)+K61*N(Data!J249)+K62*N(Data!J265)+K63*N(Data!J281) -> 0.21518227 | L91: =L49*N(Data!J58)+L50*N(Data!J74)+L51*N(Data!J90)+L52*N(Data!J106)+L53*N(Data!J122)+L54*N(Data!J138)+L55*N(Data!J154)+L56*N(Data!J170)+L57*N(Data!J186)+L58*N(Data!J202)+L59*N(Data!J218)+L60*N(Data!J234)+L61*N(Data!J250)+L62*N(Data!J266)+L63*N(Data!J282) -> 0.27813004 | M91: =M49*N(Data!J59)+M50*N(Data!J75)+M51*N(Data!J91)+M52*N(Data!J107)+M53*N(Data!J123)+M54*N(Data!J139)+M55*N(Data!J155)+M56*N(Data!J171)+M57*N(Data!J187)+M58*N(Data!J203)+M59*N(Data!J219)+M60*N(Data!J235)+M61*N(Data!J251)+M62*N(Data!J267)+M63*N(Data!J283) -> 0.36284586 | N91: =N49*N(Data!J60)+N50*N(Data!J76)+N51*N(Data!J92)+N52*N(Data!J108)+N53*N(Data!J124)+N54*N(Data!J140)+N55*N(Data!J156)+N56*N(Data!J172)+N57*N(Data!J188)+N58*N(Data!J204)+N59*N(Data!J220)+N60*N(Data!J236)+N61*N(Data!J252)+N62*N(Data!J268)+N63*N(Data!J284) -> 0.13375524 | O91: =O49*N(Data!J61)+O50*N(Data!J77)+O51*N(Data!J93)+O52*N(Data!J109)+O53*N(Data!J125)+O54*N(Data!J141)+O55*N(Data!J157)+O56*N(Data!J173)+O57*N(Data!J189)+O58*N(Data!J205)+O59*N(Data!J221)+O60*N(Data!J237)+O61*N(Data!J253)+O62*N(Data!J269)+O63*N(Data!J285) -> 0.11194387 | P91: =P49*N(Data!J62)+P50*N(Data!J78)+P51*N(Data!J94)+P52*N(Data!J110)+P53*N(Data!J126)+P54*N(Data!J142)+P55*N(Data!J158)+P56*N(Data!J174)+P57*N(Data!J190)+P58*N(Data!J206)+P59*N(Data!J222)+P60*N(Data!J238)+P61*N(Data!J254)+P62*N(Data!J270)+P63*N(Data!J286) -> 0.079461259 | Q91: =Q49*N(Data!J63)+Q50*N(Data!J79)+Q51*N(Data!J95)+Q52*N(Data!J111)+Q53*N(Data!J127)+Q54*N(Data!J143)+Q55*N(Data!J159)+Q56*N(Data!J175)+Q57*N(Data!J191)+Q58*N(Data!J207)+Q59*N(Data!J223)+Q60*N(Data!J239)+Q61*N(Data!J255)+Q62*N(Data!J271)+Q63*N(Data!J287) -> 0.063324539 | R91: =R49*N(Data!J64)+R50*N(Data!J80)+R51*N(Data!J96)+R52*N(Data!J112)+R53*N(Data!J128)+R54*N(Data!J144)+R55*N(Data!J160)+R56*N(Data!J176)+R57*N(Data!J192)+R58*N(Data!J208)+R59*N(Data!J224)+R60*N(Data!J240)+R61*N(Data!J256)+R62*N(Data!J272)+R63*N(Data!J288) -> 0.066405112 | S91: =S49*N(Data!J65)+S50*N(Data!J81)+S51*N(Data!J97)+S52*N(Data!J113)+S53*N(Data!J129)+S54*N(Data!J145)+S55*N(Data!J161)+S56*N(Data!J177)+S57*N(Data!J193)+S58*N(Data!J209)+S59*N(Data!J225)+S60*N(Data!J241)+S61*N(Data!J257)+S62*N(Data!J273)+S63*N(Data!J289) -> 0.07055722
A92: EAA | E92: =E64*N(Data!J291)+E65*N(Data!J307)+E66*N(Data!J323)+E67*N(Data!J339)+E68*N(Data!J355)+E69*N(Data!J371)+E70*N(Data!J387)+E71*N(Data!J403)+E72*N(Data!J419)+E73*N(Data!J435)+E74*N(Data!J451)+E75*N(Data!J467)+E76*N(Data!J483)+E77*N(Data!J499)+E78*N(Data!J515)+E79*N(Data!J531)+E80*N(Data!J547)+E81*N(Data!J563)+E82*N(Data!J579)+E83*N(Data!J595)+E84*N(Data!J611)+E85*N(Data!J627) -> 0.063648699 | F92: =F64*N(Data!J292)+F65*N(Data!J308)+F66*N(Data!J324)+F67*N(Data!J340)+F68*N(Data!J356)+F69*N(Data!J372)+F70*N(Data!J388)+F71*N(Data!J404)+F72*N(Data!J420)+F73*N(Data!J436)+F74*N(Data!J452)+F75*N(Data!J468)+F76*N(Data!J484)+F77*N(Data!J500)+F78*N(Data!J516)+F79*N(Data!J532)+F80*N(Data!J548)+F81*N(Data!J564)+F82*N(Data!J580)+F83*N(Data!J596)+F84*N(Data!J612)+F85*N(Data!J628) -> 0.083690125 | G92: =G64*N(Data!J293)+G65*N(Data!J309)+G66*N(Data!J325)+G67*N(Data!J341)+G68*N(Data!J357)+G69*N(Data!J373)+G70*N(Data!J389)+G71*N(Data!J405)+G72*N(Data!J421)+G73*N(Data!J437)+G74*N(Data!J453)+G75*N(Data!J469)+G76*N(Data!J485)+G77*N(Data!J501)+G78*N(Data!J517)+G79*N(Data!J533)+G80*N(Data!J549)+G81*N(Data!J565)+G82*N(Data!J581)+G83*N(Data!J597)+G84*N(Data!J613)+G85*N(Data!J629) -> 0.082925759 | H92: =H64*N(Data!J294)+H65*N(Data!J310)+H66*N(Data!J326)+H67*N(Data!J342)+H68*N(Data!J358)+H69*N(Data!J374)+H70*N(Data!J390)+H71*N(Data!J406)+H72*N(Data!J422)+H73*N(Data!J438)+H74*N(Data!J454)+H75*N(Data!J470)+H76*N(Data!J486)+H77*N(Data!J502)+H78*N(Data!J518)+H79*N(Data!J534)+H80*N(Data!J550)+H81*N(Data!J566)+H82*N(Data!J582)+H83*N(Data!J598)+H84*N(Data!J614)+H85*N(Data!J630) -> 0.057108072 | I92: =I64*N(Data!J295)+I65*N(Data!J311)+I66*N(Data!J327)+I67*N(Data!J343)+I68*N(Data!J359)+I69*N(Data!J375)+I70*N(Data!J391)+I71*N(Data!J407)+I72*N(Data!J423)+I73*N(Data!J439)+I74*N(Data!J455)+I75*N(Data!J471)+I76*N(Data!J487)+I77*N(Data!J503)+I78*N(Data!J519)+I79*N(Data!J535)+I80*N(Data!J551)+I81*N(Data!J567)+I82*N(Data!J583)+I83*N(Data!J599)+I84*N(Data!J615)+I85*N(Data!J631) -> -0.0050848956 | J92: =J64*N(Data!J296)+J65*N(Data!J312)+J66*N(Data!J328)+J67*N(Data!J344)+J68*N(Data!J360)+J69*N(Data!J376)+J70*N(Data!J392)+J71*N(Data!J408)+J72*N(Data!J424)+J73*N(Data!J440)+J74*N(Data!J456)+J75*N(Data!J472)+J76*N(Data!J488)+J77*N(Data!J504)+J78*N(Data!J520)+J79*N(Data!J536)+J80*N(Data!J552)+J81*N(Data!J568)+J82*N(Data!J584)+J83*N(Data!J600)+J84*N(Data!J616)+J85*N(Data!J632) -> 0.13588649 | K92: =K64*N(Data!J297)+K65*N(Data!J313)+K66*N(Data!J329)+K67*N(Data!J345)+K68*N(Data!J361)+K69*N(Data!J377)+K70*N(Data!J393)+K71*N(Data!J409)+K72*N(Data!J425)+K73*N(Data!J441)+K74*N(Data!J457)+K75*N(Data!J473)+K76*N(Data!J489)+K77*N(Data!J505)+K78*N(Data!J521)+K79*N(Data!J537)+K80*N(Data!J553)+K81*N(Data!J569)+K82*N(Data!J585)+K83*N(Data!J601)+K84*N(Data!J617)+K85*N(Data!J633) -> 0.096617833 | L92: =L64*N(Data!J298)+L65*N(Data!J314)+L66*N(Data!J330)+L67*N(Data!J346)+L68*N(Data!J362)+L69*N(Data!J378)+L70*N(Data!J394)+L71*N(Data!J410)+L72*N(Data!J426)+L73*N(Data!J442)+L74*N(Data!J458)+L75*N(Data!J474)+L76*N(Data!J490)+L77*N(Data!J506)+L78*N(Data!J522)+L79*N(Data!J538)+L80*N(Data!J554)+L81*N(Data!J570)+L82*N(Data!J586)+L83*N(Data!J602)+L84*N(Data!J618)+L85*N(Data!J634) -> 0.08247867 | M92: =M64*N(Data!J299)+M65*N(Data!J315)+M66*N(Data!J331)+M67*N(Data!J347)+M68*N(Data!J363)+M69*N(Data!J379)+M70*N(Data!J395)+M71*N(Data!J411)+M72*N(Data!J427)+M73*N(Data!J443)+M74*N(Data!J459)+M75*N(Data!J475)+M76*N(Data!J491)+M77*N(Data!J507)+M78*N(Data!J523)+M79*N(Data!J539)+M80*N(Data!J555)+M81*N(Data!J571)+M82*N(Data!J587)+M83*N(Data!J603)+M84*N(Data!J619)+M85*N(Data!J635) -> 0.073942142 | N92: =N64*N(Data!J300)+N65*N(Data!J316)+N66*N(Data!J332)+N67*N(Data!J348)+N68*N(Data!J364)+N69*N(Data!J380)+N70*N(Data!J396)+N71*N(Data!J412)+N72*N(Data!J428)+N73*N(Data!J444)+N74*N(Data!J460)+N75*N(Data!J476)+N76*N(Data!J492)+N77*N(Data!J508)+N78*N(Data!J524)+N79*N(Data!J540)+N80*N(Data!J556)+N81*N(Data!J572)+N82*N(Data!J588)+N83*N(Data!J604)+N84*N(Data!J620)+N85*N(Data!J636) -> 0.058288851 | O92: =O64*N(Data!J301)+O65*N(Data!J317)+O66*N(Data!J333)+O67*N(Data!J349)+O68*N(Data!J365)+O69*N(Data!J381)+O70*N(Data!J397)+O71*N(Data!J413)+O72*N(Data!J429)+O73*N(Data!J445)+O74*N(Data!J461)+O75*N(Data!J477)+O76*N(Data!J493)+O77*N(Data!J509)+O78*N(Data!J525)+O79*N(Data!J541)+O80*N(Data!J557)+O81*N(Data!J573)+O82*N(Data!J589)+O83*N(Data!J605)+O84*N(Data!J621)+O85*N(Data!J637) -> 0.069925603 | P92: =P64*N(Data!J302)+P65*N(Data!J318)+P66*N(Data!J334)+P67*N(Data!J350)+P68*N(Data!J366)+P69*N(Data!J382)+P70*N(Data!J398)+P71*N(Data!J414)+P72*N(Data!J430)+P73*N(Data!J446)+P74*N(Data!J462)+P75*N(Data!J478)+P76*N(Data!J494)+P77*N(Data!J510)+P78*N(Data!J526)+P79*N(Data!J542)+P80*N(Data!J558)+P81*N(Data!J574)+P82*N(Data!J590)+P83*N(Data!J606)+P84*N(Data!J622)+P85*N(Data!J638) -> 0.062220476 | Q92: =Q64*N(Data!J303)+Q65*N(Data!J319)+Q66*N(Data!J335)+Q67*N(Data!J351)+Q68*N(Data!J367)+Q69*N(Data!J383)+Q70*N(Data!J399)+Q71*N(Data!J415)+Q72*N(Data!J431)+Q73*N(Data!J447)+Q74*N(Data!J463)+Q75*N(Data!J479)+Q76*N(Data!J495)+Q77*N(Data!J511)+Q78*N(Data!J527)+Q79*N(Data!J543)+Q80*N(Data!J559)+Q81*N(Data!J575)+Q82*N(Data!J591)+Q83*N(Data!J607)+Q84*N(Data!J623)+Q85*N(Data!J639) -> 0.059353494 | R92: =R64*N(Data!J304)+R65*N(Data!J320)+R66*N(Data!J336)+R67*N(Data!J352)+R68*N(Data!J368)+R69*N(Data!J384)+R70*N(Data!J400)+R71*N(Data!J416)+R72*N(Data!J432)+R73*N(Data!J448)+R74*N(Data!J464)+R75*N(Data!J480)+R76*N(Data!J496)+R77*N(Data!J512)+R78*N(Data!J528)+R79*N(Data!J544)+R80*N(Data!J560)+R81*N(Data!J576)+R82*N(Data!J592)+R83*N(Data!J608)+R84*N(Data!J624)+R85*N(Data!J640) -> 0.060524495 | S92: =S64*N(Data!J305)+S65*N(Data!J321)+S66*N(Data!J337)+S67*N(Data!J353)+S68*N(Data!J369)+S69*N(Data!J385)+S70*N(Data!J401)+S71*N(Data!J417)+S72*N(Data!J433)+S73*N(Data!J449)+S74*N(Data!J465)+S75*N(Data!J481)+S76*N(Data!J497)+S77*N(Data!J513)+S78*N(Data!J529)+S79*N(Data!J545)+S80*N(Data!J561)+S81*N(Data!J577)+S82*N(Data!J593)+S83*N(Data!J609)+S84*N(Data!J625)+S85*N(Data!J641) -> 0.059967662

Sheet Ratio_history
A1: Historical ratio = Bimbo ex-FX net sales growth / regional nominal GDP growth in local currency (Regional_agg) [calc]. Team picks the forward ratio; this is the evidence
A2: region | B2: Bimbo ex-FX 2023 [sourced] | C2: Bimbo ex-FX 2024 [sourced] | D2: Bimbo ex-FX 2025 [sourced] | E2: GDP 2023 [calc] | F2: GDP 2024 [calc] | G2: GDP 2025 [calc] | H2: ratio 2023 [calc] | I2: ratio 2024 [calc] | J2: ratio 2025 [calc] | K2: Bimbo CAGR 23-25 | L2: GDP CAGR 23-25 | M2: ratio of CAGRs [calc]
A3: Mexico | B3: 0.115 | C3: 0.04 | D3: 0.024 | E3: =Regional_agg!L89 -> 0.079442489 | F3: =Regional_agg!M89 -> 0.053710432 | G3: =Regional_agg!N89 -> 0.051177534 | H3: =IF(E3=0,"",B3/E3) -> 1.4475881 | I3: =IF(F3=0,"",C3/F3) -> 0.74473429 | J3: =IF(G3=0,"",D3/G3) -> 0.46895577 | K3: =((1+B3)*(1+C3)*(1+D3))^(1/3)-1 -> 0.058935207 | L3: =((1+E3)*(1+F3)*(1+G3))^(1/3)-1 -> 0.061367096 | M3: =IF(L3=0,"",K3/L3) -> 0.96037146
A4: North America | B4: 0.067 | C4: -0.046 | D4: -0.04 | E4: =Regional_agg!L90 -> 0.065243066 | F4: =Regional_agg!M90 -> 0.05533475 | G4: =Regional_agg!N90 -> 0.049923732 | H4: =IF(E4=0,"",B4/E4) -> 1.0269291 | I4: =IF(F4=0,"",C4/F4) -> -0.83130402 | J4: =IF(G4=0,"",D4/G4) -> -0.80122215 | K4: =((1+B4)*(1+C4)*(1+D4))^(1/3)-1 -> -0.0076580697 | L4: =((1+E4)*(1+F4)*(1+G4))^(1/3)-1 -> 0.056814838 | M4: =IF(L4=0,"",K4/L4) -> -0.13478996
A5: Latin America | B5: 0.169 | C5: 0.1 | D5: 0.101 | E5: =Regional_agg!L91 -> 0.27813004 | F5: =Regional_agg!M91 -> 0.36284586 | G5: =Regional_agg!N91 -> 0.13375524 | H5: =IF(E5=0,"",B5/E5) -> 0.60762943 | I5: =IF(F5=0,"",C5/F5) -> 0.27559912 | J5: =IF(G5=0,"",D5/G5) -> 0.75511063 | K5: =((1+B5)*(1+C5)*(1+D5))^(1/3)-1 -> 0.12287524 | L5: =((1+E5)*(1+F5)*(1+G5))^(1/3)-1 -> 0.2546243 | M5: =IF(L5=0,"",K5/L5) -> 0.48257467
A6: EAA | B6: 0.235 | C6: 0.079 | D6: 0.117 | E6: =Regional_agg!L92 -> 0.08247867 | F6: =Regional_agg!M92 -> 0.073942142 | G6: =Regional_agg!N92 -> 0.058288851 | H6: =IF(E6=0,"",B6/E6) -> 2.8492215 | I6: =IF(F6=0,"",C6/F6) -> 1.0684029 | J6: =IF(G6=0,"",D6/G6) -> 2.0072449 | K6: =((1+B6)*(1+C6)*(1+D6))^(1/3)-1 -> 0.14177499 | L6: =((1+E6)*(1+F6)*(1+G6))^(1/3)-1 -> 0.071522967 | M6: =IF(L6=0,"",K6/L6) -> 1.9822302
A8: Sources Bimbo: 4Q23 release p.2 (FY2023), 4Q24 release p.2 (FY2024), RA25 p.132 (FY2025), via wiki bimbo-income-statement-fy21-fy25 §3b.
A9: FY2021-FY2022: Bimbo gives no ex-FX growth by region in a table (4Q22 release p.4); FY2021 also restated for Ricolino. Not used.
A10: Ex-FX growth is NOT organic: it includes acquisitions (EAA and Latin America mainly; US sourdough in North America 2025). Bimbo does not quantify the split (S2).
A11: FY2023 North America and group growth is held down by the 53rd week in FY2022 (group 10.7% reported vs 11.4% without it, 4Q23 release p.1).
A12: Latin America and EAA GDP include ARG and TUR at local-currency (hyperinflation) growth, weighted by prior-year GDP in USD.

Sheet Ratio_NA
A1: North America ratio: 1Q26-3Q26 ex-FX net sales growth / US nominal GDP growth 2026 (team decision 2026-10-25)
A2: quarter | B2: net sales MXN m [sourced] | C2: prior-year quarter MXN m [sourced] | D2: growth in MXN [calc] | E2: ex-FX growth [sourced] | F2: source
A3: 1Q26 | B3: 40533 | C3: 46580 | D3: =B3/C3-1 -> -0.12981967 | E3: 0.007 | F3: 1T26 release p.3
A4: 2Q26 | B4: 44368 | C4: 49124 | D4: =B4/C4-1 -> -0.09681622 | E4: 0.013 | F4: 2T26 release p.3
A5: 3Q26 | B5: 44241 | C5: 47470 | D5: =B5/C5-1 -> -0.068021909 | E5: 0.01 | F5: 3T26 release p.3
A7: 9M26 ex-FX growth [calc] (quarters weighted by prior-year quarter sales, the constant-currency basis) | B7: =SUMPRODUCT(C3:C5,E3:E5)/SUM(C3:C5) -> 0.010053306
A8: US nominal GDP growth 2026, local currency [calc] (Data, USA 2026) | B8: =Data!J29 -> 0.059930094
A9: North America ratio [calc]; adopted by the team as the FY2027E-FY2030E ratio [assumption] | B9: =B7/B8 -> 0.16775054
A11: Implied North America ex-FX growth = ratio x US nominal GDP growth [calc]
B12: 2027 | C12: 2028 | D12: 2029 | E12: 2030
A13: US nominal GDP growth [calc] | B13: =Data!J30 -> 0.054360317 | C13: =Data!J31 -> 0.047543882 | D13: =Data!J32 -> 0.041819638 | E13: =Data!J33 -> 0.041287357
A14: North America ex-FX growth [calc] | B14: =$B$9*B13 -> 0.0091189727 | C14: =$B$9*C13 -> 0.0079755121 | D14: =$B$9*D13 -> 0.007015267 | E14: =$B$9*E13 -> 0.0069259765
A16: Why this base: North America ex-FX sales fell nine quarters in a row (4Q23-4Q25) and turned positive in 1Q26-3Q26; Bimbo cites US share gains and better price mix (1T26 p.3; 2T26 p.5). FY2023-FY2025 history (ratio -0.13) reflects the decline phase.
A17: Limits: three quarters only; 2Q26 helped by the football World Cup (2T26 p.5); 2026 laps a weak 2025 base; quarterly year-on-year growth is compared with a full-year 2026 GDP forecast (quarterly US GDP not in the data); Canada (about 7% of the region GDP weight) left out by choice.

Sheet Evidence_MEX
A1: Mexico: evidence for the ratio (team decides). Peso business, so growth in MXN = ex-FX growth
A2: A. Annual | B2: Bimbo Mexico growth | C2: Mexico nominal GDP growth [calc] | D2: ratio [calc] | E2: source
A3: 2022 | B3: =130401/109089-1 -> 0.19536342 | C3: =Data!J9 -> 0.10623742 | D3: =B3/C3 -> 1.8389322 | E3: [calc] segment sales FY22 130,401 (RA23 p.358) / FY21 restated 109,089 (RA22 p.313)
A4: 2023 | B4: 0.115 | C4: =Data!J10 -> 0.079442489 | D4: =B4/C4 -> 1.4475881 | E4: [sourced] 4Q23 release p.2
A5: 2024 | B5: 0.04 | C5: =Data!J11 -> 0.053710432 | D5: =B5/C5 -> 0.74473429 | E5: [sourced] 4Q24 release p.2
A6: 2025 | B6: 0.024 | C6: =Data!J12 -> 0.051177534 | D6: =B6/C6 -> 0.46895577 | E6: [sourced] RA25 p.132
A8: B. Quarterly, year on year
A9: quarter | B9: net sales MXN m [sourced] | C9: prior-year quarter [sourced] | D9: growth [calc] | E9: growth as published [sourced] | F9: source | G9: trailing 4Q growth [calc]
A10: 3Q23 | B10: 36375 | C10: 33562 | D10: =B10/C10-1 -> 0.083815029 | E10: 0.084 | F10: 3T23 p.3
A11: 4Q23 | B11: 36985 | C11: 34818 | D11: =B11/C11-1 -> 0.062237923 | E11: 0.062 | F11: 4T23 p.3
A12: 1Q24 | B12: 37386 | C12: 36244 | D12: =B12/C12-1 -> 0.031508664 | E12: 0.032 | F12: 1T24 p.3
A13: 2Q24 | B13: 37369 | C13: 35783 | D13: =B13/C13-1 -> 0.044322723 | E13: 0.044 | F13: 2T24 p.3 | G13: =SUM(B10:B13)/SUM(C10:C13)-1 -> 0.054897548
A14: 3Q24 | B14: 38793 | C14: 36375 | D14: =B14/C14-1 -> 0.066474227 | E14: 0.066 | F14: 3T24 p.3 | G14: =SUM(B11:B14)/SUM(C11:C14)-1 -> 0.051061304
A15: 4Q24 | B15: 37616 | C15: 36985 | D15: =B15/C15-1 -> 0.017060971 | E15: 0.017 | F15: 4T24 p.3 | G15: =SUM(B12:B15)/SUM(C12:C15)-1 -> 0.039735327
A16: 1Q25 | B16: 38018 | C16: 37386 | D16: =B16/C16-1 -> 0.016904724 | E16: 0.017 | F16: 1T25 p.3 | G16: =SUM(B13:B16)/SUM(C13:C16)-1 -> 0.035945103
A17: 2Q25 | B17: 38475 | C17: 37369 | D17: =B17/C17-1 -> 0.029596725 | E17: 0.03 | F17: 2T25 p.3 | G17: =SUM(B14:B17)/SUM(C14:C17)-1 -> 0.032319481
A18: 3Q25 | B18: 38897 | C18: 38793 | D18: =B18/C18-1 -> 0.002680896 | E18: 0.003 | F18: 3T25 p.3 | G18: =SUM(B15:B18)/SUM(C15:C18)-1 -> 0.016428291
A19: 4Q25 | B19: 39419 | C19: 37616 | D19: =B19/C19-1 -> 0.047931731 | E19: 0.048 | F19: 4T25 p.4 | G19: =SUM(B16:B19)/SUM(C16:C19)-1 -> 0.024112884
A20: 1Q26 | B20: 39726 | C20: 38018 | D20: =B20/C20-1 -> 0.044926088 | E20: 0.045 | F20: 1T26 p.3 | G20: =SUM(B17:B20)/SUM(C17:C20)-1 -> 0.031100951
A21: 2Q26 | B21: 40279 | C21: 38475 | D21: =B21/C21-1 -> 0.046887589 | E21: 0.047 | F21: 2T26 p.3 | G21: =SUM(B18:B21)/SUM(C18:C21)-1 -> 0.035441001
A22: 3Q26 | B22: 40905 | C22: 38897 | D22: =B22/C22-1 -> 0.051623519 | E22: 0.052 | F22: 3T26 p.3 | G22: =SUM(B19:B22)/SUM(C19:C22)-1 -> 0.047860868
A24: C. Candidate ratios (evidence only; team picks one or another with a written reason)
A25: candidate | B25: ratio | C25: 2027 | D25: 2028 | E25: 2029 | F25: 2030
A26: Mexico nominal GDP growth [calc] | C26: =Data!J14 -> 0.066943248 | D26: =Data!J15 -> 0.060058894 | E26: =Data!J16 -> 0.058036859 | F26: =Data!J17 -> 0.04875605
A27: 9M26 (1Q26-3Q26 growth / Mexico GDP 2026) | B27: =(SUM(B20:B22)/SUM(C20:C22)-1)/Data!J13 -> 0.77470537 | C27: =$B27*C$26 -> 0.051861294 | D27: =$B27*D$26 -> 0.046527948 | E27: =$B27*E$26 -> 0.044961467 | F27: =$B27*F$26 -> 0.037771574
A28: Trailing 4Q to 3Q26 / Mexico GDP 2026 | B28: =G22/Data!J13 -> 0.77507948 | C28: =$B28*C$26 -> 0.051886338 | D28: =$B28*D$26 -> 0.046550416 | E28: =$B28*E$26 -> 0.044983178 | F28: =$B28*F$26 -> 0.037789814
A29: Two-year 9M26 vs 9M24, annualised / GDP 2025-2026 annualised (strips the weak-2025 base) | B29: =((SUM(B20:B22)/SUM(B12:B14))^(1/2)-1)/(((1+Data!J12)*(1+Data!J13))^(1/2)-1) -> 0.56525629 | C29: =$B29*C$26 -> 0.037840092 | D29: =$B29*D$26 -> 0.033948668 | E29: =$B29*E$26 -> 0.0328057 | F29: =$B29*F$26 -> 0.027559664
A30: FY2025 / GDP 2025 | B30: =D6 -> 0.46895577 | C30: =$B30*C$26 -> 0.031393423 | D30: =$B30*D$26 -> 0.028164965 | E30: =$B30*E$26 -> 0.02721672 | F30: =$B30*F$26 -> 0.022864431
A31: FY2023-FY2025 compound (backward-looking) | B31: =(((1+B4)*(1+B5)*(1+B6))^(1/3)-1)/(((1+C4)*(1+C5)*(1+C6))^(1/3)-1) -> 0.96037146 | C31: =$B31*C$26 -> 0.064290385 | D31: =$B31*D$26 -> 0.057678847 | E31: =$B31*E$26 -> 0.055736943 | F31: =$B31*F$26 -> 0.046823919
A33: Bimbo on Mexico 2026: volume up and favourable mix, growth across categories and channels (1T26 p.4); mix and volume, partly helped by World Cup consumption (2T26 p.3); categories, channels, mix, positive volumes, execution, service and innovation (3T26 p.3) [sourced]. Volumes are not quantified.
A34: No acquisitions named in Mexico 2024-2026 (handoff, S2 block), so Mexico growth is close to organic [guidance, unverified].
A35: FY2022 is a high-inflation year and its base is restated for the Ricolino sale; shown for context.
A36: TEAM DECISION 2026-10-25: Mexico ratio = 9M26 candidate (same base as North America, for consistency) [assumption]. Compound and two-year candidates rejected by the team.

Sheet Ratios_9M26
A1: Ratios on one base for all regions: 1Q26-3Q26 ex-FX net sales growth / nominal GDP growth 2026 (team decision 2026-10-25, consistency pass)
A2: region | B2: quarter | C2: net sales MXN m [sourced] | D2: prior-year quarter [sourced] | E2: ex-FX growth [sourced] | F2: source
A3: Latin America | B3: 1Q26 | C3: 11545 | D3: 10902 | E3: 0.151 | F3: 1T26 p.3
A4: Latin America | B4: 2Q26 | C4: 11620 | D4: 10735 | E4: 0.141 | F4: 2T26 p.3
A5: Latin America | B5: 3Q26 | C5: 12047 | D5: 10714 | E5: 0.152 | F5: 3T26 p.3
A6: EAA | B6: 1Q26 | C6: 12631 | D6: 12042 | E6: 0.126 | F6: 1T26 p.3
A7: EAA | B7: 2Q26 | C7: 13188 | D7: 13436 | E7: 0.084 | F7: 2T26 p.3
A8: EAA | B8: 3Q26 | C8: 13371 | D8: 14370 | E8: 0.021 | F8: 3T26 p.3
A10: Summary
A11: region | B11: 9M26 ex-FX growth [calc] | C11: GDP growth 2026 [calc] | D11: GDP used | E11: ratio [calc] | F11: implied 2027 [calc] | G11: implied 2028 [calc] | H11: implied 2029 [calc] | I11: implied 2030 [calc]
A12: North America | B12: =Ratio_NA!B7 -> 0.010053306 | C12: =Ratio_NA!B8 -> 0.059930094 | D12: US only (team choice) | E12: =B12/C12 -> 0.16775054 | F12: =$E12*(Data!J30) -> 0.0091189727 | G12: =$E12*(Data!J31) -> 0.0079755121 | H12: =$E12*(Data!J32) -> 0.007015267 | I12: =$E12*(Data!J33) -> 0.0069259765
A13: Mexico | B13: =SUM(Evidence_MEX!B20:B22)/SUM(Evidence_MEX!C20:C22)-1 -> 0.047837768 | C13: =Data!J13 -> 0.061749627 | D13: Mexico | E13: =B13/C13 -> 0.77470537 | F13: =$E13*(Data!J14) -> 0.051861294 | G13: =$E13*(Data!J15) -> 0.046527948 | H13: =$E13*(Data!J16) -> 0.044961467 | I13: =$E13*(Data!J17) -> 0.037771574
A14: Latin America | B14: =SUMPRODUCT(D3:D5,E3:E5)/SUM(D3:D5) -> 0.14801289 | C14: =Regional_agg!O91 -> 0.11194387 | D14: regional aggregate, prior-year FX | E14: =B14/C14 -> 1.3222063 | F14: =$E14*(Regional_agg!P91) -> 0.10506417 | G14: =$E14*(Regional_agg!Q91) -> 0.083728102 | H14: =$E14*(Regional_agg!R91) -> 0.087801255 | I14: =$E14*(Regional_agg!S91) -> 0.093291199
A15: EAA | B15: =SUMPRODUCT(D6:D8,E6:E8)/SUM(D6:D8) -> 0.073973248 | C15: =Regional_agg!O92 -> 0.069925603 | D15: regional aggregate, prior-year FX | E15: =B15/C15 -> 1.057885 | F15: =$E15*(Regional_agg!P92) -> 0.06582211 | G15: =$E15*(Regional_agg!Q92) -> 0.062789172 | H15: =$E15*(Regional_agg!R92) -> 0.064027957 | I15: =$E15*(Regional_agg!S92) -> 0.063438892
A17: Not organic: 9M26 includes acquisitions whose sales Bimbo does not disclose: Stone House (North America, closed 2-Jun-2025, inorganic in 1Q26 and Apr-May 2026); Wickbold (Latin America, closed 6-Oct-2025, inorganic in all of 1Q26-3Q26, comparable from 4Q26); Don Don and Karamolegos (EAA, about Jun-2025, inorganic in 1Q26); Bonel (EAA, 7-Apr-2026, inorganic in 2Q26-3Q26) [sourced] wiki bimbo-acquisitions; releases 1T26 p.4, 2T26 p.4, 3T26 p.4.
A18: Prior-year quarters are the comparatives printed in the 2026 releases; some differ from the figures first reported in 2025 (e.g. Latin America 1Q25: 10,902 in 1T26 vs 11,176 in 1T25), so the 2026 releases are used for consistency with the published growth.
A19: EAA 2026 GDP uses real GDP growth + CPI for KAZ, KOR, MAR and UKR (H-02 fix: their stored 2026 level steps are likely series breaks); local-currency GDP includes hyperinflation for ARG (Latin America) and TUR (EAA) (see IAS29_test).
A20: Next (team plan): redo all four regions on Alan's organic-only rule and compare with this table.

Sheet Organic_pass
A1: Organic pass: acquisition points per quarter = 2026 ex-FX growth - same quarter 2025 [assumption: organic growth in the deal quarters = the 2025 pace]; flag 1 = deduct
A2: region | B2: quarter | C2: prior-year quarter sales | D2: reported ex-FX 2026 | E2: same quarter 2025 [sourced] | F2: before/after points [calc] | G2: deduct? (1/0) | H2: organic growth [calc]
A3: North America | B3: 1Q26 | C3: =Ratio_NA!C3 -> 46580 | D3: =Ratio_NA!E3 -> 0.007 | E3: -0.049 | F3: =D3-E3 -> 0.056 | G3: 0 | H3: =D3-G3*F3 -> 0.007
A4: North America | B4: 2Q26 | C4: =Ratio_NA!C4 -> 49124 | D4: =Ratio_NA!E4 -> 0.013 | E4: -0.046 | F4: =D4-E4 -> 0.059 | G4: 0 | H4: =D4-G4*F4 -> 0.013
A5: North America | B5: 3Q26 | C5: =Ratio_NA!C5 -> 47470 | D5: =Ratio_NA!E5 -> 0.01 | E5: -0.035 | F5: =D5-E5 -> 0.045 | G5: 0 | H5: =D5-G5*F5 -> 0.01
A6: Mexico | B6: 1Q26 | C6: =Evidence_MEX!C20 -> 38018 | D6: =Evidence_MEX!B20/Evidence_MEX!C20-1 -> 0.044926088 | E6: 0.017 | F6: =D6-E6 -> 0.027926088 | G6: 0 | H6: =D6-G6*F6 -> 0.044926088
A7: Mexico | B7: 2Q26 | C7: =Evidence_MEX!C21 -> 38475 | D7: =Evidence_MEX!B21/Evidence_MEX!C21-1 -> 0.046887589 | E7: 0.03 | F7: =D7-E7 -> 0.016887589 | G7: 0 | H7: =D7-G7*F7 -> 0.046887589
A8: Mexico | B8: 3Q26 | C8: =Evidence_MEX!C22 -> 38897 | D8: =Evidence_MEX!B22/Evidence_MEX!C22-1 -> 0.051623519 | E8: 0.003 | F8: =D8-E8 -> 0.048623519 | G8: 0 | H8: =D8-G8*F8 -> 0.051623519
A9: Latin America | B9: 1Q26 | C9: =Ratios_9M26!D3 -> 10902 | D9: =Ratios_9M26!E3 -> 0.151 | E9: 0.052 | F9: =D9-E9 -> 0.099 | G9: 1 | H9: =D9-G9*F9 -> 0.052
A10: Latin America | B10: 2Q26 | C10: =Ratios_9M26!D4 -> 10735 | D10: =Ratios_9M26!E4 -> 0.141 | E10: 0.082 | F10: =D10-E10 -> 0.059 | G10: 1 | H10: =D10-G10*F10 -> 0.082
A11: Latin America | B11: 3Q26 | C11: =Ratios_9M26!D5 -> 10714 | D11: =Ratios_9M26!E5 -> 0.152 | E11: 0.091 | F11: =D11-E11 -> 0.061 | G11: 1 | H11: =D11-G11*F11 -> 0.091
A12: EAA | B12: 1Q26 | C12: =Ratios_9M26!D6 -> 12042 | D12: =Ratios_9M26!E6 -> 0.126 | E12: 0.045 | F12: =D12-E12 -> 0.081 | G12: 1 | H12: =D12-G12*F12 -> 0.045
A13: EAA | B13: 2Q26 | C13: =Ratios_9M26!D7 -> 13436 | D13: =Ratios_9M26!E7 -> 0.084 | E13: 0.068 | F13: =D13-E13 -> 0.016 | G13: 1 | H13: =D13-G13*F13 -> 0.068
A14: EAA | B14: 3Q26 | C14: =Ratios_9M26!D8 -> 14370 | D14: =Ratios_9M26!E8 -> 0.021 | E14: 0.173 | F14: =D14-E14 -> -0.152 | G14: 0 | H14: =D14-G14*F14 -> 0.021
A16: region | B16: organic 9M26 [calc] | C16: GDP 2026 [calc] | D16: organic ratio [calc] | E16: consistency ratio (Ratios_9M26) | F16: implied 2027 [calc] | G16: implied 2028 [calc] | H16: implied 2029 [calc] | I16: implied 2030 [calc] | J16: why
A17: North America | B17: =SUMPRODUCT(C3:C5,H3:H5)/SUM(C3:C5) -> 0.010053306 | C17: =Ratios_9M26!C12 -> 0.059930094 | D17: =B17/C17 -> 0.16775054 | E17: =Ratios_9M26!E12 -> 0.16775054 | F17: =$D17*(Data!J30) -> 0.0091189727 | G17: =$D17*(Data!J31) -> 0.0079755121 | H17: =$D17*(Data!J32) -> 0.007015267 | I17: =$D17*(Data!J33) -> 0.0069259765 | J17: Stone House (2-Jun-2025) inorganic in 1Q26 and Apr-May 2026, size not disclosed. Not deducted: the before/after points (+5.6, +5.9) are the turnaround Bimbo attributes to share gains and price mix (1T26 p.3, 2T26 p.5), not the deal.
A18: Mexico | B18: =SUMPRODUCT(C6:C8,H6:H8)/SUM(C6:C8) -> 0.047837768 | C18: =Ratios_9M26!C13 -> 0.061749627 | D18: =B18/C18 -> 0.77470537 | E18: =Ratios_9M26!E13 -> 0.77470537 | F18: =$D18*(Data!J14) -> 0.051861294 | G18: =$D18*(Data!J15) -> 0.046527948 | H18: =$D18*(Data!J16) -> 0.044961467 | I18: =$D18*(Data!J17) -> 0.037771574 | J18: No acquisitions named; growth is organic.
A19: Latin America | B19: =SUMPRODUCT(C9:C11,H9:H11)/SUM(C9:C11) -> 0.074870885 | C19: =Ratios_9M26!C14 -> 0.11194387 | D19: =B19/C19 -> 0.66882522 | E19: =Ratios_9M26!E14 -> 1.3222063 | F19: =$D19*(Regional_agg!P91) -> 0.053145694 | G19: =$D19*(Regional_agg!Q91) -> 0.042353049 | H19: =$D19*(Regional_agg!R91) -> 0.044413413 | I19: =$D19*(Regional_agg!S91) -> 0.047190448 | J19: Wickbold (6-Oct-2025) inorganic in all of 1Q26-3Q26; 1Q25-3Q25 have no Wickbold. Deducted every quarter.
A20: EAA | B20: =SUMPRODUCT(C12:C14,H12:H14)/SUM(C12:C14) -> 0.044100281 | C20: =Ratios_9M26!C15 -> 0.069925603 | D20: =B20/C20 -> 0.63067431 | E20: =Ratios_9M26!E15 -> 1.057885 | F20: =$D20*(Regional_agg!P92) -> 0.039240856 | G20: =$D20*(Regional_agg!Q92) -> 0.037432723 | H20: =$D20*(Regional_agg!R92) -> 0.038171244 | I20: =$D20*(Regional_agg!S92) -> 0.037820064 | J20: Don Don, Karamolegos (~Jun-2025) inorganic in 1Q26 and Apr-May 2026; Bonel (7-Apr-2026) in 2Q26-3Q26. 3Q26 not deducted: its 2025 base (17.3%) already contains Don Don and Karamolegos, so the difference is negative and measures nothing.
A22: Limits: the method assumes nothing else changed between the two quarters; any organic acceleration (price, volume, Argentina) is counted as acquisition. 2025 quarters also carry older deals (Pagnifique Sep-2024 and La Zarcerena 1Q25 in Latin America), so the 2025 pace is not fully organic either.

Sheet Cross_check_history
A1: Long-history cross-check: Bimbo growth / nominal GDP growth per year. Reported growth incl. acquisitions; summary = median of valid years (not a compound rate)
A2: A. FY2022 from quarters [calc] | B2: prior 1Q21 | C2: g 1Q22 | D2: prior 2Q21 | E2: g 2Q22 | F2: prior 3Q21 | G2: g 3Q22 | H2: prior 4Q21 | I2: g 4Q22 | J2: FY2022 [calc]
A3: North America | B3: 38963 | C3: 0.158 | D3: 42538 | E3: 0.168 | F3: 44028 | G3: 0.19 | H3: 50050 | I3: 0.219 | J3: =(B3*C3+D3*E3+F3*G3+H3*I3)/(B3+D3+F3+H3) -> 0.18583548
A4: Mexico | B4: 27661 | C4: 0.195 | D4: 26119 | E4: 0.216 | F4: 27867 | G4: 0.204 | H4: 29653 | I4: 0.174 | J4: =(B4*C4+D4*E4+F4*G4+H4*I4)/(B4+D4+F4+H4) -> 0.1965866
A5: Latin America | B5: 7374 | C5: 0.251 | D5: 7369 | E5: 0.377 | F5: 7830 | G5: 0.392 | H5: 8603 | I5: 0.334 | J5: =(B5*C5+D5*E5+F5*G5+H5*I5)/(B5+D5+F5+H5) -> 0.33909895
A6: EAA | B6: 7843 | C6: 0.211 | D6: 8289 | E6: 0.174 | F6: 8680 | G6: 0.233 | H6: 9384 | I6: 0.242 | J6: =(B6*C6+D6*E6+F6*G6+H6*I6)/(B6+D6+F6+H6) -> 0.21612256
A7: Sources: prior-year quarters 1T22 p.3, 2T22 p.3, 3T22 p.3, 4T22 p.5; growth: North America in US dollars through 2Q23, others ex-FX (narrative). 4Q22 North America includes a 53rd week.
A9: B. North America sales in USD m [calc] = segment sales MXN m [sourced] / MXN per USD average (FX)
A10: year | B10: 2015 | C10: 2016 | D10: 2017 | E10: 2018 | F10: 2019 | G10: 2020 | H10: 2021
A11: segment sales MXN m | B11: 116399 | C11: 135219 | D11: 137662 | E11: 143968 | F11: 144005 | G11: 176395 | H11: 176275
A12: MXN per USD | B12: =FX!B20 -> 15.881 | C12: =FX!C20 -> 18.689 | D12: =FX!D20 -> 18.907 | E12: =FX!E20 -> 19.237 | F12: =FX!F20 -> 19.257 | G12: =FX!G20 -> 21.498 | H12: =FX!H20 -> 20.282
A13: sales USD m | B13: =B11/B12 -> 7329.4503 | C13: =C11/C12 -> 7235.2186 | D13: =D11/D12 -> 7281.007 | E13: =E11/E12 -> 7483.9112 | F13: =F11/F12 -> 7478.0599 | G13: =G11/G12 -> 8205.1819 | H13: =H11/H12 -> 8691.204
A14: growth in USD | C14: =C13/B13-1 -> -0.012856586 | D14: =D13/C13-1 -> 0.006328552 | E14: =E13/D13-1 -> 0.027867598 | F14: =F13/E13-1 -> -0.00078184873 | G14: =G13/F13-1 -> 0.097234036 | H14: =H13/G13-1 -> 0.059233562
A15: Segment sales: RA18 p.373 (FY15-FY17, recast), RA20 p.286-287 (FY18-FY20; FY18 reclassified, overstates FY18 growth ~0.5 pt), RA21 p.304 (FY21 as first reported, same pre-Ricolino basis as FY20), via wiki bimbo-income-statement-fy14-fy20 and -fy21-fy25. Canada is translated through USD too.
A17: C. Yearly ratios. Bimbo growth: Mexico in pesos (= ex-FX), North America in USD, Latin America and EAA ex-FX
A18: row | B18: 2016 | C18: 2017 | D18: 2018 | E18: 2019 | F18: 2020 | G18: 2021 | H18: 2022 | I18: 2023 | J18: 2024 | K18: 2025 | M18: median of valid years [calc] | N18: valid years | O18: 9M26 organic ratio (Organic_pass)
A19: North America: Bimbo growth | B19: =C14 -> -0.012856586 | C19: =D14 -> 0.006328552 | D19: =E14 -> 0.027867598 | E19: =F14 -> -0.00078184873 | F19: =G14 -> 0.097234036 | G19: =H14 -> 0.059233562 | H19: =J3 -> 0.18583548 | I19: 0.067 | J19: -0.046 | K19: -0.04
A20: North America: GDP growth | B20: =Data!J19 -> 0.027870426 | C20: =Data!J20 -> 0.042924428 | D20: =Data!J21 -> 0.053253859 | E20: =Data!J22 -> 0.042769063 | F20: =Data!J23 -> -0.0076462467 | G20: =Data!J24 -> 0.11090241 | H20: =Data!J25 -> 0.097442711 | I20: =Data!J26 -> 0.067774354 | J20: =Data!J27 -> 0.055886802 | K20: =Data!J28 -> 0.050382918
A21: North America: ratio | B21: =IF(B20<=0,"n/a",B19/B20) -> -0.46129852 | C21: =IF(C20<=0,"n/a",C19/C20) -> 0.14743474 | D21: =IF(D20<=0,"n/a",D19/D20) -> 0.52329726 | E21: =IF(E20<=0,"n/a",E19/E20) -> -0.018280708 | F21: =IF(F20<=0,"n/a",F19/F20) -> n/a | G21: =IF(G20<=0,"n/a",G19/G20) -> 0.53410528 | H21: =IF(H20<=0,"n/a",H19/H20) -> 1.9071255 | I21: =IF(I20<=0,"n/a",I19/I20) -> 0.98857453 | ... K21: =IF(K20<=0,"n/a",K19/K20) -> -0.79391988 | M21: =MEDIAN(B21:K21) -> 0.14743474 | N21: =COUNT(B21:K21) -> 9 | O21: =Organic_pass!D17 -> 0.16775054
A23: Mexico: Bimbo growth | B23: =81455/75597-1 -> 0.077489847 | C23: =90367/81455-1 -> 0.1094101 | D23: 0.105 | E23: =102688/100327-1 -> 0.023533047 | F23: =104593/102688-1 -> 0.01855134 | G23: =118661/104593-1 -> 0.13450231 | H23: =J4 -> 0.1965866 | I23: 0.115 | J23: 0.04 | K23: 0.024
A24: Mexico: GDP growth | B24: =Data!J3 -> 0.079578295 | C24: =Data!J4 -> 0.085622524 | D24: =Data!J5 -> 0.072792186 | E24: =Data!J6 -> 0.039093473 | F24: =Data!J7 -> -0.041201633 | G24: =Data!J8 -> 0.10807888 | H24: =Data!J9 -> 0.10623742 | I24: =Data!J10 -> 0.079442489 | J24: =Data!J11 -> 0.053710432 | K24: =Data!J12 -> 0.051177534
A25: Mexico: ratio | B25: =IF(B24<=0,"n/a",B23/B24) -> 0.97375607 | C25: =IF(C24<=0,"n/a",C23/C24) -> 1.2778192 | D25: =IF(D24<=0,"n/a",D23/D24) -> 1.4424625 | E25: =IF(E24<=0,"n/a",E23/E24) -> 0.60196869 | F25: =IF(F24<=0,"n/a",F23/F24) -> n/a | G25: =IF(G24<=0,"n/a",G23/G24) -> 1.2444828 | H25: =IF(H24<=0,"n/a",H23/H24) -> 1.8504459 | I25: =IF(I24<=0,"n/a",I23/I24) -> 1.4475881 | ... K25: =IF(K24<=0,"n/a",K23/K24) -> 0.46895577 | M25: =MEDIAN(B25:K25) -> 1.2444828 | N25: =COUNT(B25:K25) -> 9 | O25: =Organic_pass!D18 -> 0.77470537
A27: Latin America: Bimbo growth | H27: =J5 -> 0.33909895 | I27: 0.169 | J27: 0.1 | K27: 0.101
A28: Latin America: GDP growth | H28: =Regional_agg!K91 -> 0.21518227 | I28: =Regional_agg!L91 -> 0.27813004 | J28: =Regional_agg!M91 -> 0.36284586 | K28: =Regional_agg!N91 -> 0.13375524
A29: Latin America: ratio | H29: =IF(H28<=0,"n/a",H27/H28) -> 1.5758684 | I29: =IF(I28<=0,"n/a",I27/I28) -> 0.60762943 | J29: =IF(J28<=0,"n/a",J27/J28) -> 0.27559912 | K29: =IF(K28<=0,"n/a",K27/K28) -> 0.75511063 | M29: =MEDIAN(B29:K29) -> 0.68137003 | N29: =COUNT(B29:K29) -> 4 | O29: =Organic_pass!D19 -> 0.66882522
A31: EAA: Bimbo growth | H31: =J6 -> 0.21612256 | I31: 0.235 | J31: 0.079 | K31: 0.117
A32: EAA: GDP growth | H32: =Regional_agg!K92 -> 0.096617833 | I32: =Regional_agg!L92 -> 0.08247867 | J32: =Regional_agg!M92 -> 0.073942142 | K32: =Regional_agg!N92 -> 0.058288851
A33: EAA: ratio | H33: =IF(H32<=0,"n/a",H31/H32) -> 2.2368806 | I33: =IF(I32<=0,"n/a",I31/I32) -> 2.8492215 | J33: =IF(J32<=0,"n/a",J31/J32) -> 1.0684029 | K33: =IF(K32<=0,"n/a",K31/K32) -> 2.0072449 | M33: =MEDIAN(B33:K33) -> 2.1220628 | N33: =COUNT(B33:K33) -> 4 | O33: =Organic_pass!D20 -> 0.63067431
A36: Mexico growth sources: FY16-FY17 segment sales (RA18 p.373); FY18 company-reported +10.5% (4T18 p.3); FY19-FY20 RA20 p.286-287; FY21 RA21 p.304 vs FY20 (both include Ricolino); FY22 from quarters (Ricolino excluded); FY23-FY25 4Q23 p.2, 4Q24 p.2, RA25 p.132.
A37: Breaks to keep in mind: Ricolino (confectionery) inside Mexico until FY21, outside from FY22; China moved from Mexico to EAA in 2017 (FY15-FY17 recast); 53rd week in North America in FY15 and FY22; COVID 2020-2021; acquisitions throughout (e.g. Canada Bread 2014, Saputo Bakery 2015, East Balt/Bimbo QSR Oct-2017 in North America).
A38: Latin America and EAA before FY2022: no ex-FX growth by region in the 4Q14-4Q21 releases or the FY2018/FY2020 BMV annual reports (searched 2026-10-25); only scattered quarter remarks (e.g. EAA 4Q19 local currency +2%, 4T19 p.4). Not usable as a series.

Sheet Regional_FX
A1: Regional FX, local currency to USD [calc]: FX ratio = local currency per USD t-1 / t (above 1 = the currency gains vs USD); region factor = sum(weight x (1 + GDP growth) x FX ratio) / sum(weight x (1 + GDP growth)), weights and growth as in Regional_agg
A2: iso3 | B2: region | C2: currency | D2: FX ratio 2027 | E2: FX ratio 2028 | F2: FX ratio 2029 | G2: FX ratio 2030
A3: MEX | B3: Mexico | C3: MXN | D3: =IFERROR(FX!M20/FX!N20,0) -> 0.96320703 | E3: =IFERROR(FX!N20/FX!O20,0) -> 0.97536154 | F3: =IFERROR(FX!O20/FX!P20,0) -> 0.9810825 | G3: =IFERROR(FX!P20/FX!Q20,0) -> 0.98908524
A4: USA | B4: North America | C4: USD | D4: =IFERROR(FX!M30/FX!N30,0) -> 1 | E4: =IFERROR(FX!N30/FX!O30,0) -> 1 | F4: =IFERROR(FX!O30/FX!P30,0) -> 1 | G4: =IFERROR(FX!P30/FX!Q30,0) -> 1
A5: CAN | B5: North America | C5: CAD | D5: =IFERROR(FX!M5/FX!N5,0) -> 1.0220588 | E5: =IFERROR(FX!N5/FX!O5,0) -> 1.0225564 | F5: =IFERROR(FX!O5/FX!P5,0) -> 1.0310078 | G5: =IFERROR(FX!P5/FX!Q5,0) -> 1.0238095
A6: ARG | B6: Latin America | C6: ARS | D6: =IFERROR(FX!M3/FX!N3,0) -> 0.86828371 | E6: =IFERROR(FX!N3/FX!O3,0) -> 0.91600987 | F6: =IFERROR(FX!O3/FX!P3,0) -> 0.97052008 | G6: =IFERROR(FX!P3/FX!Q3,0) -> 0.96609989
A7: BRA | B7: Latin America | C7: BRL | D7: =IFERROR(FX!M4/FX!N4,0) -> 0.99227799 | E7: =IFERROR(FX!N4/FX!O4,0) -> 0.97735849 | F7: =IFERROR(FX!O4/FX!P4,0) -> 0.97785978 | G7: =IFERROR(FX!P4/FX!Q4,0) -> 0.97833935
A8: CHL | B8: Latin America | C8: CLP | D8: =IFERROR(FX!M7/FX!N7,0) -> 0.98411676 | E8: =IFERROR(FX!N7/FX!O7,0) -> 1.0333241 | F8: =IFERROR(FX!O7/FX!P7,0) -> 0.9944858 | G8: =IFERROR(FX!P7/FX!Q7,0) -> 0.99128695
A9: COL | B9: Latin America | C9: COP | D9: =IFERROR(FX!M9/FX!N9,0) -> 1.0113171 | E9: =IFERROR(FX!N9/FX!O9,0) -> 0.94207658 | F9: =IFERROR(FX!O9/FX!P9,0) -> 0.98434022 | G9: =IFERROR(FX!P9/FX!Q9,0) -> 1.00021
A10: CRI | B10: Latin America | C10: CRC | D10: =IFERROR(FX!M10/FX!N10,0) -> 0.98753144 | E10: =IFERROR(FX!N10/FX!O10,0) -> 0.97536274 | F10: =IFERROR(FX!O10/FX!P10,0) -> 0.97996589 | G10: =IFERROR(FX!P10/FX!Q10,0) -> 0.97320375
A11: ECU | B11: Latin America | C11: USD | D11: =IFERROR(FX!M30/FX!N30,0) -> 1 | E11: =IFERROR(FX!N30/FX!O30,0) -> 1 | F11: =IFERROR(FX!O30/FX!P30,0) -> 1 | G11: =IFERROR(FX!P30/FX!Q30,0) -> 1
A12: SLV | B12: Latin America | C12: USD | D12: =IFERROR(FX!M30/FX!N30,0) -> 1 | E12: =IFERROR(FX!N30/FX!O30,0) -> 1 | F12: =IFERROR(FX!O30/FX!P30,0) -> 1 | G12: =IFERROR(FX!P30/FX!Q30,0) -> 1
A13: GTM | B13: Latin America | C13: GTQ | D13: =IFERROR(FX!M13/FX!N13,0) -> 0.99092088 | E13: =IFERROR(FX!N13/FX!O13,0) -> 0.9935567 | F13: =IFERROR(FX!O13/FX!P13,0) -> 0.99106003 | G13: =IFERROR(FX!P13/FX!Q13,0) -> 0.99113924
A14: HND | B14: Latin America | C14: HNL | D14: =IFERROR(FX!M14/FX!N14,0) -> 0.97560087 | E14: =IFERROR(FX!N14/FX!O14,0) -> 0.97618201 | F14: =IFERROR(FX!O14/FX!P14,0) -> 0.97639708 | G14: =IFERROR(FX!P14/FX!Q14,0) -> 0.97627923
A15: NIC | B15: Latin America | C15: NIO | D15: =IFERROR(FX!M21/FX!N21,0) -> 0.99863649 | E15: =IFERROR(FX!N21/FX!O21,0) -> 0.95172593 | F15: =IFERROR(FX!O21/FX!P21,0) -> 0.95917351 | G15: =IFERROR(FX!P21/FX!Q21,0) -> 0.95894008
A16: PAN | B16: Latin America | C16: USD | D16: =IFERROR(FX!M30/FX!N30,0) -> 1 | E16: =IFERROR(FX!N30/FX!O30,0) -> 1 | F16: =IFERROR(FX!O30/FX!P30,0) -> 1 | G16: =IFERROR(FX!P30/FX!Q30,0) -> 1
A17: PRY | B17: Latin America | C17: PYG | D17: =IFERROR(FX!M23/FX!N23,0) -> 1.0270143 | E17: =IFERROR(FX!N23/FX!O23,0) -> 0.95955197 | F17: =IFERROR(FX!O23/FX!P23,0) -> 0.96564675 | G17: =IFERROR(FX!P23/FX!Q23,0) -> 0.96782413
A18: PER | B18: Latin America | C18: PEN | D18: =IFERROR(FX!M22/FX!N22,0) -> 0.99707602 | E18: =IFERROR(FX!N22/FX!O22,0) -> 0.99418605 | F18: =IFERROR(FX!O22/FX!P22,0) -> 0.99710145 | G18: =IFERROR(FX!P22/FX!Q22,0) -> 1
A19: URY | B19: Latin America | C19: UYU | D19: =IFERROR(FX!M31/FX!N31,0) -> 0.94041755 | E19: =IFERROR(FX!N31/FX!O31,0) -> 0.96273713 | F19: =IFERROR(FX!O31/FX!P31,0) -> 0.96639022 | G19: =IFERROR(FX!P31/FX!Q31,0) -> 0.9689152
A20: VEN | B20: Latin America | C20: VES | D20: =IFERROR(FX!M32/FX!N32,0) -> 0 | E20: =IFERROR(FX!N32/FX!O32,0) -> 0 | F20: =IFERROR(FX!O32/FX!P32,0) -> 0 | G20: =IFERROR(FX!P32/FX!Q32,0) -> 0
A21: GBR | B21: EAA | C21: GBP | D21: =IFERROR(FX!M12/FX!N12,0) -> 1 | E21: =IFERROR(FX!N12/FX!O12,0) -> 1 | F21: =IFERROR(FX!O12/FX!P12,0) -> 1 | G21: =IFERROR(FX!P12/FX!Q12,0) -> 1
A22: CHE | B22: EAA | C22: CHF | D22: =IFERROR(FX!M6/FX!N6,0) -> 0.98765432 | E22: =IFERROR(FX!N6/FX!O6,0) -> 1 | F22: =IFERROR(FX!O6/FX!P6,0) -> 1.0125 | G22: =IFERROR(FX!P6/FX!Q6,0) -> 1.0126582
A23: ROU | B23: EAA | C23: RON | D23: =IFERROR(FX!M24/FX!N24,0) -> 0.95157895 | E23: =IFERROR(FX!N24/FX!O24,0) -> 1.0042283 | F23: =IFERROR(FX!O24/FX!P24,0) -> 1.0327511 | G23: =IFERROR(FX!P24/FX!Q24,0) -> 1.0200445
A24: SRB | B24: EAA | C24: RSD | D24: =IFERROR(FX!M25/FX!N25,0) -> 0.9979576 | E24: =IFERROR(FX!N25/FX!O25,0) -> 1.0213569 | F24: =IFERROR(FX!O25/FX!P25,0) -> 1.007506 | G24: =IFERROR(FX!P25/FX!Q25,0) -> 1.0024077
A25: SVN | B25: EAA | C25: EUR | D25: =IFERROR(FX!M11/FX!N11,0) -> 0.97752809 | E25: =IFERROR(FX!N11/FX!O11,0) -> 1 | F25: =IFERROR(FX!O11/FX!P11,0) -> 1.0348837 | G25: =IFERROR(FX!P11/FX!Q11,0) -> 1.0238095
A26: HRV | B26: EAA | C26: EUR | D26: =IFERROR(FX!M11/FX!N11,0) -> 0.97752809 | E26: =IFERROR(FX!N11/FX!O11,0) -> 1 | F26: =IFERROR(FX!O11/FX!P11,0) -> 1.0348837 | G26: =IFERROR(FX!P11/FX!Q11,0) -> 1.0238095
A27: MNE | B27: EAA | C27: EUR | D27: =IFERROR(FX!M11/FX!N11,0) -> 0.97752809 | E27: =IFERROR(FX!N11/FX!O11,0) -> 1 | F27: =IFERROR(FX!O11/FX!P11,0) -> 1.0348837 | G27: =IFERROR(FX!P11/FX!Q11,0) -> 1.0238095
A28: MKD | B28: EAA | C28: MKD | D28: =IFERROR(FX!M19/FX!N19,0) -> 0 | E28: =IFERROR(FX!N19/FX!O19,0) -> 0 | F28: =IFERROR(FX!O19/FX!P19,0) -> 0 | G28: =IFERROR(FX!P19/FX!Q19,0) -> 0
A29: RUS | B29: EAA | C29: RUB | D29: =IFERROR(FX!M26/FX!N26,0) -> 0.91285975 | E29: =IFERROR(FX!N26/FX!O26,0) -> 0.91322486 | F29: =IFERROR(FX!O26/FX!P26,0) -> 0.95241879 | G29: =IFERROR(FX!P26/FX!Q26,0) -> 1.0021901
A30: UKR | B30: EAA | C30: UAH | D30: =IFERROR(FX!M29/FX!N29,0) -> 0.95059076 | E30: =IFERROR(FX!N29/FX!O29,0) -> 0.99084717 | F30: =IFERROR(FX!O29/FX!P29,0) -> 1.0118458 | G30: =IFERROR(FX!P29/FX!Q29,0) -> 1.057631
A31: TUR | B31: EAA | C31: TRY | D31: =IFERROR(FX!M28/FX!N28,0) -> 0.85245304 | E31: =IFERROR(FX!N28/FX!O28,0) -> 0.90538309 | F31: =IFERROR(FX!O28/FX!P28,0) -> 0.93891473 | G31: =IFERROR(FX!P28/FX!Q28,0) -> 0.93886463
A32: KAZ | B32: EAA | C32: KZT | D32: =IFERROR(FX!M17/FX!N17,0) -> 0.97858811 | E32: =IFERROR(FX!N17/FX!O17,0) -> 0.94071038 | F32: =IFERROR(FX!O17/FX!P17,0) -> 0.99741779 | G32: =IFERROR(FX!P17/FX!Q17,0) -> 0.99536577
A33: CHN | B33: EAA | C33: CNY | D33: =IFERROR(FX!M8/FX!N8,0) -> 1.0195195 | E33: =IFERROR(FX!N8/FX!O8,0) -> 1.0060423 | F33: =IFERROR(FX!O8/FX!P8,0) -> 1.0045524 | G33: =IFERROR(FX!P8/FX!Q8,0) -> 1
A34: IND | B34: EAA | C34: INR | D34: =IFERROR(FX!M15/FX!N15,0) -> 0.97084189 | E34: =IFERROR(FX!N15/FX!O15,0) -> 1.0059905 | F34: =IFERROR(FX!O15/FX!P15,0) -> 0.99241492 | G34: =IFERROR(FX!P15/FX!Q15,0) -> 0.98406294
A35: KOR | B35: EAA | C35: KRW | D35: =IFERROR(FX!M16/FX!N16,0) -> 1.052522 | E35: =IFERROR(FX!N16/FX!O16,0) -> 1.0092802 | F35: =IFERROR(FX!O16/FX!P16,0) -> 1.0159925 | G35: =IFERROR(FX!P16/FX!Q16,0) -> 1.0093957
A36: ZAF | B36: EAA | C36: ZAR | D36: =IFERROR(FX!M33/FX!N33,0) -> 0.98675497 | E36: =IFERROR(FX!N33/FX!O33,0) -> 0.99045915 | F36: =IFERROR(FX!O33/FX!P33,0) -> 0.98357771 | G36: =IFERROR(FX!P33/FX!Q33,0) -> 0.98157743
A37: MAR | B37: EAA | C37: MAD | D37: =IFERROR(FX!M18/FX!N18,0) -> 0.96881497 | E37: =IFERROR(FX!N18/FX!O18,0) -> 0.98666667 | F37: =IFERROR(FX!O18/FX!P18,0) -> 1.0103627 | G37: =IFERROR(FX!P18/FX!Q18,0) -> 0.99587203
A38: TUN | B38: EAA | C38: TND | D38: =IFERROR(FX!M27/FX!N27,0) -> 0.93650794 | E38: =IFERROR(FX!N27/FX!O27,0) -> 0.95744681 | F38: =IFERROR(FX!O27/FX!P27,0) -> 0.97337278 | G38: =IFERROR(FX!P27/FX!Q27,0) -> 0.97971014
A39: ESP | B39: EAA | C39: EUR | D39: =IFERROR(FX!M11/FX!N11,0) -> 0.97752809 | E39: =IFERROR(FX!N11/FX!O11,0) -> 1 | F39: =IFERROR(FX!O11/FX!P11,0) -> 1.0348837 | G39: =IFERROR(FX!P11/FX!Q11,0) -> 1.0238095
A40: PRT | B40: EAA | C40: EUR | D40: =IFERROR(FX!M11/FX!N11,0) -> 0.97752809 | E40: =IFERROR(FX!N11/FX!O11,0) -> 1 | F40: =IFERROR(FX!O11/FX!P11,0) -> 1.0348837 | G40: =IFERROR(FX!P11/FX!Q11,0) -> 1.0238095
A41: FRA | B41: EAA | C41: EUR | D41: =IFERROR(FX!M11/FX!N11,0) -> 0.97752809 | E41: =IFERROR(FX!N11/FX!O11,0) -> 1 | F41: =IFERROR(FX!O11/FX!P11,0) -> 1.0348837 | G41: =IFERROR(FX!P11/FX!Q11,0) -> 1.0238095
A42: ITA | B42: EAA | C42: EUR | D42: =IFERROR(FX!M11/FX!N11,0) -> 0.97752809 | E42: =IFERROR(FX!N11/FX!O11,0) -> 1 | F42: =IFERROR(FX!O11/FX!P11,0) -> 1.0348837 | G42: =IFERROR(FX!P11/FX!Q11,0) -> 1.0238095
A44: Region factor, local currency to USD [calc] (Mexico = 1: peso business; North America = USA only, the team choice for GDP, so 1)
A45: region | D45: 2027 | E45: 2028 | F45: 2029 | G45: 2030
A46: Mexico | D46: 1 | E46: 1 | F46: 1 | G46: 1
A47: North America | D47: 1 | E47: 1 | F47: 1 | G47: 1
A48: Latin America | D48: =(Regional_agg!P49*(1+N(Data!J62))*D6+Regional_agg!P50*(1+N(Data!J78))*D7+Regional_agg!P51*(1+N(Data!J94))*D8+Regional_agg!P52*(1+N(Data!J110))*D9+Regional_agg!P53*(1+N(Data!J126))*D10+Regional_agg!P54*(1+N(Data!J142))*D11+Regional_agg!P55*(1+N(Data!J158))*D12+Regional_agg!P56*(1+N(Data!J174))*D13+Regional_agg!P57*(1+N(Data!J190))*D14+Regional_agg!P58*(1+N(Data!J206))*D15+Regional_agg!P59*(1+N(Data!J222))*D16+Regional_agg!P60*(1+N(Data!J238))*D17+Regional_agg!P61*(1+N(Data!J254))*D18+Regional_agg!P62*(1+N(Data!J270))*D19+Regional_agg!P63*(1+N(Data!J286))*D20)/(Regional_agg!P49*(1+N(Data!J62))+Regional_agg!P50*(1+N(Data!J78))+Regional_agg!P51*(1+N(Data!J94))+Regional_agg!P52*(1+N(Data!J110))+Regional_agg!P53*(1+N(Data!J126))+Regional_agg!P54*(1+N(Data!J142))+Regional_agg!P55*(1+N(Data!J158))+Regional_agg!P56*(1+N(Data!J174))+Regional_agg!P57*(1+N(Data!J190))+Regional_agg!P58*(1+N(Data!J206))+Regional_agg!P59*(1+N(Data!J222))+Regional_agg!P60*(1+N(Data!J238))+Regional_agg!P61*(1+N(Data!J254))+Regional_agg!P62*(1+N(Data!J270))+Regional_agg!P63*(1+N(Data!J286))) -> 0.97485015 | E48: =(Regional_agg!Q49*(1+N(Data!J63))*E6+Regional_agg!Q50*(1+N(Data!J79))*E7+Regional_agg!Q51*(1+N(Data!J95))*E8+Regional_agg!Q52*(1+N(Data!J111))*E9+Regional_agg!Q53*(1+N(Data!J127))*E10+Regional_agg!Q54*(1+N(Data!J143))*E11+Regional_agg!Q55*(1+N(Data!J159))*E12+Regional_agg!Q56*(1+N(Data!J175))*E13+Regional_agg!Q57*(1+N(Data!J191))*E14+Regional_agg!Q58*(1+N(Data!J207))*E15+Regional_agg!Q59*(1+N(Data!J223))*E16+Regional_agg!Q60*(1+N(Data!J239))*E17+Regional_agg!Q61*(1+N(Data!J255))*E18+Regional_agg!Q62*(1+N(Data!J271))*E19+Regional_agg!Q63*(1+N(Data!J287))*E20)/(Regional_agg!Q49*(1+N(Data!J63))+Regional_agg!Q50*(1+N(Data!J79))+Regional_agg!Q51*(1+N(Data!J95))+Regional_agg!Q52*(1+N(Data!J111))+Regional_agg!Q53*(1+N(Data!J127))+Regional_agg!Q54*(1+N(Data!J143))+Regional_agg!Q55*(1+N(Data!J159))+Regional_agg!Q56*(1+N(Data!J175))+Regional_agg!Q57*(1+N(Data!J191))+Regional_agg!Q58*(1+N(Data!J207))+Regional_agg!Q59*(1+N(Data!J223))+Regional_agg!Q60*(1+N(Data!J239))+Regional_agg!Q61*(1+N(Data!J255))+Regional_agg!Q62*(1+N(Data!J271))+Regional_agg!Q63*(1+N(Data!J287))) -> 0.97098456 | F48: =(Regional_agg!R49*(1+N(Data!J64))*F6+Regional_agg!R50*(1+N(Data!J80))*F7+Regional_agg!R51*(1+N(Data!J96))*F8+Regional_agg!R52*(1+N(Data!J112))*F9+Regional_agg!R53*(1+N(Data!J128))*F10+Regional_agg!R54*(1+N(Data!J144))*F11+Regional_agg!R55*(1+N(Data!J160))*F12+Regional_agg!R56*(1+N(Data!J176))*F13+Regional_agg!R57*(1+N(Data!J192))*F14+Regional_agg!R58*(1+N(Data!J208))*F15+Regional_agg!R59*(1+N(Data!J224))*F16+Regional_agg!R60*(1+N(Data!J240))*F17+Regional_agg!R61*(1+N(Data!J256))*F18+Regional_agg!R62*(1+N(Data!J272))*F19+Regional_agg!R63*(1+N(Data!J288))*F20)/(Regional_agg!R49*(1+N(Data!J64))+Regional_agg!R50*(1+N(Data!J80))+Regional_agg!R51*(1+N(Data!J96))+Regional_agg!R52*(1+N(Data!J112))+Regional_agg!R53*(1+N(Data!J128))+Regional_agg!R54*(1+N(Data!J144))+Regional_agg!R55*(1+N(Data!J160))+Regional_agg!R56*(1+N(Data!J176))+Regional_agg!R57*(1+N(Data!J192))+Regional_agg!R58*(1+N(Data!J208))+Regional_agg!R59*(1+N(Data!J224))+Regional_agg!R60*(1+N(Data!J240))+Regional_agg!R61*(1+N(Data!J256))+Regional_agg!R62*(1+N(Data!J272))+Regional_agg!R63*(1+N(Data!J288))) -> 0.98128512 | G48: =(Regional_agg!S49*(1+N(Data!J65))*G6+Regional_agg!S50*(1+N(Data!J81))*G7+Regional_agg!S51*(1+N(Data!J97))*G8+Regional_agg!S52*(1+N(Data!J113))*G9+Regional_agg!S53*(1+N(Data!J129))*G10+Regional_agg!S54*(1+N(Data!J145))*G11+Regional_agg!S55*(1+N(Data!J161))*G12+Regional_agg!S56*(1+N(Data!J177))*G13+Regional_agg!S57*(1+N(Data!J193))*G14+Regional_agg!S58*(1+N(Data!J209))*G15+Regional_agg!S59*(1+N(Data!J225))*G16+Regional_agg!S60*(1+N(Data!J241))*G17+Regional_agg!S61*(1+N(Data!J257))*G18+Regional_agg!S62*(1+N(Data!J273))*G19+Regional_agg!S63*(1+N(Data!J289))*G20)/(Regional_agg!S49*(1+N(Data!J65))+Regional_agg!S50*(1+N(Data!J81))+Regional_agg!S51*(1+N(Data!J97))+Regional_agg!S52*(1+N(Data!J113))+Regional_agg!S53*(1+N(Data!J129))+Regional_agg!S54*(1+N(Data!J145))+Regional_agg!S55*(1+N(Data!J161))+Regional_agg!S56*(1+N(Data!J177))+Regional_agg!S57*(1+N(Data!J193))+Regional_agg!S58*(1+N(Data!J209))+Regional_agg!S59*(1+N(Data!J225))+Regional_agg!S60*(1+N(Data!J241))+Regional_agg!S61*(1+N(Data!J257))+Regional_agg!S62*(1+N(Data!J273))+Regional_agg!S63*(1+N(Data!J289))) -> 0.98255854
A49: EAA | D49: =(Regional_agg!P64*(1+N(Data!J302))*D21+Regional_agg!P65*(1+N(Data!J318))*D22+Regional_agg!P66*(1+N(Data!J334))*D23+Regional_agg!P67*(1+N(Data!J350))*D24+Regional_agg!P68*(1+N(Data!J366))*D25+Regional_agg!P69*(1+N(Data!J382))*D26+Regional_agg!P70*(1+N(Data!J398))*D27+Regional_agg!P71*(1+N(Data!J414))*D28+Regional_agg!P72*(1+N(Data!J430))*D29+Regional_agg!P73*(1+N(Data!J446))*D30+Regional_agg!P74*(1+N(Data!J462))*D31+Regional_agg!P75*(1+N(Data!J478))*D32+Regional_agg!P76*(1+N(Data!J494))*D33+Regional_agg!P77*(1+N(Data!J510))*D34+Regional_agg!P78*(1+N(Data!J526))*D35+Regional_agg!P79*(1+N(Data!J542))*D36+Regional_agg!P80*(1+N(Data!J558))*D37+Regional_agg!P81*(1+N(Data!J574))*D38+Regional_agg!P82*(1+N(Data!J590))*D39+Regional_agg!P83*(1+N(Data!J606))*D40+Regional_agg!P84*(1+N(Data!J622))*D41+Regional_agg!P85*(1+N(Data!J638))*D42)/(Regional_agg!P64*(1+N(Data!J302))+Regional_agg!P65*(1+N(Data!J318))+Regional_agg!P66*(1+N(Data!J334))+Regional_agg!P67*(1+N(Data!J350))+Regional_agg!P68*(1+N(Data!J366))+Regional_agg!P69*(1+N(Data!J382))+Regional_agg!P70*(1+N(Data!J398))+Regional_agg!P71*(1+N(Data!J414))+Regional_agg!P72*(1+N(Data!J430))+Regional_agg!P73*(1+N(Data!J446))+Regional_agg!P74*(1+N(Data!J462))+Regional_agg!P75*(1+N(Data!J478))+Regional_agg!P76*(1+N(Data!J494))+Regional_agg!P77*(1+N(Data!J510))+Regional_agg!P78*(1+N(Data!J526))+Regional_agg!P79*(1+N(Data!J542))+Regional_agg!P80*(1+N(Data!J558))+Regional_agg!P81*(1+N(Data!J574))+Regional_agg!P82*(1+N(Data!J590))+Regional_agg!P83*(1+N(Data!J606))+Regional_agg!P84*(1+N(Data!J622))+Regional_agg!P85*(1+N(Data!J638))) -> 0.99170114 | E49: =(Regional_agg!Q64*(1+N(Data!J303))*E21+Regional_agg!Q65*(1+N(Data!J319))*E22+Regional_agg!Q66*(1+N(Data!J335))*E23+Regional_agg!Q67*(1+N(Data!J351))*E24+Regional_agg!Q68*(1+N(Data!J367))*E25+Regional_agg!Q69*(1+N(Data!J383))*E26+Regional_agg!Q70*(1+N(Data!J399))*E27+Regional_agg!Q71*(1+N(Data!J415))*E28+Regional_agg!Q72*(1+N(Data!J431))*E29+Regional_agg!Q73*(1+N(Data!J447))*E30+Regional_agg!Q74*(1+N(Data!J463))*E31+Regional_agg!Q75*(1+N(Data!J479))*E32+Regional_agg!Q76*(1+N(Data!J495))*E33+Regional_agg!Q77*(1+N(Data!J511))*E34+Regional_agg!Q78*(1+N(Data!J527))*E35+Regional_agg!Q79*(1+N(Data!J543))*E36+Regional_agg!Q80*(1+N(Data!J559))*E37+Regional_agg!Q81*(1+N(Data!J575))*E38+Regional_agg!Q82*(1+N(Data!J591))*E39+Regional_agg!Q83*(1+N(Data!J607))*E40+Regional_agg!Q84*(1+N(Data!J623))*E41+Regional_agg!Q85*(1+N(Data!J639))*E42)/(Regional_agg!Q64*(1+N(Data!J303))+Regional_agg!Q65*(1+N(Data!J319))+Regional_agg!Q66*(1+N(Data!J335))+Regional_agg!Q67*(1+N(Data!J351))+Regional_agg!Q68*(1+N(Data!J367))+Regional_agg!Q69*(1+N(Data!J383))+Regional_agg!Q70*(1+N(Data!J399))+Regional_agg!Q71*(1+N(Data!J415))+Regional_agg!Q72*(1+N(Data!J431))+Regional_agg!Q73*(1+N(Data!J447))+Regional_agg!Q74*(1+N(Data!J463))+Regional_agg!Q75*(1+N(Data!J479))+Regional_agg!Q76*(1+N(Data!J495))+Regional_agg!Q77*(1+N(Data!J511))+Regional_agg!Q78*(1+N(Data!J527))+Regional_agg!Q79*(1+N(Data!J543))+Regional_agg!Q80*(1+N(Data!J559))+Regional_agg!Q81*(1+N(Data!J575))+Regional_agg!Q82*(1+N(Data!J591))+Regional_agg!Q83*(1+N(Data!J607))+Regional_agg!Q84*(1+N(Data!J623))+Regional_agg!Q85*(1+N(Data!J639))) -> 0.99454729 | F49: =(Regional_agg!R64*(1+N(Data!J304))*F21+Regional_agg!R65*(1+N(Data!J320))*F22+Regional_agg!R66*(1+N(Data!J336))*F23+Regional_agg!R67*(1+N(Data!J352))*F24+Regional_agg!R68*(1+N(Data!J368))*F25+Regional_agg!R69*(1+N(Data!J384))*F26+Regional_agg!R70*(1+N(Data!J400))*F27+Regional_agg!R71*(1+N(Data!J416))*F28+Regional_agg!R72*(1+N(Data!J432))*F29+Regional_agg!R73*(1+N(Data!J448))*F30+Regional_agg!R74*(1+N(Data!J464))*F31+Regional_agg!R75*(1+N(Data!J480))*F32+Regional_agg!R76*(1+N(Data!J496))*F33+Regional_agg!R77*(1+N(Data!J512))*F34+Regional_agg!R78*(1+N(Data!J528))*F35+Regional_agg!R79*(1+N(Data!J544))*F36+Regional_agg!R80*(1+N(Data!J560))*F37+Regional_agg!R81*(1+N(Data!J576))*F38+Regional_agg!R82*(1+N(Data!J592))*F39+Regional_agg!R83*(1+N(Data!J608))*F40+Regional_agg!R84*(1+N(Data!J624))*F41+Regional_agg!R85*(1+N(Data!J640))*F42)/(Regional_agg!R64*(1+N(Data!J304))+Regional_agg!R65*(1+N(Data!J320))+Regional_agg!R66*(1+N(Data!J336))+Regional_agg!R67*(1+N(Data!J352))+Regional_agg!R68*(1+N(Data!J368))+Regional_agg!R69*(1+N(Data!J384))+Regional_agg!R70*(1+N(Data!J400))+Regional_agg!R71*(1+N(Data!J416))+Regional_agg!R72*(1+N(Data!J432))+Regional_agg!R73*(1+N(Data!J448))+Regional_agg!R74*(1+N(Data!J464))+Regional_agg!R75*(1+N(Data!J480))+Regional_agg!R76*(1+N(Data!J496))+Regional_agg!R77*(1+N(Data!J512))+Regional_agg!R78*(1+N(Data!J528))+Regional_agg!R79*(1+N(Data!J544))+Regional_agg!R80*(1+N(Data!J560))+Regional_agg!R81*(1+N(Data!J576))+Regional_agg!R82*(1+N(Data!J592))+Regional_agg!R83*(1+N(Data!J608))+Regional_agg!R84*(1+N(Data!J624))+Regional_agg!R85*(1+N(Data!J640))) -> 1.0035418 | G49: =(Regional_agg!S64*(1+N(Data!J305))*G21+Regional_agg!S65*(1+N(Data!J321))*G22+Regional_agg!S66*(1+N(Data!J337))*G23+Regional_agg!S67*(1+N(Data!J353))*G24+Regional_agg!S68*(1+N(Data!J369))*G25+Regional_agg!S69*(1+N(Data!J385))*G26+Regional_agg!S70*(1+N(Data!J401))*G27+Regional_agg!S71*(1+N(Data!J417))*G28+Regional_agg!S72*(1+N(Data!J433))*G29+Regional_agg!S73*(1+N(Data!J449))*G30+Regional_agg!S74*(1+N(Data!J465))*G31+Regional_agg!S75*(1+N(Data!J481))*G32+Regional_agg!S76*(1+N(Data!J497))*G33+Regional_agg!S77*(1+N(Data!J513))*G34+Regional_agg!S78*(1+N(Data!J529))*G35+Regional_agg!S79*(1+N(Data!J545))*G36+Regional_agg!S80*(1+N(Data!J561))*G37+Regional_agg!S81*(1+N(Data!J577))*G38+Regional_agg!S82*(1+N(Data!J593))*G39+Regional_agg!S83*(1+N(Data!J609))*G40+Regional_agg!S84*(1+N(Data!J625))*G41+Regional_agg!S85*(1+N(Data!J641))*G42)/(Regional_agg!S64*(1+N(Data!J305))+Regional_agg!S65*(1+N(Data!J321))+Regional_agg!S66*(1+N(Data!J337))+Regional_agg!S67*(1+N(Data!J353))+Regional_agg!S68*(1+N(Data!J369))+Regional_agg!S69*(1+N(Data!J385))+Regional_agg!S70*(1+N(Data!J401))+Regional_agg!S71*(1+N(Data!J417))+Regional_agg!S72*(1+N(Data!J433))+Regional_agg!S73*(1+N(Data!J449))+Regional_agg!S74*(1+N(Data!J465))+Regional_agg!S75*(1+N(Data!J481))+Regional_agg!S76*(1+N(Data!J497))+Regional_agg!S77*(1+N(Data!J513))+Regional_agg!S78*(1+N(Data!J529))+Regional_agg!S79*(1+N(Data!J545))+Regional_agg!S80*(1+N(Data!J561))+Regional_agg!S81*(1+N(Data!J577))+Regional_agg!S82*(1+N(Data!J593))+Regional_agg!S83*(1+N(Data!J609))+Regional_agg!S84*(1+N(Data!J625))+Regional_agg!S85*(1+N(Data!J641))) -> 1.0011711
A51: Limits: weights are GDP, not Bimbo sales by country (not disclosed): China is the largest EAA weight and Brazil the largest Latin America weight. Annual-average FX; Bimbo translates hyperinflationary Argentina at the closing rate (IAS 29, EEFF25 p.23, p.26). Capital IQ FX forecasts [sourced] via sheet FX.

Sheet PPP_terminal
A1: Terminal FX, local currency to USD, by purchasing power parity 2030 [calc]: PPP ratio = (1 + US CPI) / (1 + currency CPI); below 1 = the currency loses vs USD. CPI from IAS29_test (Capital IQ) [sourced]. USD countries = 1; EUR = GDP-weighted CPI of the euro countries
A2: iso3 | B2: region | C2: currency | D2: CPI 2030 | E2: currency CPI 2030 | F2: PPP ratio 2030
A3: MEX | B3: Mexico | C3: MXN | D3: =IAS29_test!R3 -> 0.0255 | E3: =D3 -> 0.0255 | F3: =IFERROR((1+IAS29_test!R4)/(1+E3),0) -> 0.99522184
A4: USA | B4: North America | C4: USD | D4: =IAS29_test!R4 -> 0.0206 | E4: =IAS29_test!R4 -> 0.0206 | F4: =IFERROR((1+IAS29_test!R4)/(1+E4),0) -> 1
A5: CAN | B5: North America | C5: CAD | D5: =IAS29_test!R5 -> 0.0186 | E5: =D5 -> 0.0186 | F5: =IFERROR((1+IAS29_test!R4)/(1+E5),0) -> 1.0019635
A6: ARG | B6: Latin America | C6: ARS | D6: =IAS29_test!R6 -> 0.0709 | E6: =D6 -> 0.0709 | F6: =IFERROR((1+IAS29_test!R4)/(1+E6),0) -> 0.95303016
A7: BRA | B7: Latin America | C7: BRL | D7: =IAS29_test!R7 -> 0.0321 | E7: =D7 -> 0.0321 | F7: =IFERROR((1+IAS29_test!R4)/(1+E7),0) -> 0.98885767
A8: CHL | B8: Latin America | C8: CLP | D8: =IAS29_test!R8 -> 0.0309 | E8: =D8 -> 0.0309 | F8: =IFERROR((1+IAS29_test!R4)/(1+E8),0) -> 0.99000873
A9: COL | B9: Latin America | C9: COP | D9: =IAS29_test!R9 -> 0.033 | E9: =D9 -> 0.033 | F9: =IFERROR((1+IAS29_test!R4)/(1+E9),0) -> 0.98799613
A10: CRI | B10: Latin America | C10: CRC | D10: =IAS29_test!R10 -> 0.0218 | E10: =D10 -> 0.0218 | F10: =IFERROR((1+IAS29_test!R4)/(1+E10),0) -> 0.9988256
A11: ECU | B11: Latin America | C11: USD | D11: =IAS29_test!R11 -> 0.0207 | E11: =IAS29_test!R4 -> 0.0206 | F11: =IFERROR((1+IAS29_test!R4)/(1+E11),0) -> 1
A12: SLV | B12: Latin America | C12: USD | D12: =IAS29_test!R12 -> 0.0265 | E12: =IAS29_test!R4 -> 0.0206 | F12: =IFERROR((1+IAS29_test!R4)/(1+E12),0) -> 1
A13: GTM | B13: Latin America | C13: GTQ | D13: =IAS29_test!R13 -> 0.0304 | E13: =D13 -> 0.0304 | F13: =IFERROR((1+IAS29_test!R4)/(1+E13),0) -> 0.99048913
A14: HND | B14: Latin America | C14: HNL | D14: =IAS29_test!R14 -> 0.0366 | E14: =D14 -> 0.0366 | F14: =IFERROR((1+IAS29_test!R4)/(1+E14),0) -> 0.98456492
A15: NIC | B15: Latin America | C15: NIO | D15: =IAS29_test!R15 -> 0.0335 | E15: =D15 -> 0.0335 | F15: =IFERROR((1+IAS29_test!R4)/(1+E15),0) -> 0.98751814
A16: PAN | B16: Latin America | C16: USD | D16: =IAS29_test!R16 -> 0.0196 | E16: =IAS29_test!R4 -> 0.0206 | F16: =IFERROR((1+IAS29_test!R4)/(1+E16),0) -> 1
A17: PRY | B17: Latin America | C17: PYG | D17: =IAS29_test!R17 -> 0.0337 | E17: =D17 -> 0.0337 | F17: =IFERROR((1+IAS29_test!R4)/(1+E17),0) -> 0.98732708
A18: PER | B18: Latin America | C18: PEN | D18: =IAS29_test!R18 -> 0.0277 | E18: =D18 -> 0.0277 | F18: =IFERROR((1+IAS29_test!R4)/(1+E18),0) -> 0.99309137
A19: URY | B19: Latin America | C19: UYU | D19: =IAS29_test!R19 -> 0.0311 | E19: =D19 -> 0.0311 | F19: =IFERROR((1+IAS29_test!R4)/(1+E19),0) -> 0.9898167
A20: VEN | B20: Latin America | C20: VES | D20: =IAS29_test!R20 -> 0.1177 | E20: =D20 -> 0.1177 | F20: =IFERROR((1+IAS29_test!R4)/(1+E20),0) -> 0.91312517
A21: GBR | B21: EAA | C21: GBP | D21: =IAS29_test!R21 -> 0.0213 | E21: =D21 -> 0.0213 | F21: =IFERROR((1+IAS29_test!R4)/(1+E21),0) -> 0.9993146
A22: CHE | B22: EAA | C22: CHF | D22: =IAS29_test!R22 -> 0.0075 | E22: =D22 -> 0.0075 | F22: =IFERROR((1+IAS29_test!R4)/(1+E22),0) -> 1.0130025
A23: ROU | B23: EAA | C23: RON | D23: =IAS29_test!R23 -> 0.0298 | E23: =D23 -> 0.0298 | F23: =IFERROR((1+IAS29_test!R4)/(1+E23),0) -> 0.99106623
A24: SRB | B24: EAA | C24: RSD | D24: =IAS29_test!R24 -> 0.0296 | E24: =D24 -> 0.0296 | F24: =IFERROR((1+IAS29_test!R4)/(1+E24),0) -> 0.99125874
A25: SVN | B25: EAA | C25: EUR | D25: =IAS29_test!R25 -> 0.0214 | E25: =(Regional_agg!S25*IAS29_test!R25+Regional_agg!S26*IAS29_test!R26+Regional_agg!S27*IAS29_test!R27+Regional_agg!S39*IAS29_test!R39+Regional_agg!S40*IAS29_test!R40+Regional_agg!S41*IAS29_test!R41+Regional_agg!S42*IAS29_test!R42)/(Regional_agg!S25+Regional_agg!S26+Regional_agg!S27+Regional_agg!S39+Regional_agg!S40+Regional_agg!S41+Regional_agg!S42) -> 0.018992714 | F25: =IFERROR((1+IAS29_test!R4)/(1+E25),0) -> 1.0015773
A26: HRV | B26: EAA | C26: EUR | D26: =IAS29_test!R26 -> 0.0201 | E26: =(Regional_agg!S25*IAS29_test!R25+Regional_agg!S26*IAS29_test!R26+Regional_agg!S27*IAS29_test!R27+Regional_agg!S39*IAS29_test!R39+Regional_agg!S40*IAS29_test!R40+Regional_agg!S41*IAS29_test!R41+Regional_agg!S42*IAS29_test!R42)/(Regional_agg!S25+Regional_agg!S26+Regional_agg!S27+Regional_agg!S39+Regional_agg!S40+Regional_agg!S41+Regional_agg!S42) -> 0.018992714 | F26: =IFERROR((1+IAS29_test!R4)/(1+E26),0) -> 1.0015773
A27: MNE | B27: EAA | C27: EUR | D27: =IAS29_test!R27 -> 0.0264 | E27: =(Regional_agg!S25*IAS29_test!R25+Regional_agg!S26*IAS29_test!R26+Regional_agg!S27*IAS29_test!R27+Regional_agg!S39*IAS29_test!R39+Regional_agg!S40*IAS29_test!R40+Regional_agg!S41*IAS29_test!R41+Regional_agg!S42*IAS29_test!R42)/(Regional_agg!S25+Regional_agg!S26+Regional_agg!S27+Regional_agg!S39+Regional_agg!S40+Regional_agg!S41+Regional_agg!S42) -> 0.018992714 | F27: =IFERROR((1+IAS29_test!R4)/(1+E27),0) -> 1.0015773
A28: MKD | B28: EAA | C28: MKD | D28: =IAS29_test!R28 -> 0.0229 | E28: =D28 -> 0.0229 | F28: =IFERROR((1+IAS29_test!R4)/(1+E28),0) -> 0.99775149
A29: RUS | B29: EAA | C29: RUB | D29: =IAS29_test!R29 -> 0.0526 | E29: =D29 -> 0.0526 | F29: =IFERROR((1+IAS29_test!R4)/(1+E29),0) -> 0.96959909
A30: UKR | B30: EAA | C30: UAH | D30: =IAS29_test!R30 -> 0.0713 | E30: =D30 -> 0.0713 | F30: =IFERROR((1+IAS29_test!R4)/(1+E30),0) -> 0.95267432
A31: TUR | B31: EAA | C31: TRY | D31: =IAS29_test!R31 -> 0.1077 | E31: =D31 -> 0.1077 | F31: =IFERROR((1+IAS29_test!R4)/(1+E31),0) -> 0.9213686
A32: KAZ | B32: EAA | C32: KZT | D32: =IAS29_test!R32 -> 0.0649 | E32: =D32 -> 0.0649 | F32: =IFERROR((1+IAS29_test!R4)/(1+E32),0) -> 0.95839985
A33: CHN | B33: EAA | C33: CNY | D33: =IAS29_test!R33 -> 0.0164 | E33: =D33 -> 0.0164 | F33: =IFERROR((1+IAS29_test!R4)/(1+E33),0) -> 1.0041322
A34: IND | B34: EAA | C34: INR | D34: =IAS29_test!R34 -> 0.0488 | E34: =D34 -> 0.0488 | F34: =IFERROR((1+IAS29_test!R4)/(1+E34),0) -> 0.97311213
A35: KOR | B35: EAA | C35: KRW | D35: =IAS29_test!R35 -> 0.0187 | E35: =D35 -> 0.0187 | F35: =IFERROR((1+IAS29_test!R4)/(1+E35),0) -> 1.0018651
A36: ZAF | B36: EAA | C36: ZAR | D36: =IAS29_test!R36 -> 0.0308 | E36: =D36 -> 0.0308 | F36: =IFERROR((1+IAS29_test!R4)/(1+E36),0) -> 0.99010477
A37: MAR | B37: EAA | C37: MAD | D37: =IAS29_test!R37 -> 0.0167 | E37: =D37 -> 0.0167 | F37: =IFERROR((1+IAS29_test!R4)/(1+E37),0) -> 1.0038359
A38: TUN | B38: EAA | C38: TND | D38: =IAS29_test!R38 -> 0.0278 | E38: =D38 -> 0.0278 | F38: =IFERROR((1+IAS29_test!R4)/(1+E38),0) -> 0.99299475
A39: ESP | B39: EAA | C39: EUR | D39: =IAS29_test!R39 -> 0.0203 | E39: =(Regional_agg!S25*IAS29_test!R25+Regional_agg!S26*IAS29_test!R26+Regional_agg!S27*IAS29_test!R27+Regional_agg!S39*IAS29_test!R39+Regional_agg!S40*IAS29_test!R40+Regional_agg!S41*IAS29_test!R41+Regional_agg!S42*IAS29_test!R42)/(Regional_agg!S25+Regional_agg!S26+Regional_agg!S27+Regional_agg!S39+Regional_agg!S40+Regional_agg!S41+Regional_agg!S42) -> 0.018992714 | F39: =IFERROR((1+IAS29_test!R4)/(1+E39),0) -> 1.0015773
A40: PRT | B40: EAA | C40: EUR | D40: =IAS29_test!R40 -> 0.0199 | E40: =(Regional_agg!S25*IAS29_test!R25+Regional_agg!S26*IAS29_test!R26+Regional_agg!S27*IAS29_test!R27+Regional_agg!S39*IAS29_test!R39+Regional_agg!S40*IAS29_test!R40+Regional_agg!S41*IAS29_test!R41+Regional_agg!S42*IAS29_test!R42)/(Regional_agg!S25+Regional_agg!S26+Regional_agg!S27+Regional_agg!S39+Regional_agg!S40+Regional_agg!S41+Regional_agg!S42) -> 0.018992714 | F40: =IFERROR((1+IAS29_test!R4)/(1+E40),0) -> 1.0015773
A41: FRA | B41: EAA | C41: EUR | D41: =IAS29_test!R41 -> 0.0185 | E41: =(Regional_agg!S25*IAS29_test!R25+Regional_agg!S26*IAS29_test!R26+Regional_agg!S27*IAS29_test!R27+Regional_agg!S39*IAS29_test!R39+Regional_agg!S40*IAS29_test!R40+Regional_agg!S41*IAS29_test!R41+Regional_agg!S42*IAS29_test!R42)/(Regional_agg!S25+Regional_agg!S26+Regional_agg!S27+Regional_agg!S39+Regional_agg!S40+Regional_agg!S41+Regional_agg!S42) -> 0.018992714 | F41: =IFERROR((1+IAS29_test!R4)/(1+E41),0) -> 1.0015773
A42: ITA | B42: EAA | C42: EUR | D42: =IAS29_test!R42 -> 0.0183 | E42: =(Regional_agg!S25*IAS29_test!R25+Regional_agg!S26*IAS29_test!R26+Regional_agg!S27*IAS29_test!R27+Regional_agg!S39*IAS29_test!R39+Regional_agg!S40*IAS29_test!R40+Regional_agg!S41*IAS29_test!R41+Regional_agg!S42*IAS29_test!R42)/(Regional_agg!S25+Regional_agg!S26+Regional_agg!S27+Regional_agg!S39+Regional_agg!S40+Regional_agg!S41+Regional_agg!S42) -> 0.018992714 | F42: =IFERROR((1+IAS29_test!R4)/(1+E42),0) -> 1.0015773
A44: Region factor 2030, local currency to USD, PPP [calc] = sum(weight x (1 + GDP growth) x PPP ratio) / sum(weight x (1 + GDP growth)), as Regional_FX
A45: region | D45: 2030
A46: Mexico | D46: 1
A47: North America | D47: 1
A48: Latin America | D48: =(Regional_agg!S49*(1+N(Data!J65))*F6+Regional_agg!S50*(1+N(Data!J81))*F7+Regional_agg!S51*(1+N(Data!J97))*F8+Regional_agg!S52*(1+N(Data!J113))*F9+Regional_agg!S53*(1+N(Data!J129))*F10+Regional_agg!S54*(1+N(Data!J145))*F11+Regional_agg!S55*(1+N(Data!J161))*F12+Regional_agg!S56*(1+N(Data!J177))*F13+Regional_agg!S57*(1+N(Data!J193))*F14+Regional_agg!S58*(1+N(Data!J209))*F15+Regional_agg!S59*(1+N(Data!J225))*F16+Regional_agg!S60*(1+N(Data!J241))*F17+Regional_agg!S61*(1+N(Data!J257))*F18+Regional_agg!S62*(1+N(Data!J273))*F19+Regional_agg!S63*(1+N(Data!J289))*F20)/(Regional_agg!S49*(1+N(Data!J65))+Regional_agg!S50*(1+N(Data!J81))+Regional_agg!S51*(1+N(Data!J97))+Regional_agg!S52*(1+N(Data!J113))+Regional_agg!S53*(1+N(Data!J129))+Regional_agg!S54*(1+N(Data!J145))+Regional_agg!S55*(1+N(Data!J161))+Regional_agg!S56*(1+N(Data!J177))+Regional_agg!S57*(1+N(Data!J193))+Regional_agg!S58*(1+N(Data!J209))+Regional_agg!S59*(1+N(Data!J225))+Regional_agg!S60*(1+N(Data!J241))+Regional_agg!S61*(1+N(Data!J257))+Regional_agg!S62*(1+N(Data!J273))+Regional_agg!S63*(1+N(Data!J289))) -> 0.98511538
A49: EAA | D49: =(Regional_agg!S64*(1+N(Data!J305))*F21+Regional_agg!S65*(1+N(Data!J321))*F22+Regional_agg!S66*(1+N(Data!J337))*F23+Regional_agg!S67*(1+N(Data!J353))*F24+Regional_agg!S68*(1+N(Data!J369))*F25+Regional_agg!S69*(1+N(Data!J385))*F26+Regional_agg!S70*(1+N(Data!J401))*F27+Regional_agg!S71*(1+N(Data!J417))*F28+Regional_agg!S72*(1+N(Data!J433))*F29+Regional_agg!S73*(1+N(Data!J449))*F30+Regional_agg!S74*(1+N(Data!J465))*F31+Regional_agg!S75*(1+N(Data!J481))*F32+Regional_agg!S76*(1+N(Data!J497))*F33+Regional_agg!S77*(1+N(Data!J513))*F34+Regional_agg!S78*(1+N(Data!J529))*F35+Regional_agg!S79*(1+N(Data!J545))*F36+Regional_agg!S80*(1+N(Data!J561))*F37+Regional_agg!S81*(1+N(Data!J577))*F38+Regional_agg!S82*(1+N(Data!J593))*F39+Regional_agg!S83*(1+N(Data!J609))*F40+Regional_agg!S84*(1+N(Data!J625))*F41+Regional_agg!S85*(1+N(Data!J641))*F42)/(Regional_agg!S64*(1+N(Data!J305))+Regional_agg!S65*(1+N(Data!J321))+Regional_agg!S66*(1+N(Data!J337))+Regional_agg!S67*(1+N(Data!J353))+Regional_agg!S68*(1+N(Data!J369))+Regional_agg!S69*(1+N(Data!J385))+Regional_agg!S70*(1+N(Data!J401))+Regional_agg!S71*(1+N(Data!J417))+Regional_agg!S72*(1+N(Data!J433))+Regional_agg!S73*(1+N(Data!J449))+Regional_agg!S74*(1+N(Data!J465))+Regional_agg!S75*(1+N(Data!J481))+Regional_agg!S76*(1+N(Data!J497))+Regional_agg!S77*(1+N(Data!J513))+Regional_agg!S78*(1+N(Data!J529))+Regional_agg!S79*(1+N(Data!J545))+Regional_agg!S80*(1+N(Data!J561))+Regional_agg!S81*(1+N(Data!J577))+Regional_agg!S82*(1+N(Data!J593))+Regional_agg!S83*(1+N(Data!J609))+Regional_agg!S84*(1+N(Data!J625))+Regional_agg!S85*(1+N(Data!J641))) -> 0.99425917
A51: Mexico and North America = 1 here: the USD/MXN PPP step is applied in the statements workbook ((1 + Mexico CPI) / (1 + US CPI)). Limits: GDP weights, not Bimbo sales by country; annual-average CPI; one year (2030) as the long-run proxy.
